Workbook

Sheet Scores (start here)
A1: Question | B1: Row | C1: Question text | D1: AI score | E1: Max score | F1: ★ Your score | G1: ★ Your comments | H1: Agrees with AI? | I1: Final score | J1: Score used | K1: Status | L1: Step 2 status | M1: Step 2 answer | N1: Citation | O1: Link | P1: Quote | Q1: AI's reasoning | R1: Why left for a person
A2: UPD1a | B2: Bengaluru – BWSSB | D2: =IFERROR(UPD1a!L13,"") -> 1.25 | H2: =IF(OR(F2="",NOT(ISNUMBER(D2))),"",IF(ABS(F2-D2)<0.001,"Yes","No")) | I2: =IF(ISNUMBER(F2),F2,D2) -> 1.25 | J2: =IF(ISNUMBER(F2),"Expert (overrides AI)",IF(ISNUMBER(D2),"AI","Not scored yet")) -> AI | K2: Left for a person | L2: Partially Answered | M2: ANSWER: In the sources available, I found no provision that requires BWSSB to prepare its water supply or sewerage plans or schemes jointly with, in consultation with, or with the approval of the ULG (the Greater Bengaluru Authority (GBA) and its City Corporations). On BWSSB's side, the Act gives the Board its own duty to prepare schemes. The approval it requires for big schemes comes from the State Government, not the ULG. The only ULG link is a Consultative Committee set up by the State Government that advises the Board on 'major schemes'. ULG involvement in that committee is at the State's discretion. On the ULG's side, the Greater Bengaluru Governance Act gives GBA wide powers to supervise and coordinate public authorities, including BWSSB, through binding directions. It does not require BWSSB to prepare its own plans in coordination with the ULG. The Karnataka Town and Country Planning Act is not in the Citation Sheet, so the answer is incomplete. | EVIDENCE: (1) BWSSB Act 1964 (BWSSB-02, PRS consolidated copy): s.15(2)(b)-(c) says it is the Board's duty to take steps 'for preparing and carrying out schemes' for water supply and sewerage. The s.15(2) proviso says no scheme 'estimated to cost more than a crore of rupees shall be carried out by the Board except with the approval of the State Government' (State approval, not ULG). s.14: 'The State Government shall constitute a Consultative Committee'. Its other members are appointed 'after consultation with such representat | N2: The Bangalore Water Supply and Sewerage Act, 1964 [BWSSB-02] | O2: https://prsindia.org/files/bills_acts/acts_states/karnataka/1964/1964KR36.pdf | P2: (i) to advise the Board on major questions of policy and major schemes; | Q2: I left the Score blank for three reasons. (1) SCALE-MISMATCH. The Step 2 notes say the rubric bands run from 0 to 10, but the Max Score is 5. The detailed methodology and band wording were not in my task input, so I could not check the bands or match the evidence to one. A person needs to confirm the scale. (2) The evidence fits no band without a team decision (RUBRIC-GAP). The two possible bands are 2.5 and 0. - BWSSB Act 1964 (BWSSB-02, PRS consolidated copy, amended up to Act 29 of 2021). Under s.15(2)(b)-(c) the Board prepares its own water supply and sewerage schemes. Under the s.15(2) proviso, schemes costing more than Rs 1 crore need approval from the State Government, not the city government. - The only link to the city government is s.14. The State 'shall constitute' a Consultative Committee, and it consults bodies representing the city corporation (still named as the Bruhat Bangalore Mahanagara Palike) only 'as the State Government thinks fit'. The committee's role is to 'advise the Board on major questions of policy and major schemes'. That is advice, not approval, and nothing requires the Board to follow it. - On the city government's side, the Greater Bengaluru Governance Act (BWSSB-04, Act 36 of 2025, as enacted, GBA era) gives the Greater Bengaluru Authority (GBA) several powers: - s.14(4): 'Integrating and supervising the activities of public authorities like ... the Bengaluru Water Supply and Sewerage Board ... issuing directions for the same which shall be binding'. - s.14(3)(b): coordinating the execution of schemes that implement plans prepared by GBA. - s.15(1): GBA makes the master plan and mobility plans. These are general powers to supervise and direct. None of them makes city government consultation or approval a required step when BWSSB prepares its own plans. The team must decide whether these powers count as 'coordination' for UPD1a. (3) I cannot show affirmative absence, so a 0 is not supported. The Karnataka Town and Country Planning Act 1961 is not in the Citation Sheet; I searched and found nothing. No BWSSB Rules (s.87), Regulations (s.88) or s.14(4)(iv) Rules are in the sheet either. I checked BWSSB-02 ss.12-15, BWSSB-04 ss.14-15 and the definition of 'public authority' in s.2(54), and the Step 2 review of BWSSB-23 and BWSSB-28 (these are bills, not enacted law). Also flagged: the BWSSB Act still names BBMP. No source in the sheet shows GBA or the City Corporations substituted for it. | R2: The citation didn't settle every input. "Score" left blank: the Citation Sheet doesn't decide it.
A3: UPD1a | B3: Bengaluru – BMTC | D3: =IFERROR(UPD1a!L14,"") | H3: =IF(OR(F3="",NOT(ISNUMBER(D3))),"",IF(ABS(F3-D3)<0.001,"Yes","No")) | I3: =IF(ISNUMBER(F3),F3,D3) | J3: =IF(ISNUMBER(F3),"Expert (overrides AI)",IF(ISNUMBER(D3),"AI","Not scored yet")) -> Not scored yet | K3: Left for a person | L3: Partially Answered | M3: ANSWER: None of the sources in the Citation Sheet requires BMTC to prepare its own spatial or sectoral plans together with, in consultation with, or with the approval of the Greater Bengaluru Authority (GBA) or its City Corporations. What exists runs mainly the other way. (i) The GBA's own law gives the GBA a general power to integrate and supervise BMTC's activities. Its directions are binding, BMTC must obey them, and BMTC must write the GBA's coordinating role into its Memorandum of Association. (ii) The GBA must make the master plan and the mobility plans for the Greater Bengaluru Area. (iii) The GBA may hand the planning of major infrastructure projects to public authorities, and those authorities must help when asked. (iv) Under the transport authority's Act (BMLTA), BMTC, as an 'Urban Transport Agency', must prepare its Sectoral Mobility Investment Program 'in consultation with' the BMLTA. The BMLTA is a state authority, not the city government, although the 2025 amendment bill (BMTC-24) adds the five City Corporation Mayors and Commissioners and the GBA Chief Commissioner to it and its Executive Committee. Whether the GBA's general power to supervise and direct counts as 'approval/concurrence' or fits no band at all is a judgement for the team. | EVIDENCE: BMTC's side. Road Transport Corporations Act, 1950 (BMTC-02): s.18 sets a general duty to provide an 'efficient, adequate, economical and properly co-ordinated system of road transport services'. s.19 lists BMTC's p | N3: The Greater Bengaluru Governance Act, 2024 Act No. 36 of 2025 [BMTC-04] | O3: https://prsindia.org/files/bills_acts/acts_states/karnataka/2025/Act36of2025KA.pdf | P3: Integrating and supervising the activities of public authorities like the Bangalore Development Authority, the Bengaluru Water Supply and Sewerage Board, Bangalore Metropolitan Transport Corporation, Bengaluru Solid Waste Management Corporation, Bengaluru Metro Rail Corporation Limited, the Bangalore Electricity Supply Company and such other bodies connected with municipal activities in the Greater Bengaluru Area in such a manner that all functions are streamlined and implemented in a citizen-friendly manner and issuing directions for the same which shall be binding; | Q3: Score left blank for three reasons. (1) SCALE-MISMATCH. Step 2 reports that the UPD1a rubric bands run 0-10, but this input allows only 0-5. The highest band is neither the Max Score nor a sum of components, so I have not scaled a band down. The team should confirm the scale. (2) RUBRIC-GAP / band undetermined. I checked the Step 2 answer against the source and it is accurate. The Greater Bengaluru Governance Act, 2024 (BMTC-04) gives the GBA (the city government) a general, binding power to integrate, supervise and direct BMTC's 'activities' (s.14(4)). BMTC must obey those directions and must add the GBA's coordinating role to its Memorandum of Association. But no provision requires BMTC to prepare its own spatial or sectoral plans in consultation with, or with the approval of, the GBA or the City Corporations. Other provisions read: - s.15(1): the GBA makes the master plan and mobility plans itself. - s.15(5): the GBA 'may' assign the planning of major infrastructure projects to public authorities. This is a discretionary power, not a duty on BMTC. - s.14(3)(b): covers schemes for plans prepared by the GBA, not BMTC's own plans. - BMLTA Act s.24(b) (BMTC-06): requires consultation with the BMLTA, a state authority, not the city government. Whether a general power to direct counts as 'approval/concurrence' is a judgement for the team. I have not interpolated a band. (3) No affirmative absence, so 0 cannot be scored. Not in the Citation Sheet: - BMTC's Memorandum and Articles of Association - Rules or Regulations under the Road Transport Corporations Act, 1950 or the BMLTA Act - GBA regulations or directions under s.14(4) Checked: - BMTC-04: s.8, s.9, s.13, s.14(2)-(4), s.15 - BMTC-05: the GBA amendment bill. Its amendments to s.8(2) and s.14(1) clarify the GBA's functions. They do not touch s.14(4) or add any duty on BMTC's plans. - BMTC-02, BMTC-06, BMTC-07, BMTC-22, BMTC-24: as reported in Step 2. - Sheet-wide search for BMTC plans with GBA approval or consultation: found nothing new. For the team to check: - BMTC's legal form. The GBA Act calls it 'Bangalore Metropolitan Transport Corporation Limited', which conflicts with the Road Transport Corporations Act, 1950 being listed as its enabling Act. - Whether the BMLTA amendment (BMTC-24 bill; Act 10 of 2026) is in force. The UPD1a Detailed Methodology text was not supplied in this task, which also prevents scoring. | R3: The citation didn't settle every input. "Score" left blank: the Citation Sheet doesn't decide it.
A4: UPD1a | B4: Bengaluru – BDA | D4: =IFERROR(UPD1a!L15,"") -> 3.75 | H4: =IF(OR(F4="",NOT(ISNUMBER(D4))),"",IF(ABS(F4-D4)<0.001,"Yes","No")) | I4: =IF(ISNUMBER(F4),F4,D4) -> 3.75 | J4: =IF(ISNUMBER(F4),"Expert (overrides AI)",IF(ISNUMBER(D4),"AI","Not scored yet")) -> AI | K4: Left for a person | L4: Partially Answered | M4: ANSWER: The answer depends on the type of plan, so I have not given a single band. (1) BDA's development schemes: the law requires BDA to send each scheme notification to 'the Corporation'. The Corporation has 30 days to make representations. Representations go to the Government through BDA, and BDA must consider them before submitting the scheme for sanction. If no representation arrives in time, the Corporation's concurrence is deemed given. This is mandatory consultation with a duty to consider, not a real right of approval: the Corporation's silence counts as consent, and a representation does not stop the scheme going forward. (2) Works for further development: the Corporation 'shall be consulted' if the area lies within the City limits. This is mandatory consultation with no duty to respond. (3) Private layouts within Corporation limits: BDA needs the Corporation's concurrence. If they disagree, the Government decides. This is a sanction of private layouts, not a plan BDA prepares itself. (4) Master plan under the T&CP Act: the sections I read give the local authority no role in preparing the master plan, only public notice and public comments. On top of this, the Greater Bengaluru Governance Act makes GBA itself the Planning Authority for the Greater Bengaluru Area 'notwithstanding anything contained in any other law'. GBA can also issue binding directions to BDA. These are ULG powers over BDA, but they are not a duty on BDA to prepare its plans jointly with GBA. | EVI | N4: The Bangalore Development Authority Act, 1976 (Act 12 of 1976) – PRS copy, 'Amendments appended: 19 of 2002, 19 of 2005, 27 of 2020, 42 of 2026' [BDA-02] | O4: https://prsindia.org/files/bills_acts/acts_states/karnataka/1976/1976Karnataka12.pdf | P4: (2) A copy of the said notification shall be sent to the Corporation which shall, within thirty days from the date of receipt thereof, forward to the Authority for transmission to the Government as hereinafter provided, any representation which the Corporation may think fit to make with regard to the scheme. | Q4: I have left the Score blank for three reasons. (1) SCALE-MISMATCH. The rubric bands described for UPD1a run from 0 to 10, but the Score column allows only 0 to 5. The Detailed Methodology text was not given to me in this task. Without it I cannot confirm how a band converts to the 0-5 input, so I have not scored. Possible raw band values, recorded only so a person can check them: 7.5 or 10 for development schemes, 5 for s.25 works, 10 for s.32 layouts. (2) Plan-scope question for the team. I checked Step 2's evidence against BDA-02 (PRS copy, amended up to Act 42 of 2026), and it is accurate. The wording supports these readings: - s.17(2): the Corporation must be sent the scheme notification and may make representations within 30 days. Its representations go to the Government through BDA. - s.17(4): if the Corporation sends nothing, its concurrence is 'deemed to have been given'. - s.18(1): BDA 'shall submit' the scheme to the Government 'after consideration of representations, if any', with any changes it 'may think fit'. So BDA must consider the representations but need not accept them. This is not a veto. - s.25(1) proviso: for works inside City limits, the Corporation 'shall be consulted'. This is consultation only. - s.32(1) provisos: BDA needs the Corporation's concurrence to sanction private layouts, but these are not plans BDA prepares itself. - s.26: schemes made 'on the recommendation of the Corporation' are optional. For the master plan under the KTCP Act (BDA-06), the sections Step 2 read show only public notice and comments. The KTCP Rules and the BDA Rules are not in the Citation Sheet, so I cannot claim affirmative absence of a ULG role at master-plan level. The team needs to decide whether scheme-level and layout-level mechanisms count as 'spatial/sectoral plans' for this question. (3) Jurisdiction and successor-body question. BDA-03 (GBGA 2024, Act 36 of 2025): - s.14(2)(a): 'Notwithstanding anything contained in any other law', GBA is the KTCP 'Planning Authority' for the Greater Bengaluru Area. - s.14(4): GBA integrates and supervises 'the Bangalore Development Authority', and its directions are binding. - s.15(1): GBA makes the master plan and mobility plans. BDA-05 (KTCP Amendment Bill 2025, as passed by the Assembly only) would limit BDA to the Bengaluru Metropolitan Area 'excluding the Greater Bengaluru Area'. Its s.1(2) says it comes into force on a date the State notifies, and no commencement notification is in the Citation Sheet. The BDA Act still says 'Corporation of the City of Bangalore' (s.2(i)). No source shows GBA or the City Corporations formally substituted. For a person to check: (a) the UPD1a methodology and how its bands convert to the 0-5 Score; (b) whether scheme or layout mechanisms count as plans; (c) whether BDA still plans any area inside a ULG; (d) whether the KTCP Amendment 2025 has commenced; (e) the KTCP and BDA Rules, which are needed before anyone can claim affirmative absence at master-plan level. Only PRS copies of the Acts were available. | R4: The citation didn't settle every input. "Score" left blank: the Citation Sheet doesn't decide it.
A5: UPD1a | B5: Bengaluru – BMRCL | D5: =IFERROR(UPD1a!L16,"") -> 0 | H5: =IF(OR(F5="",NOT(ISNUMBER(D5))),"",IF(ABS(F5-D5)<0.001,"Yes","No")) | I5: =IF(ISNUMBER(F5),F5,D5) -> 0 | J5: =IF(ISNUMBER(F5),"Expert (overrides AI)",IF(ISNUMBER(D5),"AI","Not scored yet")) -> AI | K5: Left for a person | L5: Partially Answered | M5: ANSWER: No source in the Citation Sheet requires BMRCL to prepare its own spatial or sectoral plans together with the ULG (the Greater Bengaluru Authority (GBA) and its City Corporations). The Sheet contains no Act that constitutes BMRCL, because BMRCL is a company. The planning relationship runs the other way, from the ULG to BMRCL. Under the GBA Act, the GBA makes the master plan and mobility plans for the Greater Bengaluru Area. It also integrates and supervises 'public authorities', naming BMRCL, and its directions to them are binding. It may give public authorities the job of planning major infrastructure projects, and they must assist it. Separately, the BMLTA Act makes BMRCL-type transport agencies consult BMLTA, a state transport authority and not the ULG, when preparing their investment programmes. None of this is a duty on BMRCL to consult the ULG, obtain its concurrence or plan jointly with it. Not every legal layer is in the Sheet, so I cannot show that such a duty is affirmatively absent. | EVIDENCE: ULG side: Greater Bengaluru Governance Act, 2024 (Act 36 of 2025), PRS text [BMRCL-02]. (1) s.2(54) names 'Bengaluru Metro Rail Corporation Limited' as a 'Public authority'. (2) s.14(4) 'Co-ordination and Supervision of Public Authorities': GBA integrates and supervises BMRCL and others, 'issuing directions for the same which shall be binding'. Public authorities 'shall cooperate ... and obey its directions'. This is a general supervisory power that a ULG body can ex | N5: The Greater Bengaluru Governance Act, 2024 Act No. 36 of 2025 [BMRCL-02] | O5: https://prsindia.org/files/bills_acts/acts_states/karnataka/2025/Act36of2025KA.pdf | P5: The Greater Bengaluru Authority may assign the task of planning the major infrastructural projects in the Greater Bengaluru Area to such public authorities or any other agencies, bodies carrying out civic functions in the Greater Bengaluru Area or take such assistance from these agencies as is necessary for successful execution of the projects. The agencies shall be bound to assist the Greater Bengaluru Authority when called up on to do so. | Q5: I left the Score blank for four reasons. (1) SCALE-MISMATCH. The Step 2 record says the UPD1a rubric bands run 0-10 but the Max Score is 5. The input asks for a number from 0 to 5. The full rubric text and Detailed Methodology were not in the task material, so I cannot choose a band or convert one. A person needs to confirm the band and the conversion. (2) RUBRIC-GAP / relationship judgement. I re-read BMRCL-02 (Greater Bengaluru Governance Act, Act 36 of 2025, as enacted, GBA era). It confirms these provisions: - s.2(54) names BMRCL as a 'Public authority'. - s.14(4): GBA integrates and supervises BMRCL's activities through directions 'which shall be binding'. Public authorities 'shall cooperate ... and obey its directions'. - s.15(1): GBA 'shall be responsible to make master plan and mobility plans'. - s.15(5): GBA 'may' give public authorities the job of planning major infrastructure projects. The agencies 'shall be bound to assist' when called on. - s.13(1)(j): BMRCL's MD sits on the GBA Executive Committee. These are ULG powers over BMRCL, plus a duty on BMRCL to assist when asked. None of them requires BMRCL to prepare its own plans in consultation with the ULG or with its concurrence. Whether they count as 'coordination with the ULG' is a methodological question for a person to decide. On the other side, the BMLTA Act s.24(b) [BMRCL-08] makes consultation mandatory ('shall be prepared in consultation with the Authority'). But that Authority is BMLTA, a state transport authority, not the ULG. ULG Mayors and Commissioners sit on BMLTA only under the 2025 Amendment Bill [BMRCL-38], and the Sheet does not show that Bill enacted. (3) No affirmative absence, so I cannot give 0. These instruments are missing from the Citation Sheet: - the Metro Railways (Construction of Works) Act, 1978 (only the 2009 amending Bill, BMRCL-37, is present) - BMRCL's Memorandum and Articles of Association - GBA Rules and Regulations - BMLTA Regulations - the notification extending the Metro Railways (O&M) Act to Bengaluru - a consolidated, current KTCP Act (4) What was checked: BMRCL-02, BMRCL-03, BMRCL-04, BMRCL-06, BMRCL-08, BMRCL-09 and BMRCL-38, as recorded in Step 2, and I re-read BMRCL-02 ss.14-15 myself. The Step 2 answer matches the source text. A person should check: (a) the band and the 0-10 to 5 conversion; (b) whether ss.14(4) and 15(5) earn credit as coordination; (c) the missing instruments listed in (3); (d) whether the BMLTA Amendment Bill 2025 has been enacted. | R5: The citation didn't settle every input. "Score" left blank: the Citation Sheet doesn't decide it.
A6: UPD1a | B6: Bengaluru – BMRDA | D6: =IFERROR(UPD1a!L17,"") -> 0 | H6: =IF(OR(F6="",NOT(ISNUMBER(D6))),"",IF(ABS(F6-D6)<0.001,"Yes","No")) | I6: =IF(ISNUMBER(F6),F6,D6) -> 0 | J6: =IF(ISNUMBER(F6),"Expert (overrides AI)",IF(ISNUMBER(D6),"AI","Not scored yet")) -> AI | K6: Left for a person | L6: Partially Answered | M6: ANSWER: I can't settle this from the Citation Sheet. The operative text of the BMRDA Act, 1985 on how the Structure Plan is prepared, and on who sits on the Authority, is not in the sheet. Nothing in the sources I read requires BMRDA to prepare its Structure Plan or schemes jointly with the ULG (GBA and its City Corporations), with ULG concurrence, or after consulting the ULG. The links that do exist run the other way. BMRDA has a duty to coordinate the city government's activities. Under the state planning Act (KTCP Act), Planning Authorities in the region must send their master plans to the State Government through BMRDA, which acts as Director of Town Planning for those plans. Neither of these is the ULG taking part in BMRDA's own plans. | EVIDENCE: (1) BMRDA side. The functions page on BMRDA's website (BMRDA-02) paraphrases the Act and is not the Act's own text. It lists: "To prepare a structure plan for thent [sic] of the Bangalore Metropolitan Region"; "To entrust to any local authority the work of execution of any development plan or town planning scheme"; "To co-ordinate the activities of the Bangalore Development Authority, the Corporation of the City of Bangalore, the Bangalore WaterSupply and Sewerage Board...". BMRDA's 2022-23 Annual Report (BMRDA-03, p.10) says these functions sit in s.9 of the Act. In this list BMRDA coordinates the ULG and may extend assistance to or entrust work to local authorities. None of the listed functions requires ULG consultation or co | N6: Annual Report of Bangalore Metropolitan Region Development Authority for the year 2022-2023 [01-04-2022 to 31-03-2023] [BMRDA-03] | O6: https://kla.kar.nic.in/council/house/Paperlaid/152/37.pdf | P6: The Executive Committee is chaired by the Minister for Urban Development, while the Metropolitan Commissioner is the Vice Chairman and the Mayor of Bangalore, the Secretaries to Government and heads of several related departments/ organisations are the Members. | Q6: I left the score blank for two separate reasons. (1) SCALE-MISMATCH. The Step 2 record says the rubric bands are 0/2.5/5/7.5/10, but the Max Score is 5. Under the v2 rules I can't map or interpolate a band, so the research team needs to confirm the scale before anyone scores this. (2) The evidence is incomplete, so I can't show affirmative absence. The Citation Sheet does not contain the text of the BMRDA Act 1985 itself (its Structure Plan preparation, publication and approval sections, or its membership provisions). It also lacks the BMRDA Rules and Regulations. Correction to Step 2: Step 2 says it found no ULG role. But the BMRDA 2022-23 Annual Report (BMRDA-03, p.10, Item 3) shows a formal ULG presence on BMRDA's governing bodies: - The Mayor of Bangalore sits on the Executive Committee. - The Act provides for the Government to nominate representatives of the Local Authorities from the Region to the Authority. However, the report says these nominated seats have been vacant since July 2005. This is the Annual Report's paraphrase, not the Act's text. It also predates GBA: the Mayor post and BBMP have since been replaced by GBA and its City Corporations. Someone needs to check: - whether the Executive Committee or the Authority approves the Structure Plan (the Revised Structure Plan-2031 was approved by Government order UDD/149/BMR/2014 dated 08/05/2017, per p.11); - whether a GBA-era official has replaced the Mayor. So a rubric 0 ('no formal role') is not supported. A positive band can't be set without the Act's text and the rubric definitions either. What else I checked: - BMRDA-02, the website functions page. It is a paraphrase of s.9. BMRDA coordinates the ULG and may entrust work to or assist local authorities. It does not mention ULG consultation or concurrence on the Structure Plan. - BMRDA-08, KTCP Act s.81-C. Master plans of Planning Authorities in the region are sent through BMRDA. This runs the opposite way: BMRDA has a role in their plans, not the ULG in BMRDA's. - BMRDA-10, the GBA Act (functions section, the BMPC under Art. 243ZE). BMRDA is not named in the GBA coordination list. I could not read the full BMPC clause. - BMRDA-11, BMLTA Act s.22. This concerns BMLTA, not a ULG role in BMRDA's plans. A person should obtain the BMRDA Act 1985 (sections on composition, the Executive Committee and the Structure Plan) and the BMRDA Rules. They should then confirm the rubric scale and score this. | R6: The citation didn't settle every input. "Score" left blank: the Citation Sheet doesn't decide it.
A7: UPD1a | B7: Surat – SUDA | D7: =IFERROR(UPD1a!L18,"") | H7: =IF(OR(F7="",NOT(ISNUMBER(D7))),"",IF(ABS(F7-D7)<0.001,"Yes","No")) | I7: =IF(ISNUMBER(F7),F7,D7) | J7: =IF(ISNUMBER(F7),"Expert (overrides AI)",IF(ISNUMBER(D7),"AI","Not scored yet")) -> Not scored yet | K7: Left for a person | L7: Insufficient Evidence | R7: Step 2 found no evidence: a source needs to be found and added. Step 2 found no evidence (Insufficient Evidence). Source needed: The full current consolidated text of the Gujarat Town Planning and Urban Development Act, 1976, specifically ss.9-17 and 19-22 on preparing, publishing, revising and sanctioning development plans and on UDA board composition, plus the town planning scheme sections, from an official Gujarat legislative or Urban Development Department source. Also the Gujarat Metropolitan Planning Committees Act, 2008, and the full GPMC Act 1949, to check for any ULG approval or consultation role in SUDA's plans.
A8: UPD1a | B8: Surat – GMRC | D8: =IFERROR(UPD1a!L19,"") | H8: =IF(OR(F8="",NOT(ISNUMBER(D8))),"",IF(ABS(F8-D8)<0.001,"Yes","No")) | I8: =IF(ISNUMBER(F8),F8,D8) | J8: =IF(ISNUMBER(F8),"Expert (overrides AI)",IF(ISNUMBER(D8),"AI","Not scored yet")) -> Not scored yet | K8: Left for a person | L8: Insufficient Evidence | R8: Step 2 found no evidence: a source needs to be found and added. Step 2 found no evidence (Insufficient Evidence). Source needed: Needed: the full text of the Metro Railways (Construction of Works) Act 1978 and the Metro Railways (Operation & Maintenance) Act 2002 (as amended in 2009), plus the central notification applying them to Surat, from an official Government of India source; GMRC's Memorandum and Articles of Association and the tripartite GoI–GoG–GMRC MoU; any Gujarat UMTA Act or notification; the current consolidated Gujarat Town Planning and Urban Development Act 1976 from the Gujarat Legislative Department; any Gujarat GO or Rules on metro-corridor or TOD planning that give Surat Municipal Corporation a consultation or concurrence role.
A9: UPD1b | B9: Bengaluru – BWSSB | D9: =IFERROR(UPD1b!L13,"") -> 5 | H9: =IF(OR(F9="",NOT(ISNUMBER(D9))),"",IF(ABS(F9-D9)<0.001,"Yes","No")) | I9: =IF(ISNUMBER(F9),F9,D9) -> 5 | J9: =IF(ISNUMBER(F9),"Expert (overrides AI)",IF(ISNUMBER(D9),"AI","Not scored yet")) -> AI | K9: Left for a person | L9: Insufficient Evidence | R9: Step 2 found no evidence: a source needs to be found and added. Step 2 found no evidence (Insufficient Evidence). Source needed: Any of these would answer the question: the BWSSB Vision Document / strategic Master plan 2050 itself, including its preparation, stakeholder-consultation and approval chapters; minutes of the BWSSB Board meeting and Consultative Committee (s.14) meetings that considered or approved it, with attendance and any GBA or City Corporation input; GBA or City Corporation council or Executive Committee resolutions or letters commenting on BWSSB plans; or a recent BWSSB annual report (after 2016-17) describing how the plan was prepared.
A10: UPD1b | B10: Bengaluru – BMTC | D10: =IFERROR(UPD1b!L14,"") | H10: =IF(OR(F10="",NOT(ISNUMBER(D10))),"",IF(ABS(F10-D10)<0.001,"Yes","No")) | I10: =IF(ISNUMBER(F10),F10,D10) | J10: =IF(ISNUMBER(F10),"Expert (overrides AI)",IF(ISNUMBER(D10),"AI","Not scored yet")) -> Not scored yet | K10: Left for a person | L10: Insufficient Evidence | R10: Step 2 found no evidence: a source needs to be found and added. Step 2 found no evidence (Insufficient Evidence). Source needed: BMTC's latest plan document (annual development plan, business or fleet plan, or route rationalisation plan) showing ULG inputs or concurrence. BMTC Board minutes recording GBA/City Corporation (or earlier BBMP) participation. GBA or City Corporation council or standing-committee resolutions or letters commenting on BMTC plans, and any BMTC replies. For Bengaluru bus priority lanes specifically: the joint ULB-BMTC proposal or DULT sanction record naming the ULG as co-applicant.
A11: UPD1b | B11: Bengaluru – BDA | D11: =IFERROR(UPD1b!L15,"") | H11: =IF(OR(F11="",NOT(ISNUMBER(D11))),"",IF(ABS(F11-D11)<0.001,"Yes","No")) | I11: =IF(ISNUMBER(F11),F11,D11) | J11: =IF(ISNUMBER(F11),"Expert (overrides AI)",IF(ISNUMBER(D11),"AI","Not scored yet")) -> Not scored yet | K11: Left for a person | L11: Insufficient Evidence | R11: Step 2 found no evidence: a source needs to be found and added. Step 2 found no evidence (Insufficient Evidence). Source needed: The documents from BDA's latest plan-making cycle: the latest Revised Master Plan or draft master plan and its report, especially any chapter on stakeholder or agency consultation. Also BDA Authority meeting minutes approving the draft plan; BBMP, GBA or City Corporation council or standing-committee resolutions, or letters commenting on the BDA draft plan; and any BDA record of how it considered and answered those ULG comments. A government notification or official statement would also be needed to show which body runs the current master-plan cycle for the Greater Bengaluru Area, and whether the KTCP (Amendment) 2025 has come into force.
A12: UPD1b | B12: Bengaluru – BMRCL | D12: =IFERROR(UPD1b!L16,"") | H12: =IF(OR(F12="",NOT(ISNUMBER(D12))),"",IF(ABS(F12-D12)<0.001,"Yes","No")) | I12: =IF(ISNUMBER(F12),F12,D12) | J12: =IF(ISNUMBER(F12),"Expert (overrides AI)",IF(ISNUMBER(D12),"AI","Not scored yet")) -> Not scored yet | K12: Left for a person | L12: Insufficient Evidence | R12: Step 2 found no evidence: a source needs to be found and added. Step 2 found no evidence (Insufficient Evidence). Source needed: Records from BMRCL's latest plan-making cycle showing what the ULG did: (a) the latest DPR (e.g. Phase-3 or later) with its stakeholder-consultation annex; (b) BMRCL letters asking BBMP, GBA or the City Corporations for comments, and their replies; (c) minutes of GBA authority meetings or City Corporation council or standing-committee meetings that discussed BMRCL plans (e.g. the Parking Policy or new corridors); (d) a GO or Board approval note for the Metro Parking Policy 2025 listing who was consulted; (e) a recent BMRCL annual report (FY2023-24 or later) describing coordination with the ULG.
A13: UPD1b | B13: Bengaluru – BMRDA | D13: =IFERROR(UPD1b!L17,"") | H13: =IF(OR(F13="",NOT(ISNUMBER(D13))),"",IF(ABS(F13-D13)<0.001,"Yes","No")) | I13: =IF(ISNUMBER(F13),F13,D13) | J13: =IF(ISNUMBER(F13),"Expert (overrides AI)",IF(ISNUMBER(D13),"AI","Not scored yet")) -> Not scored yet | K13: Left for a person | L13: Insufficient Evidence | R13: Step 2 found no evidence: a source needs to be found and added. Step 2 found no evidence (Insufficient Evidence). Source needed: Any of these would answer it: the RSP-2031 report (draft or final), especially any chapter on stakeholder consultation; BMRDA Authority or Executive Committee minutes from the RSP-2031 preparation and approval (2014-2017) showing BBMP or Mayor inputs; BBMP council or standing committee resolutions or letters commenting on the draft Structure Plan, and BMRDA's responses; or, if a new Structure Plan cycle has started, GBA-era consultation records.
A14: UPD1b | B14: Surat – SUDA | D14: =IFERROR(UPD1b!L18,"") | H14: =IF(OR(F14="",NOT(ISNUMBER(D14))),"",IF(ABS(F14-D14)<0.001,"Yes","No")) | I14: =IF(ISNUMBER(F14),F14,D14) | J14: =IF(ISNUMBER(F14),"Expert (overrides AI)",IF(ISNUMBER(D14),"AI","Not scored yet")) -> Not scored yet | K14: Left for a person | L14: Answered — Verified Source | M14: ANSWER: Yes, at the level of formal consultation. In SUDA's latest plan cycle in the Citation Sheet, the Development Plan 2035 (2013-2017), the Mayor of Surat Municipal Corporation (SMC) was formally invited on 22.04.2016 to discuss the plan, together with all MPs, MLAs and the Surat Zilla Panchayat President, and their suggestions were invited. The plan document gives no record of what SMC itself said or how SUDA considered or answered SMC's inputs. It also shows no joint preparation with SMC and no concurrence or approval by SMC. This matches the 5 band ('formally consulted or invited to provide inputs, but no evidence of how these inputs were considered'). | EVIDENCE: (1) SUDA-14, DP 2035 (2017), Ch.16 'Stakeholders Consultation', p.183 (doc p.166): 'All MP, MLA, Surat Zilla Panchayat President and Mayor (SMC) were invited on 22.04.2016 for detailed discussion on Development Plan 2035... their suggestions on the same were invited.' Table 116 (p.184 / doc p.167) gives only a combined count of 136 suggestions from all elected representatives, split by topic (Zoning 42, Road 39, Reservation 23, GDCR 16, SUDA Extension 7, Others 9). It does not say which came from the Mayor or SMC, and gives no response to them. (2) SUDA-14 §2.2 (pp.31-32): study groups, eight sub-committees and a Core Committee were formed. Ch.16 (p.183) says these committees 'included internal as well as external members' and that about 60 meetings were held. Members are not named, so no SMC role on these co | N14: DEVELOPMENT PLAN 2035 2017 SURAT URBAN DEVELOPMENT AUTHORITY [SUDA-14] | O14: https://www.sudaonline.org/wp-content/uploads/2017/03/SUDA-DP-2035-report-final-22.02.2017.pdf | P14: All MP, MLA, Surat Zilla Panchayat President and Mayor (SMC) were invited on 22.04.2016 for detailed discussion on Development Plan 2035. Discussion on various issues were carried out and their suggestions on the same were invited. | Q14: SCALE-MISMATCH. The Step 2 answer says the rubric runs 0-10 (top band 10 = substantive participation; band 5 = formally consulted or invited to give inputs, with no evidence of how they were considered). The Max Score is 5, and the input column also asks for 0-5. The question-bank anomaly rule says not to score a scale mismatch, so the Score is left blank. RAW BAND = 5 on the 0-10 rubric. A reviewer must decide how this maps to the 0-5 workbook scale. Do not just enter 5 or halve it to 2.5 without confirmation. The source supports Step 2's band reading: (1) SUDA-14 Ch.16, p.183: SMC's Mayor was invited on 22.04.2016, together with MPs, MLAs and the Zilla Panchayat President, to discuss DP 2035, and their suggestions were invited. (2) Table 116 gives only a combined count of 136 suggestions from all elected representatives. Nothing is attributed to SMC, and there is no record of how SUDA answered them. (3) §2.2 and Ch.16: the Core Committee and the eight sub-committees had 'internal as well as external members', but members are not named, so no SMC role is shown. (4) The SUDA Board in the 2016 SUDA Board list (§1.4.1, Table 5 in SUDA-14) includes SMC's Standing Committee Chairman, Municipal Commissioner and City Engineer. This is institutional design only. No Board minutes approving DP 2035 are in the Sheet. (5) The general public notice under s.13 is not ULG consultation. Please check: (a) how the 0-10 rubric maps to the 0-5 Max Score; (b) whether a mixed meeting of elected representatives that included the Mayor counts as formal ULG consultation; (c) whether SUDA Board or Core Committee minutes exist that could support a higher band. The Sheet has no SMC resolution or comments on DP 2035 and no SUDA response to SMC inputs. | R14: The citation didn't settle every input. "Score" left blank: the Citation Sheet doesn't decide it.
A15: UPD1b | B15: Surat – GMRC | D15: =IFERROR(UPD1b!L19,"") | H15: =IF(OR(F15="",NOT(ISNUMBER(D15))),"",IF(ABS(F15-D15)<0.001,"Yes","No")) | I15: =IF(ISNUMBER(F15),F15,D15) | J15: =IF(ISNUMBER(F15),"Expert (overrides AI)",IF(ISNUMBER(D15),"AI","Not scored yet")) -> Not scored yet | K15: Left for a person | L15: Answered — Verified Source | M15: ANSWER: Yes, for the latest plan cycle in the Citation Sheet (the Surat Metro Rail Phase-I DPR, December 2018), the DPR records substantive participation by Surat Municipal Corporation (SMC). SMC commissioned the Comprehensive Mobility Plan (CMP) and the travel-demand study the DPR is built on. Corridor options were presented to SMC authorities 'on various occasions', and the three corridors sent to the High Powered Committee were shortlisted 'on the suggestions of SMC & CEPT'. SMC's TOD revenue figures, land rates and its decision on the railway-station hub (MMTH) tunnel road were written into the DPR. This is documented consideration of, and response to, ULG input, which fits the top band ('substantive participation'). | EVIDENCE: (1) GMRC-08 DPR Ch.1 p.92: alignment options were 'presented before the concerned authorities of Surat Municipal Corporation (SMC) on various occasions', and 'on the suggestions of SMC & CEPT, following three corridors were shortlisted and presented before High Powered Committee (HPC)' on 13.01.2017. The HPC then approved 2 corridors (MoM letter GUDC/METRO/HPC/2017/182 dt 23.01.2017). (2) GMRC-08 Exec Summary pp.8-9 and Ch.2 pp.98-102: the CMP 2017 'got completed by Surat Municipal Corporation (SMC) through ... CEPT'. The demand estimate for Phase-I corridors was done by CEPT, 'entrusted this assignment by Surat Municipal Corporation (SMC) vide their letter No. CE.Spl.Cell/Out/339 dated 31.08.2016'. A gist of the CMP is included in the DPR. (3) GM | N15: DPR for Metro Rail Project in Surat, Gujarat (December 2018) [GMRC-08] | O15: https://www.gujaratmetrorail.com/wp-content/uploads/DPR/Surat-DPR-2020_opt.pdf | P15: Subsequently, on the suggestions of SMC & CEPT, following three corridors were shortlisted and presented before High Powered Committee (HPC) in a meeting held on 13.01.2017 at Ahmedabad | Q15: I left the Score blank because of SCALE-MISMATCH. Step 2 and the question-bank anomaly note for UPD 1b both say the top rubric band is 'raw 10', while the input runs 0 to 5. The top band is not the Max Score and is not a sum of components, so I am not converting it. The team needs to confirm how the 10-point rubric maps onto the 0-5 input. The evidence itself fits the top band ('substantive ULG participation: documented consideration of and response to ULG inputs'). I checked these points against GMRC-08 (DPR, December 2018, Phase-I): (1) The alignment options were presented to SMC 'on various occasions'. The three corridors sent to the HPC were then shortlisted 'on the suggestions of SMC & CEPT' (Ch.1 p.92). (2) SMC commissioned the CMP 2017 and the CEPT demand study (letter CE.Spl.Cell/Out/339 dated 31.08.2016). The DPR says it was prepared 'in line with' that study (Exec Summary §0.2.1, §0.3; Ch.2 §2.3.1). (3) The MMTH integration and tunnel-road decision came out of 'a series of meetings ... in the office of The Commissioner, Surat Municipal Corporation'. SMC supplied the cost estimate, and the executing agency is to be decided 'in consultation with SMC' (§0.19.2; Ch.19 §19.13). (4) SMC's TOD revenue figures (letter dated 22-12-2017) were written into the DPR (Ch.18 p.692). Points a person should check: (a) Final corridor approval came from a state HPC, not SMC. SMC shaped the inputs and the shortlist but did not concur or approve. (b) The DPR was prepared by DMRC at the request of GoG/MEGA. GMRC-25 says MEGA is GMRC's former name, which is what ties this plan to GMRC. (c) I could not see Annexure-A / Table 1.7, the list of SMC presentations. (d) The Citation Sheet has no Phase-II plan, so it is unconfirmed that this is the latest plan cycle. (e) The task input leaves the ULG blank. Only the DPR names SMC as the city corporation. (f) GMRC-09, -10 and -11 record consultations with communities and the public, not with the ULG. If the team confirms the top band maps to the Max Score, the evidence would support 5, subject to points (d) and (e). | R15: The citation didn't settle every input. "Score" left blank: the Citation Sheet doesn't decide it.
A16: UPD2a | B16: Bengaluru – BWSSB | D16: =IFERROR(UPD2a!L13,"") -> 0 | H16: =IF(OR(F16="",NOT(ISNUMBER(D16))),"",IF(ABS(F16-D16)<0.001,"Yes","No")) | I16: =IF(ISNUMBER(F16),F16,D16) -> 0 | J16: =IF(ISNUMBER(F16),"Expert (overrides AI)",IF(ISNUMBER(D16),"AI","Not scored yet")) -> AI | K16: Left for a person | L16: Partially Answered | M16: ANSWER: I can't confirm or rule out a mandate from the Citation Sheet. The BWSSB Act says nothing about it: it contains no provision, with either 'shall' or 'may', requiring BWSSB's water supply or sewerage schemes to conform to or be consistent with a city, metropolitan or regional master plan or development plan. On the city government (ULG) side, the Greater Bengaluru Governance Act gives the Greater Bengaluru Authority (GBA) binding coordination and direction powers over BWSSB. It does not state a duty on BWSSB to make its plans consistent with the master plan. The Karnataka Town and Country Planning Act, 1961, which the methodology says to review, is not in the Citation Sheet. So I can't establish that no such provision exists, which a score of 0 would require. | EVIDENCE: (1) BWSSB Act 1964 (BWSSB-02). s.15(1) gives the general duty to supply water and provide sewerage in the Bangalore Metropolitan Area. Under s.15(2)(b)-(c) 'it shall be the duty of the Board to take steps from time to time' to prepare and carry out water supply and sewerage schemes. The proviso says schemes costing over Rs 1 crore need 'the approval of the State Government'. s.15(3) sets what schemes must contain (piped supply to every part with houses, and so on). None of these refers to a master plan or development plan. Other provisions: s.14 creates an advisory Consultative Committee (advises on 'major questions of policy and major schemes'), which is advice, not a consistency duty. Under s.89 the | N16: The Greater Bengaluru Governance Act, 2024 Act No. 36 of 2025 [BWSSB-04] | O16: https://prsindia.org/files/bills_acts/acts_states/karnataka/2025/Act36of2025KA.pdf | P16: issuing directions for the same which shall be binding; and all the public authorities shall cooperate with the Greater Bengaluru Authority for successful coordination and obey its directions issued, in discharge of functions assigned in this Act. | Q16: I left the score blank. The Citation Sheet doesn't show whether there is a legal requirement for BWSSB's plans to be consistent with a city, metropolitan or regional master plan or development plan, and a 0 needs affirmative absence, which I can't show. I agree with the Step 2 answer. (1) BWSSB Act 1964 (BWSSB-02), PRS copy as amended up to 2010. I re-read s.15(1)-(7), the general duties and schemes. s.15(2)(b)-(c) say 'it shall be the duty of the Board to take steps from time to time' to prepare and carry out water supply and sewerage schemes. The proviso requires State Government approval for schemes over Rs 1 crore. s.15(3) sets what schemes must contain. None of these refers to a master plan or development plan. The Step 2 answer also reports that s.14 (advisory Consultative Committee) and s.89 (State directions) have no conformity clause. (2) Greater Bengaluru Governance Act 2024, Act 36 of 2025 (BWSSB-04), which is the city government (ULG) side, GBA era. s.14(2)(a) makes GBA the Planning Authority under the KTCP Act 1961. s.14(3)(b) gives GBA binding directions for coordinating the execution of schemes that implement GBA plans. s.14(4) names BWSSB among the public authorities GBA integrates and supervises, and those authorities 'shall cooperate... and obey its directions'. s.15(1) puts the master plan on GBA. The duty to 'incorporate the infrastructure development plan' falls on the City Corporations, not BWSSB. s.15(5) says agencies are 'bound to assist'. s.19 covers State Government directions. These are binding direction and coordination powers held by GBA and the State. None of them is an express requirement that BWSSB's own plans or schemes conform to the master plan. Whether a binding direction power counts as the middle band (alignment that is discretionary or not mandated) is a judgement for the team: CONFIRM. (3) Missing layers: the Karnataka Town and Country Planning Act 1961 isn't in the Sheet. It is the instrument most likely to make master plans or development plans binding on public authorities or their works, and the methodology says to review it. BWSSB Rules (s.87), BWSSB Regulations (s.88) and any GO on BWSSB planning are also not in the Sheet. Searches of the Sheet for 'master plan conform consistent development plan public authorities' and 'Town and Country Planning Act comprehensive development plan Board schemes' found nothing beyond the GBA Act provisions above. (4) Era: the PRS copy of the BWSSB Act still names the Bruhat Bangalore Mahanagara Palike. No source in the Sheet shows GBA or the City Corporations substituted into the BWSSB Act: CONFIRM. To score this, the team needs to add the official text of the KTCP Act 1961 (current amended version), especially the provisions on the effect of master plans on public authorities and their development, and confirm the band for the GBA direction powers. | R16: The citation didn't settle every input. "Score" left blank: the Citation Sheet doesn't decide it.
A17: UPD2b | B17: Bengaluru – BWSSB | D17: =IFERROR(UPD2b!L13,"") | H17: =IF(OR(F17="",NOT(ISNUMBER(D17))),"",IF(ABS(F17-D17)<0.001,"Yes","No")) | I17: =IF(ISNUMBER(F17),F17,D17) | J17: =IF(ISNUMBER(F17),"Expert (overrides AI)",IF(ISNUMBER(D17),"AI","Not scored yet")) -> Not scored yet | K17: Left for a person | L17: Insufficient Evidence | R17: Step 2 found no evidence: a source needs to be found and added. Step 2 found no evidence (Insufficient Evidence). Source needed: (1) BWSSB's current water supply and sewerage master plan or 2050 vision and strategic master plan document, showing its population source and how it sets service areas and sites major works (treatment plants, pumping stations, reservoirs, trunk mains). (2) The applicable statutory spatial plan for the same area: the BDA Revised Master Plan in force, or any GBA- or BMRDA-era development or regional plan, with its land-use and growth framework and population projections. (3) Where readily available, land-use conversion or regularisation orders or records for major BWSSB treatment plants or trunk infrastructure.
A18: UPD2c | B18: Bengaluru – BMTC | D18: =IFERROR(UPD2c!L14,"") -> 2.5 | H18: =IF(OR(F18="",NOT(ISNUMBER(D18))),"",IF(ABS(F18-D18)<0.001,"Yes","No")) | I18: =IF(ISNUMBER(F18),F18,D18) -> 2.5 | J18: =IF(ISNUMBER(F18),"Expert (overrides AI)",IF(ISNUMBER(D18),"AI","Not scored yet")) -> AI | K18: Left for a person | L18: Partially Answered | M18: ANSWER: No source in the Citation Sheet says that BMTC 'shall' (or 'may') make its own spatial or sectoral plan consistent with the city master plan or the metropolitan/regional plan. The only binding consistency duty found is indirect, and it ties BMTC to the Comprehensive Mobility Plan (CMP), not to a master plan. Under the Bengaluru Metropolitan Land Transport Authority (BMLTA) Act, an 'Urban Transport Agency' such as BMTC needs BMLTA approval for major urban transport projects, judged on consistency with the CMP. BMLTA prepares the CMP 'in conjunction with' the applicable land use plan. Whether this two-step chain, or the general Town and Country Planning (T&CP) rule that all development must conform to the master plan, counts for this question is a methodology call. Score left blank. | EVIDENCE: (1) Parastatal Act: Road Transport Corporations Act, 1950 (BMTC-02). s.3 (setting up corporations: coordination with other transport), s.5 (Board), s.18 (general duty: 'efficient, adequate, economical and properly co-ordinated system of road transport services'), s.19 (powers), s.20 (route extension schemes). None of these mentions a master plan, a development plan or a land-use plan. (2) BMLTA Act, 2022 (Karnataka Act 6 of 2023; PRS text with Act 10 of 2026 appended) (BMTC-06). s.2(ff): 'Urban Transport Agency' means 'both the private and public agencies engaged in providing of Urban Mobility'. The Statement of Objects names the Bengaluru Metropolitan Transport Corporation among | N18: The Bengaluru Metropolitan Land Transport Authority Act, 2022 Act No. 6 of 2023 (Amendment appended: 10 of 2026) [BMTC-06] | O18: https://prsindia.org/files/bills_acts/acts_states/karnataka/2023/Act6of2023Karnataka.pdf | P18: (a) The Sectoral Mobility Investment Program shall be aligned with the goals of the Comprehensive Mobility Plan; (b) The Sectoral Mobility Investment Program shall be prepared in consultation with the Authority; | Q18: Score left blank. The Citation Sheet does not support 2.5 (BMTC 'shall' make its plans consistent with the master/metropolitan plan) or 1.25 (a 'may' provision). It also does not establish affirmative absence, so 0 cannot be given. I checked the Step 2 answer against the sources and add these findings. (1) BMTC-06 s.24(a) is a binding 'shall', but it ties the Sectoral Mobility Investment Program of each Urban Transport Agency to the goals of the Comprehensive Mobility Plan (CMP), not to the master plan. Step 2 had not read s.24; this is the strongest provision found. s.25(1)(c) also requires extra Annual Implementation Plan projects to 'align with the Comprehensive Mobility Plan goals'. s.19(1) adds project approval 'from the perspective of consistency with the Comprehensive Mobility Plan'. The CMP is prepared by BMLTA 'in conjunction with ... the land use plan' (s.21(2)), so the link to the master plan is indirect and is BMLTA's duty, not BMTC's. (2) BMTC-04 (GBA Act 36 of 2025): s.14(4) names BMTC among the public authorities that GBA integrates and supervises. GBA's directions are binding, and BMTC must incorporate GBA's coordinating role in its Memorandum of Association. s.14(3)(b) makes GBA directions binding when it coordinates schemes that implement plans prepared by GBA. s.15(1) makes GBA responsible for the 'master plan and mobility plans', but only the City Corporations are told they 'shall incorporate' GBA's infrastructure development plan; BMTC is not. These are coordination and direction powers, not a mandate that BMTC's own plans be consistent with the master plan. (3) BMTC-07, Karnataka Town and Country Planning (KTCP) Act s.14(1): every development must conform to the Master Plan. This is general development control, not plan consistency, and BMLTA s.60(2) may override it. (4) BMTC-02, Road Transport Corporations Act 1950 (s.3, 5, 18, 19, 20): no mention of a master plan. Gaps: there are no Karnataka rules under the 1950 Act, no BMLTA Rules or Regulations (s.54(ix) leaves the procedure for the City Mobility Investment Program (CMIP) and Sectoral Mobility Investment Programs to regulations), and no BMTC MoA (which s.14(4) of the GBA Act requires to be amended). BMTC-20 (BMTC 'Rules And Regulations' page) was not shown to me. FOR THE TEAM: (a) Does a binding 'shall align with the CMP' duty (BMLTA s.24(a)) meet the 2.5 band, when the CMP is a metropolitan mobility plan prepared with the land use plan? If yes, 2.5 is supported by BMTC-06 s.24(a). If the question requires conformity with the statutory master, metropolitan or regional spatial plan, the result stays 'not found' until the Rules, Regulations and MoA are checked. (b) Please confirm BMTC is an 'Urban Transport Agency' under s.2(ff); BMTC is named only in the Statement of Objects. Source is the PRS text (Act 6 of 2023, with Amendment Act 10 of 2026 appended); this is a secondary source. | R18: The citation didn't settle every input. "Score" left blank: the Citation Sheet doesn't decide it.
A19: UPD2d | B19: Bengaluru – BMTC | D19: =IFERROR(UPD2d!L14,"") | H19: =IF(OR(F19="",NOT(ISNUMBER(D19))),"",IF(ABS(F19-D19)<0.001,"Yes","No")) | I19: =IF(ISNUMBER(F19),F19,D19) | J19: =IF(ISNUMBER(F19),"Expert (overrides AI)",IF(ISNUMBER(D19),"AI","Not scored yet")) -> Not scored yet | K19: Left for a person | L19: Insufficient Evidence | R19: Step 2 found no evidence: a source needs to be found and added. Step 2 found no evidence (Insufficient Evidence). Source needed: Needed: (1) BMTC's current network or route-rationalisation plan, fleet and depot expansion plan, Sectoral Mobility Investment Programme or Annual Implementation Plan under the BMLTA Act ss.24-25, or the 'BMTC Vision 2025' document itself. Any of these should show whether master-plan growth corridors, land use or density projections decide where routes, depots and terminals go. (2) The applicable statutory master plan for Bengaluru: the current revised master plan, or any GBA or BMPC development plan. (3) The Bengaluru Comprehensive Mobility Plan, if BMTC's planning flows through it. (4) For the context check, which does not affect the score: land-use conversion or regularisation records, or BMTC annual report or board notes, for major depots and TTMCs.
A20: UPD3a | B20: Bengaluru – BWSSB | D20: =IFERROR(UPD3a!L13,"") -> 2.5 | H20: =IF(OR(F20="",NOT(ISNUMBER(D20))),"",IF(ABS(F20-D20)<0.001,"Yes","No")) | I20: =IF(ISNUMBER(F20),F20,D20) -> 2.5 | J20: =IF(ISNUMBER(F20),"Expert (overrides AI)",IF(ISNUMBER(D20),"AI","Not scored yet")) -> AI | K20: Left for a person | L20: Partially Answered | M20: ANSWER: Only partly answered. The BWSSB Act contains one binding, general access duty: water supply schemes 'shall' provide piped water to every part of the Bangalore Metropolitan Area that has houses. Where pipes are not practicable at reasonable cost, the scheme must provide a public supply within a reasonable distance of every house. That duty is limited by reasonable cost and covers only water supply schemes, not sewerage. No source in the Citation Sheet sets an explicit requirement on women, the urban poor or slums, persons with disabilities, affordability or concessional tariffs, a minimum or lifeline supply, or access regardless of land tenure. The tariff regulations and the water supply regulations are not in the Citation Sheet, so the score is not decided. | EVIDENCE: (1) BWSSB Act 1964 (PRS text), s.15(2)(b) and s.15(3)(a)-(b), parastatal side: a scheme 'shall inter alia make provision' for piped wholesome water to every part with houses, 'at a reasonable cost'. Where piping is impracticable and the existing supply endangers health, it must provide a supply 'as far as possible' within 'a reasonable distance of every house'. Under s.15(4) the State Government settles any dispute on 'reasonable cost'. s.15(5): the Board 'shall', 'as far as is reasonably practicable', make sure every house has enough water, by using its powers over house owners. (2) s.38(1): the Board 'may', subject to payment by the city corporation (BBMP), 'provide gratuitous supply of wholesome wate | N20: The Bangalore Water Supply and Sewerage Act, 1964 [BWSSB-02] | O20: https://prsindia.org/files/bills_acts/acts_states/karnataka/1964/1964KR36.pdf | P20: A scheme under clause (b) of sub-section (2) shall inter alia make provision,— (a) for a supply of wholesome water in pipes to every part of the Bangalore Metropolitan Area in which there are houses, for the domestic purposes of the occupants thereof | Q20: SCORE LEFT BLANK. This prompt did not give me the question text, the Detailed Methodology or the rubric bands for UPD3a, so I cannot match the evidence to a band. A person must apply the rubric. I checked the Step 2 answer against the source and it holds: (1) BWSSB-02, s.15(3)(a)-(b): a binding 'shall' duty. Water supply schemes must provide piped water to every part of the Bangalore Metropolitan Area that has houses. Where pipes are not practicable at reasonable cost, they must provide a public supply within a reasonable distance of every house. The duty is limited by reasonable cost and practicability (s.15(4): the State Government decides those questions). It covers water supply only, not sewerage. (2) s.38(1) (free public supply through hydrants) and s.61A(d) (bye-laws for 'equitable distribution of water supplied to occupiers') both say 'may', so they are discretionary. (3) The Act has no provision on women, the urban poor or slums, persons with disabilities, lifeline or concessional tariffs, or access regardless of land tenure. (4) BWSSB-13 (website 'Our Services', undated) describes services for the urban poor: lower connection charges (Rs.550 for houses up to 150 sq.ft.; Rs.800 for 151-600 sq.ft.), payment in two instalments, any proof of residence accepted, and shared connections for communities without tenure security. The page cites no regulation, Board resolution or GO for these measures. It describes a programme that dates from 2003-2006 and the JICA project. It is not a binding instrument. I searched the Citation Sheet for tariff, lifeline, slum and concession provisions. None of the BWSS water supply/sewerage regulations (the website cites 'regulation 5.1'), tariff notifications, Board resolutions or GOs is in the sheet. This is the regulations and tariff layer. A 0 is not supportable for two reasons: there is no affirmative absence, and the s.15(3) universal-access duty exists. The top band cannot be judged until the regulations and tariff layer is seen. Step 2 gave a provisional 2.5, which depends on two things the team must confirm: whether that band exists in the rubric (a SCALE-MISMATCH or RUBRIC-GAP check), and whether a general universal-supply duty counts as an equity requirement. Period: the Act text is the PRS copy, as amended up to Act 15 of 2010. Later amendments were not verified. The Act still names BBMP. Whether GBA or the city corporations have been substituted is not verified and should be flagged for the team. | R20: The citation didn't settle every input. "Score" left blank: the Citation Sheet doesn't decide it.
A21: UPD3b | B21: Bengaluru – BWSSB | D21: =IFERROR(UPD3b!L13,"") -> 2.5 | H21: =IF(OR(F21="",NOT(ISNUMBER(D21))),"",IF(ABS(F21-D21)<0.001,"Yes","No")) | I21: =IF(ISNUMBER(F21),F21,D21) -> 2.5 | J21: =IF(ISNUMBER(F21),"Expert (overrides AI)",IF(ISNUMBER(D21),"AI","Not scored yet")) -> AI | K21: Left for a person | L21: Partially Answered | M21: ANSWER: In part. BWSSB's own website shows measures for slum residents and the urban poor: lower connection charges, payment in instalments, simpler documents, shared connections for communities with no land tenure, free water meters and waiver of interest on overdue bills in slums. It also mentions a JICA-assisted Slum Development component meant to cover all slums in the core area. All of this is undated or historical (2000–2006 pilots, the BBMP era, a JBIC/JICA project said to be 'currently under implementation'). No current water-supply plan, current tariff order or design standard is in the Citation Sheet. No measure for women, persons with disabilities or elderly people was found in the sources read. So the evidence does not show current practice, and Component 2 cannot be decided. | EVIDENCE: (1) BWSSB-13, 'Our Services' page, section 'Services for Urban Poor – BWSSB's Experiments and Future Plans'. This is the Board's official page, era: BBMP-era (it refers to the 'BBMP area'). (a) Affordability: 'BWSSB has offered a rationalized reduction in the connection rates' by house size, ≤150 sq ft pays only the Rs.550 meter cost; 'slum dwellers are allowed to pay the connection charges in two installments'; simpler connection papers (hakku patras, ration card, election ID card, KSCB ID). (b) Coverage/service planning: 'shared metered connections, on payment... for... communities without security of tenure are being provided'; a Social Development Unit working with NGOs and CB | N21: Our Services - Bangalore Water Supply and Sewerage Board [BWSSB-13] | O21: https://bwssb.karnataka.gov.in/info-1/Our+Services/en | P21: BWSSB has offered a rationalized reduction in the connection rates. A house with an area of 150 sq.ft. is required to pay only the meter cost of Rs.550/; between 151sq.ft. and 600 sq.ft. RS. 800/ (meter cost of Rs.550 + Rs.250 as cost of UGD connection) and a house above 600 sq. ft. has to pay the regular rates. | Q21: I left the score blank. I agree with the Step 2 answer, which matches the source. BWSSB-13 is the Board's official page on karnataka.gov.in, but it is undated and refers to the 'BBMP area' (BBMP-era wording). It describes these slum measures: lower connection charges by house size, payment in two instalments, simpler documents (hakku patras, ration card, election ID), and shared metered connections 'for... communities without security of tenure'. On their face these would meet Component 1, which Step 2 put at 2.5: one affordability measure plus one slum-coverage measure that does not depend on land tenure. But the programmes the page names are historical: the AusAID pilot (2000-02), the Package Programme (2003-06) and a JBIC/JICA slum component still described as 'currently under implementation'. Nothing dates these measures to the current plan, and this is an Implementation question about current practice. BWSSB-41 (Achievements: free meters for slum households, interest waiver on overdue bills) is also undated. I re-read BWSSB-07: its ongoing-projects item '6. Slum Developme[nt]' is cut off in the saved text and could not be read. Its Vision Document 2050 passage is generic and has no equity content. A search of the whole Citation Sheet for women, persons with disabilities, elderly people, public taps and design found nothing on BWSSB service design. The only hits were the GBG Act (BWSSB-04) Schedule I social-welfare functions, which belong to the city government, not the Board. Component 2 (gender, disability, elderly, siting or design) therefore cannot be scored 0, because absence is not affirmative. These documents are not in the Citation Sheet: the Vision Document 2050 PDF, the 2025 water tariff ready reckoner, any current slum or lifeline tariff order, current DPRs (CWSS Stage V, 110 villages), and a recent annual report (BWSSB-29 covers FY2016-17 and only contains a generic 'equitably' objective). Note: the full question text and Detailed Methodology were not in the task input. The component split (C1 up to 2.5, C2 up to 2.5) comes from the Step 2 notes and should be confirmed. Reviewer actions: (1) confirm whether the undated website text can count as the current framework; (2) add and read the Vision Document 2050, the Tariff 2025 and the full BWSSB-07 'Slum Development' item; (3) send the RTI to the BWSSB PIO on current slum, EWS and BPL concessions and any gender or disability design standards, FY2024-26. | R21: The citation didn't settle every input. "Score" left blank: the Citation Sheet doesn't decide it.
A22: UPD4a | B22: Bengaluru – BMTC | D22: =IFERROR(UPD4a!L14,"") | H22: =IF(OR(F22="",NOT(ISNUMBER(D22))),"",IF(ABS(F22-D22)<0.001,"Yes","No")) | I22: =IF(ISNUMBER(F22),F22,D22) | J22: =IF(ISNUMBER(F22),"Expert (overrides AI)",IF(ISNUMBER(D22),"AI","Not scored yet")) -> Not scored yet | K22: Left for a person | L22: Partially Answered | M22: ANSWER: None of the binding instruments in the Citation Sheet requires BMTC itself to consider the mobility needs of women, the urban poor or other vulnerable groups. The only binding provision found is in the BMLTA Act, 2022. It requires the Comprehensive Mobility Plan, which the Bengaluru Metropolitan Land Transport Authority (BMLTA) prepares, to include accessible mobility for persons with disabilities. BMTC is bound by this only indirectly: it has to follow BMLTA's policies, standards and plan. No binding provision on women, the urban poor, affordability or service to peripheral areas was found. The BMTC parent Act only lets the Corporation give free or concessional passes if it chooses ('may'). | EVIDENCE: (1) Road Transport Corporations Act, 1950 (BMTC-02). s.18 sets a general duty to provide an 'efficient, adequate, economical and properly co-ordinated system of road transport services'. This is generic wording and names no vulnerable group. Its proviso says the duty cannot be enforced in any court or tribunal. s.19(1)(d) gives a power, not a duty, 'to authorise the issue of passes to its employees and other persons either free of cost or at concessional rates and on such conditions as it may deem fit to impose'. s.34 lets the State Government issue general instructions, but no such instruction on concessions or vulnerable groups is in the sheet. (2) BMLTA Act, 2022 (Karnataka Act 6 of 2023), with amending Act 10 of 2026 appended (BMTC-06). The Comprehensive Mobility P | N22: The Bengaluru Metropolitan Land Transport Authority Act, 2022 Act No. 6 of 2023 (Amendment appended: 10 of 2026) [BMTC-06] | O22: https://prsindia.org/files/bills_acts/acts_states/karnataka/2023/Act6of2023Karnataka.pdf | P22: (h) accessible mobility and transport for persons who are persons with benchmark disability and p erson with disability as defined under the Rights of persons with Disabilities Act, 2016 (Central Act 49 of 2016); | Q22: Score left blank. Neither 2.5 nor 0 can be given safely on this evidence. **What the evidence shows** (1) The only binding provision on a vulnerable group is in the BMLTA Act. It uses 'shall include' for accessible mobility for persons with disabilities (item (h)). That duty sits on BMLTA's own Comprehensive Mobility Plan, not on BMTC. BMTC is bound only indirectly: plans made by other authorities must comply with BMLTA's Urban Mobility policies (first proviso), and agencies are bound by BMLTA's standards (s.14(1)(e), as Step 2 reports). Whether an indirect mandate covering one group counts as BMTC being 'mandated' is a judgement call for the team. If it does, the evidence fits the 'specific groups' band (2.5). (2) Road Transport Corporations Act, 1950 (BMTC-02): - s.19(1)(d), on passes 'free of cost or at concessional rates', is a power ('may'), not a duty. - The s.18 duty is generic, names no vulnerable group, and its proviso makes it unenforceable. (3) I checked the Step 2 answer against the sources and also looked at: - BMTC-20 (the Rules and Regulations page). It lists only KSRTC employee and service regulations plus the KSRTC Rules, 1961. Those Rules are linked but their text is not in the sheet. - BMTC-27 (Student Pass 2026-27). It says passes are issued free 'As per the directions of the Government of Karnataka'. That points to a state direction for students, but the order itself is not in the sheet, so it cannot be cited as a binding instrument. - BMTC-25 (DULT, the Directorate of Urban Land Transport). It has a generic line on 'equality of access ... for all economic classes'. This is a departmental webpage, not a mandate on BMTC. (4) Not credited, because none of these is a binding instrument: BMTC-32 (mission: 'Extend travel concession to the weaker sections'), BMTC-28 (one-off free travel for women on Women's Day 2023), and BMTC-27 (website description). **Why 0 is not available** Affirmative absence is not established. The sheet does not contain: - any state GO on concessions (free travel for women, students, senior citizens, persons with disabilities); - BMTC's Memorandum of Association or regulations on service or fares; - the KSRTC Rules, 1961 text; - BMLTA Rules, regulations or Urban Mobility policies; - the RPwD Act, 2016 transport accessibility standards. **Other issues** - The Detailed Methodology and band text were not given in this task. The 2.5 'limited to specific groups' band is taken from the Step 2 notes and should be confirmed. - BMTC's legal form needs checking: the GBA Act s.14(4) calls it a 'Corporation Limited' with a Memorandum of Association, while BMTC-02 is the 1950 Act. - The team should add the missing concession GOs and BMLTA policies, then re-score. **Period covered** BMLTA Act as enacted (2023), with amending Act 10 of 2026 appended; BMTC website pages as of 30-09-2026. | R22: The citation didn't settle every input. "Score" left blank: the Citation Sheet doesn't decide it.
A23: UPD4b | B23: Bengaluru – BMTC | D23: =IFERROR(UPD4b!L14,"") -> 1.25 | H23: =IF(OR(F23="",NOT(ISNUMBER(D23))),"",IF(ABS(F23-D23)<0.001,"Yes","No")) | I23: =IF(ISNUMBER(F23),F23,D23) -> 1.25 | J23: =IF(ISNUMBER(F23),"Expert (overrides AI)",IF(ISNUMBER(D23),"AI","Not scored yet")) -> AI | K23: Left for a person | L23: Partially Answered | M23: ANSWER: Partly established. BMTC does run fare measures for some vulnerable groups. In 2026-27 it issues student passes free of charge. It sells senior-citizen passes at a lower price. Its homepage lists a 'Physically Challenged Scheme' and the 'Shakthi Scheme', though only by title. Its tender index also shows the women's safety work funded under the Nirbhaya scheme: an implementation agency chosen in 2020 and a functional audit in 2023 for a mobile app with a women's safety feature and an in-bus surveillance system in city buses. The Citation Sheet has no route or coverage commitment for an identified vulnerable group, such as informal settlements, low-income or peripheral areas, or last-mile links for underserved settlements. The metro-feeder and new-route announcements are general service changes. The Sheet also has no accessible-design measures (low-floor buses, ramps, priority seating), no gender screening in planning, and no BMTC mobility plan or service-design framework. | EVIDENCE: (1) BMTC-27, BMTC Student Pass page, 'Student Pass 2026-27' (last updated 30-09-2026): 'Bangalore Metropolitan Transport Corporation is issuing student passes at a free from the date of its formation for the benefit of students community'. This is an affordability measure for students. (2) BMTC-30, KarnatakaOne BMTC services page (reviewed 14 July 2026): 'Black Board Pass Rs 725/-' vs 'Sr. Citizen Black Board Pass Rs 650/-', and 'Pushpak Pass Rs 925/-' vs 'Sr. Citizen Pushpak Pass Rs 830/- | N23: Student Pass - Bengaluru Metropolitan Transport Corporation [BMTC-27] | O23: https://mybmtc.karnataka.gov.in/info-3/Student+Pass/en | P23: Bangalore Metropolitan Transport Corporation is issuing student passes at a free from the date of its formation for the benefit of students community. | Q23: I left the score blank because two of the score components can't be decided from the Citation Sheet. I don't have the Detailed Methodology text, so I relied on the band structure set out in the Step 2 notes. A reviewer should check those bands against the question bank. Component 1, part (i), fare affordability for vulnerable groups: met for students and the elderly. (a) BMTC-27 (2026-27) says BMTC issues student passes free of charge (quoted above). (b) BMTC-30 (KarnatakaOne page, reviewed 14-07-2026) lists cheaper senior-citizen passes (Black Board Rs 650 vs Rs 725; Pushpak Rs 830 vs Rs 925). That page also says rates are subject to change and gives no date for them. (c) BMTC-32, the Vision and Mission page, lists 'Extend travel concession to the weaker sections of the society' as a mission. That is a general commitment, so I gave it no separate credit. Component 1, part (ii), route or coverage measures for an identified vulnerable group: not found. My searches for route coverage, underserved areas, slums and last-mile links returned only generic text (e.g. BMTC-32: 'serving urban, sub-urban and rural areas', 'every nook and corner of the city'). The metro-feeder and new-route press releases in BMTC-28 name no vulnerable group. The Sheet has no BMTC route-planning document or mobility plan, so absence is not established and I can't score this part 0. Component 2, a planning or design framework with specific operational measures: BMTC-10 shows the Nirbhaya-scheme women's-safety app, in-bus surveillance and passenger information system tenders: implementation agency selected on 01/12/2020, functional-audit agency on 30/8/2023, and a further tender on 16/10/2023. Only the tender titles are in the Sheet. Nothing shows the system is running now, or whether this counts as a 'current framework' for the top band. My search for low-floor, wheelchair or accessible-bus measures found nothing about BMTC. The only hit was the BMLTA Act's Comprehensive Mobility Plan clause in BMTC-06, which binds the BMLTA, not BMTC, so I gave it no credit. BMTC-01 links the 'Physically Challenged Scheme' and 'Shakthi Scheme' write-ups by title only; their terms are not in the Sheet. This is a VERIFICATION-LIMIT, not a negative finding. The Step 2 answer gives a range of 2.5 to 5. Picking any single number would be a guess, so I propose none. To settle the score, a reviewer needs: (1) the Shakti and Physically Challenged scheme write-ups (PDFs linked from BMTC-01); (2) any BMTC route or service plan naming underserved or low-income areas; (3) current evidence that the Nirbhaya system is operating, plus any accessible-fleet specifications; (4) the question's Detailed Methodology text to confirm the component bands; (5) a dated screenshot, which the question bank requires. | R23: The citation didn't settle every input. "Score" left blank: the Citation Sheet doesn't decide it.
A24: UPD5a | B24: Bengaluru – BWSSB | D24: =IFERROR(UPD5a!L13,"") -> 2.5 | H24: =IF(OR(F24="",NOT(ISNUMBER(D24))),"",IF(ABS(F24-D24)<0.001,"Yes","No")) | I24: =IF(ISNUMBER(F24),F24,D24) -> 2.5 | J24: =IF(ISNUMBER(F24),"Expert (overrides AI)",IF(ISNUMBER(D24),"AI","Not scored yet")) -> AI | K24: Left for a person | L24: Partially Answered | M24: ANSWER: The Board's own Act has some explicit environmental provisions, but each covers only one function or concern. No provision found requires BWSSB to consider environmental sustainability across its core planning and service-delivery duties. The general duty in s.15(1)-(3) covers supplying wholesome water and providing sewerage and sewage disposal. It says nothing about sustainable sources, conservation, cutting water losses, reuse or climate resilience. The specific provisions are: (i) s.15(6) gives the Board a power ('shall also have power to insist'), not a duty, to make owners adopt rainwater harvesting and wastewater recycling; (ii) s.72A puts the rainwater-harvesting duty on building owners, not on the Board; (iii) s.74 bans discharge of untreated sewage into watercourses, but only from a date the Board appoints, with treatment set by bye-laws; (iv) ss.49, 52 and 60 prevent waste of water and pollution of the water supply. On this evidence the Act fits the 'limited to particular functions, schemes or environmental concerns' band (2.5). The score is left blank because State water policies and the Board's regulations and bye-laws are not in the Citation Sheet. | EVIDENCE: BWSSB Act 1964 (PRS consolidated text with amending Acts appended, BWSSB-02): (1) s.15(1)-(3) general duties: 'general duty of providing a supply and improving the existing supply of water ... and of making adequate provision for the sewerage and the disposal of the sewage'. Schemes are for 'supply | N24: The Bangalore Water Supply and Sewerage Act, 1964 [BWSSB-02] | O24: https://prsindia.org/files/bills_acts/acts_states/karnataka/1964/1964KR36.pdf | P24: The Board shall also have power to insist on owner, occupier or builder to adopt water conservation methods like rain water harvesting and recycling of waste water for non potable or potable purposes. | Q24: I have left the score blank. The Citation Sheet does not contain all the legal layers this question needs, so the band cannot be set yet. What I checked in the Act (BWSSB-02, PRS secondary copy, as amended up to Act 29 of 2021; era n/a): - s.15(1) gives the Board a general duty to supply and improve water supply and to provide for sewerage and sewage disposal. It says nothing about environmental sustainability. - s.15(6) says the Board 'shall also have power to insist' that owners adopt rainwater harvesting and waste-water recycling. This is a power aimed at consumers, not a duty on the Board to consider sustainability in its own planning. - Narrower provisions also exist: s.72A (rainwater harvesting duty on owners), s.72 (separate drains for sewage and rainwater), s.74 proviso (treated discharge into watercourses, from a date the Board appoints and per bye-laws), and ss.49/52/60 (waste and pollution). Each covers one function or concern only. - I agree with the Step 2 answer that the Act on its own fits the 'limited to particular functions or concerns' band (2.5), not the top band. I am relying on the band description given in the Step 2 answer, because the full Detailed Methodology text was not given to me here. Why the score is still blank (rule 5/6, not an affirmative-absence case): - BWSSB-38 (the Board's Notifications page) lists Board instruments whose text is not in the Citation Sheet and that I could not read: - 'STP Notification' (21-2-2018) - 'STP, School Notification Amendment of Reg. 7 and 36' - 'RWH Notification' - 'Guideline for packaged STP' - 'Tertiary treated water availability for non-potable purposes' - These are the regulation and bye-law layer. They may add sewage-treatment or reuse duties, so they could change the band. - Not in the sheet at all: any Karnataka State Water Policy or treated-wastewater reuse policy, and any Rules under the BWSSB Act. - BWSSB-40 (Rain Water Harvesting page) is website description, not a binding instrument. It does not count as evidence for this law-level question. - BWSSB-33 (Ground Water Act s.22(4)) gives local authorities, which by its s.2(k) definition include BWSSB, a 'may impose' power over rainwater-harvesting conditions on buildings. That is also limited to one concern. What a reviewer should do: - Fetch and read the notification PDFs listed on BWSSB-38 and any state water or reuse policy. - If none of them sets a sustainability duty across the Board's core functions, score 2.5. Otherwise, re-band. The Act text used is the PRS secondary copy only, and the Act still names Bruhat Bangalore Mahanagara Palike rather than its successor bodies. | R24: The citation didn't settle every input. "Score" left blank: the Citation Sheet doesn't decide it.
A25: UPD5b | B25: Bengaluru – BWSSB | D25: =IFERROR(UPD5b!L13,"") -> 5 | H25: =IF(OR(F25="",NOT(ISNUMBER(D25))),"",IF(ABS(F25-D25)<0.001,"Yes","No")) | I25: =IF(ISNUMBER(F25),F25,D25) -> 5 | J25: =IF(ISNUMBER(F25),"Expert (overrides AI)",IF(ISNUMBER(D25),"AI","Not scored yet")) -> AI | K25: Left for a person | L25: Partially Answered | M25: ANSWER: Partly. BWSSB's own published material shows specific environmental sustainability measures under both components. However, the Citation Sheet has no current water supply or sanitation plan. The material it does have dates from about FY2015-17, before the GBA was set up. It cannot show that these measures are in the Board's current planning, so no score is proposed. | EVIDENCE: (1) BWSSB-07, BWSSB 'About BWSSB' page, undated: (a) Loss reduction: water supply improvement works for 'reduction in unaccounted for water and leakage control' over about 50% of the core area, 'envisaged to reduce the overall water losses to 16%'. These include 'Exclusive leak detection works' using JICA/MRI L-sign monitoring and helium-gas hidden leak detection, with work completed in 4 subdivisions (Rs 25 crore). (b) Source measures: a second Cauvery source, CWSS Stage V (775 MLD, after an additional 10 TMC allocation). Also rain water and groundwater recharge through shafts, galleries and lakes. The page notes that 110 villages depend on borewells. (c) Wastewater: 11 STPs treating 339 MLD under CWSS Stage IV Ph II; 6 new STPs of 520 MLD proposed, with DPRs prepared. Environmental Action Plans A, B and C replace trunk sewers to stop sewage entering storm water drains (e.g. EAP-B diverts 150 MLD to STPs). The Hebbal 'zero flow' scheme keeps sewage out of Hebbal and Nagavara lakes. Upstream STPs are proposed to avoid pollution of Bellandur and Varthur lakes. About 30% of treated effluent goes | N25: About BWSSB - Bangalore Water Supply and Sewerage Board [BWSSB-07] | O25: https://bwssb.karnataka.gov.in/info-1/About+BWSSB/en | P25: For proper water accounting and loss reduction with the aims of improvement in water distribution system, reduction in unaccounted for water and leakage control three major works are taken covering about 50% of the core area (133 sqkm) wherein it is envisaged to reduce the overall water losses to 16%. | Q25: I left the score blank. This is an Implementation question about current practice, and the only evidence is undated or old. All of it comes from before the GBA was set up, in the BBMP era. Step 2 also proposed no score, and having checked the sources myself I agree. (1) What BWSSB-07 shows. This is the undated 'About BWSSB' page, and its content points to about FY2015-16: - It names BBMP as the jurisdiction. - It says sewerage works are 'planned to be completed in 2016' and that the Bellandur STP is 'proposed to be commissioned in 2016'. - Its DPRs are priced at '2014-15 SR'. It does describe specific sustainability measures: - Water supply: a target to cut water losses to 16% over about 50% of the core area; JICA/MRI L-sign and helium leak detection; the CWSS Stage V source. - Sanitation: 11 STPs treating 339 MLD; Environmental Action Plans A, B and C to stop sewage entering storm water drains; the Hebbal zero-flow scheme; 6 new STPs of 520 MLD proposed. The page itself shows that some of these figures are out of date. For example, it gives two different versions of the same loss-reduction work: 133 sq km at Rs 655 crore, and 116 sq km at Rs 821 crore. (2) The other sources. BWSSB-29, the Annual Report for FY2016-17, records a Board decision to reuse 15 MLD of tertiary treated water from the Jakkur STP for the Yelahanka power plant. It also records monthly NRW of about 38-48%. BWSSB-41 (Achievements, undated) lists past works: pipe restoration, 218 bulk flow meters 'for plugging water leakage', the Hebbal zero-discharge scheme, mandatory rain water harvesting (RWH) and 23,000 RWH installations. BWSSB-40 (RWH page, undated) covers the RWH mandate and outreach. BWSSB-25, the Press Release page, has dated entries up to July 2026, but they are only about shutdowns, water adalats and recruitment. None deals with sustainability planning. (3) What is missing. The Citation Sheet has no current BWSSB water supply plan, sanitation plan, NRW programme or reuse plan, and no annual report after 2017. Under the period rule, an old document is not evidence of the current arrangement. (4) Indicative score. If the team accepts the undated web material as the Board's current planning framework, it would support about 2.5 for water supply (a source measure plus a loss-reduction target and programme) and about 2.5 for sanitation (STP capacity, sewage diversion and reuse), for a total of 5. Treat this as indicative only and confirm it against the full Detailed Methodology. That methodology was not reproduced in this task, so I could not check the bands myself. (5) Why not 0. A score of 0 is not justified, because measures are clearly documented. The only open question is whether they are current. ACTION for reviewer: - Get a current BWSSB plan, NRW programme or STP/reuse document, or an Annual Report from FY2023-24 onward. - Take a dated screenshot of BWSSB-07 and BWSSB-40. - Confirm the currency rule. | R25: The citation didn't settle every input. "Score" left blank: the Citation Sheet doesn't decide it.
A26: UPD6a | B26: Bengaluru – BMTC | D26: =IFERROR(UPD6a!L14,"") -> 2.5 | H26: =IF(OR(F26="",NOT(ISNUMBER(D26))),"",IF(ABS(F26-D26)<0.001,"Yes","No")) | I26: =IF(ISNUMBER(F26),F26,D26) -> 2.5 | J26: =IF(ISNUMBER(F26),"Expert (overrides AI)",IF(ISNUMBER(D26),"AI","Not scored yet")) -> AI | K26: Left for a person | L26: Partially Answered | M26: ANSWER: BMTC has no environmental duty in its own law. The 1950 Road Transport Corporations Act, under which BMTC was set up, gives it a general duty to run an efficient, adequate, economical and properly co-ordinated service, with no environmental element. The only binding environmental requirements in the Citation Sheet reach BMTC indirectly, through the Bengaluru Metropolitan Land Transport Authority (BMLTA) Act. That Act counts BMTC as an 'Urban Transport Agency' (public agencies providing urban mobility, which includes bus systems). It ties BMTC's investment planning to a Comprehensive Mobility Plan built around 'sustainable urban transport' and 'clean' transport. The Act defines sustainable urban transport only as projects that cut private-vehicle use and raise public transport, walking and cycling. Land use is linked to transport only in the plan the Authority itself prepares. None of the instruments read has an explicit BMTC requirement on emissions, cleaner fuels or vehicles, energy efficiency, climate resilience, or the environmental impact of its services or investments. On the evidence so far, the provisions point to the 2.5 band (limited to certain objectives and to the investment-planning stage). But layers that could change the band are missing from the Sheet, so no score is given. | EVIDENCE: (1) Road Transport Corporations Act, 1950 (BMTC-02): s.18 says it is the corporation's general duty to provide 'an efficient, adequate, economical and properly co-ordinat | N26: The Bengaluru Metropolitan Land Transport Authority Act, 2022 Act No. 6 of 2023 (Amendment appended: 10 of 2026) [BMTC-06] | O26: https://prsindia.org/files/bills_acts/acts_states/karnataka/2023/Act6of2023Karnataka.pdf | P26: These additional projects shall align with the Comprehensive Mobility Plan goals and promote sustainable urban transport. | Q26: I left the score blank because the Citation Sheet doesn't support a score. The full Detailed Methodology and rubric for UPD6a weren't in the task input. The 0/2.5/5 bands come only from Step 2's summary, so I couldn't check whether any band fits. **What the sources show:** - **BMTC's own Act (BMTC-02, Road Transport Corporations Act, 1950):** s.18 sets a general duty to provide 'an efficient, adequate, economical and properly co-ordinated system of road transport services'. It has no environmental element. - **BMLTA Act, 2022 (BMTC-06, PRS republication with Amendment Act 10 of 2026 appended):** BMTC is covered as an Urban Transport Agency (the Schedule lists 'Bus systems'). Its environment-related duties are indirect only: - s.24(a): its Sectoral Mobility Investment Program 'shall be aligned with the goals of the Comprehensive Mobility Plan'. - s.2(h): the Comprehensive Mobility Plan is to provide 'safe, clean and efficient urban transport'. - s.25(1)(c): additional Annual Implementation Plan projects 'shall align with the Comprehensive Mobility Plan goals and promote sustainable urban transport'. - s.2(aa) defines 'sustainable urban transport' narrowly, as cutting private-vehicle use and raising public and non-motorised transport. - **Commencement:** s.1(3) says the BMLTA Act 'shall come into force on such date as the State Government may by notification in the official Gazette, appoint'. No commencement notification and no notice setting up the Authority is in the Sheet. Whether these BMLTA duties currently bind BMTC is therefore unverified. - **City government's law (BMTC-04, GBA Act):** s.17 creates a Climate Action Cell within the GBA. I found no provision requiring BMTC to consider emissions or sustainability. - **BMTC website (BMTC-32):** the mission line 'Adopt environment-friendly and sustainable practices' is a statement of intent, not a mandate. - **Other environment items:** BMTC-01 lists press releases on BS-VI buses and on monitoring electric buses. These show implementation, not a mandate. **Why I didn't give 2.5:** it depends on two judgements a person must make. First, whether an indirect duty to align with the Authority's plan counts as BMTC being 'mandated' to consider environmental sustainability. Second, whether the Act is in force. **Why I didn't give 0:** that needs affirmative absence, and these layers are not in the Sheet or were not read: - KSRTC Rules, 1961 and the BMTC/KSRTC regulations listed on BMTC-20 (only the index page is in the Sheet). - Rules and regulations under the BMLTA Act. - The Comprehensive Mobility Plan and the Authority's policies. - State EV, clean-fuel or transport policies and government orders binding on BMTC. **To check:** 1. Get the UPD6a methodology and band definitions. 2. Find the BMLTA Act commencement notification and the notice constituting the Authority. 3. Read the KSRTC Rules 1961 and any state EV or clean-fleet government orders that name BMTC. 4. Decide whether the indirect alignment duty earns the partial band. | R26: The citation didn't settle every input. "Score" left blank: the Citation Sheet doesn't decide it.
A27: UPD6b | B27: Bengaluru – BMTC | D27: =IFERROR(UPD6b!L14,"") -> 1.25 | H27: =IF(OR(F27="",NOT(ISNUMBER(D27))),"",IF(ABS(F27-D27)<0.001,"Yes","No")) | I27: =IF(ISNUMBER(F27),F27,D27) -> 1.25 | J27: =IF(ISNUMBER(F27),"Expert (overrides AI)",IF(ISNUMBER(D27),"AI","Not scored yet")) -> AI | K27: Left for a person | L27: Human Verification Required | M27: ANSWER: Partly. BMTC's own website shows that it runs electric buses: 1,771 electric buses under the GCC model, out of 6,921 vehicles, as on 25 Sept 2026. It also runs metro feeder services. But the Citation Sheet has no current BMTC fleet plan, route or network plan, environmental or sustainability policy, or annual report. So none of these can be confirmed: (i) a fleet-transition target, (ii) an emissions or fuel-efficiency target, (iii) a phase-out schedule for high-emission buses, or (iv) operational modal-integration or energy-efficiency measures in BMTC's planning framework. Neither component can be fully decided. | EVIDENCE: (1) BMTC-15, BMTC at a Glance, as on 25 Sept 2026: 'No. of Vehicles 6921 (Including EV)'; 'No of Electric buses under GCC model 1771'. This shows a cleaner fleet in operation. It is a fleet count, not a target or a transition schedule. (2) BMTC-32, Vision and Mission: the vision is 'Make BMTC sustainable, people-centered and choice mode of travel for everyone'. Mission items include 'Adopt environment-friendly and sustainable practices' and 'Ensure inter-agency coordination and multi-modal integration'. This is generic wording, and the methodology gives it no credit unless it is turned into specific provisions. The page also says BMTC adopts 'Environmental policies', but the policy itself is not in the sheet. (3) BMTC-01, homepage: link titles include 'Metro Feeder Live Tracking', 'Metro Feeder Service', 'Inauguration of the First Batch of 100 BS-V | R27: Step 2 found no evidence: a source needs to be found and added. Step 2 found no evidence (Human Verification Required). Source needed: Needed: BMTC's current fleet plan or e-bus transition plan with targets and a diesel phase-out schedule; any emissions or fuel-efficiency (KMPL/kWh per km) targets; the latest BMTC annual report (laid before the Legislature under RTC Act s.35); the route rationalisation or network plan, including the metro feeder plan and interchange or common-ticketing arrangements; the text of BMTC's environmental policy; and any depot energy-efficiency or solar measures.
A28: DPG1a | B28: Bengaluru – BWSSB | D28: =IFERROR(DPG1a!L13,"") -> 0 | H28: =IF(OR(F28="",NOT(ISNUMBER(D28))),"",IF(ABS(F28-D28)<0.001,"Yes","No")) | I28: =IF(ISNUMBER(F28),F28,D28) -> 0 | J28: =IF(ISNUMBER(F28),"Expert (overrides AI)",IF(ISNUMBER(D28),"AI","Not scored yet")) -> AI | K28: Left for a person | L28: Partially Answered | M28: ANSWER: No. Neither Act, as far as I could read them, clearly separates BWSSB's water and sewerage role from the city government's. This is Scenario B (fully devolved, both deliver it). The Greater Bengaluru Governance Act lists water supply for domestic, industrial and commercial purposes, and liquid waste management, as core functions of the City Corporations, and they must provide these services. The BWSSB Act gives the Board the general duty of supplying water, and providing sewerage and sewage disposal, for the whole Bangalore Metropolitan Area. It does not mark out a particular aspect, area or scale. The few points where the two touch are an optional arrangement to supply water through the municipal body, a consultation on closing public hydrants, and a power to override the old municipal Act when laying mains. None of these divides the function. The Greater Bengaluru Authority (GBA) now has a binding power to coordinate and supervise BWSSB, which adds a layer of oversight but no division of the function. The evidence points to 0 under Scenario B, but I have not scored it (see LIMITS). | EVIDENCE: City government side (BWSSB-04, GBA Act 2024, Karnataka Act 36 of 2025): s.111(1): City Corporations shall prepare and implement schemes for First Schedule matters, 'subject to the provisions of this Act and the provisions of the other Acts'. Proviso to s.111(1): it 'shall be the duty of the City Corporation to render necessary services' for core functions. Sch. I(1) core func | N28: The Bangalore Water Supply and Sewerage Act, 1964 [BWSSB-02] | O28: https://prsindia.org/files/bills_acts/acts_states/karnataka/1964/1964KR36.pdf | P28: 26. Vesting of works in Board. —On and from the date of coming into force of this Chapter, all public reservoirs, tanks, cisterns, fountains, wells, pumps, pipes, taps, conduits and other works connected with the supply of water to the | Q28: I have left the score blank and not given 0. The Step 2 answer cannot be accepted as it stands. (1) The task did not include the Detailed Methodology or the score bands for DPG1a. All I have is Step 2's own wording ('Scenario B' etc.). With no rubric, I cannot place this case on the 0-5 scale. Flag as RUBRIC-GAP: a person should apply the actual DPG1a bands. (2) Step 2 says the BWSSB Act does not separate the Board's role from the city government's. That claim missed the vesting and transfer provisions, which I have now read in BWSSB-02 (PRS compilation, amended up to Act 29 of 2021). s.26 vests in the Board and places under its control all water works for the Bangalore Metropolitan Area, 'whether made at the cost of the Government, the Bruhat Bangalore Mahanagara Palike or otherwise'. s.63 vests sewers in the Board (heading seen in the table of contents only). s.123 transfers BBMP's water supply and sewerage staff to the Board. s.127(1)(c) and s.127(2)(c) vest BBMP's water supply and sewerage undertaking property in the Board. s.36 lets the Board supply water to BBMP 'on such terms ... as shall be determined by the Board'. s.38(1) has the Board provide free public supply subject to payment of charges by BBMP. The 1964 Statement of Objects records that the Act moved distribution from the Corporation to the Board. Read together, these provisions arguably allocate the whole function to the Board, away from the municipal body. That may count as an explicit distinction, or it may count only as a transfer that never defines what the city government keeps. That is a judgement call for the team. (3) The later GBA Act (BWSSB-04, Karnataka Act 36 of 2025, as enacted, GBA era) contradicts this. Sch. I(1)(v) lists 'Water supply for domestic, industrial and commercial purposes' and (vi) liquid waste management as City Corporation core functions, though s.111(1) makes them 'subject to ... the provisions of the other Acts'. Sch. I(3)(vii)(f) gives the City Corporations 'unfiltered water supply for non-domestic uses', which may be a partial split by scale or aspect. The BWSSB Act still names BBMP and the KMC Act, and no source in the Citation Sheet shows these references formally substituted by the City Corporations or GBA. So the two laws overlap or conflict rather than divide the function cleanly. (4) A 0 would need affirmative absence, and we do not have it. Neither Rules nor Regulations under the BWSSB Act, nor Rules under the GBA Act, are in the Citation Sheet. Both Act texts are PRS secondary copies. BWSSB-23 and BWSSB-28 are Bills as introduced, and the Citation Sheet does not show them enacted. Checked: BWSSB-02 (ss.14, 15, 26, 27, 31, 36, 38, 39, 123, 127, 129, and the 2010 amending Act s.31 substitution), BWSSB-04 (s.111 and Schedule I), and a search across the whole Citation Sheet. A person should apply the real DPG1a rubric to the s.26/s.127 vesting set against GBA Act Schedule I. | R28: The citation didn't settle every input. "Score" left blank: the Citation Sheet doesn't decide it.
A29: DPG1a | B29: Bengaluru – BMTC | D29: =IFERROR(DPG1a!L14,"") | H29: =IF(OR(F29="",NOT(ISNUMBER(D29))),"",IF(ABS(F29-D29)<0.001,"Yes","No")) | I29: =IF(ISNUMBER(F29),F29,D29) | J29: =IF(ISNUMBER(F29),"Expert (overrides AI)",IF(ISNUMBER(D29),"AI","Not scored yet")) -> Not scored yet | K29: Left for a person | L29: Partially Answered | M29: ANSWER: No clear demarcation was found, but I have not scored it. The sources point to Scenario C (partly devolved). BMTC's operating role is defined in the Road Transport Corporations Act. However, the city government's law (GBA Act) gives the City Corporations bus stops as a core function. It also lets BMTC put up bus stands on City Corporation land, and gives the GBA binding powers to supervise and direct BMTC and to make mobility plans. The BMTC law does not separate BMTC's role from the city government's. The answer leans to 0. It is left blank because the instrument that set up BMTC and BMTC's legal form are not in the Citation Sheet (see CAVEATS). | EVIDENCE: City government side, GBA Act 2024 (Karnataka Act 36 of 2025, PRS copy, BMTC-04): (1) Schedule I (s.111) lists 18 core functions. Public bus transport is not among them. Core function (xvii) does include 'parking spaces for vehicles, bus stops', and (xii) includes 'waiting sheds for travelers'. (2) s.112(1): the City Corporation 'may', with State or Central approval and cost cover, take on State-domain functions 'such functions may include... urban transport'. This is optional, not a transfer of the function. (3) s.14(4): the GBA is to integrate and supervise 'Bangalore Metropolitan Transport Corporation'. Its directions are binding and public authorities 'shall... obey its directions'. BMTC 'shall suitably incorporate in their Memorandum of Association the coordinating role' of the GBA. (4) s.15(1): the GBA 'shal | N29: The Greater Bengaluru Governance Act, 2024 Act No. 36 of 2025 [BMTC-04] | O29: https://prsindia.org/files/bills_acts/acts_states/karnataka/2025/Act36of2025KA.pdf | P29: Notwithstanding anything contained in this act no licence or permission shall be necessary for the Bengaluru Metropolitan Transport City Corporation in respect of the fixation or erection of posts showing places of stoppage of buses or erection or construction of passenger-shelters, ticket booths and bus stands on any road or land vested in the City Corporation: | Q29: Score left blank. A person needs to score this. 1) The sheet cannot settle the score. The task did not give me the Detailed Methodology or the scenario bands for DPG1a. Without them I cannot map the evidence to a number from 0 to 5. Treat this as a possible RUBRIC-GAP until a scorer applies the bands. 2) BMTC's own founding instrument is missing. The order that set up BMTC under section 3 of the Road Transport Corporations (RTC) Act 1950 is not in the sheet, and neither is any Memorandum of Association. GBA Act s.14(4) calls BMTC 'Bangalore Metropolitan Transport Corporation Limited' and requires it to 'suitably incorporate in their Memorandum of Association' the GBA's coordinating role. That suggests BMTC may be a company, which conflicts with treating the RTC Act as its governing law. A 0 on 'no demarcation' needs affirmative absence across BMTC's whole legal stack, and I cannot show that. 3) What I checked: - RTC Act 1950 (BMTC-02), ss.3, 18 and 19: a general duty to run road transport services and provide 'ancillary service'. There is no reference to municipal bodies. - BMTC-20 (BMTC's Rules and Regulations page): only staff and service regulations inherited from KSRTC, plus the KSRTC Rules 1961. Nothing on BMTC's role relative to the city government. - GBA Act (BMTC-04), city government side: - Schedule I gives the City Corporations bus stops, parking and waiting sheds as core functions. - s.112(1) says the City Corporation 'may' take on urban transport. This is optional. - s.14(4) gives the GBA binding supervision and directions over BMTC. - s.15(1) gives the GBA mobility plans. - s.234(2)-(3) lets BMTC put up bus-stop posts, shelters, ticket booths and bus stands on City Corporation land without a licence. It needs prior State sanction and pays ground rent to the City Corporation, either as agreed or as set by the Government. - Taken together, this is a partial demarcation on bus-stop infrastructure only, and it sits in the city government's Act. Running bus services is BMTC's under the RTC Act, but the city government may take it on with State approval (s.112(1)). This fits the Step 2 answer's 'Scenario C / partly devolved' reading, but I could not check that band against the rubric. 4) Points for the scorer: - s.234 says 'Bengaluru Metropolitan Transport City Corporation', which looks like a drafting slip for BMTC. - The GBA Act text is the PRS republication, so whether later amendments are included is unknown. - Whether the GBA (Amendment) Bill 2025 (BMTC-05) was enacted is unknown. It changes only s.8(2) and s.14(1). - The BMLTA Act (BMTC-06) sets up a State-level transport authority, not the city government. - Era: GBA era. The earlier BBMP-era arrangement was not assessed. 5) Before scoring, add BMTC's founding notification or Memorandum of Association to the sheet and apply the DPG1a scenario bands. I agree with Step 2 that the evidence leans towards no clear demarcation (overlapping bus-stop functions, binding GBA directions, and no carve-out in BMTC's own law), but that cannot be confirmed from this sheet. | R29: The citation didn't settle every input. "Score" left blank: the Citation Sheet doesn't decide it.
A30: DPG1a | B30: Bengaluru – BDA | D30: =IFERROR(DPG1a!L15,"") -> 0 | H30: =IF(OR(F30="",NOT(ISNUMBER(D30))),"",IF(ABS(F30-D30)<0.001,"Yes","No")) | I30: =IF(ISNUMBER(F30),F30,D30) -> 0 | J30: =IF(ISNUMBER(F30),"Expert (overrides AI)",IF(ISNUMBER(D30),"AI","Not scored yet")) -> AI | K30: Left for a person | L30: Answered — Verified Source | M30: ANSWER: No. Scenario B (fully devolved, both deliver it). The city government's law gives urban planning, land-use regulation and scheme-making to the Greater Bengaluru Authority (GBA) and its City Corporations. The BDA Act still gives BDA a general development mandate over the whole Bangalore Metropolitan Area, including development schemes, layouts, streets, drainage and water supply. The BDA Act has no provision that separates BDA's role from the GBA's or the Corporations'. BDA's operational mandate is defined, but its responsibilities relative to the ULG are not clearly separated. This is because GBA Act Schedule I gives the Corporations urban planning, and GBA Act s.14(2)-(4) makes the GBA the Planning Authority and scheme-maker for the Greater Bengaluru Area, with binding power to supervise BDA. The only area split (BDA as planning authority outside the Greater Bengaluru Area) appears in the Town and Country Planning (KTCP) amendment and the GBA Act, not in the BDA Act. | EVIDENCE: ULG side, GBA Act 2024 (Karnataka Act 36 of 2025) [BDA-03]: (a) Schedule I (s.111) core functions of the City Corporation are '(i) Urban planning including town planning; (ii) Regulation of land-use ... and construction of buildings; (iii) Planning for economic and social development; (iv) Roads ...; (x) Slum improvement'. (b) s.14(2)(a): the GBA 'shall be the "Planning Authority" ... for the areas comprising of the Greater Bengaluru Area'. s.14(2)(b): the GBA may approve layouts within the G | N30: The Greater Bengaluru Governance Act, 2024 (Act No. 36 of 2025) [BDA-03] | O30: https://prsindia.org/files/bills_acts/acts_states/karnataka/2025/Act36of2025KA.pdf | P30: (i) Urban planning including town planning; (ii) Regulation of land-use including protection of public land from encroachment and construction of buildings; | Q30: I left the Score blank. The task gave me no question text, Detailed Methodology or scoring notes for DPG1a, so I could not check the rubric bands myself. Step 2's description ('Scenario B ... no explicit carve-out in the Parastatal Act -> 0') does not tell me what the bands between 0 and 5 are, or whether a partial separation earns intermediate credit. Scoring from it would be a guess. A person holding the DPG1a rubric should set the score. What I checked against the sources: (1) The city government law (BDA-03, the Greater Bengaluru Governance Act 2024, Act 36 of 2025, PRS text) gives the City Corporations 'Urban planning including town planning' and land-use regulation in Schedule I (s.111). Section 223 makes Corporation land-use powers conform to the Master Plan or have the Planning Authority's concurrence. A search of the sheet also shows s.14 gives the GBA the planning, scheme-coordination and supervisory role. (2) The parastatal law (BDA-02, BDA Act 1976, PRS copy with amendments appended up to Act 42 of 2026, gazetted 07.09.2026): I read the arrangement of sections. No section refers to the GBA or the Greater Bengaluru Area. Act 42 of 2026 amends only s.10 (estimate limits raised to five crore rupees) and s.38D (allotment rates and eviction). This confirms that the BDA Act was not amended to separate BDA's role from the GBA's or the Corporations'. (3) The only area-based split (BDA as planning authority outside the Greater Bengaluru Area) is in BDA-05. That is the KTCP and Certain Other Laws (Amendment) Bill 2025, as passed by the Legislative Assembly. The sheet does not show that it was enacted or brought into force. (4) The BDA Act has interface provisions with 'the Corporation': s.15(2) (schemes recommended and funded by a local authority), the s.25 proviso (the Corporation must be consulted), s.26, s.28, s.28A (streets maintained until vested in the Corporation) and s.28B. Step 2 treats these as handover provisions only, not a division of the function. A person should decide whether the rubric gives partial credit for these. They still name the pre-GBA 'Corporation', and no source in the sheet shows a successor substituted. If the rubric really is 'no explicit separation of responsibilities in the Parastatal Act -> 0', the evidence supports 0. Affirmative absence has been checked for the BDA Act layer: arrangement of sections, the amendments appended, and ss.65-70. No BDA Rules or Regulations are in the sheet. All Act texts are PRS secondary copies or Bill papers. Era: GBA-era. RUBRIC-GAP: no methodology was supplied to me. Please confirm the rubric and set the score. | R30: The citation didn't settle every input. "Score" left blank: the Citation Sheet doesn't decide it.
A31: DPG1a | B31: Bengaluru – BMRCL | D31: =IFERROR(DPG1a!L16,"") -> 5 | H31: =IF(OR(F31="",NOT(ISNUMBER(D31))),"",IF(ABS(F31-D31)<0.001,"Yes","No")) | I31: =IF(ISNUMBER(F31),F31,D31) -> 5 | J31: =IF(ISNUMBER(F31),"Expert (overrides AI)",IF(ISNUMBER(D31),"AI","Not scored yet")) -> AI | K31: Left for a person | L31: Partially Answered | M31: ANSWER: No, the law does not clearly demarcate BMRCL's role from the ULG's. The ULG's law gives the Greater Bengaluru Authority (GBA) part of the urban-transport function: under s.14(4) of the GBA Act it 'integrates and supervises' the activities of named public authorities, including the 'Bengaluru Metro Rail Corporation Limited', and issues directions that are binding. Neither instrument sets out where that supervision ends and BMRCL's own role begins. The City Corporations' function list (Schedule I) does not include metro or mass transit. Section 112(1) puts urban transport in the State/Central domain, and a City Corporation 'may' take it on only with that government's approval and funding. So this is not Scenario A (function not given to the ULG at all). It is closest to Scenario C (only some sub-functions given to the ULG): GBA does mobility planning, coordination and binding supervision, while the metro railway administration operates and maintains the metro. That split is not shown to be non-overlapping, because GBA's binding directions reach BMRCL's own activities with no carve-out. I have not proposed a score because BMRCL's own legal stack could not be fully checked (see LIMITS). | EVIDENCE: ULG side, GBA Act 2024 (Karnataka Act 36 of 2025, PRS copy, BMRCL-02): s.14(4) 'Co-ordination and Supervision of Public Authorities: Integrating and supervising the activities of public authorities like ... Bengaluru Metro Rail Corporation Limited ... issuing directions for the | N31: The Greater Bengaluru Governance Act, 2024 Act No. 36 of 2025 [BMRCL-02] | O31: https://prsindia.org/files/bills_acts/acts_states/karnataka/2025/Act36of2025KA.pdf | P31: Integrating and supervising the activities of public authorities like the Bangalore Development Authority, the Bengaluru Water Supply and Sewerage Board, Bangalore Metropolitan Transport Corporation, Bengaluru Solid Waste Management Corporation, Bengaluru Metro Rail Corporation Limited, the Bangalore Electricity Supply Company and such other bodies connected with municipal activities in the Greater Bengaluru Area in such a manner that all functions are streamlined and implemented in a citizen-friendly manner and issuing directions for the same which shall be binding | Q31: SCORE LEFT BLANK for a person to decide. (1) The question's Detailed Methodology and Notes for scorers were not included in this task, apart from the scenario labels (A/B/C) that Step 2 uses. I cannot check which band a 0-5 score maps to, so I have not proposed a number. (2) I checked Step 2's reading against the source and it holds: - GBA Act s.14(4): GBA 'integrates and supervises' the activities of the 'Bengaluru Metro Rail Corporation Limited' and issues binding directions. Public authorities 'shall cooperate' and 'obey its directions'. There is no carve-out for metro operations. - s.15(1): GBA 'shall be responsible to make master plan and mobility plans'. - s.13(1)(j): the MD of BMRCL sits on GBA's Executive Committee. - s.112(1): a City Corporation 'may', with Central or State approval and funding, take on 'urban transport'. That is discretionary and conditional, not an assignment of the function. - s.178: the Urban Transport Fund is run by the Directorate of Urban Land Transport (DULT), not by the City Corporation. - Metro O&M Act 2002 (BMRCL-04), as amended by Act 34 of 2009: ss.5-6 cover BMRCL's operation and maintenance role. s.86 lets the Central Government give policy directions to a non-Government metro railway. Nothing I read in this Act mentions the city government or GBA, or separates BMRCL's role from GBA's supervision. - Overall, the evidence points to overlapping, undemarcated roles: GBA supervises, coordinates and plans with binding directions, while BMRCL operates. (3) A 0 needs affirmative absence, and I cannot show it. The Citation Sheet does not contain: - BMRCL's Memorandum and Articles of Association (my search found no MoA text); - the notification extending the Metro O&M Act 2002 / the 1978 Construction of Works Act to Bengaluru; - the full text of the 1978 Act; - the operative text of the BMLTA Act 2022 ss.18-19; - any Rules or GOs on how GBA and BMRCL relate. I therefore cannot confirm that there is no demarcating provision anywhere in BMRCL's legal stack. (4) Points for the team to check: - The Act names 'Bengaluru Metro Rail Corporation Limited' (ss.2(54), 13, 14(4)) but 'Bangalore Metro Rail Corporation' in s.9(3)(j). The company's own annual report (BMRCL-09) uses 'Bangalore'. Confirm the Act means this company. - The BMRCL-02 PDF also contains the text of a GBA (Second Amendment) Act 2025 (Karnataka Act 01 of 2026). It amends ss.13, 29, 30, 33 and 241, but not s.14(4). Step 2 did not mention it. - The GBA Act text is a PRS secondary copy, and its date of coming into force has not been verified. - Era: GBA era. | R31: The citation didn't settle every input. "Score" left blank: the Citation Sheet doesn't decide it.
A32: DPG1a | B32: Bengaluru – BMRDA | D32: =IFERROR(DPG1a!L17,"") | H32: =IF(OR(F32="",NOT(ISNUMBER(D32))),"",IF(ABS(F32-D32)<0.001,"Yes","No")) | I32: =IF(ISNUMBER(F32),F32,D32) | J32: =IF(ISNUMBER(F32),"Expert (overrides AI)",IF(ISNUMBER(D32),"AI","Not scored yet")) -> Not scored yet | K32: Left for a person | L32: Partially Answered | M32: ANSWER: I couldn't score this question. The city government's law clearly gives planning functions to the city government, so the case falls under Scenario B or C (the function is devolved), not A. Whether BMRDA's role is explicitly separated from the city government's can't be decided because the BMRDA Act, 1985 is not in the Citation Sheet. BMRDA's functions are known only from paraphrases on its own website and in its 2022-23 annual report. Those paraphrases describe a region-level role: surveys, a structure plan for the Bangalore Metropolitan Region, schemes to implement it, and coordinating other agencies, including the 'Corporation of the City of Bangalore'. Region versus city is a possible difference of scale. But the coordination role seems to overlap with the Greater Bengaluru Authority's (GBA's) binding power to coordinate and supervise public authorities. That can only be confirmed against the Act's own wording. | EVIDENCE: City government side (BMRDA-10, Greater Bengaluru Governance Act, 2024, Act 36 of 2025, PRS text): (1) s.14(2)(a), 'Notwithstanding anything contained in any other law', GBA 'shall be the "Planning Authority" as defined under the Karnataka Town and Country Planning Act, 1961, for the areas comprising of the Greater Bengaluru Area'. (2) s.14(2)(c): the State shall set up the Bengaluru Metropolitan Planning Committee (BMPC) under Art. 243ZE for an area 'including but not limited to the Greater Bengaluru Area', with GBA's Chief Commissioner as Memb | N32: The Greater Bengaluru Governance Act, 2024 Act No. 36 of 2025 [BMRDA-10] | O32: https://prsindia.org/files/bills_acts/acts_states/karnataka/2025/Act36of2025KA.pdf | P32: (a) the Greater Bengaluru Authority shall be the “Planning Authority” as defined under the Karnataka Town and Country Planning Act, 1961, for the areas comprising of the Greater Bengaluru Area; | Q32: I left the score blank because the Citation Sheet does not have the text needed to decide it. The question's full Detailed Methodology was not given to me. The Step 2 answer refers to Scenarios A, B and C and an 'explicit, non-overlapping carve-out' test, so I used that. (1) City government side. I checked this against BMRDA-10 (Greater Bengaluru Governance Act, 2024, Act 36 of 2025, PRS text, GBA era; commencement date not established from the Sheet). The Act clearly gives planning to the city government's system: - s.14(2) starts 'Notwithstanding anything contained in any other law'. Under s.14(2)(a), GBA 'shall be' the Planning Authority under the KTCP Act for the Greater Bengaluru Area. - Under s.14(2)(c), the state shall set up the Bengaluru Metropolitan Planning Committee (BMPC) under Art. 243ZE. - Under s.14(3)(b), GBA issues binding directions for executing schemes. - Under s.15(1), GBA 'shall be responsible to make master plan and mobility plans'. - Under s.223, City Corporations must act in line with the KTCP master plan. So Scenario A (function not devolved) does not fit. The case is Scenario B or C. The Step 2 summary of the city government side is supported by the source. (2) BMRDA side. The BMRDA Act, 1985 is not in the Citation Sheet: not s.9 (functions), not any amendment, Rules, regulations, or GO linking BMRDA to GBA or the BMPC. The only accounts of its functions are paraphrases in BMRDA-02 (website) and BMRDA-03 (FY 2022-23 annual report, BBMP era, historical). Those paraphrases give BMRDA a structure plan for the whole region. They also give it a role coordinating BDA, BWSSB and the 'Corporation of the City of Bangalore', which is a predecessor body; no successor substitution is shown in the Sheet. That role seems to overlap GBA's binding power under s.14(4) to integrate and supervise BDA, BWSSB and 'such other bodies connected with municipal activities'. A score of 0 for overlap, or a positive score for a separation by scale (regional versus city), can only be decided from the Act's own wording. A paraphrase is not enough. (3) Points for a person to check: - BMRDA is not among the bodies named in s.14(4). It does sit on GBA (s.9(3)(u)) and its Executive Committee (s.13(1)(e)). - The 'public authority' definition in s.2(54) is cut off in the saved text at 'the Bengaluru Metropolita...'. It may name BMRDA or BMLTA. Check it in the full text, because it decides whether BMRDA falls under GBA's coordination. - Choose between B and C. Schedule I sector-wise (i)(c) requires integration with 'regional development plan[s]', which suggests a split by scale (C). - The team notes say BMRDA's eligibility is 'needs_review' at screening. What is missing: the primary text of the BMRDA Act, 1985 (s.9 and amendments) from an official Karnataka source, and any notification on how BMRDA relates to GBA or the BMPC. | R32: The citation didn't settle every input. "Score" left blank: the Citation Sheet doesn't decide it.
A33: DPG1a | B33: Surat – SUDA | D33: =IFERROR(DPG1a!L18,"") | H33: =IF(OR(F33="",NOT(ISNUMBER(D33))),"",IF(ABS(F33-D33)<0.001,"Yes","No")) | I33: =IF(ISNUMBER(F33),F33,D33) | J33: =IF(ISNUMBER(F33),"Expert (overrides AI)",IF(ISNUMBER(D33),"AI","Not scored yet")) -> Not scored yet | K33: Left for a person | L33: Partially Answered | M33: ANSWER: Not determinable from the Citation Sheet. The Surat Municipal Corporation (SMC) law does give the ULG urban and town planning, but only as a discretionary function. SUDA's own planning area includes the SMC area. So the provisional scenario is B: the function is devolved to the ULG, and SUDA also plans for the SMC area. Under scenario B the score depends on whether the Gujarat Town Planning and Urban Development Act (GTPUD Act) explicitly separates SUDA's role from SMC's role (for example, which body is the 'appropriate authority' for town planning schemes or development permission inside SMC limits). The working text of that Act's sections 2, 22, 23 and 26-29 is not readable in the sheet, so that question cannot be settled. What the sheet does show points toward overlap, not separation: SUDA's development control regulations cover SMC, and the State Government may hand SUDA's powers to the local authority. | EVIDENCE: (1) ULG side, Gujarat Provincial Municipal Corporations Act, 1949 (GPMC Act), as modified up to 30-11-2017 [SUDA-04]: s.66 says 'The Corporation may, in its discretion, provide ... for all or any of the following matters', and s.66(8B) lists 'urban planning including town planning and regulation of land use'. This is a discretionary ('may') assignment, not an obligatory one. Separately, s.63(1)(23A), an obligatory duty, covers 'The preparation of plans for economic development and social justice'. (2) Parastatal side, GTPUD Act, 1976 [SUDA-01, PRS copy] | N33: Gujarat Provincial Municipal Corporations Act, 1949 (Bombay Act No. LIX of 1949) (As modified upto the 30th November, 2017) [SUDA-04] | O33: https://cpahmedabad.gujarat.gov.in/Upload/MUNCIPAL_2_16082023.pdf | P33: (8B) urban planning including town planning and regulation of land use;] | Q33: Score left blank because the law that decides this question cannot be read in the Citation Sheet. 1. The ULG side is confirmed. GPMC Act s.66 says 'The Corporation may, in its discretion, provide ...' and lists in (8B) 'urban planning including town planning and regulation of land use'. This is a discretionary ('may') function, not a duty. The team should confirm whether a discretionary function counts as 'devolved'. Step 2 also points to the obligatory s.63(1)(23A) on plans for economic development and social justice. 2. SUDA's planning area includes the SMC area: - SUDA-14 (DP 2035, 2017), ch.1.4.3: SUDA's area has included the SMC area since it was set up on 30.01.1978. - SUDA-05 (revised draft GDCR, undated), title and cl.1.1.3: the regulations cover the SMC area. - SUDA-14 also records that SUDA prepared 23 town planning schemes and SMC prepared 129. That is practice, not law. Taken together, this provisionally fits Scenario B (function devolved, and the parastatal also works in the ULG area). Scenario B then needs an explicit separation of roles in the parastatal's law. 3. What the sheet shows on separation is mixed: - GTPUD Act s.23(1), as reproduced in SUDA-14 ch.1.4.2 (a secondary reproduction, not the Act text), gives SUDA functions across the whole 'urban development area'. These include (iv) 'to guide, direct and assist the local authority or authorities ... in matters pertaining to the planning, development and use of urban land' and (v) controlling development under the development plan. This points toward overlap or coordination, not a carve-out. - s.23(2), as substituted by Gujarat Act 22 of 2017 (SUDA-01), says the State 'may ... delegate' SUDA's powers to the local authority. No delegation notification is in the sheet. - In the other direction, GDCR cl.2.13 defines Competent Authority as persons authorised 'by the Surat Urban Development Authority/Surat Municipal Corporation as the case may be'. The s.27 application form is addressed to the 'Chief Executive Authority/Municipal Commissioner'. Cl.28.3 sets up a joint SUDA–SMC appeal committee. All of this suggests some split between the two bodies, but it is a draft regulation and not an explicit division in the Act. 4. The provision that decides the question is GTPUD Act s.2(iii), the definition of 'appropriate authority'. It would show whether SMC is the appropriate authority for town planning schemes and development permission inside its limits. It cannot be read anywhere in the sheet: SUDA-01 contains only the amending gazettes, and SUDA-03 (Rules) uses the term without defining it. Nor can the working text of GTPUD ss.22–29, the 1978 constitution notification, or the 2015 boundary notifications be read. Without these I cannot support a 5 (explicit carve-out) or a 0. A 0 would need affirmative absence, and the deciding instrument was not read. Checked: SUDA-01, SUDA-03, SUDA-04 (ss.63 and 66), SUDA-05 (cl.1.1.3, 2.13, 28.3, Form C(a)), SUDA-13 and SUDA-14 (ch.1.4). For a person to check: obtain the full GTPUD Act text (s.2(iii), s.23) from an official Gujarat source, and any s.23(2) delegation notification for Surat. | R33: The citation didn't settle every input. "Score" left blank: the Citation Sheet doesn't decide it.
A34: DPG1a | B34: Surat – GMRC | D34: =IFERROR(DPG1a!L19,"") | H34: =IF(OR(F34="",NOT(ISNUMBER(D34))),"",IF(ABS(F34-D34)<0.001,"Yes","No")) | I34: =IF(ISNUMBER(F34),F34,D34) | J34: =IF(ISNUMBER(F34),"Expert (overrides AI)",IF(ISNUMBER(D34),"AI","Not scored yet")) -> Not scored yet | K34: Left for a person | L34: Partially Answered | M34: ANSWER: Not determinable from the Citation Sheet, so no score is proposed. On the city-government side, the Gujarat Provincial Municipal Corporations Act, 1949 does give the city government a role in rail transit, but only as an optional function. Section 66(20) says the Corporation 'may, in its discretion' provide for light railways, tramways and motor transport facilities 'within or without the City'. Chapter XX (ss.341-342) sets out the powers the Corporation has if it sets up a Transport Undertaking. Because the function is assigned to the city government in some form, Scenario A (not devolved, score 5) does not apply. The case points to Scenario B. On GMRC's side, there is no parastatal Act. GMRC is a company set up under the Companies Act. The only instrument in the Sheet that gives it the Surat role is the MoHUA sanction letter of 06-06-2019, para 8.3: the Surat Metro Rail Project, two named corridors, 'shall be implemented by' GMRC. That is a central government order, not an Act. It names a specific project, but it does not separate GMRC's role from the city government's s.66(20) power. The central Metro Railways Acts and GMRC's Memorandum of Association are not in the Sheet as text. So I cannot tell whether any statute carves out GMRC's role (would score 5 under B) or whether no distinction exists (would score 0). | EVIDENCE: (1) City-government law, GMRC-18 (GPMC Act 1949, modified up to 30-11-2017). s.66 opening words: 'The Corporation may, in its discretion, provi | N34: The Gujarat Provincial Municipal Corporations Act, 1949 (Bombay Act No. LIX of 1949) (As modified upto the 30th November, 2017) – Government of Gujarat, Legislative and Parliamentary Affairs Department [GMRC-18] | O34: https://cpahmedabad.gujarat.gov.in/Upload/MUNCIPAL_2_16082023.pdf | P34: the construction, purchase, organization, maintenance or management of light railways, tramways, trackless trams, or motor transport facilities for the conveyance of the public or goods within or without the City; | Q34: SCORE LEFT BLANK. I couldn't decide either side of the comparison from the Citation Sheet. (1) City-government side, GMRC-18 (GPMC Act 1949, as modified up to 30-11-2017). I checked this against the source. Section 66(20) lists light railways, tramways, trackless trams and motor transport facilities 'within or without the City' as matters the Corporation may take up at its discretion. Chapter XX (ss.341-342) gives the Corporation powers 'in the event of the Corporation acquiring or establishing a Transport Undertaking'. So the city-government law assigns the transit function, but only as an option. Following the Step 2 reading, that rules out Scenario A (not devolved, score 5) and points to Scenario B. Two things a person should check: (a) whether 'light railways/tramways/mechanically propelled transport facilities' covers metro rail; (b) whether the GPMC Act governs Surat. The extract in the Sheet does not name Surat, and the task input leaves the city government's name blank. (2) GMRC side. GMRC has no constituting Act. GMRC-03 (RTI s.4(1)(b) disclosure) says GMRC was incorporated on 4-2-2010 under the Companies Act, 1956 'to implement Metro Rail Project', and became a 50:50 GoI-GoG SPV from 20-3-2015. GMRC-07 (MoHUA sanction, 06-06-2019) is a central government order, not an Act. Para 8.3 says the Surat project 'shall be implemented by' GMRC. The central Metro Railways (Construction of Works) Act 1978, the Metro Railways (O&M) Act 2002, the 2009 amendment and GMRC's Memorandum and Articles appear in GMRC-03 only as links. Their text is not in the Sheet. My searches of the Sheet for metro-Act provisions and for anything on the Surat city government's role found nothing usable. So under Scenario B I can't apply the 5 band (a parastatal law that explicitly carves out a role distinct from the city government's), because no such text is in the Sheet. I can't apply the 0 band either (no distinction): that needs proof of absence, and the relevant instruments are not in the Sheet to read. RUBRIC-GAP / CONFIRM: the team should decide how DPG1a applies when the parastatal is a Companies Act SPV with no constituting Act. Do the central Metro Acts or the MoHUA sanction count as the 'Parastatal Act'? If the function is held to be devolved but in practice delivered only by GMRC, check whether Scenario D applies. Evidence reviewed: GMRC-18, GMRC-03, GMRC-07, plus a Sheet-wide search (GMRC-05, -06, -08 returned nothing relevant). | R34: The citation didn't settle every input. "Score" left blank: the Citation Sheet doesn't decide it.
A35: DPG1b | B35: Bengaluru – BWSSB | D35: =IFERROR(DPG1b!L13,"") -> 2.5 | H35: =IF(OR(F35="",NOT(ISNUMBER(D35))),"",IF(ABS(F35-D35)<0.001,"Yes","No")) | I35: =IF(ISNUMBER(F35),F35,D35) -> 2.5 | J35: =IF(ISNUMBER(F35),"Expert (overrides AI)",IF(ISNUMBER(D35),"AI","Not scored yet")) -> AI | K35: Scored by AI | L35: Answered — Verified Source | M35: ANSWER: Yes, but only in general terms. The BWSSB Act defines BWSSB's area by pointing to another body's jurisdiction, plus extra adjacent areas the State Government may notify from time to time. The Act has no schedule, boundary description or map reference. The city-government law does the same: it also defines its area by notification. This fits the 2.5 band ('defined only in general terms'), not the 5 band. | EVIDENCE: (1) BWSSB Act, 1964 (PRS copy). The long title and preamble cover 'water supply, sewerage and sewage disposal in Bangalore Metropolitan area'. s.2(1a), substituted by Act 15 of 2010 w.e.f. 16.04.2010: ''Bangalore Metropolitan Area' means the area falling within the jurisdiction of the Bruhat Bangalore Mahanagara Palike and includes such other areas adjacent thereto as the State Government may, by notification, from time to time specify'. s.2(3) defines 'Bruhat Bangalore Mahanagara' as the areas within the jurisdiction of the BBMP 'constituted under the Karnataka Municipal Corporations Act, 1976'. s.31 of the 2010 amending Act replaced 'City of Bangalore' with 'Bruhat Bangalore Mahanagara' throughout the Act. No schedule or map is referred to in the parts read. (2) City-government (ULG) side: Greater Bengaluru Governance Act, 2024 (Act 36 of 2025, PRS copy). s.1(2): 'It shall extend to the Greater Bengaluru Area as notified by the Government'. s.6: boundaries of City Corporations can be changed by notification. s.7(3)-(4): a final notification constitutes ne | N35: The Bangalore Water Supply and Sewerage Act, 1964 [BWSSB-02] | O35: https://prsindia.org/files/bills_acts/acts_states/karnataka/1964/1964KR36.pdf | P35: (1a) ‘Bangalore Metropolitan Area’ means the area falling within the jurisdiction of the Bruhat Bangalore Mahanagara Palike and includes such other areas adjacent thereto as the State Government may, by notification, from time to time specify; | Q35: Score is 2.5: the BWSSB Act defines BWSSB's area, but only in general terms. I checked this against BWSSB-02 (PRS copy, as amended up to Act 5 of 2011, with later amending Acts appended). Section 2(1a) defines the 'Bangalore Metropolitan Area' as the area in the jurisdiction of the Bruhat Bangalore Mahanagara Palike, plus any adjacent areas the State Government may notify from time to time. Section 2(3) defines 'Bruhat Bangalore Mahanagara' by the jurisdiction of the BBMP constituted under the KMC Act, 1976. So the area is set by pointing to another body's jurisdiction and to future notifications. The Act has no schedule, no description of boundaries and no map reference. Step 2 says this fits the 2.5 band ('defined only in general terms'), not the 5 band (boundary description, schedule or map in the enabling Act) and not 0 (no definition). I have not seen the rubric text myself, so this rests on Step 2's account of the bands. Step 2 left open whether Act 29 of 2021 changed s.2(1a). It did not: I read the appended text, and it only substitutes s.72A (rain water harvesting). The other appended amending Acts I read (32 of 2010 on s.89A, 5 of 2011 on s.72A, 28 of 2013 on s.109A) do not touch the area definition either. On the city-government side, BWSSB-04 (GBA Act) s.1(2) also defines the area 'as notified by the Government', which does not change the band. FOR THE TEAM TO CHECK: (1) Section 2(1a) still names the BBMP. Under GBA Act s.7(4) the BBMP ceases to exist once the City Corporations are notified. No source in the sheet shows the BWSSB Act's definition was changed to the Greater Bengaluru Area or the City Corporations, so it is unclear which boundary now applies. Either way the band stays at general terms. (2) There is no official state gazette copy in the sheet; the Act text is a PRS secondary copy. (3) No s.2(1a) notifications adding adjacent areas are in the sheet. They would sit outside the Act, so they would not by themselves earn the 5 band.
A36: DPG1b | B36: Bengaluru – BMTC | D36: =IFERROR(DPG1b!L14,"") | H36: =IF(OR(F36="",NOT(ISNUMBER(D36))),"",IF(ABS(F36-D36)<0.001,"Yes","No")) | I36: =IF(ISNUMBER(F36),F36,D36) | J36: =IF(ISNUMBER(F36),"Expert (overrides AI)",IF(ISNUMBER(D36),"AI","Not scored yet")) -> Not scored yet | K36: Left for a person | L36: Partially Answered | M36: ANSWER: This cannot be fully determined from the Citation Sheet. BMTC's enabling Act, the Road Transport Corporations Act, 1950, describes territory only in general terms. Section 3 lets the State Government set up a corporation "for the whole or any part of the State" by notification in the Official Gazette, and the Act has no schedule, boundary description or map. The instrument that would actually set BMTC's area is the Karnataka Government's section 3 notification establishing BMTC. That notification is not in the Citation Sheet, so it is unknown whether it gives a specific boundary. On the Act alone this looks like the 2.5 band (general terms only), but I have not scored it because the deciding notification is missing. | EVIDENCE: (1) Road Transport Corporations Act, 1950 (BMTC-02): s.3 says the State Government "may, by notification in the Official Gazette, establish a Road Transport Corporation for the whole or any part of the State". s.18 sets a general duty to provide transport services "in the State or part of the State for which it is established and in any extended area". s.19(1)(a) gives power "to operate road transport services in the State and in any extended area". s.2(c) defines "extended area" as an area or route extended under s.20, which provides for a sanctioned scheme to run services into another State, alterable by supplementary scheme under s.20(4). The Act has no schedule or map. (2) City government law, Greater Bengaluru Governance Act, 2024 (Act 36 | N36: THE ROAD TRANSPORT CORPORATIONS ACT, 1950 [BMTC-02] | O36: https://www.transport.telangana.gov.in/html/pdf/The_Road_Transport_Corporations_Act_1950.pdf | P36: may, by notification in the Official Gazette, establish a Road Transport Corporation for the whole or any part of the State under such name as may be specified in the notification. | Q36: I left the score blank because the document that would set BMTC's area is not in the Citation Sheet. I can't score without it, and I won't guess. What I checked: - I confirmed the Step 2 reading against BMTC-02, the Road Transport Corporations Act, 1950 (amended up to Act 63 of 1982). This is a central Act. The copy in the sheet is hosted on the Telangana transport portal, but for a central Act the text is the same in every state. - Section 3 does not draw any boundary. It only lets the State Government set up a corporation 'for the whole or any part of the State' by notification in the Official Gazette. Section 2(b) defines 'Corporation' as one established under section 3. Sections 18 and 19 speak only of 'the State or part of the State for which it is established' and any 'extended area' under section 20. The Act has no schedule or map. - So the actual area comes from the Karnataka section 3 notification that set up BMTC, plus any later notifications changing it. That notification is part of the enabling legal framework, and it is not in the Citation Sheet. - I searched the whole sheet for an establishment notification or area description and found none. BMTC-15 (BMTC Glance) contains only website policy and help text. BMTC-20 (Rules and Regulations) lists only KSRTC employee regulations and the KSRTC Rules, 1961, with no area or establishment notification. BMTC-01 and BMTC-32 give only a general description: 'sole public bus transport provider for Bengaluru, serving urban, sub-urban and rural areas'. BMTC-04 (the city government's Act, the Greater Bengaluru Governance Act, PRS copy) s.234 covers only bus stops, shelters and bus stands on City Corporation land, and does not define BMTC's area. BMTC-06 (BMLTA Act) s.3 defines the separate authority BMLTA's mobility region, not BMTC's area. How the bands would apply: - On the parent Act alone, this looks like the 2.5 band ('general terms'). - Scoring 2.5 now would mean stopping at the parent Act. If the notification gives a specific boundary, the answer could be 5. That makes 2.5 unsafe. - A score of 0 is not justified either. I can't show the area is undefined anywhere, because the deciding document was never checked. What the team needs to do: 1. Get the Karnataka Gazette notification establishing BMTC under s.3 of the RTC Act (and any later notifications changing its area), for example by an RTI request to the Transport Department or BMTC's Public Information Officer, and add it to the Citation Sheet. 2. Rule whether a section 3 notification counts as part of the 'enabling Act' for the 5 band. The methodology says 'in the enabling Act'; the question says 'enabling legal framework'. 3. Confirm that the GBA Act's 'Bengaluru Metropolitan Transport City Corporation' (BMTC-04, s.234) means BMTC. | R36: The citation didn't settle every input. "Score" left blank: the Citation Sheet doesn't decide it.
A37: DPG1b | B37: Bengaluru – BDA | D37: =IFERROR(DPG1b!L15,"") -> 2.5 | H37: =IF(OR(F37="",NOT(ISNUMBER(D37))),"",IF(ABS(F37-D37)<0.001,"Yes","No")) | I37: =IF(ISNUMBER(F37),F37,D37) -> 2.5 | J37: =IF(ISNUMBER(F37),"Expert (overrides AI)",IF(ISNUMBER(D37),"AI","Not scored yet")) -> AI | K37: Scored by AI | L37: Answered — Verified Source | M37: ANSWER: Yes, but only in general terms. The BDA Act, s.2(c), defines BDA's area, the 'Bangalore Metropolitan Area'. It does this by pointing to other laws: the City of Bangalore as defined in the 1949 Municipal Corporation Act, plus the areas where the 1945 Improvement Act was in force. It then adds any adjacent areas the Government 'may from time to time by notification specify'. s.3(1) sets up BDA 'for the Bangalore Metropolitan Area'. The Act has no schedule, boundary description or map. So the jurisdiction is defined, but it rests on cross-references and open-ended notifications, which fits the 2.5 band. | EVIDENCE: (1) BDA Act 1976, PRS copy with amendments up to Act 42 of 2026 (BDA-02). s.2(c) defines the BMA as quoted. s.3(1): 'constitute for the Bangalore Metropolitan Area an Authority'. The list of sections shows no territorial schedule: the only 'Schedule' is s.49, a schedule of officers and servants. The text read of the 2026 amending Act changes s.10 and s.38D; that text did not show any change to s.2(c). (2) KTCP Act 1961, PRS copy with amendments up to 2015 (BDA-06). s.2(7)(a)(i) names BDA as Planning Authority for 'the local planning area comprising the City of Bangalore'. s.81-B(i) gives BDA 'jurisdiction over the area which the City Planning Authority for the City of Bangalore had jurisdiction immediately before' BDA was constituted. That is again a reference, not a boundary description. (3) City government law: Greater Bengaluru Governance Act 2024 (BDA-03). | N37: The Bangalore Development Authority Act, 1976 (Act 12 of 1976) – PRS copy, 'Amendments appended: 19 of 2002, 19 of 2005, 27 of 2020, 42 of 2026' [BDA-02] | O37: https://prsindia.org/files/bills_acts/acts_states/karnataka/1976/1976Karnataka12.pdf | P37: (c) ‘Bangalore Metropolitan Area’ means the area comprising the City of Bangalore as defined in the City of Bangalore Municipal Corporation Act, 1949 (Mysore Act 69 of 1949), the areas where the City of Bangalore Improvement Act, 1945 (Mysore Act 5 of 1945) was immediately before the commencement of this Act in force and such other areas adjacent to the aforesaid as the Government may from time to time by notification specify; | Q37: Score 2.5: the BDA Act defines BDA's area, but only in general terms. I checked the Step 2 answer against BDA-02 (PRS copy of the BDA Act, with amending Acts up to Act 42 of 2026). (a) s.2(c) defines the Bangalore Metropolitan Area (BMA) only by reference to other laws: the City of Bangalore as defined in the 1949 Municipal Corporation Act, plus the areas covered by the 1945 Improvement Act. It then adds adjacent areas 'as the Government may from time to time by notification specify'. (b) s.3(1) sets up BDA 'for the Bangalore Metropolitan Area'. (c) The Act has no territorial schedule or map; the only schedule I saw is the one on officers and servants. (d) Act 42 of 2026 (Gazette 07.09.2026) amends only s.10 and s.38D; I re-read its text and found no change to s.2(c). (e) A search of the whole Citation Sheet for boundary, schedule, village or map wording found no boundary description of BDA's jurisdiction. BDA-06 (KTCP Act s.81-B(i)) defines BDA's planning area only by reference to the old City Planning Authority's area. BDA-03 (Greater Bengaluru Governance Act s.2(30) and s.3) defines the Greater Bengaluru Area by notification. So jurisdiction is defined, which rules out 0, but there is no specific boundary description, schedule or map, which rules out 5. That leaves 2.5. CHECKS FOR A PERSON: (1) The question's full Detailed Methodology text was not in this task message. I took the bands (5 = boundary description, schedule or map in the Act; 2.5 = defined in general terms; 0 = not defined) from the Step 2 notes. Please confirm them against the question bank. (2) Confirm that defining the area 'as defined in' the 1949 Act counts as 'general terms'. (3) Pending law: the KTCP and Certain Other Laws (Amendment) Bill 2025 (BDA-05) was passed by the Assembly, but the Sheet does not show it enacted or in force. If enacted, BDA's planning area would become the BMA minus the Greater Bengaluru Area. That is still a notification-based, general definition, so the band would stay the same. Check the official gazette. (4) Only the PRS copy is in the Sheet; there is no official gazette text. There are also no s.2(c) notifications adding adjacent areas and no GBA area declaration, so the current boundary cannot be cross-checked.
A38: DPG1b | B38: Bengaluru – BMRCL | D38: =IFERROR(DPG1b!L16,"") -> 2.5 | H38: =IF(OR(F38="",NOT(ISNUMBER(D38))),"",IF(ABS(F38-D38)<0.001,"Yes","No")) | I38: =IF(ISNUMBER(F38),F38,D38) -> 2.5 | J38: =IF(ISNUMBER(F38),"Expert (overrides AI)",IF(ISNUMBER(D38),"AI","Not scored yet")) -> AI | K38: Left for a person | L38: Partially Answered | M38: ANSWER: I cannot confirm from the Citation Sheet whether BMRCL's territorial jurisdiction is defined by a specific boundary, schedule or map. BMRCL is a company. The law it runs metro services under, the Metro Railways (Operation and Maintenance) Act, 2002, defines its area only in general terms: the 'National Capital Region, metropolitan city and metropolitan area', with the Act reaching other areas only when the Central Government issues a notification. The Act's list of 'metropolitan cities' does not include Bangalore. So Bengaluru could only be covered as a 'metropolitan area' (Article 243P(c)) through a notification, and that notification is not in the sheet. A separate Act, the Metro Railways (Construction of Works) Act, 1978, ties the 'metro alignment' to a Schedule entry for each city. That could meet the 5-point 'schedule' test, but the sheet has only short extracts of that Act and no Bangalore Schedule entry. The city government's law (the Greater Bengaluru Governance Act, 2024) names BMRCL as a 'public authority' delivering services in the Greater Bengaluru Area. It does not set BMRCL's boundary. | EVIDENCE: (1) BMRCL-04, Metro Railways (O&M) Act, 2002 as amended by Act 34 of 2009: Long title, 'metro railway in the National Capital Region, metropolitan city and metropolitan area'. s.1(2): 'extends in the first instance to the National Capital Region and the Central Government may, by notification, after consultation with the State Government, extend this Act to suc | N38: THE METRO RAILWAYS (OPERATION AND MAINTENANCE) ACT, 2002 [BMRCL-04] | O38: https://crs.gov.in/wp-content/uploads/2024/03/THE-METRO-RAILWAYS-OPERATION-AND-MAINTENANCE-ACT-2002.pdf | P38: It extends in the first instance to the National Capital Region and the Central Government may, by notification, after consultation with the State Government, extend this Act to such other metropolitan area and metropolitan city, except the metropolitan city of Calcutta | Q38: I left the score blank because the sheet cannot settle the 5-point band. The 2.5 band (general terms only) is supported, but picking 2.5 would mean the 5-point band (a specific boundary, schedule or map) is not met. The sheet does not have the documents needed to decide that. What I checked against the source: the Step 2 summary of BMRCL-04 is correct. That is the Metro Railways (Operation and Maintenance) Act, 2002, as amended by Act 34 of 2009, in force from 7-9-2009. - Its long title, s.3(1), s.5 and s.14 describe the area only in general terms: 'National Capital Region, metropolitan city and metropolitan area'. - s.1(2) applies the Act beyond the National Capital Region only when the Central Government issues a notification. - s.2(1)(ha) lists only Bombay, Calcutta, Delhi and Madras as metropolitan cities. - On its own, this text is jurisdiction in general terms, which fits 2.5. Why the 5-point band stays open: - BMRCL-37 (the 2009 Amendment Bill on PRS) quotes the 1978 Construction of Works Act. Its s.2(1)(h) defines 'metro alignment' as the alignment 'specified in the Schedule under that city', and s.32 lets the Central Government add alignments to that Schedule by notification. - So a city-specific Schedule entry for the Bengaluru metro alignment may exist. That could count as a schedule reference in the enabling law. The sheet does not have it. My searches of the whole sheet for 'Schedule metro alignment Bangalore' and 'jurisdiction / boundary / map' found no such Schedule entry. They also found no central notification extending the 1978 or 2002 Act to Bengaluru, and no BMRCL Memorandum of Association. - BMRCL-02 (Greater Bengaluru Governance Act, 2024; GBA era) names BMRCL as a public authority in the Greater Bengaluru Area under s.2(54) and s.14(4). That is a coordination role, not a definition of BMRCL's own territory. - BMRCL-08 (Bengaluru Metropolitan Land Transport Authority Act, 2022) defines an Urban Mobility Region for that authority, not for BMRCL. - BMRCL-09 (Annual Report FY 2020-21, historical, BBMP era) says only 'Metro Rail Project in the city of Bangalore', which is a description, not a legal boundary. - BMRCL-06 (Companies Act) says nothing on territory. Decisions the team needs to make: 1. Which documents count as the 'enabling legal framework' for a company-form parastatal: the Memorandum of Association, the Metro Railways Acts, or both. 2. Whether a Bengaluru entry in the 1978 Act Schedule counts for the 5-point band. 3. Whether BMRCL's legal form makes it eligible for this question at all. To decide the score, a person needs to get: - the current full text of the 1978 Act with its Schedule; - the central notifications extending both Acts to Bengaluru; - BMRCL's Memorandum and Articles of Association. If none of these gives a specific boundary, schedule or map, the score would be 2.5. | R38: The citation didn't settle every input. "Score" left blank: the Citation Sheet doesn't decide it.
A39: DPG1b | B39: Bengaluru – BMRDA | D39: =IFERROR(DPG1b!L17,"") -> 5 | H39: =IF(OR(F39="",NOT(ISNUMBER(D39))),"",IF(ABS(F39-D39)<0.001,"Yes","No")) | I39: =IF(ISNUMBER(F39),F39,D39) -> 5 | J39: =IF(ISNUMBER(F39),"Expert (overrides AI)",IF(ISNUMBER(D39),"AI","Not scored yet")) -> AI | K39: Left for a person | L39: Human Verification Required | M39: ANSWER: Not determined. I could not confirm from the Citation Sheet whether the enabling Act defines BMRDA's territorial jurisdiction with a specific boundary description, schedule or map reference. Two BMRDA sources, the annual report and the website, both say the Bangalore Metropolitan Region (BMR) covers the whole of Bangalore Urban, Bangalore Rural and Ramanagaram Districts, about 8005 sq km. That is a specific geographic definition. But neither source is the Act, and neither says whether the definition sits in the Act itself (for example a section 2 definition or a Schedule) or in a later notification. | EVIDENCE: (1) BMRDA-03, BMRDA Annual Report 2022-23, p.11, para 4 'The Metropolitan Region': BMR is '...covering the entire Bangalore Urban, Bangalore Rural and Ramanagaram Districts measuring 8005 sq. kms.' On p.10 the report names the Act (Karnataka Act No. 39 of 1985) and summarises its section 3 and section 9. It does not summarise any section defining the Region. (2) BMRDA-07, BMRDA website, 'Local Planning Areas' page (undated): 'BMR comprises Bengaluru Urban District, Bengaluru Rural District & Ramanagaram District. The total area Bengaluru Metropolitan Region is about 8005 Sq Kms.' The page also lists 12 local planning authorities inside BMR, including BDA and Ramanagara UDA. (3) BMRDA-05, BMRDA website home page: has menu links called 'Jurisdiction', 'Jurisdiction Notification', 'Jurisdiction Map' and 'BMRDA Act 1985'. The Sheet has only the link labels, not the | R39: Step 2 found no evidence: a source needs to be found and added. Step 2 found no evidence (Human Verification Required). Source needed: Needed: (a) the full text of the BMRDA Act 1985 (Karnataka Act 39 of 1985), current amended version, especially the definition of 'Bangalore Metropolitan Region' and any Schedule or power to change the area by notification. Best copy is from the Karnataka legislation or eGazette portal, or a readable copy of the Act on BMRDA's own site. (b) The government notification that declares or changes the BMR boundary, plus the jurisdiction map. (c) A check of the Greater Bengaluru Governance Act for any provision on BMR's area.
A40: DPG1b | B40: Surat – SUDA | D40: =IFERROR(DPG1b!L18,"") | H40: =IF(OR(F40="",NOT(ISNUMBER(D40))),"",IF(ABS(F40-D40)<0.001,"Yes","No")) | I40: =IF(ISNUMBER(F40),F40,D40) | J40: =IF(ISNUMBER(F40),"Expert (overrides AI)",IF(ISNUMBER(D40),"AI","Not scored yet")) -> Not scored yet | K40: Left for a person | L40: Partially Answered | M40: ANSWER: SUDA's area is set by state government notifications made under section 22 of the Gujarat Town Planning and Urban Development Act, 1976 (GTPUD Act). It does not come from a schedule or boundary description in the Act itself. Those notifications describe the area specifically, by villages and square kilometres. They also changed it several times: 722 sq km in 1978, 715 sq km after 1979, 1351 sq km from December 2015, and 985.16 sq km after villages were removed in 2016. The Citation Sheet has no readable copy of section 22 and no copy of the notifications themselves. So I cannot check from primary text whether the Act gives only a general 'notified area' power (2.5) or whether the notifications' village lists count as a specific boundary in the enabling framework (5). | EVIDENCE: (1) GTPUD Act 1976 (SUDA-01, PRS compilation with amendments up to 14 of 2019): pages 2-86, which hold the main Act, have no extractable text. Only the amending Acts are readable. The 2017 amendment shows the state government 'may, by notification in the Official Gazette, delegate any of the powers and functions of the Urban Development Authorities to the local authority ... within its jurisdiction' (s.23(2) as substituted). It defines no boundary. (2) GDCR (SUDA-05, cl.1.1.3, revised draft, undated): the rules apply to the 'Urban Development Area including Surat Municipal Corporation area notified under sub-section (2) of section 22 of the Act vide ... Notification No.GHB/R1/UDA/1177/646(4)-q | N40: DEVELOPMENT PLAN 2035 2017 SURAT URBAN DEVELOPMENT AUTHORITY [SUDA-14] | O40: https://www.sudaonline.org/wp-content/uploads/2017/03/SUDA-DP-2035-report-final-22.02.2017.pdf | P40: The Government of Gujarat in Panchayats, Housing and Urban Development Department constituted the Surat Urban Development Authority vide Government notification number GHB/23/ UDA/1177/646(5)-Q2 dated January 30, 1978, in exercise of the powers conferred b y sub sections (1), (2) and (4) of section 22 of the Gujarat Town Planning and Urban Development Act 1976 for the development area consisting of Surat Municipal Corporation and 148 villages admeasuring 722 sq. km. | Q40: I left the score blank. A person needs to score this. 1) PRIMARY TEXT MISSING. SUDA-01 is the PRS compilation of the GTPUD Act 1976. I re-read it this session: pages 2-86, which hold the main Act and so section 22, have no extractable text. Only the amending Acts are readable (2017: s.23(2), s.7(2), s.76A; 2019: s.9, s.12, s.19A). None of them sets out how SUDA's area is defined or where its boundary lies. A search of the whole Citation Sheet found no readable text of s.22. 2) WHAT THE SHEET DOES SHOW. SUDA-14 (SUDA's own Draft Development Plan 2035, dated 2017) reports the following: - SUDA's area was set by state notification under s.22(1), (2) and (4) on 30.01.1978: SMC plus 148 villages, 722 sq km. - Delad village was then deleted, giving 715 sq km. - Notifications of 9.12.2015 and 18.12.2015 added 100 villages, giving 1351 sq km. - Under s.22(2A), Khajod village was removed by notification of 19.07.2016 (GH/V/144), and villages were excluded by notifications of 24.10.2016 (GH/V/199) and 03.11.2016 (GH/V/200). - Table 153 gives a resulting area of 985.16 sq km. SUDA-05 (GDCR cl.1.1.3, a revised draft, undated) also says the area was notified under s.22(2), citing Notification No. GHB/R1/UDA/1177/646(4)-q-2 of 31.01.1978. All of this is second-hand. None of the Gazette notifications or their village schedules is in the sheet. SUDA-21 is a map based on the 9/12/2015 notifications and is out of date after the 2016 exclusions. SUDA-03 (Rules, r.3) refers only generally to 'the area within the jurisdiction'. 3) RUBRIC-GAP / interpretation. I was not given the question's Detailed Methodology text. The Step 2 notes describe a 5-point band for a 'specific boundary description, schedule, or map reference in the enabling Act' and a 2.5-point band for a 'notified area'. Two things are unresolved: - Whether a s.22 notification that lists villages counts as the 'enabling legal framework' for the 5 band. If it does, the score could be 5. If only text inside the Act counts, it points to 2.5. - Whether the readable s.22 wording, which the sheet does not contain, gives only a general power to notify an area. The evidence does not decide between 2.5 and 5. A 0 is not supported, because an area-defining mechanism clearly exists. 4) OTHER POINTS FOR THE TEAM. - The two 1978 notifications are cited differently (GDCR: 646(4), 31.01.1978; DP 2035: 646(5), 30.01.1978). They may be separate declaration and constitution instruments. - The DP records that SUDA treats Asnabad village as still inside its area, despite the wording of the 2016 notification. - The DP is internally inconsistent. Section 21.1 says 54 villages were excluded on 24.10.2016 (effectively 53) and 7 more on 03.11.2016. Table 153 gives 985.16 sq km and 135 rural settlements. - The boundary after 2017 is not confirmed. To score this, the team needs: readable official text of GTPUD Act s.22 (a gujarat.gov.in or gazette copy), copies of the 1978, 2015 and 2016 notifications, and confirmation of how the band should be read. | R40: The citation didn't settle every input. "Score" left blank: the Citation Sheet doesn't decide it.
A41: DPG1b | B41: Surat – GMRC | D41: =IFERROR(DPG1b!L19,"") | H41: =IF(OR(F41="",NOT(ISNUMBER(D41))),"",IF(ABS(F41-D41)<0.001,"Yes","No")) | I41: =IF(ISNUMBER(F41),F41,D41) | J41: =IF(ISNUMBER(F41),"Expert (overrides AI)",IF(ISNUMBER(D41),"AI","Not scored yet")) -> Not scored yet | K41: Left for a person | L41: Insufficient Evidence | R41: Step 2 found no evidence: a source needs to be found and added. Step 2 found no evidence (Insufficient Evidence). Source needed: Needed: (1) GMRC's Memorandum and Articles of Association (objects clause and any stated area of operation). (2) Official texts of the Metro Railways (Construction of Works) Act 1978 and the Metro Railways (O&M) Act 2002 as amended, especially the provisions on applying them to a metropolitan area or city. (3) The Government of India gazette notification(s) extending these Acts to Surat and/or declaring the Surat metro alignment or area, with any schedule or map. (4) Any Government of Gujarat GO or notification defining GMRC's area of operation in Surat. (5) Confirmation of Surat's city government and the boundary provisions in its governing Act.
A42: DPG2a | B42: Bengaluru – BWSSB | D42: =IFERROR(DPG2a!L13,"") -> 0 | H42: =IF(OR(F42="",NOT(ISNUMBER(D42))),"",IF(ABS(F42-D42)<0.001,"Yes","No")) | I42: =IF(ISNUMBER(F42),F42,D42) -> 0 | J42: =IF(ISNUMBER(F42),"Expert (overrides AI)",IF(ISNUMBER(D42),"AI","Not scored yet")) -> AI | K42: Left for a person | L42: Partially Answered | M42: ANSWER: Under the BWSSB Act, elected city-government representatives cannot sit on the BWSSB Board, so the 5-point band (elected ULG representatives with voting rights) is ruled out in law. All Board members are appointed by the State Government. The Act gives the city government no reserved seat, and s.3(5) disqualifies any member of a local authority. That bar appears to cover councillors of the GBA City Corporations too, but this is an interpretation. The only evidence of city representation on the Board involves officials, not elected representatives, and it is from 2016-17. That year's Annual Report lists the BBMP Commissioner (an IAS officer) first as a Board member (the report does not say whether he could vote) and, from 27-08-2016, as a 'Special/Permanent Invitee'. The Citation Sheet has no current (GBA-era) Board list. So we cannot tell whether any GBA or City Corporation official now sits on the Board, or in what capacity. | EVIDENCE: (1) BWSSB Act 1964, PRS copy with amendments up to Act 29 of 2021. s.3(2) (substituted by Act 15 of 2010): 'The Board shall consist of not less than three and not more than nine members appointed by the State Government.' s.3(3) sets qualifications: commercial and administration experience, civil and public-health engineering, and accounts and finance. There is no seat for the corporation or its councillors. s.3(4): the State Government appoints the Chairman. s.3(5): a person is disqualified from being a Board member if he is a member | N42: The Bangalore Water Supply and Sewerage Act, 1964 [BWSSB-02] | O42: https://prsindia.org/files/bills_acts/acts_states/karnataka/1964/1964KR36.pdf | P42: (5) A person shall be disqualif ied for being appointed or being a member of the Board if he is a member of the Parliament or of any State Legislature or any local authority. | Q42: I left the score blank. The sources don't show the current Board make-up, and the way the rubric treats officials is unclear. The question details were not given to me in full, so I relied on the band structure set out in the Step 2 answer: 5 = elected city-government representatives with voting rights, 2.5 = some city-government representation, 0 = none. This needs checking against the actual rubric. What the sources show: (1) BWSSB Act 1964 (BWSSB-02), PRS copy with amendments up to Act 29 of 2021. s.3(2): the Board 'shall consist of not less than three and not more than nine members appointed by the State Government'. s.3(3) sets qualifications in commercial/administrative work, engineering and finance. No seat is reserved for the city government. s.3(5) disqualifies anyone who is a member of 'any local authority'. s.6(1)(d) allows removal of a member who 'becomes or seeks to become a member of ... any local authority'. I have treated these as ruling out the 5 band in law. But whether 'local authority' covers councillors of the GBA City Corporations is an interpretation and needs confirming. (2) Annual Report 2016-17 (BWSSB-29, pp.63-66, BBMP era, historical only). I checked this against the source. The 'Commissioner, BBMP' (N. Manjunath Prasad, IAS, 25-06-2016 to 02-07-2017) is listed as a Member, and from 27-08-2016 also as a 'Special/ Permanent Invitee'. No Mayor or councillor is listed. The report doesn't say whether he could vote. This is a city official, not an elected representative, and the evidence is about nine years old. (3) GBA Act 2024 (BWSSB-04) and Second Amendment Bill 2025 (BWSSB-28). These put the BWSSB Chairman on the GBA and its Executive Committee, which is the opposite direction. They give the GBA supervisory powers (s.14(4)). I found nothing in either that gives the GBA or the City Corporations a seat on the BWSSB Board. Why I can't score 0: there is no current (GBA-era) Board list or Board-constitution notification in the sheet, and none of the BWSSB Rules made under s.4. So I can't show that the city has no representation at all. Why I can't score 2.5: it depends on (a) whether a city official as member or invitee counts as city-government representation under the rubric, and (b) current evidence that such an official sits on the Board now. Neither is settled by the sheet. This is a RUBRIC-GAP / evidence gap. For a person to check: - Confirm the rubric's treatment of official (non-elected) members and invitees. - Get the current BWSSB Board constitution notification and member/invitee list with voting status for FY 2025-26 (RTI to the BWSSB PIO or the Urban Development Department). - Check whether any official instrument replaces BBMP with the GBA or City Corporations in the BWSSB Act. The PRS text still names BBMP. Era: the BWSSB Act text is as amended to 2021; the Annual Report is from the BBMP era; the GBA Act and Bill are from the GBA era. | R42: The citation didn't settle every input. "Score" left blank: the Citation Sheet doesn't decide it.
A43: DPG2a | B43: Bengaluru – BMTC | D43: =IFERROR(DPG2a!L14,"") | H43: =IF(OR(F43="",NOT(ISNUMBER(D43))),"",IF(ABS(F43-D43)<0.001,"Yes","No")) | I43: =IF(ISNUMBER(F43),F43,D43) | J43: =IF(ISNUMBER(F43),"Expert (overrides AI)",IF(ISNUMBER(D43),"AI","Not scored yet")) -> Not scored yet | K43: Left for a person | L43: Partially Answered | M43: ANSWER: None of the sources we have gives the city government (GBA or its City Corporations) a seat on BMTC's Board. (1) The enabling Act leaves every appointment to the State Government and only requires seats for the Central and State Governments. (2) The city government's law (GBA Act) does not put the city government on BMTC's Board. It works the other way: BMTC's Managing Director sits on the GBA, and the GBA can supervise and direct BMTC. (3) The Board list on BMTC's website shows 11 directors (Chairman, Vice-Chairman and 9 'DIRECTOR (Official)'). All are State or Central Government officials or heads of state transport corporations. None is a GBA or City Corporation councillor, Mayor or official. This points to 'no representation'. However, the Rules that set out how the Board is made up are not in the Citation Sheet, so absence cannot be confirmed. | EVIDENCE: Parastatal side - Road Transport Corporations Act, 1950 (BMTC-02): s.5(1) puts the running of the Corporation in a Board of Directors. s.5(2): 'The Board shall consist of a Chairman and such other Directors, being not less than five and not more than seventeen, as the State Government may think fit to appoint.' s.5(3): the State Government 'may' appoint a Vice-Chairman. s.5(4): Rules 'shall provide for the representation, both of the Central Government and of the State Government concerned', plus any shareholders. It says nothing about local bodies. s.5(5) and s.45(2)(a): the Directors' term, how they are appoin | N43: THE ROAD TRANSPORT CORPORATIONS ACT, 1950 [BMTC-02] | O43: https://www.transport.telangana.gov.in/html/pdf/The_Road_Transport_Corporations_Act_1950.pdf | P43: (2) The Board shall consist of a Chairman and such other Directors, being not less than five and not more than seventeen, as the State Government may think fit to appoint. | Q43: I left the score blank. The evidence suggests BMTC's Board has no city-government member, but a 0 needs every relevant legal layer to have been read, and the Rules that set the Board's make-up are not in the Citation Sheet. What I checked: (1) BMTC-02, Road Transport Corporations Act, 1950 (compiled text; consolidation date not stated). s.5(2) leaves all Board appointments to the State Government: 'as the State Government may think fit to appoint'. s.5(3) says the State Government 'may' name a Vice-Chairman. Under s.5(4), Rules 'shall provide for the representation' only of the Central and State Governments, plus any shareholders. Nothing is said about local bodies. s.5(5) and s.45(2)(a) leave the Board's make-up, terms and related matters to Rules. (2) BMTC-09, BMTC 'Directors List' page (undated). It shows 11 directors: the Chairman (V.S. Aaradhya) and Vice-Chairman (M. Niketh Raj), both described only by their BMTC posts; the Transport Secretary and the Finance Secretary (Expenditure); the Managing Directors of KSRTC, BMTC, KKRTC and NWKRTC; BMTC's Director (Security & Vigilance) and Director (IT); and the Director (Transport) of MoRTH, Government of India. No GBA or City Corporation councillor, Mayor or Commissioner is listed. The page lists Directors only, so it cannot show whether there are special invitees. (3) BMTC-04, GBA Act 2024 (Act 36 of 2025), as enacted, GBA era. This runs the other way. s.9(3)(i) makes BMTC's Managing Director an ex-officio member of the GBA, and s.14(4) gives the GBA coordinating and directing powers. Neither puts the city government on BMTC's Board, so neither counts as representation. (4) BMTC-06 (BMLTA Act) and BMTC-07 (KTCP Act) are not relevant to BMTC's Board. Missing evidence: - The KSRTC Rules, 1961, or any BMTC-specific Rules. They are listed on BMTC-20, but their text is not in the Sheet. - The State Government notification that set up BMTC and its Board. - Whether the Vice-Chairman holds an elected city-government office. - Whether any special invitees attend Board meetings (the 2.5 band). If a person confirms that the Rules and the notification give no local-body seat or invitee, and that the Vice-Chairman is not a city representative, the score would be 0. Also for the team: GBA Act s.14(4) calls BMTC a 'Limited' company with a 'Memorandum of Association'. That does not match BMTC being set up under the 1950 Act, so its legal form should be confirmed, because that decides which Board-composition instrument applies. The question's full methodology text was not supplied. I assumed a 0–5 rubric with bands of 5 (city representation on the Board), 2.5 (special invitees) and 0 (none), based on the Step 2 notes. | R43: The citation didn't settle every input. "Score" left blank: the Citation Sheet doesn't decide it.
A44: DPG2a | B44: Bengaluru – BDA | D44: =IFERROR(DPG2a!L15,"") -> 5 | H44: =IF(OR(F44="",NOT(ISNUMBER(D44))),"",IF(ABS(F44-D44)<0.001,"Yes","No")) | I44: =IF(ISNUMBER(F44),F44,D44) -> 5 | J44: =IF(ISNUMBER(F44),"Expert (overrides AI)",IF(ISNUMBER(D44),"AI","Not scored yet")) -> AI | K44: Left for a person | L44: Partially Answered | M44: ANSWER: The BDA Act, as amended up to Act 42 of 2026, gives the city's elected council seats on BDA's governing board. Section 3(3)(l) adds two councillors, elected by the councillors of the 'Bangalore City Corporation' from among themselves. Section 3(3)(f) adds the Commissioner of the 'Corporation of the City of Bangalore' as an ex-officio member. These are full members of the Authority, not invitees. The question is whether this still gives the current city government a seat, and that is unresolved. The Act still names the old single Corporation. No source in the Citation Sheet shows that the Greater Bengaluru Authority (GBA) or its City Corporations have been put in its place. There is also no current list of board members. | EVIDENCE: (1) BDA Act 1976 (BDA-02), s.3(3): '(l) two persons elected by the councillors of the Bangalore City Corporation from among themselves in the prescribed manner'. Proviso: while the Corporation is superseded or run by an Administrator, 'the two persons shall be nominated by the Administrator from among the officers of the Corporations'. s.3(3)(f): 'the Commissioner, Corporation of the City of Bangalore, ex-officio' (substituted by Act 34 of 1986). s.2(i): 'Corporation' means the 'Corporation of the City of Bangalore' (substituted by Act 34 of 1986). s.4(1)(f): a member is disqualified if, 'being an elected member', he 'ceases to be a councillor of the Corporation'. s.5(1) proviso: the Corporation representative's term ends when he stops bein | N44: The Bangalore Development Authority Act, 1976 (Act 12 of 1976) – PRS copy, 'Amendments appended: 19 of 2002, 19 of 2005, 27 of 2020, 42 of 2026' [BDA-02] | O44: https://prsindia.org/files/bills_acts/acts_states/karnataka/1976/1976Karnataka12.pdf | P44: (l) two persons elected by the councillors of the Bangalore City Corporation from among themselves in the prescribed manner : | Q44: I left the score blank. The BDA Act gives council seats in law, but the Citation Sheet does not show whether those seats belong to today's city government. What the Act says (BDA-02, PRS copy with amendments up to Act 42 of 2026): - s.3(3)(l) gives two seats to people elected by the councillors of the 'Bangalore City Corporation' from among themselves. - s.3(3)(f) makes the Commissioner of the 'Corporation of the City of Bangalore' an ex-officio member. - s.8(4) says all questions are decided 'by a majority of the votes of the members present and voting'. I found nothing that limits these members' votes, so I agree with Step 2 that they are full voting members. Step 2 had not read s.8; I have now checked it. - s.4(1)(f) and the s.5(1) proviso tie the seat to remaining a Corporation councillor. - Act 42 of 2026 and Act 27 of 2020 do not amend s.3. On the law as written, this looks like the top band (elected councillors as full members). Why I did not give 5: (1) Successor body: the Act still names the old 'Bangalore City Corporation'. The Greater Bengaluru Governance Act (BDA-03) repeals the BBMP Act (s.361) and creates several City Corporations. My searches of BDA-03, BDA-04 and BDA-13 found no clause saying that references to the Corporation in the BDA Act now mean the GBA or a City Corporation. So the sheet does not show which council, if any, elects the two members. (2) Supersession proviso: if the City Corporation councils are dissolved or run by Administrators (GBA Act s.130-131), the s.3(3)(l) proviso hands the seats to Corporation officers, not elected councillors. That would fit a lower band. The sheet has no evidence on whether elected councils are sitting. (3) No current board list: there is no BDA notification under s.3(6) and no current list of members. Step 2 reports that the question bank's evidence requirement asks for one. (4) I was not given the full DPG2a rubric text, so I could not check the bands myself. I relied on Step 2's description of them. The GBA Executive Committee seat for the BDA Commissioner (BDA-13) is the reverse relationship and does not count here. For a person to resolve: - Confirm whether s.3(3)(l) counts as representation for the GBA-era City Corporations. - Confirm whether the City Corporation councils are elected and sitting. - Get the current BDA board list, by RTI to the BDA PIO if needed. If the councils are elected and the seats are filled by councillors, the law supports 5. If Administrators hold them, a lower band applies. | R44: The citation didn't settle every input. "Score" left blank: the Citation Sheet doesn't decide it.
A45: DPG2a | B45: Bengaluru – BMRCL | D45: =IFERROR(DPG2a!L16,"") -> 0 | H45: =IF(OR(F45="",NOT(ISNUMBER(D45))),"",IF(ABS(F45-D45)<0.001,"Yes","No")) | I45: =IF(ISNUMBER(F45),F45,D45) -> 0 | J45: =IF(ISNUMBER(F45),"Expert (overrides AI)",IF(ISNUMBER(D45),"AI","Not scored yet")) -> AI | K45: Left for a person | L45: Partially Answered | M45: ANSWER: Not determined. The Citation Sheet does not show that the ULG has any seat on BMRCL's board, but it is not enough to confirm that the ULG has none today. BMRCL is a company, so its board seats are set by its Articles of Association, not by a statute. The only description of those seats is in the FY2020-21 Annual Report, and it gives nomination rights only to the Government of India (GoI) and the Government of Karnataka (GoK). The board list in that report (as on 31.03.2021, when BBMP was the city government) names 12 directors: 10 GoI/GoK nominees, including the Chairman and the MD, plus 2 functional directors. None is shown as a BBMP nominee, an elected councillor or a BBMP officer. There is no current board list from the GBA era. | EVIDENCE: (1) BMRCL-09, Annual Report FY2020-21, Corporate Governance Report pp.45-46 (printed): it describes the Articles of Association as setting a board of 3 to 15 directors, 'either whole-time functional Directors or Part-time Directors nominated by the Promoter Government(s)'. It calls BMRCL 'a 50:50 joint venture of Government of India and Government of Karnataka' and says 'Both the Governments have the right to nominate five (5) Directors each'. GoI appoints the part-time Chairman and GoK appoints the MD & CEO. The 'Composition of Board as on 31.03.2021' lists 12 directors. Where the report gives a director's post, it is a state or central government office: ACS Urban Development Department, ACS Finance, ACS & Development Commissi | N45: Bangalore Metro Rail Corporation Limited Annual Report (15th AGM; Board's Report and Financial Statements for year ended 31st March, 2021) [BMRCL-09] | O45: https://kla.kar.nic.in/council/house/Paperlaid/146/33.pdf | P45: These Directors may be either whole-time functional Directors or Part-time Directors nominated by the Promoter Government(s). | Q45: I left the score blank because the Citation Sheet does not prove that the city government has no seat on BMRCL's board. What the sources show: - BMRCL is a company. Its board seats are set by its Articles of Association, which are not in the Citation Sheet. - The only description of the Articles is a summary in the Annual Report for FY2020-21 (BMRCL-09, printed pp.45-46). It says the board has 3 to 15 directors, who are either whole-time functional directors or part-time directors nominated by the 'Promoter Government(s)'. The Government of India (GoI) and the Government of Karnataka (GoK) each have the right to nominate five directors. - I checked the board list as on 31.03.2021 against the source. It names 12 directors: the ex officio Chairman, the MD, 8 nominee directors and 2 functional directors. - Where the report gives a director's post, it is a GoI or GoK office: ACS Urban Development, ACS Finance, ACS & Development Commissioner, a Railway Board official and a DMRC director. - The report does not give the posts of every nominee (for example M. Nagaraj and Jaideep). None is shown as a BBMP nominee, an elected councillor or a BBMP officer. - This list is from the BBMP era (31.03.2021). It is not evidence of the board's make-up today, under the Greater Bengaluru Authority (GBA). What I checked on the city government side: - Greater Bengaluru Governance Act (BMRCL-02). It works the other way round: BMRCL's MD sits on the GBA (s.9(3)(j)) and on its Executive Committee (s.13(1)(j)), and the GBA can supervise and direct BMRCL (s.14(4)). Neither gives the city government a seat on BMRCL's board, so neither earns credit here. - Metro Railways (O&M) Act 2002 (BMRCL-04): it has no board-composition clause. - Companies Act 2013 (BMRCL-06): general company law only. - BMLTA Act (BMRCL-08) and its 2025 amendment bill (BMRCL-38): these are about the BMLTA's own membership (they name the BBMP Mayor and Chief Commissioner), not BMRCL's board. Why a 0 is not justified: under the v2 rule a 0 needs proof of absence. The Articles and a current board list are missing, and some directors' posts are unknown, so this is a 'not found' result, not an absence. What a person should check: - Get the current Articles of Association and the current list of directors, with each director's post and which government nominated them. Ask BMRCL's Company Secretary or Public Information Officer. - If a city government official (not an elected representative) turns up on the board, the team needs to decide how to score them, since the top band (5) names only elected representatives of the city government with voting rights. - The team still needs to confirm whether BMRCL counts as a parastatal for this survey, given that it is a company. | R45: The citation didn't settle every input. "Score" left blank: the Citation Sheet doesn't decide it.
A46: DPG2a | B46: Bengaluru – BMRDA | D46: =IFERROR(DPG2a!L17,"") -> 5 | H46: =IF(OR(F46="",NOT(ISNUMBER(D46))),"",IF(ABS(F46-D46)<0.001,"Yes","No")) | I46: =IF(ISNUMBER(F46),F46,D46) -> 5 | J46: =IF(ISNUMBER(F46),"Expert (overrides AI)",IF(ISNUMBER(D46),"AI","Not scored yet")) -> AI | K46: Left for a person | L46: Partially Answered | M46: ANSWER: Not determined. The Citation Sheet does not show whether the ULG has a voting seat on BMRDA's governing board. The only evidence is BMRDA's own 2022-23 annual report, which summarises the BMRDA Act 1985 in its own words. On that summary: (i) the Authority itself has government-nominated 'representatives of the Local Authorities from the Region', and these seats have been vacant since July 2005; (ii) the Executive Committee includes 'the Mayor of Bangalore' (BBMP-era). The BMRDA Act's composition clause is not in the Citation Sheet. So it cannot be confirmed whether these seats exist in the current law, whether they vote, or whether the Mayor seat now passes to the GBA or City Corporation mayors. There is no current board member list. | EVIDENCE: (1) BMRDA-03, BMRDA Annual Report 2022-23, p.10, s.3 'Composition of the Authority and its Executive Committee': the Chief Minister chairs and the Minister for Urban Development is Vice Chairman; 'The Act also provides for nomination by the Government of individuals representing ... members of the State Legislature and representatives of the Local Authorities from the Region. Such representations fell vacant since July 2005 due to removal / resignation of the nominees.' Also: 'The Executive Committee is chaired by the Minister for Urban Development, while the Metropolitan Commissioner is the Vice Chairman and the Mayor of Bangalore, the Secretaries to Government and heads of several related departments/ organisations are the M | N46: Annual Report of Bangalore Metropolitan Region Development Authority for the year 2022-2023 [01-04-2022 to 31-03-2023] [BMRDA-03] | O46: https://kla.kar.nic.in/council/house/Paperlaid/152/37.pdf | P46: The Act also provides for nomination by the Government of individuals representing labour, women, scheduled castes, scheduled tribes, members of the State Legislature and representatives of the Local Authorities from the Region. Such representations fell vacant since July 2005 due to removal / resignation of the nominees. | Q46: I left the score blank because the Citation Sheet cannot decide it. I could not see the question's own text or Detailed Methodology, so I am reading DPG2a as asking whether the city government (ULG) has a voting seat on BMRDA's governing board. (1) The only evidence on BMRDA's board make-up is BMRDA-03, the BBMP-era annual report for FY 2022-23 (1 Apr 2022 to 31 Mar 2023). It is BMRDA's own summary of the Act, not the Act. It says the Act provides for the State Government to nominate 'representatives of the Local Authorities from the Region' to the Authority. Those seats have been vacant since July 2005. Separately, it says 'the Mayor of Bangalore' sits on the Executive Committee. It says nothing about voting rights. It does not say whether the nominees must be elected ULG representatives, and they are chosen by the State, not by the ULG. It does not say whether the Executive Committee counts as the 'governing board'. (2) The BMRDA Act 1985 text and the BMRDA Regulations of 1996, 1999 and 2000 are only linked from the website pages (BMRDA-13 lists 'act 1985 ka.pdf' and the Regulations PDFs, plus a 'constitution-of-the-authority' page). None of their text is in the Citation Sheet, so I cannot check the composition clause, voting rights or any amendment. (3) BMRDA-10, the Greater Bengaluru Governance Act 2024 (Karnataka Act 36 of 2025), works in the opposite direction. Under s.9(3)(u) and s.13(1)(e), BMRDA's Metropolitan Commissioner sits on the GBA and its Executive Committee. The parts of the Act in the Citation Sheet show nothing that substitutes a GBA or City Corporation office for the 'Mayor of Bangalore' seat in BMRDA's law. (4) BMRDA-08, the KTCP Act s.4C, covers Local Planning Authorities, which are not BMRDA's board. A score of 0 is not possible: there is no affirmative absence, because the Act and Regulations were never read and the report itself says local-authority seats exist in law. A positive score is not possible either, because voting rights, whether the seat is elected and the current member list are all unverified. ERA: the annual report is BBMP-era. The ULG has since been restructured under the GBG Act 2024, so the 'Mayor of Bangalore' wording is historical. A person should: (a) get and read the BMRDA Act 1985 composition section and the 1996 Regulations from the BMRDA Acts & Rules page, looking for voting rights and the Executive Committee's powers; (b) decide whether the Executive Committee or only the Authority counts as the governing board; (c) check whether any official instrument replaced the Mayor seat after the GBA came in; (d) get a current list of Authority members. | R46: The citation didn't settle every input. "Score" left blank: the Citation Sheet doesn't decide it.
A47: DPG2a | B47: Surat – SUDA | D47: =IFERROR(DPG2a!L18,"") | H47: =IF(OR(F47="",NOT(ISNUMBER(D47))),"",IF(ABS(F47-D47)<0.001,"Yes","No")) | I47: =IF(ISNUMBER(F47),F47,D47) | J47: =IF(ISNUMBER(F47),"Expert (overrides AI)",IF(ISNUMBER(D47),"AI","Not scored yet")) -> Not scored yet | K47: Left for a person | L47: Partially Answered | M47: ANSWER: Partly answered. In the 2016 board list, Surat Municipal Corporation (SMC) has seats on the SUDA board: the Chairman of SMC's Standing Committee sits as a 'Member', and the Municipal Commissioner and SMC City Engineer sit as ex-officio members. The Standing Committee Chairman looks like the one elected ULG representative on the board. Whether any of these members can vote could not be determined, and the composition clause of the Act (s.22) could not be read. The highest band ('ULG-elected representatives ... with voting rights') therefore cannot be confirmed. | EVIDENCE: (1) SUDA-14, Development Plan 2035 (SUDA, 2017), s.1.4.1, pp.26-27. Table 4 lists the first board, constituted in 1978 under GTPUD Act s.22(1), (2), (4): it includes 'Chairman, Standing Committee, SMC' as Member and 'City Engineer, SMC' as Ex-Officio Member. The plan says that 'After the amendment in the Section 22 of the Act in 1999, the Municipal Commissioner was added as ex-officio member'. Table 5 (Members of SUDA Board, 2016) lists the Chairman (an IAS officer); the Chairman, Standing Committee, SMC (Member); the District Collector (Member-Secretary and Chief Executive Authority); the Municipal Commissioner, SMC (Ex-Officio); the President, District Panchayat; the District Development Officer; the Chief Town Planner; the Financial Advisor, GoG; and the City Engineer, SMC (Ex-Officio). No voting or invitee status is shown for anyone. (2) SUDA-01, GTPUD Act 1976 (PRS copy with amendments): pages 2 | N47: DEVELOPMENT PLAN 2035 2017 SURAT URBAN DEVELOPMENT AUTHORITY [SUDA-14] | O47: https://www.sudaonline.org/wp-content/uploads/2017/03/SUDA-DP-2035-report-final-22.02.2017.pdf | P47: After the amendment in the Section 22 of the Act in 1999, the Municipal Commissioner was added as ex-officio member of the Urban Development Authority. The present board members of SUDA are shown in the Table below. | Q47: Score left blank because a key fact is missing: whether the SMC members can vote. What the sources show: (1) SUDA-14 (SUDA Development Plan 2035, published 2017, era n/a) lists the 2016 SUDA board. SMC holds three seats: the Chairman of SMC's Standing Committee as 'Member', and the Municipal Commissioner and the SMC City Engineer as 'Ex-Officio Member'. The 1978 first board, appointed under GTPUD Act s.22(4), also had the Standing Committee Chairman as a Member. (2) I checked one point the Step 2 answer had left open. SUDA-04 (Gujarat Provincial Municipal Corporations Act 1949, as modified up to 30-11-2017) confirms that the Standing Committee Chairman is an elected councillor. Its s.20(1) says 'The Standing Committee shall consist of twelve councillors', and s.21(1) says the Committee members 'shall appoint one of its members to be the Chairman'. So SMC has at least one elected representative on the SUDA board (as of 2016), plus two SMC officials. The Commissioner and City Engineer are officials, not elected representatives. What is missing: (a) Voting rights. No source in the Citation Sheet says whether SMC's members vote on the SUDA board. Table 5 shows positions only. The members are listed as 'Member', not 'invitee', but that alone does not prove they vote. The GTPUD Act s.22 text in SUDA-01 is on scanned pages with no readable text. The readable amendment Acts (6 of 2017, 22 of 2017, 14 of 2019) do not touch s.22. SUDA-03 (GTPUD Rules 1979) has no rule on authority meetings or voting in the parts I read. (b) The current board. The newest list is from 2016, and there is no constitution or reconstitution notification. (c) The 1999 amendment to s.22 is known only from SUDA-14's account; I did not read it directly. The question's band wording was not supplied in full. Per the Step 2 answer, the top band (5) needs 'ULG-elected representatives ... with voting rights'. The evidence fits at least the 2.5 level, but scoring 2.5 risks under-scoring and 5 would be a guess. A zero is clearly ruled out: SMC is represented. A person should get a readable official copy of GTPUD Act s.22 as amended (or SUDA's board regulations) and a current board notification showing who votes, for example through an RTI request to SUDA's PIO (Public Information Officer). If the SMC members are full voting members, the answer points to 5. If they are non-voting, it points to 2.5. | R47: The citation didn't settle every input. "Score" left blank: the Citation Sheet doesn't decide it.
A48: DPG2a | B48: Surat – GMRC | D48: =IFERROR(DPG2a!L19,"") | H48: =IF(OR(F48="",NOT(ISNUMBER(D48))),"",IF(ABS(F48-D48)<0.001,"Yes","No")) | I48: =IF(ISNUMBER(F48),F48,D48) | J48: =IF(ISNUMBER(F48),"Expert (overrides AI)",IF(ISNUMBER(D48),"AI","Not scored yet")) -> Not scored yet | K48: Left for a person | L48: Partially Answered | M48: ANSWER: The current evidence shows no representation for the city government (Surat Municipal Corporation, SMC) on GMRC's board. That covers both elected SMC councillors and SMC officials, as voting directors or as invitees. All directors are nominees of the Government of India (GoI) or the Government of Gujarat (GoG), or are GMRC's own functional directors. The rule that sets the board's composition is GMRC's Articles of Association, and that document is not in the Citation Sheet. So 'no representation' cannot be confirmed at the level of the composition rule, and no score is given. | EVIDENCE: GMRC side: (1) GMRC-04, the Present Board of Directors page (updated 12-Oct-2026), lists 'Nominated By Government of India': the Secretary of the Ministry of Housing & Urban Affairs (MoHUA, Chairman) and MoHUA's Joint Secretary & Financial Advisor. Under 'Nominated By Government of Gujarat' it lists the Additional Chief Secretary (Finance Department), the Principal Secretary (Urban Development & Urban Housing Department), the Managing Director of Gujarat Energy Limited and Shri S.S. Rathore (Managing Director). It also lists two 'Functional Directors' (Project & Planning; Finance). No SMC councillor, Mayor or Municipal Commissioner appears, and no invitee category is shown. (2) GMRC-03, the RTI s.4(1)(b) disclosure, Chapter 8: 'The board of directors of GMRCL consists of 13 directors, which include five nominees from the Government of India, five nominees from the Government of Gujara | N48: Proactive Disclosure under the provision of Section 4(1)(b) of RTI Act 2005 [GMRC-03] | O48: https://www.gujaratmetrorail.com/proactive-disclosure-under-the-provision-of-section-41b-of-rti-act-2005/ | P48: The board of directors of GMRCL consists of 13 directors, which include five nominees from the Government of India, five nominees from the Government of Gujarat Three functional directors. | Q48: I left the score blank. All the evidence I found says GMRC's board has no city government (ULG) representative. But a 0 needs affirmative absence, which I can't establish. (a) The rule that sets the board's make-up is not in the Citation Sheet. (b) The task did not include the question's rubric (Detailed Methodology / bands), so I can't map the evidence to a 0-5 band. WHAT THE SOURCES SHOW: (1) GMRC-03 (RTI s.4(1)(b) disclosure, Chapter 8): the board is 13 directors. Five are Government of India (GoI) nominees, five are Government of Gujarat (GoG) nominees and three are functional directors. No municipal seat is mentioned. (2) GMRC-04 (Present Board of Directors page, last updated 12-Oct-2026), read in full: - GoI nominees: MoHUA Secretary (Chairman) and MoHUA JS & FA. - GoG nominees: ACS Finance, PS of the Urban Development & Urban Housing Dept, MD of Gujarat Energy Ltd, and the GMRC Managing Director. - Functional directors: Director (Project & Planning) and Director (Finance). - No Surat Municipal Corporation (SMC) councillor, Mayor, Municipal Commissioner or special invitee is listed. (3) GMRC-05 (2024-25 Annual Report): - s.XII says GMRC is a 50:50 GoI/GoG SPV, and each government appoints five directors. - s.XIII says the board had 11 directors 'out of maximum fifteen (15) as provided in the Articles of Association' (as on 31-03-2025). - The board committees are made up only of GoI and GoG nominees. - SMC appears only in the acknowledgements. (4) The PS (UD&UHD) is a state government official, not an SMC representative. CHECKED: GMRC-03, GMRC-04 and GMRC-05 (read). I also searched the whole sheet for 'Municipal Commissioner Surat director board GMRC'. The only hits were the acknowledgement in GMRC-05, a line in the Gender Action Plan (GMRC-10) saying there are 12 board members, and unrelated EIA rows. WHAT'S MISSING: (i) GMRC's Memorandum & Articles of Association. The annual report names these as the rule that sets board size and nominations. No GoI-GoG agreement or nomination clause from the sanction order is in the sheet either. (ii) The ULG side: the GPMC Act, 1949 (GMRC-18) has not been read in full for any provision giving the corporation a seat on a metro company board. (iii) The rubric itself. FOR THE TEAM: - If the team accepts the current board list plus the annual report as enough, the evidence points to the lowest band ('no ULG representation'). A person should confirm this against the rubric and the Articles. - Confirm that SMC is the ULG; the ULG name was blank upstream. - The sources disagree on board size: 13 in GMRC-03, 11 of a maximum 15 in GMRC-05, 8 listed in GMRC-04, and 12 in GMRC-10. - RTI target: GMRC's Public Information Officer, for the current Articles of Association and the director-nomination clauses. | R48: The citation didn't settle every input. "Score" left blank: the Citation Sheet doesn't decide it.
A49: DPG2b | B49: Bengaluru – BWSSB | D49: =IFERROR(DPG2b!L13,"") -> 0 | H49: =IF(OR(F49="",NOT(ISNUMBER(D49))),"",IF(ABS(F49-D49)<0.001,"Yes","No")) | I49: =IF(ISNUMBER(F49),F49,D49) -> 0 | J49: =IF(ISNUMBER(F49),"Expert (overrides AI)",IF(ISNUMBER(D49),"AI","Not scored yet")) -> AI | K49: Left for a person | L49: Partially Answered | M49: ANSWER: The sources I could read contain no requirement for BWSSB to submit or table its plans, budgets or annual/performance reports before the ULG: the Greater Bengaluru Authority (GBA), a City Corporation or its council. Every submission duty in the BWSSB Act runs to the State Government, and the State Government then lays the document before the State Legislature or publishes it in the Gazette. The methodology says submission only to the State Government does not count. So the evidence points to no requirement for any of the three components. I am not proposing a 0, though, because two layers of the law were not available to check: the BWSSB Rules and Regulations, and the full GBA Act text. | EVIDENCE: Parastatal side, BWSSB Act 1964 (BWSSB-02). (1) Budget, s.17(1): 'In February of each year the Board shall submit to the State Government a statement ... of the estimated capital and revenue receipts and expenditure for the ensuing year'. Under s.17(3) the State Government lays it before both Houses of the State Legislature, and under s.17(4) the Board considers the Legislature's comments. Nothing sends it to the Corporation. (2) Annual report, s.86(1): an annual report goes to the State Government and is published in the Gazette. s.86(2): a yearly activity report goes to the State Government and is laid before the State Legislature. That report must also cover 'the activities, if any, which are likely to be undertaken by the Board in the next financial year', which is the | N49: The Bangalore Water Supply and Sewerage Act, 1964 [BWSSB-02] | O49: https://prsindia.org/files/bills_acts/acts_states/karnataka/1964/1964KR36.pdf | P49: The Board shall, before such date and in such form as may be prescribed by rules, submit to the State Government an annual report upon such matters as may be prescribed by rules, and the State Government shall cause such report to be published in the official Gazette. | Q49: Score left blank. The sources point to no requirement for BWSSB to submit its plans, budgets or reports to the city government, but a 0 needs proof that nothing exists in every layer of the law, and two layers are missing. I checked the sources against the Step 2 answer and they support it. What I read: (1) BWSSB Act 1964 (BWSSB-02, PRS consolidated copy, secondary text, era n/a). s.17(1) sends the annual budget statement to the State Government, and s.17(3) has it laid before the State Legislature. s.86(1) sends the annual report to the State Government and has it published in the Gazette. s.86(2) sends the yearly activity report, which also covers activities planned for the next year, to the State Government and the State Legislature. s.86(3) gives the State Government statistics and scheme details on demand. s.25(4)-(5) sends the audited accounts to the State Government and the State Legislature. s.14(5) has the Board place its budget statement before the Consultative Committee. That Committee is set up by the State Government and is advisory (s.14(4)). Its members are State appointees chosen 'after consultation with' bodies including the BBMP, so it is not the city government or its council. s.14(1) still names the BBMP, the predecessor body. No official source shows the Greater Bengaluru Authority (GBA) or the City Corporations substituted. (2) Greater Bengaluru Governance Act 2024, Act 36 of 2025 (BWSSB-04, GBA era), searched again. s.14(4) gives the GBA power to supervise public authorities, naming BWSSB, and to issue binding directions; that is a power to direct, not a duty on BWSSB to submit documents. s.19(1) lets 'The Government', not the GBA or the Corporations, call for periodic reports. s.21-22 cover only the GBA's own budget and annual report (s.22(2) sends copies to the City Corporations). No provision requires BWSSB to submit plans, budgets or reports to the GBA or a City Corporation. (3) Amendment Bill 81 of 2025 (BWSSB-28) has no relevant provision in the parts in the sheet. Missing: the BWSSB Rules made under s.87, which set the form and date of the annual report and budget statement; the BWSSB Regulations; and a consolidated GBA Act after amendment. None of these is in the Citation Sheet. So the result is 'not found', not an affirmative 0. If the team confirms the Rules and Regulations add no submission to the GBA or City Corporations, the evidence supports 0/5. A person should also check whether the reference to the BBMP in s.14 has been replaced by the GBA or City Corporations. | R49: The citation didn't settle every input. "Score" left blank: the Citation Sheet doesn't decide it.
