Workbook

Sheet Scores (start here)
A1: Question | B1: Row | C1: Question text | D1: AI score | E1: Max score | F1: ★ Your score | G1: ★ Your comments | H1: Agrees with AI? | I1: Final score | J1: Score used | K1: Status | L1: Step 2 status | M1: Step 2 answer | N1: Citation | O1: Link | P1: Quote | Q1: AI's reasoning | R1: Why left for a person
A2: UPD1 | B2: Bangalore | C2: Is there a provision for a State Spatial Planning Board which is mandated with planning policies and reforms for the state? | D2: =IFERROR('UPD1'!L14,"") | E2: 10 | H2: =IF(OR(F2="",NOT(ISNUMBER(D2))),"",IF(ABS(F2-D2)<0.001,"Yes","No")) | I2: =IF(ISNUMBER(F2),F2,D2) | J2: =IF(ISNUMBER(F2),"Expert (overrides AI)",IF(ISNUMBER(D2),"AI","Not scored yet")) -> Not scored yet | K2: Left for a person | L2: Partially Answered | M2: ANSWER: Partly answered. The Karnataka Town and Country Planning Act, 1961 does provide for a State Town-Planning Board. But section 4 only enables it: the State Government "may" set it up by notification. It is not a "shall" provision. Under the methodology, a "may" provision earns Part A only if the Board has actually been set up by a government notification or order, or this is shown on an official state department website. No such notification, order or website is in the Citation Sheet, so Part A cannot be decided. If Part A were met, Part B would be supported: s.4 gives the Board a stated mandate to advise the State on planning and development and to set principles and policies for the State as a whole. | EVIDENCE: (1) KTCP Act 1961, s.4 (ULG-02, PRS compilation, p.21-22): "The State Government may, by notification, constitute a State Town-Planning Board for the State ... for advising the State Government regarding planning and development and for determining principles and policies for achieving the balanced development of the State as a whole." (2) s.2(1a): "'Board' means the State Town Planning Board constituted under this Act". (3) The Act also says the State Government must consult "the Board" before amalgamating or sub-dividing planning areas (s.4A(3)), framing schemes for funds and assets (s.4A(5), s.4B(2)(ii)) and setting up Planning Authorities (s.4C(1)). These sections assume a Board exists, but they do not prove it was ever set up. (4) s.3 makes appointing a D | N2: The Karnataka Town and Country Planning Act, 1961 (Karnataka Act 11 of 1963), PRS compilation with amendments up to Act 38 of 2015 [ULG-02] | O2: https://prsindia.org/files/bills_acts/acts_states/karnataka/1963/1963KR11.pdf | P2: 4. State Town-Planning Board. —The State Government may, by notification, constitute a State Town-Planning Board for the State with such members and in such manner as may be prescribed for advising the State Government regarding planning and development and for determining principles and policies for achieving the balanced development of the State as a whole. | Q2: Part A is left blank because the evidence is not found, not because the Board is absent. Section 4 of the Karnataka Town and Country Planning (KTCP) Act 1961 (ULG-02, PRS compilation, amended up to Act 38 of 2015) only enables a State Town-Planning Board: the State Government "may, by notification, constitute" it. It is not a 'shall' provision. The methodology says a 'may' provision earns Part A only if a government notification or order, or an official department or planning-body website, shows the Board was actually set up. No such notification, order or web page is in the Citation Sheet. Other sections require consulting "the Board": s.4A(3) and (5), s.4B(2)(ii) and s.4C(1). Section 2(1a) defines the Board as "constituted under this Act". These sections assume a Board exists but do not prove it was set up, so they are not enough. I did not score NO, because there is no affirmative absence: the Board may well exist and the sheet simply lacks the proof. What I checked: KTCP Act sections 2(1a), 3, 4, 4A-4H and 51 (ULG-02). Section 3 (the Director of Town Planning, a 'shall' duty) is an official, not a board. Section 51 Joint Town Planning Boards are local bodies, not a state-level body. I also checked the KTCP Amendment Bill 2025 (ULG-03). It creates a Commissionerate and Commissioner (new ss.2A-2B) and makes the Greater Bengaluru Authority the planning authority (new s.81-G). It leaves s.4 unchanged and does not say the Board exists. It is also a Bill: its commencement depends on a notification, which is not in the sheet. I found nothing relevant in the Greater Bengaluru Governance Act 2024 (ULG-01), the GBG Amendment Bill (ULG-05), the BBMP Act 2020 (ULG-19), the BDA Act (ULG-04), the BMLTA Act (ULG-18) or the BMRDA pages (ULG-10/20/21). A sheet-wide search for 'State Town Planning Board' returned only ULG-02. Part B = YES. Section 4 explicitly gives the Board the job of "advising the State Government regarding planning and development and for determining principles and policies for achieving the balanced development of the State as a whole". That is a state-level planning-policy mandate. The word 'reforms' is not used, but under the scorer notes the Board's functions match the intent of the question. Per the column, Part B counts only if Part A = YES. To confirm: find the notification or GO constituting the State Town-Planning Board under s.4, or the official department web page showing it. Also find the KTCP Rules that set its membership. If either is found, Part A = YES and the score would be 10/10. Also check the official law department or gazette text and any amendments after 2015 (the Act text here is a PRS republication, a secondary source). | R2: The citation didn't settle every input. "Part A: State planning board provided / constituted" left blank: the Citation Sheet doesn't decide it.
A3: UPD1 | B3: Surat | C3: Is there a provision for a State Spatial Planning Board which is mandated with planning policies and reforms for the state? | D3: =IFERROR('UPD1'!L33,"") | E3: 10 | H3: =IF(OR(F3="",NOT(ISNUMBER(D3))),"",IF(ABS(F3-D3)<0.001,"Yes","No")) | I3: =IF(ISNUMBER(F3),F3,D3) | J3: =IF(ISNUMBER(F3),"Expert (overrides AI)",IF(ISNUMBER(D3),"AI","Not scored yet")) -> Not scored yet | K3: Left for a person | L3: Insufficient Evidence | R3: Step 2 found no evidence: a source needs to be found and added. Step 2 found no evidence (Insufficient Evidence). Source needed: A readable consolidated text of the Gujarat Town Planning and Urban Development Act, 1976 (official Legislative and Parliamentary Affairs Department or UD&UHD copy), checked section by section for any state town planning or spatial planning board. If the Act only says the government 'may' set one up, a Gujarat government notification or order constituting it, or the UD&UHD / Chief Town Planner page describing it and its functions.
A4: UPD2 | B4: Bangalore | C4: Is there a provision for the establishment of Planning Authorities for notified new towns or special developments? | D4: =IFERROR('UPD2'!K14,"") -> 10 | E4: 10 | H4: =IF(OR(F4="",NOT(ISNUMBER(D4))),"",IF(ABS(F4-D4)<0.001,"Yes","No")) | I4: =IF(ISNUMBER(F4),F4,D4) -> 10 | J4: =IF(ISNUMBER(F4),"Expert (overrides AI)",IF(ISNUMBER(D4),"AI","Not scored yet")) -> AI | K4: Scored by AI | L4: Answered — Verified Source | M4: ANSWER: Yes. Karnataka's town planning law, the Karnataka Town and Country Planning (KTCP) Act, 1961, lets the State Government notify any area in the state as a Local Planning Area under s.4A(1). Once it has done so, s.4C(1) lets it set up a 'Planning Authority' for that area by gazette notification. The Act can also extend an existing planning area to cover an adjacent area. Every Planning Authority must then prepare a master plan for its area within two years of the area being declared (s.9(1)). The provision covers any newly notified area. The Act has no separate 'new town' or 'special development' authority clause. The power to set up an authority is discretionary ('may'), not a duty. | EVIDENCE: (1) KTCP Act 1961 (ULG-02, PRS text with amendments up to Act 38 of 2015), Chapter IA. s.4A(1): 'The State Government may by notification declare any area in the State to be a Local Planning Area for the purposes of this Act, or include within such local planning area, any area adjacent thereto'. s.4A(2): the notification must define the area's limits. s.4A(3): areas can be amalgamated or sub-divided after consulting the State Town-Planning Board. s.4C(1): 'As soon as may be, after declaration of a local planning area, the State Government in consultation with the Board, may, by notification in the official Gazette, constitute ... an authority to be called the "Planning Authority" of that area'. s.4C(2)-(3): the authority is a body corporate, with a Chairman and a Town Planning | N4: The Karnataka Town and Country Planning Act, 1961 (Karnataka Act 11 of 1963), PRS compilation with amendments up to Act 38 of 2015 [ULG-02] | O4: https://prsindia.org/files/bills_acts/acts_states/karnataka/1963/1963KR11.pdf | P4: As soon as may be, after declaration of a local planning area, the State Government in consultation with the Board, may, by notification in the official Gazette, constitute for the purposes of the performance of the functions assigned to it, an authority to be called the “Planning Authority” of that area, having jurisdiction over that area. | Q4: I checked the Step 2 answer against the text of ULG-02 and the source supports it. The source is the KTCP Act 1961, Karnataka Act 11 of 1963, in a PRS compilation with amendments up to Act 38 of 2015. Three provisions decide the answer. s.4A(1) says 'The State Government may by notification declare any area in the State to be a Local Planning Area for the purposes of this Act, or include within such local planning area, any area adjacent thereto'. s.4C(1) lets the State set up a 'Planning Authority' for that area by Gazette notification, as a body corporate with set membership (s.4C(2)-(3)). s.9(1), substituted by Act 1 of 2005, says 'Every planning authority shall ... not later than two years from the date of declaration of the local planning area, prepare and publish ... a master plan for such area'. Taken together, the Act provides for setting up a Planning Authority for any newly notified area. It also covers the methodology's other route: an adjacent area added to an existing planning area must be planned by that area's authority. On that basis the answer is YES. Points for a reviewer: (1) s.4C uses 'may', so setting up an authority is discretionary. The methodology only asks whether a provision exists, so this still counts as YES. (2) The Act has no clause naming 'new towns' or 'special developments'. The general power to notify a new Local Planning Area and set up its authority is what meets the test. (3) ULG-02 is a PRS compilation, a secondary source. Amendments after 2015 are not in the Citation Sheet. The 2025 KTCP Amendment Bill (ULG-03) is not shown to be enacted, so I did not rely on it. (4) The KTCP Rules and the Karnataka Urban Development Authorities Act 1987 are not in the Citation Sheet. They are not needed for a YES. Context only, not used for scoring: ULG-01 (GBA Act 2024) makes GBA the Planning Authority under the KTCP Act for the Greater Bengaluru Area, and ULG-04 (BDA Act s.67, which inserted KTCP s.81-B) does the same for BDA in the City of Bangalore.
A5: UPD2 | B5: Surat | C5: Is there a provision for the establishment of Planning Authorities for notified new towns or special developments? | D5: =IFERROR('UPD2'!K33,"") -> 10 | E5: 10 | H5: =IF(OR(F5="",NOT(ISNUMBER(D5))),"",IF(ABS(F5-D5)<0.001,"Yes","No")) | I5: =IF(ISNUMBER(F5),F5,D5) -> 10 | J5: =IF(ISNUMBER(F5),"Expert (overrides AI)",IF(ISNUMBER(D5),"AI","Not scored yet")) -> AI | K5: Scored by AI | L5: Partially Answered | M5: ANSWER: Very likely yes, but the provision itself cannot be read in the Citation Sheet. Three official sources say that the Gujarat Town Planning and Urban Development Act, 1976 (GTPUD Act) lets the State constitute Area Development Authorities (s.5) and Urban Development Authorities (s.22) for areas declared as development areas. The development plan for such an area is prepared by that authority or by an officer the State authorises. However, the Citation Sheet copy of the Act (ULG-01, PRS) has no readable text for the principal Act (pages 2-86 are blank or scanned). So the actual wording of ss.3, 5 and 22 (the trigger, 'shall' or 'may', and whether new towns or special developments are covered) cannot be quoted or checked. | EVIDENCE: (1) Comprehensive General Development Control Regulations 2017 (CGDCR), Table 1.1, a binding state notification of the Urban Development and Urban Housing Department (ULG-14, p.1-2, and the same in ULG-05). It groups bodies as category D1 'Urban Development Authority (Constituted under Section 22 of The Gujarat Town Planning and Urban Development Act, 1976)', which includes Surat Urban Development Authority (SUDA), and category D2 'Urban/ Area Development Authority (Constituted under Section 22 or 5...)'. Category D3 covers Area Development Authorities 'Constituted under Section 5' (e.g. Bhuj, Bhachau, Rapar, Anjar). (2) GTPUD Rules 1979 (ULG-04): r.3 has an 'authorized Officer' appointed under s.9(2) prepare the draft development plan 'withi | N5: Comprehensive General Development Control Regulations (CGDCR) 2017, Part I: Procedure Regulations (UD&UHD, Government of Gujarat). This copy is hosted on the Rajkot Municipal Corporation website [ULG-14] | O5: https://rmc.gov.in/rmcwebsite/docs/All_TPS/TP_34/CGDCR_2017_PART_1_PROCEDURE_REGULATIONS.pdf | P5: D5(4) Area Development Authority (Constituted under Section 5 of The Gujarat Town Planning and Urban Development Act, 1976 (Special Project Areas) viz.:Alang Area Development Authority (AlADA) | Q5: Why YES: Under the methodology, the question is whether the state town planning law (here the Gujarat Town Planning and Urban Development Act, 1976, the GTPUD Act) provides for setting up a planning authority for notified new areas or special developments. I checked the Step 2 answer against the sources and it holds up. The evidence is the CGDCR 2017 (ULG-14, the same text as ULG-05). This is a binding Gujarat UD&UHD notification made under GTPUD Act s.116A/122. Its Table 1.1 records the state government's statement of the legal basis for bodies that already exist. Category D5 is Area Development Authorities 'Constituted under Section 5' of the GTPUD Act for 'Special Project Areas' (Alang, Ambaji, Shamlaji, Khambhaliya). This fits 'special developments' directly. Other categories are D1, D2 and D4 (Urban Development Authorities under s.22, including SUDA), D3 (Section 5 Area Development Authorities in Seismic Zone V) and D7A/D7B (authorities designated under s.6). Other sources point the same way. (1) The GTPUD (Amendment) Act 2017, appended in ULG-01 (p.90), amends ss.7(2) and 23(2) so that the State 'may' delegate 'the powers and functions of the Area Development Authorities' and 'of the Urban Development Authorities' to local authorities. This shows that both kinds of authority are created by the Act. (2) GTPUD Rules 1979 (ULG-04) rr.3 and 5 refer to the 'area declared as development area' and the 'area development authority or ... the authorized officer'. So where no authority is constituted, an authorised officer prepares the plan, which also fits the methodology's alternative test. (3) SUDA's DP 2035 report (ULG-06, p.13) says the 1976 Act 'made the provision for formation of Urban / Area Development Authorities' for growth beyond municipal limits. What to check (why confidence is low): The operative text of GTPUD Act ss.3, 5 and 22 cannot be read in ULG-01 (PRS copy; the principal Act's pages are scanned or blank). So I could not quote the exact trigger ('development area' or 'urban development area' declared by notification) or the verb ('may' or 'shall'). The YES rests on a binding state regulation and on amendment and Rules text that refer to these sections, not on the sections themselves. A reviewer should get readable official text of ss.3, 5 and 22 to confirm. Also confirm that UPD2 scores YES = 10 and NO = 0; the methodology does not state bands. I did not check the Gujarat Special Investment Region Act or the GIDC Act 1962 because they are not in the Citation Sheet. They are not needed for YES, since the GTPUD Act provision is enough.
A6: UPD3a | B6: Bangalore | C6: Does the Act require three levels of spatial plans for cities: Metropolitan/Regional, Municipal and Ward(s) /Local >:< Metropolitan/ Regional Plan | D6: =IFERROR(UPD3a!K14,"") -> 3.33 | E6: 10 >:< 3.33 | H6: =IF(OR(F6="",NOT(ISNUMBER(D6))),"",IF(ABS(F6-D6)<0.001,"Yes","No")) | I6: =IF(ISNUMBER(F6),F6,D6) -> 3.33 | J6: =IF(ISNUMBER(F6),"Expert (overrides AI)",IF(ISNUMBER(D6),"AI","Not scored yet")) -> AI | K6: Scored by AI | L6: Answered — Verified Source | M6: ANSWER: Yes. Karnataka law requires a metropolitan plan for Bengaluru. Clause (2)(c) of the Greater Bengaluru Governance Act, 2024 uses 'shall' twice. The State Government must set up a Bengaluru Metropolitan Planning Committee (BMPC), with membership as laid down in Article 243ZE of the Constitution, for an area at least as large as the Greater Bengaluru Area. A named planning body must then prepare a draft development plan for the Greater Bengaluru Area as a whole. On the regional side, the official BMRDA website lists preparing a structure plan for the Bangalore Metropolitan Region as one of the functions the Authority 'shall' have. Who prepares what: the metropolitan draft development plan is assigned to the 'Bengaluru Metropolitan Planning Authority' (this is the Act's wording, inside the BMPC clause). The Chief Commissioner of the Greater Bengaluru Authority (GBA) is the BMPC's Member Secretary, and the Chief Minister chairs it. BMRDA, a state body, prepares the regional structure plan. Separately, the GBA is the KTCP 'Planning Authority' for the Greater Bengaluru Area and must make its master plan. | EVIDENCE: (1) ULG-01, Greater Bengaluru Governance Act, 2024, chapter on GBA functions, sub-section (2) 'Planning Functions', clause (c) (the section number is probably 14; this is only a location note): 'The State Government shall constitute the Bengaluru Metropolitan Planning Committee (BMPC)... The Bengaluru Metropolitan Planning Authority shall prepare a draft developm | N6: The Greater Bengaluru Governance Act, 2024 (Karnataka Act No. 36 of 2025), as enacted, PRS copy of the Gazette text (DPAL notification dated 24.04.2025) [ULG-01] | O6: https://prsindia.org/files/bills_acts/acts_states/karnataka/2025/Act36of2025KA.pdf | P6: The Chief Commissioner of the Greater Bengaluru Authority shall be its Member Secretary. The Bengaluru Metropolitan Planning Authority shall prepare a draft development plan for the Greater Bengaluru Area as a whole | Q6: Scored YES. Bengaluru is a metropolitan city. In the Greater Bengaluru Governance Act, 2024 (Karnataka Act 36 of 2025), the 'Planning Functions' sub-section, clause (2)(c), says the State Government 'shall constitute' the Bengaluru Metropolitan Planning Committee (BMPC). The BMPC covers an area 'including but not limited to the Greater Bengaluru Area', and its membership follows Article 243ZE. The same clause says a draft development plan for the Greater Bengaluru Area as a whole 'shall' be prepared. Both duties use 'shall', so this is a binding requirement for a metropolitan plan, not a 'may'. The methodology lets us count a metropolitan authority Act as evidence. Section 103(1)(b) of the same Act backs this up: Ward Development Plans must be drawn up 'in accordance with the plans prepared by the Bengaluru Metropolitan Planning Committee'. On the regional side, the official BMRDA Functions page (ULG-10) says the Authority's functions 'shall be' to 'prepare a structure plan' for the Bangalore Metropolitan Region. This is only the website's restatement of the BMRDA Act, 1985. The Act's own text is not in the Citation Sheet, so it is supporting evidence only. I checked the source against the Step 2 answer and it supports it. The YES rests on the GBA Act provision. Caveats for the reviewer: (1) Drafting mismatch: the clause sets up the 'BMPC' but gives the plan-preparing duty to the 'Bengaluru Metropolitan Planning Authority', a body the excerpt never creates. The duty is mandatory either way. A reviewer should check the official Gazette text, because ULG-01 is a PRS copy. (2) The mandated plan covers the Greater Bengaluru Area 'as a whole', not the wider BMRDA region. (3) I could not confirm the commencement date or the GBA era from the Sheet. (4) ULG-02 (KTCP Act) was not fully searched for a regional-plan chapter. This does not affect a YES that already rests on a binding provision. I scored only the Metropolitan/Regional sub-question (SQ, max 3.33).
A7: UPD3a | B7: Surat | C7: Does the Act require three levels of spatial plans for cities: Metropolitan/Regional, Municipal and Ward(s) /Local >:< Metropolitan/ Regional Plan | D7: =IFERROR(UPD3a!K33,"") | E7: 10 >:< 3.33 | H7: =IF(OR(F7="",NOT(ISNUMBER(D7))),"",IF(ABS(F7-D7)<0.001,"Yes","No")) | I7: =IF(ISNUMBER(F7),F7,D7) | J7: =IF(ISNUMBER(F7),"Expert (overrides AI)",IF(ISNUMBER(D7),"AI","Not scored yet")) -> Not scored yet | K7: Left for a person | L7: Partially Answered | M7: ANSWER: The sources show that Gujarat law provides for a metropolitan-level development plan covering Surat. The Gujarat Metropolitan Planning Committees Act, 2008 (MPC Act) plans for a draft development plan that the Metropolitan Planning Committee submits to the State Government. Once the State sanctions it, that plan binds every authority in the metropolitan area. However, the section of the MPC Act that actually requires ("shall") the Committee to prepare the plan is not in the Citation Sheet. The sheet only has the 2019 amending Act, which assumes such a plan will exist. So I cannot confirm that a metropolitan or regional plan is mandatory. | EVIDENCE: (1) Gujarat Act No. 14 of 2019 (Gujarat Local Authorities and Town Planning Laws (Amendment) Act, 2019), printed in the PRS copy of the Town Planning and Urban Development Act, 1976 (TPUD Act). Clause 9 adds new s.10A to the MPC Act: "The State Government may, on receipt of the draft development plan submitted by the Metropolitan Planning Committee... either (a) sanction or refuse to sanction... or (b) return the draft development plan to the metropolitan planning committee". s.10A(3): the final development plan "shall be binding on the concerned all authorities functioning in the metropolitan area". s.10C(3)(a): an officer appointed by the State shall "assist the metropolitan planning committee in the preparation of the development plan under the Act". These sections deal with sanctioning and assisting the plan. They do n | N7: The Gujarat Town Planning and Urban Development Act, 1976 (Act 27 of 1976), with amendments appended (PRS Legislative Research copy) [ULG-01] | O7: https://prsindia.org/files/bills_acts/acts_states/gujarat/1976/1976Gujarat27.pdf | P7: (a) assist the metropolitan planning committee in the preparation of the development plan under the Act; | Q7: The Answer is left blank because the Citation Sheet does not show whether a metropolitan plan is mandatory. A 'NO' would need affirmative absence, and that is not possible here. What the sources show: Gujarat law does provide for a metropolitan-level development plan. The 2019 amending Act (Guj. 14 of 2019) is appended to the PRS copy of the Gujarat Town Planning and Urban Development Act, 1976 (TPUD Act) in ULG-01. It inserts the following into the Gujarat Metropolitan Planning Committees Act, 2008 (MPC Act): - s.10A(1): the State Government 'may', on receipt of the draft development plan submitted by the Metropolitan Planning Committee, sanction it, refuse it, or return it. - s.10A(3): the final plan 'shall be binding on the concerned all authorities functioning in the metropolitan area'. - s.10C(3)(a): a State-appointed officer shall assist the Committee 'in the preparation of the development plan under the Act'. The same Act also amends the TPUD Act. It adds a proviso to s.9(1) and a new s.19A, which say the local development plan 'shall include' the spatial proposals of the sanctioned MPC plan. These provisions only cover sanctioning (and s.10A(1) uses 'may'), the plan's binding effect, and help with preparing it. They assume a metropolitan plan will exist. None of them is itself a 'shall prepare' duty. The provision that would decide this question is not in the Citation Sheet: the MPC Act, 2008's own section requiring the Committee to prepare a draft development plan for the metropolitan area. What I checked: - ULG-01: appended amendments only. The main TPUD Act text could not be found in what I could read, and searches turned up no regional plan provision. - ULG-02: the 2019 Bill, with the same wording. - ULG-03: the GPMC Act, 1949. It covers re-development plans only. - ULG-04: the TPUD Rules, 1979. They cover the authority's development plan, not a metropolitan or regional plan. - ULG-05/14/15/16: the CGDCR 2017. - ULG-06: SUDA DP 2035. This is context only. It says the Surat Metropolitan area was declared under the MPC Act on 11/03/2016, and that as of 2017 the MPC development plan was 'not in place'. - ULG-09: the NITI Aayog plan, which is non-statutory. - Searches for 'regional plan' and 'Metropolitan Planning Committee shall prepare draft development plan' found no mandate. Other caveats: - The 2019 Act comes into force on a date the State notifies, and no commencement notification is in the sheet. - ULG-01 is a secondary PRS republication. ACTION: The research team should add the official text of the Gujarat MPC Act, 2008 (Guj. 18 of 2008) and check whether it says the MPC 'shall' prepare a draft development plan for the metropolitan area. If it does, and Surat's declared metropolitan area falls under it, 'YES' would likely be right. Otherwise this needs checking against the full TPUD Act text for any regional plan mandate. | R7: The citation didn't settle every input. "Answer" left blank: the Citation Sheet doesn't decide it.
A8: UPD3b | B8: Bangalore | C8: Does the Act require three levels of spatial plans for cities: Metropolitan/Regional, Municipal and Ward(s) /Local >:< Municipal/city plan | D8: =IFERROR(UPD3b!K14,"") -> 3.33 | E8: 10 >:< 3.33 | H8: =IF(OR(F8="",NOT(ISNUMBER(D8))),"",IF(ABS(F8-D8)<0.001,"Yes","No")) | I8: =IF(ISNUMBER(F8),F8,D8) -> 3.33 | J8: =IF(ISNUMBER(F8),"Expert (overrides AI)",IF(ISNUMBER(D8),"AI","Not scored yet")) -> AI | K8: Scored by AI | L8: Answered — Verified Source | M8: ANSWER: Yes. Section 9(1) of the Karnataka Town and Country Planning Act, 1961 says every planning authority 'shall' prepare and publish a master plan for its area. This is the city-level spatial plan. The deadline is two years from the date the local planning area is declared, and the plan goes to the State Government, through the Director, for provisional approval. If the authority misses the deadline, s.9(2) lets the State authorise the Director to prepare the plan and recover the cost from the authority. So the plan is required whoever the planning authority is. For Bengaluru, the Greater Bengaluru Governance Act, 2024 names the Greater Bengaluru Authority (GBA) as that planning authority for the Greater Bengaluru Area. Before that, KTCP s.81-B and BDA Act s.67 named the Bangalore Development Authority (BDA). The State approves the plan; the city body prepares it. | EVIDENCE: (1) KTCP Act (PRS compilation, amended up to Act 38 of 2015). s.2(3-b), inserted by Act 1 of 2005, defines a master plan as 'a plan for the development or re-development of the area within the jurisdiction of a planning authority'. s.9(1), substituted w.e.f. 14.2.2005: 'Every planning authority shall, as soon as may be, carry out a survey ... and shall, not later than two years from the date of declaration of the local planning area, prepare and publish ... a master plan'. s.9(2) is the Director fallback. s.10(1): the planning authority 'shall' declare its intention to prepare the plan and invite pub | N8: The Karnataka Town and Country Planning Act, 1961 (Karnataka Act 11 of 1963), PRS compilation with amendments up to Act 38 of 2015 [ULG-02] | O8: https://prsindia.org/files/bills_acts/acts_states/karnataka/1963/1963KR11.pdf | P8: Every planning authority shall, as soon as may be, carry out a survey of the area within its jurisdiction and shall, not later than two years from the date of declaration of the local planning area, prepare and publish in the prescribed manner a master plan for such area and submit it to the State Government, through the Director, for provisional approval. | Q8: UPD3b asks whether the state planning law requires a municipal/city plan. The answer is YES. Section 9(1) of the Karnataka Town and Country Planning Act, 1961 (PRS compilation, amended up to Act 38 of 2015; s.9 is in its 2005 substituted form) says every planning authority 'shall' prepare and publish a master plan for its area within two years of the local planning area being declared. Section 2(3-b), inserted by Act 1 of 2005, defines a master plan as 'a plan for the development or re-development of the area within the jurisdiction of a planning authority'. That is the city-level spatial plan. Other provisions back this up: - s.9(2): if the planning authority misses the deadline, the State may authorise the Director to prepare the plan and recover the cost from the authority. - s.10(1): the authority 'shall' declare its intention to prepare the plan. - s.12: 'The Master Plan shall consist of' set contents, such as land-use zoning and the street pattern. - s.13-B: a master plan is also required for any area added to the authority's jurisdiction. So the plan is mandatory ('shall'), not discretionary ('may'). Revision under s.13-D is discretionary unless the State directs it, but that does not affect whether a city plan must exist. Applying this to Bengaluru: KTCP s.81-B (inserted by BDA Act s.67) names the Bangalore Development Authority (BDA) as the planning authority. The Greater Bengaluru Governance Act, 2024 (ULG-01, 'Planning Functions' provision) makes the Greater Bengaluru Authority (GBA) the 'Planning Authority' under KTCP for the Greater Bengaluru Area. I checked this against the Step 2 answer and the source text; I did not re-read ULG-01 here. The State approves the plan, but the planning authority must prepare it. What a person should check: - When the GBA designation took effect, and whether the KTCP Amendment Bill 2025 (ULG-03) was enacted. Neither changes the answer, because s.9 binds whichever body is the planning authority. - The text relied on is a PRS compilation, not the Gazette copy. - The planning authority (BDA, now GBA) is a development or metropolitan authority, not the municipal council itself. The methodology lets a development authority Act count as evidence, so this should not matter. One point for scoring: the sheet gives a max of 3.33 but no rubric bands, so YES is treated as full marks for this sub-question (3 x 3.33 for UPD3). The metropolitan and ward levels belong to UPD3a and UPD3c and are not assessed here.
A9: UPD3b | B9: Surat | C9: Does the Act require three levels of spatial plans for cities: Metropolitan/Regional, Municipal and Ward(s) /Local >:< Municipal/city plan | D9: =IFERROR(UPD3b!K33,"") -> 3.33 | E9: 10 >:< 3.33 | H9: =IF(OR(F9="",NOT(ISNUMBER(D9))),"",IF(ABS(F9-D9)<0.001,"Yes","No")) | I9: =IF(ISNUMBER(F9),F9,D9) -> 3.33 | J9: =IF(ISNUMBER(F9),"Expert (overrides AI)",IF(ISNUMBER(D9),"AI","Not scored yet")) -> AI | K9: Scored by AI | L9: Partially Answered | M9: ANSWER: Very likely yes, but this is not confirmed from the operative text of the Act. The Gujarat Town Planning and Urban Development Act, 1976 (GTPUD Act) and its 1979 Rules set up a mandatory development plan, which works as the city's master plan for Surat. Surat Urban Development Authority (SUDA) prepares it for an area that includes Surat Municipal Corporation (SMC), and the State Government sanctions it. SMC itself does not prepare or approve the city-wide plan. Several 'shall' provisions require this plan, but the wording of the mandate in Act s.9(1) (whether it says 'shall', and any deadline) and in s.21 (revision) is not in the Citation Sheet text I could read. | EVIDENCE: (1) GTPUD Rules, 1979 (ULG-04): r.3 says 'The authorized Officer shall prepare and submit the draft development plan after carrying out the survey of the area within the jurisdiction of the area development authority'. Under its heading, r.3 applies to the officer appointed under s.9(2). r.5(1) says the area development authority or authorized officer 'shall' publish the draft 'after a draft development plan is prepared and submitted to the State Government under section 9'. Form A refers to the authority having 'prepared and submitted a draft development plan... under section 9'. (2) GTPUD Act amendments appended to the PRS copy (ULG-01): Gujarat Act 14 of 2019 adds a proviso to s.9(1): 'the development plan shall include the proposals, with regard to spatial planning, of the development plan san | N9: Gujarat Bill No. 21 of 2019: The Gujarat Local Authorities and Town Planning Laws (Amendment) Bill, 2019 (Gujarat Government Gazette Extra No.21, Part V) [ULG-02] | O9: https://prsindia.org/files/bills_acts/bills_states/gujarat/2019/BillNo21of2019Gujarat.pdf | P9: Although all three Tp Act, Mpc Act & Dpc Aet mandates toprepare the development plans | Q9: I answered YES. This is the city/municipal-plan sub-question (SQ, max 3.33), which asks whether the T&CP Act requires a city plan; the methodology lets the development authority Act count as evidence. In Gujarat the GTPUD Act, 1976 is both the T&CP Act and the Urban Development Authority Act. Several instruments in the Citation Sheet, read together, support a mandatory development plan, which works as the city's master plan: (1) ULG-02 is the State Government's official Gazette text of the 2019 Bill. Its Statement of Objects and Reasons says the appropriate authorities under the TP Act 'are required to prepare the draft development plan'. It also says 'all three Tp Act, Mpc Act & Dpc Act mandates to prepare the development plans' (the quote above copies the source's OCR spelling exactly, e.g. 'Aet', 'toprepare'). (2) ULG-01 (PRS copy) shows the 2019 amendment Act adding a proviso to s.9(1): 'the development plan shall include the proposals, with regard to spatial planning...'. It also adds s.19A: 'the appropriate authority shall include in the development plan...'. Both treat the s.9 development plan as a required instrument. (3) ULG-04, the GTPUD Rules 1979, r.3: 'The authorized Officer shall prepare and submit the draft development plan after carrying out the survey of the area within the jurisdiction of the area development authority'. r.5(1) refers to the draft 'prepared and submitted to the State Government under section 9'. (4) ULG-06, SUDA's DP-2035 report, is a description of the law, not the law. It says the plan was submitted under s.9 and 'as per section 21 of the Act, the development plan is to be revised once in 10 years'. Plans came into force in 1986 and 2004, and the draft DP-2035 was submitted on 9-5-2016. I checked the Step 2 answer against these sources. It is right that the operative text of s.9(1) and s.21 is not readable in ULG-01: only the appended amendment Acts came back again when I re-read it. Things a person should check: (a) The 'shall' and any deadline in s.9(1), and the 10-year revision duty in s.21, are confirmed only indirectly. The evidence is the Government's own Statement of Objects and Reasons, the 2019 proviso and the Rules, not the operative section text. A reviewer may want the consolidated Act text. (b) The plan is prepared by the appropriate authority for its development area. For Surat that is SUDA, whose area includes the SMC area, and the State Government sanctions it. SMC (the ULG) does not itself prepare a city-wide plan. ULG-03, the GPMC Act s.284F, covers only re-development plans for declared areas. I scored YES because the methodology expressly allows evidence from the development authority Act; confirm the rubric accepts a SUDA plan covering the city as the 'municipal/city plan'. Confidence is medium because the answer rests on 2+ instruments read together and on the PRS copy.
A10: UPD3c | B10: Bangalore | C10: Does the Act require three levels of spatial plans for cities: Metropolitan/Regional, Municipal and Ward(s) /Local >:< Ward(s)/local plan | D10: =IFERROR(UPD3c!L14,"") | E10: 10 >:< 3.33 | H10: =IF(OR(F10="",NOT(ISNUMBER(D10))),"",IF(ABS(F10-D10)<0.001,"Yes","No")) | I10: =IF(ISNUMBER(F10),F10,D10) | J10: =IF(ISNUMBER(F10),"Expert (overrides AI)",IF(ISNUMBER(D10),"AI","Not scored yet")) -> Not scored yet | K10: Left for a person | L10: Partially Answered | M10: ANSWER: The Karnataka Town and Country Planning Act text in the Citation Sheet does not appear to require a third tier of plan at zone, ward or local-area level. Under the Act as amended, the statutory plan is the Master Plan for the whole local planning area (ss.9-13D). The Act's only plan below that level is the Town Planning Scheme (s.26), which is optional ('may') and implements the Master Plan, so the methodology excludes it. The city government's own law, the Greater Bengaluru Governance Act 2024 (s.103(1)(b)), requires an annual Ward Development Plan. That plan is a ward budget and priority list of projects, not a spatial plan, and it sits in the municipal law, not the T&CP Act. So it does not count as a zonal/ward/local area plan mandate. Because some layers of the law are missing from the sheet, this is recorded as 'not found', not as a confirmed absence. | EVIDENCE: (1) KTCP Act 1961, PRS compilation, 2005 amending Act s.4 (new s.9(1)): 'Every planning authority shall ... prepare and publish in the prescribed manner a master plan for such area'. s.2(3-b): Master Plan 'means a plan for the development or re-development of the area within the jurisdiction of a planning authority'. s.12(1): the Master Plan covers 'the entire planning area' and includes 'zoning of land use ... together with Zoning Regulations'. These are zoning regulations inside the Master Plan, not separate zonal plans. The Outline Development Plan and Comprehensive Development Plan tiers (ss.19-23, 2 | N10: The Karnataka Town and Country Planning Act, 1961 (Karnataka Act 11 of 1963), PRS compilation with amendments up to Act 38 of 2015 [ULG-02] | O10: https://prsindia.org/files/bills_acts/acts_states/karnataka/1963/1963KR11.pdf | P10: Every planning authority shall, as soon as may be, carry out a survey of the area within its jurisdiction and shall, not later than two years from the date of declaration of the local planning area, prepare and publish in the prescribed manner a master plan for such area and submit it to the State Government, through the Director, for provisional approval. | Q10: I have left 'Answer' blank because the evidence shows no ward or local plan in the Act text, but it does not prove one is absent from every layer of the law. A NO would score 0, and that needs every relevant instrument to have been read. The KTCP Rules, the official gazette copy and any amendments made between 2020 and 2025 are not in the Citation Sheet. My provisional finding is NO. If a reviewer confirms those missing layers add nothing, the Answer should be NO. What I checked in ULG-02 (the KTCP Act 1961, a PRS secondary copy with amending Acts up to 2015 and the 2020 amendment appended): (1) The list of sections and Chapter III. Act 1 of 2005 replaced the Outline Development Plan and the Comprehensive Development Plan with a single Master Plan for 'such area', meaning the whole local planning area (s.9(1), which says 'shall'). That Act also deleted ss.19-23 and 25. (2) s.12(1). The Master Plan covers 'the entire planning area' and includes 'zoning of land use ... together with Zoning Regulations'. These are land-use zones inside the one plan, not a separate zonal plan level. (3) s.13-A. The Interim Master Plan is a stop-gap Master Plan, not a lower level of plan. (4) s.26(1). A Planning Authority 'may' make town planning schemes to carry out the Master Plan. This is optional, and the methodology excludes TPSs anyway. (5) The Act provides for no zonal, ward or local area plan. Nothing in the metropolitan, municipal and ward set of three levels appears as a requirement. I also read ULG-03, the KTCP and certain other laws (Amendment) Bill 2025. It only makes the GBA the planning authority for the Greater Bengaluru Area, sets up a Commissionerate and adds s.81-G. It adds no plan level. The Ward Development Plans in the city government's own laws (GBA Act 2024 s.103(1)(b), ULG-01; BBMP Act 2020 s.2(65), ULG-19) are in municipal law, not the T&CP Act. Under the GBA Act it is an annual priority list for allocating funds, so it does not count as a T&CP ward plan. Still missing: the KTCP plan-preparation Rules, an official or current consolidated text of the Act (only the PRS copy is in the sheet), and any amendments between 2020 and 2025. Scorers' note: no zonal, ward or local-area plan requirement was found in the KTCP Act. The only plan below the Master Plan is the optional Town Planning Scheme, which is excluded. | R10: The citation didn't settle every input. "Answer" left blank: the Citation Sheet doesn't decide it.
A11: UPD3c | B11: Surat | C11: Does the Act require three levels of spatial plans for cities: Metropolitan/Regional, Municipal and Ward(s) /Local >:< Ward(s)/local plan | D11: =IFERROR(UPD3c!L33,"") | E11: 10 >:< 3.33 | H11: =IF(OR(F11="",NOT(ISNUMBER(D11))),"",IF(ABS(F11-D11)<0.001,"Yes","No")) | I11: =IF(ISNUMBER(F11),F11,D11) | J11: =IF(ISNUMBER(F11),"Expert (overrides AI)",IF(ISNUMBER(D11),"AI","Not scored yet")) -> Not scored yet | K11: Left for a person | L11: Partially Answered | M11: ANSWER: I can't tell from the Citation Sheet whether Gujarat's planning law requires a zone- or ward-level plan. The Gujarat Town Planning and Urban Development (GTPUD) Act, 1976, as amended in 2017, does create a 'Local Area Plan' (LAP). It adds LAPs to the functions of area and urban development authorities, and the State Government sanctions them under section 76A. But the operative text of s.76A(1)-(6) is not in the Sheet. That is the part that would say who must prepare an LAP, for which areas, and whether it is 'shall' or 'may'. Nothing seen ties LAPs to zones or wards. The mandate type found is a 'Local Area Plan' (an area/zone-specific plan), not a ward plan. | EVIDENCE: (1) GTPUD Act, 2017 amendment (Gazette Ex. 13-04-2017, in ULG-01 p.90): in s.7(1)(ii) for area development authorities and s.23(1)(ii) for urban development authorities (SUDA is constituted under this Act), the words "or Local Area Plan" are inserted after "town planning schemes". The original wording of those clauses was not seen, so I can't tell whether this is a duty or a power. The same amendment adds s.76A(7)-(8), p.90-91: "Where the State Government sanctions the Local Area Plan under clause (a) of sub-section (6), it shall state in the notification" where the plan can be inspected and when its liabilities come into force; (8) covers eviction and enforcement. These show state sanction, but not a duty to prepare. (2) Gujarat Local Authorities and Town Planning Laws (Amendment) Act, 2019 (ULG-01 p | N11: The Gujarat Town Planning and Urban Development Act, 1976 (Act 27 of 1976), with amendments appended (PRS Legislative Research copy) [ULG-01] | O11: https://prsindia.org/files/bills_acts/acts_states/gujarat/1976/1976Gujarat27.pdf | P11: in sub-section (1), in clause (ii), after the words "town planning schemes", the words "or Local Area Plan" shall be inserted; | Q11: I left the Answer blank because the Citation Sheet does not contain the provision that would decide it. 1) What the evidence shows. The 2017 amendment to the GTPUD Act (ULG-01, pp. 90-91) adds the words 'or Local Area Plan' after 'town planning schemes' in s.7(1)(ii) and s.23(1)(ii). Those clauses list the functions of area and urban development authorities. The amendment also adds s.76A(7)-(8). Under these, when the State Government sanctions a Local Area Plan (LAP) under s.76A(6)(a), it must say where the plan can be inspected and when its liabilities take effect; (8) covers eviction and enforcement. So the T&CP Act does recognise a sub-development-plan instrument, the LAP. 2) What is missing. The text of s.76A(1)-(6) is not in the Sheet. That is the part that would say who prepares an LAP, for which areas, and whether preparation is mandatory ('shall') or optional ('may'). I searched ULG-01 three times for it, and also searched the whole Sheet, and could not find it. The original wording of s.7(1)(ii) and s.23(1)(ii) is not available either, so I cannot tell whether the authority must do these things or only may. 3) Why not YES. Being listed as a function, plus State sanction under s.76A(6)-(7), shows that LAPs exist. It does not show a mandate for a third tier of plan at zone or ward level. Nothing I saw ties LAPs to zones or wards, or requires them across the whole city. 4) Why not NO. A NO needs affirmative absence, and the decisive section is unread. 5) Other sources checked: - 2019 Amendment Act (ULG-01, pp. 93-98; ULG-02 is its Bill): links the development plan to the Metropolitan and District Planning Committee plans (s.19A; s.10A-10C of those Acts). These are upper tiers only. - GTPUD Rules, 1979 (ULG-04): written before LAPs existed. No LAP or zonal-plan rule seen. - CGDCR 2017 (ULG-05/14), reg. 2.66: defines an LAP as 'a plan prepared for a specific area or a zone by the competent authority'. The LAP mandates for the CBD and transit-oriented zones apply to AUDA only. In any case these are regulations, not the Act. - Gujarat Provincial Municipal Corporations Act s.284E-F (ULG-03): re-development plans, which the Corporation may make at its discretion. Not a third tier. - SUDA Development Plan 2035 (ULG-06): implemented through town planning (TP) schemes, which the methodology excludes. Plan type to note in comments: Local Area Plan (an area- or zone-specific plan prepared by the appropriate authority and sanctioned by the State under GTPUD s.76A). It is not a ward plan. For the reviewer: (a) Get GTPUD s.76A(1)-(6), inserted by a pre-2017 amendment, from the Gujarat Legislative and Parliamentary Affairs Department or the Urban Development and Urban Housing Department (UD&UHD), to confirm 'shall' versus 'may' and the area coverage. (b) Decide whether an LAP sanctioned by the State for a specific area counts as a 'zone/ward level' third tier under UPD3c. Version relied on: GTPUD Act as amended up to Gujarat Act 14 of 2019 (PRS copy). The Step 2 answer's description of the evidence matches the source. | R11: The citation didn't settle every input. "Answer" left blank: the Citation Sheet doesn't decide it.
A12: UPD4 | B12: Bangalore | C12: Is the planning boundary of the municipal/city plan aligned with political and administrative boundaries? | D12: =IFERROR('UPD4'!K14,"") -> 10 | E12: 10 | H12: =IF(OR(F12="",NOT(ISNUMBER(D12))),"",IF(ABS(F12-D12)<0.001,"Yes","No")) | I12: =IF(ISNUMBER(F12),F12,D12) -> 10 | J12: =IF(ISNUMBER(F12),"Expert (overrides AI)",IF(ISNUMBER(D12),"AI","Not scored yet")) -> AI | K12: Left for a person | L12: Partially Answered | M12: ANSWER: The Citation Sheet does not settle this. By law, the planning area should match the city government's area. Section 14(2)(a) of the Greater Bengaluru Governance Act makes the Greater Bengaluru Authority (GBA) the Planning Authority under the Karnataka Town and Country Planning (KTCP) Act for 'the areas comprising of the Greater Bengaluru Area'. Section 15(1) makes GBA responsible for the master plan of that same area. That area is also the GBA's own area and contains its City Corporations (s.4, s.5). Read together, these point to a planning area coterminous with the city government. But none of the documents the question says decide it are in the Sheet: no master plan in force for the GBA area, no notification declaring its planning area, no plan map, and no s.3 notification fixing the Greater Bengaluru Area. The only plan described is the Bangalore Development Authority's (BDA) Revised Master Plan 2015 (RMP 2015), and only in a secondary source. That plan covers the Bengaluru Metropolitan Area (BMA): BBMP plus 251 villages, about 1,294 sq km, which is larger than the BBMP area. Nothing in the Sheet shows whether those 251 villages are included whole or split. | EVIDENCE: (1) GBA Act 2024 (Karnataka Act 36 of 2025), city government's law: s.14(2)(a), GBA 'shall be the Planning Authority ... for the areas comprising of the Greater Bengaluru Area'. s.14(2)(d): development regulations 'shall be applied uniformly across the Greater Bengaluru Area'. s.15(1): GBA 'shall be | N12: The Greater Bengaluru Governance Act, 2024 (Karnataka Act No. 36 of 2025), as enacted, PRS copy of the Gazette text (DPAL notification dated 24.04.2025) [ULG-01] | O12: https://prsindia.org/files/bills_acts/acts_states/karnataka/2025/Act36of2025KA.pdf | P12: (a) the Greater Bengaluru Authority shall be the “Planning Authority” as defined under the Karnataka Town and Country Planning Act, 1961, for the areas comprising of the Greater Bengaluru Area; | Q12: I left the answer blank because the documents that decide this question are not in the Citation Sheet. The method says the primary source is the notification or text defining the planning area, plus the plan map. The Sheet has no master plan in force for Bengaluru, no notification declaring a planning area and no plan map. It also lacks the s.3 notification declaring the Greater Bengaluru Area and the s.7(3) final notification setting City Corporation boundaries. I checked the Step 2 answer against the sources and agree that it is only partly answered. What the law says: GBA Act 2024 s.14(2)(a) makes GBA the Planning Authority under the KTCP Act 'for the areas comprising of the Greater Bengaluru Area'. It applies 'notwithstanding anything contained in any other law'. s.15(1) makes GBA responsible for the master plan for that area, and that same area holds the City Corporations (s.4, s.5). Read together, the law points to a planning area that matches the city government's area. That would score YES (10). But this is the legal design only. It does not show where the boundary of the plan in force actually runs. Competing arrangement: - KTCP Act (ULG-02, PRS compilation to 2015) s.2(7)(a)(i) and s.81-B still make BDA the Planning Authority for the City of Bangalore. The same wording appears in BDA Act s.67 (ULG-04), whose 2026 amendment (Act 42 of 2026) changes only s.10 and s.38D, not planning jurisdiction. - The KTCP amendment Bill 2025 (ULG-03) would split planning between GBA (the Greater Bengaluru Area) and BDA (the BMA excluding the Greater Bengaluru Area). The Sheet does not show it was enacted or brought into force. - BCAP 2023 (ULG-16) is a secondary, BBMP-era source. It describes the BDA plan area (the BMA) as BBMP plus 251 villages, about 1,294 sq km. If BDA's RMP 2015 is still 'the city plan', the test is whether those 251 villages are included whole. The Sheet does not show the village list or a map. - GBA Act s.7(1) and the s.7(4) proviso allow parts of local bodies to be included. That concerns the outer boundary of the Greater Bengaluru Area, not proof that the plan boundary splits a unit. Why not NO: a NO (score 0) needs affirmative evidence that the boundary splits a unit, and there is none. Absence cannot be confirmed either, because the plan and notification are not in the Sheet. What I checked: ULG-01 (s.3, s.4, s.5, s.7, s.14(2), s.15, s.26), ULG-02, ULG-03, ULG-04 (s.67 and Act 42 of 2026), ULG-16 and ULG-20, plus a search of the whole Sheet for the local planning area, master plan and villages. A person needs to: (a) decide which plan is the operative municipal/city plan: BDA's RMP 2015 or a GBA master plan; (b) get the planning-area notification and map, or the RMP 2015 approval notification with its village list, and check the 251 villages are whole; (c) get the s.3 Greater Bengaluru Area notification; (d) confirm whether the KTCP amendment of 2025 has been enacted. | R12: The citation didn't settle every input. "Answer" left blank: the Citation Sheet doesn't decide it.
A13: UPD4 | B13: Surat | C13: Is the planning boundary of the municipal/city plan aligned with political and administrative boundaries? | D13: =IFERROR('UPD4'!K33,"") -> 0 | E13: 10 | H13: =IF(OR(F13="",NOT(ISNUMBER(D13))),"",IF(ABS(F13-D13)<0.001,"Yes","No")) | I13: =IF(ISNUMBER(F13),F13,D13) -> 0 | J13: =IF(ISNUMBER(F13),"Expert (overrides AI)",IF(ISNUMBER(D13),"AI","Not scored yet")) -> AI | K13: Left for a person | L13: Human Verification Required | M13: ANSWER: Probably not aligned, but this can't be scored on current evidence. The city plan for Surat is the Development Plan 2035 of the Surat Urban Development Authority (SUDA), a state development authority. SMC is the Surat Municipal Corporation. SUDA's February 2017 plan report defines the planning area in two ways that split existing units. First, it covers 'Surat Municipal Corporation (except Moje: Khajod)': Khajod village was moved to a separate Khajod Urban Development Authority, so part of the city government's own area sits outside the plan. Second, it includes 3 villages only in part (Velanja in Kamrej taluka; Sandhiyer and Paria in Olpad taluka). Both match the methodology's Score 0 condition ('planning boundary bisects the ULG or other administrative/local-government units'). However, the final plan was only sanctioned on 08.10.2020. The planning-area definition in that sanctioned plan, and the current SMC boundary, are not in the Citation Sheet. So the 2017 position can't be confirmed as the current one. | EVIDENCE: (1) ULG-06, SUDA DP 2035 report, 22.02.2017, ch.21.1 'Exclusion of villages' (p.216-217 of the report). The state used GTPUD Act s.22(2A) to split off SUDA's area and form Khajod UDA (notification GH/V/144 of 2016, 19.07.2016): 'Thus, Khajod village of Chorayasi Taluks was deleted from the jurisdiction of SUDA.' Notification GH/V/199 of 2016 (24.10.2016) took out 54 villages, '50 wholly and 4 partly'. Asnabad was corrected back in, leaving '53 village | R13: Step 2 found no evidence: a source needs to be found and added. Step 2 found no evidence (Human Verification Required). Source needed: The Gujarat UD&UHD notification sanctioning SUDA's Final Development Plan (GH/V/157 of 2020, dated 08.10.2020), with its schedule and plan map of the development area. The current s.22 notifications defining SUDA's development area, including whether Khajod is still outside SUDA and whether Velanja, Sandhiyer and Paria are still only partly included. The current SMC boundary notification.
A14: UPD5a | B14: Bangalore | C14: Is there a clear decentralised procedure for approvals of each level of plans? >:< Does the law mandate that the metropolitan/regional plan be approved by the state government? | D14: =IFERROR(UPD5a!K14,"") | E14: 10 >:< 3.33 | H14: =IF(OR(F14="",NOT(ISNUMBER(D14))),"",IF(ABS(F14-D14)<0.001,"Yes","No")) | I14: =IF(ISNUMBER(F14),F14,D14) | J14: =IF(ISNUMBER(F14),"Expert (overrides AI)",IF(ISNUMBER(D14),"AI","Not scored yet")) -> Not scored yet | K14: Left for a person | L14: Partially Answered | M14: ANSWER: Not determined from the Citation Sheet. The two metropolitan-planning provisions in the sheet do not say the state must approve the metropolitan plan. Under both, the Metropolitan Planning Committee prepares a draft development plan, and the older law says it is forwarded to the State Government. Approval is not mentioned. The Bengaluru Metropolitan Region Development Authority (BMRDA) Act, 1985 is the regional-planning law for the Revised Structure Plan 2031 (RSP 2031), but its text is not in the sheet. So whether state approval of the regional plan is mandatory cannot be confirmed or ruled out. | EVIDENCE: (1) Greater Bengaluru Governance (GBA) Act 2024 (Kar. Act 36 of 2025), the planning-functions sub-section (2)(c), within the section just before s.15: 'The State Government shall constitute the Bengaluru Metropolitan Planning Committee (BMPC)... The Bengaluru Metropolitan Planning Authority shall prepare a draft development plan for the Greater Bengaluru Area as a whole and discharge responsibilities as enshrined in Article 243ZE'. There is no state approval step. (2) BBMP Act 2020 s.367(6)-(8): the Metropolitan Planning Committee (MPC) 'shall prepare a draft development plan for the Bengaluru metropolitan area as a whole'; s.367(8) 'The Chairman of the Metropolitan Planning Committee shall forward the development plan, as recommended by such Committee, to the State Government'. The verb is 'forward', not 'approve'. The BBMP Act may have been superseded by the GBA | N14: The Bruhat Bengaluru Mahanagara Palike Act, 2020 (Karnataka Act No. 53 of 2020), PRS republished text with Amendments 1, 2 and 29 of 2022 [ULG-19] | O14: https://prsindia.org/files/bills_acts/acts_states/karnataka/2020/Act%2053%20of%202020%20Karnataka.pdf | P14: (8) The Chairman of the Metropolitan Planning Committee shall forward the development plan, as recommended by such Committee, to the State Government. | Q14: I left the Answer blank: the evidence is not found, not absent. The law that would decide this, the Bangalore Metropolitan Region Development Authority (BMRDA) Act 1985 and any rules made under it, is not in the Citation Sheet. That is the regional-planning law for the Structure Plan (Revised Structure Plan 2031). Without it I cannot answer YES, and I cannot show affirmative absence for a NO. What I checked: (1) ULG-19, BBMP Act 2020 s.367. Under s.367(6) the Metropolitan Planning Committee 'shall prepare a draft development plan'. Under s.367(8) the Chairman 'shall forward' the plan to the State Government. The verb is 'forward'. No approval by the state is stated, and this section may have been superseded by the GBA Act. (2) ULG-01, GBA Act 2024 (Kar. Act 36 of 2025), planning-functions clause (2)(c). It sets up the Bengaluru Metropolitan Planning Committee (BMPC), chaired by the Chief Minister, under Article 243ZE. The Committee prepares a draft development plan for the Greater Bengaluru Area. The text I read has no state-approval step. (3) ULG-02, KTCP Act 1961 (PRS text, amended to 2015). Sections 13 and 13-B require state approval of a Master Plan prepared by a local Planning Authority. That is a local plan, not a metropolitan or regional plan. My searches found no regional-plan approval provision in this Act. The Act was not read in full. (4) ULG-03, KTCP Amendment Bill 2025. This is a bill, not shown to be enacted. It changes which body is the planning authority (GBA or BDA) but has no regional-plan approval provision. (5) ULG-10, BMRDA Functions page. It lists the function 'to prepare a structure plan' and says nothing about approval. (6) ULG-18, BMLTA Act. Its state approval in s.21(4) covers only the Comprehensive Mobility Plan, which is not the metropolitan/regional plan. The Step 2 'Partially Answered / not determined' result holds up against the sources. For the reviewer: (a) Add the BMRDA Act 1985 sections on preparing and approving the Structure Plan, from an official Karnataka source, and any BMRDA rules. (b) Confirm which instrument counts as Bengaluru's 'metropolitan/regional plan'. (c) Check whether rules prescribe a BMPC procedure that includes state approval. | R14: The citation didn't settle every input. "Answer" left blank: the Citation Sheet doesn't decide it.
A15: UPD5a | B15: Surat | C15: Is there a clear decentralised procedure for approvals of each level of plans? >:< Does the law mandate that the metropolitan/regional plan be approved by the state government? | D15: =IFERROR(UPD5a!K33,"") -> 3.33 | E15: 10 >:< 3.33 | H15: =IF(OR(F15="",NOT(ISNUMBER(D15))),"",IF(ABS(F15-D15)<0.001,"Yes","No")) | I15: =IF(ISNUMBER(F15),F15,D15) -> 3.33 | J15: =IF(ISNUMBER(F15),"Expert (overrides AI)",IF(ISNUMBER(D15),"AI","Not scored yet")) -> AI | K15: Scored by AI | L15: Partially Answered | M15: ANSWER: Probably yes, but this is not confirmed. The amended Gujarat Metropolitan Planning Committees Act, 2008 (MPC Act) makes the State Government the only body that can sanction the metropolitan development plan. It can sanction it, refuse it or send it back for changes. The plan becomes the 'final development plan', binding on all authorities in the metropolitan area, only once the State sanctions it. However, the operative verb is 'may', not 'shall'. Also, nothing in the Citation Sheet shows that the 2019 amendment inserting this provision has come into force. | EVIDENCE: (1) MPC Act s.10A, inserted by clause 9 of the Gujarat Local Authorities and Town Planning Laws (Amendment) Act, 2019 (Gazette Ex. 19-08-2019, PRS copy ULG-01 p.97). s.10A(1): '(a) sanction or refuse to sanction the draft development plan ... or (b) return the draft development plan to the metropolitan planning committee or the authorized officer ... for modifying the plan as it may direct'. s.10A(2): 'The sanction accorded under clause (a) of sub section (1), shall be called the final development plan', which comes into force on the date the State notifies. s.10A(3): binding on 'all authorities functioning in the metropolitan area'. The opening words of MPC s.10A(1) are cut off in both copies. The Bill's Memorandum Regarding Delegated Legislation (ULG-02 p.9, clause 9) confirms that it 'empowers the State Government, by notification in the Official Gazette, either sanction or refuse to sanction the dra | N15: The Gujarat Town Planning and Urban Development Act, 1976 (Act 27 of 1976), with amendments appended (PRS Legislative Research copy) [ULG-01] | O15: https://prsindia.org/files/bills_acts/acts_states/gujarat/1976/1976Gujarat27.pdf | P15: (a) sanction or refuse to sanction the draft development plan so received for the whole of the area covered by the plan or separately for any part thereof, either without modification, or subject to such modification, as it may consider proper; or (b) return the draft development plan to the metropolitan planning committee or the authorized officer, as the case may be, for modifying the plan as it may direct. | Q15: Answer: YES, with low confidence and points for a person to check. (1) The metropolitan plan. MPC Act s.10A(1), inserted by Gujarat Act 14 of 2019, says: 'The State Government may, on receipt of the draft development plan submitted by the Metropolitan Planning Committee, by notification in the Official Gazette, either' (a) sanction or refuse to sanction it, or (b) return it for changes. The OCR of this opening line in ULG-01 p.97 is garbled but readable. Under s.10A(2), only the plan the State sanctions becomes the 'final development plan', and it comes into force on a date the State notifies. Under s.10A(3), only that plan binds all authorities in the metropolitan area. Variations also need State sanction (s.10B), and the State's decision on disputes is final (s.10C(2)). The word 'may' sets the State's choice of outcome: sanction, refuse or return. It does not make State approval optional. No other body can sanction the plan, and no plan becomes final without the State. So I read this as State approval being required by law. A person should confirm this reading of 'may'. (2) A second route via the development authority plan (GTPUD Act). If Surat's regional plan is taken to be the SUDA development plan, State approval is again required: - GTPUD Rules 1979 r.3 (ULG-04): the officer 'shall submit the same to the State Government through the Chief Town Planner'. - Rule 5 refers to the plan 'submitted to the State Government under section 9'. - Gazette Ex. No.124 of 24-03-2025 (ULG-17) shows the SUDA Final Development Plan 'was sanctioned under Government Notification ... dated 08.10.2020', and its variation is made by the State under GTPUD s.19(1). (3) Points to check: - (a) s.1(2) of the 2019 amending Act says it comes into force on a date the State notifies. No commencement notification is in the Citation Sheet, so it is not proven that MPC s.10A is in force. The GTPUD route in point 2 does not depend on this. - (b) The MPC amendment text exists only as a PRS republication (ULG-01, ULG-02), which is a secondary source. - (c) The GTPUD Act's own sanctioning section (s.17) and the original 2008 MPC Act text are not in the Citation Sheet. - (d) The Surat Metropolitan Area was declared under the MPC Act on 11/03/2016 (ULG-06). A person should confirm whether the MPC plan or the SUDA plan is the 'metropolitan/regional plan' for Surat. (4) Step 2 answer. I agree with its reading of the source. Its quote is accurate. Period: MPC Act as amended in 2019 (commencement not established); SUDA plan sanctioned 08.10.2020; variation notice 24-03-2025.
A16: UPD5b | B16: Bangalore | C16: Is there a clear decentralised procedure for approvals of each level of plans? >:< Does the law mandate that the municipal/city plan be approved by the MPC (Metropolitan Planning Committee) for metropolitan cities or by DPC (District Planning Committee) for non-metropolitan cities? | D16: =IFERROR(UPD5b!K14,"") | E16: 10 >:< 3.33 | H16: =IF(OR(F16="",NOT(ISNUMBER(D16))),"",IF(ABS(F16-D16)<0.001,"Yes","No")) | I16: =IF(ISNUMBER(F16),F16,D16) | J16: =IF(ISNUMBER(F16),"Expert (overrides AI)",IF(ISNUMBER(D16),"AI","Not scored yet")) -> Not scored yet | K16: Left for a person | L16: Partially Answered | M16: ANSWER: Probably not, but this is not confirmed. None of the laws in the Citation Sheet says the Metropolitan Planning Committee (MPC) must approve Bengaluru's city plan (the Master Plan). The Karnataka Town and Country Planning Act (KTCP Act) gives final approval of the Master Plan to the State Government. The Greater Bengaluru Governance Act makes the Greater Bengaluru Authority (GBA) the Planning Authority. It also sets up a Bengaluru Metropolitan Planning Committee (BMPC), but only to prepare a draft development plan for the whole area. It gives the BMPC no power to approve the GBA's Master Plan. | EVIDENCE: (1) KTCP Act 1961, PRS compilation with amendments up to Act 38 of 2015. s.9(1): the Planning Authority 'shall ... prepare and publish ... a master plan ... and submit it to the State Government, through the Director, for provisional approval'. s.13(1)-(3): the State Government may modify the plan and return it for public comments, then 'shall, in consultation with the Director, give its final approval to the plan'. s.13(4): the Planning Authority publishes the plan 'as finally approved by the State Government'. s.13-D: revisions follow the same steps in ss.9-12. The extracts read have no MPC or District Planning Committee step. (2) Greater Bengaluru Governance Act, 2024 (Karnataka Act 36 of 2025). s.14(2)(a): GBA 'shall be the "Planning Authority" as defined under the Karnataka Town and Country Planning Act, 1961' for the Greater Bengaluru Area. s.14(2)(c): the State | N16: The Karnataka Town and Country Planning Act, 1961 (Karnataka Act 11 of 1963), PRS compilation with amendments up to Act 38 of 2015 [ULG-02] | O16: https://prsindia.org/files/bills_acts/acts_states/karnataka/1963/1963KR11.pdf | P16: The State Government, after receiving the plan and the reports and the recommendations for modifications from the Planning Authority, shall, in consultation with the Director, give its final approval to the plan and the reports with such modifications as the Director may advice in the light of the comments and the recommendations of the Planning authority or otherwise. | Q16: I left 'Answer' blank. The evidence strongly points to NO, but a NO scores 0, and a 0 needs proof that every legal layer was checked and found silent. The Citation Sheet does not let me show that. What the sources say: (1) KTCP Act 1961 (ULG-02, PRS compilation, amendments up to Act 38 of 2015). Under s.9(1) the Planning Authority 'shall' send the master plan 'to the State Government, through the Director, for provisional approval'. Under s.13(3) the State Government 'shall... give its final approval'. Under s.13(4) the plan is published 'as finally approved by the State Government'. Under s.81-C, plans in the Bangalore Metropolitan Region go 'to the State Government through the Bangalore Metropolitan Region Development Authority for approval'. BMRDA is a development authority, not the Metropolitan Planning Committee (MPC). None of the text I read has an MPC or District Planning Committee approval step. (2) GBA Act 2024 (ULG-01). Under s.14(2)(a) GBA is the Planning Authority under the KTCP Act. Under s.14(2)(c) the State 'shall constitute' the BMPC. The Act then says the 'Bengaluru Metropolitan Planning Authority shall prepare a draft development plan for the Greater Bengaluru Area as a whole' (wording exactly as written). That is a power to prepare, not to approve the GBA Master Plan. Under s.15(1) GBA 'shall be responsible to make master plan'. Under s.103(1)(b) ward plans must conform to BMPC plans, which is not an approval power. (3) KTCP Amendment Bill 2025 (ULG-03, passed by the Assembly; enactment not shown). It adds s.81-G (GBA as local planning authority) and the Commissionerate. It does not change s.13 and adds no MPC approval. (4) GBA (Amendment) Bill 2025 (ULG-05) only amends ss.8 and 14(1). No planning-approval change. Bengaluru is a metropolitan city, so the methodology's 'approval by the State' fallback does not apply. Approval by the State would mean NO. Why blank, not NO: the Citation Sheet does not contain the KTCP Rules, a consolidated KTCP text with amendments after 2015 (2016–2024), any rules or notification under GBA s.14(2)(c) setting BMPC functions, or the BMRDA Act 1985. Without these, the absence of an MPC approval step cannot be confirmed across every layer. Action for the research team: add these instruments. If none of them requires MPC or BMPC approval of the GBA Master Plan, enter NO (score 0). | R16: The citation didn't settle every input. "Answer" left blank: the Citation Sheet doesn't decide it.
A17: UPD5b | B17: Surat | C17: Is there a clear decentralised procedure for approvals of each level of plans? >:< Does the law mandate that the municipal/city plan be approved by the MPC (Metropolitan Planning Committee) for metropolitan cities or by DPC (District Planning Committee) for non-metropolitan cities? | D17: =IFERROR(UPD5b!K33,"") | E17: 10 >:< 3.33 | H17: =IF(OR(F17="",NOT(ISNUMBER(D17))),"",IF(ABS(F17-D17)<0.001,"Yes","No")) | I17: =IF(ISNUMBER(F17),F17,D17) | J17: =IF(ISNUMBER(F17),"Expert (overrides AI)",IF(ISNUMBER(D17),"AI","Not scored yet")) -> Not scored yet | K17: Left for a person | L17: Human Verification Required | M17: ANSWER: Probably not, but this cannot be confirmed. Nothing found in the Citation Sheet says the Surat city/municipal plan must be approved by the Surat Metropolitan Planning Committee (MPC). What the sources show is approval by the State Government. (1) The development plan under the Gujarat Town Planning and Urban Development Act, 1976 (GTPUDA) is sanctioned by the State Government. For the Surat Municipal Corporation (SMC) area, that plan is prepared by the Surat Urban Development Authority (SUDA), not by the city government. (2) The MPC's own metropolitan development plan is also sanctioned by the State Government. (3) The link between the two plans runs the other way: the GTPUDA plan must take in the spatial proposals of the plan sanctioned under the MPC Act. The MPC does not approve the city plan. | EVIDENCE: (a) GTPUDA 1976 as amended in 2019 (ULG-01, pp.94-97, Amendment Act 2019 in Gazette Ex. 19-08-2019). New proviso to s.9(1): the development plan 'shall include the proposals, with regard to spatial planning, of the development plan sanctioned under the Gujarat Metropolitan Planning Committees Act, 2008'. New s.19A: 'the appropriate authority shall include in the development plan ... the proposals with regard to spatial planning, of the development plan to which sanction is accorded under ... section 10A of the Gujarat Metropolitan Planning Committees Act, 2008'. The 2019 amendment also deleted from s.12(1) the words 'which would be in conformity with the developmen | R17: Step 2 found no evidence: a source needs to be found and added. Step 2 found no evidence (Human Verification Required). Source needed: The full consolidated text of the Gujarat Metropolitan Planning Committees Act, 2008 (Guj. 18 of 2008), especially its MPC functions and plan-preparation sections. Also the readable original text of GTPUDA 1976 ss.9-17 (preparation, submission and sanction of the development plan). Both are needed to confirm that no provision requires MPC approval of the city/municipal plan, before a 0 can be scored.
A18: UPD5c | B18: Bangalore | C18: Is there a clear decentralised procedure for approvals of each level of plans? >:< Does the law mandate that the ward(s)/local plan be approved by the ULG? | D18: =IFERROR(UPD5c!K14,"") | E18: 10 >:< 3.33 | H18: =IF(OR(F18="",NOT(ISNUMBER(D18))),"",IF(ABS(F18-D18)<0.001,"Yes","No")) | I18: =IF(ISNUMBER(F18),F18,D18) | J18: =IF(ISNUMBER(F18),"Expert (overrides AI)",IF(ISNUMBER(D18),"AI","Not scored yet")) -> Not scored yet | K18: Left for a person | L18: Partially Answered | M18: ANSWER: Probably not, but this is not confirmed. The Karnataka Town and Country Planning (KTCP) Act text I could read provides for no zonal or ward plan that the city government approves. The only local-level plan in the Act is the town planning scheme. The Planning Authority prepares it and the State Government sanctions it. The city-wide Master Plan is also finally approved by the State Government. The Greater Bengaluru Authority (GBA) is made the KTCP 'Planning Authority' for the Greater Bengaluru Area. That makes it the body that prepares plans, not the body that approves them. The Greater Bengaluru Governance (GBG) Act does have a 'Ward Development Plan', which the Ward Committee submits to the City Corporation. But that plan is a yearly priority list of projects for allotting funds, not a statutory zonal or ward land-use plan. The provision also says 'submit … for allotment of funds', not 'approve'. I cannot give a confirmed 'No' (score 0) because the KTCP Rules and the zoning regulations are not in the Citation Sheet, and the full Acts could not be searched for 'local area plan' or 'zonal plan'. | EVIDENCE: (1) KTCP Act, s.34(1)-(3): the Planning Authority considers objections and submits the draft town planning scheme 'to the State Government through the Director and shall at the same time apply for its sanction'. The State Government 'may by notification … either sanction such scheme with or without modifications … or refuse to give sanction'. (2) KTCP Act, s.9(1): t | N18: The Karnataka Town and Country Planning Act, 1961 (Karnataka Act 11 of 1963), PRS compilation with amendments up to Act 38 of 2015 [ULG-02] | O18: https://prsindia.org/files/bills_acts/acts_states/karnataka/1963/1963KR11.pdf | P18: After receiving such application and after making such inquiry as it may think fit, the State Government, in consultation with the Director, may by notification, within six months from the date of its submission, either sanction such scheme with or without modifications and subject to such conditions as it may think fit to impose, or refuse to give sanction. | Q18: I left Answer blank because the Citation Sheet does not show the provision is absent. The evidence points toward NO. What the Karnataka Town and Country Planning (KTCP) Act (ULG-02, PRS compilation to Act 38 of 2015) says: - The only local-level plan in the Act text read is the town planning scheme. Under s.34(2)-(3) the Planning Authority submits it and the State Government sanctions it. Under s.45(1) the State also sanctions the final scheme. - The Master Plan gets final approval from the State Government (s.13(3)). - An Interim Master Plan, even for 'any part' of the area, follows the same s.13 State approval route (s.13-A(1)). - A Master Plan for an additional area also goes to the State for sanction (s.13-B). - I found no zonal, ward or local area plan in the Act that the city government approves. Other instruments checked: - **KTCP Amendment Bill, 2025 (ULG-03):** it makes the Greater Bengaluru Authority (GBA) the Planning Authority (s.2(7)(a)(i), new s.81-G) and adds a Commissionerate. It contains no ward or zonal plan approved by the city government. It is also a Bill whose commencement is still to be notified. - **Greater Bengaluru Governance (GBG) Act, 2024 (ULG-01), Planning Functions (2)(a)-(c):** the GBA is the KTCP Planning Authority, which prepares plans and does not approve them. The Bengaluru Metropolitan Planning Committee (BMPC), chaired by the Chief Minister, prepares the draft development plan for the area as a whole. - **GBG Act s.2(79) 'Ward development plan':** this is a budget plan 'prepared by the Ward Committee for the allotment of budget to it by the City Corporation'. It is not a statutory spatial ward or zonal plan. The law also says 'submit', not 'approve'. - **GBG Act, Ward Action Plan and s.279 Ward Micro Plan:** these are solid waste management plans, not spatial plans. Why NO cannot be entered (no affirmative absence): the KTCP Rules, the zoning regulations for the Greater Bengaluru Area and any planning rules under the GBG Act are not in the Citation Sheet. I also saw the KTCP Act only as excerpts, so I could not search its full text for 'zonal plan' or 'local area plan'. For the reviewer: 1. If you accept that the scope is the T&CP Act alone, the provisions read support NO. Every plan type there is approved by the State Government, not the city government. 2. Confirm that the GBG Act's budget-type Ward Development Plan should not count as a 'ward plan'. Period: KTCP Act as amended to 2015; GBG Act as enacted (notification of 24.04.2025), GBA era. | R18: The citation didn't settle every input. "Answer" left blank: the Citation Sheet doesn't decide it.
A19: UPD5c | B19: Surat | C19: Is there a clear decentralised procedure for approvals of each level of plans? >:< Does the law mandate that the ward(s)/local plan be approved by the ULG? | D19: =IFERROR(UPD5c!K33,"") | E19: 10 >:< 3.33 | H19: =IF(OR(F19="",NOT(ISNUMBER(D19))),"",IF(ABS(F19-D19)<0.001,"Yes","No")) | I19: =IF(ISNUMBER(F19),F19,D19) | J19: =IF(ISNUMBER(F19),"Expert (overrides AI)",IF(ISNUMBER(D19),"AI","Not scored yet")) -> Not scored yet | K19: Left for a person | L19: Partially Answered | M19: ANSWER: No, as far as the Gujarat law in the Citation Sheet shows. The planning law gives final approval of local plans to the State Government, not to Surat's city government (ULG). Local Area Plans are sanctioned by the State Government by notification in the Official Gazette. Draft Town Planning Schemes are sanctioned under s.48(2) 'in line with the notification of the Government'. I found no provision that requires the ULG (Surat Municipal Corporation, from its name in the DP-2035 report) to approve a ward, zonal or local plan as the approving body. However, I could not read every relevant provision, so I have not proposed a 0. | EVIDENCE: (1) Gujarat Town Planning and Urban Development (GTPUD) Act 1976 (ULG-01, PRS copy, as amended): s.76A(7), added by the amendment published in the Gujarat Gazette Ex. of 13-04-2017, reads: 'Where the State Government sanctions the Local Area Plan under clause (a) of sub-section (6), it shall state in the notification-' the place of public inspection and the date the plan comes into force. The same amendment added 'or Local Area Plan' to ss.7(1)(ii) and 23(1)(ii), the functions of area and urban development authorities. It also replaced ss.7(2) and 23(2): the State Government 'may' delegate an authority's powers to a local authority. That is a discretionary delegation, not a requirement for ULG approval. It also added a proviso to s.49(1)(b) referring to the 'Draft Town Planning Scheme sanctioned under sub-section (2) of section 48 and i | N19: The Gujarat Town Planning and Urban Development Act, 1976 (Act 27 of 1976), with amendments appended (PRS Legislative Research copy) [ULG-01] | O19: https://prsindia.org/files/bills_acts/acts_states/gujarat/1976/1976Gujarat27.pdf | P19: Where the State Government sanctions the Local Area Plan under clause (a) of sub-section (6), it shall state in the notification- | Q19: I left the Answer blank. Every source I could read says the State Government, not Surat Municipal Corporation (SMC), gives final approval to local plans. That points to NO, but I could not show affirmative absence, so a NO cannot be entered yet. What the sources show: (1) GTPUD Act s.76A(7), inserted in 2017 (ULG-01, p.90-91): Local Area Plans are sanctioned by the State Government under s.76A(6)(a), by notification. The same amendment adds a proviso to s.49(1)(b) that refers to a 'Draft Town Planning Scheme sanctioned under sub-section (2) of section 48 and in line with the notification of the Government'. The amended ss.7(2) and 23(2) say the State 'may' delegate a development authority's powers to the local authority. That is optional, not a requirement for SMC approval. (2) GTPUD Rules 1979 (ULG-04): rules 16-18 give SMC, as the 'appropriate authority', the job of passing the resolution declaring a scheme (s.41) and of making and publishing the draft scheme (s.42). Rule 36(2) has the State Government sanction amendments to scheme regulations. I found no rule that makes SMC the approving body. (3) DP-2035 report (ULG-06, p.44): 'draft schemes of SMC were sanctioned by the State Government in March, 2016'. (4) CGDCR Part II (ULG-15): the authority prepares local area plans 'and seek approval of it from the government'. (5) Municipal Act s.284F (GPMC Act, ULG-03): the Commissioner prepares a re-development plan 'with the approval of the Corporation'. It goes 'first to the Corporation and then to the State Government for approval'. The Corporation's approval is a middle step for a special re-development area, the State gives final approval, and the provision is in the Municipal Act, not the planning Act the method names. A reviewer should still decide whether ASICS counts it. Why no NO: the text of GTPUD s.76A(1)-(6) (how Local Area Plans are prepared and processed) and ss.41-48 (how Town Planning Schemes are declared, made and sanctioned) could not be found in ULG-01. Repeated reads of the PRS copy returned only the amendment Acts appended at the end. So I cannot rule out a step in the Act where the ULG must approve a plan. Under the affirmative-absence rule, a NO, which scores 0, cannot be entered yet. The Step 2 answer is consistent with what the sources say. REVIEWER: read GTPUD s.76A(1)-(6) and ss.41-48 in full. If they confirm that the State sanctions and that SMC only declares, prepares and submits, enter NO. Versions read: GTPUD Act as amended in 2017 and by Gujarat Act 14 of 2019; GTPUD Rules 1979; GPMC Act as modified up to 30-11-2017; CGDCR notified 12-10-2017. | R19: The citation didn't settle every input. "Answer" left blank: the Citation Sheet doesn't decide it.
A20: UPD6 | B20: Bangalore | C20: Does the Act clearly define the objectives/contents of each level of spatial plan? | D20: =IFERROR('UPD6'!M14,"") | E20: 10 | H20: =IF(OR(F20="",NOT(ISNUMBER(D20))),"",IF(ABS(F20-D20)<0.001,"Yes","No")) | I20: =IF(ISNUMBER(F20),F20,D20) | J20: =IF(ISNUMBER(F20),"Expert (overrides AI)",IF(ISNUMBER(D20),"AI","Not scored yet")) -> Not scored yet | K20: Left for a person | L20: Partially Answered | M20: ANSWER: Only partly. The Karnataka Town and Country Planning Act, 1961 (KTCP Act), in the PRS compilation amended up to Act 38 of 2015, sets out both the purpose and the contents of the city-level Master Plan in Section 12. For Town Planning Schemes, which are local-level plans, it gives a purpose and a list of contents in Section 26, but the wording is discretionary ('may make provisions for any of the following'). Nothing in the Act's Arrangement of Sections deals with a metropolitan or regional plan, so the Act as compiled does not define that level. Whether a Town Planning Scheme counts as the methodology's 'ward(s)/local plan' needs to be confirmed. | EVIDENCE: (1) Metropolitan/regional plan: the KTCP Act's Arrangement of Sections (Chapters I to XI: present land use, master plan, enforcement, town planning schemes, town planning officer, finance, land acquisition and others) has no regional or metropolitan plan chapter. Outside the KTCP Act, the Greater Bengaluru Governance Act, 2024, at the planning-functions provision (s.14(2)(c), section number is a location note only), says the State shall set up the Bengaluru Metropolitan Planning Committee (BMPC). That provision also says the 'Bengaluru Metropolitan Planning Authority shall prepare a draft development plan for the Greater Bengaluru Area as a whole and discharge responsibilities as enshrined in Article 243ZE'. It only points to Article 243ZE and lists no objectives or contents, and in any case it is not part of the | N20: The Karnataka Town and Country Planning Act, 1961 (Karnataka Act 11 of 1963), PRS compilation with amendments up to Act 38 of 2015 [ULG-02] | O20: https://prsindia.org/files/bills_acts/acts_states/karnataka/1963/1963KR11.pdf | P20: The Master Plan shall consist of a series of maps and documents indicating the manner in which the development and improvement of the entire planning area within the jurisdiction of the Planning Authority are to be carried out and regulated, such plan shall include proposals for the following, namely:- | Q20: Source: KTCP Act 1961, PRS compilation amended up to Act 38 of 2015 (a secondary copy). The Greater Bengaluru Authority (GBA) is the Planning Authority for the Greater Bengaluru Area: GBG Act s.14(2)(a) in ULG-01, and the proposed s.81-G in the 2025 Amendment Bill (ULG-03). Inputs, one by one. (1) MUNICIPAL/CITY = YES. s.12(1) sets the objective: maps and documents showing how 'the development and improvement of the entire planning area ... are to be carried out and regulated'. It also lists mandatory contents ('shall include proposals for' items (a) to (g)): land-use zoning with Zoning Regulations, street pattern and traffic circulation, parks, open spaces and public buildings, future expansion areas, reservations and land for acquisition, areas of special control, and stages of implementation. s.12(2) requires reports and zone regulations, and s.12(3) requires heritage buildings and precincts. I checked this against the source and it supports the Step 2 finding. (2) WARD/LOCAL = YES, but a reviewer should confirm. s.26(1) gives the objective of a town planning scheme: 'for the purpose of implementing the proposals in the Master Plan', for 'the area within its jurisdiction or any part thereof', so it is a sub-city, local-level spatial plan. s.26(2) lists its possible contents: layout or re-layout, reclamation, streets, buildings, reservations for roads, open spaces, schools, markets and so on, drainage, lighting, water supply, heritage, and building and use restrictions. That list uses 'may make provisions for any of the following'. But s.32 makes the contents of the draft scheme mandatory: it 'shall contain the following particulars', items (a) to (g). The methodology only asks that the Act 'broadly mention what each level of spatial plan should cover', and these sections do that for the local level. CAVEAT: this rests on treating a town planning scheme as the 'ward(s)/local plan'. The KTCP Act has no ward-level spatial plan. The GBG Act s.103(1)(b) Ward Development Plan is a budget-priority list, sits outside the T&CP Act, and was not credited. If reviewers decide a town planning scheme does not count as a local plan, change this input to NO, which leaves 3.33. (3) METROPOLITAN/REGIONAL = blank (not found, not affirmatively absent). The KTCP Arrangement of Sections, as compiled to 2015, has no regional or metropolitan plan chapter. The 2025 KTCP Amendment Bill (ULG-03) only adds the Commissionerate (s.2A/2B), the planning-area definitions and s.81-G, with no regional plan contents. However, amendments between 2016 and 2024 and the KTCP Rules are not in the Citation Sheet, so a 0 cannot be confirmed. Two related sources do not count because they are outside the T&CP Act: GBG Act s.14(2)(c), which on the Metropolitan Planning Committee only refers to Article 243ZE and lists no contents, and the BMRDA Act 1985 Structure Plan, which is not in the Sheet. If the current consolidated KTCP Act confirms there is no regional plan, the input would be NO, giving 6.67 in total. Things to check: the current official consolidated KTCP Act (rather than the PRS copy) and any post-2015 amendments. | R20: The citation didn't settle every input. "Objectives/contents: Metropolitan/regional plan" left blank: the Citation Sheet doesn't decide it.
A21: UPD6 | B21: Surat | C21: Does the Act clearly define the objectives/contents of each level of spatial plan? | D21: =IFERROR('UPD6'!M33,"") | E21: 10 | H21: =IF(OR(F21="",NOT(ISNUMBER(D21))),"",IF(ABS(F21-D21)<0.001,"Yes","No")) | I21: =IF(ISNUMBER(F21),F21,D21) | J21: =IF(ISNUMBER(F21),"Expert (overrides AI)",IF(ISNUMBER(D21),"AI","Not scored yet")) -> Not scored yet | K21: Left for a person | L21: Insufficient Evidence | R21: Step 2 found no evidence: a source needs to be found and added. Step 2 found no evidence (Insufficient Evidence). Source needed: A readable official copy of the GTPUD Act 1976 as amended, specifically s.12 (contents of the draft development plan), the town planning scheme contents section (around s.40) and s.76A (Local Area Plan). Also the Gujarat Metropolitan Planning Committees Act, 2008, specifically the provisions on what the metropolitan development plan must contain and aim to do, ideally from the Gujarat Legislative and Parliamentary Affairs Department or the Urban Development and Urban Housing Department (UD&UHD).
A22: UPD7a | B22: Bangalore | C22: Does the city have a functional MPC/DPC? >:< Does the law provide for the constitution of an MPC/DPC? | D22: =IFERROR(UPD7a!L14,"") | E22: 10 >:< 5 | H22: =IF(OR(F22="",NOT(ISNUMBER(D22))),"",IF(ABS(F22-D22)<0.001,"Yes","No")) | I22: =IF(ISNUMBER(F22),F22,D22) | J22: =IF(ISNUMBER(F22),"Expert (overrides AI)",IF(ISNUMBER(D22),"AI","Not scored yet")) -> Not scored yet | K22: Left for a person | L22: Partially Answered | M22: ANSWER: Part A (mandate in law): YES. Bengaluru is a metropolitan city, so the MPC applies. The city government's current law is the Greater Bengaluru Governance Act, 2024. Section 14(2)(c) says the State Government 'shall constitute' the Bengaluru Metropolitan Planning Committee (BMPC), composed as Article 243ZE of the Constitution requires. Part B (state rules for the MPC applicable to the city): NOT FOUND. The Citation Sheet has no rules on how the MPC is constituted. The Act leaves the remaining members of the BMPC 'as prescribed', which means rules are expected, but none are in the sheet. | EVIDENCE: (1) GBA Act 2024 (Karnataka Act 36 of 2025), s.14(2)(c): 'The State Government shall constitute the Bengaluru Metropolitan Planning Committee (BMPC) for area including but not limited to the Greater Bengaluru Area and with composition as per Article 243 ZE ... chaired by the Chief Minister and comprise of other members as prescribed. The Chief Commissioner of the Greater Bengaluru Authority shall be its Member Secretary.' Section 103(1)(b) also refers to 'plans prepared by the Bengaluru Metropolitan Planning Committee'. (2) BBMP Act 2020, s.367(1) (the earlier, BBMP-era law): 'The Government shall constitute a Metropolitan Planning Committee for the Bengaluru Metropolitan Area'. Under it, the elected members are chosen 'in the prescribed manner' (s.367(2)(a)) and the chairman 'in such manner as may be prescribed' (s.367(5)). GBA Act s.361(1) repeals the BBMP Act 2020 'and Ru | N22: The Greater Bengaluru Governance Act, 2024 (Karnataka Act No. 36 of 2025), as enacted, PRS copy of the Gazette text (DPAL notification dated 24.04.2025) [ULG-01] | O22: https://prsindia.org/files/bills_acts/acts_states/karnataka/2025/Act36of2025KA.pdf | P22: The State Government shall constitute the Bengaluru Metropolitan Planning Committee (BMPC) for area including but not limited to the Greater Bengaluru Area and with composition as per Article 243 ZE of the Constitution of India. The BMPC shall be chaired by the Chief Minister and comprise of other members as prescribed. | Q22: Bengaluru is a metropolitan city, so the question is about a Metropolitan Planning Committee (MPC), not a district one. Part A is YES. The city's own municipal law, the Greater Bengaluru Governance Act, 2024 (Karnataka Act 36 of 2025), was checked in its enacted text (PRS copy of the Gazette text, DPAL notification dated 24.04.2025; GBA era). Section 14(2)(c) uses mandatory wording: the State Government 'shall constitute' the Bengaluru Metropolitan Planning Committee (BMPC), with a composition following Article 243ZE of the Constitution. This is enough for Part A. The earlier BBMP Act 2020 (ULG-19), s.367(1), also said 'The Government shall constitute a Metropolitan Planning Committee', but that Act has been repealed by GBA Act s.361. One wording point: s.14(2)(c) says a 'Bengaluru Metropolitan Planning Authority' prepares the draft development plan, a different name from the committee. This is recorded exactly as written. Part B is left blank because the rules were not found. That is different from finding that they do not exist. Section 14(2)(c) says the other members of the BMPC are to be 'as prescribed', so rules are expected. However, the Citation Sheet has none of the following: - any Karnataka MPC rules made under the GBA Act; - any notification constituting the BMPC; - any MPC rules made under BBMP Act s.367 or the KMC Act 1976. Rules of that last kind could still be in force under GBA Act s.360 (transitory provisions) or the provisos to s.361 (repeal and savings). Searches of the following found no MPC rules: ULG-01, ULG-02 (KTCP Act 1961), ULG-03 (KTCP Amendment Bill 2025), ULG-04 (BDA Act), ULG-18 (BMLTA Act) and ULG-19 (BBMP Act). Since the sheet does not contain the instrument, affirmative absence cannot be shown, so Part B cannot be scored NO (0). A person needs to check whether Karnataka has notified rules on the constitution of, or election to, the MPC under the GBA Act. If not, they should check whether earlier MPC rules under BBMP Act s.367 or the KMC Act 1976 stay in force under s.360. The GBA Act commencement date is also unverified. If Part A is accepted, it gives 2.5 of the 5 points. No total is given because Part B is open. | R22: The citation didn't settle every input. "Part B: MPC/DPC rules notified" left blank: the Citation Sheet doesn't decide it.
A23: UPD7a | B23: Surat | C23: Does the city have a functional MPC/DPC? >:< Does the law provide for the constitution of an MPC/DPC? | D23: =IFERROR(UPD7a!L33,"") | E23: 10 >:< 5 | H23: =IF(OR(F23="",NOT(ISNUMBER(D23))),"",IF(ABS(F23-D23)<0.001,"Yes","No")) | I23: =IF(ISNUMBER(F23),F23,D23) | J23: =IF(ISNUMBER(F23),"Expert (overrides AI)",IF(ISNUMBER(D23),"AI","Not scored yet")) -> Not scored yet | K23: Left for a person | L23: Partially Answered | M23: ANSWER: Partly answered. Surat is a metropolitan city, so the question is about an MPC. Part A: Gujarat has a separate law for MPCs, the Gujarat Metropolitan Planning Committees Act, 2008 (Guj. 18 of 2008). It is in force, and an official 2017 report from the Surat Urban Development Authority (SUDA) says a Surat Metropolitan Area was declared and a Metropolitan Planning Committee formed under it by State notification of 11/03/2016. However, the text of that Act, including the section that requires an MPC to be set up, is not in the Citation Sheet. No such duty was found in the parts read of the Municipal Corporations Act (GPMC Act, 1949) or the Town and Country Planning Act (GTPUD Act, 1976). Part B: no Rules for the MPC under the 2008 Act, and no notification applying such Rules to Surat, are in the Citation Sheet. | EVIDENCE: (1) GTPUD Act 1976 with amendments (ULG-01, PRS copy), Gujarat Act No. 14 of 2019, pp.93-97: the long title says it amends 'the Gujarat Metropolitan Planning Committees Act, 2008, the Gujarat District Planning Committees Act, 2008 and the Gujarat Town Planning and Urban Development Act, 1976'. s.8 inserts s.2(a-1) into the MPC Act. s.9 inserts ss.10A-10C: the State Government 'may' sanction the draft development plan 'submitted by the Metropolitan Planning Committee', and 'Every Metropolitan planning committee shall carry out such directions...'. In the GTPUD Act, the new s.9(1) proviso and s.19A require the appropriate authority's development plan to | N23: Development Plan 2035 (report, 22 February 2017), Surat Urban Development Authority [ULG-06] | O23: https://www.sudaonline.org/wp-content/uploads/2017/03/SUDA-DP-2035-report-final-22.02.2017.pdf | P23: It is also necessary to mention that the State Government h as framed The Gujarat Metropolitan Planning Committees Act, 2008 ( Guj. 18 of 2008) and has also come into force. By the notification dated 11/03/2016, the Surat Metropolitan area has been declared under the said Act, 2008 which includes the SMC and Sachin Municipality area. | Q23: Surat is a metropolitan city, so this question is about an MPC (Metropolitan Planning Committee). PART A = YES. The evidence is an official State planning law that provides for MPCs and was used for Surat. (1) ULG-06 is the SUDA Development Plan 2035 report of 22 Feb 2017. It says the Gujarat Metropolitan Planning Committees Act, 2008 (Guj. 18 of 2008) is in force. It also says that a State notification of 11/03/2016 declared the Surat Metropolitan Area under that Act and constituted the Metropolitan Committee for Surat, apart from its elected members. (2) ULG-02 is Bill No. 21 of 2019, a PRS copy of the Gazette. Its Statement of Objects says the MPC Act and the DPC Act 'are in force in the State of Gujarat'. It adds that s.10 of each Act requires the committees to prepare draft development plans. (3) ULG-01 and ULG-02 contain Gujarat Act 14 of 2019. It inserts ss.10A-10C into the MPC Act ('Every Metropolitan planning committee shall carry out such directions...'). It also inserts a proviso to s.9(1) and a new s.19A into the GTPUD Act, tying the development plans of appropriate authorities to the plan sanctioned under the MPC Act. Taken together, these show that Gujarat law provides for constituting an MPC and that one was constituted for Surat. Points a reviewer should confirm: (a) The methodology asks for a mandate 'in the Municipal or T&CP Act'. Gujarat puts it in a separate MPC Act (a State planning law). I have treated that as meeting the intent; please confirm. (b) The text of the MPC Act's own constitution section is not in the Citation Sheet. So I cannot quote its exact verb ('shall' or 'may') or its section number. The support comes from SUDA's account of the 2016 notification and from the 2019 amending text. (c) The 11/03/2016 notification itself is not in the sheet. If the reviewer decides that Part A needs the Act's own constitution section, change Part A to blank. PART B = blank (NOT FOUND, not absent). I searched the Citation Sheet for Rules under the Gujarat MPC Act 2008, and for any notification applying such Rules to Surat, and found neither. What I checked: ULG-01 (GTPUD Act 1976 with amendments; amendment Act pp.93-98), ULG-02 (Bill 21 of 2019), ULG-03 (GPMC Act 1949 as of 30 Nov 2017; no MPC/DPC provision found), ULG-04 (GTPUD Rules 1979; development plans and TP schemes only), ULG-05, ULG-14, ULG-15 and ULG-16 (CGDCR 2017; development control only), and ULG-06. The MPC Act text, any MPC Rules (e.g. on electing members) and the 2016 notifications are not in the sheet, so absence cannot be confirmed. The research team should add the Gujarat MPC Act 2008 text, any MPC Rules with their Gazette notification, and the 11/03/2016 notifications. Other limits: the 2019 amending Act comes into force on a date the State notifies, and that date is not in the sheet. ULG-01 and ULG-02 are PRS republications (secondary copies). | R23: The citation didn't settle every input. "Part B: MPC/DPC rules notified" left blank: the Citation Sheet doesn't decide it.
A24: UPD7b | B24: Bangalore | C24: Does the city have a functional MPC/DPC? >:< Have they met at least once in the past two years? | D24: =IFERROR(UPD7b!K14,"") | E24: 10 >:< 5 | H24: =IF(OR(F24="",NOT(ISNUMBER(D24))),"",IF(ABS(F24-D24)<0.001,"Yes","No")) | I24: =IF(ISNUMBER(F24),F24,D24) | J24: =IF(ISNUMBER(F24),"Expert (overrides AI)",IF(ISNUMBER(D24),"AI","Not scored yet")) -> Not scored yet | K24: Left for a person | L24: Insufficient Evidence | R24: Step 2 found no evidence: a source needs to be found and added. Step 2 found no evidence (Insufficient Evidence). Source needed: Dated evidence that the MPC/BMPC met between about Sept 2024 and Sept 2026: minutes, agendas, resolutions or meeting notices from the MPC/BMPC (Member Secretary: GBA Chief Commissioner) or the Urban Development Department, Karnataka. Also needed: the government order setting up the BMPC under GBA Act s.14(2)(c) and its membership rules, or an RTI reply listing the dates of MPC meetings.
A25: UPD7b | B25: Surat | C25: Does the city have a functional MPC/DPC? >:< Have they met at least once in the past two years? | D25: =IFERROR(UPD7b!K33,"") | E25: 10 >:< 5 | H25: =IF(OR(F25="",NOT(ISNUMBER(D25))),"",IF(ABS(F25-D25)<0.001,"Yes","No")) | I25: =IF(ISNUMBER(F25),F25,D25) | J25: =IF(ISNUMBER(F25),"Expert (overrides AI)",IF(ISNUMBER(D25),"AI","Not scored yet")) -> Not scored yet | K25: Left for a person | L25: Insufficient Evidence | R25: Step 2 found no evidence: a source needs to be found and added. Step 2 found no evidence (Insufficient Evidence). Source needed: Any of these, dated within the past two years, would answer this: minutes, agendas or resolutions of the Surat Metropolitan Planning Committee (or of the Surat District Planning Committee, if that is the applicable body); a Gujarat UD&UHD Department notification or webpage recording MPC meetings; or an RTI reply from the MPC's member-secretary or the UD&UHD Department listing meeting dates.
A26: UPD8 | B26: Bangalore | C26: Does the city (million-plus) have a Metropolitan Authority? | D26: =IFERROR('UPD8'!K14,"") | E26: 10 | H26: =IF(OR(F26="",NOT(ISNUMBER(D26))),"",IF(ABS(F26-D26)<0.001,"Yes","No")) | I26: =IF(ISNUMBER(F26),F26,D26) | J26: =IF(ISNUMBER(F26),"Expert (overrides AI)",IF(ISNUMBER(D26),"AI","Not scored yet")) -> Not scored yet | K26: Left for a person | L26: Partially Answered | M26: ANSWER: A state law sets up a metropolitan-level authority for Bengaluru, but the Citation Sheet does not show that it has actually been constituted. The Greater Bengaluru Governance Act, 2024 (Karnataka Act 36 of 2025) creates the Greater Bengaluru Authority (GBA). The Act says the State Government 'shall' constitute it by notification, makes it a body corporate, and makes it the Planning Authority under the Karnataka Town and Country Planning (KTCP) Act. That meets the 'established by law' part of the test. The 'constituted for the city' part is not shown. The Sheet does not contain the notification bringing the Act into force (s.1(3)) or the notification constituting the GBA (s.9(1)). | EVIDENCE: (1) GBA Act, 2024, Preamble: 'it is expedient to establish the Greater Bengaluru Authority'. s.1(3): the Act 'shall come into force on such date as the Government may by notification appoint'. s.2(3): 'Authority' means the GBA 'created under this Act'. s.9(1): 'the Government shall, by notification, constitute an Authority for the Greater Bengaluru Area called the Greater Bengaluru Authority', within 120 days of commencement. s.9(2): body corporate with perpetual succession. s.9(3): members include the Chief Minister as Chairperson, the minister for Bengaluru Development, the Mayors of the City Corporations, and the heads of BDA, BWSSB, BMTC, etc. s.8(3): the GBA 'shall discharge the role of coordinator among all the City Corporations and other agencies in the Greater Bengaluru Ar | N26: The Greater Bengaluru Governance Act, 2024 (Karnataka Act No. 36 of 2025), as enacted, PRS copy of the Gazette text (DPAL notification dated 24.04.2025) [ULG-01] | O26: https://prsindia.org/files/bills_acts/acts_states/karnataka/2025/Act36of2025KA.pdf | P26: the Government shall, by notification, constitute an Authority for the Greater Bengaluru Area called the Greater Bengaluru Authority. | Q26: I left 'Answer' blank. The law creating the authority is in the Sheet, but nothing in the Sheet shows the authority has actually been set up (constituted) for the city. The methodology needs both to give 10. (1) Created by law: shown. The Greater Bengaluru Governance Act, 2024 (Karnataka Act 36 of 2025; gazette text 24.04.2025 in the PRS copy, ULG-01) says in s.9(1) that the Government 'shall, by notification, constitute' the Greater Bengaluru Authority (GBA) within 120 days of the Act starting. s.9(2) makes the GBA a body corporate. s.8(3) makes it the coordinator of all agencies in the Greater Bengaluru Area. s.14(2)(a) makes it the 'Planning Authority' under the Karnataka Town and Country Planning (KTCP) Act, 1961, 'notwithstanding anything contained in any other law'. (2) Set up for the city: not shown. The Act only starts on a date the Government sets by notification (s.1(3)), and the GBA comes into being only through the s.9(1) notification. Neither notification is in the Sheet. I checked these later laws and found no constitution notice or date: - ULG-01's appended amending Acts: Act 60/2025 (12.09.2025) and Act 1/2026 (07.01.2026). They change GBA functions and add members under s.9(3), and replace s.9(5). - ULG-05: the Amendment Bill and its Statement of Objects. - ULG-03: the KTCP Amendment Bill 2025. Its new s.81-G would apply 'with effect from the date Greater Bengaluru Authority is constituted'. It is a Bill, and it has not been shown to be enacted. - ULG-18: BMLTA Amendment Act 10/2026. It refers to 'City Corporations under the jurisdiction of the Greater Bengaluru Authority'. - ULG-04: BDA Act, including Act 42/2026. It does not mention the GBA. These later laws strongly suggest the GBA is up and running. But they are laws, not the s.9(1) notice, and treating them as proof would be inference. I checked the Step 2 answer against the sources and agree with it. Research-team dates for the GBA are guidance only and are not verified, so I did not use them. Why not NO: the law exists, so the absence needed for NO cannot be shown. Why not NA: Bengaluru is a million-plus metropolitan city. For a person to check: - Get the s.9(1) gazette notification constituting the GBA, and the s.1(3) commencement notification. If they exist, Answer = YES (10). - Confirm the GBA, not BMRDA, is the intended metropolitan authority. The methodology names the GBA, and the BMRDA Act is not in the Sheet. Era: GBA-era. | R26: The citation didn't settle every input. "Answer" left blank: the Citation Sheet doesn't decide it.
A27: UPD8 | B27: Surat | C27: Does the city (million-plus) have a Metropolitan Authority? | D27: =IFERROR('UPD8'!K33,"") | E27: 10 | H27: =IF(OR(F27="",NOT(ISNUMBER(D27))),"",IF(ABS(F27-D27)<0.001,"Yes","No")) | I27: =IF(ISNUMBER(F27),F27,D27) | J27: =IF(ISNUMBER(F27),"Expert (overrides AI)",IF(ISNUMBER(D27),"AI","Not scored yet")) -> Not scored yet | K27: Left for a person | L27: Partially Answered | M27: ANSWER: Cannot be scored from the Citation Sheet. Surat has two bodies that work above the level of the city government, but neither clearly matches the 'metropolitan authority' that UPD8 describes. (1) A Surat Metropolitan Planning Committee under the Gujarat Metropolitan Planning Committees Act, 2008 (Guj. 18 of 2008). A 2017 SUDA report says the Surat Metropolitan area was declared on 11/03/2016, covering only the Surat Municipal Corporation (SMC) and Sachin Municipality, and that the Committee was constituted the same day 'except for the elected members'. This is a planning committee, not a metropolitan governance or development authority like the Greater Bengaluru Authority (GBA) example. (2) The Surat Urban Development Authority (SUDA), a statutory urban development authority under section 22 of the Gujarat Town Planning and Urban Development Act, 1976. It was constituted by notification dated 30.01.1978 and covers SMC plus surrounding villages (1351 sq km after the 2015 extension, later reduced). It is a regional planning and development authority, not a metropolitan-level authority set up by a dedicated Act. A third body, the Surat Regional Economic Development Authority (SREDA), is only a proposal in NITI Aayog's 2024 Economic Master Plan; no law establishes it. | EVIDENCE: ULG-06 (SUDA Development Plan 2035 report, Feb 2017), p.19 [report p.2]: the Surat Metropolitan area was declared under the Gujarat MPC Act, 2008 on 11/03/2016, and 'The Metropolitan Committee for | N27: Development Plan 2035 (report, 22 February 2017), Surat Urban Development Authority [ULG-06] | O27: https://www.sudaonline.org/wp-content/uploads/2017/03/SUDA-DP-2035-report-final-22.02.2017.pdf | P27: By the notification dated 11/03/2016, the Surat Metropolitan area has been declared under the said Act, 2008 which includes the SMC and Sachin Municipality area. The Metropolitan Committee for Surat was also constituted by the notification of the State Government dt. 11/03/2016 except for the elected members. | Q27: I left 'Answer' blank for a person to decide. NA does not apply: Surat is a million-plus city. ULG-06 Table 1 gives SMC's 2011 population as about 44.67 lakh, so the question applies. YES and NO are both unsafe on this Citation Sheet. Points for checking: (1) BODY TYPE. The only body called 'metropolitan' is the Surat Metropolitan Planning Committee (MPC) under the Gujarat Metropolitan Planning Committees Act, 2008 (Guj. 18 of 2008). Per ULG-06 (a 2017 SUDA report, not the notification itself), it was declared and constituted on 11/03/2016 'except for the elected members'. It covers only SMC and Sachin Municipality. Its job is planning: the MPC Act s.10A-10C, inserted by Gujarat Act 14 of 2019 (ULG-01, gazette pp.14-4 to 14-6, and ULG-02), say the State 'may' sanction its draft plan and the MPC 'shall carry out such directions' of the State. That makes it a planning committee under State control, not a metropolitan authority like the methodology's example, the Greater Bengaluru Authority under a dedicated Act. SUDA is an urban development authority set up by notification dated 30.01.1978 under GTPUD Act 1976 s.22(1), (2) and (4). Nothing in the sheet calls it a metropolitan-level authority. SREDA (ULG-09, NITI Aayog 2024) is only a proposal. Whether an MPC (or SUDA) counts as a 'metropolitan authority' for UPD8 is a methodology call that needs confirming. (2) CONSTITUTION. Even if the MPC counts, it was constituted without its elected members as of 2016-17. No later notification completing it is in the sheet. (3) NO WOULD NEED AFFIRMATIVE ABSENCE, AND I DON'T HAVE IT. I checked: ULG-01 (GTPUD Act 1976 plus amendments up to Act 14 of 2019); ULG-02 (Bill 21 of 2019); ULG-03 (GPMC Act 1949 as modified to 2017: only definition s.2(34A) 'Metropolitan area' per Art. 243P, and no metropolitan authority provision in the parts read); ULG-06; ULG-09; and a sheet-wide search for 'metropolitan authority Surat'. But these are not in the sheet: the full text of the Gujarat MPC Act 2008, the 11/03/2016 notifications, and any later GO. So I cannot rule out a metropolitan authority. Next steps: get the MPC Act 2008 and the 2016 notifications, and confirm whether an MPC qualifies. If it does, and the MPC is fully constituted, YES may be right. If it does not, NO needs the absence check finished. Period: MPC declared 2016 (per 2017 report); MPC Act amended 2019; SUDA from 1978. era=n/a. | R27: The citation didn't settle every input. "Answer" left blank: the Citation Sheet doesn't decide it.
A28: UPD9 | B28: Bangalore | C28: Does the law mandate participation of all parastatals/ agencies /ULGs in creation of Spatial plans (metro/municipal/ward)? | D28: =IFERROR('UPD9'!K14,"") | E28: 10 | H28: =IF(OR(F28="",NOT(ISNUMBER(D28))),"",IF(ABS(F28-D28)<0.001,"Yes","No")) | I28: =IF(ISNUMBER(F28),F28,D28) | J28: =IF(ISNUMBER(F28),"Expert (overrides AI)",IF(ISNUMBER(D28),"AI","Not scored yet")) -> Not scored yet | K28: Left for a person | L28: Partially Answered | M28: ANSWER: Only in part. The law does require local bodies and the main parastatals to take part in the body that prepares the city-level master plan. For Bengaluru that body is the Greater Bengaluru Authority (GBA), which is the Planning Authority. The GBA Act says the GBA shall be the 'Planning Authority' under the KTCP Act, and that its members shall include the Mayors of the City Corporations and the heads of BDA, BWSSB, BMTC, BMRCL and BESCOM. Under the KTCP Act, any Planning Authority set up under s.4C must include representatives of local bodies. At metropolitan level, the GBA Act says the State shall set up a Bengaluru Metropolitan Planning Committee (BMPC) whose make-up follows Art. 243ZE. Its other members are only 'as prescribed', and the Rules that prescribe them are not in the Citation Sheet. I found no provision requiring agency participation in ward-level spatial plans. I also found no required advisory council with civic-agency members to advise on drawing up the plan. So the 'all three levels' test and the advisory-council test are not shown to be met, and no score is proposed. | EVIDENCE: (1) GBA Act 2024 s.14(2)(a): 'the Greater Bengaluru Authority shall be the "Planning Authority" as defined under the Karnataka Town and Country Planning Act, 1961, for the areas comprising of the Greater Bengaluru Area'. s.9(3): 'The Greater Bengaluru Authority shall consist of the following members', including (f) the City Corporation Mayors, (g) Commissioner BDA, (h) Chairma | N28: The Greater Bengaluru Governance Act, 2024 (Karnataka Act No. 36 of 2025), as enacted, PRS copy of the Gazette text (DPAL notification dated 24.04.2025) [ULG-01] | O28: https://prsindia.org/files/bills_acts/acts_states/karnataka/2025/Act36of2025KA.pdf | P28: the Greater Bengaluru Authority shall be the “Planning Authority” as defined under the Karnataka Town and Country Planning Act, 1961, for the areas comprising of the Greater Bengaluru Area; | Q28: I left the Answer blank. The Citation Sheet shows that some conditions of the 10-point test are met, but it cannot settle all of them. A YES is not supported, and a NO cannot be shown by affirmative absence. WHAT SUPPORTS PARTICIPATION: (1) City/master-plan level. Under GBA Act 2024 (ULG-01) s.14(2)(a), the GBA 'shall be' the Planning Authority under the KTCP Act. Under s.9(3), the GBA 'shall consist of' the City Corporation Mayors and the heads of BDA, BWSSB, BMTC and BMRCL, among others. Under s.15(1), the GBA 'shall be responsible to make master plan' and the City Corporations 'shall incorporate' its plan. KTCP s.81-G (inserted by ULG-03, LA Bill 55 of 2025) also makes the GBA the local planning authority. ULG-03 is a Bill as passed by the Assembly; I did not check whether it has been enacted or notified. Separately, KTCP s.4C(3)(iii) (ULG-02) requires every Planning Authority to include 'representatives of local bodies', but it lists no parastatals. (2) Metropolitan level. Under s.14(2)(c), the State 'shall constitute' the BMPC 'with composition as per Article 243 ZE'. Its other members are 'as prescribed', and those Rules are not in the Citation Sheet. The same clause names a 'Bengaluru Metropolitan Planning Authority' as the body that prepares the draft plan. This looks like a drafting error for BMPC; a reviewer should check it. WHAT IS UNRESOLVED: (a) Ward level. The only ward-level plan I found is the Ward Development Plan under GBA Act s.103. The Step 2 answer describes it as a priority list of projects for funding, not a spatial plan; I did not re-read s.103 myself. I found no provision requiring agencies to take part in ward-level spatial plans. (b) Advisory council with civic-agency members. GBA Act s.18 creates Sectoral Expert Committees made up of 'domain experts', not representatives of civic agencies. KTCP s.4F says a Planning Authority 'may associate with itself' advisers, which is optional, not a mandate. KTCP s.4 does set up a State Board, which s.4C and s.4A say must be consulted. However, I could not read its composition or functions in ULG-02, even after repeated searches. (c) Rules layer missing. The KTCP Rules, the BMPC Rules and any GBA planning regulations are not in the Citation Sheet. WHAT I CHECKED: - ULG-01: s.9, s.14, s.15, s.18 - ULG-02: s.4A to 4C, s.4F, s.74, s.82 - ULG-03: whole Bill - Step 2's review of ULG-04, ULG-18 and ULG-19 (the BBMP Act MPC provision in ULG-19 has probably been superseded). The methodology is ambiguous on two points, so a reviewer should decide them: (i) Does membership of the Planning Authority, created by the GBA Act rather than the KTCP Act, count as participation in creating spatial plans? (ii) Must both the three-level condition and the advisory-council condition be met to score 10? If the reviewer finds that KTCP s.4 and the Rules contain no advisory council with civic-agency members, the likely result is NO (score 0). | R28: The citation didn't settle every input. "Answer" left blank: the Citation Sheet doesn't decide it.
A29: UPD9 | B29: Surat | C29: Does the law mandate participation of all parastatals/ agencies /ULGs in creation of Spatial plans (metro/municipal/ward)? | D29: =IFERROR('UPD9'!K33,"") | E29: 10 | H29: =IF(OR(F29="",NOT(ISNUMBER(D29))),"",IF(ABS(F29-D29)<0.001,"Yes","No")) | I29: =IF(ISNUMBER(F29),F29,D29) | J29: =IF(ISNUMBER(F29),"Expert (overrides AI)",IF(ISNUMBER(D29),"AI","Not scored yet")) -> Not scored yet | K29: Left for a person | L29: Partially Answered | M29: ANSWER: Not determined. The parts of the law I could read do not show a provision requiring all parastatals, agencies or city governments to take part in making spatial plans at metro, municipal or ward level. They also do not show a required advisory council with civic-agency members. I could not read the key sections of the Gujarat Town Planning and Urban Development Act, 1976 (GTPUDA): who sits on the Urban Development Authority (UDA), how the draft plan is prepared (s.9) and how it is published (s.13). The Gujarat Metropolitan Planning Committees Act, 2008 (MPC Act) is also missing apart from its 2019 amendments. So this is 'not found', not an absence, and there is no score. | EVIDENCE: (1) GTPUDA 1976, PRS copy (ULG-01). Only the appended amendments could be read. (a) The 2019 amendment adds a proviso to s.9(1): the development plan 'shall include the proposals, with regard to spatial planning, of the development plan sanctioned under the Gujarat Metropolitan Planning Committees Act, 2008 or the Gujarat District Planning Committees Act, 2008'. (b) New s.19A: the appropriate authority 'shall include' the MPC/DPC spatial proposals by varying its plan. This requires plans to be consistent, not agencies to take part. (c) The 2017 amendment to ss.7(2) and 23(2) says the State 'may' hand authority powers to the local authority. That is a discretionary delegation, not participation in making the plan. (2) MPC Act ss.10A–10B, inserted by Gujarat Act 14 of 2019 (ULG-01, pp.96–97) | N29: The Gujarat Town Planning and Urban Development Act, 1976 (Act 27 of 1976), with amendments appended (PRS Legislative Research copy) [ULG-01] | O29: https://prsindia.org/files/bills_acts/acts_states/gujarat/1976/1976Gujarat27.pdf | P29: (3) A final development plan which has come into force shall be binding on the concerned all authorities functioning in the metropolitan area. | Q29: I left the answer blank because the citation sheet does not contain the main legal text needed to answer this question. Without it, the evidence is 'not found', which is different from proven absence. The Step 2 finding of 'not determined' is correct when checked against the source. What the readable text actually says: (1) MPC Act s.10A(3), inserted in 2019: the final development plan 'shall be binding on the concerned all authorities functioning in the metropolitan area'. This makes the finished plan binding on all authorities. It does not require them to take part in preparing it. (2) GTPUD Act s.9(1) proviso and s.19A, inserted in 2019: the development plan 'shall include' the spatial-planning proposals of the plan sanctioned under the MPC or DPC Act. This only requires the plans to be consistent with each other. It is not a participation requirement. (3) GTPUD Act ss.7(2) and 23(2), as amended in 2017: the State 'may' delegate authority powers to the local authority. This is optional ('may'), and it is about delegating powers, not taking part in plan-making. (4) MPC Act s.10B(1)-(2): for a variation, objections are invited 'from any person', and the MPC is consulted. A notice to the general public is not consultation with the city government or with parastatals. (5) Bill 21 of 2019 (ULG-02, p.7), statement of objects: says the MPC and DPC Acts require plans to be made 'in regard to' plans prepared by municipalities and panchayats. This is explanatory text, not an operative section, and the MPC Act's own section is not in the sheet. (6) GTPUD Rules 1979 (ULG-04): Form A invites objections from the public. I found no advisory council. (7) CGDCR 2017 (ULG-05, ULG-14 to ULG-16): the committees it sets up deal with development permission and heritage, not with plan-making. (8) GPMC Act s.284F (ULG-03): notices to utilities, but for objections only and only for redevelopment plans. (9) SUDA's Development Plan 2035 (ULG-06, p.183) records meetings with village sarpanchs. That is practice, not law, so it cannot score a Law/Policy question. What I checked: I read ULG-01 three times, looking for UDA constitution (s.22), s.9 and s.13. Only the appended 2017 and 2019 amendments came back. I also searched the whole sheet for consultation with local authorities, advisory committees, MPC composition and consultation with municipalities. None of these searches found an operative provision. Missing evidence: the readable operative text of the GTPUD Act 1976 is not in the sheet. That includes s.2(iii), ss.9-13 (how the draft plan is prepared and published) and ss.22-23 (who sits on the UDA, and whether it includes local-authority members). The full Gujarat MPC Act 2008 is also missing, including its composition section and any requirement to consult municipalities or agencies (the 'in regard to' wording). The DPC Act 2008 and the notification constituting the Surat MPC are missing too, and there is nothing on ward-level plans. What a person should do: add official text of these instruments, then decide YES or NO. If the MPC Act contains a binding 'shall consult / have regard to plans of municipalities' clause, or the UDA or MPC composition includes ULG and agency representatives, that could support YES. NO can only be entered once all of these have been read and nothing is found. | R29: The citation didn't settle every input. "Answer" left blank: the Citation Sheet doesn't decide it.
A30: UPD10 | B30: Bangalore | C30: Does the law mandate public participation in preparation of the municipal plan through Area Sabhas / Ward Sabhas and other means? | D30: =IFERROR('UPD10'!L14,"") | E30: 10 | H30: =IF(OR(F30="",NOT(ISNUMBER(D30))),"",IF(ABS(F30-D30)<0.001,"Yes","No")) | I30: =IF(ISNUMBER(F30),F30,D30) | J30: =IF(ISNUMBER(F30),"Expert (overrides AI)",IF(ISNUMBER(D30),"AI","Not scored yet")) -> Not scored yet | K30: Left for a person | L30: Partially Answered | M30: ANSWER: Part B (other means) is met. The Karnataka Town and Country Planning Act, 1961 (KTCP Act) requires the Planning Authority to ask the public for suggestions when it declares it will prepare a Master Plan, and later to publish the plan inviting public comments, which it 'shall consider'. The Greater Bengaluru Governance Act, 2024 (GBG Act) makes the Greater Bengaluru Authority (GBA) the Planning Authority for the Greater Bengaluru Area, so these duties fall on GBA. Part A (ward committees / Area Sabhas) is NOT FOUND, but not confirmed absent. In the KTCP Act text I read, ward committees, Ward Sabhas and Area Sabhas take no part in preparing the Master Plan. The only participation duty through a Ward Sabha in Bengaluru's law is in the GBG Act, and it covers the annual Ward Development Plan, not the city Master Plan. Other layers were not read, so a 0 for Part A cannot be justified yet. | EVIDENCE: (1) KTCP Act s.10(1), as substituted by Act 1 of 2005: the Planning Authority 'shall publish a notice of such declaration in the Official Gazette and also in one or more local newspaper in the prescribed manner calling suggestions from the public within a period of sixty days'. (2) KTCP Act s.13(1): the plan is returned to the Planning Authority, 'which shall thereupon publish, by notification, the plan and the reports inviting public comments within sixty days'. s.13(2): if a member of the public sends comments, 'the Planning authority shall consider such comments and resubmit | N30: The Karnataka Town and Country Planning Act, 1961 (Karnataka Act 11 of 1963), PRS compilation with amendments up to Act 38 of 2015 [ULG-02] | O30: https://prsindia.org/files/bills_acts/acts_states/karnataka/1963/1963KR11.pdf | P30: The planning authority shall publish a notice of such declaration in the Official Gazette and also in one or more local newspaper in the prescribed manner calling suggestions from the public within a period of sixty days | Q30: SCORE: Part B can be filled. Part A stays blank, so the total score is open. It would be 5 if Part A is confirmed NO, or 10 if YES. PART B = YES. The Karnataka Town and Country Planning (KTCP) Act has two mandatory public-input steps for the Master Plan: - s.10(1): the Planning Authority 'shall publish a notice' 'calling suggestions from the public within a period of sixty days'. s.10(2): the Planning Authority 'shall consider such suggestion'. - s.13(1): the Planning Authority 'shall thereupon publish, by notification, the plan and the reports inviting public comments within sixty days'. s.13(2): it 'shall consider such comments' and resubmit with recommended changes. Both use 'shall', and both are open to every member of the public. The methodology credits these under Part B even though no specific method is required. WHO THE DUTIES FALL ON: - Greater Bengaluru Governance (GBG) Act (ULG-01), Planning Functions sub-section (2)(a): the Greater Bengaluru Authority (GBA) 'shall be the "Planning Authority" as defined under the Karnataka Town and Country Planning Act, 1961'. - The 2025 KTCP Amendment Bill (ULG-03) would add a new s.81-G with the same effect. It is still a Bill: it comes into force only on a date the State notifies, and it says nothing about participation. PART A = BLANK. This is 'not found', not proven absent. What I checked: - KTCP Act s.6, 7, 9, 10, 12, 13 and 13-A (ULG-02): none mentions ward committees, Ward Sabhas or Area Sabhas in preparing the Master Plan. - The 2020 Second Amendment (Act 47 of 2020, appended in ULG-02): - It requires ward-level land-use maps and their display 'in the offices of the local authorities and the ward offices'. - It adds to s.13(1) that the plan 'shall be forwarded to the local authorities within the local planning area'. - That is display at offices and forwarding to the local authority, not a ward committee or Area Sabha process. - However, the rest of the s.13(1) insertion is cut off in the saved text, so I could not confirm all of its wording. - GBG Act (ULG-01): - s.103(1)(b)-(c): the Ward Sabha's role covers only the annual Ward Development Plan, which is a budget priority list. That is not the city Master Plan. - The clause on the Bengaluru Metropolitan Planning Committee's draft development plan (Planning Functions (2)(c)) is cut off at 'and disc...', so I could not read whether it requires consulting ward committees. - ULG-03 (2025 Bill): it deals only with the Commissionerate and the Planning Authority's jurisdiction. It has no participation provisions. - The KTCP Rules, which set the 'prescribed manner' for these notices, are not in the Citation Sheet. The 0 for Part A cannot be given until a reviewer checks three things: the full s.13(1) text from the 2020 amendment, the full GBG Act Bengaluru Metropolitan Planning Committee clause, and the KTCP Rules. PERIOD: KTCP Act as compiled by PRS up to Act 38 of 2015, plus Act 47 of 2020. GBG Act as enacted (notified 24.04.2025). Era: GBA era. I agree with the Step 2 answer and checked it against the source text. | R30: The citation didn't settle every input. "Part A: Formal platforms (ward committees / area sabhas)" left blank: the Citation Sheet doesn't decide it.
A31: UPD10 | B31: Surat | C31: Does the law mandate public participation in preparation of the municipal plan through Area Sabhas / Ward Sabhas and other means? | D31: =IFERROR('UPD10'!L33,"") | E31: 10 | H31: =IF(OR(F31="",NOT(ISNUMBER(D31))),"",IF(ABS(F31-D31)<0.001,"Yes","No")) | I31: =IF(ISNUMBER(F31),F31,D31) | J31: =IF(ISNUMBER(F31),"Expert (overrides AI)",IF(ISNUMBER(D31),"AI","Not scored yet")) -> Not scored yet | K31: Left for a person | L31: Partially Answered | M31: ANSWER: Part B (other means) is met. Under the Gujarat Town Planning and Urban Development Act, 1976 (GTPUD Act), as carried out by Rule 5 of the 1979 Rules, the draft development plan must be published, and objections and suggestions from any member of the public must be invited within two months and considered. For Surat, Surat Urban Development Authority (SUDA) prepares this plan, and its area includes the Surat Municipal Corporation (SMC) area. Part A (ward committees or area sabhas) is not determined. The sheet has no provision requiring ward committees or area sabhas to take part in preparing the plan. But this is 'not found', not a proven absence, because the main text of the Act could not be read and the Ward Committee rules are not in the sheet. | EVIDENCE: (1) GTPUD Rules 1979 (ULG-04), r.5(1): the area development authority or authorised officer 'shall' publish the draft development plan through a notice in the Official Gazette and in one or more Gujarati newspapers (Form A), and the notice is also pasted at the authority's head office and other prominent places. r.5(2): the notice 'shall in pursuance of the provisions of section 13' announce that, if any member of the public sends written objections or suggestions within two months, the authority 'shall consider' them and 'may modify' the plan. r.6(1) (as amended by Notification dated 22-01-87): if the authority makes extensive or substantial changes, these are republished and objections and suggestions from the p | N31: Gujarat Town Planning and Urban Development Rules, 1979 (copy hosted by Surat Urban Development Authority) [ULG-04] | O31: https://www.sudaonline.org/wp-content/uploads/2013/08/GTPUD-Rules-1979.pdf | P31: Every notice published under sub -rule (1) shall in pursuance of the provisions of section 13 announce that i f within two months from the date of publication of the notice in the Official Gazette any member of the public communicates in writing to the area development authority or as the case may be to the authorized officer, his objections or suggestions with re spect to the development plan, the development authority or as the case may be the authorized officer shall consider such objections or suggestions and may modify such plan as it/he thinks fit. | Q31: PART B = YES. I checked the Step 2 answer against the source. Under ULG-04, the GTPUD Rules 1979 (made under the Gujarat Town Planning and Urban Development Act, 1976): r.5(1) says the authority 'shall' publish the draft development plan in the Official Gazette and in Gujarati newspapers. r.5(2) says the notice 'shall', 'in pursuance of the provisions of section 13', invite written objections or suggestions from any member of the public within two months. The authority 'shall consider' them. Only modifying the plan is discretionary ('may modify'). Form A is issued 'in pursuance of sub-section (1) of section 13 of the said Act' and says objections and suggestions 'from any person … shall be considered'. Under r.6(1) and (2), substantial modifications made by the authority or by the State are republished for public objections, which 'shall be considered' before sanction. This fits the methodology's footnote: a provision for consolidating suggestions and objections counts as 'other means'. The Act's own s.13 text cannot be read in ULG-01: the PRS copy's pages 2-86 are scanned with no text layer. So the YES rests on the Rules, which state they implement the mandate in s.13. The reviewer should confirm that the Rules are enough to show the Act 'mandates' this. That is why confidence is medium-to-low. This is a general notice to the public, not ward-level consultation. PART A = blank (not found; absence not proven). I found no provision requiring ward committees or area sabhas to take part in preparing the development plan in: GTPUD Rules r.3, r.5 and r.6; the readable GTPUD amendment Acts (6 of 2017, 22 of 2017, 14 of 2019 in ULG-01 and Bill 21 of 2019 in ULG-02); the 2019 amendments to the MPC and DPC Acts (ss.10A-10C, which provide only 'any person' objections to variations); and GPMC Act s.29A (ULG-03, Wards Committees, whose functions are left to State rules under s.29A(8)). A search across the whole Citation Sheet for 'ward committee area sabha development plan participation' returned nothing relevant. But I cannot record affirmative absence. The main text of the GTPUD Act, including ss.9-17, is unreadable. The Wards Committee rules under GPMC s.29A(8) are not in the sheet. The full text of the Gujarat Metropolitan Planning Committees Act, 2008 is not in the sheet. A human should check these three instruments. If none of them has a provision, Part A = NO and the total is 5; if a provision is found, the total is 10. Period: GTPUD Act 1976 as amended up to Act 14 of 2019; Rules 1979 with the 1987 amendment; GPMC Act as modified up to 30-11-2017. | R31: The citation didn't settle every input. "Part A: Formal platforms (ward committees / area sabhas)" left blank: the Citation Sheet doesn't decide it.
A32: UPD11a | B32: Bangalore | C32: Is there public scrutiny for (including objections and responses) municipal/city plan? >:< Does the law mandate public scrutiny for (including objections and responses) municipal/city plan through Area Sabhas / Ward Sabhas and other means? | D32: =IFERROR(UPD11a!L14,"") | E32: 10 >:< 5 | H32: =IF(OR(F32="",NOT(ISNUMBER(D32))),"",IF(ABS(F32-D32)<0.001,"Yes","No")) | I32: =IF(ISNUMBER(F32),F32,D32) | J32: =IF(ISNUMBER(F32),"Expert (overrides AI)",IF(ISNUMBER(D32),"AI","Not scored yet")) -> Not scored yet | K32: Left for a person | L32: Partially Answered | M32: ANSWER: Part B (other means) is met. The Karnataka Town and Country Planning Act (KTCP Act) requires the Master Plan to be published for public comment, and the Planning Authority must consider those comments and send the plan back with recommended changes. Part A (Ward Committees / Area Sabhas) is NOT FOUND for the city plan. The Act sections read do not mention ward committees, ward sabhas or area sabhas. The city's own law, the Greater Bengaluru Governance Act (GBA Act), uses a Ward Sabha only for the Annual Ward Development Plan, not for the Master Plan. I could not show the absence for every layer, because the KTCP Rules are not in the Citation Sheet and one GBA Act planning clause could not be read in full. So Part A is undetermined, not 0. | EVIDENCE: (1) KTCP Act s.13(1), as substituted by Act 1 of 2005: after provisional approval, the Planning Authority 'shall thereupon publish, by notification, the plan and the reports inviting public comments within sixty days of such publication'. (2) s.13(2): 'the Planning authority shall consider such comments and resubmit the plan and the reports to the State Government ... with recommendations for such modifications'. This is a mandatory scrutiny, objection and response step for the city plan, so it meets Part B. (3) s.13(3)-(4): the State Government gives final approval 'in the light of the comments'. The approved plan is published and kept open for public inspection. (4) s.13-A(1): the s.13 procedure also applies to Interim | N32: The Karnataka Town and Country Planning Act, 1961 (Karnataka Act 11 of 1963), PRS compilation with amendments up to Act 38 of 2015 [ULG-02] | O32: https://prsindia.org/files/bills_acts/acts_states/karnataka/1963/1963KR11.pdf | P32: If within sixty days of the publication under sub-section (1), any member of the public communicates in writing to the Planning Authority any comments on the plan and the reports, the Planning authority shall consider such comments and resubmit the plan and the reports to the State Government, through the Director with recommendations for such modifications in the plan and reports as it considers necessary in the light of the public comments made on the plan and reports. | Q32: PART B = YES. The KTCP Act requires the Planning Authority to publicise the Master Plan and to answer what the public says. Under s.13(1), the plan returned by the State Government 'shall thereupon publish, by notification, the plan and the reports inviting public comments within sixty days'. Under s.13(2), the Planning Authority 'shall consider such comments and resubmit' the plan with recommended changes 'in the light of the public comments'. Section 10(1)-(2) adds a mandatory earlier step: the declaration of intention is published 'calling suggestions from the public within a period of sixty days', and the Planning Authority 'shall consider such suggestion'. Under s.13-A(1), the s.13 procedure also applies to Interim Master Plans. All of these are 'shall' duties covering scrutiny, comments and the response, so Part B is met (2.5). For Bengaluru, GBA Act s.14(2)(a) (ULG-01) makes the Greater Bengaluru Authority (GBA) the 'Planning Authority' under the KTCP Act for the Greater Bengaluru Area. ULG-03, a 2025 amendment Bill (inserting s.81-G), says the same, but it is the Bill as passed by the Assembly and I have not confirmed it is in force. PART A = BLANK (not found; affirmative absence not shown). What I checked: (1) KTCP Act ss.9, 10, 12, 13 and 13-A (ULG-02). No ward committee, ward sabha or area sabha appears in the Master Plan procedure. (2) ULG-03, the KTCP Amendment Bill 2025. It covers the Commissionerate and the GBA as Planning Authority. It has no participation provisions. (3) BDA Act ss.17-18 (ULG-04). These cover development schemes, with representations from 'the Corporation' and notices to affected owners. That is not ward-level scrutiny of the Master Plan, and since the GBA was set up the BDA is no longer the Planning Authority for the Greater Bengaluru Area. (4) GBA Act s.103(1)(b)-(c) (ULG-01). The Ward Sabha meets only 'for providing inputs for the formulation of the Annual Ward Development Plan', which is a budget priority list. It is not scrutiny of the Master Plan. Section 103(1)(d) lets the Ward Committee call general meetings on any issue, but that is a general power, not a requirement to scrutinise the city plan. I did not use the BBMP Act 2020 (ULG-19), which had Area Sabhas: it is a BBMP-era law that the GBA Act replaced. Why Part A is blank and not NO: (a) The GBA Act clause on the Bengaluru Metropolitan Planning Committee's draft development plan (s.14(2)(c)) is cut off at 'shall prepare a draft development plan ... and disc...' in every excerpt I could get, so I could not check it for a ward-level consultation step. (b) The KTCP Rules, which set the 'prescribed manner' of publication under ss.9, 10 and 13(4), are not in the Citation Sheet. A reviewer should read the full s.14(2)(c) and the KTCP Rules. If neither requires ward committee or area sabha scrutiny, Part A = NO (0) and the total = 2.5/5. If either does, Part A = YES and the total = 5/5. Other notes: The Step 2 answer is consistent with the source. The KTCP text I used goes only to 2015 (PRS compilation, a secondary source), and later amendments are not in the Citation Sheet. | R32: The citation didn't settle every input. "Part A: Formal platforms (ward committees / area sabhas)" left blank: the Citation Sheet doesn't decide it.
A33: UPD11a | B33: Surat | C33: Is there public scrutiny for (including objections and responses) municipal/city plan? >:< Does the law mandate public scrutiny for (including objections and responses) municipal/city plan through Area Sabhas / Ward Sabhas and other means? | D33: =IFERROR(UPD11a!L33,"") | E33: 10 >:< 5 | H33: =IF(OR(F33="",NOT(ISNUMBER(D33))),"",IF(ABS(F33-D33)<0.001,"Yes","No")) | I33: =IF(ISNUMBER(F33),F33,D33) | J33: =IF(ISNUMBER(F33),"Expert (overrides AI)",IF(ISNUMBER(D33),"AI","Not scored yet")) -> Not scored yet | K33: Left for a person | L33: Partially Answered | M33: ANSWER: Part B (other means): yes. The Gujarat planning framework requires the public to be able to examine the development plan and send objections, which must be considered. Under Rules 1979 r.5, the authority shall publish the draft development plan in the Official Gazette and in Gujarati newspapers and put notices up at its office. Any member of the public may send written objections or suggestions within two months, and the authority 'shall consider' them. Rule 6 adds a second round of notice and objections when the draft is changed substantially, first by the planning authority and then by the State Government. Part A (Ward Committees / Area Sabhas): not found. The Rules give only gazette, newspaper and posted notices. No part of the Citation Sheet I read ties plan scrutiny to Ward Committees or Area Sabhas. But the main sections of the Town Planning Act, the Ward Committees' functions under the Municipal Corporations Act, and any Area Sabha law were not all available or read, so I cannot treat this as a confirmed absence. Note on who plans: the Surat development plan is prepared by the Surat Urban Development Authority (SUDA) and sanctioned by the State Government. The Surat Municipal Corporation (SMC) prepares Town Planning Schemes. | EVIDENCE: (1) Gujarat Town Planning and Urban Development Rules, 1979 (ULG-04): r.5(1): the authority 'shall... cause the development plan also published by means of a notice in the Official Gazette, and in one or more Gujarati newspaper | N33: Gujarat Town Planning and Urban Development Rules, 1979 (copy hosted by Surat Urban Development Authority) [ULG-04] | O33: https://www.sudaonline.org/wp-content/uploads/2013/08/GTPUD-Rules-1979.pdf | P33: Every notice published under sub -rule (1) shall in pursuance of the provisions of section 13 announce that i f within two months from the date of publication of the notice in the Official Gazette any member of the public communicates in writing to the area development authority or as the case may be to the authorized officer, his objections or suggestions with re spect to the development plan, the development authority or as the case may be the authorized officer shall consider such objections or suggestions and may modify such plan as it/he thinks fit. | Q33: PART B = YES (worth 2.50). The Gujarat Town Planning and Urban Development Rules, 1979 (ULG-04) set out a public scrutiny process for the draft development plan under GTPUD Act s.13. Under r.5(1), the plan 'shall' be published by notice in the Official Gazette and in Gujarati newspapers, and copies are pasted at the head office and at prominent places. Under r.5(2), any member of the public may send objections or suggestions in writing within two months, and the authority 'shall consider' them. Rule 6 adds another round of notice and objections when the planning authority or the State Government makes substantial changes. Form A says objections received 'from any person' 'shall be considered'. This is a binding rule ('shall'), so it meets Part B ('other means', including scrutiny or objections where no mode is specified). I checked this against the source text, and the Step 2 answer is supported. Two limits: changing the plan after objections is only 'may modify', and no written reply to each objector is required. The methodology only asks for scrutiny including objections and responses, and mandatory consideration meets that. The Act's own s.13 text is not readable in the PRS copy (ULG-01). In that copy, the 2019 amendments (new s.10B in the MPC Act / DPC Act) also require Gazette notice inviting objections 'from any person' on changes to a final development plan. PART A = blank (not found; absence not confirmed). The Rules 1979 provide only Gazette, newspaper and posted notices. Ward Committees and Area Sabhas are not mentioned in r.5, r.6 or r.17-18. A search of the Citation Sheet for 'ward committee area sabha' found no provision tying plan scrutiny to ward-level forums. But GPMC Act s.29A(8) (ULG-03) says the State Government 'shall by rules define the functions and duties of the Wards Committee'. Those Ward Committee rules are not in the Citation Sheet, and neither is any Gujarat Area Sabha / Community Participation law or the full main text of GTPUD Act s.13-17. So affirmative absence cannot be shown, and NO cannot be entered. What I checked: ULG-04 (Rules r.3-6, r.16-18, Forms A/B); ULG-01 (amendments of 2017 and 2019, including MPC/DPC s.10B); ULG-03 (s.29A, s.284F); a sheet-wide search for ward committee / area sabha. A reviewer should get the Gujarat Wards Committee rules made under GPMC s.29A(8). If those rules give Ward Committees no role in scrutinising plans, Part A = NO, and the total would be 2.50 out of 5. Scope note: the statutory development plan for Surat is prepared by SUDA and sanctioned by the State, not by SMC. The reviewer should confirm that this counts as the 'municipal/city plan' for the question. GPMC s.284F re-development plans also have notice and objections (the Commissioner 'shall' publish notice; the Standing Committee 'may' modify). | R33: The citation didn't settle every input. "Part A: Formal platforms (ward committees / area sabhas)" left blank: the Citation Sheet doesn't decide it.
A34: UPD11b | B34: Bangalore | C34: Is there public scrutiny for (including objections and responses) municipal/city plan? >:< Was the public scrutiny undertaken for (including objections and responses) municipal/city plan? | D34: =IFERROR(UPD11b!K14,"") | E34: 10 >:< 5 | H34: =IF(OR(F34="",NOT(ISNUMBER(D34))),"",IF(ABS(F34-D34)<0.001,"Yes","No")) | I34: =IF(ISNUMBER(F34),F34,D34) | J34: =IF(ISNUMBER(F34),"Expert (overrides AI)",IF(ISNUMBER(D34),"AI","Not scored yet")) -> Not scored yet | K34: Left for a person | L34: Insufficient Evidence | R34: Step 2 found no evidence: a source needs to be found and added. Step 2 found no evidence (Insufficient Evidence). Source needed: Any of the following, from BDA, GBA or a city corporation, or from the Karnataka eGazette: (a) the Gazette or newspaper notice publishing the draft master plan (RMP 2015, or the draft RMP 2041 / Greater Bengaluru Area plan) and inviting public comments under s.13(1) of the Town and Country Planning Act, or the s.10(1) notice of intention calling for suggestions; (b) a record of objections received and how they were dealt with (a report on objections, hearing minutes, or the Planning Authority's recommendations to the State under s.13(2)); (c) the final approved master plan or approval GO describing the public scrutiny; (d) dated official consultation notices or minutes on the BDA or GBA website.
A35: UPD11b | B35: Surat | C35: Is there public scrutiny for (including objections and responses) municipal/city plan? >:< Was the public scrutiny undertaken for (including objections and responses) municipal/city plan? | D35: =IFERROR(UPD11b!K33,"") -> 5 | E35: 10 >:< 5 | H35: =IF(OR(F35="",NOT(ISNUMBER(D35))),"",IF(ABS(F35-D35)<0.001,"Yes","No")) | I35: =IF(ISNUMBER(F35),F35,D35) -> 5 | J35: =IF(ISNUMBER(F35),"Expert (overrides AI)",IF(ISNUMBER(D35),"AI","Not scored yet")) -> AI | K35: Scored by AI | L35: Answered — Verified Source | M35: ANSWER: Yes. Surat's city plan is the Development Plan 2035 of the Surat Urban Development Authority (SUDA). SUDA, not the municipal corporation, prepared it under the Gujarat Town Planning and Urban Development Act, 1976, and it covers the Surat Municipal Corporation area. The draft went through public scrutiny. It was published in the Official Gazette under s.13 on 10 May 2016 and in a Gujarati daily on 11 May 2016, inviting suggestions and objections from the public for two months. The State Government then told SUDA to submit the plan together with the suggestions and objections received. SUDA also held separate stakeholder consultations: about 60 committee meetings, meetings with sarpanchs of 95 villages, and a 22.04.2016 meeting with MPs, MLAs and the SMC Mayor that produced 136 recorded suggestions. | EVIDENCE: ULG-06 (SUDA Development Plan 2035 report, 22 Feb 2017), Ch.21, p.216: the draft was 'published in the Official G azette the on 10 th May 2016 under section 13 for inviting public opinion'. The newspaper notice of 11 May 2016 invited 'suggestions and objections from the general public'. Under s.14, SUDA 'has to submit the Draft Development Plan - 2035 to the State Government along with opinion on such objections and suggestions'. Ch.21, p.217: by letter dated 21.11.2016, UD&UHD told SUDA to submit the draft 'along with the sugge stions and objections received for the proposals on the Draft Development plan - 2035 published u/s 13'. Ch.16 (pp.165-167), Stakeholde | N35: Development Plan 2035 (report, 22 February 2017), Surat Urban Development Authority [ULG-06] | O35: https://www.sudaonline.org/wp-content/uploads/2017/03/SUDA-DP-2035-report-final-22.02.2017.pdf | P35: As per the statutory requirement the same was published in the Official G azette the on 10 th May 2016 under section 13 for inviting public opinion. The notice was also issued in the prescribed manner in the Gujarati daily on 11th May, 2016 inviting suggestions and objections from the general public within the statutory time limi ts of two months. | Q35: This sub-question asks about implementation: was public scrutiny actually carried out? The methodology says to score 5 if there is evidence of public scrutiny in the Development Authority's or ULG's material, including the plan itself. I checked the Step 2 answer against ULG-06 (SUDA Development Plan 2035 report, dated 22 Feb 2017), and the report supports it. What the report shows: (1) The draft DP 2035 was published in the Official Gazette under s.13 on 10 May 2016. A notice in a Gujarati daily on 11 May 2016 invited suggestions and objections from the public within two months (p.216). (2) Under s.14, SUDA had to submit the draft to the State Government together with its opinion on those objections and suggestions (p.216). (3) In a letter dated 21.11.2016, UD&UHD told SUDA to submit the draft 'along with the suggestions and objections received for the proposals on the Draft Development plan - 2035 published u/s 13' (p.217). This shows objections were actually received, not just invited. (4) Ch.16 records stakeholder consultation: about 60 committee meetings, meetings with sarpanchs of 95 villages, institutional consultations, and a 22.04.2016 meeting with MPs, MLAs and the SMC Mayor at which 136 suggestions were tabulated (pp.165-167). On that basis the answer is YES (5 points). Points for the reviewer: (a) SUDA prepared the plan, not the Surat Municipal Corporation. SUDA is a state development authority and its plan covers the SMC area. The methodology allows 'Development Authority/ULG websites (as applicable)', but please confirm that the SUDA DP counts as the municipal/city plan for this ULG. (b) For the 'responses' part, the evidence is only the s.14 duty to give an opinion on objections and the state's direction to forward the objections received. The Citation Sheet has no itemised register of objections with a response to each. (c) The Citation Sheet also does not contain the original 2016 s.13 gazette notice, the newspaper notice, or the 08.10.2020 sanction notification. The practice evidence is SUDA's own account in the report, an official A2-type source. (d) Period: draft published May 2016; report dated Feb 2017. ULG-17 (2025) shows the plan is still current and that a s.19(1) variation is open for objections, but that is the state's own process. Era: n/a.
A36: UPD12 | B36: Bangalore | C36: Does the law mandate periodic review and revision of the notified municipal/city plan, including corresponding revisions to the Development Control Regulations (DCRs)? | D36: =IFERROR('UPD12'!N14,"") -> 7.5 | E36: 10 | H36: =IF(OR(F36="",NOT(ISNUMBER(D36))),"",IF(ABS(F36-D36)<0.001,"Yes","No")) | I36: =IF(ISNUMBER(F36),F36,D36) -> 7.5 | J36: =IF(ISNUMBER(F36),"Expert (overrides AI)",IF(ISNUMBER(D36),"AI","Not scored yet")) -> AI | K36: Scored by AI | L36: Answered — Verified Source | M36: ANSWER: Only in part. Section 13-D of the Karnataka Town and Country Planning Act (KTCP Act) gives a revision timeline ('at least once in every ten years') and names the body responsible (the Planning Authority, or the State Government by direction). Revision is not mandatory, though: the Planning Authority 'may' revise, and 'shall' only 'if directed so by the State Government'. When a revision does happen, sections 9 to 12 apply to it. Section 12 makes Zoning Regulations, zone-wise regulations and building-line, height and FAR controls part of the Master Plan, so a revised plan has to carry revised development regulations. Under the Greater Bengaluru Governance Act (GBG Act), the Greater Bengaluru Authority (GBA) is the Planning Authority for the Greater Bengaluru Area. | EVIDENCE: (1) KTCP Act s.13-D 'Revision of Master Plan' (inserted by Amendment Act 2004; PRS compilation p.34-35 and p.119): 'At least once in every ten years ... the Planning Authority may and if directed so by the State Government shall, carryout a fresh survey ... with a view to revising the existing Master Plan and the provisions of section 9 to section 12 (both inclusive) shall mutatis mutandis apply in respect of such revision'. (2) KTCP Act s.12(1)(a): the Master Plan 'shall include proposals for ... zoning of land use ... together with Zoning Regulations'. s.12(1)(f): areas of special control subject to regulations on 'building line, height of the building, floor area ratio'. s.12(2)(iii): 'regulati | N36: The Karnataka Town and Country Planning Act, 1961 (Karnataka Act 11 of 1963), PRS compilation with amendments up to Act 38 of 2015 [ULG-02] | O36: https://prsindia.org/files/bills_acts/acts_states/karnataka/1963/1963KR11.pdf | P36: At least once in every ten years from the date on which the Master Plan has come into force, subject to the provisions of section 13-C, the Planning Authority may and if directed so by the State Government shall, carryout a fresh survey of the area within its jurisdiction, with a view to revising the existing Master Plan and the provisions of section 9 to section 12 (both inclusive) shall mutatis mutandis apply in respect of such revision of the Master Plan. | Q36: The inputs add up to 7.5 of 10 (C2 + C3 + C4 at 2.5 each). I checked the Step 2 answer against the source text, and it holds. C1, periodic review mandated = NO: This NO rests on a provision I found and read, not on a gap in the evidence. Under KTCP Act s.13-D the Planning Authority 'may' revise the plan. It 'shall' revise only 'if directed so by the State Government'. The law therefore allows periodic revision but does not require it. The methodology also says that ten-year wording about revision should not count for C1. Other provisions I checked do not create a periodic duty either: - s.13-B proviso: 'shall revise', but only when an additional area is added or the State directs. That is triggered by an event, not periodic. - s.13-E: the State Government 'may' amend regulations. Discretionary. - GBG Act 2024 (ULG-01), Planning Functions sub-section (2)(a): makes the GBA the Planning Authority under the KTCP Act. Its s.315(l) only lets the GBA make regulations on Master Plan contents. Neither sets up a revision cycle. - 2025 KTCP Amendment Bill (ULG-03): inserts s.81-G and amends s.2(7) and s.81-B. It does not touch s.13-D. The KTCP Rules are not in the Citation Sheet, so I could not check them. The methodology points to the State Town Planning Act. C2, timeline = YES: s.13-D says 'At least once in every ten years from the date on which the Master Plan has come into force'. C3, responsible authority = YES: s.13-D names the 'Planning Authority', with the State Government able to direct it. Under GBG Act Planning Functions (2)(a), the GBA is the Planning Authority for the Greater Bengaluru Area. ULG-03 would make this explicit through s.81-G, but there is no evidence it has been enacted. C4, matching DCR revision = YES, by reading two sections together: s.13-D says ss.9 to 12 'shall mutatis mutandis apply' to a revision. Under s.12(1)(a) the Master Plan 'shall include proposals for ... zoning of land use ... together with Zoning Regulations'. Under s.12(1)(f) it covers regulations on building line, height and FAR. Under s.12(2)(iii), 'regulations in respect of each land use zone to enforce the provisions of such plan' must be published with the plan. A revised plan must therefore come with revised zoning regulations. For the reviewer to check: (a) Whether the s.12 Zoning Regulations count as 'DCRs' under the rubric. The Act never uses the words 'Development Control Regulations'. If they do not count, the score drops to 5. (b) Whether C2 and C3 can be credited even though revision is not mandatory (C1 not met). (c) Whether s.13-D was amended after the PRS compilation (amendments up to Act 38 of 2015). The PRS copy is a secondary source, so an official consolidated text should be checked.
A37: UPD12 | B37: Surat | C37: Does the law mandate periodic review and revision of the notified municipal/city plan, including corresponding revisions to the Development Control Regulations (DCRs)? | D37: =IFERROR('UPD12'!N33,"") | E37: 10 | H37: =IF(OR(F37="",NOT(ISNUMBER(D37))),"",IF(ABS(F37-D37)<0.001,"Yes","No")) | I37: =IF(ISNUMBER(F37),F37,D37) | J37: =IF(ISNUMBER(F37),"Expert (overrides AI)",IF(ISNUMBER(D37),"AI","Not scored yet")) -> Not scored yet | K37: Left for a person | L37: Partially Answered | M37: ANSWER: Not established from the Act's own text. The only source in the Citation Sheet that addresses this is SUDA's Development Plan 2035 report. It says section 21 of the Gujarat Town Planning and Urban Development Act, 1976 (GTPUD Act) requires the development plan to be revised once in 10 years. This would suggest a fixed revision timeline, with the area development authority (here the Surat Urban Development Authority, SUDA) preparing the revision and the State Government sanctioning it. I could not read section 21 itself, so I cannot confirm its wording ('shall' or 'may'), the responsible authority, or whether it also requires the regulations (DCRs) to be revised. I found no source in the Sheet that requires the DCRs to be revised after a plan revision. | EVIDENCE: (1) ULG-06, SUDA Development Plan 2035 report (22-02-2017), p.40 (also p.30): 'As per the provisions of section 21 of the Act, the development plan is to be revised once in 10 years'. It records the plan history: first plan in force 1986, revised plan in force 15-09-2004, then DP-2035. This is a planning body describing the law, not the statute. (2) ULG-01, GTPUD Act 1976 (PRS copy with amendments): the passages I could retrieve were only the 2017 and 2019 amending Acts. The 2019 Act inserted s.19A: the appropriate authority 'shall include' the spatial proposals of District/Metropolitan Planning Committee plans 'by varying the development plan under section 19'. The text of s.21 did not come up in any search. | N37: Development Plan 2035 (report, 22 February 2017), Surat Urban Development Authority [ULG-06] | O37: https://www.sudaonline.org/wp-content/uploads/2017/03/SUDA-DP-2035-report-final-22.02.2017.pdf | P37: As per the provisions of section 21 of the Act, the development plan is to be revised once in 10 years | Q37: I left all four inputs blank. The deciding provision, s.21 of the Gujarat Town Planning and Urban Development Act 1976 (GTPUD Act), cannot be read anywhere in the Citation Sheet. (1) ULG-01 (PRS copy of the GTPUD Act): I read it from the start. The principal Act is on pages 2-86, and those pages are a scan with no readable text; they came back empty. The only readable text is the amending Acts: Act 6 of 2017 (s.51), Act 22 of 2017 (ss.7, 23, 49, 52, 76A, 119) and Act 14 of 2019 (ss.9, 12, new s.19A, plus the DPC/MPC Acts). None of these amends or restates s.21. So the verb ('shall' or 'may'), the timeline, the responsible authority and any link to the regulations cannot be checked against the statute. This is a VERIFICATION-LIMIT, not a negative finding. (2) ULG-06 (SUDA Development Plan 2035 report, 2017) is the only source. It says three times (pp.30, 40, 203) that under s.21 'the development plan is to be revised once in 10 years'. That is a planning body summarising the law, not the law itself. I don't treat it as enough to say the Act mandates a review, sets a timeline or names an authority. There is also a methodology question for a human to decide. Component 1 says a provision 'alluding to the revision or creation of a new plan say after ten years' shall not be considered. So even a confirmed 'revise at least once in ten years' rule may not earn component 1, though it would still count toward the timeline component (component 2). (3) Corresponding DCR revision: I can't record NO. Affirmative absence isn't met because the s.21 text, which may refer to 'development plan and regulations', was not readable. What I checked: - ULG-04 (GTPUD Rules 1979): r.6/7 cover sanction of the draft development plan 'and the regulations' under ss.16-17, and r.36 covers variation of TP scheme regulations. I found no periodic-revision rule. - ULG-05 / ULG-14 (CGDCR 2017): my searches found no clause tying DCR revision to plan revision. - ULG-17 (Gazette, 24 March 2025): a one-off variation under s.19(1), not a periodic review. - ULG-03 (Gujarat Provincial Municipal Corporations Act 1949): I found no periodic city-plan revision. Note: Surat's development plan is prepared by SUDA (the Surat Urban Development Authority) and sanctioned by the State Government; Surat Municipal Corporation is not the planning authority. ACTION: add a readable official copy of the GTPUD Act 1976 (the UD&UHD or Legislative Department text) to the Sheet, then re-score from s.21 and any related provision on the regulations. | R37: The citation didn't settle every input. "Periodic review & revision mandated" left blank: the Citation Sheet doesn't decide it. "Review/revision timeline specified" left blank: the Citation Sheet doesn't decide it. "Responsible authority specified" left blank: the Citation Sheet doesn't decide it. "Corresponding DCR revision required" left blank: the Citation Sheet doesn't decide it.
A38: UPD13a | B38: Bangalore | C38: Does the T&CP Act mandate the planning for: >:< a) Water Supply/ Sewerage, Sanitation and Solid Waste Management | D38: =IFERROR(UPD13a!M14,"") | E38: 10 >:< 1.67 | H38: =IF(OR(F38="",NOT(ISNUMBER(D38))),"",IF(ABS(F38-D38)<0.001,"Yes","No")) | I38: =IF(ISNUMBER(F38),F38,D38) | J38: =IF(ISNUMBER(F38),"Expert (overrides AI)",IF(ISNUMBER(D38),"AI","Not scored yet")) -> Not scored yet | K38: Left for a person | L38: Partially Answered | M38: ANSWER: Only one of the three components has any support in the Citation Sheet, and even that one has a mismatch. (3) Solid waste: the Greater Bengaluru Governance Act requires a block-level solid waste management plan. Section 279 says the City Corporation 'shall' create one for every block in a ward. But the Act names the Greater Bengaluru Authority (GBA) as the Planning Authority, not the City Corporations, and these are ward/block operating plans rather than a city-level SWM plan or a part of the master plan. (1) Water supply/sewerage and (2) City sanitation: none of the sheet's sources makes such a plan, or such a part of the master plan, mandatory for the planning authority. However, some relevant instruments are not in the sheet, so this is 'not found' rather than a confirmed absence. | EVIDENCE: Karnataka Town and Country Planning Act (KTCP) s.12(1), what a Master Plan must contain (Act 1 of 2005 text): 'such plan shall include proposals for' (a) land-use zoning, (b) street pattern and traffic, (c) parks, public buildings and civic uses, (d) future development areas, (e) land reserved for government, the Planning Authority or 'public utility undertaking', (f) special control areas and (g) stages. Water supply, sewerage, sanitation and solid waste are not listed. s.12(3) adds heritage only. KTCP s.26(2), town planning schemes: a scheme 'may make provisions for' (f) drainage inclusive of sewerage and sewage disposal and (h) water supply. This is optional ('may') and doe | N38: The Greater Bengaluru Governance Act, 2024 (Karnataka Act No. 36 of 2025), as enacted, PRS copy of the Gazette text (DPAL notification dated 24.04.2025) [ULG-01] | O38: https://prsindia.org/files/bills_acts/acts_states/karnataka/2025/Act36of2025KA.pdf | P38: The City Corporation shall create a solid waste management plan for every block in a Ward | Q38: I left all three inputs blank. The Step 2 answer matches the sources, and I checked it again. (1) Water supply/sewerage, and (2) City sanitation: no 'shall' provision found. - KTCP Act s.12(1) (ULG-02, PRS text with amendments up to Act 38 of 2015, s.12 as substituted by Act 1 of 2005) says the Master Plan 'shall include proposals for' items (a)-(g). These are zoning, streets/traffic, parks and civic uses, future expansion, land reserved for government or a 'public utility undertaking', special control areas, and stages. Water supply, sewerage, sanitation and SWM are not listed. Reserving land for a utility is not a requirement to plan the service. s.12(3) covers heritage only. - KTCP s.26(2)(f) (drainage/sewerage) and s.26(2)(h) (water supply) say a town planning scheme 'may make provisions for' these. That is a 'may' provision, so it does not count. - BDA Act s.16(1)(c) (ULG-04) requires drainage and water supply, but only inside development schemes that are themselves optional under s.15(1) ('may'). Sanitary arrangements under s.16(2)(c) are 'may'. ULG-03 (KTCP Amendment Bill 2025) makes the Greater Bengaluru Authority (GBA) the Planning Authority for the Greater Bengaluru Area (new s.81-G, revised s.2(7)) and moves BDA outside that area. So BDA schemes no longer cover this ULG. The Bill does not change s.12's list of contents. - GBA Act s.15(1) requires only a 'master plan and mobility plans'. s.14(4) is coordination of BWSSB and the solid waste corporation, not a plan. s.103(1)(h)-(j) are ward committee maintenance duties, and their recommendations are advisory (s.103(4)). - I searched the sheet again for water supply, sanitation or sewerage plan duties and found none. - Why not NO: not every relevant instrument is in the Citation Sheet. Missing are the KTCP Rules, any KTCP amendments after 2015 other than ULG-03, the GBA Act Rules, the BWSSB Act 1964, and the BMRDA Act. So this is 'not found', not confirmed absence. A 0 needs affirmative absence, so I cannot enter NO. (3) SWM: there is a 'shall' provision, but whether it fits the rubric needs a reviewer's call. - GBA Act s.279(1) says the City Corporation 'shall create a solid waste management plan for every block in a Ward'. s.278(2) says ward committees 'shall prepare Ward action plan' for SWM. - Problem 1: the methodology wants a mandate on 'the planning authority'. Under s.14(2)(a), GBA is the Planning Authority, not the City Corporations. - Problem 2: these are block/ward operating micro plans (collection times, vehicles, street sweeping, staff), not a city-level SWM plan or an SWM part of the master plan. - Following the Step 2 request for confirmation, I left this blank rather than guess. If the reviewer accepts a duty on the City Corporations (part of the ULG) and ward/block micro plans as an 'SWM Plan', enter YES (0.55). Otherwise NO can only be confirmed once the missing instruments above have been read. Period: GBA era. GBA Act as enacted (Karnataka Act 36 of 2025, DPAL notification 24.04.2025). ULG-19 (BBMP Act 2020 s.293) is the earlier BBMP-era version of the same provision and was not relied on. | R38: The citation didn't settle every input. "Water supply / sewerage" left blank: the Citation Sheet doesn't decide it. "City sanitation" left blank: the Citation Sheet doesn't decide it. "Solid waste management" left blank: the Citation Sheet doesn't decide it.
A39: UPD13a | B39: Surat | C39: Does the T&CP Act mandate the planning for: >:< a) Water Supply/ Sewerage, Sanitation and Solid Waste Management | D39: =IFERROR(UPD13a!M33,"") | E39: 10 >:< 1.67 | H39: =IF(OR(F39="",NOT(ISNUMBER(D39))),"",IF(ABS(F39-D39)<0.001,"Yes","No")) | I39: =IF(ISNUMBER(F39),F39,D39) | J39: =IF(ISNUMBER(F39),"Expert (overrides AI)",IF(ISNUMBER(D39),"AI","Not scored yet")) -> Not scored yet | K39: Left for a person | L39: Partially Answered | M39: ANSWER: Not determined, so no score. The only Citation Sheet passage on what a development plan must contain is a paraphrase of Section 12(2) of the Gujarat Town Planning and Urban Development Act, 1976 (GTPUD Act) in SUDA's Development Plan 2035 report. It says the draft development plan 'shall provide for all or any of' a list of purposes. One item is 'proposals for water supply, drainage, sewage disposal'. I could not read the Act's own Section 12 text. 'All or any' also lets the planning authority choose which items to include. So I cannot confirm a binding duty for any of the three components: (1) water supply/sewerage, (2) sanitation, (3) solid waste management. Solid waste does not appear in the clauses I could read, (a) to (f); clause (g) and later clauses were cut off. | EVIDENCE: (i) ULG-06, SUDA Development Plan 2035 report (22 Feb 2017), p.195-196, s.19.11.5: 'As per provisions of section 12(2) of the Act, the draft development plan shall provide for all or any of the following public purposes', including '(c) proposals for water supply, drainage, sewage disposal, other public utility amenities and services...' and '(f) proposals for flood control and prevention of river pollution'. This is the planning authority describing the Act, not the Act itself. SUDA's report (p.16) also lists 'Solid Waste Management' and 'Utility services for water supply, sewerage, drainage' as parts it planned for. That is practice, not a legal mandate. (ii) ULG-01, GTPUD Act 1976 (PRS c | N39: Development Plan 2035 (report, 22 February 2017), Surat Urban Development Authority [ULG-06] | O39: https://www.sudaonline.org/wp-content/uploads/2017/03/SUDA-DP-2035-report-final-22.02.2017.pdf | P39: As per provisions of section 12(2) of the Act, the draft development plan shall provide for all or any of the following public purposes: | Q39: All three inputs are left blank. Nothing has been scored. Reasons: (1) The only primary instrument that could carry the mandate is GTPUD Act 1976 Section 12 (ULG-01, PRS copy). Its principal-Act pages (PDF pp.2-86) come back with no text at all; they look like scanned images. Only the appended amending Acts can be read: 6 of 2017, 22 of 2017 and 14 of 2019. The 2019 Act changes s.9(1) and s.12(1) and adds s.19A, which requires spatial proposals from the plans of the Metropolitan or District Planning Committee. None of these amendments sets content for water, sanitation or solid waste. So the Act's own Section 12 text was not read. (2) The only text of s.12(2) is SUDA's paraphrase in the DP 2035 report (ULG-06). That is a secondary account by the planning authority, not the Act. The paraphrase says 'shall provide for all or any of the following'. 'All or any' arguably makes this a menu the authority can pick from, and the methodology does not count optional provisions. Even if it does count as a mandate, clause (c) covers water supply, drainage and sewage disposal. That would support Water supply / sewerage. Whether it also covers 'City sanitation' is a judgement call. Solid waste or refuse does not appear in clauses (a) to (f). Clause (g) and the later clauses are cut off in what could be read, so absence cannot be confirmed. (3) Other instruments checked: GTPUD Rules 1979 (ULG-04). The parts I could read cover the layout plan (r.13), the s.39 documents, Forms C to P and budget forms. I found no list of development plan contents. GPMC Act 1949 (ULG-03): s.63 makes sewage, rubbish and solid waste management services an obligatory duty of the Corporation. That is a duty to provide services, not a duty to plan, so it is not credited. CGDCR 2017 (ULG-05, ULG-14 to ULG-16): building-level rules only. DP 2035 p.16 shows that SUDA did plan for water supply, sewerage and solid waste management. That is practice, not a legal mandate. (4) Because the s.12 Act text was not read and the clauses from (g) onward are missing, a 'NO' would not meet the affirmative-absence test, and a 'YES' would rest only on a secondary paraphrase with ambiguous wording. FOR HUMAN REVIEWER: get a readable official text of GTPUD Act s.12(2), for example from the UD&UHD or Legislative Department, or a gazette copy. Then decide three things: (a) whether 'shall provide for all or any of' counts as a mandate; (b) whether 'sewage disposal' or 'drainage' satisfies the sanitation component; (c) whether any later clause mentions refuse or solid waste. I could not read the end of clause list (g) onward because I hit the tool-call limit. | R39: The citation didn't settle every input. "Water supply / sewerage" left blank: the Citation Sheet doesn't decide it. "City sanitation" left blank: the Citation Sheet doesn't decide it. "Solid waste management" left blank: the Citation Sheet doesn't decide it.
A40: UPD13b | B40: Bangalore | C40: Does the T&CP Act mandate the planning for: >:< b) Disaster Resilience | D40: =IFERROR(UPD13b!K14,"") | E40: 10 >:< 1.67 | H40: =IF(OR(F40="",NOT(ISNUMBER(D40))),"",IF(ABS(F40-D40)<0.001,"Yes","No")) | I40: =IF(ISNUMBER(F40),F40,D40) | J40: =IF(ISNUMBER(F40),"Expert (overrides AI)",IF(ISNUMBER(D40),"AI","Not scored yet")) -> Not scored yet | K40: Left for a person | L40: Partially Answered | M40: ANSWER: The Karnataka Town and Country Planning Act does not require a disaster management or resilience part in the master plan. One law does require a disaster plan. Section 270(3) of the Greater Bengaluru Governance Act, 2024 says each City Corporation 'shall' prepare a Disaster Management Plan or a Fire Hazard Response and Mitigation Plan every year, after previous publication, and publish it in the Official Gazette. That duty falls on the City Corporations. It does not fall on the Greater Bengaluru Authority (GBA), which the same Act makes the planning authority. It is also a separate yearly plan, not part of the master plan. So whether this meets the test of 'mandate the planning authority' or a 'disaster component of the municipal/city plan' depends on how the method is read, and I have not scored it. | EVIDENCE: (1) Karnataka Town and Country Planning Act, 1961 (ULG-02, PRS compilation with amendments up to Act 38 of 2015). Section 12(1), contents of the master plan, lists clauses (a) to (g): land-use zoning with zoning regulations; street pattern; parks and open spaces; areas for future development; reservations for public purposes; areas of special control; and stages. Section 12(2) lists the reports to be sent with the plan, and section 12(3) covers heritage buildings and precincts. None of these mentions disaster, hazard, flood or resilience. Section 13-A(3) (interim master plan) and section 26(2) (town planning schemes, a 'may' list) also have no disaster provisi | N40: The Greater Bengaluru Governance Act, 2024 (Karnataka Act No. 36 of 2025), as enacted, PRS copy of the Gazette text (DPAL notification dated 24.04.2025) [ULG-01] | O40: https://prsindia.org/files/bills_acts/acts_states/karnataka/2025/Act36of2025KA.pdf | P40: (3) The City Corporation shall prepare a Disaster Management Plan or Fire Hazard Response and Mitigation Plan every year as prescribed by the State Government after previous publication and publish the Plan in the Official Gazette. | Q40: I left 'Answer' blank. A person needs to decide how to read the method; I have not guessed. (1) What the planning law says. The Karnataka Town and Country Planning (KTCP) Act, 1961 is in the Citation Sheet as ULG-02, a PRS compilation with amendments up to Act 38 of 2015. I re-read it. - Section 12(1), contents of the master plan, lists clauses (a) to (g): zoning, street pattern, parks and open spaces, future development, public-purpose reservations, special control areas and stages. None of them is about disaster, hazard, flood or resilience. - Section 26(2) on town planning schemes uses 'may'. Clause (b), 'filling up or reclamation of low-lying, swamp or unhealthy areas', is optional and is not a disaster plan. - The Bangalore Development Authority Act, 1976 (ULG-04, with amendments up to 42/2026) has no disaster or resilience planning provision in the passages I read. Those passages covered s.18-19 on schemes, s.51 on the Art Commission, s.69-70 on rules and regulations, and the 2020 amendment. That amendment only bars allotting land near storm water drains, tank beds and similar areas. That is a land-allotment limit, not a planning mandate. (2) The only mandatory provision found is in an allied Act. Section 270(3) of the Greater Bengaluru Governance (GBA) Act, 2024 says the City Corporation 'shall prepare a Disaster Management Plan or Fire Hazard Response and Mitigation Plan every year'. I did not mark this YES, for three reasons: - (a) The method asks for a duty on 'the planning authority'. The same Act's Planning Functions provision makes the Greater Bengaluru Authority (GBA) the Planning Authority under the KTCP Act, not the City Corporations. Section 17 gives the GBA a Climate Action Cell to 'formulate and implement' the Bengaluru Climate Action and Resilience Plan (BCAP). But that duty is to set up a cell, and the BCAP is a climate plan, not a statutory disaster plan or a part of the master plan. - (b) The duty is worded 'or'. A Fire Hazard Response and Mitigation Plan alone would satisfy it, and that is narrower than a disaster resilience plan. - (c) It is a separate yearly plan, not a disaster part of the master or city plan. If the reviewer accepts a 'shall' duty on the ULG (the City Corporation) under an allied municipal Act as meeting the test, the answer should be YES (1.67). (3) Why I cannot answer NO. Several layers are not in the Citation Sheet, so I cannot show the provision is absent: - the KTCP Rules and Zoning Regulations - KTCP amendments after 2015 (ULG-03 is a 2025 bill that has not been shown to be enacted) - the BMRDA Act - the Karnataka Urban Development Authorities Act - any State rules prescribing the s.270(3) plan The BCAP 2023 (ULG-16, actions UPGBD-2.1 and DM-2.6) recommends adding disaster and vulnerability content to the KTCP Act and the master plan. These are policy recommendations, not law. They hint that no mandate exists, but they do not prove it. All legal texts here are PRS republications, not the official Gazette. The GBA Act's commencement date is not confirmed in the Citation Sheet. | R40: The citation didn't settle every input. "Answer" left blank: the Citation Sheet doesn't decide it.
A41: UPD13b | B41: Surat | C41: Does the T&CP Act mandate the planning for: >:< b) Disaster Resilience | D41: =IFERROR(UPD13b!K33,"") | E41: 10 >:< 1.67 | H41: =IF(OR(F41="",NOT(ISNUMBER(D41))),"",IF(ABS(F41-D41)<0.001,"Yes","No")) | I41: =IF(ISNUMBER(F41),F41,D41) | J41: =IF(ISNUMBER(F41),"Expert (overrides AI)",IF(ISNUMBER(D41),"AI","Not scored yet")) -> Not scored yet | K41: Left for a person | L41: Insufficient Evidence | R41: Step 2 found no evidence: a source needs to be found and added. Step 2 found no evidence (Insufficient Evidence). Source needed: Readable official text of the Gujarat Town Planning and Urban Development Act, 1976 as amended (s.12, contents of the development plan); the Gujarat State Disaster Management Act, 2003, for any duty on local authorities or planning authorities to prepare disaster plans; the Gujarat Metropolitan Planning Committees Act, 2008, for the contents of the metropolitan development plan; and a full read of the GPMC Act, 1949.
A42: UPD13c | B42: Bangalore | C42: Does the T&CP Act mandate the planning for: >:< c) Comprehensive mobility | D42: =IFERROR(UPD13c!K14,"") -> 1.67 | E42: 10 >:< 1.67 | H42: =IF(OR(F42="",NOT(ISNUMBER(D42))),"",IF(ABS(F42-D42)<0.001,"Yes","No")) | I42: =IF(ISNUMBER(F42),F42,D42) -> 1.67 | J42: =IF(ISNUMBER(F42),"Expert (overrides AI)",IF(ISNUMBER(D42),"AI","Not scored yet")) -> AI | K42: Scored by AI | L42: Answered — Verified Source | M42: ANSWER: Yes. Karnataka law makes mobility planning mandatory for Bengaluru through two instruments. (1) Under the Bengaluru Metropolitan Land Transport Authority (BMLTA) Act, 2022 (the allied Act), the BMLTA 'shall' prepare a Comprehensive Mobility Plan (CMP) for the Urban Mobility Region. The Act sets a time limit and what the plan must contain, and requires a revision at least every five years. Section 22 then says the Planning Authority 'shall' prepare the land use plan in its Master Plan taking the CMP into account 'in its entirety'. The Planning Authority must also consult the BMLTA, and the BMLTA must concur in the draft Master Plan. (2) Under the Karnataka Town and Country Planning (KTCP) Act, 1961, the Master Plan that every Planning Authority 'shall' prepare (s.9(1)) 'shall include' a complete street pattern and a traffic circulation pattern (s.12(1)(b)). That is a mandatory mobility part of the city plan. The Greater Bengaluru Authority (GBA) is the KTCP 'Planning Authority' for the Greater Bengaluru Area. So the city government's Master Plan must carry a mobility component and must line up with the CMP. The CMP itself is prepared by the BMLTA (a state body) and approved by the State Government. | EVIDENCE: BMLTA Act (ULG-18): s.21(1) 'The Authority shall notify its intent to prepare a Comprehensive Mobility Plan'; s.21(2) 'shall cause to prepare a Comprehensive Mobility Plan for the Urban Mobility Region within two years', listing required contents (a)-(m) such as | N42: The Bengaluru Metropolitan Land Transport Authority Act, 2022 (Karnataka Act No. 6 of 2023), PRS republished text with Amendment 10 of 2026 appended [ULG-18] | O42: https://prsindia.org/files/bills_acts/acts_states/karnataka/2023/Act6of2023Karnataka.pdf | P42: The Planning Authority in the Urban Mobility Region shall prepare the land use plan as part of preparation or revision of Master Plan of the city or local planning area by taking into consideration the Comprehensive Mobility Plan in its entirety. | Q42: The answer is YES because Karnataka law requires mobility planning to be done with 'shall', not 'may'. I checked the Step 2 answer against the source text and it holds. (1) Allied Act (ULG-18, the BMLTA Act 2022, Karnataka Act 6 of 2023). Section 21(1) says 'The Authority shall notify its intent to prepare a Comprehensive Mobility Plan'. Section 21(2) says it 'shall cause to prepare a Comprehensive Mobility Plan for the Urban Mobility Region' within two years, and lists what the plan must contain in items (a)-(m): road network, road hierarchy, public transport routes, footpaths and cycle tracks, and accessible mobility. Section 23 requires a revision 'at least once in every five years' ('shall'). Section 22(1) requires the Planning Authority to prepare the land-use part of the Master Plan taking the CMP 'in its entirety' ('shall'). Section 22(2)-(3) requires it to consult the BMLTA and send it the draft Master Plan for concurrence. (2) The KTCP Act itself (ULG-02, s.12(1), as substituted by Act 1 of 2005) says the Master Plan 'shall include proposals for ... (b) a complete street pattern ... and traffic circulation pattern, for meeting immediate and future requirements with proposals for improvements'. That is a required mobility part of the city plan. Either route meets the methodology: a required CMP, or a required mobility component in the municipal/city plan. Provisions I did not rely on because they say 'may': s.21(6) (review whenever necessary) and the proviso to s.23 (revising the plan alongside the Master Plan). Things a person should check: (a) both Acts are PRS secondary copies, not gazette copies; (b) the KTCP compilation stops at Act 38 of 2015, and I did not check whether Amendment Act 10 of 2026 to the BMLTA Act changes ss.21-23; (c) the CMP is prepared by the BMLTA, a state body, not by the city government, and the city government's own duty comes through KTCP s.12(1)(b) and BMLTA s.22, with the GBA being the KTCP Planning Authority under the GBG Act 2024 (ULG-01); (d) the notification declaring the Urban Mobility Region is not in the Citation Sheet. None of these changes the YES answer on the law.
A43: UPD13c | B43: Surat | C43: Does the T&CP Act mandate the planning for: >:< c) Comprehensive mobility | D43: =IFERROR(UPD13c!K33,"") | E43: 10 >:< 1.67 | H43: =IF(OR(F43="",NOT(ISNUMBER(D43))),"",IF(ABS(F43-D43)<0.001,"Yes","No")) | I43: =IF(ISNUMBER(F43),F43,D43) | J43: =IF(ISNUMBER(F43),"Expert (overrides AI)",IF(ISNUMBER(D43),"AI","Not scored yet")) -> Not scored yet | K43: Left for a person | L43: Partially Answered | M43: ANSWER: Not determined. None of the Citation Sheet sources requires anyone to prepare a Comprehensive Mobility Plan (CMP) for Surat. The closest provision is section 12(2) of the Gujarat Town Planning and Urban Development Act, 1976 (GTPUDA), which covers the development plan prepared by the Surat Urban Development Authority (SUDA). It is known here only from SUDA's own Development Plan 2035 report, which paraphrases it as saying the draft plan 'shall provide for all or any of' a list of public purposes. Item (b) on that list is transport and communications. The verb is 'shall', but 'all or any of' may let the authority pick which items to include. Item (b) also covers land for transport infrastructure, not a mobility plan. Whether it counts as a 'mandated mobility component' is a judgement call the methodology does not settle. I also could not confirm a zero. | EVIDENCE: (1) GTPUDA 1976, PRS copy (ULG-01): the pages I could read show only the amendment Acts. Gujarat Act 14 of 2019 adds a proviso to s.9(1): the development plan 'shall include the proposals, with regard to spatial planning' of a plan sanctioned under the Metropolitan Planning Committees Act 2008 (MPC Act) or the District Planning Committees Act. It also adds s.19A and amends s.12(1). None of this mentions mobility or transport. I could not read the original text of s.12 in this copy. (2) SUDA Development Plan 2035 report, 2017 (ULG-06), p.212-213: 'As per provisions of section 12(2) of the Act, the draft devel | N43: Development Plan 2035 (report, 22 February 2017), Surat Urban Development Authority [ULG-06] | O43: https://www.sudaonline.org/wp-content/uploads/2017/03/SUDA-DP-2035-report-final-22.02.2017.pdf | P43: As per provisions of section 12(2) of the Act, the draft development plan shall provide for all or any of the following public purposes: | Q43: I left the Answer blank because the Citation Sheet does not support either YES or NO. Why not YES: - No source in the Sheet requires anyone to prepare a Comprehensive Mobility Plan (CMP). - The closest wording is GTPUDA s.12(2). It is known here only from SUDA's own Development Plan 2035 report (ULG-06), which says the draft development plan 'shall provide for all or any of' a list of public purposes. Item (b) is 'transport and communications, such as roads, highways, railways, and airport'. - 'All or any of' lets the authority choose which items to include, so including transport is in effect optional. The methodology says optional provisions are not credited. - Item (b) is also about land for transport infrastructure. It is not a comprehensive mobility plan or mobility component. - The 2019 amendment (ULG-01: s.9(1) proviso, s.12(1) change, new s.19A) only brings in the 'spatial planning' proposals of plans made under the Gujarat Metropolitan Planning Committees (MPC) Act or District Planning Committees Act. It says nothing about mobility. - The GTPUD Rules 1979 (ULG-04) mention transport and roads only as map colours and as the index map of a town planning scheme. They do not require a mobility plan. - The CGDCR 2017 duty to 'plan for proper access, circulation and mobility' (ULG-05) applies only to development in areas with no town planning scheme. It is a road network plan for those areas, not a city-level mobility plan. - The Surat CMP of 2008 and the new one being prepared (ULG-07, ULG-06 p.201/216) show what happens in practice. They do not show a legal mandate. Why not NO (affirmative absence is not established): - The original GTPUDA s.12 text could not be read in ULG-01. That PRS copy shows only the appended amendment Acts, so the wording is known only from SUDA's paraphrase. - Only the 2019 amendments (ss.10A-10C) of the MPC Act 2008 are in the Sheet, not the full Act. - The whole Gujarat Provincial Municipal Corporations Act 1949 (ULG-03) has not been searched for transport or traffic planning duties. - No Gujarat metro or urban transport authority law is in the Sheet. What I checked: ULG-01, ULG-04, ULG-05, ULG-06, ULG-07, and a search of the whole Sheet for 'traffic and transportation plan mobility plan shall be prepared'. For the reviewer: - Get the primary GTPUDA s.12 text, the full MPC Act 2008 and the full GPMC Act 1949. - If no mandatory mobility or CMP provision turns up, NO is the likely answer. 'All or any of' transport land reservation would not count under the 'may'/optional exclusion. - Confirm whether s.12(2)(b) should count as a 'mobility component' under the methodology. | R43: The citation didn't settle every input. "Answer" left blank: the Citation Sheet doesn't decide it.
A44: UPD13d | B44: Bangalore | C44: Does the T&CP Act mandate the planning for: >:< d) Sustainability/Climate/Environmental conservation | D44: =IFERROR(UPD13d!K14,"") -> 1.67 | E44: 10 >:< 1.67 | H44: =IF(OR(F44="",NOT(ISNUMBER(D44))),"",IF(ABS(F44-D44)<0.001,"Yes","No")) | I44: =IF(ISNUMBER(F44),F44,D44) -> 1.67 | J44: =IF(ISNUMBER(F44),"Expert (overrides AI)",IF(ISNUMBER(D44),"AI","Not scored yet")) -> AI | K44: Scored by AI | L44: Answered — Verified Source | M44: ANSWER: Yes. The Greater Bengaluru Governance Act, 2024 is an allied Act that makes the Greater Bengaluru Authority (GBA) the Planning Authority under the Karnataka Town and Country Planning (KTCP) Act. It requires the GBA, through a Climate Action Cell it must set up, to formulate and implement a climate plan: the Bengaluru Climate Action and Resilience Plan (BCAP), together with plans for cutting greenhouse gas emissions. The verb is 'shall', not 'may', so this meets the 'mandate the planning authority to prepare a sustainability plan' test. The KTCP Act itself does not require a sustainability, climate or environmental-conservation part in the master plan. | EVIDENCE: (1) GBA Act (ULG-01), Planning Functions, sub-section (2)(a) of the section just before s.15 (probably s.14): 'the Greater Bengaluru Authority shall be the "Planning Authority" as defined under the Karnataka Town and Country Planning Act, 1961, for the areas comprising of the Greater Bengaluru Area'. Same provision, s.15(1): GBA 'shall be responsible to make master plan and mobility plans'. (2) GBA Act s.17(1): GBA 'shall, within one year of its constitution, establish a Climate Action Cell ... tasked with the responsibility to formulate and implement Bengaluru Climate Action and Resilience Plan and such other plans and strategies for mitigating Greenhouse Gas emissions'. s.17(2): the Cell 'shall spearhead initiatives' to get BCAP actions carried out on time. s.17(3): the Cell is headed by the Special Commiss | N44: The Greater Bengaluru Governance Act, 2024 (Karnataka Act No. 36 of 2025), as enacted, PRS copy of the Gazette text (DPAL notification dated 24.04.2025) [ULG-01] | O44: https://prsindia.org/files/bills_acts/acts_states/karnataka/2025/Act36of2025KA.pdf | P44: The Greater Bengaluru Authority shall, within one year of its constitution, establish a Climate Action Cell, with the Chief Commissioner as the chairperson, tasked with the responsibility to formulate and implement Bengaluru Climate Action and Resilience Plan and such other plans and strategies for mitigating Greenhouse Gas emissions. | Q44: I scored YES. The methodology accepts provisions in the T&CP Act, a UDA Act or an allied Act that require the planning authority to prepare a sustainability plan. The Greater Bengaluru Governance Act, 2024 (Karnataka Act 36 of 2025) is such an allied Act. Under its Planning Functions provision (2)(a), 'the Greater Bengaluru Authority shall be the "Planning Authority" as defined under the Karnataka Town and Country Planning Act, 1961', and this applies 'notwithstanding anything contained in any other law'. Section 17(1) then says the GBA 'shall' set up a Climate Action Cell to 'formulate and implement' the Bengaluru Climate Action and Resilience Plan (BCAP) and plans to cut greenhouse gas emissions. Section 17(2) says the Cell 'shall' drive timely implementation of BCAP actions. The verb is 'shall', not 'may', so the planning authority is required to prepare a climate plan. I checked both provisions in the ULG-01 text and the Step 2 answer is supported. Other instruments I checked: - KTCP Act s.12 (Contents of Master Plan, as substituted by Act 1 of 2005; PRS text with amendments up to Act 38 of 2015). The required items are zoning, streets, parks and open spaces, and so on. There is no sustainability, climate or environmental-conservation requirement, so the second route (an environmental part inside the master plan) is not met under the KTCP Act. - KTCP Act s.26(2)(e) and (i). Green belts and 'natural beauty' appear only as matters a town planning scheme 'may' cover, so they do not count. - GBA Act s.315(l). The GBA 'may' make regulations on the chapters of the Master Plan. This is discretionary and was not relied on. Points for a person to check: (1) The GBA Act text is a PRS copy, which is a secondary source; the official Gazette copy should be confirmed. (2) I could not confirm the section number of the Planning Functions provision from the excerpt. (3) The 'Yes' rests on a separate climate plan required of the planning authority, not on a climate part inside the KTCP master plan. (4) The KTCP Amendment Bill 2025 (ULG-03) and the GBA Amendment Bill 2025 (ULG-05) have not been shown to be enacted and were not relied on. (5) No KTCP Rules or zoning regulations are in the Citation Sheet. This question is about the law only. Whether the Cell or the BCAP exists in practice was not assessed.
