Workbook

Sheet Check before use
A1: DRAFT PARASTATAL scoring workbook - generated from the methodology sheet
A3: This draft follows the same layout as the UPD scoring workbook, so the app can fill, merge and read it. The scoring experts should:
A4: 1. Replace each question sheet's simple inputs (yellow) and Points formula with the real ones, keeping the row-11 instructions (e.g. SELECT YES / NO) and the column names 'Points (Auto-generate)' and 'SCORER COMMENTS'.
A5: 2. Check 'Applies?' (filled in from each agency's type and the question's Applicability). To change it, fix the agency in the city register or Sources workbook and generate again.
A6: 3. Fix the points below in the methodology sheet and generate again.
A8: Points to check:
A9: • Section 'Decentralised Participatory Governance' has no (CODE); using DPG
A10: • Question Bank row 35: the ID "DPG d" has no number. We treated it as part of DPG 5. Please correct the ID in the question bank.
A11: • Question Bank row 36: the ID "DPG f" has no number. We treated it as part of DPG 5. Please correct the ID in the question bank.
A12: • Question Bank row 38: the ID "DPG h" has no number. We treated it as part of DPG 5. Please correct the ID in the question bank.
A13: • Section 'State Capacities' has no (CODE); using SC
A14: • UPD 1a: the methodology gives scores up to 10, but the Max Score is 5. Say how the score should be scaled.

Sheet PARASTATAL_SUMMARY_RAW
A1: ASICS 2027_Report_Q No | B1: Group | C1: MQ_SQ | D1: Question | E1: Assessment level | F1: Max Score | G1: Bengaluru – BWSSB | H1: Bengaluru – BMTC | I1: Bengaluru – BDA | J1: Bengaluru – BMRCL | K1: Bengaluru – BMRDA | L1: Surat – SUDA | M1: Surat – GMRC
A2: ENTER | B2: Derived | C2: Derived | D2: Derived | E2: Derived | F2: Derived | G2: Derived | H2: Derived | I2: Derived | J2: Derived | K2: Derived | L2: Derived | M2: Derived
A3: UPD1 | B3: =VLOOKUP($A3,'PARASTATAL Questions'!$A:$J,3,0)&"" | C3: =VLOOKUP($A3,'PARASTATAL Questions'!$A:$J,4,0)&"" | D3: =VLOOKUP($A3,'PARASTATAL Questions'!$A:$J,5,0)&"" | E3: =VLOOKUP($A3,'PARASTATAL Questions'!$A:$J,7,0)&"" | F3: =VLOOKUP($A3,'PARASTATAL Questions'!$A:$J,6,0) | G3: =IF(OR(G4="ER",G5="ER"),"ER",IF(OR(G4="?",G5="?"),"?",IF(AND(G4="NA",G5="NA"),"NA",SUM(G4,G5)/((G4<>"NA")*$F$4+(G5<>"NA")*$F$5)*$F3))) | H3: =IF(OR(H4="ER",H5="ER"),"ER",IF(OR(H4="?",H5="?"),"?",IF(AND(H4="NA",H5="NA"),"NA",SUM(H4,H5)/((H4<>"NA")*$F$4+(H5<>"NA")*$F$5)*$F3))) | I3: =IF(OR(I4="ER",I5="ER"),"ER",IF(OR(I4="?",I5="?"),"?",IF(AND(I4="NA",I5="NA"),"NA",SUM(I4,I5)/((I4<>"NA")*$F$4+(I5<>"NA")*$F$5)*$F3))) | J3: =IF(OR(J4="ER",J5="ER"),"ER",IF(OR(J4="?",J5="?"),"?",IF(AND(J4="NA",J5="NA"),"NA",SUM(J4,J5)/((J4<>"NA")*$F$4+(J5<>"NA")*$F$5)*$F3))) | K3: =IF(OR(K4="ER",K5="ER"),"ER",IF(OR(K4="?",K5="?"),"?",IF(AND(K4="NA",K5="NA"),"NA",SUM(K4,K5)/((K4<>"NA")*$F$4+(K5<>"NA")*$F$5)*$F3))) | L3: =IF(OR(L4="ER",L5="ER"),"ER",IF(OR(L4="?",L5="?"),"?",IF(AND(L4="NA",L5="NA"),"NA",SUM(L4,L5)/((L4<>"NA")*$F$4+(L5<>"NA")*$F$5)*$F3))) | M3: =IF(OR(M4="ER",M5="ER"),"ER",IF(OR(M4="?",M5="?"),"?",IF(AND(M4="NA",M5="NA"),"NA",SUM(M4,M5)/((M4<>"NA")*$F$4+(M5<>"NA")*$F$5)*$F3)))
A4: UPD1a | B4: =VLOOKUP($A4,'PARASTATAL Questions'!$A:$J,3,0)&"" | C4: =VLOOKUP($A4,'PARASTATAL Questions'!$A:$J,4,0)&"" | D4: =VLOOKUP($A4,'PARASTATAL Questions'!$A:$J,5,0)&"" | E4: =VLOOKUP($A4,'PARASTATAL Questions'!$A:$J,7,0)&"" | F4: =VLOOKUP($A4,'PARASTATAL Questions'!$A:$J,6,0) | G4: =IF($F4=0,"NA",IF($A4=INDIRECT("'"&$A4&"'!$B$1"),IF(VLOOKUP(G$1,INDIRECT("'"&$A4&"'!$A$12:$Z$19"),MATCH("Points (Auto-generate)",INDIRECT("'"&$A4&"'!$A$12:$Z$12"),0),0)="","?",VLOOKUP(G$1,INDIRECT("'"&$A4&"'!$A$12:$Z$19"),MATCH("Points (Auto-generate)",INDIRECT("'"&$A4&"'!$A$12:$Z$12"),0),0)),"ER")) | H4: =IF($F4=0,"NA",IF($A4=INDIRECT("'"&$A4&"'!$B$1"),IF(VLOOKUP(H$1,INDIRECT("'"&$A4&"'!$A$12:$Z$19"),MATCH("Points (Auto-generate)",INDIRECT("'"&$A4&"'!$A$12:$Z$12"),0),0)="","?",VLOOKUP(H$1,INDIRECT("'"&$A4&"'!$A$12:$Z$19"),MATCH("Points (Auto-generate)",INDIRECT("'"&$A4&"'!$A$12:$Z$12"),0),0)),"ER")) | I4: =IF($F4=0,"NA",IF($A4=INDIRECT("'"&$A4&"'!$B$1"),IF(VLOOKUP(I$1,INDIRECT("'"&$A4&"'!$A$12:$Z$19"),MATCH("Points (Auto-generate)",INDIRECT("'"&$A4&"'!$A$12:$Z$12"),0),0)="","?",VLOOKUP(I$1,INDIRECT("'"&$A4&"'!$A$12:$Z$19"),MATCH("Points (Auto-generate)",INDIRECT("'"&$A4&"'!$A$12:$Z$12"),0),0)),"ER")) | J4: =IF($F4=0,"NA",IF($A4=INDIRECT("'"&$A4&"'!$B$1"),IF(VLOOKUP(J$1,INDIRECT("'"&$A4&"'!$A$12:$Z$19"),MATCH("Points (Auto-generate)",INDIRECT("'"&$A4&"'!$A$12:$Z$12"),0),0)="","?",VLOOKUP(J$1,INDIRECT("'"&$A4&"'!$A$12:$Z$19"),MATCH("Points (Auto-generate)",INDIRECT("'"&$A4&"'!$A$12:$Z$12"),0),0)),"ER")) | K4: =IF($F4=0,"NA",IF($A4=INDIRECT("'"&$A4&"'!$B$1"),IF(VLOOKUP(K$1,INDIRECT("'"&$A4&"'!$A$12:$Z$19"),MATCH("Points (Auto-generate)",INDIRECT("'"&$A4&"'!$A$12:$Z$12"),0),0)="","?",VLOOKUP(K$1,INDIRECT("'"&$A4&"'!$A$12:$Z$19"),MATCH("Points (Auto-generate)",INDIRECT("'"&$A4&"'!$A$12:$Z$12"),0),0)),"ER")) | L4: =IF($F4=0,"NA",IF($A4=INDIRECT("'"&$A4&"'!$B$1"),IF(VLOOKUP(L$1,INDIRECT("'"&$A4&"'!$A$12:$Z$19"),MATCH("Points (Auto-generate)",INDIRECT("'"&$A4&"'!$A$12:$Z$12"),0),0)="","?",VLOOKUP(L$1,INDIRECT("'"&$A4&"'!$A$12:$Z$19"),MATCH("Points (Auto-generate)",INDIRECT("'"&$A4&"'!$A$12:$Z$12"),0),0)),"ER")) | M4: =IF($F4=0,"NA",IF($A4=INDIRECT("'"&$A4&"'!$B$1"),IF(VLOOKUP(M$1,INDIRECT("'"&$A4&"'!$A$12:$Z$19"),MATCH("Points (Auto-generate)",INDIRECT("'"&$A4&"'!$A$12:$Z$12"),0),0)="","?",VLOOKUP(M$1,INDIRECT("'"&$A4&"'!$A$12:$Z$19"),MATCH("Points (Auto-generate)",INDIRECT("'"&$A4&"'!$A$12:$Z$12"),0),0)),"ER"))
A5: UPD1b | B5: =VLOOKUP($A5,'PARASTATAL Questions'!$A:$J,3,0)&"" | C5: =VLOOKUP($A5,'PARASTATAL Questions'!$A:$J,4,0)&"" | D5: =VLOOKUP($A5,'PARASTATAL Questions'!$A:$J,5,0)&"" | E5: =VLOOKUP($A5,'PARASTATAL Questions'!$A:$J,7,0)&"" | F5: =VLOOKUP($A5,'PARASTATAL Questions'!$A:$J,6,0) | G5: =IF($F5=0,"NA",IF($A5=INDIRECT("'"&$A5&"'!$B$1"),IF(VLOOKUP(G$1,INDIRECT("'"&$A5&"'!$A$12:$Z$19"),MATCH("Points (Auto-generate)",INDIRECT("'"&$A5&"'!$A$12:$Z$12"),0),0)="","?",VLOOKUP(G$1,INDIRECT("'"&$A5&"'!$A$12:$Z$19"),MATCH("Points (Auto-generate)",INDIRECT("'"&$A5&"'!$A$12:$Z$12"),0),0)),"ER")) | H5: =IF($F5=0,"NA",IF($A5=INDIRECT("'"&$A5&"'!$B$1"),IF(VLOOKUP(H$1,INDIRECT("'"&$A5&"'!$A$12:$Z$19"),MATCH("Points (Auto-generate)",INDIRECT("'"&$A5&"'!$A$12:$Z$12"),0),0)="","?",VLOOKUP(H$1,INDIRECT("'"&$A5&"'!$A$12:$Z$19"),MATCH("Points (Auto-generate)",INDIRECT("'"&$A5&"'!$A$12:$Z$12"),0),0)),"ER")) | I5: =IF($F5=0,"NA",IF($A5=INDIRECT("'"&$A5&"'!$B$1"),IF(VLOOKUP(I$1,INDIRECT("'"&$A5&"'!$A$12:$Z$19"),MATCH("Points (Auto-generate)",INDIRECT("'"&$A5&"'!$A$12:$Z$12"),0),0)="","?",VLOOKUP(I$1,INDIRECT("'"&$A5&"'!$A$12:$Z$19"),MATCH("Points (Auto-generate)",INDIRECT("'"&$A5&"'!$A$12:$Z$12"),0),0)),"ER")) | J5: =IF($F5=0,"NA",IF($A5=INDIRECT("'"&$A5&"'!$B$1"),IF(VLOOKUP(J$1,INDIRECT("'"&$A5&"'!$A$12:$Z$19"),MATCH("Points (Auto-generate)",INDIRECT("'"&$A5&"'!$A$12:$Z$12"),0),0)="","?",VLOOKUP(J$1,INDIRECT("'"&$A5&"'!$A$12:$Z$19"),MATCH("Points (Auto-generate)",INDIRECT("'"&$A5&"'!$A$12:$Z$12"),0),0)),"ER")) | K5: =IF($F5=0,"NA",IF($A5=INDIRECT("'"&$A5&"'!$B$1"),IF(VLOOKUP(K$1,INDIRECT("'"&$A5&"'!$A$12:$Z$19"),MATCH("Points (Auto-generate)",INDIRECT("'"&$A5&"'!$A$12:$Z$12"),0),0)="","?",VLOOKUP(K$1,INDIRECT("'"&$A5&"'!$A$12:$Z$19"),MATCH("Points (Auto-generate)",INDIRECT("'"&$A5&"'!$A$12:$Z$12"),0),0)),"ER")) | L5: =IF($F5=0,"NA",IF($A5=INDIRECT("'"&$A5&"'!$B$1"),IF(VLOOKUP(L$1,INDIRECT("'"&$A5&"'!$A$12:$Z$19"),MATCH("Points (Auto-generate)",INDIRECT("'"&$A5&"'!$A$12:$Z$12"),0),0)="","?",VLOOKUP(L$1,INDIRECT("'"&$A5&"'!$A$12:$Z$19"),MATCH("Points (Auto-generate)",INDIRECT("'"&$A5&"'!$A$12:$Z$12"),0),0)),"ER")) | M5: =IF($F5=0,"NA",IF($A5=INDIRECT("'"&$A5&"'!$B$1"),IF(VLOOKUP(M$1,INDIRECT("'"&$A5&"'!$A$12:$Z$19"),MATCH("Points (Auto-generate)",INDIRECT("'"&$A5&"'!$A$12:$Z$12"),0),0)="","?",VLOOKUP(M$1,INDIRECT("'"&$A5&"'!$A$12:$Z$19"),MATCH("Points (Auto-generate)",INDIRECT("'"&$A5&"'!$A$12:$Z$12"),0),0)),"ER"))
A6: UPD2 | B6: =VLOOKUP($A6,'PARASTATAL Questions'!$A:$J,3,0)&"" | C6: =VLOOKUP($A6,'PARASTATAL Questions'!$A:$J,4,0)&"" | D6: =VLOOKUP($A6,'PARASTATAL Questions'!$A:$J,5,0)&"" | E6: =VLOOKUP($A6,'PARASTATAL Questions'!$A:$J,7,0)&"" | F6: =VLOOKUP($A6,'PARASTATAL Questions'!$A:$J,6,0) | G6: =IF(OR(G7="ER",G8="ER",G9="ER",G10="ER"),"ER",IF(OR(G7="?",G8="?",G9="?",G10="?"),"?",IF(AND(G7="NA",G8="NA",G9="NA",G10="NA"),"NA",SUM(G7,G8,G9,G10)/((G7<>"NA")*$F$7+(G8<>"NA")*$F$8+(G9<>"NA")*$F$9+(G10<>"NA")*$F$10)*$F6))) | H6: =IF(OR(H7="ER",H8="ER",H9="ER",H10="ER"),"ER",IF(OR(H7="?",H8="?",H9="?",H10="?"),"?",IF(AND(H7="NA",H8="NA",H9="NA",H10="NA"),"NA",SUM(H7,H8,H9,H10)/((H7<>"NA")*$F$7+(H8<>"NA")*$F$8+(H9<>"NA")*$F$9+(H10<>"NA")*$F$10)*$F6))) | I6: =IF(OR(I7="ER",I8="ER",I9="ER",I10="ER"),"ER",IF(OR(I7="?",I8="?",I9="?",I10="?"),"?",IF(AND(I7="NA",I8="NA",I9="NA",I10="NA"),"NA",SUM(I7,I8,I9,I10)/((I7<>"NA")*$F$7+(I8<>"NA")*$F$8+(I9<>"NA")*$F$9+(I10<>"NA")*$F$10)*$F6))) | J6: =IF(OR(J7="ER",J8="ER",J9="ER",J10="ER"),"ER",IF(OR(J7="?",J8="?",J9="?",J10="?"),"?",IF(AND(J7="NA",J8="NA",J9="NA",J10="NA"),"NA",SUM(J7,J8,J9,J10)/((J7<>"NA")*$F$7+(J8<>"NA")*$F$8+(J9<>"NA")*$F$9+(J10<>"NA")*$F$10)*$F6))) | K6: =IF(OR(K7="ER",K8="ER",K9="ER",K10="ER"),"ER",IF(OR(K7="?",K8="?",K9="?",K10="?"),"?",IF(AND(K7="NA",K8="NA",K9="NA",K10="NA"),"NA",SUM(K7,K8,K9,K10)/((K7<>"NA")*$F$7+(K8<>"NA")*$F$8+(K9<>"NA")*$F$9+(K10<>"NA")*$F$10)*$F6))) | L6: =IF(OR(L7="ER",L8="ER",L9="ER",L10="ER"),"ER",IF(OR(L7="?",L8="?",L9="?",L10="?"),"?",IF(AND(L7="NA",L8="NA",L9="NA",L10="NA"),"NA",SUM(L7,L8,L9,L10)/((L7<>"NA")*$F$7+(L8<>"NA")*$F$8+(L9<>"NA")*$F$9+(L10<>"NA")*$F$10)*$F6))) | M6: =IF(OR(M7="ER",M8="ER",M9="ER",M10="ER"),"ER",IF(OR(M7="?",M8="?",M9="?",M10="?"),"?",IF(AND(M7="NA",M8="NA",M9="NA",M10="NA"),"NA",SUM(M7,M8,M9,M10)/((M7<>"NA")*$F$7+(M8<>"NA")*$F$8+(M9<>"NA")*$F$9+(M10<>"NA")*$F$10)*$F6)))
A7: UPD2a | B7: =VLOOKUP($A7,'PARASTATAL Questions'!$A:$J,3,0)&"" | C7: =VLOOKUP($A7,'PARASTATAL Questions'!$A:$J,4,0)&"" | D7: =VLOOKUP($A7,'PARASTATAL Questions'!$A:$J,5,0)&"" | E7: =VLOOKUP($A7,'PARASTATAL Questions'!$A:$J,7,0)&"" | F7: =VLOOKUP($A7,'PARASTATAL Questions'!$A:$J,6,0) | G7: =IF($F7=0,"NA",IF($A7=INDIRECT("'"&$A7&"'!$B$1"),IF(VLOOKUP(G$1,INDIRECT("'"&$A7&"'!$A$12:$Z$19"),MATCH("Points (Auto-generate)",INDIRECT("'"&$A7&"'!$A$12:$Z$12"),0),0)="","?",VLOOKUP(G$1,INDIRECT("'"&$A7&"'!$A$12:$Z$19"),MATCH("Points (Auto-generate)",INDIRECT("'"&$A7&"'!$A$12:$Z$12"),0),0)),"ER")) | H7: =IF($F7=0,"NA",IF($A7=INDIRECT("'"&$A7&"'!$B$1"),IF(VLOOKUP(H$1,INDIRECT("'"&$A7&"'!$A$12:$Z$19"),MATCH("Points (Auto-generate)",INDIRECT("'"&$A7&"'!$A$12:$Z$12"),0),0)="","?",VLOOKUP(H$1,INDIRECT("'"&$A7&"'!$A$12:$Z$19"),MATCH("Points (Auto-generate)",INDIRECT("'"&$A7&"'!$A$12:$Z$12"),0),0)),"ER")) | I7: =IF($F7=0,"NA",IF($A7=INDIRECT("'"&$A7&"'!$B$1"),IF(VLOOKUP(I$1,INDIRECT("'"&$A7&"'!$A$12:$Z$19"),MATCH("Points (Auto-generate)",INDIRECT("'"&$A7&"'!$A$12:$Z$12"),0),0)="","?",VLOOKUP(I$1,INDIRECT("'"&$A7&"'!$A$12:$Z$19"),MATCH("Points (Auto-generate)",INDIRECT("'"&$A7&"'!$A$12:$Z$12"),0),0)),"ER")) | J7: =IF($F7=0,"NA",IF($A7=INDIRECT("'"&$A7&"'!$B$1"),IF(VLOOKUP(J$1,INDIRECT("'"&$A7&"'!$A$12:$Z$19"),MATCH("Points (Auto-generate)",INDIRECT("'"&$A7&"'!$A$12:$Z$12"),0),0)="","?",VLOOKUP(J$1,INDIRECT("'"&$A7&"'!$A$12:$Z$19"),MATCH("Points (Auto-generate)",INDIRECT("'"&$A7&"'!$A$12:$Z$12"),0),0)),"ER")) | K7: =IF($F7=0,"NA",IF($A7=INDIRECT("'"&$A7&"'!$B$1"),IF(VLOOKUP(K$1,INDIRECT("'"&$A7&"'!$A$12:$Z$19"),MATCH("Points (Auto-generate)",INDIRECT("'"&$A7&"'!$A$12:$Z$12"),0),0)="","?",VLOOKUP(K$1,INDIRECT("'"&$A7&"'!$A$12:$Z$19"),MATCH("Points (Auto-generate)",INDIRECT("'"&$A7&"'!$A$12:$Z$12"),0),0)),"ER")) | L7: =IF($F7=0,"NA",IF($A7=INDIRECT("'"&$A7&"'!$B$1"),IF(VLOOKUP(L$1,INDIRECT("'"&$A7&"'!$A$12:$Z$19"),MATCH("Points (Auto-generate)",INDIRECT("'"&$A7&"'!$A$12:$Z$12"),0),0)="","?",VLOOKUP(L$1,INDIRECT("'"&$A7&"'!$A$12:$Z$19"),MATCH("Points (Auto-generate)",INDIRECT("'"&$A7&"'!$A$12:$Z$12"),0),0)),"ER")) | M7: =IF($F7=0,"NA",IF($A7=INDIRECT("'"&$A7&"'!$B$1"),IF(VLOOKUP(M$1,INDIRECT("'"&$A7&"'!$A$12:$Z$19"),MATCH("Points (Auto-generate)",INDIRECT("'"&$A7&"'!$A$12:$Z$12"),0),0)="","?",VLOOKUP(M$1,INDIRECT("'"&$A7&"'!$A$12:$Z$19"),MATCH("Points (Auto-generate)",INDIRECT("'"&$A7&"'!$A$12:$Z$12"),0),0)),"ER"))
A8: UPD2b | B8: =VLOOKUP($A8,'PARASTATAL Questions'!$A:$J,3,0)&"" | C8: =VLOOKUP($A8,'PARASTATAL Questions'!$A:$J,4,0)&"" | D8: =VLOOKUP($A8,'PARASTATAL Questions'!$A:$J,5,0)&"" | E8: =VLOOKUP($A8,'PARASTATAL Questions'!$A:$J,7,0)&"" | F8: =VLOOKUP($A8,'PARASTATAL Questions'!$A:$J,6,0) | G8: =IF($F8=0,"NA",IF($A8=INDIRECT("'"&$A8&"'!$B$1"),IF(VLOOKUP(G$1,INDIRECT("'"&$A8&"'!$A$12:$Z$19"),MATCH("Points (Auto-generate)",INDIRECT("'"&$A8&"'!$A$12:$Z$12"),0),0)="","?",VLOOKUP(G$1,INDIRECT("'"&$A8&"'!$A$12:$Z$19"),MATCH("Points (Auto-generate)",INDIRECT("'"&$A8&"'!$A$12:$Z$12"),0),0)),"ER")) | H8: =IF($F8=0,"NA",IF($A8=INDIRECT("'"&$A8&"'!$B$1"),IF(VLOOKUP(H$1,INDIRECT("'"&$A8&"'!$A$12:$Z$19"),MATCH("Points (Auto-generate)",INDIRECT("'"&$A8&"'!$A$12:$Z$12"),0),0)="","?",VLOOKUP(H$1,INDIRECT("'"&$A8&"'!$A$12:$Z$19"),MATCH("Points (Auto-generate)",INDIRECT("'"&$A8&"'!$A$12:$Z$12"),0),0)),"ER")) | I8: =IF($F8=0,"NA",IF($A8=INDIRECT("'"&$A8&"'!$B$1"),IF(VLOOKUP(I$1,INDIRECT("'"&$A8&"'!$A$12:$Z$19"),MATCH("Points (Auto-generate)",INDIRECT("'"&$A8&"'!$A$12:$Z$12"),0),0)="","?",VLOOKUP(I$1,INDIRECT("'"&$A8&"'!$A$12:$Z$19"),MATCH("Points (Auto-generate)",INDIRECT("'"&$A8&"'!$A$12:$Z$12"),0),0)),"ER")) | J8: =IF($F8=0,"NA",IF($A8=INDIRECT("'"&$A8&"'!$B$1"),IF(VLOOKUP(J$1,INDIRECT("'"&$A8&"'!$A$12:$Z$19"),MATCH("Points (Auto-generate)",INDIRECT("'"&$A8&"'!$A$12:$Z$12"),0),0)="","?",VLOOKUP(J$1,INDIRECT("'"&$A8&"'!$A$12:$Z$19"),MATCH("Points (Auto-generate)",INDIRECT("'"&$A8&"'!$A$12:$Z$12"),0),0)),"ER")) | K8: =IF($F8=0,"NA",IF($A8=INDIRECT("'"&$A8&"'!$B$1"),IF(VLOOKUP(K$1,INDIRECT("'"&$A8&"'!$A$12:$Z$19"),MATCH("Points (Auto-generate)",INDIRECT("'"&$A8&"'!$A$12:$Z$12"),0),0)="","?",VLOOKUP(K$1,INDIRECT("'"&$A8&"'!$A$12:$Z$19"),MATCH("Points (Auto-generate)",INDIRECT("'"&$A8&"'!$A$12:$Z$12"),0),0)),"ER")) | L8: =IF($F8=0,"NA",IF($A8=INDIRECT("'"&$A8&"'!$B$1"),IF(VLOOKUP(L$1,INDIRECT("'"&$A8&"'!$A$12:$Z$19"),MATCH("Points (Auto-generate)",INDIRECT("'"&$A8&"'!$A$12:$Z$12"),0),0)="","?",VLOOKUP(L$1,INDIRECT("'"&$A8&"'!$A$12:$Z$19"),MATCH("Points (Auto-generate)",INDIRECT("'"&$A8&"'!$A$12:$Z$12"),0),0)),"ER")) | M8: =IF($F8=0,"NA",IF($A8=INDIRECT("'"&$A8&"'!$B$1"),IF(VLOOKUP(M$1,INDIRECT("'"&$A8&"'!$A$12:$Z$19"),MATCH("Points (Auto-generate)",INDIRECT("'"&$A8&"'!$A$12:$Z$12"),0),0)="","?",VLOOKUP(M$1,INDIRECT("'"&$A8&"'!$A$12:$Z$19"),MATCH("Points (Auto-generate)",INDIRECT("'"&$A8&"'!$A$12:$Z$12"),0),0)),"ER"))
A9: UPD2c | B9: =VLOOKUP($A9,'PARASTATAL Questions'!$A:$J,3,0)&"" | C9: =VLOOKUP($A9,'PARASTATAL Questions'!$A:$J,4,0)&"" | D9: =VLOOKUP($A9,'PARASTATAL Questions'!$A:$J,5,0)&"" | E9: =VLOOKUP($A9,'PARASTATAL Questions'!$A:$J,7,0)&"" | F9: =VLOOKUP($A9,'PARASTATAL Questions'!$A:$J,6,0) | G9: =IF($F9=0,"NA",IF($A9=INDIRECT("'"&$A9&"'!$B$1"),IF(VLOOKUP(G$1,INDIRECT("'"&$A9&"'!$A$12:$Z$19"),MATCH("Points (Auto-generate)",INDIRECT("'"&$A9&"'!$A$12:$Z$12"),0),0)="","?",VLOOKUP(G$1,INDIRECT("'"&$A9&"'!$A$12:$Z$19"),MATCH("Points (Auto-generate)",INDIRECT("'"&$A9&"'!$A$12:$Z$12"),0),0)),"ER")) | H9: =IF($F9=0,"NA",IF($A9=INDIRECT("'"&$A9&"'!$B$1"),IF(VLOOKUP(H$1,INDIRECT("'"&$A9&"'!$A$12:$Z$19"),MATCH("Points (Auto-generate)",INDIRECT("'"&$A9&"'!$A$12:$Z$12"),0),0)="","?",VLOOKUP(H$1,INDIRECT("'"&$A9&"'!$A$12:$Z$19"),MATCH("Points (Auto-generate)",INDIRECT("'"&$A9&"'!$A$12:$Z$12"),0),0)),"ER")) | I9: =IF($F9=0,"NA",IF($A9=INDIRECT("'"&$A9&"'!$B$1"),IF(VLOOKUP(I$1,INDIRECT("'"&$A9&"'!$A$12:$Z$19"),MATCH("Points (Auto-generate)",INDIRECT("'"&$A9&"'!$A$12:$Z$12"),0),0)="","?",VLOOKUP(I$1,INDIRECT("'"&$A9&"'!$A$12:$Z$19"),MATCH("Points (Auto-generate)",INDIRECT("'"&$A9&"'!$A$12:$Z$12"),0),0)),"ER")) | J9: =IF($F9=0,"NA",IF($A9=INDIRECT("'"&$A9&"'!$B$1"),IF(VLOOKUP(J$1,INDIRECT("'"&$A9&"'!$A$12:$Z$19"),MATCH("Points (Auto-generate)",INDIRECT("'"&$A9&"'!$A$12:$Z$12"),0),0)="","?",VLOOKUP(J$1,INDIRECT("'"&$A9&"'!$A$12:$Z$19"),MATCH("Points (Auto-generate)",INDIRECT("'"&$A9&"'!$A$12:$Z$12"),0),0)),"ER")) | K9: =IF($F9=0,"NA",IF($A9=INDIRECT("'"&$A9&"'!$B$1"),IF(VLOOKUP(K$1,INDIRECT("'"&$A9&"'!$A$12:$Z$19"),MATCH("Points (Auto-generate)",INDIRECT("'"&$A9&"'!$A$12:$Z$12"),0),0)="","?",VLOOKUP(K$1,INDIRECT("'"&$A9&"'!$A$12:$Z$19"),MATCH("Points (Auto-generate)",INDIRECT("'"&$A9&"'!$A$12:$Z$12"),0),0)),"ER")) | L9: =IF($F9=0,"NA",IF($A9=INDIRECT("'"&$A9&"'!$B$1"),IF(VLOOKUP(L$1,INDIRECT("'"&$A9&"'!$A$12:$Z$19"),MATCH("Points (Auto-generate)",INDIRECT("'"&$A9&"'!$A$12:$Z$12"),0),0)="","?",VLOOKUP(L$1,INDIRECT("'"&$A9&"'!$A$12:$Z$19"),MATCH("Points (Auto-generate)",INDIRECT("'"&$A9&"'!$A$12:$Z$12"),0),0)),"ER")) | M9: =IF($F9=0,"NA",IF($A9=INDIRECT("'"&$A9&"'!$B$1"),IF(VLOOKUP(M$1,INDIRECT("'"&$A9&"'!$A$12:$Z$19"),MATCH("Points (Auto-generate)",INDIRECT("'"&$A9&"'!$A$12:$Z$12"),0),0)="","?",VLOOKUP(M$1,INDIRECT("'"&$A9&"'!$A$12:$Z$19"),MATCH("Points (Auto-generate)",INDIRECT("'"&$A9&"'!$A$12:$Z$12"),0),0)),"ER"))
A10: UPD2d | B10: =VLOOKUP($A10,'PARASTATAL Questions'!$A:$J,3,0)&"" | C10: =VLOOKUP($A10,'PARASTATAL Questions'!$A:$J,4,0)&"" | D10: =VLOOKUP($A10,'PARASTATAL Questions'!$A:$J,5,0)&"" | E10: =VLOOKUP($A10,'PARASTATAL Questions'!$A:$J,7,0)&"" | F10: =VLOOKUP($A10,'PARASTATAL Questions'!$A:$J,6,0) | G10: =IF($F10=0,"NA",IF($A10=INDIRECT("'"&$A10&"'!$B$1"),IF(VLOOKUP(G$1,INDIRECT("'"&$A10&"'!$A$12:$Z$19"),MATCH("Points (Auto-generate)",INDIRECT("'"&$A10&"'!$A$12:$Z$12"),0),0)="","?",VLOOKUP(G$1,INDIRECT("'"&$A10&"'!$A$12:$Z$19"),MATCH("Points (Auto-generate)",INDIRECT("'"&$A10&"'!$A$12:$Z$12"),0),0)),"ER")) | H10: =IF($F10=0,"NA",IF($A10=INDIRECT("'"&$A10&"'!$B$1"),IF(VLOOKUP(H$1,INDIRECT("'"&$A10&"'!$A$12:$Z$19"),MATCH("Points (Auto-generate)",INDIRECT("'"&$A10&"'!$A$12:$Z$12"),0),0)="","?",VLOOKUP(H$1,INDIRECT("'"&$A10&"'!$A$12:$Z$19"),MATCH("Points (Auto-generate)",INDIRECT("'"&$A10&"'!$A$12:$Z$12"),0),0)),"ER")) | I10: =IF($F10=0,"NA",IF($A10=INDIRECT("'"&$A10&"'!$B$1"),IF(VLOOKUP(I$1,INDIRECT("'"&$A10&"'!$A$12:$Z$19"),MATCH("Points (Auto-generate)",INDIRECT("'"&$A10&"'!$A$12:$Z$12"),0),0)="","?",VLOOKUP(I$1,INDIRECT("'"&$A10&"'!$A$12:$Z$19"),MATCH("Points (Auto-generate)",INDIRECT("'"&$A10&"'!$A$12:$Z$12"),0),0)),"ER")) | J10: =IF($F10=0,"NA",IF($A10=INDIRECT("'"&$A10&"'!$B$1"),IF(VLOOKUP(J$1,INDIRECT("'"&$A10&"'!$A$12:$Z$19"),MATCH("Points (Auto-generate)",INDIRECT("'"&$A10&"'!$A$12:$Z$12"),0),0)="","?",VLOOKUP(J$1,INDIRECT("'"&$A10&"'!$A$12:$Z$19"),MATCH("Points (Auto-generate)",INDIRECT("'"&$A10&"'!$A$12:$Z$12"),0),0)),"ER")) | K10: =IF($F10=0,"NA",IF($A10=INDIRECT("'"&$A10&"'!$B$1"),IF(VLOOKUP(K$1,INDIRECT("'"&$A10&"'!$A$12:$Z$19"),MATCH("Points (Auto-generate)",INDIRECT("'"&$A10&"'!$A$12:$Z$12"),0),0)="","?",VLOOKUP(K$1,INDIRECT("'"&$A10&"'!$A$12:$Z$19"),MATCH("Points (Auto-generate)",INDIRECT("'"&$A10&"'!$A$12:$Z$12"),0),0)),"ER")) | L10: =IF($F10=0,"NA",IF($A10=INDIRECT("'"&$A10&"'!$B$1"),IF(VLOOKUP(L$1,INDIRECT("'"&$A10&"'!$A$12:$Z$19"),MATCH("Points (Auto-generate)",INDIRECT("'"&$A10&"'!$A$12:$Z$12"),0),0)="","?",VLOOKUP(L$1,INDIRECT("'"&$A10&"'!$A$12:$Z$19"),MATCH("Points (Auto-generate)",INDIRECT("'"&$A10&"'!$A$12:$Z$12"),0),0)),"ER")) | M10: =IF($F10=0,"NA",IF($A10=INDIRECT("'"&$A10&"'!$B$1"),IF(VLOOKUP(M$1,INDIRECT("'"&$A10&"'!$A$12:$Z$19"),MATCH("Points (Auto-generate)",INDIRECT("'"&$A10&"'!$A$12:$Z$12"),0),0)="","?",VLOOKUP(M$1,INDIRECT("'"&$A10&"'!$A$12:$Z$19"),MATCH("Points (Auto-generate)",INDIRECT("'"&$A10&"'!$A$12:$Z$12"),0),0)),"ER"))
A11: UPD3 | B11: =VLOOKUP($A11,'PARASTATAL Questions'!$A:$J,3,0)&"" | C11: =VLOOKUP($A11,'PARASTATAL Questions'!$A:$J,4,0)&"" | D11: =VLOOKUP($A11,'PARASTATAL Questions'!$A:$J,5,0)&"" | E11: =VLOOKUP($A11,'PARASTATAL Questions'!$A:$J,7,0)&"" | F11: =VLOOKUP($A11,'PARASTATAL Questions'!$A:$J,6,0) | G11: =IF(OR(G12="ER",G13="ER"),"ER",IF(OR(G12="?",G13="?"),"?",IF(AND(G12="NA",G13="NA"),"NA",SUM(G12,G13)/((G12<>"NA")*$F$12+(G13<>"NA")*$F$13)*$F11))) | H11: =IF(OR(H12="ER",H13="ER"),"ER",IF(OR(H12="?",H13="?"),"?",IF(AND(H12="NA",H13="NA"),"NA",SUM(H12,H13)/((H12<>"NA")*$F$12+(H13<>"NA")*$F$13)*$F11))) | I11: =IF(OR(I12="ER",I13="ER"),"ER",IF(OR(I12="?",I13="?"),"?",IF(AND(I12="NA",I13="NA"),"NA",SUM(I12,I13)/((I12<>"NA")*$F$12+(I13<>"NA")*$F$13)*$F11))) | J11: =IF(OR(J12="ER",J13="ER"),"ER",IF(OR(J12="?",J13="?"),"?",IF(AND(J12="NA",J13="NA"),"NA",SUM(J12,J13)/((J12<>"NA")*$F$12+(J13<>"NA")*$F$13)*$F11))) | K11: =IF(OR(K12="ER",K13="ER"),"ER",IF(OR(K12="?",K13="?"),"?",IF(AND(K12="NA",K13="NA"),"NA",SUM(K12,K13)/((K12<>"NA")*$F$12+(K13<>"NA")*$F$13)*$F11))) | L11: =IF(OR(L12="ER",L13="ER"),"ER",IF(OR(L12="?",L13="?"),"?",IF(AND(L12="NA",L13="NA"),"NA",SUM(L12,L13)/((L12<>"NA")*$F$12+(L13<>"NA")*$F$13)*$F11))) | M11: =IF(OR(M12="ER",M13="ER"),"ER",IF(OR(M12="?",M13="?"),"?",IF(AND(M12="NA",M13="NA"),"NA",SUM(M12,M13)/((M12<>"NA")*$F$12+(M13<>"NA")*$F$13)*$F11)))
A12: UPD3a | B12: =VLOOKUP($A12,'PARASTATAL Questions'!$A:$J,3,0)&"" | C12: =VLOOKUP($A12,'PARASTATAL Questions'!$A:$J,4,0)&"" | D12: =VLOOKUP($A12,'PARASTATAL Questions'!$A:$J,5,0)&"" | E12: =VLOOKUP($A12,'PARASTATAL Questions'!$A:$J,7,0)&"" | F12: =VLOOKUP($A12,'PARASTATAL Questions'!$A:$J,6,0) | G12: =IF($F12=0,"NA",IF($A12=INDIRECT("'"&$A12&"'!$B$1"),IF(VLOOKUP(G$1,INDIRECT("'"&$A12&"'!$A$12:$Z$19"),MATCH("Points (Auto-generate)",INDIRECT("'"&$A12&"'!$A$12:$Z$12"),0),0)="","?",VLOOKUP(G$1,INDIRECT("'"&$A12&"'!$A$12:$Z$19"),MATCH("Points (Auto-generate)",INDIRECT("'"&$A12&"'!$A$12:$Z$12"),0),0)),"ER")) | H12: =IF($F12=0,"NA",IF($A12=INDIRECT("'"&$A12&"'!$B$1"),IF(VLOOKUP(H$1,INDIRECT("'"&$A12&"'!$A$12:$Z$19"),MATCH("Points (Auto-generate)",INDIRECT("'"&$A12&"'!$A$12:$Z$12"),0),0)="","?",VLOOKUP(H$1,INDIRECT("'"&$A12&"'!$A$12:$Z$19"),MATCH("Points (Auto-generate)",INDIRECT("'"&$A12&"'!$A$12:$Z$12"),0),0)),"ER")) | I12: =IF($F12=0,"NA",IF($A12=INDIRECT("'"&$A12&"'!$B$1"),IF(VLOOKUP(I$1,INDIRECT("'"&$A12&"'!$A$12:$Z$19"),MATCH("Points (Auto-generate)",INDIRECT("'"&$A12&"'!$A$12:$Z$12"),0),0)="","?",VLOOKUP(I$1,INDIRECT("'"&$A12&"'!$A$12:$Z$19"),MATCH("Points (Auto-generate)",INDIRECT("'"&$A12&"'!$A$12:$Z$12"),0),0)),"ER")) | J12: =IF($F12=0,"NA",IF($A12=INDIRECT("'"&$A12&"'!$B$1"),IF(VLOOKUP(J$1,INDIRECT("'"&$A12&"'!$A$12:$Z$19"),MATCH("Points (Auto-generate)",INDIRECT("'"&$A12&"'!$A$12:$Z$12"),0),0)="","?",VLOOKUP(J$1,INDIRECT("'"&$A12&"'!$A$12:$Z$19"),MATCH("Points (Auto-generate)",INDIRECT("'"&$A12&"'!$A$12:$Z$12"),0),0)),"ER")) | K12: =IF($F12=0,"NA",IF($A12=INDIRECT("'"&$A12&"'!$B$1"),IF(VLOOKUP(K$1,INDIRECT("'"&$A12&"'!$A$12:$Z$19"),MATCH("Points (Auto-generate)",INDIRECT("'"&$A12&"'!$A$12:$Z$12"),0),0)="","?",VLOOKUP(K$1,INDIRECT("'"&$A12&"'!$A$12:$Z$19"),MATCH("Points (Auto-generate)",INDIRECT("'"&$A12&"'!$A$12:$Z$12"),0),0)),"ER")) | L12: =IF($F12=0,"NA",IF($A12=INDIRECT("'"&$A12&"'!$B$1"),IF(VLOOKUP(L$1,INDIRECT("'"&$A12&"'!$A$12:$Z$19"),MATCH("Points (Auto-generate)",INDIRECT("'"&$A12&"'!$A$12:$Z$12"),0),0)="","?",VLOOKUP(L$1,INDIRECT("'"&$A12&"'!$A$12:$Z$19"),MATCH("Points (Auto-generate)",INDIRECT("'"&$A12&"'!$A$12:$Z$12"),0),0)),"ER")) | M12: =IF($F12=0,"NA",IF($A12=INDIRECT("'"&$A12&"'!$B$1"),IF(VLOOKUP(M$1,INDIRECT("'"&$A12&"'!$A$12:$Z$19"),MATCH("Points (Auto-generate)",INDIRECT("'"&$A12&"'!$A$12:$Z$12"),0),0)="","?",VLOOKUP(M$1,INDIRECT("'"&$A12&"'!$A$12:$Z$19"),MATCH("Points (Auto-generate)",INDIRECT("'"&$A12&"'!$A$12:$Z$12"),0),0)),"ER"))
A13: UPD3b | B13: =VLOOKUP($A13,'PARASTATAL Questions'!$A:$J,3,0)&"" | C13: =VLOOKUP($A13,'PARASTATAL Questions'!$A:$J,4,0)&"" | D13: =VLOOKUP($A13,'PARASTATAL Questions'!$A:$J,5,0)&"" | E13: =VLOOKUP($A13,'PARASTATAL Questions'!$A:$J,7,0)&"" | F13: =VLOOKUP($A13,'PARASTATAL Questions'!$A:$J,6,0) | G13: =IF($F13=0,"NA",IF($A13=INDIRECT("'"&$A13&"'!$B$1"),IF(VLOOKUP(G$1,INDIRECT("'"&$A13&"'!$A$12:$Z$19"),MATCH("Points (Auto-generate)",INDIRECT("'"&$A13&"'!$A$12:$Z$12"),0),0)="","?",VLOOKUP(G$1,INDIRECT("'"&$A13&"'!$A$12:$Z$19"),MATCH("Points (Auto-generate)",INDIRECT("'"&$A13&"'!$A$12:$Z$12"),0),0)),"ER")) | H13: =IF($F13=0,"NA",IF($A13=INDIRECT("'"&$A13&"'!$B$1"),IF(VLOOKUP(H$1,INDIRECT("'"&$A13&"'!$A$12:$Z$19"),MATCH("Points (Auto-generate)",INDIRECT("'"&$A13&"'!$A$12:$Z$12"),0),0)="","?",VLOOKUP(H$1,INDIRECT("'"&$A13&"'!$A$12:$Z$19"),MATCH("Points (Auto-generate)",INDIRECT("'"&$A13&"'!$A$12:$Z$12"),0),0)),"ER")) | I13: =IF($F13=0,"NA",IF($A13=INDIRECT("'"&$A13&"'!$B$1"),IF(VLOOKUP(I$1,INDIRECT("'"&$A13&"'!$A$12:$Z$19"),MATCH("Points (Auto-generate)",INDIRECT("'"&$A13&"'!$A$12:$Z$12"),0),0)="","?",VLOOKUP(I$1,INDIRECT("'"&$A13&"'!$A$12:$Z$19"),MATCH("Points (Auto-generate)",INDIRECT("'"&$A13&"'!$A$12:$Z$12"),0),0)),"ER")) | J13: =IF($F13=0,"NA",IF($A13=INDIRECT("'"&$A13&"'!$B$1"),IF(VLOOKUP(J$1,INDIRECT("'"&$A13&"'!$A$12:$Z$19"),MATCH("Points (Auto-generate)",INDIRECT("'"&$A13&"'!$A$12:$Z$12"),0),0)="","?",VLOOKUP(J$1,INDIRECT("'"&$A13&"'!$A$12:$Z$19"),MATCH("Points (Auto-generate)",INDIRECT("'"&$A13&"'!$A$12:$Z$12"),0),0)),"ER")) | K13: =IF($F13=0,"NA",IF($A13=INDIRECT("'"&$A13&"'!$B$1"),IF(VLOOKUP(K$1,INDIRECT("'"&$A13&"'!$A$12:$Z$19"),MATCH("Points (Auto-generate)",INDIRECT("'"&$A13&"'!$A$12:$Z$12"),0),0)="","?",VLOOKUP(K$1,INDIRECT("'"&$A13&"'!$A$12:$Z$19"),MATCH("Points (Auto-generate)",INDIRECT("'"&$A13&"'!$A$12:$Z$12"),0),0)),"ER")) | L13: =IF($F13=0,"NA",IF($A13=INDIRECT("'"&$A13&"'!$B$1"),IF(VLOOKUP(L$1,INDIRECT("'"&$A13&"'!$A$12:$Z$19"),MATCH("Points (Auto-generate)",INDIRECT("'"&$A13&"'!$A$12:$Z$12"),0),0)="","?",VLOOKUP(L$1,INDIRECT("'"&$A13&"'!$A$12:$Z$19"),MATCH("Points (Auto-generate)",INDIRECT("'"&$A13&"'!$A$12:$Z$12"),0),0)),"ER")) | M13: =IF($F13=0,"NA",IF($A13=INDIRECT("'"&$A13&"'!$B$1"),IF(VLOOKUP(M$1,INDIRECT("'"&$A13&"'!$A$12:$Z$19"),MATCH("Points (Auto-generate)",INDIRECT("'"&$A13&"'!$A$12:$Z$12"),0),0)="","?",VLOOKUP(M$1,INDIRECT("'"&$A13&"'!$A$12:$Z$19"),MATCH("Points (Auto-generate)",INDIRECT("'"&$A13&"'!$A$12:$Z$12"),0),0)),"ER"))
A14: UPD4 | B14: =VLOOKUP($A14,'PARASTATAL Questions'!$A:$J,3,0)&"" | C14: =VLOOKUP($A14,'PARASTATAL Questions'!$A:$J,4,0)&"" | D14: =VLOOKUP($A14,'PARASTATAL Questions'!$A:$J,5,0)&"" | E14: =VLOOKUP($A14,'PARASTATAL Questions'!$A:$J,7,0)&"" | F14: =VLOOKUP($A14,'PARASTATAL Questions'!$A:$J,6,0) | G14: =IF(OR(G15="ER",G16="ER"),"ER",IF(OR(G15="?",G16="?"),"?",IF(AND(G15="NA",G16="NA"),"NA",SUM(G15,G16)/((G15<>"NA")*$F$15+(G16<>"NA")*$F$16)*$F14))) | H14: =IF(OR(H15="ER",H16="ER"),"ER",IF(OR(H15="?",H16="?"),"?",IF(AND(H15="NA",H16="NA"),"NA",SUM(H15,H16)/((H15<>"NA")*$F$15+(H16<>"NA")*$F$16)*$F14))) | I14: =IF(OR(I15="ER",I16="ER"),"ER",IF(OR(I15="?",I16="?"),"?",IF(AND(I15="NA",I16="NA"),"NA",SUM(I15,I16)/((I15<>"NA")*$F$15+(I16<>"NA")*$F$16)*$F14))) | J14: =IF(OR(J15="ER",J16="ER"),"ER",IF(OR(J15="?",J16="?"),"?",IF(AND(J15="NA",J16="NA"),"NA",SUM(J15,J16)/((J15<>"NA")*$F$15+(J16<>"NA")*$F$16)*$F14))) | K14: =IF(OR(K15="ER",K16="ER"),"ER",IF(OR(K15="?",K16="?"),"?",IF(AND(K15="NA",K16="NA"),"NA",SUM(K15,K16)/((K15<>"NA")*$F$15+(K16<>"NA")*$F$16)*$F14))) | L14: =IF(OR(L15="ER",L16="ER"),"ER",IF(OR(L15="?",L16="?"),"?",IF(AND(L15="NA",L16="NA"),"NA",SUM(L15,L16)/((L15<>"NA")*$F$15+(L16<>"NA")*$F$16)*$F14))) | M14: =IF(OR(M15="ER",M16="ER"),"ER",IF(OR(M15="?",M16="?"),"?",IF(AND(M15="NA",M16="NA"),"NA",SUM(M15,M16)/((M15<>"NA")*$F$15+(M16<>"NA")*$F$16)*$F14)))
A15: UPD4a | B15: =VLOOKUP($A15,'PARASTATAL Questions'!$A:$J,3,0)&"" | C15: =VLOOKUP($A15,'PARASTATAL Questions'!$A:$J,4,0)&"" | D15: =VLOOKUP($A15,'PARASTATAL Questions'!$A:$J,5,0)&"" | E15: =VLOOKUP($A15,'PARASTATAL Questions'!$A:$J,7,0)&"" | F15: =VLOOKUP($A15,'PARASTATAL Questions'!$A:$J,6,0) | G15: =IF($F15=0,"NA",IF($A15=INDIRECT("'"&$A15&"'!$B$1"),IF(VLOOKUP(G$1,INDIRECT("'"&$A15&"'!$A$12:$Z$19"),MATCH("Points (Auto-generate)",INDIRECT("'"&$A15&"'!$A$12:$Z$12"),0),0)="","?",VLOOKUP(G$1,INDIRECT("'"&$A15&"'!$A$12:$Z$19"),MATCH("Points (Auto-generate)",INDIRECT("'"&$A15&"'!$A$12:$Z$12"),0),0)),"ER")) | H15: =IF($F15=0,"NA",IF($A15=INDIRECT("'"&$A15&"'!$B$1"),IF(VLOOKUP(H$1,INDIRECT("'"&$A15&"'!$A$12:$Z$19"),MATCH("Points (Auto-generate)",INDIRECT("'"&$A15&"'!$A$12:$Z$12"),0),0)="","?",VLOOKUP(H$1,INDIRECT("'"&$A15&"'!$A$12:$Z$19"),MATCH("Points (Auto-generate)",INDIRECT("'"&$A15&"'!$A$12:$Z$12"),0),0)),"ER")) | I15: =IF($F15=0,"NA",IF($A15=INDIRECT("'"&$A15&"'!$B$1"),IF(VLOOKUP(I$1,INDIRECT("'"&$A15&"'!$A$12:$Z$19"),MATCH("Points (Auto-generate)",INDIRECT("'"&$A15&"'!$A$12:$Z$12"),0),0)="","?",VLOOKUP(I$1,INDIRECT("'"&$A15&"'!$A$12:$Z$19"),MATCH("Points (Auto-generate)",INDIRECT("'"&$A15&"'!$A$12:$Z$12"),0),0)),"ER")) | J15: =IF($F15=0,"NA",IF($A15=INDIRECT("'"&$A15&"'!$B$1"),IF(VLOOKUP(J$1,INDIRECT("'"&$A15&"'!$A$12:$Z$19"),MATCH("Points (Auto-generate)",INDIRECT("'"&$A15&"'!$A$12:$Z$12"),0),0)="","?",VLOOKUP(J$1,INDIRECT("'"&$A15&"'!$A$12:$Z$19"),MATCH("Points (Auto-generate)",INDIRECT("'"&$A15&"'!$A$12:$Z$12"),0),0)),"ER")) | K15: =IF($F15=0,"NA",IF($A15=INDIRECT("'"&$A15&"'!$B$1"),IF(VLOOKUP(K$1,INDIRECT("'"&$A15&"'!$A$12:$Z$19"),MATCH("Points (Auto-generate)",INDIRECT("'"&$A15&"'!$A$12:$Z$12"),0),0)="","?",VLOOKUP(K$1,INDIRECT("'"&$A15&"'!$A$12:$Z$19"),MATCH("Points (Auto-generate)",INDIRECT("'"&$A15&"'!$A$12:$Z$12"),0),0)),"ER")) | L15: =IF($F15=0,"NA",IF($A15=INDIRECT("'"&$A15&"'!$B$1"),IF(VLOOKUP(L$1,INDIRECT("'"&$A15&"'!$A$12:$Z$19"),MATCH("Points (Auto-generate)",INDIRECT("'"&$A15&"'!$A$12:$Z$12"),0),0)="","?",VLOOKUP(L$1,INDIRECT("'"&$A15&"'!$A$12:$Z$19"),MATCH("Points (Auto-generate)",INDIRECT("'"&$A15&"'!$A$12:$Z$12"),0),0)),"ER")) | M15: =IF($F15=0,"NA",IF($A15=INDIRECT("'"&$A15&"'!$B$1"),IF(VLOOKUP(M$1,INDIRECT("'"&$A15&"'!$A$12:$Z$19"),MATCH("Points (Auto-generate)",INDIRECT("'"&$A15&"'!$A$12:$Z$12"),0),0)="","?",VLOOKUP(M$1,INDIRECT("'"&$A15&"'!$A$12:$Z$19"),MATCH("Points (Auto-generate)",INDIRECT("'"&$A15&"'!$A$12:$Z$12"),0),0)),"ER"))
A16: UPD4b | B16: =VLOOKUP($A16,'PARASTATAL Questions'!$A:$J,3,0)&"" | C16: =VLOOKUP($A16,'PARASTATAL Questions'!$A:$J,4,0)&"" | D16: =VLOOKUP($A16,'PARASTATAL Questions'!$A:$J,5,0)&"" | E16: =VLOOKUP($A16,'PARASTATAL Questions'!$A:$J,7,0)&"" | F16: =VLOOKUP($A16,'PARASTATAL Questions'!$A:$J,6,0) | G16: =IF($F16=0,"NA",IF($A16=INDIRECT("'"&$A16&"'!$B$1"),IF(VLOOKUP(G$1,INDIRECT("'"&$A16&"'!$A$12:$Z$19"),MATCH("Points (Auto-generate)",INDIRECT("'"&$A16&"'!$A$12:$Z$12"),0),0)="","?",VLOOKUP(G$1,INDIRECT("'"&$A16&"'!$A$12:$Z$19"),MATCH("Points (Auto-generate)",INDIRECT("'"&$A16&"'!$A$12:$Z$12"),0),0)),"ER")) | H16: =IF($F16=0,"NA",IF($A16=INDIRECT("'"&$A16&"'!$B$1"),IF(VLOOKUP(H$1,INDIRECT("'"&$A16&"'!$A$12:$Z$19"),MATCH("Points (Auto-generate)",INDIRECT("'"&$A16&"'!$A$12:$Z$12"),0),0)="","?",VLOOKUP(H$1,INDIRECT("'"&$A16&"'!$A$12:$Z$19"),MATCH("Points (Auto-generate)",INDIRECT("'"&$A16&"'!$A$12:$Z$12"),0),0)),"ER")) | I16: =IF($F16=0,"NA",IF($A16=INDIRECT("'"&$A16&"'!$B$1"),IF(VLOOKUP(I$1,INDIRECT("'"&$A16&"'!$A$12:$Z$19"),MATCH("Points (Auto-generate)",INDIRECT("'"&$A16&"'!$A$12:$Z$12"),0),0)="","?",VLOOKUP(I$1,INDIRECT("'"&$A16&"'!$A$12:$Z$19"),MATCH("Points (Auto-generate)",INDIRECT("'"&$A16&"'!$A$12:$Z$12"),0),0)),"ER")) | J16: =IF($F16=0,"NA",IF($A16=INDIRECT("'"&$A16&"'!$B$1"),IF(VLOOKUP(J$1,INDIRECT("'"&$A16&"'!$A$12:$Z$19"),MATCH("Points (Auto-generate)",INDIRECT("'"&$A16&"'!$A$12:$Z$12"),0),0)="","?",VLOOKUP(J$1,INDIRECT("'"&$A16&"'!$A$12:$Z$19"),MATCH("Points (Auto-generate)",INDIRECT("'"&$A16&"'!$A$12:$Z$12"),0),0)),"ER")) | K16: =IF($F16=0,"NA",IF($A16=INDIRECT("'"&$A16&"'!$B$1"),IF(VLOOKUP(K$1,INDIRECT("'"&$A16&"'!$A$12:$Z$19"),MATCH("Points (Auto-generate)",INDIRECT("'"&$A16&"'!$A$12:$Z$12"),0),0)="","?",VLOOKUP(K$1,INDIRECT("'"&$A16&"'!$A$12:$Z$19"),MATCH("Points (Auto-generate)",INDIRECT("'"&$A16&"'!$A$12:$Z$12"),0),0)),"ER")) | L16: =IF($F16=0,"NA",IF($A16=INDIRECT("'"&$A16&"'!$B$1"),IF(VLOOKUP(L$1,INDIRECT("'"&$A16&"'!$A$12:$Z$19"),MATCH("Points (Auto-generate)",INDIRECT("'"&$A16&"'!$A$12:$Z$12"),0),0)="","?",VLOOKUP(L$1,INDIRECT("'"&$A16&"'!$A$12:$Z$19"),MATCH("Points (Auto-generate)",INDIRECT("'"&$A16&"'!$A$12:$Z$12"),0),0)),"ER")) | M16: =IF($F16=0,"NA",IF($A16=INDIRECT("'"&$A16&"'!$B$1"),IF(VLOOKUP(M$1,INDIRECT("'"&$A16&"'!$A$12:$Z$19"),MATCH("Points (Auto-generate)",INDIRECT("'"&$A16&"'!$A$12:$Z$12"),0),0)="","?",VLOOKUP(M$1,INDIRECT("'"&$A16&"'!$A$12:$Z$19"),MATCH("Points (Auto-generate)",INDIRECT("'"&$A16&"'!$A$12:$Z$12"),0),0)),"ER"))
A17: UPD5 | B17: =VLOOKUP($A17,'PARASTATAL Questions'!$A:$J,3,0)&"" | C17: =VLOOKUP($A17,'PARASTATAL Questions'!$A:$J,4,0)&"" | D17: =VLOOKUP($A17,'PARASTATAL Questions'!$A:$J,5,0)&"" | E17: =VLOOKUP($A17,'PARASTATAL Questions'!$A:$J,7,0)&"" | F17: =VLOOKUP($A17,'PARASTATAL Questions'!$A:$J,6,0) | G17: =IF(OR(G18="ER",G19="ER"),"ER",IF(OR(G18="?",G19="?"),"?",IF(AND(G18="NA",G19="NA"),"NA",SUM(G18,G19)/((G18<>"NA")*$F$18+(G19<>"NA")*$F$19)*$F17))) | H17: =IF(OR(H18="ER",H19="ER"),"ER",IF(OR(H18="?",H19="?"),"?",IF(AND(H18="NA",H19="NA"),"NA",SUM(H18,H19)/((H18<>"NA")*$F$18+(H19<>"NA")*$F$19)*$F17))) | I17: =IF(OR(I18="ER",I19="ER"),"ER",IF(OR(I18="?",I19="?"),"?",IF(AND(I18="NA",I19="NA"),"NA",SUM(I18,I19)/((I18<>"NA")*$F$18+(I19<>"NA")*$F$19)*$F17))) | J17: =IF(OR(J18="ER",J19="ER"),"ER",IF(OR(J18="?",J19="?"),"?",IF(AND(J18="NA",J19="NA"),"NA",SUM(J18,J19)/((J18<>"NA")*$F$18+(J19<>"NA")*$F$19)*$F17))) | K17: =IF(OR(K18="ER",K19="ER"),"ER",IF(OR(K18="?",K19="?"),"?",IF(AND(K18="NA",K19="NA"),"NA",SUM(K18,K19)/((K18<>"NA")*$F$18+(K19<>"NA")*$F$19)*$F17))) | L17: =IF(OR(L18="ER",L19="ER"),"ER",IF(OR(L18="?",L19="?"),"?",IF(AND(L18="NA",L19="NA"),"NA",SUM(L18,L19)/((L18<>"NA")*$F$18+(L19<>"NA")*$F$19)*$F17))) | M17: =IF(OR(M18="ER",M19="ER"),"ER",IF(OR(M18="?",M19="?"),"?",IF(AND(M18="NA",M19="NA"),"NA",SUM(M18,M19)/((M18<>"NA")*$F$18+(M19<>"NA")*$F$19)*$F17)))
A18: UPD5a | B18: =VLOOKUP($A18,'PARASTATAL Questions'!$A:$J,3,0)&"" | C18: =VLOOKUP($A18,'PARASTATAL Questions'!$A:$J,4,0)&"" | D18: =VLOOKUP($A18,'PARASTATAL Questions'!$A:$J,5,0)&"" | E18: =VLOOKUP($A18,'PARASTATAL Questions'!$A:$J,7,0)&"" | F18: =VLOOKUP($A18,'PARASTATAL Questions'!$A:$J,6,0) | G18: =IF($F18=0,"NA",IF($A18=INDIRECT("'"&$A18&"'!$B$1"),IF(VLOOKUP(G$1,INDIRECT("'"&$A18&"'!$A$12:$Z$19"),MATCH("Points (Auto-generate)",INDIRECT("'"&$A18&"'!$A$12:$Z$12"),0),0)="","?",VLOOKUP(G$1,INDIRECT("'"&$A18&"'!$A$12:$Z$19"),MATCH("Points (Auto-generate)",INDIRECT("'"&$A18&"'!$A$12:$Z$12"),0),0)),"ER")) | H18: =IF($F18=0,"NA",IF($A18=INDIRECT("'"&$A18&"'!$B$1"),IF(VLOOKUP(H$1,INDIRECT("'"&$A18&"'!$A$12:$Z$19"),MATCH("Points (Auto-generate)",INDIRECT("'"&$A18&"'!$A$12:$Z$12"),0),0)="","?",VLOOKUP(H$1,INDIRECT("'"&$A18&"'!$A$12:$Z$19"),MATCH("Points (Auto-generate)",INDIRECT("'"&$A18&"'!$A$12:$Z$12"),0),0)),"ER")) | I18: =IF($F18=0,"NA",IF($A18=INDIRECT("'"&$A18&"'!$B$1"),IF(VLOOKUP(I$1,INDIRECT("'"&$A18&"'!$A$12:$Z$19"),MATCH("Points (Auto-generate)",INDIRECT("'"&$A18&"'!$A$12:$Z$12"),0),0)="","?",VLOOKUP(I$1,INDIRECT("'"&$A18&"'!$A$12:$Z$19"),MATCH("Points (Auto-generate)",INDIRECT("'"&$A18&"'!$A$12:$Z$12"),0),0)),"ER")) | J18: =IF($F18=0,"NA",IF($A18=INDIRECT("'"&$A18&"'!$B$1"),IF(VLOOKUP(J$1,INDIRECT("'"&$A18&"'!$A$12:$Z$19"),MATCH("Points (Auto-generate)",INDIRECT("'"&$A18&"'!$A$12:$Z$12"),0),0)="","?",VLOOKUP(J$1,INDIRECT("'"&$A18&"'!$A$12:$Z$19"),MATCH("Points (Auto-generate)",INDIRECT("'"&$A18&"'!$A$12:$Z$12"),0),0)),"ER")) | K18: =IF($F18=0,"NA",IF($A18=INDIRECT("'"&$A18&"'!$B$1"),IF(VLOOKUP(K$1,INDIRECT("'"&$A18&"'!$A$12:$Z$19"),MATCH("Points (Auto-generate)",INDIRECT("'"&$A18&"'!$A$12:$Z$12"),0),0)="","?",VLOOKUP(K$1,INDIRECT("'"&$A18&"'!$A$12:$Z$19"),MATCH("Points (Auto-generate)",INDIRECT("'"&$A18&"'!$A$12:$Z$12"),0),0)),"ER")) | L18: =IF($F18=0,"NA",IF($A18=INDIRECT("'"&$A18&"'!$B$1"),IF(VLOOKUP(L$1,INDIRECT("'"&$A18&"'!$A$12:$Z$19"),MATCH("Points (Auto-generate)",INDIRECT("'"&$A18&"'!$A$12:$Z$12"),0),0)="","?",VLOOKUP(L$1,INDIRECT("'"&$A18&"'!$A$12:$Z$19"),MATCH("Points (Auto-generate)",INDIRECT("'"&$A18&"'!$A$12:$Z$12"),0),0)),"ER")) | M18: =IF($F18=0,"NA",IF($A18=INDIRECT("'"&$A18&"'!$B$1"),IF(VLOOKUP(M$1,INDIRECT("'"&$A18&"'!$A$12:$Z$19"),MATCH("Points (Auto-generate)",INDIRECT("'"&$A18&"'!$A$12:$Z$12"),0),0)="","?",VLOOKUP(M$1,INDIRECT("'"&$A18&"'!$A$12:$Z$19"),MATCH("Points (Auto-generate)",INDIRECT("'"&$A18&"'!$A$12:$Z$12"),0),0)),"ER"))
A19: UPD5b | B19: =VLOOKUP($A19,'PARASTATAL Questions'!$A:$J,3,0)&"" | C19: =VLOOKUP($A19,'PARASTATAL Questions'!$A:$J,4,0)&"" | D19: =VLOOKUP($A19,'PARASTATAL Questions'!$A:$J,5,0)&"" | E19: =VLOOKUP($A19,'PARASTATAL Questions'!$A:$J,7,0)&"" | F19: =VLOOKUP($A19,'PARASTATAL Questions'!$A:$J,6,0) | G19: =IF($F19=0,"NA",IF($A19=INDIRECT("'"&$A19&"'!$B$1"),IF(VLOOKUP(G$1,INDIRECT("'"&$A19&"'!$A$12:$Z$19"),MATCH("Points (Auto-generate)",INDIRECT("'"&$A19&"'!$A$12:$Z$12"),0),0)="","?",VLOOKUP(G$1,INDIRECT("'"&$A19&"'!$A$12:$Z$19"),MATCH("Points (Auto-generate)",INDIRECT("'"&$A19&"'!$A$12:$Z$12"),0),0)),"ER")) | H19: =IF($F19=0,"NA",IF($A19=INDIRECT("'"&$A19&"'!$B$1"),IF(VLOOKUP(H$1,INDIRECT("'"&$A19&"'!$A$12:$Z$19"),MATCH("Points (Auto-generate)",INDIRECT("'"&$A19&"'!$A$12:$Z$12"),0),0)="","?",VLOOKUP(H$1,INDIRECT("'"&$A19&"'!$A$12:$Z$19"),MATCH("Points (Auto-generate)",INDIRECT("'"&$A19&"'!$A$12:$Z$12"),0),0)),"ER")) | I19: =IF($F19=0,"NA",IF($A19=INDIRECT("'"&$A19&"'!$B$1"),IF(VLOOKUP(I$1,INDIRECT("'"&$A19&"'!$A$12:$Z$19"),MATCH("Points (Auto-generate)",INDIRECT("'"&$A19&"'!$A$12:$Z$12"),0),0)="","?",VLOOKUP(I$1,INDIRECT("'"&$A19&"'!$A$12:$Z$19"),MATCH("Points (Auto-generate)",INDIRECT("'"&$A19&"'!$A$12:$Z$12"),0),0)),"ER")) | J19: =IF($F19=0,"NA",IF($A19=INDIRECT("'"&$A19&"'!$B$1"),IF(VLOOKUP(J$1,INDIRECT("'"&$A19&"'!$A$12:$Z$19"),MATCH("Points (Auto-generate)",INDIRECT("'"&$A19&"'!$A$12:$Z$12"),0),0)="","?",VLOOKUP(J$1,INDIRECT("'"&$A19&"'!$A$12:$Z$19"),MATCH("Points (Auto-generate)",INDIRECT("'"&$A19&"'!$A$12:$Z$12"),0),0)),"ER")) | K19: =IF($F19=0,"NA",IF($A19=INDIRECT("'"&$A19&"'!$B$1"),IF(VLOOKUP(K$1,INDIRECT("'"&$A19&"'!$A$12:$Z$19"),MATCH("Points (Auto-generate)",INDIRECT("'"&$A19&"'!$A$12:$Z$12"),0),0)="","?",VLOOKUP(K$1,INDIRECT("'"&$A19&"'!$A$12:$Z$19"),MATCH("Points (Auto-generate)",INDIRECT("'"&$A19&"'!$A$12:$Z$12"),0),0)),"ER")) | L19: =IF($F19=0,"NA",IF($A19=INDIRECT("'"&$A19&"'!$B$1"),IF(VLOOKUP(L$1,INDIRECT("'"&$A19&"'!$A$12:$Z$19"),MATCH("Points (Auto-generate)",INDIRECT("'"&$A19&"'!$A$12:$Z$12"),0),0)="","?",VLOOKUP(L$1,INDIRECT("'"&$A19&"'!$A$12:$Z$19"),MATCH("Points (Auto-generate)",INDIRECT("'"&$A19&"'!$A$12:$Z$12"),0),0)),"ER")) | M19: =IF($F19=0,"NA",IF($A19=INDIRECT("'"&$A19&"'!$B$1"),IF(VLOOKUP(M$1,INDIRECT("'"&$A19&"'!$A$12:$Z$19"),MATCH("Points (Auto-generate)",INDIRECT("'"&$A19&"'!$A$12:$Z$12"),0),0)="","?",VLOOKUP(M$1,INDIRECT("'"&$A19&"'!$A$12:$Z$19"),MATCH("Points (Auto-generate)",INDIRECT("'"&$A19&"'!$A$12:$Z$12"),0),0)),"ER"))
A20: UPD6 | B20: =VLOOKUP($A20,'PARASTATAL Questions'!$A:$J,3,0)&"" | C20: =VLOOKUP($A20,'PARASTATAL Questions'!$A:$J,4,0)&"" | D20: =VLOOKUP($A20,'PARASTATAL Questions'!$A:$J,5,0)&"" | E20: =VLOOKUP($A20,'PARASTATAL Questions'!$A:$J,7,0)&"" | F20: =VLOOKUP($A20,'PARASTATAL Questions'!$A:$J,6,0) | G20: =IF(OR(G21="ER",G22="ER"),"ER",IF(OR(G21="?",G22="?"),"?",IF(AND(G21="NA",G22="NA"),"NA",SUM(G21,G22)/((G21<>"NA")*$F$21+(G22<>"NA")*$F$22)*$F20))) | H20: =IF(OR(H21="ER",H22="ER"),"ER",IF(OR(H21="?",H22="?"),"?",IF(AND(H21="NA",H22="NA"),"NA",SUM(H21,H22)/((H21<>"NA")*$F$21+(H22<>"NA")*$F$22)*$F20))) | I20: =IF(OR(I21="ER",I22="ER"),"ER",IF(OR(I21="?",I22="?"),"?",IF(AND(I21="NA",I22="NA"),"NA",SUM(I21,I22)/((I21<>"NA")*$F$21+(I22<>"NA")*$F$22)*$F20))) | J20: =IF(OR(J21="ER",J22="ER"),"ER",IF(OR(J21="?",J22="?"),"?",IF(AND(J21="NA",J22="NA"),"NA",SUM(J21,J22)/((J21<>"NA")*$F$21+(J22<>"NA")*$F$22)*$F20))) | K20: =IF(OR(K21="ER",K22="ER"),"ER",IF(OR(K21="?",K22="?"),"?",IF(AND(K21="NA",K22="NA"),"NA",SUM(K21,K22)/((K21<>"NA")*$F$21+(K22<>"NA")*$F$22)*$F20))) | L20: =IF(OR(L21="ER",L22="ER"),"ER",IF(OR(L21="?",L22="?"),"?",IF(AND(L21="NA",L22="NA"),"NA",SUM(L21,L22)/((L21<>"NA")*$F$21+(L22<>"NA")*$F$22)*$F20))) | M20: =IF(OR(M21="ER",M22="ER"),"ER",IF(OR(M21="?",M22="?"),"?",IF(AND(M21="NA",M22="NA"),"NA",SUM(M21,M22)/((M21<>"NA")*$F$21+(M22<>"NA")*$F$22)*$F20)))
A21: UPD6a | B21: =VLOOKUP($A21,'PARASTATAL Questions'!$A:$J,3,0)&"" | C21: =VLOOKUP($A21,'PARASTATAL Questions'!$A:$J,4,0)&"" | D21: =VLOOKUP($A21,'PARASTATAL Questions'!$A:$J,5,0)&"" | E21: =VLOOKUP($A21,'PARASTATAL Questions'!$A:$J,7,0)&"" | F21: =VLOOKUP($A21,'PARASTATAL Questions'!$A:$J,6,0) | G21: =IF($F21=0,"NA",IF($A21=INDIRECT("'"&$A21&"'!$B$1"),IF(VLOOKUP(G$1,INDIRECT("'"&$A21&"'!$A$12:$Z$19"),MATCH("Points (Auto-generate)",INDIRECT("'"&$A21&"'!$A$12:$Z$12"),0),0)="","?",VLOOKUP(G$1,INDIRECT("'"&$A21&"'!$A$12:$Z$19"),MATCH("Points (Auto-generate)",INDIRECT("'"&$A21&"'!$A$12:$Z$12"),0),0)),"ER")) | H21: =IF($F21=0,"NA",IF($A21=INDIRECT("'"&$A21&"'!$B$1"),IF(VLOOKUP(H$1,INDIRECT("'"&$A21&"'!$A$12:$Z$19"),MATCH("Points (Auto-generate)",INDIRECT("'"&$A21&"'!$A$12:$Z$12"),0),0)="","?",VLOOKUP(H$1,INDIRECT("'"&$A21&"'!$A$12:$Z$19"),MATCH("Points (Auto-generate)",INDIRECT("'"&$A21&"'!$A$12:$Z$12"),0),0)),"ER")) | I21: =IF($F21=0,"NA",IF($A21=INDIRECT("'"&$A21&"'!$B$1"),IF(VLOOKUP(I$1,INDIRECT("'"&$A21&"'!$A$12:$Z$19"),MATCH("Points (Auto-generate)",INDIRECT("'"&$A21&"'!$A$12:$Z$12"),0),0)="","?",VLOOKUP(I$1,INDIRECT("'"&$A21&"'!$A$12:$Z$19"),MATCH("Points (Auto-generate)",INDIRECT("'"&$A21&"'!$A$12:$Z$12"),0),0)),"ER")) | J21: =IF($F21=0,"NA",IF($A21=INDIRECT("'"&$A21&"'!$B$1"),IF(VLOOKUP(J$1,INDIRECT("'"&$A21&"'!$A$12:$Z$19"),MATCH("Points (Auto-generate)",INDIRECT("'"&$A21&"'!$A$12:$Z$12"),0),0)="","?",VLOOKUP(J$1,INDIRECT("'"&$A21&"'!$A$12:$Z$19"),MATCH("Points (Auto-generate)",INDIRECT("'"&$A21&"'!$A$12:$Z$12"),0),0)),"ER")) | K21: =IF($F21=0,"NA",IF($A21=INDIRECT("'"&$A21&"'!$B$1"),IF(VLOOKUP(K$1,INDIRECT("'"&$A21&"'!$A$12:$Z$19"),MATCH("Points (Auto-generate)",INDIRECT("'"&$A21&"'!$A$12:$Z$12"),0),0)="","?",VLOOKUP(K$1,INDIRECT("'"&$A21&"'!$A$12:$Z$19"),MATCH("Points (Auto-generate)",INDIRECT("'"&$A21&"'!$A$12:$Z$12"),0),0)),"ER")) | L21: =IF($F21=0,"NA",IF($A21=INDIRECT("'"&$A21&"'!$B$1"),IF(VLOOKUP(L$1,INDIRECT("'"&$A21&"'!$A$12:$Z$19"),MATCH("Points (Auto-generate)",INDIRECT("'"&$A21&"'!$A$12:$Z$12"),0),0)="","?",VLOOKUP(L$1,INDIRECT("'"&$A21&"'!$A$12:$Z$19"),MATCH("Points (Auto-generate)",INDIRECT("'"&$A21&"'!$A$12:$Z$12"),0),0)),"ER")) | M21: =IF($F21=0,"NA",IF($A21=INDIRECT("'"&$A21&"'!$B$1"),IF(VLOOKUP(M$1,INDIRECT("'"&$A21&"'!$A$12:$Z$19"),MATCH("Points (Auto-generate)",INDIRECT("'"&$A21&"'!$A$12:$Z$12"),0),0)="","?",VLOOKUP(M$1,INDIRECT("'"&$A21&"'!$A$12:$Z$19"),MATCH("Points (Auto-generate)",INDIRECT("'"&$A21&"'!$A$12:$Z$12"),0),0)),"ER"))
A22: UPD6b | B22: =VLOOKUP($A22,'PARASTATAL Questions'!$A:$J,3,0)&"" | C22: =VLOOKUP($A22,'PARASTATAL Questions'!$A:$J,4,0)&"" | D22: =VLOOKUP($A22,'PARASTATAL Questions'!$A:$J,5,0)&"" | E22: =VLOOKUP($A22,'PARASTATAL Questions'!$A:$J,7,0)&"" | F22: =VLOOKUP($A22,'PARASTATAL Questions'!$A:$J,6,0) | G22: =IF($F22=0,"NA",IF($A22=INDIRECT("'"&$A22&"'!$B$1"),IF(VLOOKUP(G$1,INDIRECT("'"&$A22&"'!$A$12:$Z$19"),MATCH("Points (Auto-generate)",INDIRECT("'"&$A22&"'!$A$12:$Z$12"),0),0)="","?",VLOOKUP(G$1,INDIRECT("'"&$A22&"'!$A$12:$Z$19"),MATCH("Points (Auto-generate)",INDIRECT("'"&$A22&"'!$A$12:$Z$12"),0),0)),"ER")) | H22: =IF($F22=0,"NA",IF($A22=INDIRECT("'"&$A22&"'!$B$1"),IF(VLOOKUP(H$1,INDIRECT("'"&$A22&"'!$A$12:$Z$19"),MATCH("Points (Auto-generate)",INDIRECT("'"&$A22&"'!$A$12:$Z$12"),0),0)="","?",VLOOKUP(H$1,INDIRECT("'"&$A22&"'!$A$12:$Z$19"),MATCH("Points (Auto-generate)",INDIRECT("'"&$A22&"'!$A$12:$Z$12"),0),0)),"ER")) | I22: =IF($F22=0,"NA",IF($A22=INDIRECT("'"&$A22&"'!$B$1"),IF(VLOOKUP(I$1,INDIRECT("'"&$A22&"'!$A$12:$Z$19"),MATCH("Points (Auto-generate)",INDIRECT("'"&$A22&"'!$A$12:$Z$12"),0),0)="","?",VLOOKUP(I$1,INDIRECT("'"&$A22&"'!$A$12:$Z$19"),MATCH("Points (Auto-generate)",INDIRECT("'"&$A22&"'!$A$12:$Z$12"),0),0)),"ER")) | J22: =IF($F22=0,"NA",IF($A22=INDIRECT("'"&$A22&"'!$B$1"),IF(VLOOKUP(J$1,INDIRECT("'"&$A22&"'!$A$12:$Z$19"),MATCH("Points (Auto-generate)",INDIRECT("'"&$A22&"'!$A$12:$Z$12"),0),0)="","?",VLOOKUP(J$1,INDIRECT("'"&$A22&"'!$A$12:$Z$19"),MATCH("Points (Auto-generate)",INDIRECT("'"&$A22&"'!$A$12:$Z$12"),0),0)),"ER")) | K22: =IF($F22=0,"NA",IF($A22=INDIRECT("'"&$A22&"'!$B$1"),IF(VLOOKUP(K$1,INDIRECT("'"&$A22&"'!$A$12:$Z$19"),MATCH("Points (Auto-generate)",INDIRECT("'"&$A22&"'!$A$12:$Z$12"),0),0)="","?",VLOOKUP(K$1,INDIRECT("'"&$A22&"'!$A$12:$Z$19"),MATCH("Points (Auto-generate)",INDIRECT("'"&$A22&"'!$A$12:$Z$12"),0),0)),"ER")) | L22: =IF($F22=0,"NA",IF($A22=INDIRECT("'"&$A22&"'!$B$1"),IF(VLOOKUP(L$1,INDIRECT("'"&$A22&"'!$A$12:$Z$19"),MATCH("Points (Auto-generate)",INDIRECT("'"&$A22&"'!$A$12:$Z$12"),0),0)="","?",VLOOKUP(L$1,INDIRECT("'"&$A22&"'!$A$12:$Z$19"),MATCH("Points (Auto-generate)",INDIRECT("'"&$A22&"'!$A$12:$Z$12"),0),0)),"ER")) | M22: =IF($F22=0,"NA",IF($A22=INDIRECT("'"&$A22&"'!$B$1"),IF(VLOOKUP(M$1,INDIRECT("'"&$A22&"'!$A$12:$Z$19"),MATCH("Points (Auto-generate)",INDIRECT("'"&$A22&"'!$A$12:$Z$12"),0),0)="","?",VLOOKUP(M$1,INDIRECT("'"&$A22&"'!$A$12:$Z$19"),MATCH("Points (Auto-generate)",INDIRECT("'"&$A22&"'!$A$12:$Z$12"),0),0)),"ER"))
A23: DPG1 | B23: =VLOOKUP($A23,'PARASTATAL Questions'!$A:$J,3,0)&"" | C23: =VLOOKUP($A23,'PARASTATAL Questions'!$A:$J,4,0)&"" | D23: =VLOOKUP($A23,'PARASTATAL Questions'!$A:$J,5,0)&"" | E23: =VLOOKUP($A23,'PARASTATAL Questions'!$A:$J,7,0)&"" | F23: =VLOOKUP($A23,'PARASTATAL Questions'!$A:$J,6,0) | G23: =IF(OR(G24="ER",G25="ER"),"ER",IF(OR(G24="?",G25="?"),"?",IF(AND(G24="NA",G25="NA"),"NA",SUM(G24,G25)/((G24<>"NA")*$F$24+(G25<>"NA")*$F$25)*$F23))) | H23: =IF(OR(H24="ER",H25="ER"),"ER",IF(OR(H24="?",H25="?"),"?",IF(AND(H24="NA",H25="NA"),"NA",SUM(H24,H25)/((H24<>"NA")*$F$24+(H25<>"NA")*$F$25)*$F23))) | I23: =IF(OR(I24="ER",I25="ER"),"ER",IF(OR(I24="?",I25="?"),"?",IF(AND(I24="NA",I25="NA"),"NA",SUM(I24,I25)/((I24<>"NA")*$F$24+(I25<>"NA")*$F$25)*$F23))) | J23: =IF(OR(J24="ER",J25="ER"),"ER",IF(OR(J24="?",J25="?"),"?",IF(AND(J24="NA",J25="NA"),"NA",SUM(J24,J25)/((J24<>"NA")*$F$24+(J25<>"NA")*$F$25)*$F23))) | K23: =IF(OR(K24="ER",K25="ER"),"ER",IF(OR(K24="?",K25="?"),"?",IF(AND(K24="NA",K25="NA"),"NA",SUM(K24,K25)/((K24<>"NA")*$F$24+(K25<>"NA")*$F$25)*$F23))) | L23: =IF(OR(L24="ER",L25="ER"),"ER",IF(OR(L24="?",L25="?"),"?",IF(AND(L24="NA",L25="NA"),"NA",SUM(L24,L25)/((L24<>"NA")*$F$24+(L25<>"NA")*$F$25)*$F23))) | M23: =IF(OR(M24="ER",M25="ER"),"ER",IF(OR(M24="?",M25="?"),"?",IF(AND(M24="NA",M25="NA"),"NA",SUM(M24,M25)/((M24<>"NA")*$F$24+(M25<>"NA")*$F$25)*$F23)))
A24: DPG1a | B24: =VLOOKUP($A24,'PARASTATAL Questions'!$A:$J,3,0)&"" | C24: =VLOOKUP($A24,'PARASTATAL Questions'!$A:$J,4,0)&"" | D24: =VLOOKUP($A24,'PARASTATAL Questions'!$A:$J,5,0)&"" | E24: =VLOOKUP($A24,'PARASTATAL Questions'!$A:$J,7,0)&"" | F24: =VLOOKUP($A24,'PARASTATAL Questions'!$A:$J,6,0) | G24: =IF($F24=0,"NA",IF($A24=INDIRECT("'"&$A24&"'!$B$1"),IF(VLOOKUP(G$1,INDIRECT("'"&$A24&"'!$A$12:$Z$19"),MATCH("Points (Auto-generate)",INDIRECT("'"&$A24&"'!$A$12:$Z$12"),0),0)="","?",VLOOKUP(G$1,INDIRECT("'"&$A24&"'!$A$12:$Z$19"),MATCH("Points (Auto-generate)",INDIRECT("'"&$A24&"'!$A$12:$Z$12"),0),0)),"ER")) | H24: =IF($F24=0,"NA",IF($A24=INDIRECT("'"&$A24&"'!$B$1"),IF(VLOOKUP(H$1,INDIRECT("'"&$A24&"'!$A$12:$Z$19"),MATCH("Points (Auto-generate)",INDIRECT("'"&$A24&"'!$A$12:$Z$12"),0),0)="","?",VLOOKUP(H$1,INDIRECT("'"&$A24&"'!$A$12:$Z$19"),MATCH("Points (Auto-generate)",INDIRECT("'"&$A24&"'!$A$12:$Z$12"),0),0)),"ER")) | I24: =IF($F24=0,"NA",IF($A24=INDIRECT("'"&$A24&"'!$B$1"),IF(VLOOKUP(I$1,INDIRECT("'"&$A24&"'!$A$12:$Z$19"),MATCH("Points (Auto-generate)",INDIRECT("'"&$A24&"'!$A$12:$Z$12"),0),0)="","?",VLOOKUP(I$1,INDIRECT("'"&$A24&"'!$A$12:$Z$19"),MATCH("Points (Auto-generate)",INDIRECT("'"&$A24&"'!$A$12:$Z$12"),0),0)),"ER")) | J24: =IF($F24=0,"NA",IF($A24=INDIRECT("'"&$A24&"'!$B$1"),IF(VLOOKUP(J$1,INDIRECT("'"&$A24&"'!$A$12:$Z$19"),MATCH("Points (Auto-generate)",INDIRECT("'"&$A24&"'!$A$12:$Z$12"),0),0)="","?",VLOOKUP(J$1,INDIRECT("'"&$A24&"'!$A$12:$Z$19"),MATCH("Points (Auto-generate)",INDIRECT("'"&$A24&"'!$A$12:$Z$12"),0),0)),"ER")) | K24: =IF($F24=0,"NA",IF($A24=INDIRECT("'"&$A24&"'!$B$1"),IF(VLOOKUP(K$1,INDIRECT("'"&$A24&"'!$A$12:$Z$19"),MATCH("Points (Auto-generate)",INDIRECT("'"&$A24&"'!$A$12:$Z$12"),0),0)="","?",VLOOKUP(K$1,INDIRECT("'"&$A24&"'!$A$12:$Z$19"),MATCH("Points (Auto-generate)",INDIRECT("'"&$A24&"'!$A$12:$Z$12"),0),0)),"ER")) | L24: =IF($F24=0,"NA",IF($A24=INDIRECT("'"&$A24&"'!$B$1"),IF(VLOOKUP(L$1,INDIRECT("'"&$A24&"'!$A$12:$Z$19"),MATCH("Points (Auto-generate)",INDIRECT("'"&$A24&"'!$A$12:$Z$12"),0),0)="","?",VLOOKUP(L$1,INDIRECT("'"&$A24&"'!$A$12:$Z$19"),MATCH("Points (Auto-generate)",INDIRECT("'"&$A24&"'!$A$12:$Z$12"),0),0)),"ER")) | M24: =IF($F24=0,"NA",IF($A24=INDIRECT("'"&$A24&"'!$B$1"),IF(VLOOKUP(M$1,INDIRECT("'"&$A24&"'!$A$12:$Z$19"),MATCH("Points (Auto-generate)",INDIRECT("'"&$A24&"'!$A$12:$Z$12"),0),0)="","?",VLOOKUP(M$1,INDIRECT("'"&$A24&"'!$A$12:$Z$19"),MATCH("Points (Auto-generate)",INDIRECT("'"&$A24&"'!$A$12:$Z$12"),0),0)),"ER"))
A25: DPG1b | B25: =VLOOKUP($A25,'PARASTATAL Questions'!$A:$J,3,0)&"" | C25: =VLOOKUP($A25,'PARASTATAL Questions'!$A:$J,4,0)&"" | D25: =VLOOKUP($A25,'PARASTATAL Questions'!$A:$J,5,0)&"" | E25: =VLOOKUP($A25,'PARASTATAL Questions'!$A:$J,7,0)&"" | F25: =VLOOKUP($A25,'PARASTATAL Questions'!$A:$J,6,0) | G25: =IF($F25=0,"NA",IF($A25=INDIRECT("'"&$A25&"'!$B$1"),IF(VLOOKUP(G$1,INDIRECT("'"&$A25&"'!$A$12:$Z$19"),MATCH("Points (Auto-generate)",INDIRECT("'"&$A25&"'!$A$12:$Z$12"),0),0)="","?",VLOOKUP(G$1,INDIRECT("'"&$A25&"'!$A$12:$Z$19"),MATCH("Points (Auto-generate)",INDIRECT("'"&$A25&"'!$A$12:$Z$12"),0),0)),"ER")) | H25: =IF($F25=0,"NA",IF($A25=INDIRECT("'"&$A25&"'!$B$1"),IF(VLOOKUP(H$1,INDIRECT("'"&$A25&"'!$A$12:$Z$19"),MATCH("Points (Auto-generate)",INDIRECT("'"&$A25&"'!$A$12:$Z$12"),0),0)="","?",VLOOKUP(H$1,INDIRECT("'"&$A25&"'!$A$12:$Z$19"),MATCH("Points (Auto-generate)",INDIRECT("'"&$A25&"'!$A$12:$Z$12"),0),0)),"ER")) | I25: =IF($F25=0,"NA",IF($A25=INDIRECT("'"&$A25&"'!$B$1"),IF(VLOOKUP(I$1,INDIRECT("'"&$A25&"'!$A$12:$Z$19"),MATCH("Points (Auto-generate)",INDIRECT("'"&$A25&"'!$A$12:$Z$12"),0),0)="","?",VLOOKUP(I$1,INDIRECT("'"&$A25&"'!$A$12:$Z$19"),MATCH("Points (Auto-generate)",INDIRECT("'"&$A25&"'!$A$12:$Z$12"),0),0)),"ER")) | J25: =IF($F25=0,"NA",IF($A25=INDIRECT("'"&$A25&"'!$B$1"),IF(VLOOKUP(J$1,INDIRECT("'"&$A25&"'!$A$12:$Z$19"),MATCH("Points (Auto-generate)",INDIRECT("'"&$A25&"'!$A$12:$Z$12"),0),0)="","?",VLOOKUP(J$1,INDIRECT("'"&$A25&"'!$A$12:$Z$19"),MATCH("Points (Auto-generate)",INDIRECT("'"&$A25&"'!$A$12:$Z$12"),0),0)),"ER")) | K25: =IF($F25=0,"NA",IF($A25=INDIRECT("'"&$A25&"'!$B$1"),IF(VLOOKUP(K$1,INDIRECT("'"&$A25&"'!$A$12:$Z$19"),MATCH("Points (Auto-generate)",INDIRECT("'"&$A25&"'!$A$12:$Z$12"),0),0)="","?",VLOOKUP(K$1,INDIRECT("'"&$A25&"'!$A$12:$Z$19"),MATCH("Points (Auto-generate)",INDIRECT("'"&$A25&"'!$A$12:$Z$12"),0),0)),"ER")) | L25: =IF($F25=0,"NA",IF($A25=INDIRECT("'"&$A25&"'!$B$1"),IF(VLOOKUP(L$1,INDIRECT("'"&$A25&"'!$A$12:$Z$19"),MATCH("Points (Auto-generate)",INDIRECT("'"&$A25&"'!$A$12:$Z$12"),0),0)="","?",VLOOKUP(L$1,INDIRECT("'"&$A25&"'!$A$12:$Z$19"),MATCH("Points (Auto-generate)",INDIRECT("'"&$A25&"'!$A$12:$Z$12"),0),0)),"ER")) | M25: =IF($F25=0,"NA",IF($A25=INDIRECT("'"&$A25&"'!$B$1"),IF(VLOOKUP(M$1,INDIRECT("'"&$A25&"'!$A$12:$Z$19"),MATCH("Points (Auto-generate)",INDIRECT("'"&$A25&"'!$A$12:$Z$12"),0),0)="","?",VLOOKUP(M$1,INDIRECT("'"&$A25&"'!$A$12:$Z$19"),MATCH("Points (Auto-generate)",INDIRECT("'"&$A25&"'!$A$12:$Z$12"),0),0)),"ER"))
A26: DPG2 | B26: =VLOOKUP($A26,'PARASTATAL Questions'!$A:$J,3,0)&"" | C26: =VLOOKUP($A26,'PARASTATAL Questions'!$A:$J,4,0)&"" | D26: =VLOOKUP($A26,'PARASTATAL Questions'!$A:$J,5,0)&"" | E26: =VLOOKUP($A26,'PARASTATAL Questions'!$A:$J,7,0)&"" | F26: =VLOOKUP($A26,'PARASTATAL Questions'!$A:$J,6,0) | G26: =IF(OR(G27="ER",G28="ER"),"ER",IF(OR(G27="?",G28="?"),"?",IF(AND(G27="NA",G28="NA"),"NA",SUM(G27,G28)/((G27<>"NA")*$F$27+(G28<>"NA")*$F$28)*$F26))) | H26: =IF(OR(H27="ER",H28="ER"),"ER",IF(OR(H27="?",H28="?"),"?",IF(AND(H27="NA",H28="NA"),"NA",SUM(H27,H28)/((H27<>"NA")*$F$27+(H28<>"NA")*$F$28)*$F26))) | I26: =IF(OR(I27="ER",I28="ER"),"ER",IF(OR(I27="?",I28="?"),"?",IF(AND(I27="NA",I28="NA"),"NA",SUM(I27,I28)/((I27<>"NA")*$F$27+(I28<>"NA")*$F$28)*$F26))) | J26: =IF(OR(J27="ER",J28="ER"),"ER",IF(OR(J27="?",J28="?"),"?",IF(AND(J27="NA",J28="NA"),"NA",SUM(J27,J28)/((J27<>"NA")*$F$27+(J28<>"NA")*$F$28)*$F26))) | K26: =IF(OR(K27="ER",K28="ER"),"ER",IF(OR(K27="?",K28="?"),"?",IF(AND(K27="NA",K28="NA"),"NA",SUM(K27,K28)/((K27<>"NA")*$F$27+(K28<>"NA")*$F$28)*$F26))) | L26: =IF(OR(L27="ER",L28="ER"),"ER",IF(OR(L27="?",L28="?"),"?",IF(AND(L27="NA",L28="NA"),"NA",SUM(L27,L28)/((L27<>"NA")*$F$27+(L28<>"NA")*$F$28)*$F26))) | M26: =IF(OR(M27="ER",M28="ER"),"ER",IF(OR(M27="?",M28="?"),"?",IF(AND(M27="NA",M28="NA"),"NA",SUM(M27,M28)/((M27<>"NA")*$F$27+(M28<>"NA")*$F$28)*$F26)))
A27: DPG2a | B27: =VLOOKUP($A27,'PARASTATAL Questions'!$A:$J,3,0)&"" | C27: =VLOOKUP($A27,'PARASTATAL Questions'!$A:$J,4,0)&"" | D27: =VLOOKUP($A27,'PARASTATAL Questions'!$A:$J,5,0)&"" | E27: =VLOOKUP($A27,'PARASTATAL Questions'!$A:$J,7,0)&"" | F27: =VLOOKUP($A27,'PARASTATAL Questions'!$A:$J,6,0) | G27: =IF($F27=0,"NA",IF($A27=INDIRECT("'"&$A27&"'!$B$1"),IF(VLOOKUP(G$1,INDIRECT("'"&$A27&"'!$A$12:$Z$19"),MATCH("Points (Auto-generate)",INDIRECT("'"&$A27&"'!$A$12:$Z$12"),0),0)="","?",VLOOKUP(G$1,INDIRECT("'"&$A27&"'!$A$12:$Z$19"),MATCH("Points (Auto-generate)",INDIRECT("'"&$A27&"'!$A$12:$Z$12"),0),0)),"ER")) | H27: =IF($F27=0,"NA",IF($A27=INDIRECT("'"&$A27&"'!$B$1"),IF(VLOOKUP(H$1,INDIRECT("'"&$A27&"'!$A$12:$Z$19"),MATCH("Points (Auto-generate)",INDIRECT("'"&$A27&"'!$A$12:$Z$12"),0),0)="","?",VLOOKUP(H$1,INDIRECT("'"&$A27&"'!$A$12:$Z$19"),MATCH("Points (Auto-generate)",INDIRECT("'"&$A27&"'!$A$12:$Z$12"),0),0)),"ER")) | I27: =IF($F27=0,"NA",IF($A27=INDIRECT("'"&$A27&"'!$B$1"),IF(VLOOKUP(I$1,INDIRECT("'"&$A27&"'!$A$12:$Z$19"),MATCH("Points (Auto-generate)",INDIRECT("'"&$A27&"'!$A$12:$Z$12"),0),0)="","?",VLOOKUP(I$1,INDIRECT("'"&$A27&"'!$A$12:$Z$19"),MATCH("Points (Auto-generate)",INDIRECT("'"&$A27&"'!$A$12:$Z$12"),0),0)),"ER")) | J27: =IF($F27=0,"NA",IF($A27=INDIRECT("'"&$A27&"'!$B$1"),IF(VLOOKUP(J$1,INDIRECT("'"&$A27&"'!$A$12:$Z$19"),MATCH("Points (Auto-generate)",INDIRECT("'"&$A27&"'!$A$12:$Z$12"),0),0)="","?",VLOOKUP(J$1,INDIRECT("'"&$A27&"'!$A$12:$Z$19"),MATCH("Points (Auto-generate)",INDIRECT("'"&$A27&"'!$A$12:$Z$12"),0),0)),"ER")) | K27: =IF($F27=0,"NA",IF($A27=INDIRECT("'"&$A27&"'!$B$1"),IF(VLOOKUP(K$1,INDIRECT("'"&$A27&"'!$A$12:$Z$19"),MATCH("Points (Auto-generate)",INDIRECT("'"&$A27&"'!$A$12:$Z$12"),0),0)="","?",VLOOKUP(K$1,INDIRECT("'"&$A27&"'!$A$12:$Z$19"),MATCH("Points (Auto-generate)",INDIRECT("'"&$A27&"'!$A$12:$Z$12"),0),0)),"ER")) | L27: =IF($F27=0,"NA",IF($A27=INDIRECT("'"&$A27&"'!$B$1"),IF(VLOOKUP(L$1,INDIRECT("'"&$A27&"'!$A$12:$Z$19"),MATCH("Points (Auto-generate)",INDIRECT("'"&$A27&"'!$A$12:$Z$12"),0),0)="","?",VLOOKUP(L$1,INDIRECT("'"&$A27&"'!$A$12:$Z$19"),MATCH("Points (Auto-generate)",INDIRECT("'"&$A27&"'!$A$12:$Z$12"),0),0)),"ER")) | M27: =IF($F27=0,"NA",IF($A27=INDIRECT("'"&$A27&"'!$B$1"),IF(VLOOKUP(M$1,INDIRECT("'"&$A27&"'!$A$12:$Z$19"),MATCH("Points (Auto-generate)",INDIRECT("'"&$A27&"'!$A$12:$Z$12"),0),0)="","?",VLOOKUP(M$1,INDIRECT("'"&$A27&"'!$A$12:$Z$19"),MATCH("Points (Auto-generate)",INDIRECT("'"&$A27&"'!$A$12:$Z$12"),0),0)),"ER"))
A28: DPG2b | B28: =VLOOKUP($A28,'PARASTATAL Questions'!$A:$J,3,0)&"" | C28: =VLOOKUP($A28,'PARASTATAL Questions'!$A:$J,4,0)&"" | D28: =VLOOKUP($A28,'PARASTATAL Questions'!$A:$J,5,0)&"" | E28: =VLOOKUP($A28,'PARASTATAL Questions'!$A:$J,7,0)&"" | F28: =VLOOKUP($A28,'PARASTATAL Questions'!$A:$J,6,0) | G28: =IF($F28=0,"NA",IF($A28=INDIRECT("'"&$A28&"'!$B$1"),IF(VLOOKUP(G$1,INDIRECT("'"&$A28&"'!$A$12:$Z$19"),MATCH("Points (Auto-generate)",INDIRECT("'"&$A28&"'!$A$12:$Z$12"),0),0)="","?",VLOOKUP(G$1,INDIRECT("'"&$A28&"'!$A$12:$Z$19"),MATCH("Points (Auto-generate)",INDIRECT("'"&$A28&"'!$A$12:$Z$12"),0),0)),"ER")) | H28: =IF($F28=0,"NA",IF($A28=INDIRECT("'"&$A28&"'!$B$1"),IF(VLOOKUP(H$1,INDIRECT("'"&$A28&"'!$A$12:$Z$19"),MATCH("Points (Auto-generate)",INDIRECT("'"&$A28&"'!$A$12:$Z$12"),0),0)="","?",VLOOKUP(H$1,INDIRECT("'"&$A28&"'!$A$12:$Z$19"),MATCH("Points (Auto-generate)",INDIRECT("'"&$A28&"'!$A$12:$Z$12"),0),0)),"ER")) | I28: =IF($F28=0,"NA",IF($A28=INDIRECT("'"&$A28&"'!$B$1"),IF(VLOOKUP(I$1,INDIRECT("'"&$A28&"'!$A$12:$Z$19"),MATCH("Points (Auto-generate)",INDIRECT("'"&$A28&"'!$A$12:$Z$12"),0),0)="","?",VLOOKUP(I$1,INDIRECT("'"&$A28&"'!$A$12:$Z$19"),MATCH("Points (Auto-generate)",INDIRECT("'"&$A28&"'!$A$12:$Z$12"),0),0)),"ER")) | J28: =IF($F28=0,"NA",IF($A28=INDIRECT("'"&$A28&"'!$B$1"),IF(VLOOKUP(J$1,INDIRECT("'"&$A28&"'!$A$12:$Z$19"),MATCH("Points (Auto-generate)",INDIRECT("'"&$A28&"'!$A$12:$Z$12"),0),0)="","?",VLOOKUP(J$1,INDIRECT("'"&$A28&"'!$A$12:$Z$19"),MATCH("Points (Auto-generate)",INDIRECT("'"&$A28&"'!$A$12:$Z$12"),0),0)),"ER")) | K28: =IF($F28=0,"NA",IF($A28=INDIRECT("'"&$A28&"'!$B$1"),IF(VLOOKUP(K$1,INDIRECT("'"&$A28&"'!$A$12:$Z$19"),MATCH("Points (Auto-generate)",INDIRECT("'"&$A28&"'!$A$12:$Z$12"),0),0)="","?",VLOOKUP(K$1,INDIRECT("'"&$A28&"'!$A$12:$Z$19"),MATCH("Points (Auto-generate)",INDIRECT("'"&$A28&"'!$A$12:$Z$12"),0),0)),"ER")) | L28: =IF($F28=0,"NA",IF($A28=INDIRECT("'"&$A28&"'!$B$1"),IF(VLOOKUP(L$1,INDIRECT("'"&$A28&"'!$A$12:$Z$19"),MATCH("Points (Auto-generate)",INDIRECT("'"&$A28&"'!$A$12:$Z$12"),0),0)="","?",VLOOKUP(L$1,INDIRECT("'"&$A28&"'!$A$12:$Z$19"),MATCH("Points (Auto-generate)",INDIRECT("'"&$A28&"'!$A$12:$Z$12"),0),0)),"ER")) | M28: =IF($F28=0,"NA",IF($A28=INDIRECT("'"&$A28&"'!$B$1"),IF(VLOOKUP(M$1,INDIRECT("'"&$A28&"'!$A$12:$Z$19"),MATCH("Points (Auto-generate)",INDIRECT("'"&$A28&"'!$A$12:$Z$12"),0),0)="","?",VLOOKUP(M$1,INDIRECT("'"&$A28&"'!$A$12:$Z$19"),MATCH("Points (Auto-generate)",INDIRECT("'"&$A28&"'!$A$12:$Z$12"),0),0)),"ER"))
A29: DPG4 | B29: =VLOOKUP($A29,'PARASTATAL Questions'!$A:$J,3,0)&"" | C29: =VLOOKUP($A29,'PARASTATAL Questions'!$A:$J,4,0)&"" | D29: =VLOOKUP($A29,'PARASTATAL Questions'!$A:$J,5,0)&"" | E29: =VLOOKUP($A29,'PARASTATAL Questions'!$A:$J,7,0)&"" | F29: =VLOOKUP($A29,'PARASTATAL Questions'!$A:$J,6,0) | G29: =IF($F29=0,"NA",IF($A29=INDIRECT("'"&$A29&"'!$B$1"),IF(VLOOKUP(G$1,INDIRECT("'"&$A29&"'!$A$12:$Z$19"),MATCH("Points (Auto-generate)",INDIRECT("'"&$A29&"'!$A$12:$Z$12"),0),0)="","?",VLOOKUP(G$1,INDIRECT("'"&$A29&"'!$A$12:$Z$19"),MATCH("Points (Auto-generate)",INDIRECT("'"&$A29&"'!$A$12:$Z$12"),0),0)),"ER")) | H29: =IF($F29=0,"NA",IF($A29=INDIRECT("'"&$A29&"'!$B$1"),IF(VLOOKUP(H$1,INDIRECT("'"&$A29&"'!$A$12:$Z$19"),MATCH("Points (Auto-generate)",INDIRECT("'"&$A29&"'!$A$12:$Z$12"),0),0)="","?",VLOOKUP(H$1,INDIRECT("'"&$A29&"'!$A$12:$Z$19"),MATCH("Points (Auto-generate)",INDIRECT("'"&$A29&"'!$A$12:$Z$12"),0),0)),"ER")) | I29: =IF($F29=0,"NA",IF($A29=INDIRECT("'"&$A29&"'!$B$1"),IF(VLOOKUP(I$1,INDIRECT("'"&$A29&"'!$A$12:$Z$19"),MATCH("Points (Auto-generate)",INDIRECT("'"&$A29&"'!$A$12:$Z$12"),0),0)="","?",VLOOKUP(I$1,INDIRECT("'"&$A29&"'!$A$12:$Z$19"),MATCH("Points (Auto-generate)",INDIRECT("'"&$A29&"'!$A$12:$Z$12"),0),0)),"ER")) | J29: =IF($F29=0,"NA",IF($A29=INDIRECT("'"&$A29&"'!$B$1"),IF(VLOOKUP(J$1,INDIRECT("'"&$A29&"'!$A$12:$Z$19"),MATCH("Points (Auto-generate)",INDIRECT("'"&$A29&"'!$A$12:$Z$12"),0),0)="","?",VLOOKUP(J$1,INDIRECT("'"&$A29&"'!$A$12:$Z$19"),MATCH("Points (Auto-generate)",INDIRECT("'"&$A29&"'!$A$12:$Z$12"),0),0)),"ER")) | K29: =IF($F29=0,"NA",IF($A29=INDIRECT("'"&$A29&"'!$B$1"),IF(VLOOKUP(K$1,INDIRECT("'"&$A29&"'!$A$12:$Z$19"),MATCH("Points (Auto-generate)",INDIRECT("'"&$A29&"'!$A$12:$Z$12"),0),0)="","?",VLOOKUP(K$1,INDIRECT("'"&$A29&"'!$A$12:$Z$19"),MATCH("Points (Auto-generate)",INDIRECT("'"&$A29&"'!$A$12:$Z$12"),0),0)),"ER")) | L29: =IF($F29=0,"NA",IF($A29=INDIRECT("'"&$A29&"'!$B$1"),IF(VLOOKUP(L$1,INDIRECT("'"&$A29&"'!$A$12:$Z$19"),MATCH("Points (Auto-generate)",INDIRECT("'"&$A29&"'!$A$12:$Z$12"),0),0)="","?",VLOOKUP(L$1,INDIRECT("'"&$A29&"'!$A$12:$Z$19"),MATCH("Points (Auto-generate)",INDIRECT("'"&$A29&"'!$A$12:$Z$12"),0),0)),"ER")) | M29: =IF($F29=0,"NA",IF($A29=INDIRECT("'"&$A29&"'!$B$1"),IF(VLOOKUP(M$1,INDIRECT("'"&$A29&"'!$A$12:$Z$19"),MATCH("Points (Auto-generate)",INDIRECT("'"&$A29&"'!$A$12:$Z$12"),0),0)="","?",VLOOKUP(M$1,INDIRECT("'"&$A29&"'!$A$12:$Z$19"),MATCH("Points (Auto-generate)",INDIRECT("'"&$A29&"'!$A$12:$Z$12"),0),0)),"ER"))
A30: DPG5 | B30: =VLOOKUP($A30,'PARASTATAL Questions'!$A:$J,3,0)&"" | C30: =VLOOKUP($A30,'PARASTATAL Questions'!$A:$J,4,0)&"" | D30: =VLOOKUP($A30,'PARASTATAL Questions'!$A:$J,5,0)&"" | E30: =VLOOKUP($A30,'PARASTATAL Questions'!$A:$J,7,0)&"" | F30: =VLOOKUP($A30,'PARASTATAL Questions'!$A:$J,6,0) | G30: =IF(OR(G31="ER",G32="ER",G33="ER",G34="ER",G35="ER",G36="ER",G37="ER",G38="ER",G39="ER",G40="ER"),"ER",IF(OR(G31="?",G32="?",G33="?",G34="?",G35="?",G36="?",G37="?",G38="?",G39="?",G40="?"),"?",IF(AND(G31="NA",G32="NA",G33="NA",G34="NA",G35="NA",G36="NA",G37="NA",G38="NA",G39="NA",G40="NA"),"NA",SUM(G31,G32,G33,G34,G35,G36,G37,G38,G39,G40)/((G31<>"NA")*$F$31+(G32<>"NA")*$F$32+(G33<>"NA")*$F$33+(G34<>"NA")*$F$34+(G35<>"NA")*$F$35+(G36<>"NA")*$F$36+(G37<>"NA")*$F$37+(G38<>"NA")*$F$38+(G39<>"NA")*$F$39+(G40<>"NA")*$F$40)*$F30))) | H30: =IF(OR(H31="ER",H32="ER",H33="ER",H34="ER",H35="ER",H36="ER",H37="ER",H38="ER",H39="ER",H40="ER"),"ER",IF(OR(H31="?",H32="?",H33="?",H34="?",H35="?",H36="?",H37="?",H38="?",H39="?",H40="?"),"?",IF(AND(H31="NA",H32="NA",H33="NA",H34="NA",H35="NA",H36="NA",H37="NA",H38="NA",H39="NA",H40="NA"),"NA",SUM(H31,H32,H33,H34,H35,H36,H37,H38,H39,H40)/((H31<>"NA")*$F$31+(H32<>"NA")*$F$32+(H33<>"NA")*$F$33+(H34<>"NA")*$F$34+(H35<>"NA")*$F$35+(H36<>"NA")*$F$36+(H37<>"NA")*$F$37+(H38<>"NA")*$F$38+(H39<>"NA")*$F$39+(H40<>"NA")*$F$40)*$F30))) | I30: =IF(OR(I31="ER",I32="ER",I33="ER",I34="ER",I35="ER",I36="ER",I37="ER",I38="ER",I39="ER",I40="ER"),"ER",IF(OR(I31="?",I32="?",I33="?",I34="?",I35="?",I36="?",I37="?",I38="?",I39="?",I40="?"),"?",IF(AND(I31="NA",I32="NA",I33="NA",I34="NA",I35="NA",I36="NA",I37="NA",I38="NA",I39="NA",I40="NA"),"NA",SUM(I31,I32,I33,I34,I35,I36,I37,I38,I39,I40)/((I31<>"NA")*$F$31+(I32<>"NA")*$F$32+(I33<>"NA")*$F$33+(I34<>"NA")*$F$34+(I35<>"NA")*$F$35+(I36<>"NA")*$F$36+(I37<>"NA")*$F$37+(I38<>"NA")*$F$38+(I39<>"NA")*$F$39+(I40<>"NA")*$F$40)*$F30))) | J30: =IF(OR(J31="ER",J32="ER",J33="ER",J34="ER",J35="ER",J36="ER",J37="ER",J38="ER",J39="ER",J40="ER"),"ER",IF(OR(J31="?",J32="?",J33="?",J34="?",J35="?",J36="?",J37="?",J38="?",J39="?",J40="?"),"?",IF(AND(J31="NA",J32="NA",J33="NA",J34="NA",J35="NA",J36="NA",J37="NA",J38="NA",J39="NA",J40="NA"),"NA",SUM(J31,J32,J33,J34,J35,J36,J37,J38,J39,J40)/((J31<>"NA")*$F$31+(J32<>"NA")*$F$32+(J33<>"NA")*$F$33+(J34<>"NA")*$F$34+(J35<>"NA")*$F$35+(J36<>"NA")*$F$36+(J37<>"NA")*$F$37+(J38<>"NA")*$F$38+(J39<>"NA")*$F$39+(J40<>"NA")*$F$40)*$F30))) | K30: =IF(OR(K31="ER",K32="ER",K33="ER",K34="ER",K35="ER",K36="ER",K37="ER",K38="ER",K39="ER",K40="ER"),"ER",IF(OR(K31="?",K32="?",K33="?",K34="?",K35="?",K36="?",K37="?",K38="?",K39="?",K40="?"),"?",IF(AND(K31="NA",K32="NA",K33="NA",K34="NA",K35="NA",K36="NA",K37="NA",K38="NA",K39="NA",K40="NA"),"NA",SUM(K31,K32,K33,K34,K35,K36,K37,K38,K39,K40)/((K31<>"NA")*$F$31+(K32<>"NA")*$F$32+(K33<>"NA")*$F$33+(K34<>"NA")*$F$34+(K35<>"NA")*$F$35+(K36<>"NA")*$F$36+(K37<>"NA")*$F$37+(K38<>"NA")*$F$38+(K39<>"NA")*$F$39+(K40<>"NA")*$F$40)*$F30))) | L30: =IF(OR(L31="ER",L32="ER",L33="ER",L34="ER",L35="ER",L36="ER",L37="ER",L38="ER",L39="ER",L40="ER"),"ER",IF(OR(L31="?",L32="?",L33="?",L34="?",L35="?",L36="?",L37="?",L38="?",L39="?",L40="?"),"?",IF(AND(L31="NA",L32="NA",L33="NA",L34="NA",L35="NA",L36="NA",L37="NA",L38="NA",L39="NA",L40="NA"),"NA",SUM(L31,L32,L33,L34,L35,L36,L37,L38,L39,L40)/((L31<>"NA")*$F$31+(L32<>"NA")*$F$32+(L33<>"NA")*$F$33+(L34<>"NA")*$F$34+(L35<>"NA")*$F$35+(L36<>"NA")*$F$36+(L37<>"NA")*$F$37+(L38<>"NA")*$F$38+(L39<>"NA")*$F$39+(L40<>"NA")*$F$40)*$F30))) | M30: =IF(OR(M31="ER",M32="ER",M33="ER",M34="ER",M35="ER",M36="ER",M37="ER",M38="ER",M39="ER",M40="ER"),"ER",IF(OR(M31="?",M32="?",M33="?",M34="?",M35="?",M36="?",M37="?",M38="?",M39="?",M40="?"),"?",IF(AND(M31="NA",M32="NA",M33="NA",M34="NA",M35="NA",M36="NA",M37="NA",M38="NA",M39="NA",M40="NA"),"NA",SUM(M31,M32,M33,M34,M35,M36,M37,M38,M39,M40)/((M31<>"NA")*$F$31+(M32<>"NA")*$F$32+(M33<>"NA")*$F$33+(M34<>"NA")*$F$34+(M35<>"NA")*$F$35+(M36<>"NA")*$F$36+(M37<>"NA")*$F$37+(M38<>"NA")*$F$38+(M39<>"NA")*$F$39+(M40<>"NA")*$F$40)*$F30)))
A31: DPG5a | B31: =VLOOKUP($A31,'PARASTATAL Questions'!$A:$J,3,0)&"" | C31: =VLOOKUP($A31,'PARASTATAL Questions'!$A:$J,4,0)&"" | D31: =VLOOKUP($A31,'PARASTATAL Questions'!$A:$J,5,0)&"" | E31: =VLOOKUP($A31,'PARASTATAL Questions'!$A:$J,7,0)&"" | F31: =VLOOKUP($A31,'PARASTATAL Questions'!$A:$J,6,0) | G31: =IF($F31=0,"NA",IF($A31=INDIRECT("'"&$A31&"'!$B$1"),IF(VLOOKUP(G$1,INDIRECT("'"&$A31&"'!$A$12:$Z$19"),MATCH("Points (Auto-generate)",INDIRECT("'"&$A31&"'!$A$12:$Z$12"),0),0)="","?",VLOOKUP(G$1,INDIRECT("'"&$A31&"'!$A$12:$Z$19"),MATCH("Points (Auto-generate)",INDIRECT("'"&$A31&"'!$A$12:$Z$12"),0),0)),"ER")) | H31: =IF($F31=0,"NA",IF($A31=INDIRECT("'"&$A31&"'!$B$1"),IF(VLOOKUP(H$1,INDIRECT("'"&$A31&"'!$A$12:$Z$19"),MATCH("Points (Auto-generate)",INDIRECT("'"&$A31&"'!$A$12:$Z$12"),0),0)="","?",VLOOKUP(H$1,INDIRECT("'"&$A31&"'!$A$12:$Z$19"),MATCH("Points (Auto-generate)",INDIRECT("'"&$A31&"'!$A$12:$Z$12"),0),0)),"ER")) | I31: =IF($F31=0,"NA",IF($A31=INDIRECT("'"&$A31&"'!$B$1"),IF(VLOOKUP(I$1,INDIRECT("'"&$A31&"'!$A$12:$Z$19"),MATCH("Points (Auto-generate)",INDIRECT("'"&$A31&"'!$A$12:$Z$12"),0),0)="","?",VLOOKUP(I$1,INDIRECT("'"&$A31&"'!$A$12:$Z$19"),MATCH("Points (Auto-generate)",INDIRECT("'"&$A31&"'!$A$12:$Z$12"),0),0)),"ER")) | J31: =IF($F31=0,"NA",IF($A31=INDIRECT("'"&$A31&"'!$B$1"),IF(VLOOKUP(J$1,INDIRECT("'"&$A31&"'!$A$12:$Z$19"),MATCH("Points (Auto-generate)",INDIRECT("'"&$A31&"'!$A$12:$Z$12"),0),0)="","?",VLOOKUP(J$1,INDIRECT("'"&$A31&"'!$A$12:$Z$19"),MATCH("Points (Auto-generate)",INDIRECT("'"&$A31&"'!$A$12:$Z$12"),0),0)),"ER")) | K31: =IF($F31=0,"NA",IF($A31=INDIRECT("'"&$A31&"'!$B$1"),IF(VLOOKUP(K$1,INDIRECT("'"&$A31&"'!$A$12:$Z$19"),MATCH("Points (Auto-generate)",INDIRECT("'"&$A31&"'!$A$12:$Z$12"),0),0)="","?",VLOOKUP(K$1,INDIRECT("'"&$A31&"'!$A$12:$Z$19"),MATCH("Points (Auto-generate)",INDIRECT("'"&$A31&"'!$A$12:$Z$12"),0),0)),"ER")) | L31: =IF($F31=0,"NA",IF($A31=INDIRECT("'"&$A31&"'!$B$1"),IF(VLOOKUP(L$1,INDIRECT("'"&$A31&"'!$A$12:$Z$19"),MATCH("Points (Auto-generate)",INDIRECT("'"&$A31&"'!$A$12:$Z$12"),0),0)="","?",VLOOKUP(L$1,INDIRECT("'"&$A31&"'!$A$12:$Z$19"),MATCH("Points (Auto-generate)",INDIRECT("'"&$A31&"'!$A$12:$Z$12"),0),0)),"ER")) | M31: =IF($F31=0,"NA",IF($A31=INDIRECT("'"&$A31&"'!$B$1"),IF(VLOOKUP(M$1,INDIRECT("'"&$A31&"'!$A$12:$Z$19"),MATCH("Points (Auto-generate)",INDIRECT("'"&$A31&"'!$A$12:$Z$12"),0),0)="","?",VLOOKUP(M$1,INDIRECT("'"&$A31&"'!$A$12:$Z$19"),MATCH("Points (Auto-generate)",INDIRECT("'"&$A31&"'!$A$12:$Z$12"),0),0)),"ER"))
A32: DPG5b | B32: =VLOOKUP($A32,'PARASTATAL Questions'!$A:$J,3,0)&"" | C32: =VLOOKUP($A32,'PARASTATAL Questions'!$A:$J,4,0)&"" | D32: =VLOOKUP($A32,'PARASTATAL Questions'!$A:$J,5,0)&"" | E32: =VLOOKUP($A32,'PARASTATAL Questions'!$A:$J,7,0)&"" | F32: =VLOOKUP($A32,'PARASTATAL Questions'!$A:$J,6,0) | G32: =IF($F32=0,"NA",IF($A32=INDIRECT("'"&$A32&"'!$B$1"),IF(VLOOKUP(G$1,INDIRECT("'"&$A32&"'!$A$12:$Z$19"),MATCH("Points (Auto-generate)",INDIRECT("'"&$A32&"'!$A$12:$Z$12"),0),0)="","?",VLOOKUP(G$1,INDIRECT("'"&$A32&"'!$A$12:$Z$19"),MATCH("Points (Auto-generate)",INDIRECT("'"&$A32&"'!$A$12:$Z$12"),0),0)),"ER")) | H32: =IF($F32=0,"NA",IF($A32=INDIRECT("'"&$A32&"'!$B$1"),IF(VLOOKUP(H$1,INDIRECT("'"&$A32&"'!$A$12:$Z$19"),MATCH("Points (Auto-generate)",INDIRECT("'"&$A32&"'!$A$12:$Z$12"),0),0)="","?",VLOOKUP(H$1,INDIRECT("'"&$A32&"'!$A$12:$Z$19"),MATCH("Points (Auto-generate)",INDIRECT("'"&$A32&"'!$A$12:$Z$12"),0),0)),"ER")) | I32: =IF($F32=0,"NA",IF($A32=INDIRECT("'"&$A32&"'!$B$1"),IF(VLOOKUP(I$1,INDIRECT("'"&$A32&"'!$A$12:$Z$19"),MATCH("Points (Auto-generate)",INDIRECT("'"&$A32&"'!$A$12:$Z$12"),0),0)="","?",VLOOKUP(I$1,INDIRECT("'"&$A32&"'!$A$12:$Z$19"),MATCH("Points (Auto-generate)",INDIRECT("'"&$A32&"'!$A$12:$Z$12"),0),0)),"ER")) | J32: =IF($F32=0,"NA",IF($A32=INDIRECT("'"&$A32&"'!$B$1"),IF(VLOOKUP(J$1,INDIRECT("'"&$A32&"'!$A$12:$Z$19"),MATCH("Points (Auto-generate)",INDIRECT("'"&$A32&"'!$A$12:$Z$12"),0),0)="","?",VLOOKUP(J$1,INDIRECT("'"&$A32&"'!$A$12:$Z$19"),MATCH("Points (Auto-generate)",INDIRECT("'"&$A32&"'!$A$12:$Z$12"),0),0)),"ER")) | K32: =IF($F32=0,"NA",IF($A32=INDIRECT("'"&$A32&"'!$B$1"),IF(VLOOKUP(K$1,INDIRECT("'"&$A32&"'!$A$12:$Z$19"),MATCH("Points (Auto-generate)",INDIRECT("'"&$A32&"'!$A$12:$Z$12"),0),0)="","?",VLOOKUP(K$1,INDIRECT("'"&$A32&"'!$A$12:$Z$19"),MATCH("Points (Auto-generate)",INDIRECT("'"&$A32&"'!$A$12:$Z$12"),0),0)),"ER")) | L32: =IF($F32=0,"NA",IF($A32=INDIRECT("'"&$A32&"'!$B$1"),IF(VLOOKUP(L$1,INDIRECT("'"&$A32&"'!$A$12:$Z$19"),MATCH("Points (Auto-generate)",INDIRECT("'"&$A32&"'!$A$12:$Z$12"),0),0)="","?",VLOOKUP(L$1,INDIRECT("'"&$A32&"'!$A$12:$Z$19"),MATCH("Points (Auto-generate)",INDIRECT("'"&$A32&"'!$A$12:$Z$12"),0),0)),"ER")) | M32: =IF($F32=0,"NA",IF($A32=INDIRECT("'"&$A32&"'!$B$1"),IF(VLOOKUP(M$1,INDIRECT("'"&$A32&"'!$A$12:$Z$19"),MATCH("Points (Auto-generate)",INDIRECT("'"&$A32&"'!$A$12:$Z$12"),0),0)="","?",VLOOKUP(M$1,INDIRECT("'"&$A32&"'!$A$12:$Z$19"),MATCH("Points (Auto-generate)",INDIRECT("'"&$A32&"'!$A$12:$Z$12"),0),0)),"ER"))
A33: DPG5c | B33: =VLOOKUP($A33,'PARASTATAL Questions'!$A:$J,3,0)&"" | C33: =VLOOKUP($A33,'PARASTATAL Questions'!$A:$J,4,0)&"" | D33: =VLOOKUP($A33,'PARASTATAL Questions'!$A:$J,5,0)&"" | E33: =VLOOKUP($A33,'PARASTATAL Questions'!$A:$J,7,0)&"" | F33: =VLOOKUP($A33,'PARASTATAL Questions'!$A:$J,6,0) | G33: =IF($F33=0,"NA",IF($A33=INDIRECT("'"&$A33&"'!$B$1"),IF(VLOOKUP(G$1,INDIRECT("'"&$A33&"'!$A$12:$Z$19"),MATCH("Points (Auto-generate)",INDIRECT("'"&$A33&"'!$A$12:$Z$12"),0),0)="","?",VLOOKUP(G$1,INDIRECT("'"&$A33&"'!$A$12:$Z$19"),MATCH("Points (Auto-generate)",INDIRECT("'"&$A33&"'!$A$12:$Z$12"),0),0)),"ER")) | H33: =IF($F33=0,"NA",IF($A33=INDIRECT("'"&$A33&"'!$B$1"),IF(VLOOKUP(H$1,INDIRECT("'"&$A33&"'!$A$12:$Z$19"),MATCH("Points (Auto-generate)",INDIRECT("'"&$A33&"'!$A$12:$Z$12"),0),0)="","?",VLOOKUP(H$1,INDIRECT("'"&$A33&"'!$A$12:$Z$19"),MATCH("Points (Auto-generate)",INDIRECT("'"&$A33&"'!$A$12:$Z$12"),0),0)),"ER")) | I33: =IF($F33=0,"NA",IF($A33=INDIRECT("'"&$A33&"'!$B$1"),IF(VLOOKUP(I$1,INDIRECT("'"&$A33&"'!$A$12:$Z$19"),MATCH("Points (Auto-generate)",INDIRECT("'"&$A33&"'!$A$12:$Z$12"),0),0)="","?",VLOOKUP(I$1,INDIRECT("'"&$A33&"'!$A$12:$Z$19"),MATCH("Points (Auto-generate)",INDIRECT("'"&$A33&"'!$A$12:$Z$12"),0),0)),"ER")) | J33: =IF($F33=0,"NA",IF($A33=INDIRECT("'"&$A33&"'!$B$1"),IF(VLOOKUP(J$1,INDIRECT("'"&$A33&"'!$A$12:$Z$19"),MATCH("Points (Auto-generate)",INDIRECT("'"&$A33&"'!$A$12:$Z$12"),0),0)="","?",VLOOKUP(J$1,INDIRECT("'"&$A33&"'!$A$12:$Z$19"),MATCH("Points (Auto-generate)",INDIRECT("'"&$A33&"'!$A$12:$Z$12"),0),0)),"ER")) | K33: =IF($F33=0,"NA",IF($A33=INDIRECT("'"&$A33&"'!$B$1"),IF(VLOOKUP(K$1,INDIRECT("'"&$A33&"'!$A$12:$Z$19"),MATCH("Points (Auto-generate)",INDIRECT("'"&$A33&"'!$A$12:$Z$12"),0),0)="","?",VLOOKUP(K$1,INDIRECT("'"&$A33&"'!$A$12:$Z$19"),MATCH("Points (Auto-generate)",INDIRECT("'"&$A33&"'!$A$12:$Z$12"),0),0)),"ER")) | L33: =IF($F33=0,"NA",IF($A33=INDIRECT("'"&$A33&"'!$B$1"),IF(VLOOKUP(L$1,INDIRECT("'"&$A33&"'!$A$12:$Z$19"),MATCH("Points (Auto-generate)",INDIRECT("'"&$A33&"'!$A$12:$Z$12"),0),0)="","?",VLOOKUP(L$1,INDIRECT("'"&$A33&"'!$A$12:$Z$19"),MATCH("Points (Auto-generate)",INDIRECT("'"&$A33&"'!$A$12:$Z$12"),0),0)),"ER")) | M33: =IF($F33=0,"NA",IF($A33=INDIRECT("'"&$A33&"'!$B$1"),IF(VLOOKUP(M$1,INDIRECT("'"&$A33&"'!$A$12:$Z$19"),MATCH("Points (Auto-generate)",INDIRECT("'"&$A33&"'!$A$12:$Z$12"),0),0)="","?",VLOOKUP(M$1,INDIRECT("'"&$A33&"'!$A$12:$Z$19"),MATCH("Points (Auto-generate)",INDIRECT("'"&$A33&"'!$A$12:$Z$12"),0),0)),"ER"))
A34: DPG5d | B34: =VLOOKUP($A34,'PARASTATAL Questions'!$A:$J,3,0)&"" | C34: =VLOOKUP($A34,'PARASTATAL Questions'!$A:$J,4,0)&"" | D34: =VLOOKUP($A34,'PARASTATAL Questions'!$A:$J,5,0)&"" | E34: =VLOOKUP($A34,'PARASTATAL Questions'!$A:$J,7,0)&"" | F34: =VLOOKUP($A34,'PARASTATAL Questions'!$A:$J,6,0) | G34: =IF($F34=0,"NA",IF($A34=INDIRECT("'"&$A34&"'!$B$1"),IF(VLOOKUP(G$1,INDIRECT("'"&$A34&"'!$A$12:$Z$19"),MATCH("Points (Auto-generate)",INDIRECT("'"&$A34&"'!$A$12:$Z$12"),0),0)="","?",VLOOKUP(G$1,INDIRECT("'"&$A34&"'!$A$12:$Z$19"),MATCH("Points (Auto-generate)",INDIRECT("'"&$A34&"'!$A$12:$Z$12"),0),0)),"ER")) | H34: =IF($F34=0,"NA",IF($A34=INDIRECT("'"&$A34&"'!$B$1"),IF(VLOOKUP(H$1,INDIRECT("'"&$A34&"'!$A$12:$Z$19"),MATCH("Points (Auto-generate)",INDIRECT("'"&$A34&"'!$A$12:$Z$12"),0),0)="","?",VLOOKUP(H$1,INDIRECT("'"&$A34&"'!$A$12:$Z$19"),MATCH("Points (Auto-generate)",INDIRECT("'"&$A34&"'!$A$12:$Z$12"),0),0)),"ER")) | I34: =IF($F34=0,"NA",IF($A34=INDIRECT("'"&$A34&"'!$B$1"),IF(VLOOKUP(I$1,INDIRECT("'"&$A34&"'!$A$12:$Z$19"),MATCH("Points (Auto-generate)",INDIRECT("'"&$A34&"'!$A$12:$Z$12"),0),0)="","?",VLOOKUP(I$1,INDIRECT("'"&$A34&"'!$A$12:$Z$19"),MATCH("Points (Auto-generate)",INDIRECT("'"&$A34&"'!$A$12:$Z$12"),0),0)),"ER")) | J34: =IF($F34=0,"NA",IF($A34=INDIRECT("'"&$A34&"'!$B$1"),IF(VLOOKUP(J$1,INDIRECT("'"&$A34&"'!$A$12:$Z$19"),MATCH("Points (Auto-generate)",INDIRECT("'"&$A34&"'!$A$12:$Z$12"),0),0)="","?",VLOOKUP(J$1,INDIRECT("'"&$A34&"'!$A$12:$Z$19"),MATCH("Points (Auto-generate)",INDIRECT("'"&$A34&"'!$A$12:$Z$12"),0),0)),"ER")) | K34: =IF($F34=0,"NA",IF($A34=INDIRECT("'"&$A34&"'!$B$1"),IF(VLOOKUP(K$1,INDIRECT("'"&$A34&"'!$A$12:$Z$19"),MATCH("Points (Auto-generate)",INDIRECT("'"&$A34&"'!$A$12:$Z$12"),0),0)="","?",VLOOKUP(K$1,INDIRECT("'"&$A34&"'!$A$12:$Z$19"),MATCH("Points (Auto-generate)",INDIRECT("'"&$A34&"'!$A$12:$Z$12"),0),0)),"ER")) | L34: =IF($F34=0,"NA",IF($A34=INDIRECT("'"&$A34&"'!$B$1"),IF(VLOOKUP(L$1,INDIRECT("'"&$A34&"'!$A$12:$Z$19"),MATCH("Points (Auto-generate)",INDIRECT("'"&$A34&"'!$A$12:$Z$12"),0),0)="","?",VLOOKUP(L$1,INDIRECT("'"&$A34&"'!$A$12:$Z$19"),MATCH("Points (Auto-generate)",INDIRECT("'"&$A34&"'!$A$12:$Z$12"),0),0)),"ER")) | M34: =IF($F34=0,"NA",IF($A34=INDIRECT("'"&$A34&"'!$B$1"),IF(VLOOKUP(M$1,INDIRECT("'"&$A34&"'!$A$12:$Z$19"),MATCH("Points (Auto-generate)",INDIRECT("'"&$A34&"'!$A$12:$Z$12"),0),0)="","?",VLOOKUP(M$1,INDIRECT("'"&$A34&"'!$A$12:$Z$19"),MATCH("Points (Auto-generate)",INDIRECT("'"&$A34&"'!$A$12:$Z$12"),0),0)),"ER"))
A35: DPG5f | B35: =VLOOKUP($A35,'PARASTATAL Questions'!$A:$J,3,0)&"" | C35: =VLOOKUP($A35,'PARASTATAL Questions'!$A:$J,4,0)&"" | D35: =VLOOKUP($A35,'PARASTATAL Questions'!$A:$J,5,0)&"" | E35: =VLOOKUP($A35,'PARASTATAL Questions'!$A:$J,7,0)&"" | F35: =VLOOKUP($A35,'PARASTATAL Questions'!$A:$J,6,0) | G35: =IF($F35=0,"NA",IF($A35=INDIRECT("'"&$A35&"'!$B$1"),IF(VLOOKUP(G$1,INDIRECT("'"&$A35&"'!$A$12:$Z$19"),MATCH("Points (Auto-generate)",INDIRECT("'"&$A35&"'!$A$12:$Z$12"),0),0)="","?",VLOOKUP(G$1,INDIRECT("'"&$A35&"'!$A$12:$Z$19"),MATCH("Points (Auto-generate)",INDIRECT("'"&$A35&"'!$A$12:$Z$12"),0),0)),"ER")) | H35: =IF($F35=0,"NA",IF($A35=INDIRECT("'"&$A35&"'!$B$1"),IF(VLOOKUP(H$1,INDIRECT("'"&$A35&"'!$A$12:$Z$19"),MATCH("Points (Auto-generate)",INDIRECT("'"&$A35&"'!$A$12:$Z$12"),0),0)="","?",VLOOKUP(H$1,INDIRECT("'"&$A35&"'!$A$12:$Z$19"),MATCH("Points (Auto-generate)",INDIRECT("'"&$A35&"'!$A$12:$Z$12"),0),0)),"ER")) | I35: =IF($F35=0,"NA",IF($A35=INDIRECT("'"&$A35&"'!$B$1"),IF(VLOOKUP(I$1,INDIRECT("'"&$A35&"'!$A$12:$Z$19"),MATCH("Points (Auto-generate)",INDIRECT("'"&$A35&"'!$A$12:$Z$12"),0),0)="","?",VLOOKUP(I$1,INDIRECT("'"&$A35&"'!$A$12:$Z$19"),MATCH("Points (Auto-generate)",INDIRECT("'"&$A35&"'!$A$12:$Z$12"),0),0)),"ER")) | J35: =IF($F35=0,"NA",IF($A35=INDIRECT("'"&$A35&"'!$B$1"),IF(VLOOKUP(J$1,INDIRECT("'"&$A35&"'!$A$12:$Z$19"),MATCH("Points (Auto-generate)",INDIRECT("'"&$A35&"'!$A$12:$Z$12"),0),0)="","?",VLOOKUP(J$1,INDIRECT("'"&$A35&"'!$A$12:$Z$19"),MATCH("Points (Auto-generate)",INDIRECT("'"&$A35&"'!$A$12:$Z$12"),0),0)),"ER")) | K35: =IF($F35=0,"NA",IF($A35=INDIRECT("'"&$A35&"'!$B$1"),IF(VLOOKUP(K$1,INDIRECT("'"&$A35&"'!$A$12:$Z$19"),MATCH("Points (Auto-generate)",INDIRECT("'"&$A35&"'!$A$12:$Z$12"),0),0)="","?",VLOOKUP(K$1,INDIRECT("'"&$A35&"'!$A$12:$Z$19"),MATCH("Points (Auto-generate)",INDIRECT("'"&$A35&"'!$A$12:$Z$12"),0),0)),"ER")) | L35: =IF($F35=0,"NA",IF($A35=INDIRECT("'"&$A35&"'!$B$1"),IF(VLOOKUP(L$1,INDIRECT("'"&$A35&"'!$A$12:$Z$19"),MATCH("Points (Auto-generate)",INDIRECT("'"&$A35&"'!$A$12:$Z$12"),0),0)="","?",VLOOKUP(L$1,INDIRECT("'"&$A35&"'!$A$12:$Z$19"),MATCH("Points (Auto-generate)",INDIRECT("'"&$A35&"'!$A$12:$Z$12"),0),0)),"ER")) | M35: =IF($F35=0,"NA",IF($A35=INDIRECT("'"&$A35&"'!$B$1"),IF(VLOOKUP(M$1,INDIRECT("'"&$A35&"'!$A$12:$Z$19"),MATCH("Points (Auto-generate)",INDIRECT("'"&$A35&"'!$A$12:$Z$12"),0),0)="","?",VLOOKUP(M$1,INDIRECT("'"&$A35&"'!$A$12:$Z$19"),MATCH("Points (Auto-generate)",INDIRECT("'"&$A35&"'!$A$12:$Z$12"),0),0)),"ER"))
A36: DPG5g | B36: =VLOOKUP($A36,'PARASTATAL Questions'!$A:$J,3,0)&"" | C36: =VLOOKUP($A36,'PARASTATAL Questions'!$A:$J,4,0)&"" | D36: =VLOOKUP($A36,'PARASTATAL Questions'!$A:$J,5,0)&"" | E36: =VLOOKUP($A36,'PARASTATAL Questions'!$A:$J,7,0)&"" | F36: =VLOOKUP($A36,'PARASTATAL Questions'!$A:$J,6,0) | G36: =IF($F36=0,"NA",IF($A36=INDIRECT("'"&$A36&"'!$B$1"),IF(VLOOKUP(G$1,INDIRECT("'"&$A36&"'!$A$12:$Z$19"),MATCH("Points (Auto-generate)",INDIRECT("'"&$A36&"'!$A$12:$Z$12"),0),0)="","?",VLOOKUP(G$1,INDIRECT("'"&$A36&"'!$A$12:$Z$19"),MATCH("Points (Auto-generate)",INDIRECT("'"&$A36&"'!$A$12:$Z$12"),0),0)),"ER")) | H36: =IF($F36=0,"NA",IF($A36=INDIRECT("'"&$A36&"'!$B$1"),IF(VLOOKUP(H$1,INDIRECT("'"&$A36&"'!$A$12:$Z$19"),MATCH("Points (Auto-generate)",INDIRECT("'"&$A36&"'!$A$12:$Z$12"),0),0)="","?",VLOOKUP(H$1,INDIRECT("'"&$A36&"'!$A$12:$Z$19"),MATCH("Points (Auto-generate)",INDIRECT("'"&$A36&"'!$A$12:$Z$12"),0),0)),"ER")) | I36: =IF($F36=0,"NA",IF($A36=INDIRECT("'"&$A36&"'!$B$1"),IF(VLOOKUP(I$1,INDIRECT("'"&$A36&"'!$A$12:$Z$19"),MATCH("Points (Auto-generate)",INDIRECT("'"&$A36&"'!$A$12:$Z$12"),0),0)="","?",VLOOKUP(I$1,INDIRECT("'"&$A36&"'!$A$12:$Z$19"),MATCH("Points (Auto-generate)",INDIRECT("'"&$A36&"'!$A$12:$Z$12"),0),0)),"ER")) | J36: =IF($F36=0,"NA",IF($A36=INDIRECT("'"&$A36&"'!$B$1"),IF(VLOOKUP(J$1,INDIRECT("'"&$A36&"'!$A$12:$Z$19"),MATCH("Points (Auto-generate)",INDIRECT("'"&$A36&"'!$A$12:$Z$12"),0),0)="","?",VLOOKUP(J$1,INDIRECT("'"&$A36&"'!$A$12:$Z$19"),MATCH("Points (Auto-generate)",INDIRECT("'"&$A36&"'!$A$12:$Z$12"),0),0)),"ER")) | K36: =IF($F36=0,"NA",IF($A36=INDIRECT("'"&$A36&"'!$B$1"),IF(VLOOKUP(K$1,INDIRECT("'"&$A36&"'!$A$12:$Z$19"),MATCH("Points (Auto-generate)",INDIRECT("'"&$A36&"'!$A$12:$Z$12"),0),0)="","?",VLOOKUP(K$1,INDIRECT("'"&$A36&"'!$A$12:$Z$19"),MATCH("Points (Auto-generate)",INDIRECT("'"&$A36&"'!$A$12:$Z$12"),0),0)),"ER")) | L36: =IF($F36=0,"NA",IF($A36=INDIRECT("'"&$A36&"'!$B$1"),IF(VLOOKUP(L$1,INDIRECT("'"&$A36&"'!$A$12:$Z$19"),MATCH("Points (Auto-generate)",INDIRECT("'"&$A36&"'!$A$12:$Z$12"),0),0)="","?",VLOOKUP(L$1,INDIRECT("'"&$A36&"'!$A$12:$Z$19"),MATCH("Points (Auto-generate)",INDIRECT("'"&$A36&"'!$A$12:$Z$12"),0),0)),"ER")) | M36: =IF($F36=0,"NA",IF($A36=INDIRECT("'"&$A36&"'!$B$1"),IF(VLOOKUP(M$1,INDIRECT("'"&$A36&"'!$A$12:$Z$19"),MATCH("Points (Auto-generate)",INDIRECT("'"&$A36&"'!$A$12:$Z$12"),0),0)="","?",VLOOKUP(M$1,INDIRECT("'"&$A36&"'!$A$12:$Z$19"),MATCH("Points (Auto-generate)",INDIRECT("'"&$A36&"'!$A$12:$Z$12"),0),0)),"ER"))
A37: DPG5h | B37: =VLOOKUP($A37,'PARASTATAL Questions'!$A:$J,3,0)&"" | C37: =VLOOKUP($A37,'PARASTATAL Questions'!$A:$J,4,0)&"" | D37: =VLOOKUP($A37,'PARASTATAL Questions'!$A:$J,5,0)&"" | E37: =VLOOKUP($A37,'PARASTATAL Questions'!$A:$J,7,0)&"" | F37: =VLOOKUP($A37,'PARASTATAL Questions'!$A:$J,6,0) | G37: =IF($F37=0,"NA",IF($A37=INDIRECT("'"&$A37&"'!$B$1"),IF(VLOOKUP(G$1,INDIRECT("'"&$A37&"'!$A$12:$Z$19"),MATCH("Points (Auto-generate)",INDIRECT("'"&$A37&"'!$A$12:$Z$12"),0),0)="","?",VLOOKUP(G$1,INDIRECT("'"&$A37&"'!$A$12:$Z$19"),MATCH("Points (Auto-generate)",INDIRECT("'"&$A37&"'!$A$12:$Z$12"),0),0)),"ER")) | H37: =IF($F37=0,"NA",IF($A37=INDIRECT("'"&$A37&"'!$B$1"),IF(VLOOKUP(H$1,INDIRECT("'"&$A37&"'!$A$12:$Z$19"),MATCH("Points (Auto-generate)",INDIRECT("'"&$A37&"'!$A$12:$Z$12"),0),0)="","?",VLOOKUP(H$1,INDIRECT("'"&$A37&"'!$A$12:$Z$19"),MATCH("Points (Auto-generate)",INDIRECT("'"&$A37&"'!$A$12:$Z$12"),0),0)),"ER")) | I37: =IF($F37=0,"NA",IF($A37=INDIRECT("'"&$A37&"'!$B$1"),IF(VLOOKUP(I$1,INDIRECT("'"&$A37&"'!$A$12:$Z$19"),MATCH("Points (Auto-generate)",INDIRECT("'"&$A37&"'!$A$12:$Z$12"),0),0)="","?",VLOOKUP(I$1,INDIRECT("'"&$A37&"'!$A$12:$Z$19"),MATCH("Points (Auto-generate)",INDIRECT("'"&$A37&"'!$A$12:$Z$12"),0),0)),"ER")) | J37: =IF($F37=0,"NA",IF($A37=INDIRECT("'"&$A37&"'!$B$1"),IF(VLOOKUP(J$1,INDIRECT("'"&$A37&"'!$A$12:$Z$19"),MATCH("Points (Auto-generate)",INDIRECT("'"&$A37&"'!$A$12:$Z$12"),0),0)="","?",VLOOKUP(J$1,INDIRECT("'"&$A37&"'!$A$12:$Z$19"),MATCH("Points (Auto-generate)",INDIRECT("'"&$A37&"'!$A$12:$Z$12"),0),0)),"ER")) | K37: =IF($F37=0,"NA",IF($A37=INDIRECT("'"&$A37&"'!$B$1"),IF(VLOOKUP(K$1,INDIRECT("'"&$A37&"'!$A$12:$Z$19"),MATCH("Points (Auto-generate)",INDIRECT("'"&$A37&"'!$A$12:$Z$12"),0),0)="","?",VLOOKUP(K$1,INDIRECT("'"&$A37&"'!$A$12:$Z$19"),MATCH("Points (Auto-generate)",INDIRECT("'"&$A37&"'!$A$12:$Z$12"),0),0)),"ER")) | L37: =IF($F37=0,"NA",IF($A37=INDIRECT("'"&$A37&"'!$B$1"),IF(VLOOKUP(L$1,INDIRECT("'"&$A37&"'!$A$12:$Z$19"),MATCH("Points (Auto-generate)",INDIRECT("'"&$A37&"'!$A$12:$Z$12"),0),0)="","?",VLOOKUP(L$1,INDIRECT("'"&$A37&"'!$A$12:$Z$19"),MATCH("Points (Auto-generate)",INDIRECT("'"&$A37&"'!$A$12:$Z$12"),0),0)),"ER")) | M37: =IF($F37=0,"NA",IF($A37=INDIRECT("'"&$A37&"'!$B$1"),IF(VLOOKUP(M$1,INDIRECT("'"&$A37&"'!$A$12:$Z$19"),MATCH("Points (Auto-generate)",INDIRECT("'"&$A37&"'!$A$12:$Z$12"),0),0)="","?",VLOOKUP(M$1,INDIRECT("'"&$A37&"'!$A$12:$Z$19"),MATCH("Points (Auto-generate)",INDIRECT("'"&$A37&"'!$A$12:$Z$12"),0),0)),"ER"))
A38: DPG5i | B38: =VLOOKUP($A38,'PARASTATAL Questions'!$A:$J,3,0)&"" | C38: =VLOOKUP($A38,'PARASTATAL Questions'!$A:$J,4,0)&"" | D38: =VLOOKUP($A38,'PARASTATAL Questions'!$A:$J,5,0)&"" | E38: =VLOOKUP($A38,'PARASTATAL Questions'!$A:$J,7,0)&"" | F38: =VLOOKUP($A38,'PARASTATAL Questions'!$A:$J,6,0) | G38: =IF($F38=0,"NA",IF($A38=INDIRECT("'"&$A38&"'!$B$1"),IF(VLOOKUP(G$1,INDIRECT("'"&$A38&"'!$A$12:$Z$19"),MATCH("Points (Auto-generate)",INDIRECT("'"&$A38&"'!$A$12:$Z$12"),0),0)="","?",VLOOKUP(G$1,INDIRECT("'"&$A38&"'!$A$12:$Z$19"),MATCH("Points (Auto-generate)",INDIRECT("'"&$A38&"'!$A$12:$Z$12"),0),0)),"ER")) | H38: =IF($F38=0,"NA",IF($A38=INDIRECT("'"&$A38&"'!$B$1"),IF(VLOOKUP(H$1,INDIRECT("'"&$A38&"'!$A$12:$Z$19"),MATCH("Points (Auto-generate)",INDIRECT("'"&$A38&"'!$A$12:$Z$12"),0),0)="","?",VLOOKUP(H$1,INDIRECT("'"&$A38&"'!$A$12:$Z$19"),MATCH("Points (Auto-generate)",INDIRECT("'"&$A38&"'!$A$12:$Z$12"),0),0)),"ER")) | I38: =IF($F38=0,"NA",IF($A38=INDIRECT("'"&$A38&"'!$B$1"),IF(VLOOKUP(I$1,INDIRECT("'"&$A38&"'!$A$12:$Z$19"),MATCH("Points (Auto-generate)",INDIRECT("'"&$A38&"'!$A$12:$Z$12"),0),0)="","?",VLOOKUP(I$1,INDIRECT("'"&$A38&"'!$A$12:$Z$19"),MATCH("Points (Auto-generate)",INDIRECT("'"&$A38&"'!$A$12:$Z$12"),0),0)),"ER")) | J38: =IF($F38=0,"NA",IF($A38=INDIRECT("'"&$A38&"'!$B$1"),IF(VLOOKUP(J$1,INDIRECT("'"&$A38&"'!$A$12:$Z$19"),MATCH("Points (Auto-generate)",INDIRECT("'"&$A38&"'!$A$12:$Z$12"),0),0)="","?",VLOOKUP(J$1,INDIRECT("'"&$A38&"'!$A$12:$Z$19"),MATCH("Points (Auto-generate)",INDIRECT("'"&$A38&"'!$A$12:$Z$12"),0),0)),"ER")) | K38: =IF($F38=0,"NA",IF($A38=INDIRECT("'"&$A38&"'!$B$1"),IF(VLOOKUP(K$1,INDIRECT("'"&$A38&"'!$A$12:$Z$19"),MATCH("Points (Auto-generate)",INDIRECT("'"&$A38&"'!$A$12:$Z$12"),0),0)="","?",VLOOKUP(K$1,INDIRECT("'"&$A38&"'!$A$12:$Z$19"),MATCH("Points (Auto-generate)",INDIRECT("'"&$A38&"'!$A$12:$Z$12"),0),0)),"ER")) | L38: =IF($F38=0,"NA",IF($A38=INDIRECT("'"&$A38&"'!$B$1"),IF(VLOOKUP(L$1,INDIRECT("'"&$A38&"'!$A$12:$Z$19"),MATCH("Points (Auto-generate)",INDIRECT("'"&$A38&"'!$A$12:$Z$12"),0),0)="","?",VLOOKUP(L$1,INDIRECT("'"&$A38&"'!$A$12:$Z$19"),MATCH("Points (Auto-generate)",INDIRECT("'"&$A38&"'!$A$12:$Z$12"),0),0)),"ER")) | M38: =IF($F38=0,"NA",IF($A38=INDIRECT("'"&$A38&"'!$B$1"),IF(VLOOKUP(M$1,INDIRECT("'"&$A38&"'!$A$12:$Z$19"),MATCH("Points (Auto-generate)",INDIRECT("'"&$A38&"'!$A$12:$Z$12"),0),0)="","?",VLOOKUP(M$1,INDIRECT("'"&$A38&"'!$A$12:$Z$19"),MATCH("Points (Auto-generate)",INDIRECT("'"&$A38&"'!$A$12:$Z$12"),0),0)),"ER"))
A39: DPG5j | B39: =VLOOKUP($A39,'PARASTATAL Questions'!$A:$J,3,0)&"" | C39: =VLOOKUP($A39,'PARASTATAL Questions'!$A:$J,4,0)&"" | D39: =VLOOKUP($A39,'PARASTATAL Questions'!$A:$J,5,0)&"" | E39: =VLOOKUP($A39,'PARASTATAL Questions'!$A:$J,7,0)&"" | F39: =VLOOKUP($A39,'PARASTATAL Questions'!$A:$J,6,0) | G39: =IF($F39=0,"NA",IF($A39=INDIRECT("'"&$A39&"'!$B$1"),IF(VLOOKUP(G$1,INDIRECT("'"&$A39&"'!$A$12:$Z$19"),MATCH("Points (Auto-generate)",INDIRECT("'"&$A39&"'!$A$12:$Z$12"),0),0)="","?",VLOOKUP(G$1,INDIRECT("'"&$A39&"'!$A$12:$Z$19"),MATCH("Points (Auto-generate)",INDIRECT("'"&$A39&"'!$A$12:$Z$12"),0),0)),"ER")) | H39: =IF($F39=0,"NA",IF($A39=INDIRECT("'"&$A39&"'!$B$1"),IF(VLOOKUP(H$1,INDIRECT("'"&$A39&"'!$A$12:$Z$19"),MATCH("Points (Auto-generate)",INDIRECT("'"&$A39&"'!$A$12:$Z$12"),0),0)="","?",VLOOKUP(H$1,INDIRECT("'"&$A39&"'!$A$12:$Z$19"),MATCH("Points (Auto-generate)",INDIRECT("'"&$A39&"'!$A$12:$Z$12"),0),0)),"ER")) | I39: =IF($F39=0,"NA",IF($A39=INDIRECT("'"&$A39&"'!$B$1"),IF(VLOOKUP(I$1,INDIRECT("'"&$A39&"'!$A$12:$Z$19"),MATCH("Points (Auto-generate)",INDIRECT("'"&$A39&"'!$A$12:$Z$12"),0),0)="","?",VLOOKUP(I$1,INDIRECT("'"&$A39&"'!$A$12:$Z$19"),MATCH("Points (Auto-generate)",INDIRECT("'"&$A39&"'!$A$12:$Z$12"),0),0)),"ER")) | J39: =IF($F39=0,"NA",IF($A39=INDIRECT("'"&$A39&"'!$B$1"),IF(VLOOKUP(J$1,INDIRECT("'"&$A39&"'!$A$12:$Z$19"),MATCH("Points (Auto-generate)",INDIRECT("'"&$A39&"'!$A$12:$Z$12"),0),0)="","?",VLOOKUP(J$1,INDIRECT("'"&$A39&"'!$A$12:$Z$19"),MATCH("Points (Auto-generate)",INDIRECT("'"&$A39&"'!$A$12:$Z$12"),0),0)),"ER")) | K39: =IF($F39=0,"NA",IF($A39=INDIRECT("'"&$A39&"'!$B$1"),IF(VLOOKUP(K$1,INDIRECT("'"&$A39&"'!$A$12:$Z$19"),MATCH("Points (Auto-generate)",INDIRECT("'"&$A39&"'!$A$12:$Z$12"),0),0)="","?",VLOOKUP(K$1,INDIRECT("'"&$A39&"'!$A$12:$Z$19"),MATCH("Points (Auto-generate)",INDIRECT("'"&$A39&"'!$A$12:$Z$12"),0),0)),"ER")) | L39: =IF($F39=0,"NA",IF($A39=INDIRECT("'"&$A39&"'!$B$1"),IF(VLOOKUP(L$1,INDIRECT("'"&$A39&"'!$A$12:$Z$19"),MATCH("Points (Auto-generate)",INDIRECT("'"&$A39&"'!$A$12:$Z$12"),0),0)="","?",VLOOKUP(L$1,INDIRECT("'"&$A39&"'!$A$12:$Z$19"),MATCH("Points (Auto-generate)",INDIRECT("'"&$A39&"'!$A$12:$Z$12"),0),0)),"ER")) | M39: =IF($F39=0,"NA",IF($A39=INDIRECT("'"&$A39&"'!$B$1"),IF(VLOOKUP(M$1,INDIRECT("'"&$A39&"'!$A$12:$Z$19"),MATCH("Points (Auto-generate)",INDIRECT("'"&$A39&"'!$A$12:$Z$12"),0),0)="","?",VLOOKUP(M$1,INDIRECT("'"&$A39&"'!$A$12:$Z$19"),MATCH("Points (Auto-generate)",INDIRECT("'"&$A39&"'!$A$12:$Z$12"),0),0)),"ER"))
A40: DPG5k | B40: =VLOOKUP($A40,'PARASTATAL Questions'!$A:$J,3,0)&"" | C40: =VLOOKUP($A40,'PARASTATAL Questions'!$A:$J,4,0)&"" | D40: =VLOOKUP($A40,'PARASTATAL Questions'!$A:$J,5,0)&"" | E40: =VLOOKUP($A40,'PARASTATAL Questions'!$A:$J,7,0)&"" | F40: =VLOOKUP($A40,'PARASTATAL Questions'!$A:$J,6,0) | G40: =IF($F40=0,"NA",IF($A40=INDIRECT("'"&$A40&"'!$B$1"),IF(VLOOKUP(G$1,INDIRECT("'"&$A40&"'!$A$12:$Z$19"),MATCH("Points (Auto-generate)",INDIRECT("'"&$A40&"'!$A$12:$Z$12"),0),0)="","?",VLOOKUP(G$1,INDIRECT("'"&$A40&"'!$A$12:$Z$19"),MATCH("Points (Auto-generate)",INDIRECT("'"&$A40&"'!$A$12:$Z$12"),0),0)),"ER")) | H40: =IF($F40=0,"NA",IF($A40=INDIRECT("'"&$A40&"'!$B$1"),IF(VLOOKUP(H$1,INDIRECT("'"&$A40&"'!$A$12:$Z$19"),MATCH("Points (Auto-generate)",INDIRECT("'"&$A40&"'!$A$12:$Z$12"),0),0)="","?",VLOOKUP(H$1,INDIRECT("'"&$A40&"'!$A$12:$Z$19"),MATCH("Points (Auto-generate)",INDIRECT("'"&$A40&"'!$A$12:$Z$12"),0),0)),"ER")) | I40: =IF($F40=0,"NA",IF($A40=INDIRECT("'"&$A40&"'!$B$1"),IF(VLOOKUP(I$1,INDIRECT("'"&$A40&"'!$A$12:$Z$19"),MATCH("Points (Auto-generate)",INDIRECT("'"&$A40&"'!$A$12:$Z$12"),0),0)="","?",VLOOKUP(I$1,INDIRECT("'"&$A40&"'!$A$12:$Z$19"),MATCH("Points (Auto-generate)",INDIRECT("'"&$A40&"'!$A$12:$Z$12"),0),0)),"ER")) | J40: =IF($F40=0,"NA",IF($A40=INDIRECT("'"&$A40&"'!$B$1"),IF(VLOOKUP(J$1,INDIRECT("'"&$A40&"'!$A$12:$Z$19"),MATCH("Points (Auto-generate)",INDIRECT("'"&$A40&"'!$A$12:$Z$12"),0),0)="","?",VLOOKUP(J$1,INDIRECT("'"&$A40&"'!$A$12:$Z$19"),MATCH("Points (Auto-generate)",INDIRECT("'"&$A40&"'!$A$12:$Z$12"),0),0)),"ER")) | K40: =IF($F40=0,"NA",IF($A40=INDIRECT("'"&$A40&"'!$B$1"),IF(VLOOKUP(K$1,INDIRECT("'"&$A40&"'!$A$12:$Z$19"),MATCH("Points (Auto-generate)",INDIRECT("'"&$A40&"'!$A$12:$Z$12"),0),0)="","?",VLOOKUP(K$1,INDIRECT("'"&$A40&"'!$A$12:$Z$19"),MATCH("Points (Auto-generate)",INDIRECT("'"&$A40&"'!$A$12:$Z$12"),0),0)),"ER")) | L40: =IF($F40=0,"NA",IF($A40=INDIRECT("'"&$A40&"'!$B$1"),IF(VLOOKUP(L$1,INDIRECT("'"&$A40&"'!$A$12:$Z$19"),MATCH("Points (Auto-generate)",INDIRECT("'"&$A40&"'!$A$12:$Z$12"),0),0)="","?",VLOOKUP(L$1,INDIRECT("'"&$A40&"'!$A$12:$Z$19"),MATCH("Points (Auto-generate)",INDIRECT("'"&$A40&"'!$A$12:$Z$12"),0),0)),"ER")) | M40: =IF($F40=0,"NA",IF($A40=INDIRECT("'"&$A40&"'!$B$1"),IF(VLOOKUP(M$1,INDIRECT("'"&$A40&"'!$A$12:$Z$19"),MATCH("Points (Auto-generate)",INDIRECT("'"&$A40&"'!$A$12:$Z$12"),0),0)="","?",VLOOKUP(M$1,INDIRECT("'"&$A40&"'!$A$12:$Z$19"),MATCH("Points (Auto-generate)",INDIRECT("'"&$A40&"'!$A$12:$Z$12"),0),0)),"ER"))
A41: DPG6 | B41: =VLOOKUP($A41,'PARASTATAL Questions'!$A:$J,3,0)&"" | C41: =VLOOKUP($A41,'PARASTATAL Questions'!$A:$J,4,0)&"" | D41: =VLOOKUP($A41,'PARASTATAL Questions'!$A:$J,5,0)&"" | E41: =VLOOKUP($A41,'PARASTATAL Questions'!$A:$J,7,0)&"" | F41: =VLOOKUP($A41,'PARASTATAL Questions'!$A:$J,6,0) | G41: =IF(OR(G42="ER",G43="ER"),"ER",IF(OR(G42="?",G43="?"),"?",IF(AND(G42="NA",G43="NA"),"NA",SUM(G42,G43)/((G42<>"NA")*$F$42+(G43<>"NA")*$F$43)*$F41))) | H41: =IF(OR(H42="ER",H43="ER"),"ER",IF(OR(H42="?",H43="?"),"?",IF(AND(H42="NA",H43="NA"),"NA",SUM(H42,H43)/((H42<>"NA")*$F$42+(H43<>"NA")*$F$43)*$F41))) | I41: =IF(OR(I42="ER",I43="ER"),"ER",IF(OR(I42="?",I43="?"),"?",IF(AND(I42="NA",I43="NA"),"NA",SUM(I42,I43)/((I42<>"NA")*$F$42+(I43<>"NA")*$F$43)*$F41))) | J41: =IF(OR(J42="ER",J43="ER"),"ER",IF(OR(J42="?",J43="?"),"?",IF(AND(J42="NA",J43="NA"),"NA",SUM(J42,J43)/((J42<>"NA")*$F$42+(J43<>"NA")*$F$43)*$F41))) | K41: =IF(OR(K42="ER",K43="ER"),"ER",IF(OR(K42="?",K43="?"),"?",IF(AND(K42="NA",K43="NA"),"NA",SUM(K42,K43)/((K42<>"NA")*$F$42+(K43<>"NA")*$F$43)*$F41))) | L41: =IF(OR(L42="ER",L43="ER"),"ER",IF(OR(L42="?",L43="?"),"?",IF(AND(L42="NA",L43="NA"),"NA",SUM(L42,L43)/((L42<>"NA")*$F$42+(L43<>"NA")*$F$43)*$F41))) | M41: =IF(OR(M42="ER",M43="ER"),"ER",IF(OR(M42="?",M43="?"),"?",IF(AND(M42="NA",M43="NA"),"NA",SUM(M42,M43)/((M42<>"NA")*$F$42+(M43<>"NA")*$F$43)*$F41)))
A42: DPG6a | B42: =VLOOKUP($A42,'PARASTATAL Questions'!$A:$J,3,0)&"" | C42: =VLOOKUP($A42,'PARASTATAL Questions'!$A:$J,4,0)&"" | D42: =VLOOKUP($A42,'PARASTATAL Questions'!$A:$J,5,0)&"" | E42: =VLOOKUP($A42,'PARASTATAL Questions'!$A:$J,7,0)&"" | F42: =VLOOKUP($A42,'PARASTATAL Questions'!$A:$J,6,0) | G42: =IF($F42=0,"NA",IF($A42=INDIRECT("'"&$A42&"'!$B$1"),IF(VLOOKUP(G$1,INDIRECT("'"&$A42&"'!$A$12:$Z$19"),MATCH("Points (Auto-generate)",INDIRECT("'"&$A42&"'!$A$12:$Z$12"),0),0)="","?",VLOOKUP(G$1,INDIRECT("'"&$A42&"'!$A$12:$Z$19"),MATCH("Points (Auto-generate)",INDIRECT("'"&$A42&"'!$A$12:$Z$12"),0),0)),"ER")) | H42: =IF($F42=0,"NA",IF($A42=INDIRECT("'"&$A42&"'!$B$1"),IF(VLOOKUP(H$1,INDIRECT("'"&$A42&"'!$A$12:$Z$19"),MATCH("Points (Auto-generate)",INDIRECT("'"&$A42&"'!$A$12:$Z$12"),0),0)="","?",VLOOKUP(H$1,INDIRECT("'"&$A42&"'!$A$12:$Z$19"),MATCH("Points (Auto-generate)",INDIRECT("'"&$A42&"'!$A$12:$Z$12"),0),0)),"ER")) | I42: =IF($F42=0,"NA",IF($A42=INDIRECT("'"&$A42&"'!$B$1"),IF(VLOOKUP(I$1,INDIRECT("'"&$A42&"'!$A$12:$Z$19"),MATCH("Points (Auto-generate)",INDIRECT("'"&$A42&"'!$A$12:$Z$12"),0),0)="","?",VLOOKUP(I$1,INDIRECT("'"&$A42&"'!$A$12:$Z$19"),MATCH("Points (Auto-generate)",INDIRECT("'"&$A42&"'!$A$12:$Z$12"),0),0)),"ER")) | J42: =IF($F42=0,"NA",IF($A42=INDIRECT("'"&$A42&"'!$B$1"),IF(VLOOKUP(J$1,INDIRECT("'"&$A42&"'!$A$12:$Z$19"),MATCH("Points (Auto-generate)",INDIRECT("'"&$A42&"'!$A$12:$Z$12"),0),0)="","?",VLOOKUP(J$1,INDIRECT("'"&$A42&"'!$A$12:$Z$19"),MATCH("Points (Auto-generate)",INDIRECT("'"&$A42&"'!$A$12:$Z$12"),0),0)),"ER")) | K42: =IF($F42=0,"NA",IF($A42=INDIRECT("'"&$A42&"'!$B$1"),IF(VLOOKUP(K$1,INDIRECT("'"&$A42&"'!$A$12:$Z$19"),MATCH("Points (Auto-generate)",INDIRECT("'"&$A42&"'!$A$12:$Z$12"),0),0)="","?",VLOOKUP(K$1,INDIRECT("'"&$A42&"'!$A$12:$Z$19"),MATCH("Points (Auto-generate)",INDIRECT("'"&$A42&"'!$A$12:$Z$12"),0),0)),"ER")) | L42: =IF($F42=0,"NA",IF($A42=INDIRECT("'"&$A42&"'!$B$1"),IF(VLOOKUP(L$1,INDIRECT("'"&$A42&"'!$A$12:$Z$19"),MATCH("Points (Auto-generate)",INDIRECT("'"&$A42&"'!$A$12:$Z$12"),0),0)="","?",VLOOKUP(L$1,INDIRECT("'"&$A42&"'!$A$12:$Z$19"),MATCH("Points (Auto-generate)",INDIRECT("'"&$A42&"'!$A$12:$Z$12"),0),0)),"ER")) | M42: =IF($F42=0,"NA",IF($A42=INDIRECT("'"&$A42&"'!$B$1"),IF(VLOOKUP(M$1,INDIRECT("'"&$A42&"'!$A$12:$Z$19"),MATCH("Points (Auto-generate)",INDIRECT("'"&$A42&"'!$A$12:$Z$12"),0),0)="","?",VLOOKUP(M$1,INDIRECT("'"&$A42&"'!$A$12:$Z$19"),MATCH("Points (Auto-generate)",INDIRECT("'"&$A42&"'!$A$12:$Z$12"),0),0)),"ER"))
A43: DPG6b | B43: =VLOOKUP($A43,'PARASTATAL Questions'!$A:$J,3,0)&"" | C43: =VLOOKUP($A43,'PARASTATAL Questions'!$A:$J,4,0)&"" | D43: =VLOOKUP($A43,'PARASTATAL Questions'!$A:$J,5,0)&"" | E43: =VLOOKUP($A43,'PARASTATAL Questions'!$A:$J,7,0)&"" | F43: =VLOOKUP($A43,'PARASTATAL Questions'!$A:$J,6,0) | G43: =IF($F43=0,"NA",IF($A43=INDIRECT("'"&$A43&"'!$B$1"),IF(VLOOKUP(G$1,INDIRECT("'"&$A43&"'!$A$12:$Z$19"),MATCH("Points (Auto-generate)",INDIRECT("'"&$A43&"'!$A$12:$Z$12"),0),0)="","?",VLOOKUP(G$1,INDIRECT("'"&$A43&"'!$A$12:$Z$19"),MATCH("Points (Auto-generate)",INDIRECT("'"&$A43&"'!$A$12:$Z$12"),0),0)),"ER")) | H43: =IF($F43=0,"NA",IF($A43=INDIRECT("'"&$A43&"'!$B$1"),IF(VLOOKUP(H$1,INDIRECT("'"&$A43&"'!$A$12:$Z$19"),MATCH("Points (Auto-generate)",INDIRECT("'"&$A43&"'!$A$12:$Z$12"),0),0)="","?",VLOOKUP(H$1,INDIRECT("'"&$A43&"'!$A$12:$Z$19"),MATCH("Points (Auto-generate)",INDIRECT("'"&$A43&"'!$A$12:$Z$12"),0),0)),"ER")) | I43: =IF($F43=0,"NA",IF($A43=INDIRECT("'"&$A43&"'!$B$1"),IF(VLOOKUP(I$1,INDIRECT("'"&$A43&"'!$A$12:$Z$19"),MATCH("Points (Auto-generate)",INDIRECT("'"&$A43&"'!$A$12:$Z$12"),0),0)="","?",VLOOKUP(I$1,INDIRECT("'"&$A43&"'!$A$12:$Z$19"),MATCH("Points (Auto-generate)",INDIRECT("'"&$A43&"'!$A$12:$Z$12"),0),0)),"ER")) | J43: =IF($F43=0,"NA",IF($A43=INDIRECT("'"&$A43&"'!$B$1"),IF(VLOOKUP(J$1,INDIRECT("'"&$A43&"'!$A$12:$Z$19"),MATCH("Points (Auto-generate)",INDIRECT("'"&$A43&"'!$A$12:$Z$12"),0),0)="","?",VLOOKUP(J$1,INDIRECT("'"&$A43&"'!$A$12:$Z$19"),MATCH("Points (Auto-generate)",INDIRECT("'"&$A43&"'!$A$12:$Z$12"),0),0)),"ER")) | K43: =IF($F43=0,"NA",IF($A43=INDIRECT("'"&$A43&"'!$B$1"),IF(VLOOKUP(K$1,INDIRECT("'"&$A43&"'!$A$12:$Z$19"),MATCH("Points (Auto-generate)",INDIRECT("'"&$A43&"'!$A$12:$Z$12"),0),0)="","?",VLOOKUP(K$1,INDIRECT("'"&$A43&"'!$A$12:$Z$19"),MATCH("Points (Auto-generate)",INDIRECT("'"&$A43&"'!$A$12:$Z$12"),0),0)),"ER")) | L43: =IF($F43=0,"NA",IF($A43=INDIRECT("'"&$A43&"'!$B$1"),IF(VLOOKUP(L$1,INDIRECT("'"&$A43&"'!$A$12:$Z$19"),MATCH("Points (Auto-generate)",INDIRECT("'"&$A43&"'!$A$12:$Z$12"),0),0)="","?",VLOOKUP(L$1,INDIRECT("'"&$A43&"'!$A$12:$Z$19"),MATCH("Points (Auto-generate)",INDIRECT("'"&$A43&"'!$A$12:$Z$12"),0),0)),"ER")) | M43: =IF($F43=0,"NA",IF($A43=INDIRECT("'"&$A43&"'!$B$1"),IF(VLOOKUP(M$1,INDIRECT("'"&$A43&"'!$A$12:$Z$19"),MATCH("Points (Auto-generate)",INDIRECT("'"&$A43&"'!$A$12:$Z$12"),0),0)="","?",VLOOKUP(M$1,INDIRECT("'"&$A43&"'!$A$12:$Z$19"),MATCH("Points (Auto-generate)",INDIRECT("'"&$A43&"'!$A$12:$Z$12"),0),0)),"ER"))
A44: DPG7 | B44: =VLOOKUP($A44,'PARASTATAL Questions'!$A:$J,3,0)&"" | C44: =VLOOKUP($A44,'PARASTATAL Questions'!$A:$J,4,0)&"" | D44: =VLOOKUP($A44,'PARASTATAL Questions'!$A:$J,5,0)&"" | E44: =VLOOKUP($A44,'PARASTATAL Questions'!$A:$J,7,0)&"" | F44: =VLOOKUP($A44,'PARASTATAL Questions'!$A:$J,6,0) | G44: =IF(OR(G45="ER",G46="ER"),"ER",IF(OR(G45="?",G46="?"),"?",IF(AND(G45="NA",G46="NA"),"NA",SUM(G45,G46)/((G45<>"NA")*$F$45+(G46<>"NA")*$F$46)*$F44))) | H44: =IF(OR(H45="ER",H46="ER"),"ER",IF(OR(H45="?",H46="?"),"?",IF(AND(H45="NA",H46="NA"),"NA",SUM(H45,H46)/((H45<>"NA")*$F$45+(H46<>"NA")*$F$46)*$F44))) | I44: =IF(OR(I45="ER",I46="ER"),"ER",IF(OR(I45="?",I46="?"),"?",IF(AND(I45="NA",I46="NA"),"NA",SUM(I45,I46)/((I45<>"NA")*$F$45+(I46<>"NA")*$F$46)*$F44))) | J44: =IF(OR(J45="ER",J46="ER"),"ER",IF(OR(J45="?",J46="?"),"?",IF(AND(J45="NA",J46="NA"),"NA",SUM(J45,J46)/((J45<>"NA")*$F$45+(J46<>"NA")*$F$46)*$F44))) | K44: =IF(OR(K45="ER",K46="ER"),"ER",IF(OR(K45="?",K46="?"),"?",IF(AND(K45="NA",K46="NA"),"NA",SUM(K45,K46)/((K45<>"NA")*$F$45+(K46<>"NA")*$F$46)*$F44))) | L44: =IF(OR(L45="ER",L46="ER"),"ER",IF(OR(L45="?",L46="?"),"?",IF(AND(L45="NA",L46="NA"),"NA",SUM(L45,L46)/((L45<>"NA")*$F$45+(L46<>"NA")*$F$46)*$F44))) | M44: =IF(OR(M45="ER",M46="ER"),"ER",IF(OR(M45="?",M46="?"),"?",IF(AND(M45="NA",M46="NA"),"NA",SUM(M45,M46)/((M45<>"NA")*$F$45+(M46<>"NA")*$F$46)*$F44)))
A45: DPG7a | B45: =VLOOKUP($A45,'PARASTATAL Questions'!$A:$J,3,0)&"" | C45: =VLOOKUP($A45,'PARASTATAL Questions'!$A:$J,4,0)&"" | D45: =VLOOKUP($A45,'PARASTATAL Questions'!$A:$J,5,0)&"" | E45: =VLOOKUP($A45,'PARASTATAL Questions'!$A:$J,7,0)&"" | F45: =VLOOKUP($A45,'PARASTATAL Questions'!$A:$J,6,0) | G45: =IF($F45=0,"NA",IF($A45=INDIRECT("'"&$A45&"'!$B$1"),IF(VLOOKUP(G$1,INDIRECT("'"&$A45&"'!$A$12:$Z$19"),MATCH("Points (Auto-generate)",INDIRECT("'"&$A45&"'!$A$12:$Z$12"),0),0)="","?",VLOOKUP(G$1,INDIRECT("'"&$A45&"'!$A$12:$Z$19"),MATCH("Points (Auto-generate)",INDIRECT("'"&$A45&"'!$A$12:$Z$12"),0),0)),"ER")) | H45: =IF($F45=0,"NA",IF($A45=INDIRECT("'"&$A45&"'!$B$1"),IF(VLOOKUP(H$1,INDIRECT("'"&$A45&"'!$A$12:$Z$19"),MATCH("Points (Auto-generate)",INDIRECT("'"&$A45&"'!$A$12:$Z$12"),0),0)="","?",VLOOKUP(H$1,INDIRECT("'"&$A45&"'!$A$12:$Z$19"),MATCH("Points (Auto-generate)",INDIRECT("'"&$A45&"'!$A$12:$Z$12"),0),0)),"ER")) | I45: =IF($F45=0,"NA",IF($A45=INDIRECT("'"&$A45&"'!$B$1"),IF(VLOOKUP(I$1,INDIRECT("'"&$A45&"'!$A$12:$Z$19"),MATCH("Points (Auto-generate)",INDIRECT("'"&$A45&"'!$A$12:$Z$12"),0),0)="","?",VLOOKUP(I$1,INDIRECT("'"&$A45&"'!$A$12:$Z$19"),MATCH("Points (Auto-generate)",INDIRECT("'"&$A45&"'!$A$12:$Z$12"),0),0)),"ER")) | J45: =IF($F45=0,"NA",IF($A45=INDIRECT("'"&$A45&"'!$B$1"),IF(VLOOKUP(J$1,INDIRECT("'"&$A45&"'!$A$12:$Z$19"),MATCH("Points (Auto-generate)",INDIRECT("'"&$A45&"'!$A$12:$Z$12"),0),0)="","?",VLOOKUP(J$1,INDIRECT("'"&$A45&"'!$A$12:$Z$19"),MATCH("Points (Auto-generate)",INDIRECT("'"&$A45&"'!$A$12:$Z$12"),0),0)),"ER")) | K45: =IF($F45=0,"NA",IF($A45=INDIRECT("'"&$A45&"'!$B$1"),IF(VLOOKUP(K$1,INDIRECT("'"&$A45&"'!$A$12:$Z$19"),MATCH("Points (Auto-generate)",INDIRECT("'"&$A45&"'!$A$12:$Z$12"),0),0)="","?",VLOOKUP(K$1,INDIRECT("'"&$A45&"'!$A$12:$Z$19"),MATCH("Points (Auto-generate)",INDIRECT("'"&$A45&"'!$A$12:$Z$12"),0),0)),"ER")) | L45: =IF($F45=0,"NA",IF($A45=INDIRECT("'"&$A45&"'!$B$1"),IF(VLOOKUP(L$1,INDIRECT("'"&$A45&"'!$A$12:$Z$19"),MATCH("Points (Auto-generate)",INDIRECT("'"&$A45&"'!$A$12:$Z$12"),0),0)="","?",VLOOKUP(L$1,INDIRECT("'"&$A45&"'!$A$12:$Z$19"),MATCH("Points (Auto-generate)",INDIRECT("'"&$A45&"'!$A$12:$Z$12"),0),0)),"ER")) | M45: =IF($F45=0,"NA",IF($A45=INDIRECT("'"&$A45&"'!$B$1"),IF(VLOOKUP(M$1,INDIRECT("'"&$A45&"'!$A$12:$Z$19"),MATCH("Points (Auto-generate)",INDIRECT("'"&$A45&"'!$A$12:$Z$12"),0),0)="","?",VLOOKUP(M$1,INDIRECT("'"&$A45&"'!$A$12:$Z$19"),MATCH("Points (Auto-generate)",INDIRECT("'"&$A45&"'!$A$12:$Z$12"),0),0)),"ER"))
A46: DPG7b | B46: =VLOOKUP($A46,'PARASTATAL Questions'!$A:$J,3,0)&"" | C46: =VLOOKUP($A46,'PARASTATAL Questions'!$A:$J,4,0)&"" | D46: =VLOOKUP($A46,'PARASTATAL Questions'!$A:$J,5,0)&"" | E46: =VLOOKUP($A46,'PARASTATAL Questions'!$A:$J,7,0)&"" | F46: =VLOOKUP($A46,'PARASTATAL Questions'!$A:$J,6,0) | G46: =IF($F46=0,"NA",IF($A46=INDIRECT("'"&$A46&"'!$B$1"),IF(VLOOKUP(G$1,INDIRECT("'"&$A46&"'!$A$12:$Z$19"),MATCH("Points (Auto-generate)",INDIRECT("'"&$A46&"'!$A$12:$Z$12"),0),0)="","?",VLOOKUP(G$1,INDIRECT("'"&$A46&"'!$A$12:$Z$19"),MATCH("Points (Auto-generate)",INDIRECT("'"&$A46&"'!$A$12:$Z$12"),0),0)),"ER")) | H46: =IF($F46=0,"NA",IF($A46=INDIRECT("'"&$A46&"'!$B$1"),IF(VLOOKUP(H$1,INDIRECT("'"&$A46&"'!$A$12:$Z$19"),MATCH("Points (Auto-generate)",INDIRECT("'"&$A46&"'!$A$12:$Z$12"),0),0)="","?",VLOOKUP(H$1,INDIRECT("'"&$A46&"'!$A$12:$Z$19"),MATCH("Points (Auto-generate)",INDIRECT("'"&$A46&"'!$A$12:$Z$12"),0),0)),"ER")) | I46: =IF($F46=0,"NA",IF($A46=INDIRECT("'"&$A46&"'!$B$1"),IF(VLOOKUP(I$1,INDIRECT("'"&$A46&"'!$A$12:$Z$19"),MATCH("Points (Auto-generate)",INDIRECT("'"&$A46&"'!$A$12:$Z$12"),0),0)="","?",VLOOKUP(I$1,INDIRECT("'"&$A46&"'!$A$12:$Z$19"),MATCH("Points (Auto-generate)",INDIRECT("'"&$A46&"'!$A$12:$Z$12"),0),0)),"ER")) | J46: =IF($F46=0,"NA",IF($A46=INDIRECT("'"&$A46&"'!$B$1"),IF(VLOOKUP(J$1,INDIRECT("'"&$A46&"'!$A$12:$Z$19"),MATCH("Points (Auto-generate)",INDIRECT("'"&$A46&"'!$A$12:$Z$12"),0),0)="","?",VLOOKUP(J$1,INDIRECT("'"&$A46&"'!$A$12:$Z$19"),MATCH("Points (Auto-generate)",INDIRECT("'"&$A46&"'!$A$12:$Z$12"),0),0)),"ER")) | K46: =IF($F46=0,"NA",IF($A46=INDIRECT("'"&$A46&"'!$B$1"),IF(VLOOKUP(K$1,INDIRECT("'"&$A46&"'!$A$12:$Z$19"),MATCH("Points (Auto-generate)",INDIRECT("'"&$A46&"'!$A$12:$Z$12"),0),0)="","?",VLOOKUP(K$1,INDIRECT("'"&$A46&"'!$A$12:$Z$19"),MATCH("Points (Auto-generate)",INDIRECT("'"&$A46&"'!$A$12:$Z$12"),0),0)),"ER")) | L46: =IF($F46=0,"NA",IF($A46=INDIRECT("'"&$A46&"'!$B$1"),IF(VLOOKUP(L$1,INDIRECT("'"&$A46&"'!$A$12:$Z$19"),MATCH("Points (Auto-generate)",INDIRECT("'"&$A46&"'!$A$12:$Z$12"),0),0)="","?",VLOOKUP(L$1,INDIRECT("'"&$A46&"'!$A$12:$Z$19"),MATCH("Points (Auto-generate)",INDIRECT("'"&$A46&"'!$A$12:$Z$12"),0),0)),"ER")) | M46: =IF($F46=0,"NA",IF($A46=INDIRECT("'"&$A46&"'!$B$1"),IF(VLOOKUP(M$1,INDIRECT("'"&$A46&"'!$A$12:$Z$19"),MATCH("Points (Auto-generate)",INDIRECT("'"&$A46&"'!$A$12:$Z$12"),0),0)="","?",VLOOKUP(M$1,INDIRECT("'"&$A46&"'!$A$12:$Z$19"),MATCH("Points (Auto-generate)",INDIRECT("'"&$A46&"'!$A$12:$Z$12"),0),0)),"ER"))
A47: SC1 | B47: =VLOOKUP($A47,'PARASTATAL Questions'!$A:$J,3,0)&"" | C47: =VLOOKUP($A47,'PARASTATAL Questions'!$A:$J,4,0)&"" | D47: =VLOOKUP($A47,'PARASTATAL Questions'!$A:$J,5,0)&"" | E47: =VLOOKUP($A47,'PARASTATAL Questions'!$A:$J,7,0)&"" | F47: =VLOOKUP($A47,'PARASTATAL Questions'!$A:$J,6,0) | G47: =IF($F47=0,"NA",IF($A47=INDIRECT("'"&$A47&"'!$B$1"),IF(VLOOKUP(G$1,INDIRECT("'"&$A47&"'!$A$12:$Z$19"),MATCH("Points (Auto-generate)",INDIRECT("'"&$A47&"'!$A$12:$Z$12"),0),0)="","?",VLOOKUP(G$1,INDIRECT("'"&$A47&"'!$A$12:$Z$19"),MATCH("Points (Auto-generate)",INDIRECT("'"&$A47&"'!$A$12:$Z$12"),0),0)),"ER")) | H47: =IF($F47=0,"NA",IF($A47=INDIRECT("'"&$A47&"'!$B$1"),IF(VLOOKUP(H$1,INDIRECT("'"&$A47&"'!$A$12:$Z$19"),MATCH("Points (Auto-generate)",INDIRECT("'"&$A47&"'!$A$12:$Z$12"),0),0)="","?",VLOOKUP(H$1,INDIRECT("'"&$A47&"'!$A$12:$Z$19"),MATCH("Points (Auto-generate)",INDIRECT("'"&$A47&"'!$A$12:$Z$12"),0),0)),"ER")) | I47: =IF($F47=0,"NA",IF($A47=INDIRECT("'"&$A47&"'!$B$1"),IF(VLOOKUP(I$1,INDIRECT("'"&$A47&"'!$A$12:$Z$19"),MATCH("Points (Auto-generate)",INDIRECT("'"&$A47&"'!$A$12:$Z$12"),0),0)="","?",VLOOKUP(I$1,INDIRECT("'"&$A47&"'!$A$12:$Z$19"),MATCH("Points (Auto-generate)",INDIRECT("'"&$A47&"'!$A$12:$Z$12"),0),0)),"ER")) | J47: =IF($F47=0,"NA",IF($A47=INDIRECT("'"&$A47&"'!$B$1"),IF(VLOOKUP(J$1,INDIRECT("'"&$A47&"'!$A$12:$Z$19"),MATCH("Points (Auto-generate)",INDIRECT("'"&$A47&"'!$A$12:$Z$12"),0),0)="","?",VLOOKUP(J$1,INDIRECT("'"&$A47&"'!$A$12:$Z$19"),MATCH("Points (Auto-generate)",INDIRECT("'"&$A47&"'!$A$12:$Z$12"),0),0)),"ER")) | K47: =IF($F47=0,"NA",IF($A47=INDIRECT("'"&$A47&"'!$B$1"),IF(VLOOKUP(K$1,INDIRECT("'"&$A47&"'!$A$12:$Z$19"),MATCH("Points (Auto-generate)",INDIRECT("'"&$A47&"'!$A$12:$Z$12"),0),0)="","?",VLOOKUP(K$1,INDIRECT("'"&$A47&"'!$A$12:$Z$19"),MATCH("Points (Auto-generate)",INDIRECT("'"&$A47&"'!$A$12:$Z$12"),0),0)),"ER")) | L47: =IF($F47=0,"NA",IF($A47=INDIRECT("'"&$A47&"'!$B$1"),IF(VLOOKUP(L$1,INDIRECT("'"&$A47&"'!$A$12:$Z$19"),MATCH("Points (Auto-generate)",INDIRECT("'"&$A47&"'!$A$12:$Z$12"),0),0)="","?",VLOOKUP(L$1,INDIRECT("'"&$A47&"'!$A$12:$Z$19"),MATCH("Points (Auto-generate)",INDIRECT("'"&$A47&"'!$A$12:$Z$12"),0),0)),"ER")) | M47: =IF($F47=0,"NA",IF($A47=INDIRECT("'"&$A47&"'!$B$1"),IF(VLOOKUP(M$1,INDIRECT("'"&$A47&"'!$A$12:$Z$19"),MATCH("Points (Auto-generate)",INDIRECT("'"&$A47&"'!$A$12:$Z$12"),0),0)="","?",VLOOKUP(M$1,INDIRECT("'"&$A47&"'!$A$12:$Z$19"),MATCH("Points (Auto-generate)",INDIRECT("'"&$A47&"'!$A$12:$Z$12"),0),0)),"ER"))
A48: SC2 | B48: =VLOOKUP($A48,'PARASTATAL Questions'!$A:$J,3,0)&"" | C48: =VLOOKUP($A48,'PARASTATAL Questions'!$A:$J,4,0)&"" | D48: =VLOOKUP($A48,'PARASTATAL Questions'!$A:$J,5,0)&"" | E48: =VLOOKUP($A48,'PARASTATAL Questions'!$A:$J,7,0)&"" | F48: =VLOOKUP($A48,'PARASTATAL Questions'!$A:$J,6,0) | G48: =IF($F48=0,"NA",IF($A48=INDIRECT("'"&$A48&"'!$B$1"),IF(VLOOKUP(G$1,INDIRECT("'"&$A48&"'!$A$12:$Z$19"),MATCH("Points (Auto-generate)",INDIRECT("'"&$A48&"'!$A$12:$Z$12"),0),0)="","?",VLOOKUP(G$1,INDIRECT("'"&$A48&"'!$A$12:$Z$19"),MATCH("Points (Auto-generate)",INDIRECT("'"&$A48&"'!$A$12:$Z$12"),0),0)),"ER")) | H48: =IF($F48=0,"NA",IF($A48=INDIRECT("'"&$A48&"'!$B$1"),IF(VLOOKUP(H$1,INDIRECT("'"&$A48&"'!$A$12:$Z$19"),MATCH("Points (Auto-generate)",INDIRECT("'"&$A48&"'!$A$12:$Z$12"),0),0)="","?",VLOOKUP(H$1,INDIRECT("'"&$A48&"'!$A$12:$Z$19"),MATCH("Points (Auto-generate)",INDIRECT("'"&$A48&"'!$A$12:$Z$12"),0),0)),"ER")) | I48: =IF($F48=0,"NA",IF($A48=INDIRECT("'"&$A48&"'!$B$1"),IF(VLOOKUP(I$1,INDIRECT("'"&$A48&"'!$A$12:$Z$19"),MATCH("Points (Auto-generate)",INDIRECT("'"&$A48&"'!$A$12:$Z$12"),0),0)="","?",VLOOKUP(I$1,INDIRECT("'"&$A48&"'!$A$12:$Z$19"),MATCH("Points (Auto-generate)",INDIRECT("'"&$A48&"'!$A$12:$Z$12"),0),0)),"ER")) | J48: =IF($F48=0,"NA",IF($A48=INDIRECT("'"&$A48&"'!$B$1"),IF(VLOOKUP(J$1,INDIRECT("'"&$A48&"'!$A$12:$Z$19"),MATCH("Points (Auto-generate)",INDIRECT("'"&$A48&"'!$A$12:$Z$12"),0),0)="","?",VLOOKUP(J$1,INDIRECT("'"&$A48&"'!$A$12:$Z$19"),MATCH("Points (Auto-generate)",INDIRECT("'"&$A48&"'!$A$12:$Z$12"),0),0)),"ER")) | K48: =IF($F48=0,"NA",IF($A48=INDIRECT("'"&$A48&"'!$B$1"),IF(VLOOKUP(K$1,INDIRECT("'"&$A48&"'!$A$12:$Z$19"),MATCH("Points (Auto-generate)",INDIRECT("'"&$A48&"'!$A$12:$Z$12"),0),0)="","?",VLOOKUP(K$1,INDIRECT("'"&$A48&"'!$A$12:$Z$19"),MATCH("Points (Auto-generate)",INDIRECT("'"&$A48&"'!$A$12:$Z$12"),0),0)),"ER")) | L48: =IF($F48=0,"NA",IF($A48=INDIRECT("'"&$A48&"'!$B$1"),IF(VLOOKUP(L$1,INDIRECT("'"&$A48&"'!$A$12:$Z$19"),MATCH("Points (Auto-generate)",INDIRECT("'"&$A48&"'!$A$12:$Z$12"),0),0)="","?",VLOOKUP(L$1,INDIRECT("'"&$A48&"'!$A$12:$Z$19"),MATCH("Points (Auto-generate)",INDIRECT("'"&$A48&"'!$A$12:$Z$12"),0),0)),"ER")) | M48: =IF($F48=0,"NA",IF($A48=INDIRECT("'"&$A48&"'!$B$1"),IF(VLOOKUP(M$1,INDIRECT("'"&$A48&"'!$A$12:$Z$19"),MATCH("Points (Auto-generate)",INDIRECT("'"&$A48&"'!$A$12:$Z$12"),0),0)="","?",VLOOKUP(M$1,INDIRECT("'"&$A48&"'!$A$12:$Z$19"),MATCH("Points (Auto-generate)",INDIRECT("'"&$A48&"'!$A$12:$Z$12"),0),0)),"ER"))
A49: SC3 | B49: =VLOOKUP($A49,'PARASTATAL Questions'!$A:$J,3,0)&"" | C49: =VLOOKUP($A49,'PARASTATAL Questions'!$A:$J,4,0)&"" | D49: =VLOOKUP($A49,'PARASTATAL Questions'!$A:$J,5,0)&"" | E49: =VLOOKUP($A49,'PARASTATAL Questions'!$A:$J,7,0)&"" | F49: =VLOOKUP($A49,'PARASTATAL Questions'!$A:$J,6,0) | G49: =IF($F49=0,"NA",IF($A49=INDIRECT("'"&$A49&"'!$B$1"),IF(VLOOKUP(G$1,INDIRECT("'"&$A49&"'!$A$12:$Z$19"),MATCH("Points (Auto-generate)",INDIRECT("'"&$A49&"'!$A$12:$Z$12"),0),0)="","?",VLOOKUP(G$1,INDIRECT("'"&$A49&"'!$A$12:$Z$19"),MATCH("Points (Auto-generate)",INDIRECT("'"&$A49&"'!$A$12:$Z$12"),0),0)),"ER")) | H49: =IF($F49=0,"NA",IF($A49=INDIRECT("'"&$A49&"'!$B$1"),IF(VLOOKUP(H$1,INDIRECT("'"&$A49&"'!$A$12:$Z$19"),MATCH("Points (Auto-generate)",INDIRECT("'"&$A49&"'!$A$12:$Z$12"),0),0)="","?",VLOOKUP(H$1,INDIRECT("'"&$A49&"'!$A$12:$Z$19"),MATCH("Points (Auto-generate)",INDIRECT("'"&$A49&"'!$A$12:$Z$12"),0),0)),"ER")) | I49: =IF($F49=0,"NA",IF($A49=INDIRECT("'"&$A49&"'!$B$1"),IF(VLOOKUP(I$1,INDIRECT("'"&$A49&"'!$A$12:$Z$19"),MATCH("Points (Auto-generate)",INDIRECT("'"&$A49&"'!$A$12:$Z$12"),0),0)="","?",VLOOKUP(I$1,INDIRECT("'"&$A49&"'!$A$12:$Z$19"),MATCH("Points (Auto-generate)",INDIRECT("'"&$A49&"'!$A$12:$Z$12"),0),0)),"ER")) | J49: =IF($F49=0,"NA",IF($A49=INDIRECT("'"&$A49&"'!$B$1"),IF(VLOOKUP(J$1,INDIRECT("'"&$A49&"'!$A$12:$Z$19"),MATCH("Points (Auto-generate)",INDIRECT("'"&$A49&"'!$A$12:$Z$12"),0),0)="","?",VLOOKUP(J$1,INDIRECT("'"&$A49&"'!$A$12:$Z$19"),MATCH("Points (Auto-generate)",INDIRECT("'"&$A49&"'!$A$12:$Z$12"),0),0)),"ER")) | K49: =IF($F49=0,"NA",IF($A49=INDIRECT("'"&$A49&"'!$B$1"),IF(VLOOKUP(K$1,INDIRECT("'"&$A49&"'!$A$12:$Z$19"),MATCH("Points (Auto-generate)",INDIRECT("'"&$A49&"'!$A$12:$Z$12"),0),0)="","?",VLOOKUP(K$1,INDIRECT("'"&$A49&"'!$A$12:$Z$19"),MATCH("Points (Auto-generate)",INDIRECT("'"&$A49&"'!$A$12:$Z$12"),0),0)),"ER")) | L49: =IF($F49=0,"NA",IF($A49=INDIRECT("'"&$A49&"'!$B$1"),IF(VLOOKUP(L$1,INDIRECT("'"&$A49&"'!$A$12:$Z$19"),MATCH("Points (Auto-generate)",INDIRECT("'"&$A49&"'!$A$12:$Z$12"),0),0)="","?",VLOOKUP(L$1,INDIRECT("'"&$A49&"'!$A$12:$Z$19"),MATCH("Points (Auto-generate)",INDIRECT("'"&$A49&"'!$A$12:$Z$12"),0),0)),"ER")) | M49: =IF($F49=0,"NA",IF($A49=INDIRECT("'"&$A49&"'!$B$1"),IF(VLOOKUP(M$1,INDIRECT("'"&$A49&"'!$A$12:$Z$19"),MATCH("Points (Auto-generate)",INDIRECT("'"&$A49&"'!$A$12:$Z$12"),0),0)="","?",VLOOKUP(M$1,INDIRECT("'"&$A49&"'!$A$12:$Z$19"),MATCH("Points (Auto-generate)",INDIRECT("'"&$A49&"'!$A$12:$Z$12"),0),0)),"ER"))
A50: SC4 | B50: =VLOOKUP($A50,'PARASTATAL Questions'!$A:$J,3,0)&"" | C50: =VLOOKUP($A50,'PARASTATAL Questions'!$A:$J,4,0)&"" | D50: =VLOOKUP($A50,'PARASTATAL Questions'!$A:$J,5,0)&"" | E50: =VLOOKUP($A50,'PARASTATAL Questions'!$A:$J,7,0)&"" | F50: =VLOOKUP($A50,'PARASTATAL Questions'!$A:$J,6,0) | G50: =IF(OR(G51="ER",G52="ER"),"ER",IF(OR(G51="?",G52="?"),"?",IF(AND(G51="NA",G52="NA"),"NA",SUM(G51,G52)/((G51<>"NA")*$F$51+(G52<>"NA")*$F$52)*$F50))) | H50: =IF(OR(H51="ER",H52="ER"),"ER",IF(OR(H51="?",H52="?"),"?",IF(AND(H51="NA",H52="NA"),"NA",SUM(H51,H52)/((H51<>"NA")*$F$51+(H52<>"NA")*$F$52)*$F50))) | I50: =IF(OR(I51="ER",I52="ER"),"ER",IF(OR(I51="?",I52="?"),"?",IF(AND(I51="NA",I52="NA"),"NA",SUM(I51,I52)/((I51<>"NA")*$F$51+(I52<>"NA")*$F$52)*$F50))) | J50: =IF(OR(J51="ER",J52="ER"),"ER",IF(OR(J51="?",J52="?"),"?",IF(AND(J51="NA",J52="NA"),"NA",SUM(J51,J52)/((J51<>"NA")*$F$51+(J52<>"NA")*$F$52)*$F50))) | K50: =IF(OR(K51="ER",K52="ER"),"ER",IF(OR(K51="?",K52="?"),"?",IF(AND(K51="NA",K52="NA"),"NA",SUM(K51,K52)/((K51<>"NA")*$F$51+(K52<>"NA")*$F$52)*$F50))) | L50: =IF(OR(L51="ER",L52="ER"),"ER",IF(OR(L51="?",L52="?"),"?",IF(AND(L51="NA",L52="NA"),"NA",SUM(L51,L52)/((L51<>"NA")*$F$51+(L52<>"NA")*$F$52)*$F50))) | M50: =IF(OR(M51="ER",M52="ER"),"ER",IF(OR(M51="?",M52="?"),"?",IF(AND(M51="NA",M52="NA"),"NA",SUM(M51,M52)/((M51<>"NA")*$F$51+(M52<>"NA")*$F$52)*$F50)))
A51: SC4a | B51: =VLOOKUP($A51,'PARASTATAL Questions'!$A:$J,3,0)&"" | C51: =VLOOKUP($A51,'PARASTATAL Questions'!$A:$J,4,0)&"" | D51: =VLOOKUP($A51,'PARASTATAL Questions'!$A:$J,5,0)&"" | E51: =VLOOKUP($A51,'PARASTATAL Questions'!$A:$J,7,0)&"" | F51: =VLOOKUP($A51,'PARASTATAL Questions'!$A:$J,6,0) | G51: =IF($F51=0,"NA",IF($A51=INDIRECT("'"&$A51&"'!$B$1"),IF(VLOOKUP(G$1,INDIRECT("'"&$A51&"'!$A$12:$Z$19"),MATCH("Points (Auto-generate)",INDIRECT("'"&$A51&"'!$A$12:$Z$12"),0),0)="","?",VLOOKUP(G$1,INDIRECT("'"&$A51&"'!$A$12:$Z$19"),MATCH("Points (Auto-generate)",INDIRECT("'"&$A51&"'!$A$12:$Z$12"),0),0)),"ER")) | H51: =IF($F51=0,"NA",IF($A51=INDIRECT("'"&$A51&"'!$B$1"),IF(VLOOKUP(H$1,INDIRECT("'"&$A51&"'!$A$12:$Z$19"),MATCH("Points (Auto-generate)",INDIRECT("'"&$A51&"'!$A$12:$Z$12"),0),0)="","?",VLOOKUP(H$1,INDIRECT("'"&$A51&"'!$A$12:$Z$19"),MATCH("Points (Auto-generate)",INDIRECT("'"&$A51&"'!$A$12:$Z$12"),0),0)),"ER")) | I51: =IF($F51=0,"NA",IF($A51=INDIRECT("'"&$A51&"'!$B$1"),IF(VLOOKUP(I$1,INDIRECT("'"&$A51&"'!$A$12:$Z$19"),MATCH("Points (Auto-generate)",INDIRECT("'"&$A51&"'!$A$12:$Z$12"),0),0)="","?",VLOOKUP(I$1,INDIRECT("'"&$A51&"'!$A$12:$Z$19"),MATCH("Points (Auto-generate)",INDIRECT("'"&$A51&"'!$A$12:$Z$12"),0),0)),"ER")) | J51: =IF($F51=0,"NA",IF($A51=INDIRECT("'"&$A51&"'!$B$1"),IF(VLOOKUP(J$1,INDIRECT("'"&$A51&"'!$A$12:$Z$19"),MATCH("Points (Auto-generate)",INDIRECT("'"&$A51&"'!$A$12:$Z$12"),0),0)="","?",VLOOKUP(J$1,INDIRECT("'"&$A51&"'!$A$12:$Z$19"),MATCH("Points (Auto-generate)",INDIRECT("'"&$A51&"'!$A$12:$Z$12"),0),0)),"ER")) | K51: =IF($F51=0,"NA",IF($A51=INDIRECT("'"&$A51&"'!$B$1"),IF(VLOOKUP(K$1,INDIRECT("'"&$A51&"'!$A$12:$Z$19"),MATCH("Points (Auto-generate)",INDIRECT("'"&$A51&"'!$A$12:$Z$12"),0),0)="","?",VLOOKUP(K$1,INDIRECT("'"&$A51&"'!$A$12:$Z$19"),MATCH("Points (Auto-generate)",INDIRECT("'"&$A51&"'!$A$12:$Z$12"),0),0)),"ER")) | L51: =IF($F51=0,"NA",IF($A51=INDIRECT("'"&$A51&"'!$B$1"),IF(VLOOKUP(L$1,INDIRECT("'"&$A51&"'!$A$12:$Z$19"),MATCH("Points (Auto-generate)",INDIRECT("'"&$A51&"'!$A$12:$Z$12"),0),0)="","?",VLOOKUP(L$1,INDIRECT("'"&$A51&"'!$A$12:$Z$19"),MATCH("Points (Auto-generate)",INDIRECT("'"&$A51&"'!$A$12:$Z$12"),0),0)),"ER")) | M51: =IF($F51=0,"NA",IF($A51=INDIRECT("'"&$A51&"'!$B$1"),IF(VLOOKUP(M$1,INDIRECT("'"&$A51&"'!$A$12:$Z$19"),MATCH("Points (Auto-generate)",INDIRECT("'"&$A51&"'!$A$12:$Z$12"),0),0)="","?",VLOOKUP(M$1,INDIRECT("'"&$A51&"'!$A$12:$Z$19"),MATCH("Points (Auto-generate)",INDIRECT("'"&$A51&"'!$A$12:$Z$12"),0),0)),"ER"))
A52: SC4b | B52: =VLOOKUP($A52,'PARASTATAL Questions'!$A:$J,3,0)&"" | C52: =VLOOKUP($A52,'PARASTATAL Questions'!$A:$J,4,0)&"" | D52: =VLOOKUP($A52,'PARASTATAL Questions'!$A:$J,5,0)&"" | E52: =VLOOKUP($A52,'PARASTATAL Questions'!$A:$J,7,0)&"" | F52: =VLOOKUP($A52,'PARASTATAL Questions'!$A:$J,6,0) | G52: =IF($F52=0,"NA",IF($A52=INDIRECT("'"&$A52&"'!$B$1"),IF(VLOOKUP(G$1,INDIRECT("'"&$A52&"'!$A$12:$Z$19"),MATCH("Points (Auto-generate)",INDIRECT("'"&$A52&"'!$A$12:$Z$12"),0),0)="","?",VLOOKUP(G$1,INDIRECT("'"&$A52&"'!$A$12:$Z$19"),MATCH("Points (Auto-generate)",INDIRECT("'"&$A52&"'!$A$12:$Z$12"),0),0)),"ER")) | H52: =IF($F52=0,"NA",IF($A52=INDIRECT("'"&$A52&"'!$B$1"),IF(VLOOKUP(H$1,INDIRECT("'"&$A52&"'!$A$12:$Z$19"),MATCH("Points (Auto-generate)",INDIRECT("'"&$A52&"'!$A$12:$Z$12"),0),0)="","?",VLOOKUP(H$1,INDIRECT("'"&$A52&"'!$A$12:$Z$19"),MATCH("Points (Auto-generate)",INDIRECT("'"&$A52&"'!$A$12:$Z$12"),0),0)),"ER")) | I52: =IF($F52=0,"NA",IF($A52=INDIRECT("'"&$A52&"'!$B$1"),IF(VLOOKUP(I$1,INDIRECT("'"&$A52&"'!$A$12:$Z$19"),MATCH("Points (Auto-generate)",INDIRECT("'"&$A52&"'!$A$12:$Z$12"),0),0)="","?",VLOOKUP(I$1,INDIRECT("'"&$A52&"'!$A$12:$Z$19"),MATCH("Points (Auto-generate)",INDIRECT("'"&$A52&"'!$A$12:$Z$12"),0),0)),"ER")) | J52: =IF($F52=0,"NA",IF($A52=INDIRECT("'"&$A52&"'!$B$1"),IF(VLOOKUP(J$1,INDIRECT("'"&$A52&"'!$A$12:$Z$19"),MATCH("Points (Auto-generate)",INDIRECT("'"&$A52&"'!$A$12:$Z$12"),0),0)="","?",VLOOKUP(J$1,INDIRECT("'"&$A52&"'!$A$12:$Z$19"),MATCH("Points (Auto-generate)",INDIRECT("'"&$A52&"'!$A$12:$Z$12"),0),0)),"ER")) | K52: =IF($F52=0,"NA",IF($A52=INDIRECT("'"&$A52&"'!$B$1"),IF(VLOOKUP(K$1,INDIRECT("'"&$A52&"'!$A$12:$Z$19"),MATCH("Points (Auto-generate)",INDIRECT("'"&$A52&"'!$A$12:$Z$12"),0),0)="","?",VLOOKUP(K$1,INDIRECT("'"&$A52&"'!$A$12:$Z$19"),MATCH("Points (Auto-generate)",INDIRECT("'"&$A52&"'!$A$12:$Z$12"),0),0)),"ER")) | L52: =IF($F52=0,"NA",IF($A52=INDIRECT("'"&$A52&"'!$B$1"),IF(VLOOKUP(L$1,INDIRECT("'"&$A52&"'!$A$12:$Z$19"),MATCH("Points (Auto-generate)",INDIRECT("'"&$A52&"'!$A$12:$Z$12"),0),0)="","?",VLOOKUP(L$1,INDIRECT("'"&$A52&"'!$A$12:$Z$19"),MATCH("Points (Auto-generate)",INDIRECT("'"&$A52&"'!$A$12:$Z$12"),0),0)),"ER")) | M52: =IF($F52=0,"NA",IF($A52=INDIRECT("'"&$A52&"'!$B$1"),IF(VLOOKUP(M$1,INDIRECT("'"&$A52&"'!$A$12:$Z$19"),MATCH("Points (Auto-generate)",INDIRECT("'"&$A52&"'!$A$12:$Z$12"),0),0)="","?",VLOOKUP(M$1,INDIRECT("'"&$A52&"'!$A$12:$Z$19"),MATCH("Points (Auto-generate)",INDIRECT("'"&$A52&"'!$A$12:$Z$12"),0),0)),"ER"))
A53: SC5 | B53: =VLOOKUP($A53,'PARASTATAL Questions'!$A:$J,3,0)&"" | C53: =VLOOKUP($A53,'PARASTATAL Questions'!$A:$J,4,0)&"" | D53: =VLOOKUP($A53,'PARASTATAL Questions'!$A:$J,5,0)&"" | E53: =VLOOKUP($A53,'PARASTATAL Questions'!$A:$J,7,0)&"" | F53: =VLOOKUP($A53,'PARASTATAL Questions'!$A:$J,6,0) | G53: =IF($F53=0,"NA",IF($A53=INDIRECT("'"&$A53&"'!$B$1"),IF(VLOOKUP(G$1,INDIRECT("'"&$A53&"'!$A$12:$Z$19"),MATCH("Points (Auto-generate)",INDIRECT("'"&$A53&"'!$A$12:$Z$12"),0),0)="","?",VLOOKUP(G$1,INDIRECT("'"&$A53&"'!$A$12:$Z$19"),MATCH("Points (Auto-generate)",INDIRECT("'"&$A53&"'!$A$12:$Z$12"),0),0)),"ER")) | H53: =IF($F53=0,"NA",IF($A53=INDIRECT("'"&$A53&"'!$B$1"),IF(VLOOKUP(H$1,INDIRECT("'"&$A53&"'!$A$12:$Z$19"),MATCH("Points (Auto-generate)",INDIRECT("'"&$A53&"'!$A$12:$Z$12"),0),0)="","?",VLOOKUP(H$1,INDIRECT("'"&$A53&"'!$A$12:$Z$19"),MATCH("Points (Auto-generate)",INDIRECT("'"&$A53&"'!$A$12:$Z$12"),0),0)),"ER")) | I53: =IF($F53=0,"NA",IF($A53=INDIRECT("'"&$A53&"'!$B$1"),IF(VLOOKUP(I$1,INDIRECT("'"&$A53&"'!$A$12:$Z$19"),MATCH("Points (Auto-generate)",INDIRECT("'"&$A53&"'!$A$12:$Z$12"),0),0)="","?",VLOOKUP(I$1,INDIRECT("'"&$A53&"'!$A$12:$Z$19"),MATCH("Points (Auto-generate)",INDIRECT("'"&$A53&"'!$A$12:$Z$12"),0),0)),"ER")) | J53: =IF($F53=0,"NA",IF($A53=INDIRECT("'"&$A53&"'!$B$1"),IF(VLOOKUP(J$1,INDIRECT("'"&$A53&"'!$A$12:$Z$19"),MATCH("Points (Auto-generate)",INDIRECT("'"&$A53&"'!$A$12:$Z$12"),0),0)="","?",VLOOKUP(J$1,INDIRECT("'"&$A53&"'!$A$12:$Z$19"),MATCH("Points (Auto-generate)",INDIRECT("'"&$A53&"'!$A$12:$Z$12"),0),0)),"ER")) | K53: =IF($F53=0,"NA",IF($A53=INDIRECT("'"&$A53&"'!$B$1"),IF(VLOOKUP(K$1,INDIRECT("'"&$A53&"'!$A$12:$Z$19"),MATCH("Points (Auto-generate)",INDIRECT("'"&$A53&"'!$A$12:$Z$12"),0),0)="","?",VLOOKUP(K$1,INDIRECT("'"&$A53&"'!$A$12:$Z$19"),MATCH("Points (Auto-generate)",INDIRECT("'"&$A53&"'!$A$12:$Z$12"),0),0)),"ER")) | L53: =IF($F53=0,"NA",IF($A53=INDIRECT("'"&$A53&"'!$B$1"),IF(VLOOKUP(L$1,INDIRECT("'"&$A53&"'!$A$12:$Z$19"),MATCH("Points (Auto-generate)",INDIRECT("'"&$A53&"'!$A$12:$Z$12"),0),0)="","?",VLOOKUP(L$1,INDIRECT("'"&$A53&"'!$A$12:$Z$19"),MATCH("Points (Auto-generate)",INDIRECT("'"&$A53&"'!$A$12:$Z$12"),0),0)),"ER")) | M53: =IF($F53=0,"NA",IF($A53=INDIRECT("'"&$A53&"'!$B$1"),IF(VLOOKUP(M$1,INDIRECT("'"&$A53&"'!$A$12:$Z$19"),MATCH("Points (Auto-generate)",INDIRECT("'"&$A53&"'!$A$12:$Z$12"),0),0)="","?",VLOOKUP(M$1,INDIRECT("'"&$A53&"'!$A$12:$Z$19"),MATCH("Points (Auto-generate)",INDIRECT("'"&$A53&"'!$A$12:$Z$12"),0),0)),"ER"))
A54: SC6 | B54: =VLOOKUP($A54,'PARASTATAL Questions'!$A:$J,3,0)&"" | C54: =VLOOKUP($A54,'PARASTATAL Questions'!$A:$J,4,0)&"" | D54: =VLOOKUP($A54,'PARASTATAL Questions'!$A:$J,5,0)&"" | E54: =VLOOKUP($A54,'PARASTATAL Questions'!$A:$J,7,0)&"" | F54: =VLOOKUP($A54,'PARASTATAL Questions'!$A:$J,6,0) | G54: =IF($F54=0,"NA",IF($A54=INDIRECT("'"&$A54&"'!$B$1"),IF(VLOOKUP(G$1,INDIRECT("'"&$A54&"'!$A$12:$Z$19"),MATCH("Points (Auto-generate)",INDIRECT("'"&$A54&"'!$A$12:$Z$12"),0),0)="","?",VLOOKUP(G$1,INDIRECT("'"&$A54&"'!$A$12:$Z$19"),MATCH("Points (Auto-generate)",INDIRECT("'"&$A54&"'!$A$12:$Z$12"),0),0)),"ER")) | H54: =IF($F54=0,"NA",IF($A54=INDIRECT("'"&$A54&"'!$B$1"),IF(VLOOKUP(H$1,INDIRECT("'"&$A54&"'!$A$12:$Z$19"),MATCH("Points (Auto-generate)",INDIRECT("'"&$A54&"'!$A$12:$Z$12"),0),0)="","?",VLOOKUP(H$1,INDIRECT("'"&$A54&"'!$A$12:$Z$19"),MATCH("Points (Auto-generate)",INDIRECT("'"&$A54&"'!$A$12:$Z$12"),0),0)),"ER")) | I54: =IF($F54=0,"NA",IF($A54=INDIRECT("'"&$A54&"'!$B$1"),IF(VLOOKUP(I$1,INDIRECT("'"&$A54&"'!$A$12:$Z$19"),MATCH("Points (Auto-generate)",INDIRECT("'"&$A54&"'!$A$12:$Z$12"),0),0)="","?",VLOOKUP(I$1,INDIRECT("'"&$A54&"'!$A$12:$Z$19"),MATCH("Points (Auto-generate)",INDIRECT("'"&$A54&"'!$A$12:$Z$12"),0),0)),"ER")) | J54: =IF($F54=0,"NA",IF($A54=INDIRECT("'"&$A54&"'!$B$1"),IF(VLOOKUP(J$1,INDIRECT("'"&$A54&"'!$A$12:$Z$19"),MATCH("Points (Auto-generate)",INDIRECT("'"&$A54&"'!$A$12:$Z$12"),0),0)="","?",VLOOKUP(J$1,INDIRECT("'"&$A54&"'!$A$12:$Z$19"),MATCH("Points (Auto-generate)",INDIRECT("'"&$A54&"'!$A$12:$Z$12"),0),0)),"ER")) | K54: =IF($F54=0,"NA",IF($A54=INDIRECT("'"&$A54&"'!$B$1"),IF(VLOOKUP(K$1,INDIRECT("'"&$A54&"'!$A$12:$Z$19"),MATCH("Points (Auto-generate)",INDIRECT("'"&$A54&"'!$A$12:$Z$12"),0),0)="","?",VLOOKUP(K$1,INDIRECT("'"&$A54&"'!$A$12:$Z$19"),MATCH("Points (Auto-generate)",INDIRECT("'"&$A54&"'!$A$12:$Z$12"),0),0)),"ER")) | L54: =IF($F54=0,"NA",IF($A54=INDIRECT("'"&$A54&"'!$B$1"),IF(VLOOKUP(L$1,INDIRECT("'"&$A54&"'!$A$12:$Z$19"),MATCH("Points (Auto-generate)",INDIRECT("'"&$A54&"'!$A$12:$Z$12"),0),0)="","?",VLOOKUP(L$1,INDIRECT("'"&$A54&"'!$A$12:$Z$19"),MATCH("Points (Auto-generate)",INDIRECT("'"&$A54&"'!$A$12:$Z$12"),0),0)),"ER")) | M54: =IF($F54=0,"NA",IF($A54=INDIRECT("'"&$A54&"'!$B$1"),IF(VLOOKUP(M$1,INDIRECT("'"&$A54&"'!$A$12:$Z$19"),MATCH("Points (Auto-generate)",INDIRECT("'"&$A54&"'!$A$12:$Z$12"),0),0)="","?",VLOOKUP(M$1,INDIRECT("'"&$A54&"'!$A$12:$Z$19"),MATCH("Points (Auto-generate)",INDIRECT("'"&$A54&"'!$A$12:$Z$12"),0),0)),"ER"))
A55: SC7 | B55: =VLOOKUP($A55,'PARASTATAL Questions'!$A:$J,3,0)&"" | C55: =VLOOKUP($A55,'PARASTATAL Questions'!$A:$J,4,0)&"" | D55: =VLOOKUP($A55,'PARASTATAL Questions'!$A:$J,5,0)&"" | E55: =VLOOKUP($A55,'PARASTATAL Questions'!$A:$J,7,0)&"" | F55: =VLOOKUP($A55,'PARASTATAL Questions'!$A:$J,6,0) | G55: =IF(OR(G56="ER",G57="ER"),"ER",IF(OR(G56="?",G57="?"),"?",IF(AND(G56="NA",G57="NA"),"NA",SUM(G56,G57)/((G56<>"NA")*$F$56+(G57<>"NA")*$F$57)*$F55))) | H55: =IF(OR(H56="ER",H57="ER"),"ER",IF(OR(H56="?",H57="?"),"?",IF(AND(H56="NA",H57="NA"),"NA",SUM(H56,H57)/((H56<>"NA")*$F$56+(H57<>"NA")*$F$57)*$F55))) | I55: =IF(OR(I56="ER",I57="ER"),"ER",IF(OR(I56="?",I57="?"),"?",IF(AND(I56="NA",I57="NA"),"NA",SUM(I56,I57)/((I56<>"NA")*$F$56+(I57<>"NA")*$F$57)*$F55))) | J55: =IF(OR(J56="ER",J57="ER"),"ER",IF(OR(J56="?",J57="?"),"?",IF(AND(J56="NA",J57="NA"),"NA",SUM(J56,J57)/((J56<>"NA")*$F$56+(J57<>"NA")*$F$57)*$F55))) | K55: =IF(OR(K56="ER",K57="ER"),"ER",IF(OR(K56="?",K57="?"),"?",IF(AND(K56="NA",K57="NA"),"NA",SUM(K56,K57)/((K56<>"NA")*$F$56+(K57<>"NA")*$F$57)*$F55))) | L55: =IF(OR(L56="ER",L57="ER"),"ER",IF(OR(L56="?",L57="?"),"?",IF(AND(L56="NA",L57="NA"),"NA",SUM(L56,L57)/((L56<>"NA")*$F$56+(L57<>"NA")*$F$57)*$F55))) | M55: =IF(OR(M56="ER",M57="ER"),"ER",IF(OR(M56="?",M57="?"),"?",IF(AND(M56="NA",M57="NA"),"NA",SUM(M56,M57)/((M56<>"NA")*$F$56+(M57<>"NA")*$F$57)*$F55)))
A56: SC7a | B56: =VLOOKUP($A56,'PARASTATAL Questions'!$A:$J,3,0)&"" | C56: =VLOOKUP($A56,'PARASTATAL Questions'!$A:$J,4,0)&"" | D56: =VLOOKUP($A56,'PARASTATAL Questions'!$A:$J,5,0)&"" | E56: =VLOOKUP($A56,'PARASTATAL Questions'!$A:$J,7,0)&"" | F56: =VLOOKUP($A56,'PARASTATAL Questions'!$A:$J,6,0) | G56: =IF($F56=0,"NA",IF($A56=INDIRECT("'"&$A56&"'!$B$1"),IF(VLOOKUP(G$1,INDIRECT("'"&$A56&"'!$A$12:$Z$19"),MATCH("Points (Auto-generate)",INDIRECT("'"&$A56&"'!$A$12:$Z$12"),0),0)="","?",VLOOKUP(G$1,INDIRECT("'"&$A56&"'!$A$12:$Z$19"),MATCH("Points (Auto-generate)",INDIRECT("'"&$A56&"'!$A$12:$Z$12"),0),0)),"ER")) | H56: =IF($F56=0,"NA",IF($A56=INDIRECT("'"&$A56&"'!$B$1"),IF(VLOOKUP(H$1,INDIRECT("'"&$A56&"'!$A$12:$Z$19"),MATCH("Points (Auto-generate)",INDIRECT("'"&$A56&"'!$A$12:$Z$12"),0),0)="","?",VLOOKUP(H$1,INDIRECT("'"&$A56&"'!$A$12:$Z$19"),MATCH("Points (Auto-generate)",INDIRECT("'"&$A56&"'!$A$12:$Z$12"),0),0)),"ER")) | I56: =IF($F56=0,"NA",IF($A56=INDIRECT("'"&$A56&"'!$B$1"),IF(VLOOKUP(I$1,INDIRECT("'"&$A56&"'!$A$12:$Z$19"),MATCH("Points (Auto-generate)",INDIRECT("'"&$A56&"'!$A$12:$Z$12"),0),0)="","?",VLOOKUP(I$1,INDIRECT("'"&$A56&"'!$A$12:$Z$19"),MATCH("Points (Auto-generate)",INDIRECT("'"&$A56&"'!$A$12:$Z$12"),0),0)),"ER")) | J56: =IF($F56=0,"NA",IF($A56=INDIRECT("'"&$A56&"'!$B$1"),IF(VLOOKUP(J$1,INDIRECT("'"&$A56&"'!$A$12:$Z$19"),MATCH("Points (Auto-generate)",INDIRECT("'"&$A56&"'!$A$12:$Z$12"),0),0)="","?",VLOOKUP(J$1,INDIRECT("'"&$A56&"'!$A$12:$Z$19"),MATCH("Points (Auto-generate)",INDIRECT("'"&$A56&"'!$A$12:$Z$12"),0),0)),"ER")) | K56: =IF($F56=0,"NA",IF($A56=INDIRECT("'"&$A56&"'!$B$1"),IF(VLOOKUP(K$1,INDIRECT("'"&$A56&"'!$A$12:$Z$19"),MATCH("Points (Auto-generate)",INDIRECT("'"&$A56&"'!$A$12:$Z$12"),0),0)="","?",VLOOKUP(K$1,INDIRECT("'"&$A56&"'!$A$12:$Z$19"),MATCH("Points (Auto-generate)",INDIRECT("'"&$A56&"'!$A$12:$Z$12"),0),0)),"ER")) | L56: =IF($F56=0,"NA",IF($A56=INDIRECT("'"&$A56&"'!$B$1"),IF(VLOOKUP(L$1,INDIRECT("'"&$A56&"'!$A$12:$Z$19"),MATCH("Points (Auto-generate)",INDIRECT("'"&$A56&"'!$A$12:$Z$12"),0),0)="","?",VLOOKUP(L$1,INDIRECT("'"&$A56&"'!$A$12:$Z$19"),MATCH("Points (Auto-generate)",INDIRECT("'"&$A56&"'!$A$12:$Z$12"),0),0)),"ER")) | M56: =IF($F56=0,"NA",IF($A56=INDIRECT("'"&$A56&"'!$B$1"),IF(VLOOKUP(M$1,INDIRECT("'"&$A56&"'!$A$12:$Z$19"),MATCH("Points (Auto-generate)",INDIRECT("'"&$A56&"'!$A$12:$Z$12"),0),0)="","?",VLOOKUP(M$1,INDIRECT("'"&$A56&"'!$A$12:$Z$19"),MATCH("Points (Auto-generate)",INDIRECT("'"&$A56&"'!$A$12:$Z$12"),0),0)),"ER"))
A57: SC7b | B57: =VLOOKUP($A57,'PARASTATAL Questions'!$A:$J,3,0)&"" | C57: =VLOOKUP($A57,'PARASTATAL Questions'!$A:$J,4,0)&"" | D57: =VLOOKUP($A57,'PARASTATAL Questions'!$A:$J,5,0)&"" | E57: =VLOOKUP($A57,'PARASTATAL Questions'!$A:$J,7,0)&"" | F57: =VLOOKUP($A57,'PARASTATAL Questions'!$A:$J,6,0) | G57: =IF($F57=0,"NA",IF($A57=INDIRECT("'"&$A57&"'!$B$1"),IF(VLOOKUP(G$1,INDIRECT("'"&$A57&"'!$A$12:$Z$19"),MATCH("Points (Auto-generate)",INDIRECT("'"&$A57&"'!$A$12:$Z$12"),0),0)="","?",VLOOKUP(G$1,INDIRECT("'"&$A57&"'!$A$12:$Z$19"),MATCH("Points (Auto-generate)",INDIRECT("'"&$A57&"'!$A$12:$Z$12"),0),0)),"ER")) | H57: =IF($F57=0,"NA",IF($A57=INDIRECT("'"&$A57&"'!$B$1"),IF(VLOOKUP(H$1,INDIRECT("'"&$A57&"'!$A$12:$Z$19"),MATCH("Points (Auto-generate)",INDIRECT("'"&$A57&"'!$A$12:$Z$12"),0),0)="","?",VLOOKUP(H$1,INDIRECT("'"&$A57&"'!$A$12:$Z$19"),MATCH("Points (Auto-generate)",INDIRECT("'"&$A57&"'!$A$12:$Z$12"),0),0)),"ER")) | I57: =IF($F57=0,"NA",IF($A57=INDIRECT("'"&$A57&"'!$B$1"),IF(VLOOKUP(I$1,INDIRECT("'"&$A57&"'!$A$12:$Z$19"),MATCH("Points (Auto-generate)",INDIRECT("'"&$A57&"'!$A$12:$Z$12"),0),0)="","?",VLOOKUP(I$1,INDIRECT("'"&$A57&"'!$A$12:$Z$19"),MATCH("Points (Auto-generate)",INDIRECT("'"&$A57&"'!$A$12:$Z$12"),0),0)),"ER")) | J57: =IF($F57=0,"NA",IF($A57=INDIRECT("'"&$A57&"'!$B$1"),IF(VLOOKUP(J$1,INDIRECT("'"&$A57&"'!$A$12:$Z$19"),MATCH("Points (Auto-generate)",INDIRECT("'"&$A57&"'!$A$12:$Z$12"),0),0)="","?",VLOOKUP(J$1,INDIRECT("'"&$A57&"'!$A$12:$Z$19"),MATCH("Points (Auto-generate)",INDIRECT("'"&$A57&"'!$A$12:$Z$12"),0),0)),"ER")) | K57: =IF($F57=0,"NA",IF($A57=INDIRECT("'"&$A57&"'!$B$1"),IF(VLOOKUP(K$1,INDIRECT("'"&$A57&"'!$A$12:$Z$19"),MATCH("Points (Auto-generate)",INDIRECT("'"&$A57&"'!$A$12:$Z$12"),0),0)="","?",VLOOKUP(K$1,INDIRECT("'"&$A57&"'!$A$12:$Z$19"),MATCH("Points (Auto-generate)",INDIRECT("'"&$A57&"'!$A$12:$Z$12"),0),0)),"ER")) | L57: =IF($F57=0,"NA",IF($A57=INDIRECT("'"&$A57&"'!$B$1"),IF(VLOOKUP(L$1,INDIRECT("'"&$A57&"'!$A$12:$Z$19"),MATCH("Points (Auto-generate)",INDIRECT("'"&$A57&"'!$A$12:$Z$12"),0),0)="","?",VLOOKUP(L$1,INDIRECT("'"&$A57&"'!$A$12:$Z$19"),MATCH("Points (Auto-generate)",INDIRECT("'"&$A57&"'!$A$12:$Z$12"),0),0)),"ER")) | M57: =IF($F57=0,"NA",IF($A57=INDIRECT("'"&$A57&"'!$B$1"),IF(VLOOKUP(M$1,INDIRECT("'"&$A57&"'!$A$12:$Z$19"),MATCH("Points (Auto-generate)",INDIRECT("'"&$A57&"'!$A$12:$Z$12"),0),0)="","?",VLOOKUP(M$1,INDIRECT("'"&$A57&"'!$A$12:$Z$19"),MATCH("Points (Auto-generate)",INDIRECT("'"&$A57&"'!$A$12:$Z$12"),0),0)),"ER"))
D59: PARASTATAL_Scores | G59: Bengaluru – BWSSB | H59: Bengaluru – BMTC | I59: Bengaluru – BDA | J59: Bengaluru – BMRCL | K59: Bengaluru – BMRDA | L59: Surat – SUDA | M59: Surat – GMRC
D60: PARASTATAL_OVERALL_SCORE | G60: =IFERROR(SUMIFS(G$3:G$57,$C$3:$C$57,"MQ")/(COUNTIFS($C$3:$C$57,"MQ")-COUNTIFS($C$3:$C$57,"MQ",G$3:G$57,"NA")),"NA") | H60: =IFERROR(SUMIFS(H$3:H$57,$C$3:$C$57,"MQ")/(COUNTIFS($C$3:$C$57,"MQ")-COUNTIFS($C$3:$C$57,"MQ",H$3:H$57,"NA")),"NA") | I60: =IFERROR(SUMIFS(I$3:I$57,$C$3:$C$57,"MQ")/(COUNTIFS($C$3:$C$57,"MQ")-COUNTIFS($C$3:$C$57,"MQ",I$3:I$57,"NA")),"NA") | J60: =IFERROR(SUMIFS(J$3:J$57,$C$3:$C$57,"MQ")/(COUNTIFS($C$3:$C$57,"MQ")-COUNTIFS($C$3:$C$57,"MQ",J$3:J$57,"NA")),"NA") | K60: =IFERROR(SUMIFS(K$3:K$57,$C$3:$C$57,"MQ")/(COUNTIFS($C$3:$C$57,"MQ")-COUNTIFS($C$3:$C$57,"MQ",K$3:K$57,"NA")),"NA") | L60: =IFERROR(SUMIFS(L$3:L$57,$C$3:$C$57,"MQ")/(COUNTIFS($C$3:$C$57,"MQ")-COUNTIFS($C$3:$C$57,"MQ",L$3:L$57,"NA")),"NA") | M60: =IFERROR(SUMIFS(M$3:M$57,$C$3:$C$57,"MQ")/(COUNTIFS($C$3:$C$57,"MQ")-COUNTIFS($C$3:$C$57,"MQ",M$3:M$57,"NA")),"NA")
D61: No. of MQs not yet scored ("?") - overall score is provisional while > 0 | G61: =COUNTIFS($C$3:$C$57,"MQ",G$3:G$57,"?") | H61: =COUNTIFS($C$3:$C$57,"MQ",H$3:H$57,"?") | I61: =COUNTIFS($C$3:$C$57,"MQ",I$3:I$57,"?") | J61: =COUNTIFS($C$3:$C$57,"MQ",J$3:J$57,"?") | K61: =COUNTIFS($C$3:$C$57,"MQ",K$3:K$57,"?") | L61: =COUNTIFS($C$3:$C$57,"MQ",L$3:L$57,"?") | M61: =COUNTIFS($C$3:$C$57,"MQ",M$3:M$57,"?")
D62: No. of MQs marked NA (excluded from overall score) | G62: =COUNTIFS($C$3:$C$57,"MQ",G$3:G$57,"NA") | H62: =COUNTIFS($C$3:$C$57,"MQ",H$3:H$57,"NA") | I62: =COUNTIFS($C$3:$C$57,"MQ",I$3:I$57,"NA") | J62: =COUNTIFS($C$3:$C$57,"MQ",J$3:J$57,"NA") | K62: =COUNTIFS($C$3:$C$57,"MQ",K$3:K$57,"NA") | L62: =COUNTIFS($C$3:$C$57,"MQ",L$3:L$57,"NA") | M62: =COUNTIFS($C$3:$C$57,"MQ",M$3:M$57,"NA")

Sheet PARASTATAL_CITY_SCORES
A1: City | B1: Agencies | C1: PARASTATAL score | D1: Agencies with a score
A2: Bengaluru | B2: BWSSB, BMTC, BDA, BMRCL, BMRDA | C2: =IFERROR(AVERAGEIFS('PARASTATAL_SUMMARY_RAW'!$G$60:$M$60,'PARASTATAL_SUMMARY_RAW'!$G$59:$M$59,$A2&" – *"),"NA") | D2: =COUNTIFS('PARASTATAL_SUMMARY_RAW'!$G$59:$M$59,$A2&" – *",'PARASTATAL_SUMMARY_RAW'!$G$60:$M$60,">=0")
A3: Surat | B3: SUDA, GMRC | C3: =IFERROR(AVERAGEIFS('PARASTATAL_SUMMARY_RAW'!$G$60:$M$60,'PARASTATAL_SUMMARY_RAW'!$G$59:$M$59,$A3&" – *"),"NA") | D3: =COUNTIFS('PARASTATAL_SUMMARY_RAW'!$G$59:$M$59,$A3&" – *",'PARASTATAL_SUMMARY_RAW'!$G$60:$M$60,">=0")
A5: A city's score is the average of its agencies' overall scores. Agencies with no applicable questions (NA) are left out.

Sheet PARASTATAL Questions
A1: Q No | B1: Original ID | C1: Group | D1: MQ_SQ | E1: Question | F1: Max Score | G1: Assessment level | H1: Applicability | I1: Detailed Methodology | J1: Notes for scorers
A2: UPD1 | B2: UPD 1 | C2: Urban Planning & Design (UPD) | D2: MQ | E2: Does the parastatal coordinate with the ULG(s) in preparing its spatial and/or sectoral plans? | F2: 10 | H2: Common — all parastatal types. | I2: Sum total of the sub-indicators below - | J2: See sub-indicators
A3: UPD1a | B3: UPD 1a | C3: Urban Planning & Design (UPD) | D3: SQ | E3: Is the parastatal mandated to prepare its spatial and/or sectoral plans in coordination with the ULG(s) within its jurisdiction? | F3: 5 | G3: Law/Policy | H3: Common — all parastatal types. | I3: Review the relevant Parastatal Act and the State Town and Country Planning (T&CP) Act. 10 — ULG approval/concurrence or joint preparation is required. 7.5 — formal consultation is mandatory, and ULG response must be considered/responded to. 5 — consultation is mandatory, but there is no obligation to incorporate/respond. 2.5 — consultation is discretionary (“may”). 0 — no formal role. | J3: Relevant Parastatal Act; applicable Town and Country Planning (T&CP) Act.
A4: UPD1b | B4: UPD 1b | C4: Urban Planning & Design (UPD) | D4: SQ | E4: Has the ULG participated in the parastatal’s plan-making process? | F4: 5 | G4: Implementation | H4: Common — all parastatal types. | I4: Review the latest available plan-making cycle for evidence of ULG participation in the parastatal’s plan-making process, irrespective of whether such participation is legally mandated. Score 10 where there is evidence of substantive ULG participation, such as joint preparation, concurrence/approval, or documented consideration of and response to ULG inputs. Score 5 where the ULG was formally consulted or invited to provide inputs, but there is no evidence of how these inputs were considered. Score 2.5 where there is evidence of limited or informal engagement with the ULG. Score 0 where there is no evidence of ULG participation. Evidence may include plan documents, consultation records, meeting minutes, ULG resolutions/comments, responses to ULG inputs, or information published on the parastatal/ULG website. | J4: Evidence may include plan documents, consultation records, meeting minutes, ULG resolutions/comments, responses to ULG inputs, or information published on the parastatal website.
A5: UPD2 | B5: UPD 2 | C5: Urban Planning & Design (UPD) | D5: MQ | E5: Where multiple statutory or sectoral plans apply to the same territory, does the water supply board and transport corporation ensure consistency with the applicable metropolitan/regional or city master plan/strategic plan for the city? | F5: 10 | H5: All parastatals excluding Development Authorities | I5: Sum of the sub-questions below - | J5: See sub-indicators
A6: UPD2a | B6: UPD 2a | C6: Urban Planning & Design (UPD) | D6: SQ | E6: Where multiple statutory or sectoral plans apply to the same territory, is the water board mandated to ensure consistency with the applicable metropolitan/regional or city master plan/strategic plan for the city? | F6: 2.5 | G6: Law/Policy | H6: Water supply board | I6: Review the relevant Parastatal Act and Town and Country Planning Act. Score 2.50 if the parastatal shall/is required to ensure that its spatial/sectoral plan is consistent with the applicable city, metropolitan or regional statutory plan. Score 1.25 if the law provides that the parastatal may ensure/seek such consistency or otherwise makes alignment discretionary. Score 0 if no such provision exists. For example, a provision stating that a water supply plan shall conform to the applicable Master Plan or Metropolitan Plan would score 2.5, while a provision stating that the authority may have regard to such a plan would score 1.25. | J6: Relevant Parastatal Act; applicable Town and Country Planning (T&CP) Act.
A7: UPD2b | B7: UPD 2b | C7: Urban Planning & Design (UPD) | D7: SQ | E7: Where multiple statutory or sectoral plans apply to the same territory, does the water supply board ensure consistency with the applicable metropolitan/regional or city master plan/strategic plan for the city? | F7: 2.5 | G7: Implementation | H7: Water supply board | I7: Review the Board’s current water supply/sewerage master plan, or equivalent sectoral planning document, together with the applicable Master Plan/Development Plan/Metropolitan or Regional Plan. Score 2.5 if the water plan demonstrates substantive spatial alignment with the city’s master plan: It explicitly draws reference to the city master plan, uses the master plan’s growth/service areas and/or land-use framework to determine network expansion and major infrastructure siting, and also refers to the master plan or its projections as an input. Score 1.25 if there is partial alignment: the water plan refers to the master plan and/or uses its population, density or land-use projections, but does not clearly demonstrate that these inputs determine the spatial location of network expansion, service areas or major infrastructure. Score 0 if there is no identifiable evidence that the Master Plan or its spatial/population framework informs water planning. The score sheet should record components for scores, the plan/document relied upon, year, applicable statutory master plan and the specific reference demonstrating alignment. Additional quality check, and not for scoring: Where readily available, record whether major treatment plants, trunk infrastructure or other significant facilities have required subsequent land-use conversion/regularisation because they were located on land not originally designated for that use. Treat this as contextual evidence of planning misalignment; it should not require a project-by-project review across the entire city. | J7: Water Supply Board's current water supply/sewerage master plan or equivalent sectoral planning document; applicable Master Plan/Development Plan/Metropolitan or Regional Plan; land-use conversion/regularisation records for major treatment plants or trunk infrastructure, where available.
A8: UPD2c | B8: UPD 2c | C8: Urban Planning & Design (UPD) | D8: SQ | E8: Where multiple statutory or sectoral plans apply to the same territory, is the transport corporation mandated to ensure consistency with the applicable metropolitan/regional or city master plan/strategic plan for the city? | F8: 2.5 | G8: Law/Policy | H8: Transport Corporation | I8: Review the relevant Parastatal Act and Town and Country Planning Act. Score 2.5 if the parastatal shall/is required to ensure that its spatial/sectoral plan is consistent with the applicable city, metropolitan or regional statutory plan. Score 1.25 if the law provides that the parastatal may ensure/seek such consistency or otherwise makes alignment discretionary. Score 0 if no such provision exists. For example, a provision stating that a transport plan shall conform to the applicable Master Plan or Metropolitan Plan would score 2.5, while a provision stating that the authority may have regard to such a plan would score 1.25. | J8: Relevant Parastatal Act; applicable Town and Country Planning (T&CP) Act.
A9: UPD2d | B9: UPD 2d | C9: Urban Planning & Design (UPD) | D9: SQ | E9: Where multiple statutory or sectoral plans apply to the same territory, does the transport corporation ensure consistency with the applicable metropolitan/regional or city master plan/strategic plan for the city? | F9: 2.5 | G9: Implementation | H9: Transport Corporation | I9: Review the transport corporation's current transport/mobility master plan, network expansion plan, or equivalent sectoral planning document, together with the applicable Master Plan/Development Plan/Metropolitan or Regional Plan. Score 2.5 if the transport plan demonstrates substantive spatial alignment with the city's master plan: it explicitly draws reference to the city master plan, uses the master plan's growth corridors, land-use framework and/or density projections to determine route planning, station/depot siting or network expansion, and refers to the master plan or its projections as an input. Score 1.25 if there is partial alignment: the transport plan refers to the master plan and/or uses its population, density or land-use projections, but does not clearly demonstrate that these inputs determine the spatial location of routes, stations or major infrastructure. Score 0 if there is no identifiable evidence that the Master Plan or its spatial/population framework informs transport planning. The score sheet should record components for scores, the plan/document relied upon, year, applicable statutory master plan, and the specific reference demonstrating alignment. Additional quality check, not for scoring: where readily available, record whether major depots, terminals or transit infrastructure required subsequent land-use conversion/regularisation because they were sited on land not originally designated for that use. Treat this as contextual evidence of planning misalignment; it should not require a project-by-project review across the entire city. | J9: Transport corporation's current mobility/network plan; applicable Master Plan/Development Plan/Metropolitan or Regional Plan; land-use conversion/regularisation records for major transport infrastructure, where available.
A10: UPD3 | B10: UPD 3 | C10: Urban Planning & Design (UPD) | D10: MQ | E10: Are the needs of women, the urban poor, and other vulnerable groups explicitly considered in the water board’s planning, service delivery or major investment decisions? | F10: 10 | G10: Law/Policy | H10: Water supply board | I10: Review the relevant Act of the parastatal and applicable sectoral legislation, rules, regulations and other binding policy instruments. Do not award credit solely for broad references such as “public interest”, “public welfare” or “welfare of inhabitants”; there must be an identifiable requirement relating to women, the urban poor, EWS/slum residents, persons with disabilities, informal workers, disadvantaged/vulnerable groups, affordability, equitable/universal access, safety, or rehabilitation/resettlement protections. | J10: Relevant Act of the parastatal and applicable sectoral legislation, rules, regulations and other binding policy instruments
A11: UPD3a | B11: UPD 3a | C11: Urban Planning & Design (UPD) | D11: SQ | E11: Is the water supply board mandated to consider the needs of women, the urban poor and other vulnerable groups in decisions relating to access, affordability and delivery of water and sanitation services? | F11: 5 | G11: Law/Policy | H11: Water supply board | I11: Review the Water Supply Board/utility Act, water and sanitation legislation, tariff regulations, service rules, State policies and other applicable binding instruments. Look for explicit requirements relating to universal/equitable access, service to slums or informal settlements, low-income/EWS households, affordability or concessional tariffs, minimum/lifeline supply, tenure-neutral access, women’s needs, persons with disabilities or other identified vulnerable groups. Score 5 if equity requirements apply across core service-access and delivery decisions Score 2.5 if limited to particular groups, services or schemes Score 0 if no explicit requirement is found. | J11: Water Supply Board/utility Act, water and sanitation legislation, tariff regulations, service rules, State policies and other applicable binding instruments
A12: UPD3b | B12: UPD 3b | C12: Urban Planning & Design (UPD) | D12: SQ | E12: Does the water supply board actually consider the needs of women, the urban poor and other vulnerable groups in decisions relating to access, affordability and delivery of water and sanitation services? | F12: 5 | G12: Implementation | H12: Water supply board | I12: Review the Board’s current water supply plan. Assess whether the Board’s it contains identifiable equity and inclusion measures for groups such as EWS/BPL households, slum/informal-settlement residents, women, persons with disabilities, elderly persons or other specifically identified vulnerable/disadvantaged groups. Do not award credit for generic language such as “public interest”, “all consumers”, “universal service” or “inclusive development” unless this is translated into a specific planning, service, tariff, connection or design provision. Component 1 – Affordability and inclusion in service coverage: 2.5 marks Look for identifiable provisions such as: concessional/lifeline tariff, connection fee concession, deposit concession or other affordability measure for EWS/BPL/slum/low-income households a named scheme or coverage commitment for slums/informal settlements inclusion of slums/informal settlements within the water-supply master plan’s demand assessment, network design or service area, including where relevant irrespective of land tenure or notified status priority/admissible category for network extension to low-income or underserved settlements decentralised/service alternatives such as community stand posts, water ATMs or mini-networks where individual household connections are not feasible. Scoring Score 2.5 if there is evidence of both (i) an affordability/access measure and (ii) an explicit service-planning/coverage measure for an identified vulnerable group. Score 1.25 if only one of the above is present. Score 0 if neither is present. Component 2 – Gender, and accessible design: 2.5 marks Look for identifiable planning or design measures such as: GESI/gender/social inclusion screening or analysis within water-supply planning or DPR preparation explicit design consideration for women, PwDs, elderly persons, children or other identified vulnerable users siting of shared water infrastructure to reduce time, distance or physical burden safe and accessible approaches to community water points barrier-free/universal-access design standards for public-facing water infrastructure, including ramps, step-free access, appropriate tap heights or other accessible design features other specific design or service measures intended to address identified access barriers. Scoring Score 2.5 if the Board’s current planning/design framework contains specific operational or design measures addressing the needs of identified vulnerable groups. Score 1.25 if vulnerable groups are specifically identified and considered, but the provision does not translate into a clear operational/design requirement. Score 0 if there is no identifiable equity/accessibility consideration. | J12: Water Supply Board's current water supply/sanitation plan; scheme/coverage documents; tariff or connection-concession orders; design/service standards.
A13: UPD4 | B13: UPD 4 | C13: Urban Planning & Design (UPD) | D13: MQ | E13: Are the needs of women, the urban poor, and other vulnerable groups explicitly considered in the transport Corporation’s planning, service delivery or major investment decisions? | F13: 10 | H13: Transport Corporation | I13: Sum of the sub-questions below - | J13: See sub-indicators
A14: UPD4a | B14: UPD 4a | C14: Urban Planning & Design (UPD) | D14: SQ | E14: Is the transport corporation mandated to consider the mobility needs of women, the urban poor and other vulnerable groups in planning and delivering public transport services? | F14: 5 | G14: Law/Policy | H14: Transport Corporation | I14: Review the transport authority/corporation Act, applicable transport legislation, rules, service regulations, fare policies and other binding policy instruments. Look for requirements relating to women’s safety and mobility, affordability/concessional fares, service coverage for low-income or peripheral areas, universal accessibility, persons with disabilities, last-mile access or other identified vulnerable users. Score 5 if such considerations are explicitly embedded across core service-planning and delivery functions Score 2.5 if limited to specific groups, services or schemes Score 0 if no explicit requirement is found. | J14: Transport authority/corporation Act, applicable transport legislation, rules, service regulations, fare policies and other binding policy instruments
A15: UPD4b | B15: UPD 4b | C15: Urban Planning & Design (UPD) | D15: SQ | E15: Does the Transport Corporation actually consider the needs of women, the urban poor and other vulnerable groups in decisions relating to access, affordability and delivery of public transport services? | F15: 5 | G15: Implementation | H15: Transport Corporation | I15: Review the Corporation's current transport/mobility plan or service-delivery framework. Assess whether it contains identifiable equity and inclusion measures for groups such as EWS/BPL households, informal-settlement residents, women, persons with disabilities, elderly persons or other specifically identified vulnerable/disadvantaged groups. Do not award credit for generic language such as "public interest," "all commuters," "universal service" or "inclusive development" unless this is translated into a specific route, fare, service or design provision. Component 1 – Affordability and inclusion in service coverage: 2.5 marks. Look for: concessional/subsidised fares for EWS/BPL, students, elderly persons, persons with disabilities or women; a named coverage commitment for low-income/peripheral areas; inclusion of informal settlements within route planning; last-mile connectivity measures for underserved settlements. Score 2.5 if there is evidence of both (i) an affordability/fare-concession measure and (ii) an explicit route/coverage measure for an identified vulnerable group. Score 1.25 if only one is present. Score 0 if neither is present. Component 2 – Gender, safety and accessible design: 2.5 marks. Look for: women's safety features (CCTV, panic buttons, adequate lighting); GESI/gender screening in transport planning; accessible design for persons with disabilities and elderly users (low-floor buses, ramps, priority seating, step-free access). Score 2.5 if the Corporation's current planning/design framework contains specific operational or design measures. Score 1.25 if vulnerable groups are identified but this doesn't translate into an operational/design requirement. Score 0 if no identifiable consideration. | J15: Transport Corporation's current transport/mobility plan; fare policy/concession orders; service design standards or specifications; annual report.
A16: UPD5 | B16: UPD 5 | C16: Urban Planning & Design (UPD) | D16: MQ | E16: Are environmental considerations explicitly required to be integrated into the water supply board’s planning, service-delivery or major investment decisions? | F16: 10 | G16: Law/Policy | H16: Water supply board | I16: Assess through the relevant parastatal-specific question below. Review the enabling Act of the parastatal, applicable sectoral legislation, T&CP/planning legislation where relevant, environmental rules/regulations, and other binding policy instruments governing the parastatal’s functions. Do not award credit solely for general references to “environment”, “public interest” or compliance with project-level environmental clearances. The legal/policy framework should require environmental considerations to inform the parastatal’s own planning, investment or service-delivery decisions. | J16: Enabling Act of the parastatal, applicable sectoral legislation, T&CP/planning legislation, relevant environmental rules/regulations, and other binding policy instruments
A17: UPD5a | B17: UPD 5a | C17: Urban Planning & Design (UPD) | D17: SQ | E17: Is the water supply board mandated to consider environmental sustainability in planning and delivering water and sanitation services? | F17: 5 | G17: Law/Policy | H17: Water supply board | I17: Review the Water Supply Board/utility Act, water and sanitation legislation, service rules, State water policies, groundwater/source-protection provisions and other binding instruments. Look for explicit requirements relating to sustainable water sources, source protection, demand management or conservation, reduction of water losses, wastewater treatment/reuse, protection from pollution, environmental flows where applicable, climate resilience or environmentally sustainable service delivery. Score 5 if environmental sustainability requirements apply across core water/sanitation planning and service-delivery functions; Score 2.5 if limited to particular functions, schemes or environmental concerns; Score 0 if no explicit requirement is found. | J17: Water Supply Board/utility Act, water and sanitation legislation, service rules, State water policies, groundwater/source-protection provisions and other binding instruments
A18: UPD5b | B18: UPD 5b | C18: Urban Planning & Design (UPD) | D18: SQ | E18: Does the water supply board actually consider environmental sustainability in planning and delivering water and sanitation services? | F18: 5 | G18: Implementation | H18: Water supply board | I18: Review the Board's latest water supply plan. Assess whether it contains identifiable environmental sustainability measures relating to source management, conservation, wastewater management, or climate resilience. Do not award credit for generic language such as "sustainable development," "efficient service," "environment friendly" or "public interest" unless this is translated into a specific planning, operational, or design provision. Component 1 – Sustainable source management, conservation and loss reduction: 2.5 marks Look for identifiable provisions such as: sustainable or diversified water source development, or measures to reduce over-extraction/dependence on a stressed source groundwater recharge, rainwater harvesting, or source-protection measures within the Board's own infrastructure planning a non-revenue water (NRW)/water-loss reduction target or programme demand management or water conservation measures (e.g., universal metering, leak detection and repair programme, conservation-oriented design standards) measures to protect water sources from pollution or encroachment (buffer/catchment protection, control of upstream effluent discharge) any other specific measure on sustainable source management, and/or conservation and loss reduction Scoring: Score 2.5 if there is evidence of both (i) a sustainable source/protection measure and (ii) an explicit loss-reduction or demand-management target/programme. Score 1.25 if only one of the above is present. Score 0 if neither is present. Component 2 – Wastewater management, reuse and climate resilience: 2.5 marks Look for identifiable planning or operational measures such as: wastewater treatment capacity or quality targets aligned with service expansion a treated-wastewater reuse/recycling target or scheme (industrial, horticultural, non-potable reuse, etc.) climate resilience or adaptation measures for water sources or infrastructure (drought contingency planning, flood-proofing of treatment/pumping assets) energy efficiency measures in water/wastewater operations (energy audits, renewable energy use in pumping/treatment) environmental flow or ecological considerations where surface water sources are used other specific measures addressing the environmental impact of water or wastewater operations Scoring: Score 2.5 if the Board's current planning framework contains specific operational measures addressing wastewater management, climate resilience or energy use. Score 1.25 if such considerations are mentioned or identified but do not translate into a clear operational or target-based requirement. Score 0 if there is no identifiable environmental sustainability consideration. | J18: Water Supply Board's current water supply/sanitation plan; source-protection or conservation programme documents; wastewater treatment/reuse scheme documents; annual report.
A19: UPD6 | B19: UPD 6 | C19: Urban Planning & Design (UPD) | D19: MQ | E19: Are environmental considerations explicitly required to be integrated into the transport corporation’s planning, service-delivery or major investment decisions? | F19: 10 | H19: Transport Corporation | I19: Sum of the sub-questions below - | J19: See sub-indicators
A20: UPD6a | B20: UPD 6a | C20: Urban Planning & Design (UPD) | D20: SQ | E20: Is the transport corporation mandated to consider environmental sustainability in planning and delivering urban transport services and investments? | F20: 5 | G20: Law/Policy | H20: Transport Corporation | I20: Review the transport authority/corporation Act, applicable transport legislation, rules, mobility/transport policies and other binding instruments. Look for explicit requirements relating to public and non-motorised transport prioritisation, emissions reduction, cleaner vehicle/fuel transition, energy efficiency, integration of land use and transport, reduction of congestion or vehicle dependence, climate resilience, or environmental impacts of major transport investments. Score 5 if environmental considerations are explicitly embedded across core transport planning/investment/service-delivery functions Score 2.5 if limited to specific modes, projects or environmental objectives Score 0 if no explicit requirement is found. | J20: Transport authority/corporation Act, applicable transport legislation, rules, mobility/transport policies and other binding instruments
A21: UPD6b | B21: UPD 6b | C21: Urban Planning & Design (UPD) | D21: SQ | E21: Does the transport corporation actually considers environmental sustainability in planning and delivering urban transport services and investments? | F21: 5 | G21: Implementation | H21: Transport Corporation | I21: Review the Corporation's current fleet plan, network/route plan or environmental/sustainability policy. Assess whether it contains identifiable environmental sustainability measures relating to fleet composition, emissions, energy use or modal integration. Do not award credit for generic language such as "sustainable development," "green transport" or "environment friendly" unless translated into a specific fleet, operational or design provision. Component 1 – Cleaner fleet and emissions reduction: 2.5 marks. Look for: an electric/CNG/hybrid fleet-transition target; an emissions or fuel-efficiency target; a retirement/phase-out schedule for high-emission vehicles. Score 2.5 if evidence of both (i) a cleaner-fuel/fleet-transition measure and (ii) an explicit emissions/efficiency target. Score 1.25 if only one is present. Score 0 if neither. Component 2 – Modal integration and demand-side measures: 2.5 marks. Look for: route planning informed by land-use/density to reduce vehicle-km travelled; NMT integration at stops/stations; multimodal integration (common ticketing, interchange with metro/rail); energy efficiency in depots/operations. Score 2.5 if the Corporation's planning framework contains specific operational measures. Score 1.25 if mentioned but not operationalised/targeted. Score 0 if no identifiable consideration. | J21: Transport Corporation's fleet plan; route/network plan; environmental/sustainability policy; annual report.
A22: DPG1 | B22: DPG 1 | C22: Decentralised Participatory Governance | D22: MQ | E22: Are the functions and geographical jurisdiction of the parastatal clearly defined vis-à-vis the ULG and other relevant agencies? | F22: 10 | G22: Institutional Design | H22: Common — all parastatal types. | I22: Sum of the sub-questions below - | J22: Parastatal, 12th Schedule mapping exercise
A23: DPG1a | B23: DPG 1a | C23: Decentralised Participatory Governance | D23: SQ | E23: Does the legal framework clearly demarcate the functions/responsibilities of the parastatal vis-à-vis the ULG? | F23: 5 | G23: Institutional Design | H23: Common — all parastatal types. | I23: Step 1 — Check devolution status under the Municipal Act. Review the Municipal Act to determine whether the specific function/service is: A — Not devolved: the function is not assigned to the ULG at all. B — Fully devolved: the function is assigned to the ULG in full, and the parastatal also delivers it (i.e. a potential overlap exists). C — Partially devolved: only specific sub-functions are assigned to the ULG (e.g. domestic water supply to the ULG, bulk supply/production to the parastatal). Step 2 — Score based on which scenario applies. If A (not devolved): Score 5. There is no ULG claim to the function, so there is nothing to demarcate against — the parastatal Act's assignment stands on its own. If B (fully devolved, both deliver it): Check whether the Parastatal Act explicitly carves out or distinguishes the parastatal's role from the ULG's (e.g. the parastatal Act specifies it handles a particular aspect, area, or scale of the function, rather than simply repeating the ULG's full assignment). Score 5 if such a distinction is explicit in the Parastatal Act. Score 0 if both Acts assign the same function with no distinction between them. If C (partially devolved): Check whether the aspect assigned to the parastatal is explicit and does not overlap with the aspect assigned to the ULG (e.g. Municipal Act assigns domestic water supply to the ULG; Parastatal Act assigns bulk supply/production to the parastatal — no overlap). Score 5 if the two Acts' assignments are explicit and non-overlapping. Score 0 if the assigned aspects overlap, or if the parastatal's aspect is not clearly specified in its Act. Record the devolution scenario (A/B/C) and the specific provisions relied upon in the evidence column. | J23: Relevant Parastatal Act; State Municipal Act — record the specific provisions establishing devolution status and (where applicable) the functional carve-out.
A24: DPG1b | B24: DPG 1b | C24: Decentralised Participatory Governance | D24: SQ | E24: Is the parastatal's territorial/geographic jurisdiction clearly and specifically defined in its enabling legal framework? | F24: 5 | G24: Institutional Design | H24: Common — all parastatal types. | I24: Review the relevant Parastatal Act and Municipal Act as the primary source. Since jurisdiction may be amended or updated after the parent Act through subsequent notifications, gazette orders, or administrative boundary changes not yet reflected in the Act, also cross-check the parastatal's official website and any government notifications/gazette publications for the current jurisdictional boundary. Score 5 if jurisdiction is defined with a specific boundary description, schedule, or map reference in the enabling Act. Review the relevant Parastatal Act and Municipal Act. Score 2.5 if defined only in general terms (e.g. "notified area" with no schedule). Score 0 if jurisdiction is not defined. | J24: Enabling Act, 12th Schedule mapping exercise
A25: DPG2 | B25: DPG 2 | C25: Decentralised Participatory Governance | D25: MQ | E25: Is the parastatal accountable to the ULG? | F25: 10 | G25: Institutional Design | H25: Common — all parastatal types. | I25: Sum of the sub-questions below - | J25: See sub-indicators
A26: DPG2a | B26: DPG 2a | C26: Decentralised Participatory Governance | D26: SQ | E26: Does the ULG have representation on the parastatal's governing board? | F26: 5 | G26: Institutional Design | H26: Common — all parastatal types. | I26: Review the relevant Parastatal Act and Municipal Act for composition. Score 5 if ULG-elected representatives sit on the board with voting rights. Score 2.5 if represented without voting rights or only as invitees. Score 0 if no representation. | J26: Composition clause of enabling Act; current board member list
A27: DPG2b | B27: DPG-2b | C27: Decentralised Participatory Governance | D27: SQ | E27: Is the parastatal mandated to submit its plans, budgets or reports to the ULG/council? | F27: 5 | G27: Law/Policy | H27: Common — all parastatal types. | I27: Review the relevant Parastatal Act and Municipal Act for provisions requiring the parastatal to submit or table its plans, budgets and reports before the ULG/council. The requirement may be provided through a general provision covering these documents or through specific provisions for each. Award 1.67 points each where: 1. plans are required to be submitted/tabled; 2. budgets are required to be submitted/tabled; and 3. annual/performance reports are required to be submitted/tabled. Score 0 for each component where no such requirement exists. Where all three are provided for, award the full score of 5. Record the relevant provision and the documents covered in the evidence column. Submission only to the State Government or another authority should not be counted as submission to the ULG/council. | J27: Plan/Budget preparation/Annual report preparation clause of the enabling Act of the relevant parastatal
A28: DPG4 | B28: DPG 4 | C28: Decentralised Participatory Governance | D28: MQ | E28: Does the parastatal maintain an active and functional website? | F28: 10 | G28: Implementation | H28: Common. | I28: Check the official website of the relevant parastatal. Score 10 if an official website of the relevant parastatal exists, opens without error, and shows content updated within the last 12 months (verifiable "last updated" date or dated content such as a recent notice/circular). Score 0 if no official website is found. This is a point-in-time check — record the date of verification and an archived screenshot/link as evidence, since website status can change. | J28: Live URL, screenshot/web-archive capture, date of check of the website of the relevant parastatal
A29: DPG5 | B29: DPG 5 | C29: Decentralised Participatory Governance | D29: MQ | E29: Are the parastatal's key financial, governance, and operational documents available on the website and published in accessible, open-data formats? | F29: 10 | G29: Implementation | H29: Common. | I29: Sum of sub-questions below - Assess each of the ten components below independently. Each component carries 1 point: 0.5 for online availability and 0.5 for publication in an open, machine-readable/reusable format, as appropriate to the information type. For online availability, score 0.5 if the document/information is publicly available online and current, relating to the current financial year or at least the immediately preceding financial year, as applicable; score 0 if it is unavailable or outdated. Aggregate the scores across all ten components to arrive at the total score out of 10. | J29: Website screenshots/archived URLs with date of access, for each document type
A30: DPG5a | B30: DPG5a | C30: Decentralised Participatory Governance | D30: SQ | E30: Annual budget | F30: 1 | G30: Implementation | H30: Common. | I30: Availability and currency — 0.5 0.5: Budget for the current FY or immediately preceding FY is publicly available online 0: Budget cannot be found/accessed online or is older than the permitted period. Record the FY/year/date of the latest information found in a separate evidence field even where the score is 0. Minimum format/accessibility — 0.5 0.5: Budget data available in a structured, machine-readable/reusable format (XLS/XLSX, CSV, ODS, structured HTML table, downloadable structured dataset) 0: Budget data is available but does not meet that standard (Scanned PDF/image; PDF containing only tables that cannot be readily extracted/reused) | J30: Website screenshots/archived URLs with date of access, for each document type
A31: DPG5b | B31: DPG 5b | C31: Decentralised Participatory Governance | D31: SQ | E31: Audited annual accounts | F31: 1 | G31: Implementation | H31: Common. | I31: Availability and currency — 0.5 Score 0.5: Audited accounts for the immediately preceding FY, or the latest FY for which audited accounts are due, are publicly available online. Allow a one-FY lag where audit timelines make preceding-year accounts not yet due. Score 0: Audited accounts cannot be found/accessed online or is older than the permitted period. Record the FY/year/date of the latest information found in a separate evidence field even where the score is 0. Minimum format/accessibility — 0.5 Score 0.5: Financial statements available in a structured, machine-readable/reusable format (XLS/XLSX, CSV, ODS, structured HTML table, downloadable structured dataset) Score 0: Financial statements is available but does not meet that standard (Scanned PDF/image; PDF containing only tables that cannot be readily extracted/reused) | J31: Website screenshots/archived URLs with date of access, for each document type
... A56: SC7b | B56: SC-7b | C56: State Capacities | D56: SQ | E56: What proportion of the parastatal's workforce is women? | F56: 5 | G56: Implementation (Numeric) | H56: Common — all parastatal types. | I56: Compute women employees as a proportion of total filled posts using the latest available staffing data. % women in workforce = (Number of women employees ÷ Total filled posts) × 100, using the latest available staffing data. Scoring bands: Score 5 — women constitute ≥33% of the workforce Score 2.5 — women constitute 15–32% of the workforce Score 0 — women constitute <15% of the workforce Also record, wherever available, the proportion of women in senior/decision-making positions and technical/professional cadres. | J56: Staffing records on the website/ RTI and/or formal data request with the parastatal/ annual report

Sheet UPD1a
A1: Question Code | B1: UPD1a | C1: <Sheet name and this code must match>
A2: Group | B2: =VLOOKUP($B$1,'PARASTATAL Questions'!$A:$J,3,0)&""
A3: Original ID | B3: =VLOOKUP($B$1,'PARASTATAL Questions'!$A:$J,2,0)&""
A4: MQ_SQ | B4: =VLOOKUP($B$1,'PARASTATAL Questions'!$A:$J,4,0)&""
A5: Question | B5: =VLOOKUP($B$1,'PARASTATAL Questions'!$A:$J,5,0)&""
A6: Max Score | B6: =VLOOKUP($B$1,'PARASTATAL Questions'!$A:$J,6,0)
A7: Assessment level | B7: =VLOOKUP($B$1,'PARASTATAL Questions'!$A:$J,7,0)&""
A8: Applicability | B8: =VLOOKUP($B$1,'PARASTATAL Questions'!$A:$J,8,0)&""
A9: Detailed Methodology | B9: =VLOOKUP($B$1,'PARASTATAL Questions'!$A:$J,9,0)&""
A10: Notes for scorers | B10: =VLOOKUP($B$1,'PARASTATAL Questions'!$A:$J,10,0)&""
B11: PRE-FILLED - DO NOT ALTER | I11: ENTER A NUMBER 0 TO 5 | J11: DO NOT ALTER FORMULA
A12: City | B12: Applies? | C12: Act Name/Web name/Doc name | D12: Chapter | E12: Provision | F12: Clause | G12: Page Number | H12: Link | I12: Score | J12: Points (Auto-generate) | K12: SCORER COMMENTS
A13: Bengaluru – BWSSB | B13: YES | J13: =IF($B13="NO","NA",IF(I13="","",MIN(I13,$B$6)))
A14: Bengaluru – BMTC | B14: YES | J14: =IF($B14="NO","NA",IF(I14="","",MIN(I14,$B$6)))
A15: Bengaluru – BDA | B15: YES | J15: =IF($B15="NO","NA",IF(I15="","",MIN(I15,$B$6)))
A16: Bengaluru – BMRCL | B16: YES | J16: =IF($B16="NO","NA",IF(I16="","",MIN(I16,$B$6)))
A17: Bengaluru – BMRDA | B17: YES | J17: =IF($B17="NO","NA",IF(I17="","",MIN(I17,$B$6)))
A18: Surat – SUDA | B18: YES | J18: =IF($B18="NO","NA",IF(I18="","",MIN(I18,$B$6)))
A19: Surat – GMRC | B19: YES | J19: =IF($B19="NO","NA",IF(I19="","",MIN(I19,$B$6)))

Sheet UPD1b
A1: Question Code | B1: UPD1b | C1: <Sheet name and this code must match>
A2: Group | B2: =VLOOKUP($B$1,'PARASTATAL Questions'!$A:$J,3,0)&""
A3: Original ID | B3: =VLOOKUP($B$1,'PARASTATAL Questions'!$A:$J,2,0)&""
A4: MQ_SQ | B4: =VLOOKUP($B$1,'PARASTATAL Questions'!$A:$J,4,0)&""
A5: Question | B5: =VLOOKUP($B$1,'PARASTATAL Questions'!$A:$J,5,0)&""
A6: Max Score | B6: =VLOOKUP($B$1,'PARASTATAL Questions'!$A:$J,6,0)
A7: Assessment level | B7: =VLOOKUP($B$1,'PARASTATAL Questions'!$A:$J,7,0)&""
A8: Applicability | B8: =VLOOKUP($B$1,'PARASTATAL Questions'!$A:$J,8,0)&""
A9: Detailed Methodology | B9: =VLOOKUP($B$1,'PARASTATAL Questions'!$A:$J,9,0)&""
A10: Notes for scorers | B10: =VLOOKUP($B$1,'PARASTATAL Questions'!$A:$J,10,0)&""
B11: PRE-FILLED - DO NOT ALTER | I11: ENTER A NUMBER 0 TO 5 | J11: DO NOT ALTER FORMULA
A12: City | B12: Applies? | C12: Act Name/Web name/Doc name | D12: Chapter | E12: Provision | F12: Clause | G12: Page Number | H12: Link | I12: Score | J12: Points (Auto-generate) | K12: SCORER COMMENTS
A13: Bengaluru – BWSSB | B13: YES | J13: =IF($B13="NO","NA",IF(I13="","",MIN(I13,$B$6)))
A14: Bengaluru – BMTC | B14: YES | J14: =IF($B14="NO","NA",IF(I14="","",MIN(I14,$B$6)))
A15: Bengaluru – BDA | B15: YES | J15: =IF($B15="NO","NA",IF(I15="","",MIN(I15,$B$6)))
A16: Bengaluru – BMRCL | B16: YES | J16: =IF($B16="NO","NA",IF(I16="","",MIN(I16,$B$6)))
A17: Bengaluru – BMRDA | B17: YES | J17: =IF($B17="NO","NA",IF(I17="","",MIN(I17,$B$6)))
A18: Surat – SUDA | B18: YES | J18: =IF($B18="NO","NA",IF(I18="","",MIN(I18,$B$6)))
A19: Surat – GMRC | B19: YES | J19: =IF($B19="NO","NA",IF(I19="","",MIN(I19,$B$6)))

Sheet UPD2a
A1: Question Code | B1: UPD2a | C1: <Sheet name and this code must match>
A2: Group | B2: =VLOOKUP($B$1,'PARASTATAL Questions'!$A:$J,3,0)&""
A3: Original ID | B3: =VLOOKUP($B$1,'PARASTATAL Questions'!$A:$J,2,0)&""
A4: MQ_SQ | B4: =VLOOKUP($B$1,'PARASTATAL Questions'!$A:$J,4,0)&""
A5: Question | B5: =VLOOKUP($B$1,'PARASTATAL Questions'!$A:$J,5,0)&""
A6: Max Score | B6: =VLOOKUP($B$1,'PARASTATAL Questions'!$A:$J,6,0)
A7: Assessment level | B7: =VLOOKUP($B$1,'PARASTATAL Questions'!$A:$J,7,0)&""
A8: Applicability | B8: =VLOOKUP($B$1,'PARASTATAL Questions'!$A:$J,8,0)&""
A9: Detailed Methodology | B9: =VLOOKUP($B$1,'PARASTATAL Questions'!$A:$J,9,0)&""
A10: Notes for scorers | B10: =VLOOKUP($B$1,'PARASTATAL Questions'!$A:$J,10,0)&""
B11: PRE-FILLED - DO NOT ALTER | I11: ENTER A NUMBER 0 TO 2.5 | J11: DO NOT ALTER FORMULA
A12: City | B12: Applies? | C12: Act Name/Web name/Doc name | D12: Chapter | E12: Provision | F12: Clause | G12: Page Number | H12: Link | I12: Score | J12: Points (Auto-generate) | K12: SCORER COMMENTS
A13: Bengaluru – BWSSB | B13: YES | J13: =IF($B13="NO","NA",IF(I13="","",MIN(I13,$B$6)))
A14: Bengaluru – BMTC | B14: NO | J14: =IF($B14="NO","NA",IF(I14="","",MIN(I14,$B$6)))
A15: Bengaluru – BDA | B15: NO | J15: =IF($B15="NO","NA",IF(I15="","",MIN(I15,$B$6)))
A16: Bengaluru – BMRCL | B16: NO | J16: =IF($B16="NO","NA",IF(I16="","",MIN(I16,$B$6)))
A17: Bengaluru – BMRDA | B17: NO | J17: =IF($B17="NO","NA",IF(I17="","",MIN(I17,$B$6)))
A18: Surat – SUDA | B18: NO | J18: =IF($B18="NO","NA",IF(I18="","",MIN(I18,$B$6)))
A19: Surat – GMRC | B19: NO | J19: =IF($B19="NO","NA",IF(I19="","",MIN(I19,$B$6)))

Sheet UPD2b
A1: Question Code | B1: UPD2b | C1: <Sheet name and this code must match>
A2: Group | B2: =VLOOKUP($B$1,'PARASTATAL Questions'!$A:$J,3,0)&""
A3: Original ID | B3: =VLOOKUP($B$1,'PARASTATAL Questions'!$A:$J,2,0)&""
A4: MQ_SQ | B4: =VLOOKUP($B$1,'PARASTATAL Questions'!$A:$J,4,0)&""
A5: Question | B5: =VLOOKUP($B$1,'PARASTATAL Questions'!$A:$J,5,0)&""
A6: Max Score | B6: =VLOOKUP($B$1,'PARASTATAL Questions'!$A:$J,6,0)
A7: Assessment level | B7: =VLOOKUP($B$1,'PARASTATAL Questions'!$A:$J,7,0)&""
A8: Applicability | B8: =VLOOKUP($B$1,'PARASTATAL Questions'!$A:$J,8,0)&""
A9: Detailed Methodology | B9: =VLOOKUP($B$1,'PARASTATAL Questions'!$A:$J,9,0)&""
A10: Notes for scorers | B10: =VLOOKUP($B$1,'PARASTATAL Questions'!$A:$J,10,0)&""
B11: PRE-FILLED - DO NOT ALTER | I11: ENTER A NUMBER 0 TO 2.5 | J11: DO NOT ALTER FORMULA
A12: City | B12: Applies? | C12: Act Name/Web name/Doc name | D12: Chapter | E12: Provision | F12: Clause | G12: Page Number | H12: Link | I12: Score | J12: Points (Auto-generate) | K12: SCORER COMMENTS
A13: Bengaluru – BWSSB | B13: YES | J13: =IF($B13="NO","NA",IF(I13="","",MIN(I13,$B$6)))
A14: Bengaluru – BMTC | B14: NO | J14: =IF($B14="NO","NA",IF(I14="","",MIN(I14,$B$6)))
A15: Bengaluru – BDA | B15: NO | J15: =IF($B15="NO","NA",IF(I15="","",MIN(I15,$B$6)))
A16: Bengaluru – BMRCL | B16: NO | J16: =IF($B16="NO","NA",IF(I16="","",MIN(I16,$B$6)))
A17: Bengaluru – BMRDA | B17: NO | J17: =IF($B17="NO","NA",IF(I17="","",MIN(I17,$B$6)))
A18: Surat – SUDA | B18: NO | J18: =IF($B18="NO","NA",IF(I18="","",MIN(I18,$B$6)))
A19: Surat – GMRC | B19: NO | J19: =IF($B19="NO","NA",IF(I19="","",MIN(I19,$B$6)))

Sheet UPD2c
A1: Question Code | B1: UPD2c | C1: <Sheet name and this code must match>
A2: Group | B2: =VLOOKUP($B$1,'PARASTATAL Questions'!$A:$J,3,0)&""
A3: Original ID | B3: =VLOOKUP($B$1,'PARASTATAL Questions'!$A:$J,2,0)&""
A4: MQ_SQ | B4: =VLOOKUP($B$1,'PARASTATAL Questions'!$A:$J,4,0)&""
A5: Question | B5: =VLOOKUP($B$1,'PARASTATAL Questions'!$A:$J,5,0)&""
A6: Max Score | B6: =VLOOKUP($B$1,'PARASTATAL Questions'!$A:$J,6,0)
A7: Assessment level | B7: =VLOOKUP($B$1,'PARASTATAL Questions'!$A:$J,7,0)&""
A8: Applicability | B8: =VLOOKUP($B$1,'PARASTATAL Questions'!$A:$J,8,0)&""
A9: Detailed Methodology | B9: =VLOOKUP($B$1,'PARASTATAL Questions'!$A:$J,9,0)&""
A10: Notes for scorers | B10: =VLOOKUP($B$1,'PARASTATAL Questions'!$A:$J,10,0)&""
B11: PRE-FILLED - DO NOT ALTER | I11: ENTER A NUMBER 0 TO 2.5 | J11: DO NOT ALTER FORMULA
A12: City | B12: Applies? | C12: Act Name/Web name/Doc name | D12: Chapter | E12: Provision | F12: Clause | G12: Page Number | H12: Link | I12: Score | J12: Points (Auto-generate) | K12: SCORER COMMENTS
A13: Bengaluru – BWSSB | B13: NO | J13: =IF($B13="NO","NA",IF(I13="","",MIN(I13,$B$6)))
A14: Bengaluru – BMTC | B14: YES | J14: =IF($B14="NO","NA",IF(I14="","",MIN(I14,$B$6)))
A15: Bengaluru – BDA | B15: NO | J15: =IF($B15="NO","NA",IF(I15="","",MIN(I15,$B$6)))
A16: Bengaluru – BMRCL | B16: NO | J16: =IF($B16="NO","NA",IF(I16="","",MIN(I16,$B$6)))
A17: Bengaluru – BMRDA | B17: NO | J17: =IF($B17="NO","NA",IF(I17="","",MIN(I17,$B$6)))
A18: Surat – SUDA | B18: NO | J18: =IF($B18="NO","NA",IF(I18="","",MIN(I18,$B$6)))
A19: Surat – GMRC | B19: NO | J19: =IF($B19="NO","NA",IF(I19="","",MIN(I19,$B$6)))

Sheet UPD2d
A1: Question Code | B1: UPD2d | C1: <Sheet name and this code must match>
A2: Group | B2: =VLOOKUP($B$1,'PARASTATAL Questions'!$A:$J,3,0)&""
A3: Original ID | B3: =VLOOKUP($B$1,'PARASTATAL Questions'!$A:$J,2,0)&""
A4: MQ_SQ | B4: =VLOOKUP($B$1,'PARASTATAL Questions'!$A:$J,4,0)&""
A5: Question | B5: =VLOOKUP($B$1,'PARASTATAL Questions'!$A:$J,5,0)&""
A6: Max Score | B6: =VLOOKUP($B$1,'PARASTATAL Questions'!$A:$J,6,0)
A7: Assessment level | B7: =VLOOKUP($B$1,'PARASTATAL Questions'!$A:$J,7,0)&""
A8: Applicability | B8: =VLOOKUP($B$1,'PARASTATAL Questions'!$A:$J,8,0)&""
A9: Detailed Methodology | B9: =VLOOKUP($B$1,'PARASTATAL Questions'!$A:$J,9,0)&""
A10: Notes for scorers | B10: =VLOOKUP($B$1,'PARASTATAL Questions'!$A:$J,10,0)&""
B11: PRE-FILLED - DO NOT ALTER | I11: ENTER A NUMBER 0 TO 2.5 | J11: DO NOT ALTER FORMULA
A12: City | B12: Applies? | C12: Act Name/Web name/Doc name | D12: Chapter | E12: Provision | F12: Clause | G12: Page Number | H12: Link | I12: Score | J12: Points (Auto-generate) | K12: SCORER COMMENTS
A13: Bengaluru – BWSSB | B13: NO | J13: =IF($B13="NO","NA",IF(I13="","",MIN(I13,$B$6)))
A14: Bengaluru – BMTC | B14: YES | J14: =IF($B14="NO","NA",IF(I14="","",MIN(I14,$B$6)))
A15: Bengaluru – BDA | B15: NO | J15: =IF($B15="NO","NA",IF(I15="","",MIN(I15,$B$6)))
A16: Bengaluru – BMRCL | B16: NO | J16: =IF($B16="NO","NA",IF(I16="","",MIN(I16,$B$6)))
A17: Bengaluru – BMRDA | B17: NO | J17: =IF($B17="NO","NA",IF(I17="","",MIN(I17,$B$6)))
A18: Surat – SUDA | B18: NO | J18: =IF($B18="NO","NA",IF(I18="","",MIN(I18,$B$6)))
A19: Surat – GMRC | B19: NO | J19: =IF($B19="NO","NA",IF(I19="","",MIN(I19,$B$6)))

Sheet UPD3a
A1: Question Code | B1: UPD3a | C1: <Sheet name and this code must match>
A2: Group | B2: =VLOOKUP($B$1,'PARASTATAL Questions'!$A:$J,3,0)&""
A3: Original ID | B3: =VLOOKUP($B$1,'PARASTATAL Questions'!$A:$J,2,0)&""
A4: MQ_SQ | B4: =VLOOKUP($B$1,'PARASTATAL Questions'!$A:$J,4,0)&""
A5: Question | B5: =VLOOKUP($B$1,'PARASTATAL Questions'!$A:$J,5,0)&""
A6: Max Score | B6: =VLOOKUP($B$1,'PARASTATAL Questions'!$A:$J,6,0)
A7: Assessment level | B7: =VLOOKUP($B$1,'PARASTATAL Questions'!$A:$J,7,0)&""
A8: Applicability | B8: =VLOOKUP($B$1,'PARASTATAL Questions'!$A:$J,8,0)&""
A9: Detailed Methodology | B9: =VLOOKUP($B$1,'PARASTATAL Questions'!$A:$J,9,0)&""
A10: Notes for scorers | B10: =VLOOKUP($B$1,'PARASTATAL Questions'!$A:$J,10,0)&""
B11: PRE-FILLED - DO NOT ALTER | I11: ENTER A NUMBER 0 TO 5 | J11: DO NOT ALTER FORMULA
A12: City | B12: Applies? | C12: Act Name/Web name/Doc name | D12: Chapter | E12: Provision | F12: Clause | G12: Page Number | H12: Link | I12: Score | J12: Points (Auto-generate) | K12: SCORER COMMENTS
A13: Bengaluru – BWSSB | B13: YES | J13: =IF($B13="NO","NA",IF(I13="","",MIN(I13,$B$6)))
A14: Bengaluru – BMTC | B14: NO | J14: =IF($B14="NO","NA",IF(I14="","",MIN(I14,$B$6)))
A15: Bengaluru – BDA | B15: NO | J15: =IF($B15="NO","NA",IF(I15="","",MIN(I15,$B$6)))
A16: Bengaluru – BMRCL | B16: NO | J16: =IF($B16="NO","NA",IF(I16="","",MIN(I16,$B$6)))
A17: Bengaluru – BMRDA | B17: NO | J17: =IF($B17="NO","NA",IF(I17="","",MIN(I17,$B$6)))
A18: Surat – SUDA | B18: NO | J18: =IF($B18="NO","NA",IF(I18="","",MIN(I18,$B$6)))
A19: Surat – GMRC | B19: NO | J19: =IF($B19="NO","NA",IF(I19="","",MIN(I19,$B$6)))

Sheet UPD3b
A1: Question Code | B1: UPD3b | C1: <Sheet name and this code must match>
A2: Group | B2: =VLOOKUP($B$1,'PARASTATAL Questions'!$A:$J,3,0)&""
A3: Original ID | B3: =VLOOKUP($B$1,'PARASTATAL Questions'!$A:$J,2,0)&""
A4: MQ_SQ | B4: =VLOOKUP($B$1,'PARASTATAL Questions'!$A:$J,4,0)&""
A5: Question | B5: =VLOOKUP($B$1,'PARASTATAL Questions'!$A:$J,5,0)&""
A6: Max Score | B6: =VLOOKUP($B$1,'PARASTATAL Questions'!$A:$J,6,0)
A7: Assessment level | B7: =VLOOKUP($B$1,'PARASTATAL Questions'!$A:$J,7,0)&""
A8: Applicability | B8: =VLOOKUP($B$1,'PARASTATAL Questions'!$A:$J,8,0)&""
A9: Detailed Methodology | B9: =VLOOKUP($B$1,'PARASTATAL Questions'!$A:$J,9,0)&""
A10: Notes for scorers | B10: =VLOOKUP($B$1,'PARASTATAL Questions'!$A:$J,10,0)&""
B11: PRE-FILLED - DO NOT ALTER | I11: ENTER A NUMBER 0 TO 5 | J11: DO NOT ALTER FORMULA
A12: City | B12: Applies? | C12: Act Name/Web name/Doc name | D12: Chapter | E12: Provision | F12: Clause | G12: Page Number | H12: Link | I12: Score | J12: Points (Auto-generate) | K12: SCORER COMMENTS
A13: Bengaluru – BWSSB | B13: YES | J13: =IF($B13="NO","NA",IF(I13="","",MIN(I13,$B$6)))
A14: Bengaluru – BMTC | B14: NO | J14: =IF($B14="NO","NA",IF(I14="","",MIN(I14,$B$6)))
A15: Bengaluru – BDA | B15: NO | J15: =IF($B15="NO","NA",IF(I15="","",MIN(I15,$B$6)))
A16: Bengaluru – BMRCL | B16: NO | J16: =IF($B16="NO","NA",IF(I16="","",MIN(I16,$B$6)))
A17: Bengaluru – BMRDA | B17: NO | J17: =IF($B17="NO","NA",IF(I17="","",MIN(I17,$B$6)))
A18: Surat – SUDA | B18: NO | J18: =IF($B18="NO","NA",IF(I18="","",MIN(I18,$B$6)))
A19: Surat – GMRC | B19: NO | J19: =IF($B19="NO","NA",IF(I19="","",MIN(I19,$B$6)))

Sheet UPD4a
A1: Question Code | B1: UPD4a | C1: <Sheet name and this code must match>
A2: Group | B2: =VLOOKUP($B$1,'PARASTATAL Questions'!$A:$J,3,0)&""
A3: Original ID | B3: =VLOOKUP($B$1,'PARASTATAL Questions'!$A:$J,2,0)&""
A4: MQ_SQ | B4: =VLOOKUP($B$1,'PARASTATAL Questions'!$A:$J,4,0)&""
A5: Question | B5: =VLOOKUP($B$1,'PARASTATAL Questions'!$A:$J,5,0)&""
A6: Max Score | B6: =VLOOKUP($B$1,'PARASTATAL Questions'!$A:$J,6,0)
A7: Assessment level | B7: =VLOOKUP($B$1,'PARASTATAL Questions'!$A:$J,7,0)&""
A8: Applicability | B8: =VLOOKUP($B$1,'PARASTATAL Questions'!$A:$J,8,0)&""
A9: Detailed Methodology | B9: =VLOOKUP($B$1,'PARASTATAL Questions'!$A:$J,9,0)&""
A10: Notes for scorers | B10: =VLOOKUP($B$1,'PARASTATAL Questions'!$A:$J,10,0)&""
B11: PRE-FILLED - DO NOT ALTER | I11: ENTER A NUMBER 0 TO 5 | J11: DO NOT ALTER FORMULA
A12: City | B12: Applies? | C12: Act Name/Web name/Doc name | D12: Chapter | E12: Provision | F12: Clause | G12: Page Number | H12: Link | I12: Score | J12: Points (Auto-generate) | K12: SCORER COMMENTS
A13: Bengaluru – BWSSB | B13: NO | J13: =IF($B13="NO","NA",IF(I13="","",MIN(I13,$B$6)))
A14: Bengaluru – BMTC | B14: YES | J14: =IF($B14="NO","NA",IF(I14="","",MIN(I14,$B$6)))
A15: Bengaluru – BDA | B15: NO | J15: =IF($B15="NO","NA",IF(I15="","",MIN(I15,$B$6)))
A16: Bengaluru – BMRCL | B16: NO | J16: =IF($B16="NO","NA",IF(I16="","",MIN(I16,$B$6)))
A17: Bengaluru – BMRDA | B17: NO | J17: =IF($B17="NO","NA",IF(I17="","",MIN(I17,$B$6)))
A18: Surat – SUDA | B18: NO | J18: =IF($B18="NO","NA",IF(I18="","",MIN(I18,$B$6)))
A19: Surat – GMRC | B19: NO | J19: =IF($B19="NO","NA",IF(I19="","",MIN(I19,$B$6)))

Sheet UPD4b
A1: Question Code | B1: UPD4b | C1: <Sheet name and this code must match>
A2: Group | B2: =VLOOKUP($B$1,'PARASTATAL Questions'!$A:$J,3,0)&""
A3: Original ID | B3: =VLOOKUP($B$1,'PARASTATAL Questions'!$A:$J,2,0)&""
A4: MQ_SQ | B4: =VLOOKUP($B$1,'PARASTATAL Questions'!$A:$J,4,0)&""
A5: Question | B5: =VLOOKUP($B$1,'PARASTATAL Questions'!$A:$J,5,0)&""
A6: Max Score | B6: =VLOOKUP($B$1,'PARASTATAL Questions'!$A:$J,6,0)
A7: Assessment level | B7: =VLOOKUP($B$1,'PARASTATAL Questions'!$A:$J,7,0)&""
A8: Applicability | B8: =VLOOKUP($B$1,'PARASTATAL Questions'!$A:$J,8,0)&""
A9: Detailed Methodology | B9: =VLOOKUP($B$1,'PARASTATAL Questions'!$A:$J,9,0)&""
A10: Notes for scorers | B10: =VLOOKUP($B$1,'PARASTATAL Questions'!$A:$J,10,0)&""
B11: PRE-FILLED - DO NOT ALTER | I11: ENTER A NUMBER 0 TO 5 | J11: DO NOT ALTER FORMULA
A12: City | B12: Applies? | C12: Act Name/Web name/Doc name | D12: Chapter | E12: Provision | F12: Clause | G12: Page Number | H12: Link | I12: Score | J12: Points (Auto-generate) | K12: SCORER COMMENTS
A13: Bengaluru – BWSSB | B13: NO | J13: =IF($B13="NO","NA",IF(I13="","",MIN(I13,$B$6)))
A14: Bengaluru – BMTC | B14: YES | J14: =IF($B14="NO","NA",IF(I14="","",MIN(I14,$B$6)))
A15: Bengaluru – BDA | B15: NO | J15: =IF($B15="NO","NA",IF(I15="","",MIN(I15,$B$6)))
A16: Bengaluru – BMRCL | B16: NO | J16: =IF($B16="NO","NA",IF(I16="","",MIN(I16,$B$6)))
A17: Bengaluru – BMRDA | B17: NO | J17: =IF($B17="NO","NA",IF(I17="","",MIN(I17,$B$6)))
A18: Surat – SUDA | B18: NO | J18: =IF($B18="NO","NA",IF(I18="","",MIN(I18,$B$6)))
A19: Surat – GMRC | B19: NO | J19: =IF($B19="NO","NA",IF(I19="","",MIN(I19,$B$6)))

Sheet UPD5a
A1: Question Code | B1: UPD5a | C1: <Sheet name and this code must match>
A2: Group | B2: =VLOOKUP($B$1,'PARASTATAL Questions'!$A:$J,3,0)&""
A3: Original ID | B3: =VLOOKUP($B$1,'PARASTATAL Questions'!$A:$J,2,0)&""
A4: MQ_SQ | B4: =VLOOKUP($B$1,'PARASTATAL Questions'!$A:$J,4,0)&""
A5: Question | B5: =VLOOKUP($B$1,'PARASTATAL Questions'!$A:$J,5,0)&""
A6: Max Score | B6: =VLOOKUP($B$1,'PARASTATAL Questions'!$A:$J,6,0)
A7: Assessment level | B7: =VLOOKUP($B$1,'PARASTATAL Questions'!$A:$J,7,0)&""
A8: Applicability | B8: =VLOOKUP($B$1,'PARASTATAL Questions'!$A:$J,8,0)&""
A9: Detailed Methodology | B9: =VLOOKUP($B$1,'PARASTATAL Questions'!$A:$J,9,0)&""
A10: Notes for scorers | B10: =VLOOKUP($B$1,'PARASTATAL Questions'!$A:$J,10,0)&""
B11: PRE-FILLED - DO NOT ALTER | I11: ENTER A NUMBER 0 TO 5 | J11: DO NOT ALTER FORMULA
A12: City | B12: Applies? | C12: Act Name/Web name/Doc name | D12: Chapter | E12: Provision | F12: Clause | G12: Page Number | H12: Link | I12: Score | J12: Points (Auto-generate) | K12: SCORER COMMENTS
A13: Bengaluru – BWSSB | B13: YES | J13: =IF($B13="NO","NA",IF(I13="","",MIN(I13,$B$6)))
A14: Bengaluru – BMTC | B14: NO | J14: =IF($B14="NO","NA",IF(I14="","",MIN(I14,$B$6)))
A15: Bengaluru – BDA | B15: NO | J15: =IF($B15="NO","NA",IF(I15="","",MIN(I15,$B$6)))
A16: Bengaluru – BMRCL | B16: NO | J16: =IF($B16="NO","NA",IF(I16="","",MIN(I16,$B$6)))
A17: Bengaluru – BMRDA | B17: NO | J17: =IF($B17="NO","NA",IF(I17="","",MIN(I17,$B$6)))
A18: Surat – SUDA | B18: NO | J18: =IF($B18="NO","NA",IF(I18="","",MIN(I18,$B$6)))
A19: Surat – GMRC | B19: NO | J19: =IF($B19="NO","NA",IF(I19="","",MIN(I19,$B$6)))

Sheet UPD5b
A1: Question Code | B1: UPD5b | C1: <Sheet name and this code must match>
A2: Group | B2: =VLOOKUP($B$1,'PARASTATAL Questions'!$A:$J,3,0)&""
A3: Original ID | B3: =VLOOKUP($B$1,'PARASTATAL Questions'!$A:$J,2,0)&""
A4: MQ_SQ | B4: =VLOOKUP($B$1,'PARASTATAL Questions'!$A:$J,4,0)&""
A5: Question | B5: =VLOOKUP($B$1,'PARASTATAL Questions'!$A:$J,5,0)&""
A6: Max Score | B6: =VLOOKUP($B$1,'PARASTATAL Questions'!$A:$J,6,0)
A7: Assessment level | B7: =VLOOKUP($B$1,'PARASTATAL Questions'!$A:$J,7,0)&""
A8: Applicability | B8: =VLOOKUP($B$1,'PARASTATAL Questions'!$A:$J,8,0)&""
A9: Detailed Methodology | B9: =VLOOKUP($B$1,'PARASTATAL Questions'!$A:$J,9,0)&""
A10: Notes for scorers | B10: =VLOOKUP($B$1,'PARASTATAL Questions'!$A:$J,10,0)&""
B11: PRE-FILLED - DO NOT ALTER | I11: ENTER A NUMBER 0 TO 5 | J11: DO NOT ALTER FORMULA
A12: City | B12: Applies? | C12: Act Name/Web name/Doc name | D12: Chapter | E12: Provision | F12: Clause | G12: Page Number | H12: Link | I12: Score | J12: Points (Auto-generate) | K12: SCORER COMMENTS
A13: Bengaluru – BWSSB | B13: YES | J13: =IF($B13="NO","NA",IF(I13="","",MIN(I13,$B$6)))
A14: Bengaluru – BMTC | B14: NO | J14: =IF($B14="NO","NA",IF(I14="","",MIN(I14,$B$6)))
A15: Bengaluru – BDA | B15: NO | J15: =IF($B15="NO","NA",IF(I15="","",MIN(I15,$B$6)))
A16: Bengaluru – BMRCL | B16: NO | J16: =IF($B16="NO","NA",IF(I16="","",MIN(I16,$B$6)))
A17: Bengaluru – BMRDA | B17: NO | J17: =IF($B17="NO","NA",IF(I17="","",MIN(I17,$B$6)))
A18: Surat – SUDA | B18: NO | J18: =IF($B18="NO","NA",IF(I18="","",MIN(I18,$B$6)))
A19: Surat – GMRC | B19: NO | J19: =IF($B19="NO","NA",IF(I19="","",MIN(I19,$B$6)))

Sheet UPD6a
A1: Question Code | B1: UPD6a | C1: <Sheet name and this code must match>
A2: Group | B2: =VLOOKUP($B$1,'PARASTATAL Questions'!$A:$J,3,0)&""
A3: Original ID | B3: =VLOOKUP($B$1,'PARASTATAL Questions'!$A:$J,2,0)&""
A4: MQ_SQ | B4: =VLOOKUP($B$1,'PARASTATAL Questions'!$A:$J,4,0)&""
A5: Question | B5: =VLOOKUP($B$1,'PARASTATAL Questions'!$A:$J,5,0)&""
A6: Max Score | B6: =VLOOKUP($B$1,'PARASTATAL Questions'!$A:$J,6,0)
A7: Assessment level | B7: =VLOOKUP($B$1,'PARASTATAL Questions'!$A:$J,7,0)&""
A8: Applicability | B8: =VLOOKUP($B$1,'PARASTATAL Questions'!$A:$J,8,0)&""
A9: Detailed Methodology | B9: =VLOOKUP($B$1,'PARASTATAL Questions'!$A:$J,9,0)&""
A10: Notes for scorers | B10: =VLOOKUP($B$1,'PARASTATAL Questions'!$A:$J,10,0)&""
B11: PRE-FILLED - DO NOT ALTER | I11: ENTER A NUMBER 0 TO 5 | J11: DO NOT ALTER FORMULA
A12: City | B12: Applies? | C12: Act Name/Web name/Doc name | D12: Chapter | E12: Provision | F12: Clause | G12: Page Number | H12: Link | I12: Score | J12: Points (Auto-generate) | K12: SCORER COMMENTS
A13: Bengaluru – BWSSB | B13: NO | J13: =IF($B13="NO","NA",IF(I13="","",MIN(I13,$B$6)))
A14: Bengaluru – BMTC | B14: YES | J14: =IF($B14="NO","NA",IF(I14="","",MIN(I14,$B$6)))
A15: Bengaluru – BDA | B15: NO | J15: =IF($B15="NO","NA",IF(I15="","",MIN(I15,$B$6)))
A16: Bengaluru – BMRCL | B16: NO | J16: =IF($B16="NO","NA",IF(I16="","",MIN(I16,$B$6)))
A17: Bengaluru – BMRDA | B17: NO | J17: =IF($B17="NO","NA",IF(I17="","",MIN(I17,$B$6)))
A18: Surat – SUDA | B18: NO | J18: =IF($B18="NO","NA",IF(I18="","",MIN(I18,$B$6)))
A19: Surat – GMRC | B19: NO | J19: =IF($B19="NO","NA",IF(I19="","",MIN(I19,$B$6)))

Sheet UPD6b
A1: Question Code | B1: UPD6b | C1: <Sheet name and this code must match>
A2: Group | B2: =VLOOKUP($B$1,'PARASTATAL Questions'!$A:$J,3,0)&""
A3: Original ID | B3: =VLOOKUP($B$1,'PARASTATAL Questions'!$A:$J,2,0)&""
A4: MQ_SQ | B4: =VLOOKUP($B$1,'PARASTATAL Questions'!$A:$J,4,0)&""
A5: Question | B5: =VLOOKUP($B$1,'PARASTATAL Questions'!$A:$J,5,0)&""
A6: Max Score | B6: =VLOOKUP($B$1,'PARASTATAL Questions'!$A:$J,6,0)
A7: Assessment level | B7: =VLOOKUP($B$1,'PARASTATAL Questions'!$A:$J,7,0)&""
A8: Applicability | B8: =VLOOKUP($B$1,'PARASTATAL Questions'!$A:$J,8,0)&""
A9: Detailed Methodology | B9: =VLOOKUP($B$1,'PARASTATAL Questions'!$A:$J,9,0)&""
A10: Notes for scorers | B10: =VLOOKUP($B$1,'PARASTATAL Questions'!$A:$J,10,0)&""
B11: PRE-FILLED - DO NOT ALTER | I11: ENTER A NUMBER 0 TO 5 | J11: DO NOT ALTER FORMULA
A12: City | B12: Applies? | C12: Act Name/Web name/Doc name | D12: Chapter | E12: Provision | F12: Clause | G12: Page Number | H12: Link | I12: Score | J12: Points (Auto-generate) | K12: SCORER COMMENTS
A13: Bengaluru – BWSSB | B13: NO | J13: =IF($B13="NO","NA",IF(I13="","",MIN(I13,$B$6)))
A14: Bengaluru – BMTC | B14: YES | J14: =IF($B14="NO","NA",IF(I14="","",MIN(I14,$B$6)))
A15: Bengaluru – BDA | B15: NO | J15: =IF($B15="NO","NA",IF(I15="","",MIN(I15,$B$6)))
A16: Bengaluru – BMRCL | B16: NO | J16: =IF($B16="NO","NA",IF(I16="","",MIN(I16,$B$6)))
A17: Bengaluru – BMRDA | B17: NO | J17: =IF($B17="NO","NA",IF(I17="","",MIN(I17,$B$6)))
A18: Surat – SUDA | B18: NO | J18: =IF($B18="NO","NA",IF(I18="","",MIN(I18,$B$6)))
A19: Surat – GMRC | B19: NO | J19: =IF($B19="NO","NA",IF(I19="","",MIN(I19,$B$6)))

Sheet DPG1a
A1: Question Code | B1: DPG1a | C1: <Sheet name and this code must match>
A2: Group | B2: =VLOOKUP($B$1,'PARASTATAL Questions'!$A:$J,3,0)&""
A3: Original ID | B3: =VLOOKUP($B$1,'PARASTATAL Questions'!$A:$J,2,0)&""
A4: MQ_SQ | B4: =VLOOKUP($B$1,'PARASTATAL Questions'!$A:$J,4,0)&""
A5: Question | B5: =VLOOKUP($B$1,'PARASTATAL Questions'!$A:$J,5,0)&""
A6: Max Score | B6: =VLOOKUP($B$1,'PARASTATAL Questions'!$A:$J,6,0)
A7: Assessment level | B7: =VLOOKUP($B$1,'PARASTATAL Questions'!$A:$J,7,0)&""
A8: Applicability | B8: =VLOOKUP($B$1,'PARASTATAL Questions'!$A:$J,8,0)&""
A9: Detailed Methodology | B9: =VLOOKUP($B$1,'PARASTATAL Questions'!$A:$J,9,0)&""
A10: Notes for scorers | B10: =VLOOKUP($B$1,'PARASTATAL Questions'!$A:$J,10,0)&""
B11: PRE-FILLED - DO NOT ALTER | I11: ENTER A NUMBER 0 TO 5 | J11: DO NOT ALTER FORMULA
A12: City | B12: Applies? | C12: Act Name/Web name/Doc name | D12: Chapter | E12: Provision | F12: Clause | G12: Page Number | H12: Link | I12: Score | J12: Points (Auto-generate) | K12: SCORER COMMENTS
A13: Bengaluru – BWSSB | B13: YES | J13: =IF($B13="NO","NA",IF(I13="","",MIN(I13,$B$6)))
A14: Bengaluru – BMTC | B14: YES | J14: =IF($B14="NO","NA",IF(I14="","",MIN(I14,$B$6)))
A15: Bengaluru – BDA | B15: YES | J15: =IF($B15="NO","NA",IF(I15="","",MIN(I15,$B$6)))
A16: Bengaluru – BMRCL | B16: YES | J16: =IF($B16="NO","NA",IF(I16="","",MIN(I16,$B$6)))
A17: Bengaluru – BMRDA | B17: YES | J17: =IF($B17="NO","NA",IF(I17="","",MIN(I17,$B$6)))
A18: Surat – SUDA | B18: YES | J18: =IF($B18="NO","NA",IF(I18="","",MIN(I18,$B$6)))
A19: Surat – GMRC | B19: YES | J19: =IF($B19="NO","NA",IF(I19="","",MIN(I19,$B$6)))

Sheet DPG1b
A1: Question Code | B1: DPG1b | C1: <Sheet name and this code must match>
A2: Group | B2: =VLOOKUP($B$1,'PARASTATAL Questions'!$A:$J,3,0)&""
A3: Original ID | B3: =VLOOKUP($B$1,'PARASTATAL Questions'!$A:$J,2,0)&""
A4: MQ_SQ | B4: =VLOOKUP($B$1,'PARASTATAL Questions'!$A:$J,4,0)&""
A5: Question | B5: =VLOOKUP($B$1,'PARASTATAL Questions'!$A:$J,5,0)&""
A6: Max Score | B6: =VLOOKUP($B$1,'PARASTATAL Questions'!$A:$J,6,0)
A7: Assessment level | B7: =VLOOKUP($B$1,'PARASTATAL Questions'!$A:$J,7,0)&""
A8: Applicability | B8: =VLOOKUP($B$1,'PARASTATAL Questions'!$A:$J,8,0)&""
A9: Detailed Methodology | B9: =VLOOKUP($B$1,'PARASTATAL Questions'!$A:$J,9,0)&""
A10: Notes for scorers | B10: =VLOOKUP($B$1,'PARASTATAL Questions'!$A:$J,10,0)&""
B11: PRE-FILLED - DO NOT ALTER | I11: ENTER A NUMBER 0 TO 5 | J11: DO NOT ALTER FORMULA
A12: City | B12: Applies? | C12: Act Name/Web name/Doc name | D12: Chapter | E12: Provision | F12: Clause | G12: Page Number | H12: Link | I12: Score | J12: Points (Auto-generate) | K12: SCORER COMMENTS
A13: Bengaluru – BWSSB | B13: YES | J13: =IF($B13="NO","NA",IF(I13="","",MIN(I13,$B$6)))
A14: Bengaluru – BMTC | B14: YES | J14: =IF($B14="NO","NA",IF(I14="","",MIN(I14,$B$6)))
A15: Bengaluru – BDA | B15: YES | J15: =IF($B15="NO","NA",IF(I15="","",MIN(I15,$B$6)))
A16: Bengaluru – BMRCL | B16: YES | J16: =IF($B16="NO","NA",IF(I16="","",MIN(I16,$B$6)))
A17: Bengaluru – BMRDA | B17: YES | J17: =IF($B17="NO","NA",IF(I17="","",MIN(I17,$B$6)))
A18: Surat – SUDA | B18: YES | J18: =IF($B18="NO","NA",IF(I18="","",MIN(I18,$B$6)))
A19: Surat – GMRC | B19: YES | J19: =IF($B19="NO","NA",IF(I19="","",MIN(I19,$B$6)))

Sheet DPG2a
A1: Question Code | B1: DPG2a | C1: <Sheet name and this code must match>
A2: Group | B2: =VLOOKUP($B$1,'PARASTATAL Questions'!$A:$J,3,0)&""
A3: Original ID | B3: =VLOOKUP($B$1,'PARASTATAL Questions'!$A:$J,2,0)&""
A4: MQ_SQ | B4: =VLOOKUP($B$1,'PARASTATAL Questions'!$A:$J,4,0)&""
A5: Question | B5: =VLOOKUP($B$1,'PARASTATAL Questions'!$A:$J,5,0)&""
A6: Max Score | B6: =VLOOKUP($B$1,'PARASTATAL Questions'!$A:$J,6,0)
A7: Assessment level | B7: =VLOOKUP($B$1,'PARASTATAL Questions'!$A:$J,7,0)&""
A8: Applicability | B8: =VLOOKUP($B$1,'PARASTATAL Questions'!$A:$J,8,0)&""
A9: Detailed Methodology | B9: =VLOOKUP($B$1,'PARASTATAL Questions'!$A:$J,9,0)&""
A10: Notes for scorers | B10: =VLOOKUP($B$1,'PARASTATAL Questions'!$A:$J,10,0)&""
B11: PRE-FILLED - DO NOT ALTER | I11: ENTER A NUMBER 0 TO 5 | J11: DO NOT ALTER FORMULA
A12: City | B12: Applies? | C12: Act Name/Web name/Doc name | D12: Chapter | E12: Provision | F12: Clause | G12: Page Number | H12: Link | I12: Score | J12: Points (Auto-generate) | K12: SCORER COMMENTS
A13: Bengaluru – BWSSB | B13: YES | J13: =IF($B13="NO","NA",IF(I13="","",MIN(I13,$B$6)))
A14: Bengaluru – BMTC | B14: YES | J14: =IF($B14="NO","NA",IF(I14="","",MIN(I14,$B$6)))
A15: Bengaluru – BDA | B15: YES | J15: =IF($B15="NO","NA",IF(I15="","",MIN(I15,$B$6)))
A16: Bengaluru – BMRCL | B16: YES | J16: =IF($B16="NO","NA",IF(I16="","",MIN(I16,$B$6)))
A17: Bengaluru – BMRDA | B17: YES | J17: =IF($B17="NO","NA",IF(I17="","",MIN(I17,$B$6)))
A18: Surat – SUDA | B18: YES | J18: =IF($B18="NO","NA",IF(I18="","",MIN(I18,$B$6)))
A19: Surat – GMRC | B19: YES | J19: =IF($B19="NO","NA",IF(I19="","",MIN(I19,$B$6)))

Sheet DPG2b
A1: Question Code | B1: DPG2b | C1: <Sheet name and this code must match>
A2: Group | B2: =VLOOKUP($B$1,'PARASTATAL Questions'!$A:$J,3,0)&""
A3: Original ID | B3: =VLOOKUP($B$1,'PARASTATAL Questions'!$A:$J,2,0)&""
A4: MQ_SQ | B4: =VLOOKUP($B$1,'PARASTATAL Questions'!$A:$J,4,0)&""
A5: Question | B5: =VLOOKUP($B$1,'PARASTATAL Questions'!$A:$J,5,0)&""
A6: Max Score | B6: =VLOOKUP($B$1,'PARASTATAL Questions'!$A:$J,6,0)
A7: Assessment level | B7: =VLOOKUP($B$1,'PARASTATAL Questions'!$A:$J,7,0)&""
A8: Applicability | B8: =VLOOKUP($B$1,'PARASTATAL Questions'!$A:$J,8,0)&""
A9: Detailed Methodology | B9: =VLOOKUP($B$1,'PARASTATAL Questions'!$A:$J,9,0)&""
A10: Notes for scorers | B10: =VLOOKUP($B$1,'PARASTATAL Questions'!$A:$J,10,0)&""
B11: PRE-FILLED - DO NOT ALTER | I11: ENTER A NUMBER 0 TO 5 | J11: DO NOT ALTER FORMULA
A12: City | B12: Applies? | C12: Act Name/Web name/Doc name | D12: Chapter | E12: Provision | F12: Clause | G12: Page Number | H12: Link | I12: Score | J12: Points (Auto-generate) | K12: SCORER COMMENTS
A13: Bengaluru – BWSSB | B13: YES | J13: =IF($B13="NO","NA",IF(I13="","",MIN(I13,$B$6)))
A14: Bengaluru – BMTC | B14: YES | J14: =IF($B14="NO","NA",IF(I14="","",MIN(I14,$B$6)))
A15: Bengaluru – BDA | B15: YES | J15: =IF($B15="NO","NA",IF(I15="","",MIN(I15,$B$6)))
A16: Bengaluru – BMRCL | B16: YES | J16: =IF($B16="NO","NA",IF(I16="","",MIN(I16,$B$6)))
A17: Bengaluru – BMRDA | B17: YES | J17: =IF($B17="NO","NA",IF(I17="","",MIN(I17,$B$6)))
A18: Surat – SUDA | B18: YES | J18: =IF($B18="NO","NA",IF(I18="","",MIN(I18,$B$6)))
A19: Surat – GMRC | B19: YES | J19: =IF($B19="NO","NA",IF(I19="","",MIN(I19,$B$6)))

Sheet DPG4
A1: Question Code | B1: DPG4 | C1: <Sheet name and this code must match>
A2: Group | B2: =VLOOKUP($B$1,'PARASTATAL Questions'!$A:$J,3,0)&""
A3: Original ID | B3: =VLOOKUP($B$1,'PARASTATAL Questions'!$A:$J,2,0)&""
A4: MQ_SQ | B4: =VLOOKUP($B$1,'PARASTATAL Questions'!$A:$J,4,0)&""
A5: Question | B5: =VLOOKUP($B$1,'PARASTATAL Questions'!$A:$J,5,0)&""
A6: Max Score | B6: =VLOOKUP($B$1,'PARASTATAL Questions'!$A:$J,6,0)
A7: Assessment level | B7: =VLOOKUP($B$1,'PARASTATAL Questions'!$A:$J,7,0)&""
A8: Applicability | B8: =VLOOKUP($B$1,'PARASTATAL Questions'!$A:$J,8,0)&""
A9: Detailed Methodology | B9: =VLOOKUP($B$1,'PARASTATAL Questions'!$A:$J,9,0)&""
A10: Notes for scorers | B10: =VLOOKUP($B$1,'PARASTATAL Questions'!$A:$J,10,0)&""
B11: PRE-FILLED - DO NOT ALTER | I11: ENTER A NUMBER 0 TO 10 | J11: DO NOT ALTER FORMULA
A12: City | B12: Applies? | C12: Act Name/Web name/Doc name | D12: Chapter | E12: Provision | F12: Clause | G12: Page Number | H12: Link | I12: Score | J12: Points (Auto-generate) | K12: SCORER COMMENTS
A13: Bengaluru – BWSSB | B13: YES | J13: =IF($B13="NO","NA",IF(I13="","",MIN(I13,$B$6)))
A14: Bengaluru – BMTC | B14: YES | J14: =IF($B14="NO","NA",IF(I14="","",MIN(I14,$B$6)))
A15: Bengaluru – BDA | B15: YES | J15: =IF($B15="NO","NA",IF(I15="","",MIN(I15,$B$6)))
A16: Bengaluru – BMRCL | B16: YES | J16: =IF($B16="NO","NA",IF(I16="","",MIN(I16,$B$6)))
A17: Bengaluru – BMRDA | B17: YES | J17: =IF($B17="NO","NA",IF(I17="","",MIN(I17,$B$6)))
A18: Surat – SUDA | B18: YES | J18: =IF($B18="NO","NA",IF(I18="","",MIN(I18,$B$6)))
A19: Surat – GMRC | B19: YES | J19: =IF($B19="NO","NA",IF(I19="","",MIN(I19,$B$6)))

Sheet DPG5a
A1: Question Code | B1: DPG5a | C1: <Sheet name and this code must match>
A2: Group | B2: =VLOOKUP($B$1,'PARASTATAL Questions'!$A:$J,3,0)&""
A3: Original ID | B3: =VLOOKUP($B$1,'PARASTATAL Questions'!$A:$J,2,0)&""
A4: MQ_SQ | B4: =VLOOKUP($B$1,'PARASTATAL Questions'!$A:$J,4,0)&""
A5: Question | B5: =VLOOKUP($B$1,'PARASTATAL Questions'!$A:$J,5,0)&""
A6: Max Score | B6: =VLOOKUP($B$1,'PARASTATAL Questions'!$A:$J,6,0)
A7: Assessment level | B7: =VLOOKUP($B$1,'PARASTATAL Questions'!$A:$J,7,0)&""
A8: Applicability | B8: =VLOOKUP($B$1,'PARASTATAL Questions'!$A:$J,8,0)&""
A9: Detailed Methodology | B9: =VLOOKUP($B$1,'PARASTATAL Questions'!$A:$J,9,0)&""
A10: Notes for scorers | B10: =VLOOKUP($B$1,'PARASTATAL Questions'!$A:$J,10,0)&""
B11: PRE-FILLED - DO NOT ALTER | I11: ENTER A NUMBER 0 TO 1 | J11: DO NOT ALTER FORMULA
A12: City | B12: Applies? | C12: Act Name/Web name/Doc name | D12: Chapter | E12: Provision | F12: Clause | G12: Page Number | H12: Link | I12: Score | J12: Points (Auto-generate) | K12: SCORER COMMENTS
