Workbook

Sheet UPD Questions_290926 
A1: S_No | B1: ASICS_2017_Report_Q_No | C1: ASICS 2023 Question number | D1: New City-Systems | E1: ASICS 2027_Report_Q No | F1: Group | G1: Thematic questions | H1: Sub-themes | I1: Question | J1: MQ_SQ | K1: Max Score | L1: Assessment level | M1: Detailed Methodology | N1: Notes for scorers
A2: 1 | B2: UPD1 | C2: UPD1 | D2: UPD | E2: UPD1 | F2: Planning | G2: Legal and institutional planning architecture | H2: State-level planning framework | I2: Is there a provision for a State Spatial Planning Board which is mandated with planning policies and reforms for the state? | J2: MQ | K2: 10 | L2: Law or Policy | M2: Part A - Check if the state Town and Country Planning (T&CP) act provides for a state-level town and country planning board/ spatial planning board or equivalent body with a 'Shall' provision. If yes, score 5. Where the law only enables the constitution of such a body (e.g., “the State Government may constitute”), additionally verify whether the body has actually been constituted through a government notification or order, or by checking the official website of the relevant State Government department or planning body. If yes, score 5. Part B - If Part A is scored as 'Yes', check whether the body has an explicit mandate to advise on or formulate state-level spatial planning policies and reforms. if yes, score 5. | N2: Please note that the name of the body need not be identical, provided its statutory functions correspond to the intent of the question.
A3: 2 | B3: UPD9 | C3: UPD6 | D3: UPD | E3: UPD2 | F3: Planning | G3: Legal and institutional planning architecture | H3: State-level planning framework | I3: Is there a provision for the establishment of Planning Authorities for notified new towns or special developments? | J3: MQ | K3: 10 | L3: Law or Policy | M3: Check if the T&CP Act has provisions for establishing a planning authority for new areas/towns notified. The state can also be considered, if the provision mandates the existing planning authority to develop a plan for the notified new area.
A4: 3 | B4: UPD2 | C4: UPD2 | D4: UPD | E4: UPD3 | F4: Planning | G4: Legal and institutional planning architecture | H4: Spatial planning hierarchy | I4: Does the Act require three levels of spatial plans for cities: Metropolitan/Regional, Municipal and Ward(s) /Local | J4: MQ | K4: 10 | L4: Law or Policy | M4: The T&CP Act should mandate three levels of spatial plans.
A5: 3a | B5: UPD2a | C5: UPD2a | D5: UPD | E5: UPD3a | F5: Planning | G5: Legal and institutional planning architecture | H5: Spatial planning hierarchy | I5: Metropolitan/ Regional Plan | J5: SQ | K5: 3.33 | L5: Law or Policy | M5: Check the T&CP/Metropolitan Planning Act for provisions that mandate the creation of a metropolitan/regional plan. Relevant metropolitan authority act/urban areas development authority act can also be considered for evidence. If the city is not a metropolitan, the act should mandate the creation of a regional plan.
A6: 3b | B6: UPD2b | C6: UPD2b | D6: UPD | E6: UPD3b | F6: Planning | G6: Legal and institutional planning architecture | H6: Spatial planning hierarchy | I6: Municipal/city plan | J6: SQ | K6: 3.33 | L6: Law or Policy | M6: Check the T&CP Act for provisions that mandate the creation of a municipal/city plan. Relevant urban areas development authority act can also be considered for evidence.
A7: 3c | B7: UPD2c | C7: UPD2c | D7: UPD | E7: UPD3c | F7: Planning | G7: Legal and institutional planning architecture | H7: Spatial planning hierarchy | I7: Ward(s)/local plan | J7: SQ | K7: 3.33 | L7: Law or Policy | M7: Check the T&CP Act for provisions that mandate the creation of a third tier of plan at the zone/ward level. Town planning schemes that are developed within the framework of the municipal/city plan shall not be considered. | N7: Note: Please capture in the comments if the mandate is for a zonal/ward/local area plan, mention the type.
A8: 4 | B8: UPD6 | C8: NA | D8: UPD | E8: UPD4 | F8: Planning | G8: Legal and institutional planning architecture | H8: Spatial planning hierarchy | I8: Is the planning boundary of the municipal/city plan aligned with political and administrative boundaries? | J8: MQ | K8: 10 | L8: Law or Policy | M8: Review the applicable municipal/city plan, its maps and/or the notification defining the planning area. Identify the ULG and administrative units used to define the planning area. First, compare the planning boundary with the ULG boundary. If the planning boundary is coterminous with the ULG boundary, score 10. Where the planning area extends beyond the ULG boundary, identify how the additional area has been defined in the plan or notification. The extension need not follow district boundaries. It may comprise whole gram panchayats, revenue villages, taluks/tehsils or other notified administrative/local-government units. The key test is whether existing units are included in their entirety rather than split by the planning boundary. For example: Entire ULG only = Score 10 Entire ULG + 10 complete Gram Panchayats = Score 10 Entire ULG + 15 complete revenue villages = Score 10 Entire ULG + 2 complete taluks = Score 10 ULG + only part of a Gram Panchayat/revenue village = Score 0 Planning boundary itself divides the ULG, leaving part of the ULG outside the plan = Score 0 Use the notification/text defining the planning area as the primary source. Refer to the plan map where necessary to verify the boundary. Do not assess whether the planning boundary is appropriate or whether it represents the functional urban region; assess only whether it aligns with identifiable political/local-government and administrative units. Score 10: The municipal/city plan boundary corresponds to the ULG boundary, or any area extending beyond the ULG is defined using whole administrative/local-government units. Score 0: The planning boundary bisects the ULG or other administrative/local-government units used to constitute the planning area.
A9: 5 | B9: UPD | C9: NA | D9: UPD | E9: UPD5 | F9: Planning | G9: Legal and institutional planning architecture | H9: Spatial planning hierarchy | I9: Is there a clear decentralised procedure for approvals of each level of plans? | J9: MQ | K9: 10 | L9: Law or Policy | M9: Check the state T&CP Act for provisions that delineate a decentralised plan approval process.
A10: 5a | B10: UPD | C10: NA | D10: UPD | E10: UPD5a | F10: Planning | G10: Legal and institutional planning architecture | H10: Spatial planning hierarchy | I10: Does the law mandate that the metropolitan/regional plan be approved by the state government? | J10: SQ | K10: 3.33 | L10: Law or Policy | M10: Check if the T&CP Act/metropolitan planning act mandates the metropolitan/regional plan to be approved by the state government.
A11: 5b | B11: UPD | C11: NA | D11: UPD | E11: UPD5b | F11: Planning | G11: Legal and institutional planning architecture | H11: Spatial planning hierarchy | I11: Does the law mandate that the municipal/city plan be approved by the MPC (Metropolitan Planning Committee) for metropolitan cities or by DPC (District Planning Committee) for non-metropolitan cities? | J11: SQ | K11: 3.33 | L11: Law or Policy | M11: Check if the T&CP Act mandates the municipal/city plans to be approved by the metropolitan planning committee in case of million plus cities and District Planning Committees in the case of non-metropolitan cities. In the case of states with no metropolitan cities, check if the municipal/city plan is to be approved by the state.
A12: 5c | B12: UPD | C12: NA | D12: UPD | E12: UPD5c | F12: Planning | G12: Legal and institutional planning architecture | H12: Spatial planning hierarchy | I12: Does the law mandate that the ward(s)/local plan be approved by the ULG? | J12: SQ | K12: 3.33 | L12: Law or Policy | M12: Check if the T&CP Act mandates the zonal/ward plans to be approved by the ULG.
A13: 6 | B13: UPD5 | C13: UPD4 | D13: UPD | E13: UPD6 | F13: Planning | G13: Legal and institutional planning architecture | H13: Objectives of each level of Municipal/City Plans | I13: Does the Act clearly define the objectives/contents of each level of spatial plan? | J13: MQ | K13: 10 | L13: Law or Policy | M13: Check the T&CP Act for provisions that detail the objectives and contents of each level of spatial plan. The Act should broadly mention what each level of spatial plan should cover. Score 3.33 each for the objectives and contents of - 1. Metropolitan/regional plan 2. Municipal/city plan 3. Ward(s)/local plan If the T&CP Act provides for all three, score 10.
A14: 7 | B14: UPD16 | C14: UPD9 | D14: UPD | E14: UPD7 | F14: Planning | G14: Legal and institutional planning architecture | H14: Metropolitan and district planning institutions | I14: Does the city have a functional MPC/DPC? | J14: MQ | K14: 10 | L14: Law/Policy & Implementation | M14: Sum of the sub-questions
A15: 7a | B15: UPD16a | C15: UPD9a | D15: UPD | E15: UPD7a | F15: Planning | G15: Legal and institutional planning architecture | H15: Metropolitan and district planning institutions | I15: Does the law provide for the constitution of an MPC/DPC? | J15: SQ | K15: 5 | L15: Law/Policy | M15: Part A: Check whether there is a mandate in the Municipal or T&CP Act for the constitution of MPC/DPC. If yes, score 2.5 Part B: Check whether the State has notified the rules for the MPC/DPC applicable to the city. If yes, score 2.5. MPC applies to metropolitan cities (46 cities); DPC applies for non-metropolitan cities
A16: 7b | B16: UPD16b | C16: UPD9b | D16: UPD | E16: UPD7b | F16: Planning | G16: Legal and institutional planning architecture | H16: Metropolitan and district planning institutions | I16: Have they met at least once in the past two years? | J16: SQ | K16: 5 | L16: Implementation | M16: Check whether the MPC/DPC has met at least once in the past two years. Score 5 where there is evidence of meeting in the last two years. Evidence: State UD/Municipal Administration department notifications/constitution orders/website; MPC/DPC meeting minutes, agendas or resolutions; MPC/DPC and metropolitan planning authority/development authority websites and RTIs.
A17: 8 | B17: NA | C17: NA | D17: UPD | E17: UPD8 | F17: Planning | G17: Legal and institutional planning architecture | H17: Metropolitan and district planning institutions | I17: Does the city (million-plus) have a Metropolitan Authority? | J17: MQ | K17: 10 | L17: Law or Policy | M17: Check if the state municipal and T&CP Act mandates a statutory metropolitan-level authority. For example the Greater Bengaluru Authority (GBA) under the Greater Bengaluru Governance Act, 2024. Score 10 where such a metropolitan authority has been established by law and constituted for the city. Note: The question is NA for non-metropolitan cities
A18: 9 | B18: UPD4 | C18: UPD3 | D18: UPD | E18: UPD9 | F18: Planning | G18: Municipal/City Plan preparation, participation and review | H18: Inter-agency participation | I18: Does the law mandate participation of all parastatals/ agencies /ULGs in creation of Spatial plans (metro/municipal/ward)? | J18: MQ | K18: 10 | L18: Law or Policy | M18: Check the T&CP Act for provisions that mandate the participation of all parastatals/agencies/ULGs in creation of spatial plans at all three levels with respect to its jurisdiction. The clause may either state verbatim "all parastatals/agencies/ULGs" or allude to their presence using other terminologies such as local bodies/relevant authorities. Check if the act mandates the constitution of an advisory council to advise the planning authorities on drawing up the plan. The advisory council should have representation from various civic agencies. Score 10 if there are such provisions, else, score 0.
A19: 10 | B19: UPD33 | C19: UPD18 | D19: UPD | E19: UPD10 | F19: Planning | G19: Municipal/City Plan preparation, participation and review | H19: Public participation and scrutiny | I19: Does the law mandate public participation in preparation of the municipal plan through Area Sabhas / Ward Sabhas and other means? | J19: MQ | K19: 10 | L19: Law or Policy | M19: Check if the T&CP Act mandates public participation in preparation of municipal/city plan through: Part A: Formal platforms such as ward committees and area sabhas. If yes, score 5. Part B: Other means* for municipal/city plan. If yes, score 5. *Even if the provision alludes to 'public participation/consultation or consolidation of suggestions and objections without specifying the mode for the same
... A31: 14 | B31: UPD3 | C31: NA | D31: UPD | E31: UPD14 | F31: Implementation | G31: Municipal/City Plan status, hierarchy and coordination | H31: Existence of Municipal/City Plans at each level | I31: Are the spatial plans at the Metropolitan/Regional, Municipal and Ward(s) /Local level notified? | J31: MQ | K31: 10 | L31: Implementation | M31: The existence of such a document or map should be notified in respective state gazettes
A32: 14a | B32: UPD3a | C32: NA | D32: UPD | E32: UPD14a | F32: Implementation | G32: Municipal/City Plan status, hierarchy and coordination | H32: Existence of Municipal/City Plans at each level | I32: Is there a Metropolitan/Regional Plan? | J32: SQ | K32: 3.33 | L32: Implementation | M32: Document should mention the words metropolitan/regional plan or any word that can be safely assumed to be a synonym for a metropolitan region. Check the website of the metro region development authority or urban development authority or ULB website. Score 3.33 if any of these apply, else, 0. | N32: Note: Please ensure an existence of a notified document of the plan. Maps alone will not make the cut
A33: 14b | B33: UPD3b | C33: NA | D33: UPD | E33: UPD14b | F33: Implementation | G33: Municipal/City Plan status, hierarchy and coordination | H33: Existence of Municipal/City Plans at each level | I33: Is there Municipal/City Plan? | J33: SQ | K33: 3.33 | L33: Implementation | M33: Document should mention the word municipal/development/city plan or municipal/city plan. Check the website of the urban development authority or ULG website or T&CP Dept. Score 3.33 if any of these apply, else, 0. | N33: Note: Please ensure an existence of a notified document of the plan. Maps alone will not make the cut
A34: 14c | B34: UPD3c | C34: NA | D34: UPD | E34: UPD14c | F34: Implementation | G34: Municipal/City Plan status, hierarchy and coordination | H34: Existence of Municipal/City Plans at each level | I34: Is there a Ward(s) /Local area/ neighbourhood Plan? | J34: SQ | K34: 3.33 | L34: Implementation | M34: Document should mention the word ward development plan/zonal plan/local area plan. This can exist as a standalone document or spatial plans or map. Score 3.33 if any of these apply, else, 0.
A35: 15 | B35: NA | C35: NA | D35: UPD | E35: UPD15 | F35: Implementation | G35: Municipal/City Plan status, hierarchy and coordination | H35: Validity of Municipal/City Plans | I35: Does the city have a municipal/city plan that is currently in force and within its prescribed validity period? | J35: MQ | K35: 10 | L35: Implementation | M35: Review the applicable municipal/ city plan to identify the valid period, and the gazette notification date of the current and immediately preceding municipal/city plan Score 10 — notified within the statutory period Score 0 — municipal/city plans that have lapsed and have not been replaced by a new municipal/city plan should be treated as ‘no municipal/city plans/inactive municipal/city plans. The scorer to capture in the scoring sheet the amount of time (in months) that has been passed since the end of the validity period
A36: 16 | B36: UPD7 | C36: NA | D36: UPD | E36: UPD16 | F36: Implementation | G36: Municipal/City Plan status, hierarchy and coordination | H36: Alignment across planning levels | I36: Are the spatial plans at the Metropolitan/Regional, Municipal and Ward(s) /Local level in a concurrent or nested timeline of validity? | J36: MQ | K36: 10 | L36: Implementation | M36: Check whether the validity periods of the metropolitan/regional, municipal/city, and ward/zonal/local area/neighbourhood-level spatial plans align, ensuring that lower-level plans do not extend beyond the metropolitan/regional plan's validity.
A37: 16a | B37: UPD7a | C37: NA | D37: UPD | E37: UPD16a | F37: Implementation | G37: Municipal/City Plan status, hierarchy and coordination | H37: Alignment across planning levels | I37: Is the Metropolitan/Regional plan in a concurrent or nested timeline of validity with municipal plan? | J37: SQ | K37: 5 | L37: Implementation | M37: Check whether the validity periods of the metropolitan/regional and municipal/city-level plans overlap and align, so that the municipal/city plan does not extend beyond the metropolitan/regional plan's validity. For example, if the metropolitan/regional plan is valid from 2001–2021, the municipal/city plan should not extend beyond 2021.
A38: 16b | B38: UPD7b | C38: NA | D38: UPD | E38: UPD16b | F38: Implementation | G38: Municipal/City Plan status, hierarchy and coordination | H38: Alignment across planning levels | I38: Is the Municipal municipal/city plan in a concurrent or nested timeline of validity with Ward municipal/city plan? | J38: SQ | K38: 5 | L38: Implementation | M38: Check whether the validity periods of the municipal/city municipal/city plan and ward/local-level plans overlap and are aligned, such that the validity of the ward/local-level plan does not extend beyond that of the municipal/city municipal/city plan. For example: if the municipal/city plan is valid from 2021–2041, the applicable ward/zonal/local-level plan should fall within and not extend beyond 2041.
A39: 17 | B39: UPD12 | C39: NA | D39: UPD | E39: UPD17 | F39: Implementation | G39: Municipal/City Plan status, hierarchy and coordination | H39: Inter-agency coordination and integration | I39: Do the municipal/city plans at each level, integrate the plans and priorities of various sectoral public departments and agencies? | J39: MQ | K39: 10 | L39: Implementation | M39: Check if creation of the municipal/city plan at each level involved creation of a committee/process for deliberation and decision making where all sectoral public departments and agencies were invited (at least water and sewerage, traffic, electricity, transport, health and education). Details of such delibrations can be available in the municipal/city plan, or as MoM / notes on the planning authority's website.
A40: 18 | B40: UPD27 | C40: NA | D40: UPD | E40: UPD18 | F40: Implementation | G40: Municipal/City Plan status, hierarchy and coordination | H40: Objectives of the Municipal/City Plan | I40: Does the municipal/city plan include objectives on jobs and economy? | J40: MQ | K40: 10 | L40: Implementation | M40: Check whether the municipal/city plan identifies key economic development priorities and provides measurable targets/outcomes for them. These may include: Increase in workforce participation. Number of jobs to be generated across economic sectors. Land identified/allocated for economic activities. Number/area of enterprises, industries or commercial activities to be facilitated. Provision of designated spaces/facilities for street vendors and other informal livelihoods. Score based on whether the municipal/city plan contains both: 1. A clearly stated objective or priority in the municipal/city plan relating to the city’s economy, employment or livelihoods. This could include job creation, workforce participation, industrial/commercial development, informal livelihoods, economic clusters, markets, tourism, or allocating land/infrastructure to support economic activity. 2. Quantifiable targets or outcome indicators to measure progress. Score 10: The municipal/city plan identifies clear economic development priorities and includes measurable/quantifiable targets or outcome indicators against which progress can be assessed. Score 5: The municipal/city plan identifies clear economic development priorities and proposed interventions/actions, but does not provide measurable targets/outcome indicators. Score 0: The municipal/city plan does not identify clear economic development priorities and associated interventions. General or aspirational references to economic development, employment, jobs or livelihoods without clearly identified priorities and interventions shall not be considered for scoring.
A41: 19 | B41: UPD28 | C41: NA | D41: UPD | E41: UPD19 | F41: Implementation | G41: Municipal/City Plan status, hierarchy and coordination | H41: Objectives of the Municipal/City Plan | I41: Does the municipal/city plan include objectives on environment and heritage conservation? | J41: MQ | K41: 10 | L41: Implementation | M41: Sum of the sub-questions below -
A42: 19a | B42: NA | C42: NA | D42: UPD | E42: UPD19a | F42: Implementation | G42: Municipal/City Plan status, hierarchy and coordination | H42: Objectives of the Municipal/City Plan | I42: a) Environmental Conservation | J42: SQ | K42: 5 | L42: Implementation | M42: Check whether the municipal/city plan identifies clear priorities, interventions and measurable targets/outcomes across the following two components: Natural Environment and Climate Resilience These may include: Protection, enhancement or increase of recreational and non-recreational green spaces, urban forests and natural habitats. Conservation, restoration or revival of lakes, wetlands and other water bodies. Protection of environmentally sensitive areas and natural assets through appropriate zoning, buffers or other development controls. Increase in green cover, afforestation or reforestation. Protection/restoration of biodiversity and ecologically significant areas. Reduction in air, water and soil pollution. Climate-change mitigation and adaptation, including reduction in greenhouse gas emissions. Promotion of renewable energy and clean technologies. Disaster-risk reduction and resilience of natural systems. For each component, score as follows: Score 5: The municipal/city plan identifies atleast 2 or more clear priorities and associated interventions/actions and provides measurable/quantifiable targets or outcome indicators. Score 2.5: The municipal/city plan identifies atleast 2 or more clear priorities and associated interventions/actions, but does not provide measurable targets/outcome indicators. Score 0: The component is absent, or is referred to only in general/aspirational terms without clearly identified priorities and associated interventions
A43: 19b | B43: NA | C43: NA | D43: UPD | E43: UPD19b | F43: Implementation | G43: Municipal/City Plan status, hierarchy and coordination | H43: Objectives of the Municipal/City Plan | I43: b) Heritage Conservation | J43: SQ | K43: 5 | L43: Implementation | M43: Check whether the municipal/city plan identifies clear priorities, interventions and measurable targets/outcomes across the following two components: Heritage Conservation These may include: Identification and protection of heritage buildings, precincts, sites and other heritage assets. Identification and protection of natural heritage and culturally significant landscapes. Conservation, restoration or adaptive reuse of heritage buildings/sites. Designation of heritage zones/precincts and appropriate development controls or buffer areas. Protection of the character and built form of heritage areas. Integration of heritage conservation with redevelopment and other development proposals. Measurable targets for conservation, restoration or protection of identified heritage assets/precincts. For each component, score as follows: Score 5: The municipal/city plan identifies atleast 2 or more clear priorities and associated interventions/actions and provides measurable/quantifiable targets or outcome indicators. Score 2.5: The municipal/city plan identifies atleast 2 or more clear priorities and associated interventions/actions, but does not provide measurable targets/outcme indicators. Score 0: The component is absent, or is referred to only in general/aspirational terms without clearly identified priorities and associated interventions.
A44: 20 | B44: UPD29 | C44: UPD 11f | D44: UPD | E44: UPD20 | F44: Implementation | G44: Municipal/City Plan status, hierarchy and coordination | H44: Objectives of the Municipal/City Plan | I44: Does the municipal/city plan include objectives on social development (health care, education)? | J44: MQ | K44: 10 | L44: Implementation | M44: Check whether the municipal/city plan identifies clear priorities, interventions and measurable targets/outcomes across the following three components:
A45: 20a | B45: NA | C45: NA | D45: UPD | E45: UPD20a | F45: Implementation | G45: Municipal/City Plan status, hierarchy and coordination | H45: Objectives of the Municipal/City Plan | I45: a) Education | J45: SQ | K45: 3.33 | L45: Implementation | M45: Education These may include: Coverage/accessibility of anganwadis and pre-primary facilities. Availability of schools relative to population/service standards. Accessibility of educational facilities, including for persons with disabilities. Other measurable education-related service or accessibility outcomes. For each component, score as follows: Score: 3.33 - The municipal/city plan identifies atleast two or more clear priorities and associated interventions/actions and provides measurable/quantifiable targets or outcome indicators. Score: 1.67 - If the municipal/city plan identifies atleast two or more clear priorities and associated interventions/actions, but does not provide measurable targets/outcome indicators. Score 0 if the component is absent, or is referred to only in general/aspirational terms without clearly identified priorities and associated interventions.
... A63: 24 | B63: UPD19 | C63: NA | D63: UPD | E63: UPD24 | F63: Implementation | G63: Sectoral planning | H63: Sustainability, resilience and climate action | I63: Does your city have a Sustainability/ Resilience Strategy/Climate Action Plan that clearly articulates development priorities, measurable objectives, and the roles and responsibilities of the ULG? | J63: MQ | K63: 10 | L63: Implementation | M63: NA
A64: 24a | B64: UPD19a | C64: NA | D64: UPD | E64: UPD24a | F64: Implementation | G64: Sectoral planning | H64: Sustainability, resilience and climate action | I64: Does the city have a notified and active Sustainability/Resilience Strategy? | J64: SQ | K64: 3.33 | L64: Implementation | M64: Check the municipal/city plan/ULB website/parastatal website/city website for the existence of a Climate Action Plan, City Resilience Strategy or Sustainability Strategy. The document must be formally adopted or approved by the competent authority (a ULG/Council resolution, a Government Order, or integration into the statutory municipal/city plan/DP) to be scored. A Disaster Management Plan may also be considered as evidence. If the plan/ strategy does exist score 3.33, or score 0 otherwise. Note: A draft document. Independent consultant's report/academic /NGO reports will not be considered. | N64: Note: Independent consultant's report/academic reports will not be considered.
A65: 24b | B65: UPD19b | C65: NA | D65: UPD | E65: UPD24b | F65: Implementation | G65: Sectoral planning | H65: Sustainability, resilience and climate action | I65: Does the plan have development priorities and measurable objectives? | J65: SQ | K65: 3.33 | L65: Implementation | M65: Check whether the climate action plan, city resilience strategy, sustainability strategy or disaster management plan identifies clear priorities and specifies measurable objectives or targets against those priorities, including quantitative or qualitative indicators, as appropriate. Examples may include greenhouse-gas emission reduction or net-zero targets; reduction in exposure to heat, flooding or other climate hazards; increase in green cover; flood-risk mitigation; water security; or other climate adaptation and resilience outcomes. A general statement of intent, such as becoming climate-resilient, sustainable or reducing emissions, without identifiable priorities and measurable objectives or targets, shall not qualify. Score 3.33 if the plan identifies atleast two or more clear priorities and includes measurable objectives or targets against those priorities; score 0 otherwise.
A66: 24c | B66: NA | C66: NA | D66: UPD | E66: UPD24c | F66: Implementation | G66: Sectoral planning | H66: Sustainability, resilience and climate action | I66: Does the plan clearly articulate the role of the ULG? | J66: SQ | K66: 3.33 | L66: Implementation | M66: Score 3.33 where the plan clearly articulates the role/responsibilities of the ULG in its preparation/implementation; score 0 otherwise.
A67: 25 | B67: UPD20 | C67: NA | D67: UPD | E67: UPD25 | F67: Implementation | G67: Sectoral planning | H67: Comprehensive mobility planning | I67: Does your city have a Comprehensive Mobility Plan that clearly articulates development priorities, measurable objectives, and the roles and responsibilities of the ULG? | J67: MQ | K67: 10 | L67: Implementation | M67: NA
A68: 25a | B68: NA | C68: NA | D68: UPD | E68: UPD25a | F68: Implementation | G68: Sectoral planning | H68: Comprehensive mobility planning | I68: Does the city have a notified and active Comprehensive Mobility Plan? | J68: SQ | K68: 3.33 | L68: Implementation | M68: Check the municipal/city plan/ULB website/parastatal website/UMTA or State transport department website for the existence of a Comprehensive Mobility Plan (CMP). The plan must be formally adopted or approved by the competent authority (approval by the UMTA where one exists, the State Government, or a Municipal Corporation/Council resolution) to be scored - a draft, a consultant's report or an unadopted study will not be considered. Check whether the city has a Comprehensive Mobility Plan (CMP) that has been formally adopted or approved by the competent authority, such as the UMTA, the Urban Development Department, Transport Department or the ULG/Council through a resolution. Sources may include the municipal/city plan, the ULB website, parastatal websites, and the UMTA or State Transport Department website. A draft CMP, a consultant's report, or an unadopted study, without evidence of formal adoption or approval, shall not qualify. Score 3.33 if the city has a CMP formally adopted or approved by the competent authority; score 0 otherwise.
A69: 25b | B69: NA | C69: NA | D69: UPD | E69: UPD25b | F69: Implementation | G69: Sectoral planning | H69: Comprehensive mobility planning | I69: Does the plan have development priorities and measurable objectives? | J69: SQ | K69: 3.33 | L69: Implementation | M69: Check whether the CMP identifies clear priorities and specifies measurable objectives or targets against those priorities, including quantitative or qualitative indicators, as appropriate. Examples may include a target mode share for sustainable modes (public transport, walking and cycling); targets for road safety or transport-related emissions; or actionable projects with measurable timelines, budget estimates and a phasing plan. A general statement of intent, such as improving mobility, promoting public transport or reducing congestion, without identifiable priorities and measurable objectives or targets, shall not qualify. Score 3.33 if the CMP identifies atleast two or more clear priorities and includes measurable objectives or targets against those priorities; score 0 otherwise.
A70: 25c | B70: NA | C70: NA | D70: UPD | E70: UPD25c | F70: Implementation | G70: Sectoral planning | H70: Comprehensive mobility planning | I70: Does the plan clearly articulate the role of the ULG? | J70: SQ | K70: 3.33 | L70: Implementation | M70: Check whether the CMP clearly articulates the roles and responsibilities of the Urban Local Government (ULG) in its preparation and/or implementation. Examples may include the ULG's participation in preparing the plan, such as membership of the steering or technical committee or a council resolution endorsing it; the assignment of specific projects, programmes or actions to the ULG; responsibilities for funding, execution, operation or maintenance of identified interventions; or the ULG's role in monitoring and reviewing the plan's progress. A passing mention of the ULG as a stakeholder, or a general reference to coordination among agencies, without specifying the ULG's role or responsibilities, shall not qualify. Score 3.3 if the CMP clearly articulates the roles and responsibilities of the ULG in its preparation and/or implementation; score 0 otherwise.
A71: 26 | B71: NA | C71: NA | D71: UPD | E71: UPD26 | F71: Implementation | G71: Sectoral planning | H71: Economic development planning | I71: Does your city have an Economic Vision Plan that clearly articulates development priorities, measurable objectives, and the roles and responsibilities of the ULG? | J71: MQ | K71: 10 | L71: Implementation | M71: NA
A72: 26a | B72: NA | C72: NA | D72: UPD | E72: UPD26a | F72: Implementation | G72: Sectoral planning | H72: Economic development planning | I72: Does the city have a notified and active Economic Vision Plan? | J72: SQ | K72: 3.33 | L72: Implementation | M72: Check the municipal/city plan, ULG website, relevant parastatal website, or city/district website for the existence of an Economic Vision, Economic Development Plan or equivalent city-level economic strategy. The document must: Be a final document; draft documents shall not be considered. Be formally adopted/approved by the competent authority, evidenced through a Municipal Corporation/Council resolution, Government Order, formal approval by the competent authority, or integration into the statutory municipal/city plan/Development Plan. Be currently active/applicable. Where the document specifies a validity or implementation period, the city must be within that period at the time of assessment. An expired or superseded plan shall not be considered. Independent consultant reports, academic studies/reports, background studies or other documents that have not been formally adopted/approved by the competent authority shall not be considered. Score 3.3 if the city has a final, formally adopted/approved and currently active/applicable Economic Vision, Economic Development Plan or equivalent city-level economic strategy that meets all the above conditions; score 0 otherwise.
A73: 26b | B73: NA | C73: NA | D73: UPD | E73: UPD26b | F73: Implementation | G73: Sectoral planning | H73: Economic development planning | I73: Does the plan have development priorities and measurable objectives? | J73: SQ | K73: 3.33 | L73: Implementation | M73: Check whether the plan identifies clear economic development priorities and specifies measurable objectives or targets against those priorities, including quantitative or qualitative indicators, as appropriate. Examples may include targets relating to employment/job creation, workforce participation, development of identified economic sectors or clusters, land/infrastructure provision for economic activities, enterprise development, or investment to be mobilised. A general statement of intent, such as making the city an economic hub, promoting economic growth or generating employment, without identifiable priorities and measurable objectives or targets, shall not qualify. Score 3.3 if the plan identifies atleast two or more clear economic development priorities and includes measurable objectives or targets against those priorities; score 0 otherwise.
A74: 26c | B74: NA | C74: NA | D74: UPD | E74: UPD26c | F74: Implementation | G74: Sectoral planning | H74: Economic development planning | I74: Does the plan clearly articulate the role of the ULG? | J74: SQ | K74: 3.33 | L74: Implementation | M74: Check whether the plan clearly assigns the ULG a defined role and/or specific responsibilities in implementation of the economic vision/strategy. This may include responsibility for facilitating economic development initiatives, providing enabling infrastructure, supporting livelihoods or enterprises, financing, implementing identified projects, monitoring progress against economic targets, or coordinating with relevant government departments, parastatals, and other agencies. A general reference to the ULG as a stakeholder, partner or participating institution, without identifiable responsibilities, shall not qualify. Score 3.3 where the plan clearly assigns the ULG defined roles and/or specific responsibilities in implementation; score 0 otherwise.
A75: 27 | B75: NA | C75: NA | D75: UPD | E75: UPD27 | F75: Implementation | G75: Specialised institutional capacity | H75: Specialised institutional capacity | I75: Does the city have adequate and representative professional town-planning capacity? | J75: MQ | K75: 10 | L75: Implementation | M75: Sum of the sub-questions below
A76: 27a | B76: NA | C76: NA | D76: UPD | E76: UPD27a | F76: Implementation | G76: Specialised institutional capacity | H76: Specialised institutional capacity | I76: Does the city have adequate professional town-planning capacity? | J76: SQ | K76: 5 | L76: Implementation | M76: Check the number of filled positions (against the sanctioned posts) of town/urban planners in the ULG and, where applicable, the Development/Planning Authority responsible for planning the city. Town planners per lakh population = (Filled qualified town planners in the ULG + filled qualified town planners attributable to the city in the Development/Planning Authority) ÷ Census 2011 population × 1,00,000 Cities assessed will receive a Score of 5. All other cities will be scored proportionately against this benchmark. Score = (Town planners per lakh population in the city ÷ Highest town planners per lakh population among cities assessed) × 5 For example, if the highest-performing city has 2 planners/lakh, a city with 1.5 planners/lakh scores 3.75, and one with 1 planner/lakh scores 2.5. | N76: Scorer comment - Record in the score sheet, separately for the ULG and Development/Planning Authority: total sanctioned town-planner positions; total filled positions; vacancies and vacancy rate; women and men among filled positions; and town planners per lakh population.
A77: 27b | B77: NA | C77: NA | D77: UPD | E77: UPD27b | F77: Implementation | G77: Specialised institutional capacity | H77: Specialised institutional capacity | I77: What proportion of the city's professional town-planning workforce is women? | J77: SQ | K77: 5 | L77: Implementation | M77: Compute women town planners as a proportion of the total filled qualified town-planner positions across the ULG and, where applicable, the Development/Planning Authority staff attributable to the city, using the latest available staffing data. % women town planners = (Number of women town planners ÷ Total filled qualified town-planner positions) × 100 Scoring bands: Score 5 — women constitute ≥33% of the professional town-planning workforce Score 2.5 — women constitute 15–32% Score 0 — women constitute <15% | N77: Note: Record, wherever available, the proportion of women among senior/decision-making town-planning positions.
A78: 28 | B78: NA | C78: NA | D78: UPD | E78: UPD28 | F78: Implementation | G78: Specialised institutional capacity | H78: Specialised institutional capacity | I78: Does the city have dedicated institutional cells/units for specialised functions? | J78: MQ | K78: 10 | L78: Implementation | M78: Score 10, assessed through 4 sub-questions of 2.5 each: an Urban Design Cell; a Climate Action/Sustainability/Disaster Management Cell; an Economic Development Cell; and a dedicated Women's Welfare/Development Cell
A79: 28a | B79: NA | C79: NA | D79: UPD | E79: UPD28a | F79: Implementation | G79: Specialised institutional capacity | H79: Urban design | I79: Does the city have an Urban Design Cell? | J79: SQ | K79: 2.5 | L79: Implementation | M79: Check the ULG website to determine whether the city has an Urban Design Cell/Unit/Vertical or equivalent. If this information is not available on the ULG website, evidence may be obtained from official government sources, credible media reports on the establishment/functioning of such a cell, or through RTI/official email requests. For towns with a population below five lakh, consider a shared Urban Design Cell/resource available to the city at the State or district level. Score 2.5 if there is evidence that an Urban Design Cell/Unit/Vertical exists, including a qualifying shared State/district-level resource for towns below five lakh; score 0 otherwise.
A80: 28b | B80: NA | C80: NA | D80: UPD | E80: UPD28b | F80: Implementation | G80: Does the city have dedicated institutional capacity to undertake specialised planning and development functions? | H80: Climate | I80: Does the city have a Climate Action/Sustainability/Disaster Management Cell? | J80: SQ | K80: 2.5 | L80: Implementation | M80: Check the ULG website to determine whether the city has a climate action, sustainability, resilience and/or disaster management cell/unit/vertical or equivalent. If this information is not available on the ULG website, you may obtain evidence from official government sources, credible media reports on the establishment/functioning of such a cell, or RTI/official email requests. For towns with a population below five lakh, consider a shared climate action/sustainability/disaster management cell or resource available to the city at the state or district level. Score 2.5 if there is evidence that such a cell/unit/vertical exists and is functional for the city, including a qualifying shared state/district-level resource for towns below five lakh; score 0 otherwise.
A81: 28c | B81: NA | C81: NA | D81: UPD | E81: UPD28c | F81: Implementation | G81: Does the city have dedicated institutional capacity to undertake specialised planning and development functions? | H81: Economic development | I81: Does the city have an Economic Develepment Cell ? | J81: SQ | K81: 2.5 | L81: Implementation | M81: Check the ULG website to determine whether the city has an economic development cell/unit/vertical or equivalent. If this information is not available on the ULG website, evidence may be obtained from official government sources, credible media reports on the establishment/functioning of such a cell, or through RTI/official email requests. Score 2.5 if there is evidence that an economic development cell/unit/vertical exists and is functional for the city; score 0 otherwise. Applicability: this indicator is applicable only to million-plus cities (population of 10 lakh or more). For all other cities, score NA.
A82: 28d | B82: NA | C82: NA | D82: UPD | E82: UPD28d | F82: Implementation | G82: Does the city have dedicated institutional capacity to undertake specialised planning and development functions? | H82: Women's welfare or development | I82: Does the city have a dedicated Women's Welfare/Development Cell? | J82: SQ | K82: 2.5 | L82: Implementation | M82: Check the ULG website to determine whether the city has a dedicated women’s welfare/development cell/unit/vertical or equivalent. If this information is not available on the ULG website, evidence may be obtained from official government sources, credible media reports on the establishment/functioning of such a cell, or through RTI/official email requests. Score 2.5 if there is evidence that a dedicated women’s welfare/development cell/unit/vertical exists and is functional for the city; score 0 otherwise. Applicability: This indicator is applicable only to million-plus cities. For all non-million-plus cities, score NA.
A83: 29 | B83: UPD23 | C83: UPD12 | D83: UPD | E83: UPD29 | F83: Implementation | G83: Urban design, accessibility and parking | H83: Urban design standards and universal accessibility | I83: Are there prescribed urban design standards to guide the execution of urban projects, including standards for universal accessibility? | J83: MQ | K83: 10 | L83: Law or Policy | M83: Sum of the sub-questions below
A84: 29a | B84: NA | C84: NA | D84: UPD | E84: UPD29a | F84: Implementation | G84: Urban design, accessibility and parking | H84: Urban design standards and universal accessibility | I84: Does the law mandate comprehensive urban design standards and universal accessibility? | J84: SQ | K84: 5 | L84: Law or Policy | M84: Check whether the applicable T&CP Act or Municipal Act provides for urban design standards/guidelines for the planning, design or execution of urban development across the following four categories: 1. Roads and streetscapes – including different categories/hierarchies of urban roads. 2. Footpaths/pedestrian infrastructure. 3. Underground public utilities – including water supply, sewerage, storm-water drainage, electricity, telecommunications/internet and gas. 4. Buit form based codes - build to line, minimum frontage, floor heights, building material etc. 5. Universal accessibility For each of the five categories, check whether the applicable law mandates or enables urban design standards/guidelines for the planning, design or execution of urban development. For each category, score as follows: Score 1: Where the law uses mandatory language (e.g., “shall”) requiring the preparation, prescription, adoption or application of urban design standards/guidelines. Score 0.5: Where the law uses enabling/discretionary language (e.g., “may”) permitting the preparation, prescription, adoption or application of such standards/guidelines. Score 0: Where there is no such provision. Maximum score: 5 points (5 categories × 1 point). A general power to regulate development, without a specific provision for relevant design standards/guidelines, shall not qualify.
A85: 29b | B85: NA | C85: NA | D85: UPD | E85: UPD29b | F85: Implementation | G85: Urban design, accessibility and parking | H85: Urban design standards and universal accessibility | I85: Does the city have urban design standards to guide the execution of urban projects? | J85: SQ | K85: 5 | L85: Implementation | M85: Check whether the city has adopted/notified urban design standards or guidelines for the planning, design or execution of urban development across the following five categories: 1. Roads and streetscapes – including different categories/hierarchies of urban roads. 2. Footpaths/pedestrian infrastructure. 3. Underground public utilities – including water supply, sewerage, storm-water drainage, electricity, telecommunications/internet and gas. 4. Buit form based codes - build to line, minimum frontage, floor heights, building material etc. 5. Universal accessibility Check the ULG website, Development Authority website, Urban Development Department website, Department of Urban Land Transport / Unified Metropolitan Transport Authority or equivalent specialised agency website for evidence of such standards/guidelines. For categories (a)–(c), the standards may be contained in a standalone urban/street design guideline or other formally adopted/notified city-level document. Evidence on an official website that the city has formally adopted an identified set of standards/guidelines may also be considered. For residential and commercial buildings (categories (d) and (e)), standards contained in the applicable DCRs/building bye-laws or equivalent regulations may also be considered. These may include urban design requirements relating to building frontage/interface with the street, signage, façade treatment, building materials, or other design controls applicable to residential or commercial development. For each category, there must be evidence that the standards/guidelines are applicable to or adopted for the city. Mere reference to national/model guidelines or standards, without evidence of their adoption or application by the city, shall not qualify. Scoring: Award 1 point for each category for which applicable urban design standards/guidelines have been adopted/notified (5 categories × 1 = 5); score 0 for a category where no such standards/guidelines
A86: 30 | B86: NA | C86: NA | D86: UPD | E86: UPD30 | F86: Implementation | G86: Urban design, accessibility and parking | H86: Parking policy | I86: Does the city have a parking policy? | J86: MQ | K86: 10 | L86: Implementation | M86: Sum of the sub-questions below
A87: 30a | B87: NA | C87: NA | D87: UPD | E87: UPD30a | F87: Implementation | G87: Urban design, accessibility and parking | H87: Parking policy | I87: Is there a clear mandate in the law for a parking policy? | J87: SQ | K87: 5 | L87: Law or Policy | M87: Check whether the applicable T&CP Act or Municipal Act mandates the ULG to prepare and/or adopt a standalone parking policy or parking management policy. A general provision prescribing parking standards for individual buildings/developments, or empowering the ULG to regulate parking, shall not qualify. The law must specifically provide for the preparation/adoption of a city-level parking policy. Distinguish between mandatory and enabling provisions: Score 5 where the law uses mandatory language (e.g., “shall”) requiring the ULG/city to prepare or adopt a standalone Parking Policy/Parking Management Policy. Score 2.5 where the law uses enabling/discretionary language (e.g., “may”) permitting the ULG/city to prepare or adopt such a policy. Score 0 where there is no such statutory provision.
A88: 30b | B88: NA | C88: NA | D88: UPD | E88: UPD30b | F88: Implementation | G88: Urban design, accessibility and parking | H88: Parking policy | I88: Has the parking policy been implemented? | J88: SQ | K88: 5 | L88: Implementation | M88: Check whether a city-level parking policy exists, regardless of whether a legal mandate requires the city to prepare one. Check the websites of the ULG, state urban/transport department, UMTA/ DULT or equivalent competent authority for the policy document. Where the policy document is not available on an official website, check credible media reports to establish whether the city has formally adopted a parking policy. Score 5 if a city-level parking policy exists or its formal adoption can be established through reliable evidence. Score 0 otherwise. | N88: Note: Score this question independently of the legal mandate. A city may score 5 on this question even where there is no legal mandate for a parking policy.
A89: 31 | B89: NA | C89: NA | D89: UPD | E89: UPD31 | F89: Implementation | G89: Development Control Regulations and land-management instruments | H89: Applicability and currency of DCRs | I89: Does the city have a city-specific Development Control Regulation (DCR)? | J89: MQ | K89: 10 | L89: Law or Policy & Implementation | M89: Check the applicable DCR to determine whether a city-specific DCR applies. Evidence can be present on the websites of the ULG/Development Authority/T&CP/UDD Department. Score 10 — A city-specific DCR is applicable to the city. Score 0 — The city relies on a generic/state-wide DCR and does not have a city-specific DCR. NA — City has a population below one million. Note to scorer: For cities with a population below one million, mark this question as NA. However, record in the scorer comments the DCR applicable to the city and its status, including whether the city is governed by a city-specific DCR or a generic/state-wide DCR.
A90: 32 | B90: NA | C90: NA | D90: UPD | E90: UPD32 | F90: Implementation | G90: Development Control Regulations and land-management instruments | H90: DCR revision and public consultation | I90: Does the city’s DCR provide development controls, standards or incentives that enable positive economic, environmental, public health, heritage, and inclusion outcomes? | J90: MQ | K90: 10 | L90: Law or Policy | M90: For each dimension, assess whether the DCR contains specific development controls, standards, relaxations, permissions or incentives that enable or promote the identified outcome. A provision need not provide a financial incentive to qualify. Enabling provisions may include, for example, additional FAR/FSI, relaxation of setbacks/parking/plot-size requirements, flexible or mixed-use permissions, density incentives, transferable development rights, simplified development standards, adaptive reuse permissions, inclusionary requirements, or specific design/development standards that facilitate the intended outcome. Total score = sum of the five sub-question scores (2*5=10).
A91: 32a | B91: NA | C91: NA | D91: UPD | E91: UPD32a | F91: Implementation | G91: Development Control Regulations and land-management instruments | H91: DCR revision and public consultation | I91: Do the DCRs provide development controls, standards or incentives that enable different types and scales of economic activity? | J91: SQ | K91: 2 | L91: Law or Policy | M91: Review whether the DCR enables economic activities of different types and scales through the regulation of land use, mixed use, permissible activities, development intensity and development standards. Look particularly for provisions that enable MSMEs/small enterprises, home-based economic activities, commercial activity, mixed-use development, markets/street vending, industrial or productive uses, and specialised economic districts, including through relaxed or differentiated requirements relating to plot size, FAR/FSI, setbacks, parking, access or other development standards. Score 2: Specific provisions enable or incentivise two or more types/scales of economic activity, beyond merely designating land for commercial/industrial use. Score 1: Two or more Economic activities are provided for through conventional land-use zoning/permissible-use provisions, but no specific enabling or incentivising development provision is found. Score 0: No relevant provision addressing economic activity is found. (For example: Just mentioning zoning an area as commercial will get a score of 1, whereas enabling mixed use, home enterprises, MSMEs, flexible use categories, reduced parking/plot requirements, or other provisions specifically facilitating economic activity) Keywords for scorer: mixed use; mixed-use; commercial; commerce; shop; retail; market; vendor; street vending; hawker; home occupation; home-based; cottage industry; household industry; MSME; small enterprise; micro enterprise; industrial; productive use; work-live; special economic; business district; FAR; FSI; parking relaxation; permissible use.
A92: 32b | D92: UPD | E92: UPD32b | F92: Implementation | G92: Development Control Regulations and land-management instruments | H92: DCR revision and public consultation | I92: Do the DCRs provide development controls, standards or incentives that improve access, safety, affordability and development outcomes for women and the urban poor? | J92: SQ | K92: 2 | L92: Law or Policy | M92: Check whether development regulation contains specific controls, standards, relaxations or incentives addressing the needs of women and the urban poor. For the urban poor, check for provisions enabling or incentivising EWS/LIG or affordable housing, inclusionary housing, slum redevelopment/upgradation, in-situ redevelopment, incremental housing or other affordable housing options through measures such as additional FAR/FSI, density incentives, reduced plot-size/setback/parking requirements, reservation of dwelling units or built-up area, cross-subsidy, TDR or other regulatory flexibility. For women, check for development/design provisions specifically addressing women's safety, accessibility and use of buildings and public spaces, such as gender-responsive design standards, requirements relating to safe access, lighting/visibility, sanitation/facilities for women, childcare facilities, or other provisions explicitly addressing women's needs. Score 2: Atleast two or more specific development controls, standards, relaxations or incentives addressing both women and the urban poor are provided. Score 1: Specific development controls, standards, relaxations or incentives addressing either women or the urban poor, but not both, are mentioned in atleast two or more provisions. Score 0: No specific development provision addressing either women or the urban poor is found. Note: General provisions applicable to all developments or users should not be counted unless they specifically address the needs of women or the urban poor. Similarly, merely referring to EWS/LIG housing or women's safety without prescribing a corresponding development control, standard, requirement, relaxation or incentive should not qualify. For example: Additional FAR/FSI or relaxed development standards for EWS/affordable housing would qualify as a provision for the urban poor. Specific design requirements addressing women's safety or access would qualify as a provision for women. Keywords for scorer: Urban poor: EWS; LIG; economically weaker section; low income; affordable housing; inclusionary housing; inclusive housing; social housing; slum; slum rehabilitation; slum redevelopment; in-situ; incremental housing; small dwelling; small plot; density bonus; FAR; FSI; TDR; cross subsidy; development standards; relaxation. Women: women; woman; female; gender; gender responsive; gender sensitive; women safety; safety; safe access; lighting; visibility; toilet for women; female toilet; sanitary facility; childcare; crèche; public space; public realm. | N92: Note: Please capture the text that mentions the broad provisions related to the theme and the incentives it offers clearly
A93: 32c | D93: UPD | E93: UPD32c | F93: Implementation | G93: Development Control Regulations and land-management instruments | H93: DCR revision and public consultation | I93: Do the DCRs provide development controls, standards or incentives that promote environmental sustainability and climate resilience? | J93: SQ | K93: 2 | L93: Law or Policy | M93: Check whether development regulation promotes environmentally sustainable or climate-resilient development, including through standards, incentives, or enabling provisions relating to green buildings, energy efficiency, water conservation, permeability, green cover, rainwater management, heat mitigation, flood resilience, or development appropriate to environmentally sensitive areas. Score 2: Specific controls, standards or incentives actively promote environmental sustainability or climate resilience. Score 1: The DCR protects environmentally sensitive/climate-vulnerable areas or imposes environmental restrictions, but does not contain a clear enabling/incentive provision. Score 0 — No relevant environmental or climate-related development provision is found. Note: A generic requirement to obtain environmental clearance based on project size does not, by itself, qualify as an enabling environmental/climate provision. For example: Prohibiting construction within a lake buffer will score 1, whereas permeability/green-cover standards, incentives for green buildings, resilience-oriented development standards, and additional benefits for achieving specified environmental outcomes will score 2 Keywords for scorer: environment; climate; resilience; green building; green rating; GRIHA; IGBC; LEED; energy efficiency; solar; renewable energy; rainwater harvesting; stormwater; flood; floodplain; wetland; water body; lake; buffer; coastal; CRZ; groundwater; recharge; permeability; pervious; green cover; tree cover; open space; heat; cool roof; sustainable; FAR incentive; FSI incentive. | N93: Note: Capture the text that mentions the broad provisions related to the theme and the incentives it offers
A94: 32d | D94: UPD | E94: UPD32d | F94: Implementation | G94: Development Control Regulations and land-management instruments | H94: DCR revision and public consultation | I94: Do the DCRs provide development controls or standards that promote positive public-health outcomes? | J94: SQ | K94: 2 | L94: Law or Policy | M94: Check whether development regulation promotes positive public-health outcomes through controls, standards or enabling provisions relating to ventilation and natural light, sanitation, overcrowding/density, separation of hazardous or incompatible uses, buffers from polluting activities, or other health-related spatial risks. Score 2: Specific development controls or standards actively promote positive public-health outcomes beyond routine minimum building requirements are mentioned in two or more places. Score 1: The DCR/building regulations prescribe basic or minimum requirements relating to ventilation/light, sanitation, density, hazardous uses or separation from polluting activities, but do not contain additional provisions aimed at improving public-health outcomes. Identify atleast two or more such provisions. Score 0: No relevant development control or standard addressing public-health-related spatial risks is found. Note: Routine building requirements that establish minimum standards for individual buildings should not, by themselves, receive Score 2. Award the full score where development regulation goes beyond these basic requirements to address a broader public-health outcome or spatial risk. For example: A general requirement prescribing minimum window area or provision of toilets for buildings will score 1, whereas specific controls addressing overcrowding, density in relation to health, buffers/separation distances from hazardous or polluting uses, enhanced ventilation/light standards for identified contexts, or other development standards explicitly addressing health-related spatial risks will score 2. Keywords for scorer: public health; health; sanitation; ventilation; natural ventilation; light; natural light; lighting; overcrowding; density; occupancy; hazardous use; hazardous industry; noxious; polluting; pollution; buffer; buffer zone; separation distance; setback; incompatible use; industrial use; industrial hazard; waste; solid waste; sewerage; toilet; latrine; open space; health hazard. | N94: Note: Please capture the text that mentions the broad provisions related to the theme and the incentives it offers clearly
A95: 32e | D95: UPD | E95: UPD32e | F95: Implementation | G95: Development Control Regulations and land-management instruments | H95: DCR revision and public consultation | I95: Do the DCRs provide development controls, standards or incentives that enable the conservation and adaptive reuse of heritage buildings, precincts or historic areas? | J95: SQ | K95: 2 | L95: Law or Policy | M95: Check whether development regulation enables or incentivises the conservation, restoration, continued use or adaptive reuse of heritage buildings, precincts or historic areas, including through transferable development rights (TDR), additional/transferable FAR or FSI, relaxation of setbacks or parking requirements, permission for compatible alternative uses, adaptive reuse provisions, financial/development incentives, or other regulatory flexibility linked to heritage conservation. Score 2: Specific controls, standards, relaxations or incentives actively enable or incentivise conservation, restoration, continued use or adaptive reuse of heritage buildings/areas are mentioned in atleast two or more such provisions. Score 1: The DCR protects heritage buildings/areas through restrictions or approval requirements. For example, restrictions on demolition, alteration, height, façade or development within heritage precincts, but does not contain provisions that actively enable or incentivise conservation or adaptive reuse. Identify atleast two or more such provisions. Score 0: No heritage-specific development control, standard or incentive is found. Note: Merely identifying/listing heritage buildings or requiring permission from a heritage conservation committee or other authority does not qualify for score 2 unless the DCR also provides an enabling or incentivising development provision. For example: Requiring heritage committee approval before alteration/demolition will score 1, whereas permitting adaptive reuse, granting TDR/development rights, allowing compatible alternative uses, or relaxing parking/setback requirements to facilitate conservation will score 2. Keywords for scorer: heritage; heritage building; listed building; heritage precinct; historic; historic core; conservation; preservation; restoration; adaptive reuse; reuse; change of use; alternative use; special character; heritage committee; demolition; alteration; façade; TDR; transferable development rights; FAR; FSI; incentive; parking relaxation; setback relaxation. | N95: Note: Please capture the text that mentions the broad provisions related to the theme and the incentives it offers clearly
A96: 33 | B96: UPD17 | C96: UPD10 | D96: UPD | E96: UPD33 | F96: Implementation | G96: Development Control Regulations and land-management instruments | H96: Green-building incentives | I96: Does the city have a mandate to provide incentives for green buildings, and are these incentives operationalised? | J96: MQ | K96: 10 | L96: Law or Policy & Implementation | M96: Sum of the sub-questions below
A97: 33a | B97: NA | C97: NA | D97: UPD | E97: UPD33a | F97: Implementation | G97: Development Control Regulations and land-management instruments | H97: Green-building incentives | I97: Does the law mandate incentives for green buildings ? | J97: SQ | K97: 5 | L97: Law or Policy | M97: Check the applicable T&CP Act and Municipal Act for a provision mandating or enabling the provision of incentives for green buildings. The Act need not specify the nature or quantum of the incentive; a clear statutory provision requiring or enabling green-building incentives is sufficient. Where specified, incentives may include additional FAR/FSI, property-tax rebates, fee/development-charge concessions, or other fiscal or development-control incentives. Score 5 if the Act provides a clear mandate or enabling provision for green-building incentives, even if the specific incentives are to be prescribed subsequently through rules, regulations or other instruments. Score 0 otherwise.
A98: 33b | B98: NA | C98: NA | D98: UPD | E98: UPD33b | F98: Implementation | G98: Development Control Regulations and land-management instruments | H98: Green-building incentives | I98: Does your city give incentives for green buildings ? | J98: SQ | K98: 5 | L98: Implementation | M98: Check the applicable municipal/city plan, DCR, ULG or state government (UDD/Energy) website for evidence of any incentives provided for green buildings in the city. Also check the Indian Green Building Council (IGBC), Green Rating for Integrated Habitat Assessment (GRIHA), and Leadership in Energy and Environmental Design (LEED) websites as secondary sources for state government/ULG incentives linked to green-building ratings. Reliable media reports may also be considered. Incentives may include additional FAR/FSI, rebates in property tax, building-permission fees or development charges, or other fiscal or development-control incentives. Score 5 if at least one green-building incentive is operational in the city, based on an official source or reliable secondary evidence. Score 0 if no such incentive can be established.
A99: 34 | B99: UPD24 | C99: UPD13 | D99: UPD | E99: UPD34 | F99: Implementation | G99: Development Control Regulations and land-management instruments | H99: Land-management instruments | I99: Does the law enable a guaranteed land titling system ? | J99: MQ | K99: 10 | L99: Law or Policy | M99: Part A – Legal/Policy Provision Check whether the State has enacted a land titling law providing for certification/guarantee of land titles; or issued a Government Order/circular/notification establishing a framework for certification of land titles. A general land-record digitisation, mutation or property-registration framework shall not qualify unless it specifically provides for certification/guarantee of title. Part B – Operationalisation Where the framework is provided through an Act, check whether the rules/regulations necessary to operationalise the land titling framework have been notified. Scoring: Score 10: Land titling is provided through an Act and the necessary rules/regulations have been notified; OR an applicable Government Order/circular/notification establishes an operational framework that does not require separate rules. Score 5: A land titling Act has been enacted, but the necessary rules/regulations have not been notified. Score 0: No land titling law or applicable Government Order/circular/notification exists.
A100: 35 | B100: UPD25 | C100: UPD14 | D100: UPD | E100: UPD35 | F100: Implementation | G100: Development Control Regulations and land-management instruments | H100: Land-management instruments | I100: Does the law enable a guaranteed land pooling system ? | J100: MQ | K100: 10 | L100: Law or Policy | M100: Part A – Legal/Policy Provision Check whether the State has enacted legislation or issued a Government Order/circular/notification providing for a land assembly/reconstitution mechanism such as: a. Town Planning Scheme (TPS)/land reconstitution; or b. Land pooling. Score 5 if at least one such mechanism is formally provided for through legislation or an applicable Government Order/circular/notification. Score 0 otherwise. Part B – Operationalisation Where the mechanism is provided for through an Act, check whether the rules/regulations necessary to operationalise the mechanism have been notified. Score 5 if the rules/regulations necessary for implementation of the mechanism have been notified and are currently in force. Score 0 if the enabling provision exists but the necessary rules/regulations have not been notified. | N100: Note: Record separately whether the applicable mechanism is TPS/land reconstitution, land pooling, or both.
A101: 36 | B101: UPD26 | C101: NA | D101: UPD | E101: UPD36 | F101: Implementation | G101: Development Compliance | H101: Development approvals | I101: Does your city have a single window clearance process in place for development projects that are in conformity with municipal/city plans? | J101: MQ | K101: 10 | L101: Implementation | M101: Check for the existence of an online portal / platform that acts as a one-stop solution for filing complete application for development projects (education, health, affordable housing) and provides option for tracking status of application. Score 10 if any 2 out of the 3 project types are available on the portal/platform/DA Website
A102: 37 | B102: UPD30 | C102: UPD15 | D102: UPD | E102: UPD37 | F102: Enforcement | G102: Development Compliance | H102: Development approvals | I102: Is there an effective system to prevent approval of plans that are not in conformity with municipal/city plan? | J102: MQ | K102: 10 | L102: Law or Policy/Implementation | M102: Check whether there is a system with all of the following aspects: 1. An approval authority for projects at each level, as defined under the T&CP Act or allied Act and/or the MPC Act 2. A defined process for rejection and/or variance approvals for plans that are not in conformity with the SDP, as provided under the T&CP Act or allied Act and/or the MPC Act 3. A registry of public projects (bus terminals, metro stations, railway stations, protected heritage buildings) and private projects. Evidence can be present on ULG/Development Authority websites 4. Disclosure of all approvals, denials and variance approvals in the public domain. Evidence can be present on ULG/Development Authority websites Score 10 only if all four of the above aspects are met Score 0 otherwise.
A103: 38 | B103: UPD31 | C103: UPD16 | D103: UPD | E103: UPD38 | F103: Enforcement | G103: Development Compliance | H103: Construction monitoring | I103: Does the law mandate mechanisms for monitoring ongoing construction/development projects for compliance with approved plans and permissions? | J103: MQ | K103: 10 | L103: Implementation | M103: Sum of the sub-questions below
A104: 38a | B104: NA | C104: NA | D104: UPD | E104: UPD38a | F104: Enforcement | G104: Development Compliance | H104: Construction monitoring | I104: Does the law mandate a system for monitoring ongoing construction/projects for possible violations? | J104: SQ | K104: 5 | L104: Implementation | M104: Check the applicable T&CP Act or the allied Act, and Municipal Act for provisions for the following: 1. Authority to inspect ongoing construction/projects. 2. Stage-wise inspections or monitoring during construction, including, where applicable, commencement, plinth, intermediate stages and/or completion. 3. Power to issue notices or stop-work directions where unauthorised or non-conforming construction is identified. Score 5 if all three of the aspects are met. Score 0 otherwise.
A105: 38b | B105: NA | C105: NA | D105: UPD | E105: UPD38b | F105: Enforcement | G105: Development Compliance | H105: Construction monitoring | I105: Has a system for monitoring ongoing construction/projects for possible violations been implemented? | J105: SQ | K105: 5 | L105: Implementation | M105: Check the ULG/Development Authority websites whether the monitoring process includes all of the following: 1.Online self-assessment/reporting of construction progress, including uploading photographs and requisite compliance documents 2. Periodic ground surveys/inspections of approved projects, covering either all projects or a defined sample 3. Public disclosure of monitoring information, including compliance numbers/status, violations registered and action taken. Score 5 if all three elements are operational. Score 0 otherwise.
A106: 39 | B106: UPD32 | C106: UPD17 | D106: UPD | E106: UPD39 | F106: Enforcement | G106: Development Compliance | H106: Corrective action | I106: Are there provisions to penalise violating plans? | J106: MQ | K106: 10 | L106: Law or Policy | M106: Check if the T&CP Act mentions the penal provisions under the following heads (at least five of the below to mark as 'Yes'): 1. DCR (Development Control Regulations) violations: a. Zoning/ land use b. Permitted uses (including change in building use eg; dwelling to commercial use; warehouse to office space etc.) c. Setbacks (setbacks are the minimum space required between the plot boundary and building), d. Building height (maximum permissible height according to the location) e. Floor Area Ratio (FAR)/ Floor Space Index (FSI) f. Parking g. Heritage conservation (violations occur if such areas/structures are recognised to be of historical importance) i. Environmental conservation etc 2. Building code violations: (at plan approval stage, these codes dictate the following details) a. Fire norms (primarily important at both plan approval level and again at Occupancy Certificate (OC) level) b. Provision of lifts and staircases c. Corridor length d. Earthquake/flood/tsunami/flood resistance (in disaster prone areas) e. Plot access (the points of entry/exit to your building/plot in accordance with the road) f. Loading/ unloading bays (for commercial and industrial buildings, service access, safety etc. as detailed out by building code) etc 3. NOC violations a. Fire safety b. Water supply and sewerage (absence of rainwater harvesting systems, discharge of waste into any public land, alley, waterbody, sidewalk etc.) c. Electricity (particularly for large-scale/commercial buildings) d. Pollution e. Solid waste management f. Height (near airports) 4. Encroachment of land 5. Building refurbishment without permit/ approvals (addition/demolition/remodeling etc.) 6. Urban design regulations vioations (includes signages, dispaly boards, streetscapes, pedestrian circulation, open areas, plazas, arcades etc.) | N106: Please give the text of the provisions in the scorer comment's column in the scoresheet

Sheet UPD_SUMMARY_RAW
A1: ASICS 2027_Report_Q No | B1: Group | C1: Thematic questions | D1: Sub-themes | E1: MQ_SQ | F1: Question | G1: Assessment level | H1: Max Score | I1: Ahmedabad | J1: Bangalore | K1: Bhopal | L1: Bhubaneswar | M1: Chandigarh | N1: Chennai | O1: Dehradun | P1: Delhi | Q1: Guwahati | R1: Hyderabad | S1: Jaipur | T1: Kanpur | U1: Kolkata | V1: Lucknow | W1: Ludhiana | X1: Mumbai | Y1: Patna | Z1: Pune | AA1: Raipur | AB1: Ranchi | AC1: Surat | AD1: Thiruvananthapuram | AE1: Visakhapatnam | AF1: Solan | AG1: Panaji | AH1: Agartala | AI1: New York | AJ1: London | AK1: Johannesburg
A2: ENTER | B2: Derived | C2: Derived | D2: Derived | E2: Derived | F2: Derived | G2: Derived | H2: Derived | I2: Derived
A3: UPD1 | B3: =IF(ISBLANK($A3),"NO_CODE",VLOOKUP($A3,'UPD Questions_290926 '!$E$1:$N$300,MATCH(B$1,'UPD Questions_290926 '!$E$1:$N$1,0),0)&"") -> Planning | C3: =IF(ISBLANK($A3),"NO_CODE",VLOOKUP($A3,'UPD Questions_290926 '!$E$1:$N$300,MATCH(C$1,'UPD Questions_290926 '!$E$1:$N$1,0),0)&"") -> Legal and institutional planning architecture | D3: =IF(ISBLANK($A3),"NO_CODE",VLOOKUP($A3,'UPD Questions_290926 '!$E$1:$N$300,MATCH(D$1,'UPD Questions_290926 '!$E$1:$N$1,0),0)&"") -> State-level planning framework | E3: =IF(ISBLANK($A3),"NO_CODE",VLOOKUP($A3,'UPD Questions_290926 '!$E$1:$N$300,MATCH(E$1,'UPD Questions_290926 '!$E$1:$N$1,0),0)&"") -> MQ | F3: =IF(ISBLANK($A3),"NO_CODE",VLOOKUP($A3,'UPD Questions_290926 '!$E$1:$N$300,MATCH(F$1,'UPD Questions_290926 '!$E$1:$N$1,0),0)&"") -> Is there a provision for a State Spatial Planning Board which is mandated with planning policies and reforms for the state? | G3: =IF(ISBLANK($A3),"NO_CODE",VLOOKUP($A3,'UPD Questions_290926 '!$E$1:$N$300,MATCH(G$1,'UPD Questions_290926 '!$E$1:$N$1,0),0)&"") -> Law or Policy | H3: =IF(ISBLANK($A3),"NO_CODE",VLOOKUP($A3,'UPD Questions_290926 '!$E$1:$N$300,MATCH(H$1,'UPD Questions_290926 '!$E$1:$N$1,0),0)) -> 10 | I3: =IF($H3=0,"NA",IF($A3=INDIRECT("'"&$A3&"'!$B$1"),IF(VLOOKUP(I$1,INDIRECT("'"&$A3&"'!$A$12:$Z$41"),MATCH("Points (Auto-generate)",INDIRECT("'"&$A3&"'!$A$12:$Z$12"),0),0)="","?",VLOOKUP(I$1,INDIRECT("'"&$A3&"'!$A$12:$Z$41"),MATCH("Points (Auto-generate)",INDIRECT("'"&$A3&"'!$A$12:$Z$12"),0),0)),"ER")) -> ? | J3: =IF($H3=0,"NA",IF($A3=INDIRECT("'"&$A3&"'!$B$1"),IF(VLOOKUP(J$1,INDIRECT("'"&$A3&"'!$A$12:$Z$41"),MATCH("Points (Auto-generate)",INDIRECT("'"&$A3&"'!$A$12:$Z$12"),0),0)="","?",VLOOKUP(J$1,INDIRECT("'"&$A3&"'!$A$12:$Z$41"),MATCH("Points (Auto-generate)",INDIRECT("'"&$A3&"'!$A$12:$Z$12"),0),0)),"ER")) -> ? | K3: =IF($H3=0,"NA",IF($A3=INDIRECT("'"&$A3&"'!$B$1"),IF(VLOOKUP(K$1,INDIRECT("'"&$A3&"'!$A$12:$Z$41"),MATCH("Points (Auto-generate)",INDIRECT("'"&$A3&"'!$A$12:$Z$12"),0),0)="","?",VLOOKUP(K$1,INDIRECT("'"&$A3&"'!$A$12:$Z$41"),MATCH("Points (Auto-generate)",INDIRECT("'"&$A3&"'!$A$12:$Z$12"),0),0)),"ER")) -> ? | L3: =IF($H3=0,"NA",IF($A3=INDIRECT("'"&$A3&"'!$B$1"),IF(VLOOKUP(L$1,INDIRECT("'"&$A3&"'!$A$12:$Z$41"),MATCH("Points (Auto-generate)",INDIRECT("'"&$A3&"'!$A$12:$Z$12"),0),0)="","?",VLOOKUP(L$1,INDIRECT("'"&$A3&"'!$A$12:$Z$41"),MATCH("Points (Auto-generate)",INDIRECT("'"&$A3&"'!$A$12:$Z$12"),0),0)),"ER")) -> ? | M3: =IF($H3=0,"NA",IF($A3=INDIRECT("'"&$A3&"'!$B$1"),IF(VLOOKUP(M$1,INDIRECT("'"&$A3&"'!$A$12:$Z$41"),MATCH("Points (Auto-generate)",INDIRECT("'"&$A3&"'!$A$12:$Z$12"),0),0)="","?",VLOOKUP(M$1,INDIRECT("'"&$A3&"'!$A$12:$Z$41"),MATCH("Points (Auto-generate)",INDIRECT("'"&$A3&"'!$A$12:$Z$12"),0),0)),"ER")) -> ? | N3: =IF($H3=0,"NA",IF($A3=INDIRECT("'"&$A3&"'!$B$1"),IF(VLOOKUP(N$1,INDIRECT("'"&$A3&"'!$A$12:$Z$41"),MATCH("Points (Auto-generate)",INDIRECT("'"&$A3&"'!$A$12:$Z$12"),0),0)="","?",VLOOKUP(N$1,INDIRECT("'"&$A3&"'!$A$12:$Z$41"),MATCH("Points (Auto-generate)",INDIRECT("'"&$A3&"'!$A$12:$Z$12"),0),0)),"ER")) -> ? | O3: =IF($H3=0,"NA",IF($A3=INDIRECT("'"&$A3&"'!$B$1"),IF(VLOOKUP(O$1,INDIRECT("'"&$A3&"'!$A$12:$Z$41"),MATCH("Points (Auto-generate)",INDIRECT("'"&$A3&"'!$A$12:$Z$12"),0),0)="","?",VLOOKUP(O$1,INDIRECT("'"&$A3&"'!$A$12:$Z$41"),MATCH("Points (Auto-generate)",INDIRECT("'"&$A3&"'!$A$12:$Z$12"),0),0)),"ER")) -> ? | P3: =IF($H3=0,"NA",IF($A3=INDIRECT("'"&$A3&"'!$B$1"),IF(VLOOKUP(P$1,INDIRECT("'"&$A3&"'!$A$12:$Z$41"),MATCH("Points (Auto-generate)",INDIRECT("'"&$A3&"'!$A$12:$Z$12"),0),0)="","?",VLOOKUP(P$1,INDIRECT("'"&$A3&"'!$A$12:$Z$41"),MATCH("Points (Auto-generate)",INDIRECT("'"&$A3&"'!$A$12:$Z$12"),0),0)),"ER")) -> ? | ... AK3: =IF($H3=0,"NA",IF($A3=INDIRECT("'"&$A3&"'!$B$1"),IF(VLOOKUP(AK$1,INDIRECT("'"&$A3&"'!$A$12:$Z$41"),MATCH("Points (Auto-generate)",INDIRECT("'"&$A3&"'!$A$12:$Z$12"),0),0)="","?",VLOOKUP(AK$1,INDIRECT("'"&$A3&"'!$A$12:$Z$41"),MATCH("Points (Auto-generate)",INDIRECT("'"&$A3&"'!$A$12:$Z$12"),0),0)),"ER")) -> ?
A4: UPD2 | B4: =IF(ISBLANK($A4),"NO_CODE",VLOOKUP($A4,'UPD Questions_290926 '!$E$1:$N$300,MATCH(B$1,'UPD Questions_290926 '!$E$1:$N$1,0),0)&"") -> Planning | C4: =IF(ISBLANK($A4),"NO_CODE",VLOOKUP($A4,'UPD Questions_290926 '!$E$1:$N$300,MATCH(C$1,'UPD Questions_290926 '!$E$1:$N$1,0),0)&"") -> Legal and institutional planning architecture | D4: =IF(ISBLANK($A4),"NO_CODE",VLOOKUP($A4,'UPD Questions_290926 '!$E$1:$N$300,MATCH(D$1,'UPD Questions_290926 '!$E$1:$N$1,0),0)&"") -> State-level planning framework | E4: =IF(ISBLANK($A4),"NO_CODE",VLOOKUP($A4,'UPD Questions_290926 '!$E$1:$N$300,MATCH(E$1,'UPD Questions_290926 '!$E$1:$N$1,0),0)&"") -> MQ | F4: =IF(ISBLANK($A4),"NO_CODE",VLOOKUP($A4,'UPD Questions_290926 '!$E$1:$N$300,MATCH(F$1,'UPD Questions_290926 '!$E$1:$N$1,0),0)&"") -> Is there a provision for the establishment of Planning Authorities for notified new towns or special developments? | G4: =IF(ISBLANK($A4),"NO_CODE",VLOOKUP($A4,'UPD Questions_290926 '!$E$1:$N$300,MATCH(G$1,'UPD Questions_290926 '!$E$1:$N$1,0),0)&"") -> Law or Policy | H4: =IF(ISBLANK($A4),"NO_CODE",VLOOKUP($A4,'UPD Questions_290926 '!$E$1:$N$300,MATCH(H$1,'UPD Questions_290926 '!$E$1:$N$1,0),0)) -> 10 | I4: =IF($H4=0,"NA",IF($A4=INDIRECT("'"&$A4&"'!$B$1"),IF(VLOOKUP(I$1,INDIRECT("'"&$A4&"'!$A$12:$Z$41"),MATCH("Points (Auto-generate)",INDIRECT("'"&$A4&"'!$A$12:$Z$12"),0),0)="","?",VLOOKUP(I$1,INDIRECT("'"&$A4&"'!$A$12:$Z$41"),MATCH("Points (Auto-generate)",INDIRECT("'"&$A4&"'!$A$12:$Z$12"),0),0)),"ER")) -> ? | J4: =IF($H4=0,"NA",IF($A4=INDIRECT("'"&$A4&"'!$B$1"),IF(VLOOKUP(J$1,INDIRECT("'"&$A4&"'!$A$12:$Z$41"),MATCH("Points (Auto-generate)",INDIRECT("'"&$A4&"'!$A$12:$Z$12"),0),0)="","?",VLOOKUP(J$1,INDIRECT("'"&$A4&"'!$A$12:$Z$41"),MATCH("Points (Auto-generate)",INDIRECT("'"&$A4&"'!$A$12:$Z$12"),0),0)),"ER")) -> ? | K4: =IF($H4=0,"NA",IF($A4=INDIRECT("'"&$A4&"'!$B$1"),IF(VLOOKUP(K$1,INDIRECT("'"&$A4&"'!$A$12:$Z$41"),MATCH("Points (Auto-generate)",INDIRECT("'"&$A4&"'!$A$12:$Z$12"),0),0)="","?",VLOOKUP(K$1,INDIRECT("'"&$A4&"'!$A$12:$Z$41"),MATCH("Points (Auto-generate)",INDIRECT("'"&$A4&"'!$A$12:$Z$12"),0),0)),"ER")) -> ? | L4: =IF($H4=0,"NA",IF($A4=INDIRECT("'"&$A4&"'!$B$1"),IF(VLOOKUP(L$1,INDIRECT("'"&$A4&"'!$A$12:$Z$41"),MATCH("Points (Auto-generate)",INDIRECT("'"&$A4&"'!$A$12:$Z$12"),0),0)="","?",VLOOKUP(L$1,INDIRECT("'"&$A4&"'!$A$12:$Z$41"),MATCH("Points (Auto-generate)",INDIRECT("'"&$A4&"'!$A$12:$Z$12"),0),0)),"ER")) -> ? | M4: =IF($H4=0,"NA",IF($A4=INDIRECT("'"&$A4&"'!$B$1"),IF(VLOOKUP(M$1,INDIRECT("'"&$A4&"'!$A$12:$Z$41"),MATCH("Points (Auto-generate)",INDIRECT("'"&$A4&"'!$A$12:$Z$12"),0),0)="","?",VLOOKUP(M$1,INDIRECT("'"&$A4&"'!$A$12:$Z$41"),MATCH("Points (Auto-generate)",INDIRECT("'"&$A4&"'!$A$12:$Z$12"),0),0)),"ER")) -> ? | N4: =IF($H4=0,"NA",IF($A4=INDIRECT("'"&$A4&"'!$B$1"),IF(VLOOKUP(N$1,INDIRECT("'"&$A4&"'!$A$12:$Z$41"),MATCH("Points (Auto-generate)",INDIRECT("'"&$A4&"'!$A$12:$Z$12"),0),0)="","?",VLOOKUP(N$1,INDIRECT("'"&$A4&"'!$A$12:$Z$41"),MATCH("Points (Auto-generate)",INDIRECT("'"&$A4&"'!$A$12:$Z$12"),0),0)),"ER")) -> ? | O4: =IF($H4=0,"NA",IF($A4=INDIRECT("'"&$A4&"'!$B$1"),IF(VLOOKUP(O$1,INDIRECT("'"&$A4&"'!$A$12:$Z$41"),MATCH("Points (Auto-generate)",INDIRECT("'"&$A4&"'!$A$12:$Z$12"),0),0)="","?",VLOOKUP(O$1,INDIRECT("'"&$A4&"'!$A$12:$Z$41"),MATCH("Points (Auto-generate)",INDIRECT("'"&$A4&"'!$A$12:$Z$12"),0),0)),"ER")) -> ? | P4: =IF($H4=0,"NA",IF($A4=INDIRECT("'"&$A4&"'!$B$1"),IF(VLOOKUP(P$1,INDIRECT("'"&$A4&"'!$A$12:$Z$41"),MATCH("Points (Auto-generate)",INDIRECT("'"&$A4&"'!$A$12:$Z$12"),0),0)="","?",VLOOKUP(P$1,INDIRECT("'"&$A4&"'!$A$12:$Z$41"),MATCH("Points (Auto-generate)",INDIRECT("'"&$A4&"'!$A$12:$Z$12"),0),0)),"ER")) -> ? | ... AK4: =IF($H4=0,"NA",IF($A4=INDIRECT("'"&$A4&"'!$B$1"),IF(VLOOKUP(AK$1,INDIRECT("'"&$A4&"'!$A$12:$Z$41"),MATCH("Points (Auto-generate)",INDIRECT("'"&$A4&"'!$A$12:$Z$12"),0),0)="","?",VLOOKUP(AK$1,INDIRECT("'"&$A4&"'!$A$12:$Z$41"),MATCH("Points (Auto-generate)",INDIRECT("'"&$A4&"'!$A$12:$Z$12"),0),0)),"ER")) -> ?
A5: UPD3 | B5: =IF(ISBLANK($A5),"NO_CODE",VLOOKUP($A5,'UPD Questions_290926 '!$E$1:$N$300,MATCH(B$1,'UPD Questions_290926 '!$E$1:$N$1,0),0)&"") -> Planning | C5: =IF(ISBLANK($A5),"NO_CODE",VLOOKUP($A5,'UPD Questions_290926 '!$E$1:$N$300,MATCH(C$1,'UPD Questions_290926 '!$E$1:$N$1,0),0)&"") -> Legal and institutional planning architecture | D5: =IF(ISBLANK($A5),"NO_CODE",VLOOKUP($A5,'UPD Questions_290926 '!$E$1:$N$300,MATCH(D$1,'UPD Questions_290926 '!$E$1:$N$1,0),0)&"") -> Spatial planning hierarchy | E5: =IF(ISBLANK($A5),"NO_CODE",VLOOKUP($A5,'UPD Questions_290926 '!$E$1:$N$300,MATCH(E$1,'UPD Questions_290926 '!$E$1:$N$1,0),0)&"") -> MQ | F5: =IF(ISBLANK($A5),"NO_CODE",VLOOKUP($A5,'UPD Questions_290926 '!$E$1:$N$300,MATCH(F$1,'UPD Questions_290926 '!$E$1:$N$1,0),0)&"") -> Does the Act require three levels of spatial plans for cities: Metropolitan/Regional, Municipal and Ward(s) /Local | G5: =IF(ISBLANK($A5),"NO_CODE",VLOOKUP($A5,'UPD Questions_290926 '!$E$1:$N$300,MATCH(G$1,'UPD Questions_290926 '!$E$1:$N$1,0),0)&"") -> Law or Policy | H5: =IF(ISBLANK($A5),"NO_CODE",VLOOKUP($A5,'UPD Questions_290926 '!$E$1:$N$300,MATCH(H$1,'UPD Questions_290926 '!$E$1:$N$1,0),0)) -> 10 | I5: =IF(OR(I6="ER",I7="ER",I8="ER"),"ER",IF(OR(I6="?",I7="?",I8="?"),"?",IF(AND(I6="NA",I7="NA",I8="NA"),"NA",SUM(I6,I7,I8)/((I6<>"NA")*$H$6+(I7<>"NA")*$H$7+(I8<>"NA")*$H$8)*$H5))) -> ? | J5: =IF(OR(J6="ER",J7="ER",J8="ER"),"ER",IF(OR(J6="?",J7="?",J8="?"),"?",IF(AND(J6="NA",J7="NA",J8="NA"),"NA",SUM(J6,J7,J8)/((J6<>"NA")*$H$6+(J7<>"NA")*$H$7+(J8<>"NA")*$H$8)*$H5))) -> ? | K5: =IF(OR(K6="ER",K7="ER",K8="ER"),"ER",IF(OR(K6="?",K7="?",K8="?"),"?",IF(AND(K6="NA",K7="NA",K8="NA"),"NA",SUM(K6,K7,K8)/((K6<>"NA")*$H$6+(K7<>"NA")*$H$7+(K8<>"NA")*$H$8)*$H5))) -> ? | L5: =IF(OR(L6="ER",L7="ER",L8="ER"),"ER",IF(OR(L6="?",L7="?",L8="?"),"?",IF(AND(L6="NA",L7="NA",L8="NA"),"NA",SUM(L6,L7,L8)/((L6<>"NA")*$H$6+(L7<>"NA")*$H$7+(L8<>"NA")*$H$8)*$H5))) -> ? | M5: =IF(OR(M6="ER",M7="ER",M8="ER"),"ER",IF(OR(M6="?",M7="?",M8="?"),"?",IF(AND(M6="NA",M7="NA",M8="NA"),"NA",SUM(M6,M7,M8)/((M6<>"NA")*$H$6+(M7<>"NA")*$H$7+(M8<>"NA")*$H$8)*$H5))) -> ? | N5: =IF(OR(N6="ER",N7="ER",N8="ER"),"ER",IF(OR(N6="?",N7="?",N8="?"),"?",IF(AND(N6="NA",N7="NA",N8="NA"),"NA",SUM(N6,N7,N8)/((N6<>"NA")*$H$6+(N7<>"NA")*$H$7+(N8<>"NA")*$H$8)*$H5))) -> ? | O5: =IF(OR(O6="ER",O7="ER",O8="ER"),"ER",IF(OR(O6="?",O7="?",O8="?"),"?",IF(AND(O6="NA",O7="NA",O8="NA"),"NA",SUM(O6,O7,O8)/((O6<>"NA")*$H$6+(O7<>"NA")*$H$7+(O8<>"NA")*$H$8)*$H5))) -> ? | P5: =IF(OR(P6="ER",P7="ER",P8="ER"),"ER",IF(OR(P6="?",P7="?",P8="?"),"?",IF(AND(P6="NA",P7="NA",P8="NA"),"NA",SUM(P6,P7,P8)/((P6<>"NA")*$H$6+(P7<>"NA")*$H$7+(P8<>"NA")*$H$8)*$H5))) -> ? | ... AK5: =IF(OR(AK6="ER",AK7="ER",AK8="ER"),"ER",IF(OR(AK6="?",AK7="?",AK8="?"),"?",IF(AND(AK6="NA",AK7="NA",AK8="NA"),"NA",SUM(AK6,AK7,AK8)/((AK6<>"NA")*$H$6+(AK7<>"NA")*$H$7+(AK8<>"NA")*$H$8)*$H5))) -> ?
A6: UPD3a | B6: =IF(ISBLANK($A6),"NO_CODE",VLOOKUP($A6,'UPD Questions_290926 '!$E$1:$N$300,MATCH(B$1,'UPD Questions_290926 '!$E$1:$N$1,0),0)&"") -> Planning | C6: =IF(ISBLANK($A6),"NO_CODE",VLOOKUP($A6,'UPD Questions_290926 '!$E$1:$N$300,MATCH(C$1,'UPD Questions_290926 '!$E$1:$N$1,0),0)&"") -> Legal and institutional planning architecture | D6: =IF(ISBLANK($A6),"NO_CODE",VLOOKUP($A6,'UPD Questions_290926 '!$E$1:$N$300,MATCH(D$1,'UPD Questions_290926 '!$E$1:$N$1,0),0)&"") -> Spatial planning hierarchy | E6: =IF(ISBLANK($A6),"NO_CODE",VLOOKUP($A6,'UPD Questions_290926 '!$E$1:$N$300,MATCH(E$1,'UPD Questions_290926 '!$E$1:$N$1,0),0)&"") -> SQ | F6: =IF(ISBLANK($A6),"NO_CODE",VLOOKUP($A6,'UPD Questions_290926 '!$E$1:$N$300,MATCH(F$1,'UPD Questions_290926 '!$E$1:$N$1,0),0)&"") -> Metropolitan/ Regional Plan | G6: =IF(ISBLANK($A6),"NO_CODE",VLOOKUP($A6,'UPD Questions_290926 '!$E$1:$N$300,MATCH(G$1,'UPD Questions_290926 '!$E$1:$N$1,0),0)&"") -> Law or Policy | H6: =IF(ISBLANK($A6),"NO_CODE",VLOOKUP($A6,'UPD Questions_290926 '!$E$1:$N$300,MATCH(H$1,'UPD Questions_290926 '!$E$1:$N$1,0),0)) -> 3.33 | I6: =IF($H6=0,"NA",IF($A6=INDIRECT("'"&$A6&"'!$B$1"),IF(VLOOKUP(I$1,INDIRECT("'"&$A6&"'!$A$12:$Z$41"),MATCH("Points (Auto-generate)",INDIRECT("'"&$A6&"'!$A$12:$Z$12"),0),0)="","?",VLOOKUP(I$1,INDIRECT("'"&$A6&"'!$A$12:$Z$41"),MATCH("Points (Auto-generate)",INDIRECT("'"&$A6&"'!$A$12:$Z$12"),0),0)),"ER")) -> ? | J6: =IF($H6=0,"NA",IF($A6=INDIRECT("'"&$A6&"'!$B$1"),IF(VLOOKUP(J$1,INDIRECT("'"&$A6&"'!$A$12:$Z$41"),MATCH("Points (Auto-generate)",INDIRECT("'"&$A6&"'!$A$12:$Z$12"),0),0)="","?",VLOOKUP(J$1,INDIRECT("'"&$A6&"'!$A$12:$Z$41"),MATCH("Points (Auto-generate)",INDIRECT("'"&$A6&"'!$A$12:$Z$12"),0),0)),"ER")) -> ? | K6: =IF($H6=0,"NA",IF($A6=INDIRECT("'"&$A6&"'!$B$1"),IF(VLOOKUP(K$1,INDIRECT("'"&$A6&"'!$A$12:$Z$41"),MATCH("Points (Auto-generate)",INDIRECT("'"&$A6&"'!$A$12:$Z$12"),0),0)="","?",VLOOKUP(K$1,INDIRECT("'"&$A6&"'!$A$12:$Z$41"),MATCH("Points (Auto-generate)",INDIRECT("'"&$A6&"'!$A$12:$Z$12"),0),0)),"ER")) -> ? | L6: =IF($H6=0,"NA",IF($A6=INDIRECT("'"&$A6&"'!$B$1"),IF(VLOOKUP(L$1,INDIRECT("'"&$A6&"'!$A$12:$Z$41"),MATCH("Points (Auto-generate)",INDIRECT("'"&$A6&"'!$A$12:$Z$12"),0),0)="","?",VLOOKUP(L$1,INDIRECT("'"&$A6&"'!$A$12:$Z$41"),MATCH("Points (Auto-generate)",INDIRECT("'"&$A6&"'!$A$12:$Z$12"),0),0)),"ER")) -> ? | M6: =IF($H6=0,"NA",IF($A6=INDIRECT("'"&$A6&"'!$B$1"),IF(VLOOKUP(M$1,INDIRECT("'"&$A6&"'!$A$12:$Z$41"),MATCH("Points (Auto-generate)",INDIRECT("'"&$A6&"'!$A$12:$Z$12"),0),0)="","?",VLOOKUP(M$1,INDIRECT("'"&$A6&"'!$A$12:$Z$41"),MATCH("Points (Auto-generate)",INDIRECT("'"&$A6&"'!$A$12:$Z$12"),0),0)),"ER")) -> ? | N6: =IF($H6=0,"NA",IF($A6=INDIRECT("'"&$A6&"'!$B$1"),IF(VLOOKUP(N$1,INDIRECT("'"&$A6&"'!$A$12:$Z$41"),MATCH("Points (Auto-generate)",INDIRECT("'"&$A6&"'!$A$12:$Z$12"),0),0)="","?",VLOOKUP(N$1,INDIRECT("'"&$A6&"'!$A$12:$Z$41"),MATCH("Points (Auto-generate)",INDIRECT("'"&$A6&"'!$A$12:$Z$12"),0),0)),"ER")) -> ? | O6: =IF($H6=0,"NA",IF($A6=INDIRECT("'"&$A6&"'!$B$1"),IF(VLOOKUP(O$1,INDIRECT("'"&$A6&"'!$A$12:$Z$41"),MATCH("Points (Auto-generate)",INDIRECT("'"&$A6&"'!$A$12:$Z$12"),0),0)="","?",VLOOKUP(O$1,INDIRECT("'"&$A6&"'!$A$12:$Z$41"),MATCH("Points (Auto-generate)",INDIRECT("'"&$A6&"'!$A$12:$Z$12"),0),0)),"ER")) -> ? | P6: =IF($H6=0,"NA",IF($A6=INDIRECT("'"&$A6&"'!$B$1"),IF(VLOOKUP(P$1,INDIRECT("'"&$A6&"'!$A$12:$Z$41"),MATCH("Points (Auto-generate)",INDIRECT("'"&$A6&"'!$A$12:$Z$12"),0),0)="","?",VLOOKUP(P$1,INDIRECT("'"&$A6&"'!$A$12:$Z$41"),MATCH("Points (Auto-generate)",INDIRECT("'"&$A6&"'!$A$12:$Z$12"),0),0)),"ER")) -> ? | ... AK6: =IF($H6=0,"NA",IF($A6=INDIRECT("'"&$A6&"'!$B$1"),IF(VLOOKUP(AK$1,INDIRECT("'"&$A6&"'!$A$12:$Z$41"),MATCH("Points (Auto-generate)",INDIRECT("'"&$A6&"'!$A$12:$Z$12"),0),0)="","?",VLOOKUP(AK$1,INDIRECT("'"&$A6&"'!$A$12:$Z$41"),MATCH("Points (Auto-generate)",INDIRECT("'"&$A6&"'!$A$12:$Z$12"),0),0)),"ER")) -> ?
A7: UPD3b | B7: =IF(ISBLANK($A7),"NO_CODE",VLOOKUP($A7,'UPD Questions_290926 '!$E$1:$N$300,MATCH(B$1,'UPD Questions_290926 '!$E$1:$N$1,0),0)&"") -> Planning | C7: =IF(ISBLANK($A7),"NO_CODE",VLOOKUP($A7,'UPD Questions_290926 '!$E$1:$N$300,MATCH(C$1,'UPD Questions_290926 '!$E$1:$N$1,0),0)&"") -> Legal and institutional planning architecture | D7: =IF(ISBLANK($A7),"NO_CODE",VLOOKUP($A7,'UPD Questions_290926 '!$E$1:$N$300,MATCH(D$1,'UPD Questions_290926 '!$E$1:$N$1,0),0)&"") -> Spatial planning hierarchy | E7: =IF(ISBLANK($A7),"NO_CODE",VLOOKUP($A7,'UPD Questions_290926 '!$E$1:$N$300,MATCH(E$1,'UPD Questions_290926 '!$E$1:$N$1,0),0)&"") -> SQ | F7: =IF(ISBLANK($A7),"NO_CODE",VLOOKUP($A7,'UPD Questions_290926 '!$E$1:$N$300,MATCH(F$1,'UPD Questions_290926 '!$E$1:$N$1,0),0)&"") -> Municipal/city plan | G7: =IF(ISBLANK($A7),"NO_CODE",VLOOKUP($A7,'UPD Questions_290926 '!$E$1:$N$300,MATCH(G$1,'UPD Questions_290926 '!$E$1:$N$1,0),0)&"") -> Law or Policy | H7: =IF(ISBLANK($A7),"NO_CODE",VLOOKUP($A7,'UPD Questions_290926 '!$E$1:$N$300,MATCH(H$1,'UPD Questions_290926 '!$E$1:$N$1,0),0)) -> 3.33 | I7: =IF($H7=0,"NA",IF($A7=INDIRECT("'"&$A7&"'!$B$1"),IF(VLOOKUP(I$1,INDIRECT("'"&$A7&"'!$A$12:$Z$41"),MATCH("Points (Auto-generate)",INDIRECT("'"&$A7&"'!$A$12:$Z$12"),0),0)="","?",VLOOKUP(I$1,INDIRECT("'"&$A7&"'!$A$12:$Z$41"),MATCH("Points (Auto-generate)",INDIRECT("'"&$A7&"'!$A$12:$Z$12"),0),0)),"ER")) -> ? | J7: =IF($H7=0,"NA",IF($A7=INDIRECT("'"&$A7&"'!$B$1"),IF(VLOOKUP(J$1,INDIRECT("'"&$A7&"'!$A$12:$Z$41"),MATCH("Points (Auto-generate)",INDIRECT("'"&$A7&"'!$A$12:$Z$12"),0),0)="","?",VLOOKUP(J$1,INDIRECT("'"&$A7&"'!$A$12:$Z$41"),MATCH("Points (Auto-generate)",INDIRECT("'"&$A7&"'!$A$12:$Z$12"),0),0)),"ER")) -> ? | K7: =IF($H7=0,"NA",IF($A7=INDIRECT("'"&$A7&"'!$B$1"),IF(VLOOKUP(K$1,INDIRECT("'"&$A7&"'!$A$12:$Z$41"),MATCH("Points (Auto-generate)",INDIRECT("'"&$A7&"'!$A$12:$Z$12"),0),0)="","?",VLOOKUP(K$1,INDIRECT("'"&$A7&"'!$A$12:$Z$41"),MATCH("Points (Auto-generate)",INDIRECT("'"&$A7&"'!$A$12:$Z$12"),0),0)),"ER")) -> ? | L7: =IF($H7=0,"NA",IF($A7=INDIRECT("'"&$A7&"'!$B$1"),IF(VLOOKUP(L$1,INDIRECT("'"&$A7&"'!$A$12:$Z$41"),MATCH("Points (Auto-generate)",INDIRECT("'"&$A7&"'!$A$12:$Z$12"),0),0)="","?",VLOOKUP(L$1,INDIRECT("'"&$A7&"'!$A$12:$Z$41"),MATCH("Points (Auto-generate)",INDIRECT("'"&$A7&"'!$A$12:$Z$12"),0),0)),"ER")) -> ? | M7: =IF($H7=0,"NA",IF($A7=INDIRECT("'"&$A7&"'!$B$1"),IF(VLOOKUP(M$1,INDIRECT("'"&$A7&"'!$A$12:$Z$41"),MATCH("Points (Auto-generate)",INDIRECT("'"&$A7&"'!$A$12:$Z$12"),0),0)="","?",VLOOKUP(M$1,INDIRECT("'"&$A7&"'!$A$12:$Z$41"),MATCH("Points (Auto-generate)",INDIRECT("'"&$A7&"'!$A$12:$Z$12"),0),0)),"ER")) -> ? | N7: =IF($H7=0,"NA",IF($A7=INDIRECT("'"&$A7&"'!$B$1"),IF(VLOOKUP(N$1,INDIRECT("'"&$A7&"'!$A$12:$Z$41"),MATCH("Points (Auto-generate)",INDIRECT("'"&$A7&"'!$A$12:$Z$12"),0),0)="","?",VLOOKUP(N$1,INDIRECT("'"&$A7&"'!$A$12:$Z$41"),MATCH("Points (Auto-generate)",INDIRECT("'"&$A7&"'!$A$12:$Z$12"),0),0)),"ER")) -> ? | O7: =IF($H7=0,"NA",IF($A7=INDIRECT("'"&$A7&"'!$B$1"),IF(VLOOKUP(O$1,INDIRECT("'"&$A7&"'!$A$12:$Z$41"),MATCH("Points (Auto-generate)",INDIRECT("'"&$A7&"'!$A$12:$Z$12"),0),0)="","?",VLOOKUP(O$1,INDIRECT("'"&$A7&"'!$A$12:$Z$41"),MATCH("Points (Auto-generate)",INDIRECT("'"&$A7&"'!$A$12:$Z$12"),0),0)),"ER")) -> ? | P7: =IF($H7=0,"NA",IF($A7=INDIRECT("'"&$A7&"'!$B$1"),IF(VLOOKUP(P$1,INDIRECT("'"&$A7&"'!$A$12:$Z$41"),MATCH("Points (Auto-generate)",INDIRECT("'"&$A7&"'!$A$12:$Z$12"),0),0)="","?",VLOOKUP(P$1,INDIRECT("'"&$A7&"'!$A$12:$Z$41"),MATCH("Points (Auto-generate)",INDIRECT("'"&$A7&"'!$A$12:$Z$12"),0),0)),"ER")) -> ? | ... AK7: =IF($H7=0,"NA",IF($A7=INDIRECT("'"&$A7&"'!$B$1"),IF(VLOOKUP(AK$1,INDIRECT("'"&$A7&"'!$A$12:$Z$41"),MATCH("Points (Auto-generate)",INDIRECT("'"&$A7&"'!$A$12:$Z$12"),0),0)="","?",VLOOKUP(AK$1,INDIRECT("'"&$A7&"'!$A$12:$Z$41"),MATCH("Points (Auto-generate)",INDIRECT("'"&$A7&"'!$A$12:$Z$12"),0),0)),"ER")) -> ?
A8: UPD3c | B8: =IF(ISBLANK($A8),"NO_CODE",VLOOKUP($A8,'UPD Questions_290926 '!$E$1:$N$300,MATCH(B$1,'UPD Questions_290926 '!$E$1:$N$1,0),0)&"") -> Planning | C8: =IF(ISBLANK($A8),"NO_CODE",VLOOKUP($A8,'UPD Questions_290926 '!$E$1:$N$300,MATCH(C$1,'UPD Questions_290926 '!$E$1:$N$1,0),0)&"") -> Legal and institutional planning architecture | D8: =IF(ISBLANK($A8),"NO_CODE",VLOOKUP($A8,'UPD Questions_290926 '!$E$1:$N$300,MATCH(D$1,'UPD Questions_290926 '!$E$1:$N$1,0),0)&"") -> Spatial planning hierarchy | E8: =IF(ISBLANK($A8),"NO_CODE",VLOOKUP($A8,'UPD Questions_290926 '!$E$1:$N$300,MATCH(E$1,'UPD Questions_290926 '!$E$1:$N$1,0),0)&"") -> SQ | F8: =IF(ISBLANK($A8),"NO_CODE",VLOOKUP($A8,'UPD Questions_290926 '!$E$1:$N$300,MATCH(F$1,'UPD Questions_290926 '!$E$1:$N$1,0),0)&"") -> Ward(s)/local plan | G8: =IF(ISBLANK($A8),"NO_CODE",VLOOKUP($A8,'UPD Questions_290926 '!$E$1:$N$300,MATCH(G$1,'UPD Questions_290926 '!$E$1:$N$1,0),0)&"") -> Law or Policy | H8: =IF(ISBLANK($A8),"NO_CODE",VLOOKUP($A8,'UPD Questions_290926 '!$E$1:$N$300,MATCH(H$1,'UPD Questions_290926 '!$E$1:$N$1,0),0)) -> 3.33 | I8: =IF($H8=0,"NA",IF($A8=INDIRECT("'"&$A8&"'!$B$1"),IF(VLOOKUP(I$1,INDIRECT("'"&$A8&"'!$A$12:$Z$41"),MATCH("Points (Auto-generate)",INDIRECT("'"&$A8&"'!$A$12:$Z$12"),0),0)="","?",VLOOKUP(I$1,INDIRECT("'"&$A8&"'!$A$12:$Z$41"),MATCH("Points (Auto-generate)",INDIRECT("'"&$A8&"'!$A$12:$Z$12"),0),0)),"ER")) -> ? | J8: =IF($H8=0,"NA",IF($A8=INDIRECT("'"&$A8&"'!$B$1"),IF(VLOOKUP(J$1,INDIRECT("'"&$A8&"'!$A$12:$Z$41"),MATCH("Points (Auto-generate)",INDIRECT("'"&$A8&"'!$A$12:$Z$12"),0),0)="","?",VLOOKUP(J$1,INDIRECT("'"&$A8&"'!$A$12:$Z$41"),MATCH("Points (Auto-generate)",INDIRECT("'"&$A8&"'!$A$12:$Z$12"),0),0)),"ER")) -> ? | K8: =IF($H8=0,"NA",IF($A8=INDIRECT("'"&$A8&"'!$B$1"),IF(VLOOKUP(K$1,INDIRECT("'"&$A8&"'!$A$12:$Z$41"),MATCH("Points (Auto-generate)",INDIRECT("'"&$A8&"'!$A$12:$Z$12"),0),0)="","?",VLOOKUP(K$1,INDIRECT("'"&$A8&"'!$A$12:$Z$41"),MATCH("Points (Auto-generate)",INDIRECT("'"&$A8&"'!$A$12:$Z$12"),0),0)),"ER")) -> ? | L8: =IF($H8=0,"NA",IF($A8=INDIRECT("'"&$A8&"'!$B$1"),IF(VLOOKUP(L$1,INDIRECT("'"&$A8&"'!$A$12:$Z$41"),MATCH("Points (Auto-generate)",INDIRECT("'"&$A8&"'!$A$12:$Z$12"),0),0)="","?",VLOOKUP(L$1,INDIRECT("'"&$A8&"'!$A$12:$Z$41"),MATCH("Points (Auto-generate)",INDIRECT("'"&$A8&"'!$A$12:$Z$12"),0),0)),"ER")) -> ? | M8: =IF($H8=0,"NA",IF($A8=INDIRECT("'"&$A8&"'!$B$1"),IF(VLOOKUP(M$1,INDIRECT("'"&$A8&"'!$A$12:$Z$41"),MATCH("Points (Auto-generate)",INDIRECT("'"&$A8&"'!$A$12:$Z$12"),0),0)="","?",VLOOKUP(M$1,INDIRECT("'"&$A8&"'!$A$12:$Z$41"),MATCH("Points (Auto-generate)",INDIRECT("'"&$A8&"'!$A$12:$Z$12"),0),0)),"ER")) -> ? | N8: =IF($H8=0,"NA",IF($A8=INDIRECT("'"&$A8&"'!$B$1"),IF(VLOOKUP(N$1,INDIRECT("'"&$A8&"'!$A$12:$Z$41"),MATCH("Points (Auto-generate)",INDIRECT("'"&$A8&"'!$A$12:$Z$12"),0),0)="","?",VLOOKUP(N$1,INDIRECT("'"&$A8&"'!$A$12:$Z$41"),MATCH("Points (Auto-generate)",INDIRECT("'"&$A8&"'!$A$12:$Z$12"),0),0)),"ER")) -> ? | O8: =IF($H8=0,"NA",IF($A8=INDIRECT("'"&$A8&"'!$B$1"),IF(VLOOKUP(O$1,INDIRECT("'"&$A8&"'!$A$12:$Z$41"),MATCH("Points (Auto-generate)",INDIRECT("'"&$A8&"'!$A$12:$Z$12"),0),0)="","?",VLOOKUP(O$1,INDIRECT("'"&$A8&"'!$A$12:$Z$41"),MATCH("Points (Auto-generate)",INDIRECT("'"&$A8&"'!$A$12:$Z$12"),0),0)),"ER")) -> ? | P8: =IF($H8=0,"NA",IF($A8=INDIRECT("'"&$A8&"'!$B$1"),IF(VLOOKUP(P$1,INDIRECT("'"&$A8&"'!$A$12:$Z$41"),MATCH("Points (Auto-generate)",INDIRECT("'"&$A8&"'!$A$12:$Z$12"),0),0)="","?",VLOOKUP(P$1,INDIRECT("'"&$A8&"'!$A$12:$Z$41"),MATCH("Points (Auto-generate)",INDIRECT("'"&$A8&"'!$A$12:$Z$12"),0),0)),"ER")) -> ? | ... AK8: =IF($H8=0,"NA",IF($A8=INDIRECT("'"&$A8&"'!$B$1"),IF(VLOOKUP(AK$1,INDIRECT("'"&$A8&"'!$A$12:$Z$41"),MATCH("Points (Auto-generate)",INDIRECT("'"&$A8&"'!$A$12:$Z$12"),0),0)="","?",VLOOKUP(AK$1,INDIRECT("'"&$A8&"'!$A$12:$Z$41"),MATCH("Points (Auto-generate)",INDIRECT("'"&$A8&"'!$A$12:$Z$12"),0),0)),"ER")) -> ?
A9: UPD4 | B9: =IF(ISBLANK($A9),"NO_CODE",VLOOKUP($A9,'UPD Questions_290926 '!$E$1:$N$300,MATCH(B$1,'UPD Questions_290926 '!$E$1:$N$1,0),0)&"") -> Planning | C9: =IF(ISBLANK($A9),"NO_CODE",VLOOKUP($A9,'UPD Questions_290926 '!$E$1:$N$300,MATCH(C$1,'UPD Questions_290926 '!$E$1:$N$1,0),0)&"") -> Legal and institutional planning architecture | D9: =IF(ISBLANK($A9),"NO_CODE",VLOOKUP($A9,'UPD Questions_290926 '!$E$1:$N$300,MATCH(D$1,'UPD Questions_290926 '!$E$1:$N$1,0),0)&"") -> Spatial planning hierarchy | E9: =IF(ISBLANK($A9),"NO_CODE",VLOOKUP($A9,'UPD Questions_290926 '!$E$1:$N$300,MATCH(E$1,'UPD Questions_290926 '!$E$1:$N$1,0),0)&"") -> MQ | F9: =IF(ISBLANK($A9),"NO_CODE",VLOOKUP($A9,'UPD Questions_290926 '!$E$1:$N$300,MATCH(F$1,'UPD Questions_290926 '!$E$1:$N$1,0),0)&"") -> Is the planning boundary of the municipal/city plan aligned with political and administrative boundaries? | G9: =IF(ISBLANK($A9),"NO_CODE",VLOOKUP($A9,'UPD Questions_290926 '!$E$1:$N$300,MATCH(G$1,'UPD Questions_290926 '!$E$1:$N$1,0),0)&"") -> Law or Policy | H9: =IF(ISBLANK($A9),"NO_CODE",VLOOKUP($A9,'UPD Questions_290926 '!$E$1:$N$300,MATCH(H$1,'UPD Questions_290926 '!$E$1:$N$1,0),0)) -> 10 | I9: =IF($H9=0,"NA",IF($A9=INDIRECT("'"&$A9&"'!$B$1"),IF(VLOOKUP(I$1,INDIRECT("'"&$A9&"'!$A$12:$Z$41"),MATCH("Points (Auto-generate)",INDIRECT("'"&$A9&"'!$A$12:$Z$12"),0),0)="","?",VLOOKUP(I$1,INDIRECT("'"&$A9&"'!$A$12:$Z$41"),MATCH("Points (Auto-generate)",INDIRECT("'"&$A9&"'!$A$12:$Z$12"),0),0)),"ER")) -> ? | J9: =IF($H9=0,"NA",IF($A9=INDIRECT("'"&$A9&"'!$B$1"),IF(VLOOKUP(J$1,INDIRECT("'"&$A9&"'!$A$12:$Z$41"),MATCH("Points (Auto-generate)",INDIRECT("'"&$A9&"'!$A$12:$Z$12"),0),0)="","?",VLOOKUP(J$1,INDIRECT("'"&$A9&"'!$A$12:$Z$41"),MATCH("Points (Auto-generate)",INDIRECT("'"&$A9&"'!$A$12:$Z$12"),0),0)),"ER")) -> 10 | K9: =IF($H9=0,"NA",IF($A9=INDIRECT("'"&$A9&"'!$B$1"),IF(VLOOKUP(K$1,INDIRECT("'"&$A9&"'!$A$12:$Z$41"),MATCH("Points (Auto-generate)",INDIRECT("'"&$A9&"'!$A$12:$Z$12"),0),0)="","?",VLOOKUP(K$1,INDIRECT("'"&$A9&"'!$A$12:$Z$41"),MATCH("Points (Auto-generate)",INDIRECT("'"&$A9&"'!$A$12:$Z$12"),0),0)),"ER")) -> ? | L9: =IF($H9=0,"NA",IF($A9=INDIRECT("'"&$A9&"'!$B$1"),IF(VLOOKUP(L$1,INDIRECT("'"&$A9&"'!$A$12:$Z$41"),MATCH("Points (Auto-generate)",INDIRECT("'"&$A9&"'!$A$12:$Z$12"),0),0)="","?",VLOOKUP(L$1,INDIRECT("'"&$A9&"'!$A$12:$Z$41"),MATCH("Points (Auto-generate)",INDIRECT("'"&$A9&"'!$A$12:$Z$12"),0),0)),"ER")) -> ? | M9: =IF($H9=0,"NA",IF($A9=INDIRECT("'"&$A9&"'!$B$1"),IF(VLOOKUP(M$1,INDIRECT("'"&$A9&"'!$A$12:$Z$41"),MATCH("Points (Auto-generate)",INDIRECT("'"&$A9&"'!$A$12:$Z$12"),0),0)="","?",VLOOKUP(M$1,INDIRECT("'"&$A9&"'!$A$12:$Z$41"),MATCH("Points (Auto-generate)",INDIRECT("'"&$A9&"'!$A$12:$Z$12"),0),0)),"ER")) -> ? | N9: =IF($H9=0,"NA",IF($A9=INDIRECT("'"&$A9&"'!$B$1"),IF(VLOOKUP(N$1,INDIRECT("'"&$A9&"'!$A$12:$Z$41"),MATCH("Points (Auto-generate)",INDIRECT("'"&$A9&"'!$A$12:$Z$12"),0),0)="","?",VLOOKUP(N$1,INDIRECT("'"&$A9&"'!$A$12:$Z$41"),MATCH("Points (Auto-generate)",INDIRECT("'"&$A9&"'!$A$12:$Z$12"),0),0)),"ER")) -> ? | O9: =IF($H9=0,"NA",IF($A9=INDIRECT("'"&$A9&"'!$B$1"),IF(VLOOKUP(O$1,INDIRECT("'"&$A9&"'!$A$12:$Z$41"),MATCH("Points (Auto-generate)",INDIRECT("'"&$A9&"'!$A$12:$Z$12"),0),0)="","?",VLOOKUP(O$1,INDIRECT("'"&$A9&"'!$A$12:$Z$41"),MATCH("Points (Auto-generate)",INDIRECT("'"&$A9&"'!$A$12:$Z$12"),0),0)),"ER")) -> ? | P9: =IF($H9=0,"NA",IF($A9=INDIRECT("'"&$A9&"'!$B$1"),IF(VLOOKUP(P$1,INDIRECT("'"&$A9&"'!$A$12:$Z$41"),MATCH("Points (Auto-generate)",INDIRECT("'"&$A9&"'!$A$12:$Z$12"),0),0)="","?",VLOOKUP(P$1,INDIRECT("'"&$A9&"'!$A$12:$Z$41"),MATCH("Points (Auto-generate)",INDIRECT("'"&$A9&"'!$A$12:$Z$12"),0),0)),"ER")) -> ? | ... AK9: =IF($H9=0,"NA",IF($A9=INDIRECT("'"&$A9&"'!$B$1"),IF(VLOOKUP(AK$1,INDIRECT("'"&$A9&"'!$A$12:$Z$41"),MATCH("Points (Auto-generate)",INDIRECT("'"&$A9&"'!$A$12:$Z$12"),0),0)="","?",VLOOKUP(AK$1,INDIRECT("'"&$A9&"'!$A$12:$Z$41"),MATCH("Points (Auto-generate)",INDIRECT("'"&$A9&"'!$A$12:$Z$12"),0),0)),"ER")) -> ?
A10: UPD5 | B10: =IF(ISBLANK($A10),"NO_CODE",VLOOKUP($A10,'UPD Questions_290926 '!$E$1:$N$300,MATCH(B$1,'UPD Questions_290926 '!$E$1:$N$1,0),0)&"") -> Planning | C10: =IF(ISBLANK($A10),"NO_CODE",VLOOKUP($A10,'UPD Questions_290926 '!$E$1:$N$300,MATCH(C$1,'UPD Questions_290926 '!$E$1:$N$1,0),0)&"") -> Legal and institutional planning architecture | D10: =IF(ISBLANK($A10),"NO_CODE",VLOOKUP($A10,'UPD Questions_290926 '!$E$1:$N$300,MATCH(D$1,'UPD Questions_290926 '!$E$1:$N$1,0),0)&"") -> Spatial planning hierarchy | E10: =IF(ISBLANK($A10),"NO_CODE",VLOOKUP($A10,'UPD Questions_290926 '!$E$1:$N$300,MATCH(E$1,'UPD Questions_290926 '!$E$1:$N$1,0),0)&"") -> MQ | F10: =IF(ISBLANK($A10),"NO_CODE",VLOOKUP($A10,'UPD Questions_290926 '!$E$1:$N$300,MATCH(F$1,'UPD Questions_290926 '!$E$1:$N$1,0),0)&"") -> Is there a clear decentralised procedure for approvals of each level of plans? | G10: =IF(ISBLANK($A10),"NO_CODE",VLOOKUP($A10,'UPD Questions_290926 '!$E$1:$N$300,MATCH(G$1,'UPD Questions_290926 '!$E$1:$N$1,0),0)&"") -> Law or Policy | H10: =IF(ISBLANK($A10),"NO_CODE",VLOOKUP($A10,'UPD Questions_290926 '!$E$1:$N$300,MATCH(H$1,'UPD Questions_290926 '!$E$1:$N$1,0),0)) -> 10 | I10: =IF(OR(I11="ER",I12="ER",I13="ER"),"ER",IF(OR(I11="?",I12="?",I13="?"),"?",IF(AND(I11="NA",I12="NA",I13="NA"),"NA",SUM(I11,I12,I13)/((I11<>"NA")*$H$11+(I12<>"NA")*$H$12+(I13<>"NA")*$H$13)*$H10))) -> ? | J10: =IF(OR(J11="ER",J12="ER",J13="ER"),"ER",IF(OR(J11="?",J12="?",J13="?"),"?",IF(AND(J11="NA",J12="NA",J13="NA"),"NA",SUM(J11,J12,J13)/((J11<>"NA")*$H$11+(J12<>"NA")*$H$12+(J13<>"NA")*$H$13)*$H10))) -> ? | K10: =IF(OR(K11="ER",K12="ER",K13="ER"),"ER",IF(OR(K11="?",K12="?",K13="?"),"?",IF(AND(K11="NA",K12="NA",K13="NA"),"NA",SUM(K11,K12,K13)/((K11<>"NA")*$H$11+(K12<>"NA")*$H$12+(K13<>"NA")*$H$13)*$H10))) -> ? | L10: =IF(OR(L11="ER",L12="ER",L13="ER"),"ER",IF(OR(L11="?",L12="?",L13="?"),"?",IF(AND(L11="NA",L12="NA",L13="NA"),"NA",SUM(L11,L12,L13)/((L11<>"NA")*$H$11+(L12<>"NA")*$H$12+(L13<>"NA")*$H$13)*$H10))) -> ? | M10: =IF(OR(M11="ER",M12="ER",M13="ER"),"ER",IF(OR(M11="?",M12="?",M13="?"),"?",IF(AND(M11="NA",M12="NA",M13="NA"),"NA",SUM(M11,M12,M13)/((M11<>"NA")*$H$11+(M12<>"NA")*$H$12+(M13<>"NA")*$H$13)*$H10))) -> ? | N10: =IF(OR(N11="ER",N12="ER",N13="ER"),"ER",IF(OR(N11="?",N12="?",N13="?"),"?",IF(AND(N11="NA",N12="NA",N13="NA"),"NA",SUM(N11,N12,N13)/((N11<>"NA")*$H$11+(N12<>"NA")*$H$12+(N13<>"NA")*$H$13)*$H10))) -> ? | O10: =IF(OR(O11="ER",O12="ER",O13="ER"),"ER",IF(OR(O11="?",O12="?",O13="?"),"?",IF(AND(O11="NA",O12="NA",O13="NA"),"NA",SUM(O11,O12,O13)/((O11<>"NA")*$H$11+(O12<>"NA")*$H$12+(O13<>"NA")*$H$13)*$H10))) -> ? | P10: =IF(OR(P11="ER",P12="ER",P13="ER"),"ER",IF(OR(P11="?",P12="?",P13="?"),"?",IF(AND(P11="NA",P12="NA",P13="NA"),"NA",SUM(P11,P12,P13)/((P11<>"NA")*$H$11+(P12<>"NA")*$H$12+(P13<>"NA")*$H$13)*$H10))) -> ? | ... AK10: =IF(OR(AK11="ER",AK12="ER",AK13="ER"),"ER",IF(OR(AK11="?",AK12="?",AK13="?"),"?",IF(AND(AK11="NA",AK12="NA",AK13="NA"),"NA",SUM(AK11,AK12,AK13)/((AK11<>"NA")*$H$11+(AK12<>"NA")*$H$12+(AK13<>"NA")*$H$13)*$H10))) -> ?
A11: UPD5a | B11: =IF(ISBLANK($A11),"NO_CODE",VLOOKUP($A11,'UPD Questions_290926 '!$E$1:$N$300,MATCH(B$1,'UPD Questions_290926 '!$E$1:$N$1,0),0)&"") -> Planning | C11: =IF(ISBLANK($A11),"NO_CODE",VLOOKUP($A11,'UPD Questions_290926 '!$E$1:$N$300,MATCH(C$1,'UPD Questions_290926 '!$E$1:$N$1,0),0)&"") -> Legal and institutional planning architecture | D11: =IF(ISBLANK($A11),"NO_CODE",VLOOKUP($A11,'UPD Questions_290926 '!$E$1:$N$300,MATCH(D$1,'UPD Questions_290926 '!$E$1:$N$1,0),0)&"") -> Spatial planning hierarchy | E11: =IF(ISBLANK($A11),"NO_CODE",VLOOKUP($A11,'UPD Questions_290926 '!$E$1:$N$300,MATCH(E$1,'UPD Questions_290926 '!$E$1:$N$1,0),0)&"") -> SQ | F11: =IF(ISBLANK($A11),"NO_CODE",VLOOKUP($A11,'UPD Questions_290926 '!$E$1:$N$300,MATCH(F$1,'UPD Questions_290926 '!$E$1:$N$1,0),0)&"") -> Does the law mandate that the metropolitan/regional plan be approved by the state government? | G11: =IF(ISBLANK($A11),"NO_CODE",VLOOKUP($A11,'UPD Questions_290926 '!$E$1:$N$300,MATCH(G$1,'UPD Questions_290926 '!$E$1:$N$1,0),0)&"") -> Law or Policy | H11: =IF(ISBLANK($A11),"NO_CODE",VLOOKUP($A11,'UPD Questions_290926 '!$E$1:$N$300,MATCH(H$1,'UPD Questions_290926 '!$E$1:$N$1,0),0)) -> 3.33 | I11: =IF($H11=0,"NA",IF($A11=INDIRECT("'"&$A11&"'!$B$1"),IF(VLOOKUP(I$1,INDIRECT("'"&$A11&"'!$A$12:$Z$41"),MATCH("Points (Auto-generate)",INDIRECT("'"&$A11&"'!$A$12:$Z$12"),0),0)="","?",VLOOKUP(I$1,INDIRECT("'"&$A11&"'!$A$12:$Z$41"),MATCH("Points (Auto-generate)",INDIRECT("'"&$A11&"'!$A$12:$Z$12"),0),0)),"ER")) -> ? | J11: =IF($H11=0,"NA",IF($A11=INDIRECT("'"&$A11&"'!$B$1"),IF(VLOOKUP(J$1,INDIRECT("'"&$A11&"'!$A$12:$Z$41"),MATCH("Points (Auto-generate)",INDIRECT("'"&$A11&"'!$A$12:$Z$12"),0),0)="","?",VLOOKUP(J$1,INDIRECT("'"&$A11&"'!$A$12:$Z$41"),MATCH("Points (Auto-generate)",INDIRECT("'"&$A11&"'!$A$12:$Z$12"),0),0)),"ER")) -> ? | K11: =IF($H11=0,"NA",IF($A11=INDIRECT("'"&$A11&"'!$B$1"),IF(VLOOKUP(K$1,INDIRECT("'"&$A11&"'!$A$12:$Z$41"),MATCH("Points (Auto-generate)",INDIRECT("'"&$A11&"'!$A$12:$Z$12"),0),0)="","?",VLOOKUP(K$1,INDIRECT("'"&$A11&"'!$A$12:$Z$41"),MATCH("Points (Auto-generate)",INDIRECT("'"&$A11&"'!$A$12:$Z$12"),0),0)),"ER")) -> ? | L11: =IF($H11=0,"NA",IF($A11=INDIRECT("'"&$A11&"'!$B$1"),IF(VLOOKUP(L$1,INDIRECT("'"&$A11&"'!$A$12:$Z$41"),MATCH("Points (Auto-generate)",INDIRECT("'"&$A11&"'!$A$12:$Z$12"),0),0)="","?",VLOOKUP(L$1,INDIRECT("'"&$A11&"'!$A$12:$Z$41"),MATCH("Points (Auto-generate)",INDIRECT("'"&$A11&"'!$A$12:$Z$12"),0),0)),"ER")) -> ? | M11: =IF($H11=0,"NA",IF($A11=INDIRECT("'"&$A11&"'!$B$1"),IF(VLOOKUP(M$1,INDIRECT("'"&$A11&"'!$A$12:$Z$41"),MATCH("Points (Auto-generate)",INDIRECT("'"&$A11&"'!$A$12:$Z$12"),0),0)="","?",VLOOKUP(M$1,INDIRECT("'"&$A11&"'!$A$12:$Z$41"),MATCH("Points (Auto-generate)",INDIRECT("'"&$A11&"'!$A$12:$Z$12"),0),0)),"ER")) -> ? | N11: =IF($H11=0,"NA",IF($A11=INDIRECT("'"&$A11&"'!$B$1"),IF(VLOOKUP(N$1,INDIRECT("'"&$A11&"'!$A$12:$Z$41"),MATCH("Points (Auto-generate)",INDIRECT("'"&$A11&"'!$A$12:$Z$12"),0),0)="","?",VLOOKUP(N$1,INDIRECT("'"&$A11&"'!$A$12:$Z$41"),MATCH("Points (Auto-generate)",INDIRECT("'"&$A11&"'!$A$12:$Z$12"),0),0)),"ER")) -> ? | O11: =IF($H11=0,"NA",IF($A11=INDIRECT("'"&$A11&"'!$B$1"),IF(VLOOKUP(O$1,INDIRECT("'"&$A11&"'!$A$12:$Z$41"),MATCH("Points (Auto-generate)",INDIRECT("'"&$A11&"'!$A$12:$Z$12"),0),0)="","?",VLOOKUP(O$1,INDIRECT("'"&$A11&"'!$A$12:$Z$41"),MATCH("Points (Auto-generate)",INDIRECT("'"&$A11&"'!$A$12:$Z$12"),0),0)),"ER")) -> ? | P11: =IF($H11=0,"NA",IF($A11=INDIRECT("'"&$A11&"'!$B$1"),IF(VLOOKUP(P$1,INDIRECT("'"&$A11&"'!$A$12:$Z$41"),MATCH("Points (Auto-generate)",INDIRECT("'"&$A11&"'!$A$12:$Z$12"),0),0)="","?",VLOOKUP(P$1,INDIRECT("'"&$A11&"'!$A$12:$Z$41"),MATCH("Points (Auto-generate)",INDIRECT("'"&$A11&"'!$A$12:$Z$12"),0),0)),"ER")) -> ? | ... AK11: =IF($H11=0,"NA",IF($A11=INDIRECT("'"&$A11&"'!$B$1"),IF(VLOOKUP(AK$1,INDIRECT("'"&$A11&"'!$A$12:$Z$41"),MATCH("Points (Auto-generate)",INDIRECT("'"&$A11&"'!$A$12:$Z$12"),0),0)="","?",VLOOKUP(AK$1,INDIRECT("'"&$A11&"'!$A$12:$Z$41"),MATCH("Points (Auto-generate)",INDIRECT("'"&$A11&"'!$A$12:$Z$12"),0),0)),"ER")) -> ?
A12: UPD5b | B12: =IF(ISBLANK($A12),"NO_CODE",VLOOKUP($A12,'UPD Questions_290926 '!$E$1:$N$300,MATCH(B$1,'UPD Questions_290926 '!$E$1:$N$1,0),0)&"") -> Planning | C12: =IF(ISBLANK($A12),"NO_CODE",VLOOKUP($A12,'UPD Questions_290926 '!$E$1:$N$300,MATCH(C$1,'UPD Questions_290926 '!$E$1:$N$1,0),0)&"") -> Legal and institutional planning architecture | D12: =IF(ISBLANK($A12),"NO_CODE",VLOOKUP($A12,'UPD Questions_290926 '!$E$1:$N$300,MATCH(D$1,'UPD Questions_290926 '!$E$1:$N$1,0),0)&"") -> Spatial planning hierarchy | E12: =IF(ISBLANK($A12),"NO_CODE",VLOOKUP($A12,'UPD Questions_290926 '!$E$1:$N$300,MATCH(E$1,'UPD Questions_290926 '!$E$1:$N$1,0),0)&"") -> SQ | F12: =IF(ISBLANK($A12),"NO_CODE",VLOOKUP($A12,'UPD Questions_290926 '!$E$1:$N$300,MATCH(F$1,'UPD Questions_290926 '!$E$1:$N$1,0),0)&"") -> Does the law mandate that the municipal/city plan be approved by the MPC (Metropolitan Planning Committee) for metropolitan cities or by DPC (District Planning Committee) for non-metropolitan cities? | G12: =IF(ISBLANK($A12),"NO_CODE",VLOOKUP($A12,'UPD Questions_290926 '!$E$1:$N$300,MATCH(G$1,'UPD Questions_290926 '!$E$1:$N$1,0),0)&"") -> Law or Policy | H12: =IF(ISBLANK($A12),"NO_CODE",VLOOKUP($A12,'UPD Questions_290926 '!$E$1:$N$300,MATCH(H$1,'UPD Questions_290926 '!$E$1:$N$1,0),0)) -> 3.33 | I12: =IF($H12=0,"NA",IF($A12=INDIRECT("'"&$A12&"'!$B$1"),IF(VLOOKUP(I$1,INDIRECT("'"&$A12&"'!$A$12:$Z$41"),MATCH("Points (Auto-generate)",INDIRECT("'"&$A12&"'!$A$12:$Z$12"),0),0)="","?",VLOOKUP(I$1,INDIRECT("'"&$A12&"'!$A$12:$Z$41"),MATCH("Points (Auto-generate)",INDIRECT("'"&$A12&"'!$A$12:$Z$12"),0),0)),"ER")) -> ? | J12: =IF($H12=0,"NA",IF($A12=INDIRECT("'"&$A12&"'!$B$1"),IF(VLOOKUP(J$1,INDIRECT("'"&$A12&"'!$A$12:$Z$41"),MATCH("Points (Auto-generate)",INDIRECT("'"&$A12&"'!$A$12:$Z$12"),0),0)="","?",VLOOKUP(J$1,INDIRECT("'"&$A12&"'!$A$12:$Z$41"),MATCH("Points (Auto-generate)",INDIRECT("'"&$A12&"'!$A$12:$Z$12"),0),0)),"ER")) -> ? | K12: =IF($H12=0,"NA",IF($A12=INDIRECT("'"&$A12&"'!$B$1"),IF(VLOOKUP(K$1,INDIRECT("'"&$A12&"'!$A$12:$Z$41"),MATCH("Points (Auto-generate)",INDIRECT("'"&$A12&"'!$A$12:$Z$12"),0),0)="","?",VLOOKUP(K$1,INDIRECT("'"&$A12&"'!$A$12:$Z$41"),MATCH("Points (Auto-generate)",INDIRECT("'"&$A12&"'!$A$12:$Z$12"),0),0)),"ER")) -> ? | L12: =IF($H12=0,"NA",IF($A12=INDIRECT("'"&$A12&"'!$B$1"),IF(VLOOKUP(L$1,INDIRECT("'"&$A12&"'!$A$12:$Z$41"),MATCH("Points (Auto-generate)",INDIRECT("'"&$A12&"'!$A$12:$Z$12"),0),0)="","?",VLOOKUP(L$1,INDIRECT("'"&$A12&"'!$A$12:$Z$41"),MATCH("Points (Auto-generate)",INDIRECT("'"&$A12&"'!$A$12:$Z$12"),0),0)),"ER")) -> ? | M12: =IF($H12=0,"NA",IF($A12=INDIRECT("'"&$A12&"'!$B$1"),IF(VLOOKUP(M$1,INDIRECT("'"&$A12&"'!$A$12:$Z$41"),MATCH("Points (Auto-generate)",INDIRECT("'"&$A12&"'!$A$12:$Z$12"),0),0)="","?",VLOOKUP(M$1,INDIRECT("'"&$A12&"'!$A$12:$Z$41"),MATCH("Points (Auto-generate)",INDIRECT("'"&$A12&"'!$A$12:$Z$12"),0),0)),"ER")) -> ? | N12: =IF($H12=0,"NA",IF($A12=INDIRECT("'"&$A12&"'!$B$1"),IF(VLOOKUP(N$1,INDIRECT("'"&$A12&"'!$A$12:$Z$41"),MATCH("Points (Auto-generate)",INDIRECT("'"&$A12&"'!$A$12:$Z$12"),0),0)="","?",VLOOKUP(N$1,INDIRECT("'"&$A12&"'!$A$12:$Z$41"),MATCH("Points (Auto-generate)",INDIRECT("'"&$A12&"'!$A$12:$Z$12"),0),0)),"ER")) -> ? | O12: =IF($H12=0,"NA",IF($A12=INDIRECT("'"&$A12&"'!$B$1"),IF(VLOOKUP(O$1,INDIRECT("'"&$A12&"'!$A$12:$Z$41"),MATCH("Points (Auto-generate)",INDIRECT("'"&$A12&"'!$A$12:$Z$12"),0),0)="","?",VLOOKUP(O$1,INDIRECT("'"&$A12&"'!$A$12:$Z$41"),MATCH("Points (Auto-generate)",INDIRECT("'"&$A12&"'!$A$12:$Z$12"),0),0)),"ER")) -> ? | P12: =IF($H12=0,"NA",IF($A12=INDIRECT("'"&$A12&"'!$B$1"),IF(VLOOKUP(P$1,INDIRECT("'"&$A12&"'!$A$12:$Z$41"),MATCH("Points (Auto-generate)",INDIRECT("'"&$A12&"'!$A$12:$Z$12"),0),0)="","?",VLOOKUP(P$1,INDIRECT("'"&$A12&"'!$A$12:$Z$41"),MATCH("Points (Auto-generate)",INDIRECT("'"&$A12&"'!$A$12:$Z$12"),0),0)),"ER")) -> ? | ... AK12: =IF($H12=0,"NA",IF($A12=INDIRECT("'"&$A12&"'!$B$1"),IF(VLOOKUP(AK$1,INDIRECT("'"&$A12&"'!$A$12:$Z$41"),MATCH("Points (Auto-generate)",INDIRECT("'"&$A12&"'!$A$12:$Z$12"),0),0)="","?",VLOOKUP(AK$1,INDIRECT("'"&$A12&"'!$A$12:$Z$41"),MATCH("Points (Auto-generate)",INDIRECT("'"&$A12&"'!$A$12:$Z$12"),0),0)),"ER")) -> ?
A13: UPD5c | B13: =IF(ISBLANK($A13),"NO_CODE",VLOOKUP($A13,'UPD Questions_290926 '!$E$1:$N$300,MATCH(B$1,'UPD Questions_290926 '!$E$1:$N$1,0),0)&"") -> Planning | C13: =IF(ISBLANK($A13),"NO_CODE",VLOOKUP($A13,'UPD Questions_290926 '!$E$1:$N$300,MATCH(C$1,'UPD Questions_290926 '!$E$1:$N$1,0),0)&"") -> Legal and institutional planning architecture | D13: =IF(ISBLANK($A13),"NO_CODE",VLOOKUP($A13,'UPD Questions_290926 '!$E$1:$N$300,MATCH(D$1,'UPD Questions_290926 '!$E$1:$N$1,0),0)&"") -> Spatial planning hierarchy | E13: =IF(ISBLANK($A13),"NO_CODE",VLOOKUP($A13,'UPD Questions_290926 '!$E$1:$N$300,MATCH(E$1,'UPD Questions_290926 '!$E$1:$N$1,0),0)&"") -> SQ | F13: =IF(ISBLANK($A13),"NO_CODE",VLOOKUP($A13,'UPD Questions_290926 '!$E$1:$N$300,MATCH(F$1,'UPD Questions_290926 '!$E$1:$N$1,0),0)&"") -> Does the law mandate that the ward(s)/local plan be approved by the ULG? | G13: =IF(ISBLANK($A13),"NO_CODE",VLOOKUP($A13,'UPD Questions_290926 '!$E$1:$N$300,MATCH(G$1,'UPD Questions_290926 '!$E$1:$N$1,0),0)&"") -> Law or Policy | H13: =IF(ISBLANK($A13),"NO_CODE",VLOOKUP($A13,'UPD Questions_290926 '!$E$1:$N$300,MATCH(H$1,'UPD Questions_290926 '!$E$1:$N$1,0),0)) -> 3.33 | I13: =IF($H13=0,"NA",IF($A13=INDIRECT("'"&$A13&"'!$B$1"),IF(VLOOKUP(I$1,INDIRECT("'"&$A13&"'!$A$12:$Z$41"),MATCH("Points (Auto-generate)",INDIRECT("'"&$A13&"'!$A$12:$Z$12"),0),0)="","?",VLOOKUP(I$1,INDIRECT("'"&$A13&"'!$A$12:$Z$41"),MATCH("Points (Auto-generate)",INDIRECT("'"&$A13&"'!$A$12:$Z$12"),0),0)),"ER")) -> ? | J13: =IF($H13=0,"NA",IF($A13=INDIRECT("'"&$A13&"'!$B$1"),IF(VLOOKUP(J$1,INDIRECT("'"&$A13&"'!$A$12:$Z$41"),MATCH("Points (Auto-generate)",INDIRECT("'"&$A13&"'!$A$12:$Z$12"),0),0)="","?",VLOOKUP(J$1,INDIRECT("'"&$A13&"'!$A$12:$Z$41"),MATCH("Points (Auto-generate)",INDIRECT("'"&$A13&"'!$A$12:$Z$12"),0),0)),"ER")) -> ? | K13: =IF($H13=0,"NA",IF($A13=INDIRECT("'"&$A13&"'!$B$1"),IF(VLOOKUP(K$1,INDIRECT("'"&$A13&"'!$A$12:$Z$41"),MATCH("Points (Auto-generate)",INDIRECT("'"&$A13&"'!$A$12:$Z$12"),0),0)="","?",VLOOKUP(K$1,INDIRECT("'"&$A13&"'!$A$12:$Z$41"),MATCH("Points (Auto-generate)",INDIRECT("'"&$A13&"'!$A$12:$Z$12"),0),0)),"ER")) -> ? | L13: =IF($H13=0,"NA",IF($A13=INDIRECT("'"&$A13&"'!$B$1"),IF(VLOOKUP(L$1,INDIRECT("'"&$A13&"'!$A$12:$Z$41"),MATCH("Points (Auto-generate)",INDIRECT("'"&$A13&"'!$A$12:$Z$12"),0),0)="","?",VLOOKUP(L$1,INDIRECT("'"&$A13&"'!$A$12:$Z$41"),MATCH("Points (Auto-generate)",INDIRECT("'"&$A13&"'!$A$12:$Z$12"),0),0)),"ER")) -> ? | M13: =IF($H13=0,"NA",IF($A13=INDIRECT("'"&$A13&"'!$B$1"),IF(VLOOKUP(M$1,INDIRECT("'"&$A13&"'!$A$12:$Z$41"),MATCH("Points (Auto-generate)",INDIRECT("'"&$A13&"'!$A$12:$Z$12"),0),0)="","?",VLOOKUP(M$1,INDIRECT("'"&$A13&"'!$A$12:$Z$41"),MATCH("Points (Auto-generate)",INDIRECT("'"&$A13&"'!$A$12:$Z$12"),0),0)),"ER")) -> ? | N13: =IF($H13=0,"NA",IF($A13=INDIRECT("'"&$A13&"'!$B$1"),IF(VLOOKUP(N$1,INDIRECT("'"&$A13&"'!$A$12:$Z$41"),MATCH("Points (Auto-generate)",INDIRECT("'"&$A13&"'!$A$12:$Z$12"),0),0)="","?",VLOOKUP(N$1,INDIRECT("'"&$A13&"'!$A$12:$Z$41"),MATCH("Points (Auto-generate)",INDIRECT("'"&$A13&"'!$A$12:$Z$12"),0),0)),"ER")) -> ? | O13: =IF($H13=0,"NA",IF($A13=INDIRECT("'"&$A13&"'!$B$1"),IF(VLOOKUP(O$1,INDIRECT("'"&$A13&"'!$A$12:$Z$41"),MATCH("Points (Auto-generate)",INDIRECT("'"&$A13&"'!$A$12:$Z$12"),0),0)="","?",VLOOKUP(O$1,INDIRECT("'"&$A13&"'!$A$12:$Z$41"),MATCH("Points (Auto-generate)",INDIRECT("'"&$A13&"'!$A$12:$Z$12"),0),0)),"ER")) -> ? | P13: =IF($H13=0,"NA",IF($A13=INDIRECT("'"&$A13&"'!$B$1"),IF(VLOOKUP(P$1,INDIRECT("'"&$A13&"'!$A$12:$Z$41"),MATCH("Points (Auto-generate)",INDIRECT("'"&$A13&"'!$A$12:$Z$12"),0),0)="","?",VLOOKUP(P$1,INDIRECT("'"&$A13&"'!$A$12:$Z$41"),MATCH("Points (Auto-generate)",INDIRECT("'"&$A13&"'!$A$12:$Z$12"),0),0)),"ER")) -> ? | ... AK13: =IF($H13=0,"NA",IF($A13=INDIRECT("'"&$A13&"'!$B$1"),IF(VLOOKUP(AK$1,INDIRECT("'"&$A13&"'!$A$12:$Z$41"),MATCH("Points (Auto-generate)",INDIRECT("'"&$A13&"'!$A$12:$Z$12"),0),0)="","?",VLOOKUP(AK$1,INDIRECT("'"&$A13&"'!$A$12:$Z$41"),MATCH("Points (Auto-generate)",INDIRECT("'"&$A13&"'!$A$12:$Z$12"),0),0)),"ER")) -> ?
A14: UPD6 | B14: =IF(ISBLANK($A14),"NO_CODE",VLOOKUP($A14,'UPD Questions_290926 '!$E$1:$N$300,MATCH(B$1,'UPD Questions_290926 '!$E$1:$N$1,0),0)&"") -> Planning | C14: =IF(ISBLANK($A14),"NO_CODE",VLOOKUP($A14,'UPD Questions_290926 '!$E$1:$N$300,MATCH(C$1,'UPD Questions_290926 '!$E$1:$N$1,0),0)&"") -> Legal and institutional planning architecture | D14: =IF(ISBLANK($A14),"NO_CODE",VLOOKUP($A14,'UPD Questions_290926 '!$E$1:$N$300,MATCH(D$1,'UPD Questions_290926 '!$E$1:$N$1,0),0)&"") -> Objectives of each level of Municipal/City Plans | E14: =IF(ISBLANK($A14),"NO_CODE",VLOOKUP($A14,'UPD Questions_290926 '!$E$1:$N$300,MATCH(E$1,'UPD Questions_290926 '!$E$1:$N$1,0),0)&"") -> MQ | F14: =IF(ISBLANK($A14),"NO_CODE",VLOOKUP($A14,'UPD Questions_290926 '!$E$1:$N$300,MATCH(F$1,'UPD Questions_290926 '!$E$1:$N$1,0),0)&"") -> Does the Act clearly define the objectives/contents of each level of spatial plan? | G14: =IF(ISBLANK($A14),"NO_CODE",VLOOKUP($A14,'UPD Questions_290926 '!$E$1:$N$300,MATCH(G$1,'UPD Questions_290926 '!$E$1:$N$1,0),0)&"") -> Law or Policy | H14: =IF(ISBLANK($A14),"NO_CODE",VLOOKUP($A14,'UPD Questions_290926 '!$E$1:$N$300,MATCH(H$1,'UPD Questions_290926 '!$E$1:$N$1,0),0)) -> 10 | I14: =IF($H14=0,"NA",IF($A14=INDIRECT("'"&$A14&"'!$B$1"),IF(VLOOKUP(I$1,INDIRECT("'"&$A14&"'!$A$12:$Z$41"),MATCH("Points (Auto-generate)",INDIRECT("'"&$A14&"'!$A$12:$Z$12"),0),0)="","?",VLOOKUP(I$1,INDIRECT("'"&$A14&"'!$A$12:$Z$41"),MATCH("Points (Auto-generate)",INDIRECT("'"&$A14&"'!$A$12:$Z$12"),0),0)),"ER")) -> ? | J14: =IF($H14=0,"NA",IF($A14=INDIRECT("'"&$A14&"'!$B$1"),IF(VLOOKUP(J$1,INDIRECT("'"&$A14&"'!$A$12:$Z$41"),MATCH("Points (Auto-generate)",INDIRECT("'"&$A14&"'!$A$12:$Z$12"),0),0)="","?",VLOOKUP(J$1,INDIRECT("'"&$A14&"'!$A$12:$Z$41"),MATCH("Points (Auto-generate)",INDIRECT("'"&$A14&"'!$A$12:$Z$12"),0),0)),"ER")) -> ? | K14: =IF($H14=0,"NA",IF($A14=INDIRECT("'"&$A14&"'!$B$1"),IF(VLOOKUP(K$1,INDIRECT("'"&$A14&"'!$A$12:$Z$41"),MATCH("Points (Auto-generate)",INDIRECT("'"&$A14&"'!$A$12:$Z$12"),0),0)="","?",VLOOKUP(K$1,INDIRECT("'"&$A14&"'!$A$12:$Z$41"),MATCH("Points (Auto-generate)",INDIRECT("'"&$A14&"'!$A$12:$Z$12"),0),0)),"ER")) -> ? | L14: =IF($H14=0,"NA",IF($A14=INDIRECT("'"&$A14&"'!$B$1"),IF(VLOOKUP(L$1,INDIRECT("'"&$A14&"'!$A$12:$Z$41"),MATCH("Points (Auto-generate)",INDIRECT("'"&$A14&"'!$A$12:$Z$12"),0),0)="","?",VLOOKUP(L$1,INDIRECT("'"&$A14&"'!$A$12:$Z$41"),MATCH("Points (Auto-generate)",INDIRECT("'"&$A14&"'!$A$12:$Z$12"),0),0)),"ER")) -> ? | M14: =IF($H14=0,"NA",IF($A14=INDIRECT("'"&$A14&"'!$B$1"),IF(VLOOKUP(M$1,INDIRECT("'"&$A14&"'!$A$12:$Z$41"),MATCH("Points (Auto-generate)",INDIRECT("'"&$A14&"'!$A$12:$Z$12"),0),0)="","?",VLOOKUP(M$1,INDIRECT("'"&$A14&"'!$A$12:$Z$41"),MATCH("Points (Auto-generate)",INDIRECT("'"&$A14&"'!$A$12:$Z$12"),0),0)),"ER")) -> ? | N14: =IF($H14=0,"NA",IF($A14=INDIRECT("'"&$A14&"'!$B$1"),IF(VLOOKUP(N$1,INDIRECT("'"&$A14&"'!$A$12:$Z$41"),MATCH("Points (Auto-generate)",INDIRECT("'"&$A14&"'!$A$12:$Z$12"),0),0)="","?",VLOOKUP(N$1,INDIRECT("'"&$A14&"'!$A$12:$Z$41"),MATCH("Points (Auto-generate)",INDIRECT("'"&$A14&"'!$A$12:$Z$12"),0),0)),"ER")) -> ? | O14: =IF($H14=0,"NA",IF($A14=INDIRECT("'"&$A14&"'!$B$1"),IF(VLOOKUP(O$1,INDIRECT("'"&$A14&"'!$A$12:$Z$41"),MATCH("Points (Auto-generate)",INDIRECT("'"&$A14&"'!$A$12:$Z$12"),0),0)="","?",VLOOKUP(O$1,INDIRECT("'"&$A14&"'!$A$12:$Z$41"),MATCH("Points (Auto-generate)",INDIRECT("'"&$A14&"'!$A$12:$Z$12"),0),0)),"ER")) -> ? | P14: =IF($H14=0,"NA",IF($A14=INDIRECT("'"&$A14&"'!$B$1"),IF(VLOOKUP(P$1,INDIRECT("'"&$A14&"'!$A$12:$Z$41"),MATCH("Points (Auto-generate)",INDIRECT("'"&$A14&"'!$A$12:$Z$12"),0),0)="","?",VLOOKUP(P$1,INDIRECT("'"&$A14&"'!$A$12:$Z$41"),MATCH("Points (Auto-generate)",INDIRECT("'"&$A14&"'!$A$12:$Z$12"),0),0)),"ER")) -> ? | ... AK14: =IF($H14=0,"NA",IF($A14=INDIRECT("'"&$A14&"'!$B$1"),IF(VLOOKUP(AK$1,INDIRECT("'"&$A14&"'!$A$12:$Z$41"),MATCH("Points (Auto-generate)",INDIRECT("'"&$A14&"'!$A$12:$Z$12"),0),0)="","?",VLOOKUP(AK$1,INDIRECT("'"&$A14&"'!$A$12:$Z$41"),MATCH("Points (Auto-generate)",INDIRECT("'"&$A14&"'!$A$12:$Z$12"),0),0)),"ER")) -> ?
A15: UPD7 | B15: =IF(ISBLANK($A15),"NO_CODE",VLOOKUP($A15,'UPD Questions_290926 '!$E$1:$N$300,MATCH(B$1,'UPD Questions_290926 '!$E$1:$N$1,0),0)&"") -> Planning | C15: =IF(ISBLANK($A15),"NO_CODE",VLOOKUP($A15,'UPD Questions_290926 '!$E$1:$N$300,MATCH(C$1,'UPD Questions_290926 '!$E$1:$N$1,0),0)&"") -> Legal and institutional planning architecture | D15: =IF(ISBLANK($A15),"NO_CODE",VLOOKUP($A15,'UPD Questions_290926 '!$E$1:$N$300,MATCH(D$1,'UPD Questions_290926 '!$E$1:$N$1,0),0)&"") -> Metropolitan and district planning institutions | E15: =IF(ISBLANK($A15),"NO_CODE",VLOOKUP($A15,'UPD Questions_290926 '!$E$1:$N$300,MATCH(E$1,'UPD Questions_290926 '!$E$1:$N$1,0),0)&"") -> MQ | F15: =IF(ISBLANK($A15),"NO_CODE",VLOOKUP($A15,'UPD Questions_290926 '!$E$1:$N$300,MATCH(F$1,'UPD Questions_290926 '!$E$1:$N$1,0),0)&"") -> Does the city have a functional MPC/DPC? | G15: =IF(ISBLANK($A15),"NO_CODE",VLOOKUP($A15,'UPD Questions_290926 '!$E$1:$N$300,MATCH(G$1,'UPD Questions_290926 '!$E$1:$N$1,0),0)&"") -> Law/Policy & Implementation | H15: =IF(ISBLANK($A15),"NO_CODE",VLOOKUP($A15,'UPD Questions_290926 '!$E$1:$N$300,MATCH(H$1,'UPD Questions_290926 '!$E$1:$N$1,0),0)) -> 10 | I15: =IF(OR(I16="ER",I17="ER"),"ER",IF(OR(I16="?",I17="?"),"?",IF(AND(I16="NA",I17="NA"),"NA",SUM(I16,I17)/((I16<>"NA")*$H$16+(I17<>"NA")*$H$17)*$H15))) -> ? | J15: =IF(OR(J16="ER",J17="ER"),"ER",IF(OR(J16="?",J17="?"),"?",IF(AND(J16="NA",J17="NA"),"NA",SUM(J16,J17)/((J16<>"NA")*$H$16+(J17<>"NA")*$H$17)*$H15))) -> ? | K15: =IF(OR(K16="ER",K17="ER"),"ER",IF(OR(K16="?",K17="?"),"?",IF(AND(K16="NA",K17="NA"),"NA",SUM(K16,K17)/((K16<>"NA")*$H$16+(K17<>"NA")*$H$17)*$H15))) -> ? | L15: =IF(OR(L16="ER",L17="ER"),"ER",IF(OR(L16="?",L17="?"),"?",IF(AND(L16="NA",L17="NA"),"NA",SUM(L16,L17)/((L16<>"NA")*$H$16+(L17<>"NA")*$H$17)*$H15))) -> ? | M15: =IF(OR(M16="ER",M17="ER"),"ER",IF(OR(M16="?",M17="?"),"?",IF(AND(M16="NA",M17="NA"),"NA",SUM(M16,M17)/((M16<>"NA")*$H$16+(M17<>"NA")*$H$17)*$H15))) -> ? | N15: =IF(OR(N16="ER",N17="ER"),"ER",IF(OR(N16="?",N17="?"),"?",IF(AND(N16="NA",N17="NA"),"NA",SUM(N16,N17)/((N16<>"NA")*$H$16+(N17<>"NA")*$H$17)*$H15))) -> ? | O15: =IF(OR(O16="ER",O17="ER"),"ER",IF(OR(O16="?",O17="?"),"?",IF(AND(O16="NA",O17="NA"),"NA",SUM(O16,O17)/((O16<>"NA")*$H$16+(O17<>"NA")*$H$17)*$H15))) -> ? | P15: =IF(OR(P16="ER",P17="ER"),"ER",IF(OR(P16="?",P17="?"),"?",IF(AND(P16="NA",P17="NA"),"NA",SUM(P16,P17)/((P16<>"NA")*$H$16+(P17<>"NA")*$H$17)*$H15))) -> ? | ... AK15: =IF(OR(AK16="ER",AK17="ER"),"ER",IF(OR(AK16="?",AK17="?"),"?",IF(AND(AK16="NA",AK17="NA"),"NA",SUM(AK16,AK17)/((AK16<>"NA")*$H$16+(AK17<>"NA")*$H$17)*$H15))) -> ?
A16: UPD7a | B16: =IF(ISBLANK($A16),"NO_CODE",VLOOKUP($A16,'UPD Questions_290926 '!$E$1:$N$300,MATCH(B$1,'UPD Questions_290926 '!$E$1:$N$1,0),0)&"") -> Planning | C16: =IF(ISBLANK($A16),"NO_CODE",VLOOKUP($A16,'UPD Questions_290926 '!$E$1:$N$300,MATCH(C$1,'UPD Questions_290926 '!$E$1:$N$1,0),0)&"") -> Legal and institutional planning architecture | D16: =IF(ISBLANK($A16),"NO_CODE",VLOOKUP($A16,'UPD Questions_290926 '!$E$1:$N$300,MATCH(D$1,'UPD Questions_290926 '!$E$1:$N$1,0),0)&"") -> Metropolitan and district planning institutions | E16: =IF(ISBLANK($A16),"NO_CODE",VLOOKUP($A16,'UPD Questions_290926 '!$E$1:$N$300,MATCH(E$1,'UPD Questions_290926 '!$E$1:$N$1,0),0)&"") -> SQ | F16: =IF(ISBLANK($A16),"NO_CODE",VLOOKUP($A16,'UPD Questions_290926 '!$E$1:$N$300,MATCH(F$1,'UPD Questions_290926 '!$E$1:$N$1,0),0)&"") -> Does the law provide for the constitution of an MPC/DPC? | G16: =IF(ISBLANK($A16),"NO_CODE",VLOOKUP($A16,'UPD Questions_290926 '!$E$1:$N$300,MATCH(G$1,'UPD Questions_290926 '!$E$1:$N$1,0),0)&"") -> Law/Policy | H16: =IF(ISBLANK($A16),"NO_CODE",VLOOKUP($A16,'UPD Questions_290926 '!$E$1:$N$300,MATCH(H$1,'UPD Questions_290926 '!$E$1:$N$1,0),0)) -> 5 | I16: =IF($H16=0,"NA",IF($A16=INDIRECT("'"&$A16&"'!$B$1"),IF(VLOOKUP(I$1,INDIRECT("'"&$A16&"'!$A$12:$Z$41"),MATCH("Points (Auto-generate)",INDIRECT("'"&$A16&"'!$A$12:$Z$12"),0),0)="","?",VLOOKUP(I$1,INDIRECT("'"&$A16&"'!$A$12:$Z$41"),MATCH("Points (Auto-generate)",INDIRECT("'"&$A16&"'!$A$12:$Z$12"),0),0)),"ER")) -> ? | J16: =IF($H16=0,"NA",IF($A16=INDIRECT("'"&$A16&"'!$B$1"),IF(VLOOKUP(J$1,INDIRECT("'"&$A16&"'!$A$12:$Z$41"),MATCH("Points (Auto-generate)",INDIRECT("'"&$A16&"'!$A$12:$Z$12"),0),0)="","?",VLOOKUP(J$1,INDIRECT("'"&$A16&"'!$A$12:$Z$41"),MATCH("Points (Auto-generate)",INDIRECT("'"&$A16&"'!$A$12:$Z$12"),0),0)),"ER")) -> ? | K16: =IF($H16=0,"NA",IF($A16=INDIRECT("'"&$A16&"'!$B$1"),IF(VLOOKUP(K$1,INDIRECT("'"&$A16&"'!$A$12:$Z$41"),MATCH("Points (Auto-generate)",INDIRECT("'"&$A16&"'!$A$12:$Z$12"),0),0)="","?",VLOOKUP(K$1,INDIRECT("'"&$A16&"'!$A$12:$Z$41"),MATCH("Points (Auto-generate)",INDIRECT("'"&$A16&"'!$A$12:$Z$12"),0),0)),"ER")) -> ? | L16: =IF($H16=0,"NA",IF($A16=INDIRECT("'"&$A16&"'!$B$1"),IF(VLOOKUP(L$1,INDIRECT("'"&$A16&"'!$A$12:$Z$41"),MATCH("Points (Auto-generate)",INDIRECT("'"&$A16&"'!$A$12:$Z$12"),0),0)="","?",VLOOKUP(L$1,INDIRECT("'"&$A16&"'!$A$12:$Z$41"),MATCH("Points (Auto-generate)",INDIRECT("'"&$A16&"'!$A$12:$Z$12"),0),0)),"ER")) -> ? | M16: =IF($H16=0,"NA",IF($A16=INDIRECT("'"&$A16&"'!$B$1"),IF(VLOOKUP(M$1,INDIRECT("'"&$A16&"'!$A$12:$Z$41"),MATCH("Points (Auto-generate)",INDIRECT("'"&$A16&"'!$A$12:$Z$12"),0),0)="","?",VLOOKUP(M$1,INDIRECT("'"&$A16&"'!$A$12:$Z$41"),MATCH("Points (Auto-generate)",INDIRECT("'"&$A16&"'!$A$12:$Z$12"),0),0)),"ER")) -> ? | N16: =IF($H16=0,"NA",IF($A16=INDIRECT("'"&$A16&"'!$B$1"),IF(VLOOKUP(N$1,INDIRECT("'"&$A16&"'!$A$12:$Z$41"),MATCH("Points (Auto-generate)",INDIRECT("'"&$A16&"'!$A$12:$Z$12"),0),0)="","?",VLOOKUP(N$1,INDIRECT("'"&$A16&"'!$A$12:$Z$41"),MATCH("Points (Auto-generate)",INDIRECT("'"&$A16&"'!$A$12:$Z$12"),0),0)),"ER")) -> ? | O16: =IF($H16=0,"NA",IF($A16=INDIRECT("'"&$A16&"'!$B$1"),IF(VLOOKUP(O$1,INDIRECT("'"&$A16&"'!$A$12:$Z$41"),MATCH("Points (Auto-generate)",INDIRECT("'"&$A16&"'!$A$12:$Z$12"),0),0)="","?",VLOOKUP(O$1,INDIRECT("'"&$A16&"'!$A$12:$Z$41"),MATCH("Points (Auto-generate)",INDIRECT("'"&$A16&"'!$A$12:$Z$12"),0),0)),"ER")) -> ? | P16: =IF($H16=0,"NA",IF($A16=INDIRECT("'"&$A16&"'!$B$1"),IF(VLOOKUP(P$1,INDIRECT("'"&$A16&"'!$A$12:$Z$41"),MATCH("Points (Auto-generate)",INDIRECT("'"&$A16&"'!$A$12:$Z$12"),0),0)="","?",VLOOKUP(P$1,INDIRECT("'"&$A16&"'!$A$12:$Z$41"),MATCH("Points (Auto-generate)",INDIRECT("'"&$A16&"'!$A$12:$Z$12"),0),0)),"ER")) -> ? | ... AK16: =IF($H16=0,"NA",IF($A16=INDIRECT("'"&$A16&"'!$B$1"),IF(VLOOKUP(AK$1,INDIRECT("'"&$A16&"'!$A$12:$Z$41"),MATCH("Points (Auto-generate)",INDIRECT("'"&$A16&"'!$A$12:$Z$12"),0),0)="","?",VLOOKUP(AK$1,INDIRECT("'"&$A16&"'!$A$12:$Z$41"),MATCH("Points (Auto-generate)",INDIRECT("'"&$A16&"'!$A$12:$Z$12"),0),0)),"ER")) -> ?
A17: UPD7b | B17: =IF(ISBLANK($A17),"NO_CODE",VLOOKUP($A17,'UPD Questions_290926 '!$E$1:$N$300,MATCH(B$1,'UPD Questions_290926 '!$E$1:$N$1,0),0)&"") -> Planning | C17: =IF(ISBLANK($A17),"NO_CODE",VLOOKUP($A17,'UPD Questions_290926 '!$E$1:$N$300,MATCH(C$1,'UPD Questions_290926 '!$E$1:$N$1,0),0)&"") -> Legal and institutional planning architecture | D17: =IF(ISBLANK($A17),"NO_CODE",VLOOKUP($A17,'UPD Questions_290926 '!$E$1:$N$300,MATCH(D$1,'UPD Questions_290926 '!$E$1:$N$1,0),0)&"") -> Metropolitan and district planning institutions | E17: =IF(ISBLANK($A17),"NO_CODE",VLOOKUP($A17,'UPD Questions_290926 '!$E$1:$N$300,MATCH(E$1,'UPD Questions_290926 '!$E$1:$N$1,0),0)&"") -> SQ | F17: =IF(ISBLANK($A17),"NO_CODE",VLOOKUP($A17,'UPD Questions_290926 '!$E$1:$N$300,MATCH(F$1,'UPD Questions_290926 '!$E$1:$N$1,0),0)&"") -> Have they met at least once in the past two years? | G17: =IF(ISBLANK($A17),"NO_CODE",VLOOKUP($A17,'UPD Questions_290926 '!$E$1:$N$300,MATCH(G$1,'UPD Questions_290926 '!$E$1:$N$1,0),0)&"") -> Implementation | H17: =IF(ISBLANK($A17),"NO_CODE",VLOOKUP($A17,'UPD Questions_290926 '!$E$1:$N$300,MATCH(H$1,'UPD Questions_290926 '!$E$1:$N$1,0),0)) -> 5 | I17: =IF($H17=0,"NA",IF($A17=INDIRECT("'"&$A17&"'!$B$1"),IF(VLOOKUP(I$1,INDIRECT("'"&$A17&"'!$A$12:$Z$41"),MATCH("Points (Auto-generate)",INDIRECT("'"&$A17&"'!$A$12:$Z$12"),0),0)="","?",VLOOKUP(I$1,INDIRECT("'"&$A17&"'!$A$12:$Z$41"),MATCH("Points (Auto-generate)",INDIRECT("'"&$A17&"'!$A$12:$Z$12"),0),0)),"ER")) -> ? | J17: =IF($H17=0,"NA",IF($A17=INDIRECT("'"&$A17&"'!$B$1"),IF(VLOOKUP(J$1,INDIRECT("'"&$A17&"'!$A$12:$Z$41"),MATCH("Points (Auto-generate)",INDIRECT("'"&$A17&"'!$A$12:$Z$12"),0),0)="","?",VLOOKUP(J$1,INDIRECT("'"&$A17&"'!$A$12:$Z$41"),MATCH("Points (Auto-generate)",INDIRECT("'"&$A17&"'!$A$12:$Z$12"),0),0)),"ER")) -> ? | K17: =IF($H17=0,"NA",IF($A17=INDIRECT("'"&$A17&"'!$B$1"),IF(VLOOKUP(K$1,INDIRECT("'"&$A17&"'!$A$12:$Z$41"),MATCH("Points (Auto-generate)",INDIRECT("'"&$A17&"'!$A$12:$Z$12"),0),0)="","?",VLOOKUP(K$1,INDIRECT("'"&$A17&"'!$A$12:$Z$41"),MATCH("Points (Auto-generate)",INDIRECT("'"&$A17&"'!$A$12:$Z$12"),0),0)),"ER")) -> ? | L17: =IF($H17=0,"NA",IF($A17=INDIRECT("'"&$A17&"'!$B$1"),IF(VLOOKUP(L$1,INDIRECT("'"&$A17&"'!$A$12:$Z$41"),MATCH("Points (Auto-generate)",INDIRECT("'"&$A17&"'!$A$12:$Z$12"),0),0)="","?",VLOOKUP(L$1,INDIRECT("'"&$A17&"'!$A$12:$Z$41"),MATCH("Points (Auto-generate)",INDIRECT("'"&$A17&"'!$A$12:$Z$12"),0),0)),"ER")) -> ? | M17: =IF($H17=0,"NA",IF($A17=INDIRECT("'"&$A17&"'!$B$1"),IF(VLOOKUP(M$1,INDIRECT("'"&$A17&"'!$A$12:$Z$41"),MATCH("Points (Auto-generate)",INDIRECT("'"&$A17&"'!$A$12:$Z$12"),0),0)="","?",VLOOKUP(M$1,INDIRECT("'"&$A17&"'!$A$12:$Z$41"),MATCH("Points (Auto-generate)",INDIRECT("'"&$A17&"'!$A$12:$Z$12"),0),0)),"ER")) -> ? | N17: =IF($H17=0,"NA",IF($A17=INDIRECT("'"&$A17&"'!$B$1"),IF(VLOOKUP(N$1,INDIRECT("'"&$A17&"'!$A$12:$Z$41"),MATCH("Points (Auto-generate)",INDIRECT("'"&$A17&"'!$A$12:$Z$12"),0),0)="","?",VLOOKUP(N$1,INDIRECT("'"&$A17&"'!$A$12:$Z$41"),MATCH("Points (Auto-generate)",INDIRECT("'"&$A17&"'!$A$12:$Z$12"),0),0)),"ER")) -> ? | O17: =IF($H17=0,"NA",IF($A17=INDIRECT("'"&$A17&"'!$B$1"),IF(VLOOKUP(O$1,INDIRECT("'"&$A17&"'!$A$12:$Z$41"),MATCH("Points (Auto-generate)",INDIRECT("'"&$A17&"'!$A$12:$Z$12"),0),0)="","?",VLOOKUP(O$1,INDIRECT("'"&$A17&"'!$A$12:$Z$41"),MATCH("Points (Auto-generate)",INDIRECT("'"&$A17&"'!$A$12:$Z$12"),0),0)),"ER")) -> ? | P17: =IF($H17=0,"NA",IF($A17=INDIRECT("'"&$A17&"'!$B$1"),IF(VLOOKUP(P$1,INDIRECT("'"&$A17&"'!$A$12:$Z$41"),MATCH("Points (Auto-generate)",INDIRECT("'"&$A17&"'!$A$12:$Z$12"),0),0)="","?",VLOOKUP(P$1,INDIRECT("'"&$A17&"'!$A$12:$Z$41"),MATCH("Points (Auto-generate)",INDIRECT("'"&$A17&"'!$A$12:$Z$12"),0),0)),"ER")) -> ? | ... AK17: =IF($H17=0,"NA",IF($A17=INDIRECT("'"&$A17&"'!$B$1"),IF(VLOOKUP(AK$1,INDIRECT("'"&$A17&"'!$A$12:$Z$41"),MATCH("Points (Auto-generate)",INDIRECT("'"&$A17&"'!$A$12:$Z$12"),0),0)="","?",VLOOKUP(AK$1,INDIRECT("'"&$A17&"'!$A$12:$Z$41"),MATCH("Points (Auto-generate)",INDIRECT("'"&$A17&"'!$A$12:$Z$12"),0),0)),"ER")) -> ?
A18: UPD8 | B18: =IF(ISBLANK($A18),"NO_CODE",VLOOKUP($A18,'UPD Questions_290926 '!$E$1:$N$300,MATCH(B$1,'UPD Questions_290926 '!$E$1:$N$1,0),0)&"") -> Planning | C18: =IF(ISBLANK($A18),"NO_CODE",VLOOKUP($A18,'UPD Questions_290926 '!$E$1:$N$300,MATCH(C$1,'UPD Questions_290926 '!$E$1:$N$1,0),0)&"") -> Legal and institutional planning architecture | D18: =IF(ISBLANK($A18),"NO_CODE",VLOOKUP($A18,'UPD Questions_290926 '!$E$1:$N$300,MATCH(D$1,'UPD Questions_290926 '!$E$1:$N$1,0),0)&"") -> Metropolitan and district planning institutions | E18: =IF(ISBLANK($A18),"NO_CODE",VLOOKUP($A18,'UPD Questions_290926 '!$E$1:$N$300,MATCH(E$1,'UPD Questions_290926 '!$E$1:$N$1,0),0)&"") -> MQ | F18: =IF(ISBLANK($A18),"NO_CODE",VLOOKUP($A18,'UPD Questions_290926 '!$E$1:$N$300,MATCH(F$1,'UPD Questions_290926 '!$E$1:$N$1,0),0)&"") -> Does the city (million-plus) have a Metropolitan Authority? | G18: =IF(ISBLANK($A18),"NO_CODE",VLOOKUP($A18,'UPD Questions_290926 '!$E$1:$N$300,MATCH(G$1,'UPD Questions_290926 '!$E$1:$N$1,0),0)&"") -> Law or Policy | H18: =IF(ISBLANK($A18),"NO_CODE",VLOOKUP($A18,'UPD Questions_290926 '!$E$1:$N$300,MATCH(H$1,'UPD Questions_290926 '!$E$1:$N$1,0),0)) -> 10 | I18: =IF($H18=0,"NA",IF($A18=INDIRECT("'"&$A18&"'!$B$1"),IF(VLOOKUP(I$1,INDIRECT("'"&$A18&"'!$A$12:$Z$41"),MATCH("Points (Auto-generate)",INDIRECT("'"&$A18&"'!$A$12:$Z$12"),0),0)="","?",VLOOKUP(I$1,INDIRECT("'"&$A18&"'!$A$12:$Z$41"),MATCH("Points (Auto-generate)",INDIRECT("'"&$A18&"'!$A$12:$Z$12"),0),0)),"ER")) -> ? | J18: =IF($H18=0,"NA",IF($A18=INDIRECT("'"&$A18&"'!$B$1"),IF(VLOOKUP(J$1,INDIRECT("'"&$A18&"'!$A$12:$Z$41"),MATCH("Points (Auto-generate)",INDIRECT("'"&$A18&"'!$A$12:$Z$12"),0),0)="","?",VLOOKUP(J$1,INDIRECT("'"&$A18&"'!$A$12:$Z$41"),MATCH("Points (Auto-generate)",INDIRECT("'"&$A18&"'!$A$12:$Z$12"),0),0)),"ER")) -> ? | K18: =IF($H18=0,"NA",IF($A18=INDIRECT("'"&$A18&"'!$B$1"),IF(VLOOKUP(K$1,INDIRECT("'"&$A18&"'!$A$12:$Z$41"),MATCH("Points (Auto-generate)",INDIRECT("'"&$A18&"'!$A$12:$Z$12"),0),0)="","?",VLOOKUP(K$1,INDIRECT("'"&$A18&"'!$A$12:$Z$41"),MATCH("Points (Auto-generate)",INDIRECT("'"&$A18&"'!$A$12:$Z$12"),0),0)),"ER")) -> ? | L18: =IF($H18=0,"NA",IF($A18=INDIRECT("'"&$A18&"'!$B$1"),IF(VLOOKUP(L$1,INDIRECT("'"&$A18&"'!$A$12:$Z$41"),MATCH("Points (Auto-generate)",INDIRECT("'"&$A18&"'!$A$12:$Z$12"),0),0)="","?",VLOOKUP(L$1,INDIRECT("'"&$A18&"'!$A$12:$Z$41"),MATCH("Points (Auto-generate)",INDIRECT("'"&$A18&"'!$A$12:$Z$12"),0),0)),"ER")) -> ? | M18: =IF($H18=0,"NA",IF($A18=INDIRECT("'"&$A18&"'!$B$1"),IF(VLOOKUP(M$1,INDIRECT("'"&$A18&"'!$A$12:$Z$41"),MATCH("Points (Auto-generate)",INDIRECT("'"&$A18&"'!$A$12:$Z$12"),0),0)="","?",VLOOKUP(M$1,INDIRECT("'"&$A18&"'!$A$12:$Z$41"),MATCH("Points (Auto-generate)",INDIRECT("'"&$A18&"'!$A$12:$Z$12"),0),0)),"ER")) -> ? | N18: =IF($H18=0,"NA",IF($A18=INDIRECT("'"&$A18&"'!$B$1"),IF(VLOOKUP(N$1,INDIRECT("'"&$A18&"'!$A$12:$Z$41"),MATCH("Points (Auto-generate)",INDIRECT("'"&$A18&"'!$A$12:$Z$12"),0),0)="","?",VLOOKUP(N$1,INDIRECT("'"&$A18&"'!$A$12:$Z$41"),MATCH("Points (Auto-generate)",INDIRECT("'"&$A18&"'!$A$12:$Z$12"),0),0)),"ER")) -> ? | O18: =IF($H18=0,"NA",IF($A18=INDIRECT("'"&$A18&"'!$B$1"),IF(VLOOKUP(O$1,INDIRECT("'"&$A18&"'!$A$12:$Z$41"),MATCH("Points (Auto-generate)",INDIRECT("'"&$A18&"'!$A$12:$Z$12"),0),0)="","?",VLOOKUP(O$1,INDIRECT("'"&$A18&"'!$A$12:$Z$41"),MATCH("Points (Auto-generate)",INDIRECT("'"&$A18&"'!$A$12:$Z$12"),0),0)),"ER")) -> ? | P18: =IF($H18=0,"NA",IF($A18=INDIRECT("'"&$A18&"'!$B$1"),IF(VLOOKUP(P$1,INDIRECT("'"&$A18&"'!$A$12:$Z$41"),MATCH("Points (Auto-generate)",INDIRECT("'"&$A18&"'!$A$12:$Z$12"),0),0)="","?",VLOOKUP(P$1,INDIRECT("'"&$A18&"'!$A$12:$Z$41"),MATCH("Points (Auto-generate)",INDIRECT("'"&$A18&"'!$A$12:$Z$12"),0),0)),"ER")) -> ? | ... AK18: =IF($H18=0,"NA",IF($A18=INDIRECT("'"&$A18&"'!$B$1"),IF(VLOOKUP(AK$1,INDIRECT("'"&$A18&"'!$A$12:$Z$41"),MATCH("Points (Auto-generate)",INDIRECT("'"&$A18&"'!$A$12:$Z$12"),0),0)="","?",VLOOKUP(AK$1,INDIRECT("'"&$A18&"'!$A$12:$Z$41"),MATCH("Points (Auto-generate)",INDIRECT("'"&$A18&"'!$A$12:$Z$12"),0),0)),"ER")) -> ?
A19: UPD9 | B19: =IF(ISBLANK($A19),"NO_CODE",VLOOKUP($A19,'UPD Questions_290926 '!$E$1:$N$300,MATCH(B$1,'UPD Questions_290926 '!$E$1:$N$1,0),0)&"") -> Planning | C19: =IF(ISBLANK($A19),"NO_CODE",VLOOKUP($A19,'UPD Questions_290926 '!$E$1:$N$300,MATCH(C$1,'UPD Questions_290926 '!$E$1:$N$1,0),0)&"") -> Municipal/City Plan preparation, participation and review | D19: =IF(ISBLANK($A19),"NO_CODE",VLOOKUP($A19,'UPD Questions_290926 '!$E$1:$N$300,MATCH(D$1,'UPD Questions_290926 '!$E$1:$N$1,0),0)&"") -> Inter-agency participation | E19: =IF(ISBLANK($A19),"NO_CODE",VLOOKUP($A19,'UPD Questions_290926 '!$E$1:$N$300,MATCH(E$1,'UPD Questions_290926 '!$E$1:$N$1,0),0)&"") -> MQ | F19: =IF(ISBLANK($A19),"NO_CODE",VLOOKUP($A19,'UPD Questions_290926 '!$E$1:$N$300,MATCH(F$1,'UPD Questions_290926 '!$E$1:$N$1,0),0)&"") -> Does the law mandate participation of all parastatals/ agencies /ULGs in creation of Spatial plans (metro/municipal/ward)? | G19: =IF(ISBLANK($A19),"NO_CODE",VLOOKUP($A19,'UPD Questions_290926 '!$E$1:$N$300,MATCH(G$1,'UPD Questions_290926 '!$E$1:$N$1,0),0)&"") -> Law or Policy | H19: =IF(ISBLANK($A19),"NO_CODE",VLOOKUP($A19,'UPD Questions_290926 '!$E$1:$N$300,MATCH(H$1,'UPD Questions_290926 '!$E$1:$N$1,0),0)) -> 10 | I19: =IF($H19=0,"NA",IF($A19=INDIRECT("'"&$A19&"'!$B$1"),IF(VLOOKUP(I$1,INDIRECT("'"&$A19&"'!$A$12:$Z$41"),MATCH("Points (Auto-generate)",INDIRECT("'"&$A19&"'!$A$12:$Z$12"),0),0)="","?",VLOOKUP(I$1,INDIRECT("'"&$A19&"'!$A$12:$Z$41"),MATCH("Points (Auto-generate)",INDIRECT("'"&$A19&"'!$A$12:$Z$12"),0),0)),"ER")) -> ? | J19: =IF($H19=0,"NA",IF($A19=INDIRECT("'"&$A19&"'!$B$1"),IF(VLOOKUP(J$1,INDIRECT("'"&$A19&"'!$A$12:$Z$41"),MATCH("Points (Auto-generate)",INDIRECT("'"&$A19&"'!$A$12:$Z$12"),0),0)="","?",VLOOKUP(J$1,INDIRECT("'"&$A19&"'!$A$12:$Z$41"),MATCH("Points (Auto-generate)",INDIRECT("'"&$A19&"'!$A$12:$Z$12"),0),0)),"ER")) -> ? | K19: =IF($H19=0,"NA",IF($A19=INDIRECT("'"&$A19&"'!$B$1"),IF(VLOOKUP(K$1,INDIRECT("'"&$A19&"'!$A$12:$Z$41"),MATCH("Points (Auto-generate)",INDIRECT("'"&$A19&"'!$A$12:$Z$12"),0),0)="","?",VLOOKUP(K$1,INDIRECT("'"&$A19&"'!$A$12:$Z$41"),MATCH("Points (Auto-generate)",INDIRECT("'"&$A19&"'!$A$12:$Z$12"),0),0)),"ER")) -> ? | L19: =IF($H19=0,"NA",IF($A19=INDIRECT("'"&$A19&"'!$B$1"),IF(VLOOKUP(L$1,INDIRECT("'"&$A19&"'!$A$12:$Z$41"),MATCH("Points (Auto-generate)",INDIRECT("'"&$A19&"'!$A$12:$Z$12"),0),0)="","?",VLOOKUP(L$1,INDIRECT("'"&$A19&"'!$A$12:$Z$41"),MATCH("Points (Auto-generate)",INDIRECT("'"&$A19&"'!$A$12:$Z$12"),0),0)),"ER")) -> ? | M19: =IF($H19=0,"NA",IF($A19=INDIRECT("'"&$A19&"'!$B$1"),IF(VLOOKUP(M$1,INDIRECT("'"&$A19&"'!$A$12:$Z$41"),MATCH("Points (Auto-generate)",INDIRECT("'"&$A19&"'!$A$12:$Z$12"),0),0)="","?",VLOOKUP(M$1,INDIRECT("'"&$A19&"'!$A$12:$Z$41"),MATCH("Points (Auto-generate)",INDIRECT("'"&$A19&"'!$A$12:$Z$12"),0),0)),"ER")) -> ? | N19: =IF($H19=0,"NA",IF($A19=INDIRECT("'"&$A19&"'!$B$1"),IF(VLOOKUP(N$1,INDIRECT("'"&$A19&"'!$A$12:$Z$41"),MATCH("Points (Auto-generate)",INDIRECT("'"&$A19&"'!$A$12:$Z$12"),0),0)="","?",VLOOKUP(N$1,INDIRECT("'"&$A19&"'!$A$12:$Z$41"),MATCH("Points (Auto-generate)",INDIRECT("'"&$A19&"'!$A$12:$Z$12"),0),0)),"ER")) -> ? | O19: =IF($H19=0,"NA",IF($A19=INDIRECT("'"&$A19&"'!$B$1"),IF(VLOOKUP(O$1,INDIRECT("'"&$A19&"'!$A$12:$Z$41"),MATCH("Points (Auto-generate)",INDIRECT("'"&$A19&"'!$A$12:$Z$12"),0),0)="","?",VLOOKUP(O$1,INDIRECT("'"&$A19&"'!$A$12:$Z$41"),MATCH("Points (Auto-generate)",INDIRECT("'"&$A19&"'!$A$12:$Z$12"),0),0)),"ER")) -> ? | P19: =IF($H19=0,"NA",IF($A19=INDIRECT("'"&$A19&"'!$B$1"),IF(VLOOKUP(P$1,INDIRECT("'"&$A19&"'!$A$12:$Z$41"),MATCH("Points (Auto-generate)",INDIRECT("'"&$A19&"'!$A$12:$Z$12"),0),0)="","?",VLOOKUP(P$1,INDIRECT("'"&$A19&"'!$A$12:$Z$41"),MATCH("Points (Auto-generate)",INDIRECT("'"&$A19&"'!$A$12:$Z$12"),0),0)),"ER")) -> ? | ... AK19: =IF($H19=0,"NA",IF($A19=INDIRECT("'"&$A19&"'!$B$1"),IF(VLOOKUP(AK$1,INDIRECT("'"&$A19&"'!$A$12:$Z$41"),MATCH("Points (Auto-generate)",INDIRECT("'"&$A19&"'!$A$12:$Z$12"),0),0)="","?",VLOOKUP(AK$1,INDIRECT("'"&$A19&"'!$A$12:$Z$41"),MATCH("Points (Auto-generate)",INDIRECT("'"&$A19&"'!$A$12:$Z$12"),0),0)),"ER")) -> ?
A20: UPD10 | B20: =IF(ISBLANK($A20),"NO_CODE",VLOOKUP($A20,'UPD Questions_290926 '!$E$1:$N$300,MATCH(B$1,'UPD Questions_290926 '!$E$1:$N$1,0),0)&"") -> Planning | C20: =IF(ISBLANK($A20),"NO_CODE",VLOOKUP($A20,'UPD Questions_290926 '!$E$1:$N$300,MATCH(C$1,'UPD Questions_290926 '!$E$1:$N$1,0),0)&"") -> Municipal/City Plan preparation, participation and review | D20: =IF(ISBLANK($A20),"NO_CODE",VLOOKUP($A20,'UPD Questions_290926 '!$E$1:$N$300,MATCH(D$1,'UPD Questions_290926 '!$E$1:$N$1,0),0)&"") -> Public participation and scrutiny | E20: =IF(ISBLANK($A20),"NO_CODE",VLOOKUP($A20,'UPD Questions_290926 '!$E$1:$N$300,MATCH(E$1,'UPD Questions_290926 '!$E$1:$N$1,0),0)&"") -> MQ | F20: =IF(ISBLANK($A20),"NO_CODE",VLOOKUP($A20,'UPD Questions_290926 '!$E$1:$N$300,MATCH(F$1,'UPD Questions_290926 '!$E$1:$N$1,0),0)&"") -> Does the law mandate public participation in preparation of the municipal plan through Area Sabhas / Ward Sabhas and other means? | G20: =IF(ISBLANK($A20),"NO_CODE",VLOOKUP($A20,'UPD Questions_290926 '!$E$1:$N$300,MATCH(G$1,'UPD Questions_290926 '!$E$1:$N$1,0),0)&"") -> Law or Policy | H20: =IF(ISBLANK($A20),"NO_CODE",VLOOKUP($A20,'UPD Questions_290926 '!$E$1:$N$300,MATCH(H$1,'UPD Questions_290926 '!$E$1:$N$1,0),0)) -> 10 | I20: =IF($H20=0,"NA",IF($A20=INDIRECT("'"&$A20&"'!$B$1"),IF(VLOOKUP(I$1,INDIRECT("'"&$A20&"'!$A$12:$Z$41"),MATCH("Points (Auto-generate)",INDIRECT("'"&$A20&"'!$A$12:$Z$12"),0),0)="","?",VLOOKUP(I$1,INDIRECT("'"&$A20&"'!$A$12:$Z$41"),MATCH("Points (Auto-generate)",INDIRECT("'"&$A20&"'!$A$12:$Z$12"),0),0)),"ER")) -> ? | J20: =IF($H20=0,"NA",IF($A20=INDIRECT("'"&$A20&"'!$B$1"),IF(VLOOKUP(J$1,INDIRECT("'"&$A20&"'!$A$12:$Z$41"),MATCH("Points (Auto-generate)",INDIRECT("'"&$A20&"'!$A$12:$Z$12"),0),0)="","?",VLOOKUP(J$1,INDIRECT("'"&$A20&"'!$A$12:$Z$41"),MATCH("Points (Auto-generate)",INDIRECT("'"&$A20&"'!$A$12:$Z$12"),0),0)),"ER")) -> ? | K20: =IF($H20=0,"NA",IF($A20=INDIRECT("'"&$A20&"'!$B$1"),IF(VLOOKUP(K$1,INDIRECT("'"&$A20&"'!$A$12:$Z$41"),MATCH("Points (Auto-generate)",INDIRECT("'"&$A20&"'!$A$12:$Z$12"),0),0)="","?",VLOOKUP(K$1,INDIRECT("'"&$A20&"'!$A$12:$Z$41"),MATCH("Points (Auto-generate)",INDIRECT("'"&$A20&"'!$A$12:$Z$12"),0),0)),"ER")) -> ? | L20: =IF($H20=0,"NA",IF($A20=INDIRECT("'"&$A20&"'!$B$1"),IF(VLOOKUP(L$1,INDIRECT("'"&$A20&"'!$A$12:$Z$41"),MATCH("Points (Auto-generate)",INDIRECT("'"&$A20&"'!$A$12:$Z$12"),0),0)="","?",VLOOKUP(L$1,INDIRECT("'"&$A20&"'!$A$12:$Z$41"),MATCH("Points (Auto-generate)",INDIRECT("'"&$A20&"'!$A$12:$Z$12"),0),0)),"ER")) -> ? | M20: =IF($H20=0,"NA",IF($A20=INDIRECT("'"&$A20&"'!$B$1"),IF(VLOOKUP(M$1,INDIRECT("'"&$A20&"'!$A$12:$Z$41"),MATCH("Points (Auto-generate)",INDIRECT("'"&$A20&"'!$A$12:$Z$12"),0),0)="","?",VLOOKUP(M$1,INDIRECT("'"&$A20&"'!$A$12:$Z$41"),MATCH("Points (Auto-generate)",INDIRECT("'"&$A20&"'!$A$12:$Z$12"),0),0)),"ER")) -> ? | N20: =IF($H20=0,"NA",IF($A20=INDIRECT("'"&$A20&"'!$B$1"),IF(VLOOKUP(N$1,INDIRECT("'"&$A20&"'!$A$12:$Z$41"),MATCH("Points (Auto-generate)",INDIRECT("'"&$A20&"'!$A$12:$Z$12"),0),0)="","?",VLOOKUP(N$1,INDIRECT("'"&$A20&"'!$A$12:$Z$41"),MATCH("Points (Auto-generate)",INDIRECT("'"&$A20&"'!$A$12:$Z$12"),0),0)),"ER")) -> ? | O20: =IF($H20=0,"NA",IF($A20=INDIRECT("'"&$A20&"'!$B$1"),IF(VLOOKUP(O$1,INDIRECT("'"&$A20&"'!$A$12:$Z$41"),MATCH("Points (Auto-generate)",INDIRECT("'"&$A20&"'!$A$12:$Z$12"),0),0)="","?",VLOOKUP(O$1,INDIRECT("'"&$A20&"'!$A$12:$Z$41"),MATCH("Points (Auto-generate)",INDIRECT("'"&$A20&"'!$A$12:$Z$12"),0),0)),"ER")) -> ? | P20: =IF($H20=0,"NA",IF($A20=INDIRECT("'"&$A20&"'!$B$1"),IF(VLOOKUP(P$1,INDIRECT("'"&$A20&"'!$A$12:$Z$41"),MATCH("Points (Auto-generate)",INDIRECT("'"&$A20&"'!$A$12:$Z$12"),0),0)="","?",VLOOKUP(P$1,INDIRECT("'"&$A20&"'!$A$12:$Z$41"),MATCH("Points (Auto-generate)",INDIRECT("'"&$A20&"'!$A$12:$Z$12"),0),0)),"ER")) -> ? | ... AK20: =IF($H20=0,"NA",IF($A20=INDIRECT("'"&$A20&"'!$B$1"),IF(VLOOKUP(AK$1,INDIRECT("'"&$A20&"'!$A$12:$Z$41"),MATCH("Points (Auto-generate)",INDIRECT("'"&$A20&"'!$A$12:$Z$12"),0),0)="","?",VLOOKUP(AK$1,INDIRECT("'"&$A20&"'!$A$12:$Z$41"),MATCH("Points (Auto-generate)",INDIRECT("'"&$A20&"'!$A$12:$Z$12"),0),0)),"ER")) -> ?
A21: UPD11 | B21: =IF(ISBLANK($A21),"NO_CODE",VLOOKUP($A21,'UPD Questions_290926 '!$E$1:$N$300,MATCH(B$1,'UPD Questions_290926 '!$E$1:$N$1,0),0)&"") -> Planning | C21: =IF(ISBLANK($A21),"NO_CODE",VLOOKUP($A21,'UPD Questions_290926 '!$E$1:$N$300,MATCH(C$1,'UPD Questions_290926 '!$E$1:$N$1,0),0)&"") -> Municipal/City Plan preparation, participation and review | D21: =IF(ISBLANK($A21),"NO_CODE",VLOOKUP($A21,'UPD Questions_290926 '!$E$1:$N$300,MATCH(D$1,'UPD Questions_290926 '!$E$1:$N$1,0),0)&"") -> Public participation and scrutiny | E21: =IF(ISBLANK($A21),"NO_CODE",VLOOKUP($A21,'UPD Questions_290926 '!$E$1:$N$300,MATCH(E$1,'UPD Questions_290926 '!$E$1:$N$1,0),0)&"") -> MQ | F21: =IF(ISBLANK($A21),"NO_CODE",VLOOKUP($A21,'UPD Questions_290926 '!$E$1:$N$300,MATCH(F$1,'UPD Questions_290926 '!$E$1:$N$1,0),0)&"") -> Is there public scrutiny for (including objections and responses) municipal/city plan? | G21: =IF(ISBLANK($A21),"NO_CODE",VLOOKUP($A21,'UPD Questions_290926 '!$E$1:$N$300,MATCH(G$1,'UPD Questions_290926 '!$E$1:$N$1,0),0)&"") -> Law/Policy & Implementation | H21: =IF(ISBLANK($A21),"NO_CODE",VLOOKUP($A21,'UPD Questions_290926 '!$E$1:$N$300,MATCH(H$1,'UPD Questions_290926 '!$E$1:$N$1,0),0)) -> 10 | I21: =IF(OR(I22="ER",I23="ER"),"ER",IF(OR(I22="?",I23="?"),"?",IF(AND(I22="NA",I23="NA"),"NA",SUM(I22,I23)/((I22<>"NA")*$H$22+(I23<>"NA")*$H$23)*$H21))) -> ? | J21: =IF(OR(J22="ER",J23="ER"),"ER",IF(OR(J22="?",J23="?"),"?",IF(AND(J22="NA",J23="NA"),"NA",SUM(J22,J23)/((J22<>"NA")*$H$22+(J23<>"NA")*$H$23)*$H21))) -> ? | K21: =IF(OR(K22="ER",K23="ER"),"ER",IF(OR(K22="?",K23="?"),"?",IF(AND(K22="NA",K23="NA"),"NA",SUM(K22,K23)/((K22<>"NA")*$H$22+(K23<>"NA")*$H$23)*$H21))) -> ? | L21: =IF(OR(L22="ER",L23="ER"),"ER",IF(OR(L22="?",L23="?"),"?",IF(AND(L22="NA",L23="NA"),"NA",SUM(L22,L23)/((L22<>"NA")*$H$22+(L23<>"NA")*$H$23)*$H21))) -> ? | M21: =IF(OR(M22="ER",M23="ER"),"ER",IF(OR(M22="?",M23="?"),"?",IF(AND(M22="NA",M23="NA"),"NA",SUM(M22,M23)/((M22<>"NA")*$H$22+(M23<>"NA")*$H$23)*$H21))) -> ? | N21: =IF(OR(N22="ER",N23="ER"),"ER",IF(OR(N22="?",N23="?"),"?",IF(AND(N22="NA",N23="NA"),"NA",SUM(N22,N23)/((N22<>"NA")*$H$22+(N23<>"NA")*$H$23)*$H21))) -> ? | O21: =IF(OR(O22="ER",O23="ER"),"ER",IF(OR(O22="?",O23="?"),"?",IF(AND(O22="NA",O23="NA"),"NA",SUM(O22,O23)/((O22<>"NA")*$H$22+(O23<>"NA")*$H$23)*$H21))) -> ? | P21: =IF(OR(P22="ER",P23="ER"),"ER",IF(OR(P22="?",P23="?"),"?",IF(AND(P22="NA",P23="NA"),"NA",SUM(P22,P23)/((P22<>"NA")*$H$22+(P23<>"NA")*$H$23)*$H21))) -> ? | ... AK21: =IF(OR(AK22="ER",AK23="ER"),"ER",IF(OR(AK22="?",AK23="?"),"?",IF(AND(AK22="NA",AK23="NA"),"NA",SUM(AK22,AK23)/((AK22<>"NA")*$H$22+(AK23<>"NA")*$H$23)*$H21))) -> ?
A22: UPD11a | B22: =IF(ISBLANK($A22),"NO_CODE",VLOOKUP($A22,'UPD Questions_290926 '!$E$1:$N$300,MATCH(B$1,'UPD Questions_290926 '!$E$1:$N$1,0),0)&"") -> Planning | C22: =IF(ISBLANK($A22),"NO_CODE",VLOOKUP($A22,'UPD Questions_290926 '!$E$1:$N$300,MATCH(C$1,'UPD Questions_290926 '!$E$1:$N$1,0),0)&"") -> Municipal/City Plan preparation, participation and review | D22: =IF(ISBLANK($A22),"NO_CODE",VLOOKUP($A22,'UPD Questions_290926 '!$E$1:$N$300,MATCH(D$1,'UPD Questions_290926 '!$E$1:$N$1,0),0)&"") -> Public participation and scrutiny | E22: =IF(ISBLANK($A22),"NO_CODE",VLOOKUP($A22,'UPD Questions_290926 '!$E$1:$N$300,MATCH(E$1,'UPD Questions_290926 '!$E$1:$N$1,0),0)&"") -> SQ | F22: =IF(ISBLANK($A22),"NO_CODE",VLOOKUP($A22,'UPD Questions_290926 '!$E$1:$N$300,MATCH(F$1,'UPD Questions_290926 '!$E$1:$N$1,0),0)&"") -> Does the law mandate public scrutiny for (including objections and responses) municipal/city plan through Area Sabhas / Ward Sabhas and other means? | G22: =IF(ISBLANK($A22),"NO_CODE",VLOOKUP($A22,'UPD Questions_290926 '!$E$1:$N$300,MATCH(G$1,'UPD Questions_290926 '!$E$1:$N$1,0),0)&"") -> Law/Policy | H22: =IF(ISBLANK($A22),"NO_CODE",VLOOKUP($A22,'UPD Questions_290926 '!$E$1:$N$300,MATCH(H$1,'UPD Questions_290926 '!$E$1:$N$1,0),0)) -> 5 | I22: =IF($H22=0,"NA",IF($A22=INDIRECT("'"&$A22&"'!$B$1"),IF(VLOOKUP(I$1,INDIRECT("'"&$A22&"'!$A$12:$Z$41"),MATCH("Points (Auto-generate)",INDIRECT("'"&$A22&"'!$A$12:$Z$12"),0),0)="","?",VLOOKUP(I$1,INDIRECT("'"&$A22&"'!$A$12:$Z$41"),MATCH("Points (Auto-generate)",INDIRECT("'"&$A22&"'!$A$12:$Z$12"),0),0)),"ER")) -> ? | J22: =IF($H22=0,"NA",IF($A22=INDIRECT("'"&$A22&"'!$B$1"),IF(VLOOKUP(J$1,INDIRECT("'"&$A22&"'!$A$12:$Z$41"),MATCH("Points (Auto-generate)",INDIRECT("'"&$A22&"'!$A$12:$Z$12"),0),0)="","?",VLOOKUP(J$1,INDIRECT("'"&$A22&"'!$A$12:$Z$41"),MATCH("Points (Auto-generate)",INDIRECT("'"&$A22&"'!$A$12:$Z$12"),0),0)),"ER")) -> ? | K22: =IF($H22=0,"NA",IF($A22=INDIRECT("'"&$A22&"'!$B$1"),IF(VLOOKUP(K$1,INDIRECT("'"&$A22&"'!$A$12:$Z$41"),MATCH("Points (Auto-generate)",INDIRECT("'"&$A22&"'!$A$12:$Z$12"),0),0)="","?",VLOOKUP(K$1,INDIRECT("'"&$A22&"'!$A$12:$Z$41"),MATCH("Points (Auto-generate)",INDIRECT("'"&$A22&"'!$A$12:$Z$12"),0),0)),"ER")) -> ? | L22: =IF($H22=0,"NA",IF($A22=INDIRECT("'"&$A22&"'!$B$1"),IF(VLOOKUP(L$1,INDIRECT("'"&$A22&"'!$A$12:$Z$41"),MATCH("Points (Auto-generate)",INDIRECT("'"&$A22&"'!$A$12:$Z$12"),0),0)="","?",VLOOKUP(L$1,INDIRECT("'"&$A22&"'!$A$12:$Z$41"),MATCH("Points (Auto-generate)",INDIRECT("'"&$A22&"'!$A$12:$Z$12"),0),0)),"ER")) -> ? | M22: =IF($H22=0,"NA",IF($A22=INDIRECT("'"&$A22&"'!$B$1"),IF(VLOOKUP(M$1,INDIRECT("'"&$A22&"'!$A$12:$Z$41"),MATCH("Points (Auto-generate)",INDIRECT("'"&$A22&"'!$A$12:$Z$12"),0),0)="","?",VLOOKUP(M$1,INDIRECT("'"&$A22&"'!$A$12:$Z$41"),MATCH("Points (Auto-generate)",INDIRECT("'"&$A22&"'!$A$12:$Z$12"),0),0)),"ER")) -> ? | N22: =IF($H22=0,"NA",IF($A22=INDIRECT("'"&$A22&"'!$B$1"),IF(VLOOKUP(N$1,INDIRECT("'"&$A22&"'!$A$12:$Z$41"),MATCH("Points (Auto-generate)",INDIRECT("'"&$A22&"'!$A$12:$Z$12"),0),0)="","?",VLOOKUP(N$1,INDIRECT("'"&$A22&"'!$A$12:$Z$41"),MATCH("Points (Auto-generate)",INDIRECT("'"&$A22&"'!$A$12:$Z$12"),0),0)),"ER")) -> ? | O22: =IF($H22=0,"NA",IF($A22=INDIRECT("'"&$A22&"'!$B$1"),IF(VLOOKUP(O$1,INDIRECT("'"&$A22&"'!$A$12:$Z$41"),MATCH("Points (Auto-generate)",INDIRECT("'"&$A22&"'!$A$12:$Z$12"),0),0)="","?",VLOOKUP(O$1,INDIRECT("'"&$A22&"'!$A$12:$Z$41"),MATCH("Points (Auto-generate)",INDIRECT("'"&$A22&"'!$A$12:$Z$12"),0),0)),"ER")) -> ? | P22: =IF($H22=0,"NA",IF($A22=INDIRECT("'"&$A22&"'!$B$1"),IF(VLOOKUP(P$1,INDIRECT("'"&$A22&"'!$A$12:$Z$41"),MATCH("Points (Auto-generate)",INDIRECT("'"&$A22&"'!$A$12:$Z$12"),0),0)="","?",VLOOKUP(P$1,INDIRECT("'"&$A22&"'!$A$12:$Z$41"),MATCH("Points (Auto-generate)",INDIRECT("'"&$A22&"'!$A$12:$Z$12"),0),0)),"ER")) -> ? | ... AK22: =IF($H22=0,"NA",IF($A22=INDIRECT("'"&$A22&"'!$B$1"),IF(VLOOKUP(AK$1,INDIRECT("'"&$A22&"'!$A$12:$Z$41"),MATCH("Points (Auto-generate)",INDIRECT("'"&$A22&"'!$A$12:$Z$12"),0),0)="","?",VLOOKUP(AK$1,INDIRECT("'"&$A22&"'!$A$12:$Z$41"),MATCH("Points (Auto-generate)",INDIRECT("'"&$A22&"'!$A$12:$Z$12"),0),0)),"ER")) -> ?
A23: UPD11b | B23: =IF(ISBLANK($A23),"NO_CODE",VLOOKUP($A23,'UPD Questions_290926 '!$E$1:$N$300,MATCH(B$1,'UPD Questions_290926 '!$E$1:$N$1,0),0)&"") -> Planning | C23: =IF(ISBLANK($A23),"NO_CODE",VLOOKUP($A23,'UPD Questions_290926 '!$E$1:$N$300,MATCH(C$1,'UPD Questions_290926 '!$E$1:$N$1,0),0)&"") -> Municipal/City Plan preparation, participation and review | D23: =IF(ISBLANK($A23),"NO_CODE",VLOOKUP($A23,'UPD Questions_290926 '!$E$1:$N$300,MATCH(D$1,'UPD Questions_290926 '!$E$1:$N$1,0),0)&"") -> Public participation and scrutiny | E23: =IF(ISBLANK($A23),"NO_CODE",VLOOKUP($A23,'UPD Questions_290926 '!$E$1:$N$300,MATCH(E$1,'UPD Questions_290926 '!$E$1:$N$1,0),0)&"") -> SQ | F23: =IF(ISBLANK($A23),"NO_CODE",VLOOKUP($A23,'UPD Questions_290926 '!$E$1:$N$300,MATCH(F$1,'UPD Questions_290926 '!$E$1:$N$1,0),0)&"") -> Was the public scrutiny undertaken for (including objections and responses) municipal/city plan? | G23: =IF(ISBLANK($A23),"NO_CODE",VLOOKUP($A23,'UPD Questions_290926 '!$E$1:$N$300,MATCH(G$1,'UPD Questions_290926 '!$E$1:$N$1,0),0)&"") -> Implementation | H23: =IF(ISBLANK($A23),"NO_CODE",VLOOKUP($A23,'UPD Questions_290926 '!$E$1:$N$300,MATCH(H$1,'UPD Questions_290926 '!$E$1:$N$1,0),0)) -> 5 | I23: =IF($H23=0,"NA",IF($A23=INDIRECT("'"&$A23&"'!$B$1"),IF(VLOOKUP(I$1,INDIRECT("'"&$A23&"'!$A$12:$Z$41"),MATCH("Points (Auto-generate)",INDIRECT("'"&$A23&"'!$A$12:$Z$12"),0),0)="","?",VLOOKUP(I$1,INDIRECT("'"&$A23&"'!$A$12:$Z$41"),MATCH("Points (Auto-generate)",INDIRECT("'"&$A23&"'!$A$12:$Z$12"),0),0)),"ER")) -> ? | J23: =IF($H23=0,"NA",IF($A23=INDIRECT("'"&$A23&"'!$B$1"),IF(VLOOKUP(J$1,INDIRECT("'"&$A23&"'!$A$12:$Z$41"),MATCH("Points (Auto-generate)",INDIRECT("'"&$A23&"'!$A$12:$Z$12"),0),0)="","?",VLOOKUP(J$1,INDIRECT("'"&$A23&"'!$A$12:$Z$41"),MATCH("Points (Auto-generate)",INDIRECT("'"&$A23&"'!$A$12:$Z$12"),0),0)),"ER")) -> ? | K23: =IF($H23=0,"NA",IF($A23=INDIRECT("'"&$A23&"'!$B$1"),IF(VLOOKUP(K$1,INDIRECT("'"&$A23&"'!$A$12:$Z$41"),MATCH("Points (Auto-generate)",INDIRECT("'"&$A23&"'!$A$12:$Z$12"),0),0)="","?",VLOOKUP(K$1,INDIRECT("'"&$A23&"'!$A$12:$Z$41"),MATCH("Points (Auto-generate)",INDIRECT("'"&$A23&"'!$A$12:$Z$12"),0),0)),"ER")) -> ? | L23: =IF($H23=0,"NA",IF($A23=INDIRECT("'"&$A23&"'!$B$1"),IF(VLOOKUP(L$1,INDIRECT("'"&$A23&"'!$A$12:$Z$41"),MATCH("Points (Auto-generate)",INDIRECT("'"&$A23&"'!$A$12:$Z$12"),0),0)="","?",VLOOKUP(L$1,INDIRECT("'"&$A23&"'!$A$12:$Z$41"),MATCH("Points (Auto-generate)",INDIRECT("'"&$A23&"'!$A$12:$Z$12"),0),0)),"ER")) -> ? | M23: =IF($H23=0,"NA",IF($A23=INDIRECT("'"&$A23&"'!$B$1"),IF(VLOOKUP(M$1,INDIRECT("'"&$A23&"'!$A$12:$Z$41"),MATCH("Points (Auto-generate)",INDIRECT("'"&$A23&"'!$A$12:$Z$12"),0),0)="","?",VLOOKUP(M$1,INDIRECT("'"&$A23&"'!$A$12:$Z$41"),MATCH("Points (Auto-generate)",INDIRECT("'"&$A23&"'!$A$12:$Z$12"),0),0)),"ER")) -> ? | N23: =IF($H23=0,"NA",IF($A23=INDIRECT("'"&$A23&"'!$B$1"),IF(VLOOKUP(N$1,INDIRECT("'"&$A23&"'!$A$12:$Z$41"),MATCH("Points (Auto-generate)",INDIRECT("'"&$A23&"'!$A$12:$Z$12"),0),0)="","?",VLOOKUP(N$1,INDIRECT("'"&$A23&"'!$A$12:$Z$41"),MATCH("Points (Auto-generate)",INDIRECT("'"&$A23&"'!$A$12:$Z$12"),0),0)),"ER")) -> ? | O23: =IF($H23=0,"NA",IF($A23=INDIRECT("'"&$A23&"'!$B$1"),IF(VLOOKUP(O$1,INDIRECT("'"&$A23&"'!$A$12:$Z$41"),MATCH("Points (Auto-generate)",INDIRECT("'"&$A23&"'!$A$12:$Z$12"),0),0)="","?",VLOOKUP(O$1,INDIRECT("'"&$A23&"'!$A$12:$Z$41"),MATCH("Points (Auto-generate)",INDIRECT("'"&$A23&"'!$A$12:$Z$12"),0),0)),"ER")) -> ? | P23: =IF($H23=0,"NA",IF($A23=INDIRECT("'"&$A23&"'!$B$1"),IF(VLOOKUP(P$1,INDIRECT("'"&$A23&"'!$A$12:$Z$41"),MATCH("Points (Auto-generate)",INDIRECT("'"&$A23&"'!$A$12:$Z$12"),0),0)="","?",VLOOKUP(P$1,INDIRECT("'"&$A23&"'!$A$12:$Z$41"),MATCH("Points (Auto-generate)",INDIRECT("'"&$A23&"'!$A$12:$Z$12"),0),0)),"ER")) -> ? | ... AK23: =IF($H23=0,"NA",IF($A23=INDIRECT("'"&$A23&"'!$B$1"),IF(VLOOKUP(AK$1,INDIRECT("'"&$A23&"'!$A$12:$Z$41"),MATCH("Points (Auto-generate)",INDIRECT("'"&$A23&"'!$A$12:$Z$12"),0),0)="","?",VLOOKUP(AK$1,INDIRECT("'"&$A23&"'!$A$12:$Z$41"),MATCH("Points (Auto-generate)",INDIRECT("'"&$A23&"'!$A$12:$Z$12"),0),0)),"ER")) -> ?
A24: UPD12 | B24: =IF(ISBLANK($A24),"NO_CODE",VLOOKUP($A24,'UPD Questions_290926 '!$E$1:$N$300,MATCH(B$1,'UPD Questions_290926 '!$E$1:$N$1,0),0)&"") -> Planning | C24: =IF(ISBLANK($A24),"NO_CODE",VLOOKUP($A24,'UPD Questions_290926 '!$E$1:$N$300,MATCH(C$1,'UPD Questions_290926 '!$E$1:$N$1,0),0)&"") -> Municipal/City Plan preparation, participation and review | D24: =IF(ISBLANK($A24),"NO_CODE",VLOOKUP($A24,'UPD Questions_290926 '!$E$1:$N$300,MATCH(D$1,'UPD Questions_290926 '!$E$1:$N$1,0),0)&"") -> Plan modification and implementation review | E24: =IF(ISBLANK($A24),"NO_CODE",VLOOKUP($A24,'UPD Questions_290926 '!$E$1:$N$300,MATCH(E$1,'UPD Questions_290926 '!$E$1:$N$1,0),0)&"") -> MQ | F24: =IF(ISBLANK($A24),"NO_CODE",VLOOKUP($A24,'UPD Questions_290926 '!$E$1:$N$300,MATCH(F$1,'UPD Questions_290926 '!$E$1:$N$1,0),0)&"") -> Does the law mandate periodic review and revision of the notified municipal/city plan, including corresponding revisions to the Development Control Regulations (DCRs)? | G24: =IF(ISBLANK($A24),"NO_CODE",VLOOKUP($A24,'UPD Questions_290926 '!$E$1:$N$300,MATCH(G$1,'UPD Questions_290926 '!$E$1:$N$1,0),0)&"") -> Law or Policy | H24: =IF(ISBLANK($A24),"NO_CODE",VLOOKUP($A24,'UPD Questions_290926 '!$E$1:$N$300,MATCH(H$1,'UPD Questions_290926 '!$E$1:$N$1,0),0)) -> 10 | I24: =IF($H24=0,"NA",IF($A24=INDIRECT("'"&$A24&"'!$B$1"),IF(VLOOKUP(I$1,INDIRECT("'"&$A24&"'!$A$12:$Z$41"),MATCH("Points (Auto-generate)",INDIRECT("'"&$A24&"'!$A$12:$Z$12"),0),0)="","?",VLOOKUP(I$1,INDIRECT("'"&$A24&"'!$A$12:$Z$41"),MATCH("Points (Auto-generate)",INDIRECT("'"&$A24&"'!$A$12:$Z$12"),0),0)),"ER")) -> ? | J24: =IF($H24=0,"NA",IF($A24=INDIRECT("'"&$A24&"'!$B$1"),IF(VLOOKUP(J$1,INDIRECT("'"&$A24&"'!$A$12:$Z$41"),MATCH("Points (Auto-generate)",INDIRECT("'"&$A24&"'!$A$12:$Z$12"),0),0)="","?",VLOOKUP(J$1,INDIRECT("'"&$A24&"'!$A$12:$Z$41"),MATCH("Points (Auto-generate)",INDIRECT("'"&$A24&"'!$A$12:$Z$12"),0),0)),"ER")) -> ? | K24: =IF($H24=0,"NA",IF($A24=INDIRECT("'"&$A24&"'!$B$1"),IF(VLOOKUP(K$1,INDIRECT("'"&$A24&"'!$A$12:$Z$41"),MATCH("Points (Auto-generate)",INDIRECT("'"&$A24&"'!$A$12:$Z$12"),0),0)="","?",VLOOKUP(K$1,INDIRECT("'"&$A24&"'!$A$12:$Z$41"),MATCH("Points (Auto-generate)",INDIRECT("'"&$A24&"'!$A$12:$Z$12"),0),0)),"ER")) -> ? | L24: =IF($H24=0,"NA",IF($A24=INDIRECT("'"&$A24&"'!$B$1"),IF(VLOOKUP(L$1,INDIRECT("'"&$A24&"'!$A$12:$Z$41"),MATCH("Points (Auto-generate)",INDIRECT("'"&$A24&"'!$A$12:$Z$12"),0),0)="","?",VLOOKUP(L$1,INDIRECT("'"&$A24&"'!$A$12:$Z$41"),MATCH("Points (Auto-generate)",INDIRECT("'"&$A24&"'!$A$12:$Z$12"),0),0)),"ER")) -> ? | M24: =IF($H24=0,"NA",IF($A24=INDIRECT("'"&$A24&"'!$B$1"),IF(VLOOKUP(M$1,INDIRECT("'"&$A24&"'!$A$12:$Z$41"),MATCH("Points (Auto-generate)",INDIRECT("'"&$A24&"'!$A$12:$Z$12"),0),0)="","?",VLOOKUP(M$1,INDIRECT("'"&$A24&"'!$A$12:$Z$41"),MATCH("Points (Auto-generate)",INDIRECT("'"&$A24&"'!$A$12:$Z$12"),0),0)),"ER")) -> ? | N24: =IF($H24=0,"NA",IF($A24=INDIRECT("'"&$A24&"'!$B$1"),IF(VLOOKUP(N$1,INDIRECT("'"&$A24&"'!$A$12:$Z$41"),MATCH("Points (Auto-generate)",INDIRECT("'"&$A24&"'!$A$12:$Z$12"),0),0)="","?",VLOOKUP(N$1,INDIRECT("'"&$A24&"'!$A$12:$Z$41"),MATCH("Points (Auto-generate)",INDIRECT("'"&$A24&"'!$A$12:$Z$12"),0),0)),"ER")) -> ? | O24: =IF($H24=0,"NA",IF($A24=INDIRECT("'"&$A24&"'!$B$1"),IF(VLOOKUP(O$1,INDIRECT("'"&$A24&"'!$A$12:$Z$41"),MATCH("Points (Auto-generate)",INDIRECT("'"&$A24&"'!$A$12:$Z$12"),0),0)="","?",VLOOKUP(O$1,INDIRECT("'"&$A24&"'!$A$12:$Z$41"),MATCH("Points (Auto-generate)",INDIRECT("'"&$A24&"'!$A$12:$Z$12"),0),0)),"ER")) -> ? | P24: =IF($H24=0,"NA",IF($A24=INDIRECT("'"&$A24&"'!$B$1"),IF(VLOOKUP(P$1,INDIRECT("'"&$A24&"'!$A$12:$Z$41"),MATCH("Points (Auto-generate)",INDIRECT("'"&$A24&"'!$A$12:$Z$12"),0),0)="","?",VLOOKUP(P$1,INDIRECT("'"&$A24&"'!$A$12:$Z$41"),MATCH("Points (Auto-generate)",INDIRECT("'"&$A24&"'!$A$12:$Z$12"),0),0)),"ER")) -> ? | ... AK24: =IF($H24=0,"NA",IF($A24=INDIRECT("'"&$A24&"'!$B$1"),IF(VLOOKUP(AK$1,INDIRECT("'"&$A24&"'!$A$12:$Z$41"),MATCH("Points (Auto-generate)",INDIRECT("'"&$A24&"'!$A$12:$Z$12"),0),0)="","?",VLOOKUP(AK$1,INDIRECT("'"&$A24&"'!$A$12:$Z$41"),MATCH("Points (Auto-generate)",INDIRECT("'"&$A24&"'!$A$12:$Z$12"),0),0)),"ER")) -> ?
A25: UPD13 | B25: =IF(ISBLANK($A25),"NO_CODE",VLOOKUP($A25,'UPD Questions_290926 '!$E$1:$N$300,MATCH(B$1,'UPD Questions_290926 '!$E$1:$N$1,0),0)&"") -> Planning | C25: =IF(ISBLANK($A25),"NO_CODE",VLOOKUP($A25,'UPD Questions_290926 '!$E$1:$N$300,MATCH(C$1,'UPD Questions_290926 '!$E$1:$N$1,0),0)&"") -> Municipal/City Plan objectives and contents | D25: =IF(ISBLANK($A25),"NO_CODE",VLOOKUP($A25,'UPD Questions_290926 '!$E$1:$N$300,MATCH(D$1,'UPD Questions_290926 '!$E$1:$N$1,0),0)&"") -> Statutory requirements for plan content | E25: =IF(ISBLANK($A25),"NO_CODE",VLOOKUP($A25,'UPD Questions_290926 '!$E$1:$N$300,MATCH(E$1,'UPD Questions_290926 '!$E$1:$N$1,0),0)&"") -> MQ | F25: =IF(ISBLANK($A25),"NO_CODE",VLOOKUP($A25,'UPD Questions_290926 '!$E$1:$N$300,MATCH(F$1,'UPD Questions_290926 '!$E$1:$N$1,0),0)&"") -> Does the T&CP Act mandate the planning for: | G25: =IF(ISBLANK($A25),"NO_CODE",VLOOKUP($A25,'UPD Questions_290926 '!$E$1:$N$300,MATCH(G$1,'UPD Questions_290926 '!$E$1:$N$1,0),0)&"") -> NA- question already covered in ASICS 2017 | H25: =IF(ISBLANK($A25),"NO_CODE",VLOOKUP($A25,'UPD Questions_290926 '!$E$1:$N$300,MATCH(H$1,'UPD Questions_290926 '!$E$1:$N$1,0),0)) -> 10 | I25: =IF(OR(I26="ER",I27="ER",I28="ER",I29="ER",I30="ER",I31="ER"),"ER",IF(OR(I26="?",I27="?",I28="?",I29="?",I30="?",I31="?"),"?",IF(AND(I26="NA",I27="NA",I28="NA",I29="NA",I30="NA",I31="NA"),"NA",SUM(I26,I27,I28,I29,I30,I31)/((I26<>"NA")*$H$26+(I27<>"NA")*$H$27+(I28<>"NA")*$H$28+(I29<>"NA")*$H$29+(I30<>"NA")*$H$30+(I31<>"NA")*$H$31)*$H25))) -> ? | J25: =IF(OR(J26="ER",J27="ER",J28="ER",J29="ER",J30="ER",J31="ER"),"ER",IF(OR(J26="?",J27="?",J28="?",J29="?",J30="?",J31="?"),"?",IF(AND(J26="NA",J27="NA",J28="NA",J29="NA",J30="NA",J31="NA"),"NA",SUM(J26,J27,J28,J29,J30,J31)/((J26<>"NA")*$H$26+(J27<>"NA")*$H$27+(J28<>"NA")*$H$28+(J29<>"NA")*$H$29+(J30<>"NA")*$H$30+(J31<>"NA")*$H$31)*$H25))) -> ? | K25: =IF(OR(K26="ER",K27="ER",K28="ER",K29="ER",K30="ER",K31="ER"),"ER",IF(OR(K26="?",K27="?",K28="?",K29="?",K30="?",K31="?"),"?",IF(AND(K26="NA",K27="NA",K28="NA",K29="NA",K30="NA",K31="NA"),"NA",SUM(K26,K27,K28,K29,K30,K31)/((K26<>"NA")*$H$26+(K27<>"NA")*$H$27+(K28<>"NA")*$H$28+(K29<>"NA")*$H$29+(K30<>"NA")*$H$30+(K31<>"NA")*$H$31)*$H25))) -> ? | L25: =IF(OR(L26="ER",L27="ER",L28="ER",L29="ER",L30="ER",L31="ER"),"ER",IF(OR(L26="?",L27="?",L28="?",L29="?",L30="?",L31="?"),"?",IF(AND(L26="NA",L27="NA",L28="NA",L29="NA",L30="NA",L31="NA"),"NA",SUM(L26,L27,L28,L29,L30,L31)/((L26<>"NA")*$H$26+(L27<>"NA")*$H$27+(L28<>"NA")*$H$28+(L29<>"NA")*$H$29+(L30<>"NA")*$H$30+(L31<>"NA")*$H$31)*$H25))) -> ? | M25: =IF(OR(M26="ER",M27="ER",M28="ER",M29="ER",M30="ER",M31="ER"),"ER",IF(OR(M26="?",M27="?",M28="?",M29="?",M30="?",M31="?"),"?",IF(AND(M26="NA",M27="NA",M28="NA",M29="NA",M30="NA",M31="NA"),"NA",SUM(M26,M27,M28,M29,M30,M31)/((M26<>"NA")*$H$26+(M27<>"NA")*$H$27+(M28<>"NA")*$H$28+(M29<>"NA")*$H$29+(M30<>"NA")*$H$30+(M31<>"NA")*$H$31)*$H25))) -> ? | N25: =IF(OR(N26="ER",N27="ER",N28="ER",N29="ER",N30="ER",N31="ER"),"ER",IF(OR(N26="?",N27="?",N28="?",N29="?",N30="?",N31="?"),"?",IF(AND(N26="NA",N27="NA",N28="NA",N29="NA",N30="NA",N31="NA"),"NA",SUM(N26,N27,N28,N29,N30,N31)/((N26<>"NA")*$H$26+(N27<>"NA")*$H$27+(N28<>"NA")*$H$28+(N29<>"NA")*$H$29+(N30<>"NA")*$H$30+(N31<>"NA")*$H$31)*$H25))) -> ? | O25: =IF(OR(O26="ER",O27="ER",O28="ER",O29="ER",O30="ER",O31="ER"),"ER",IF(OR(O26="?",O27="?",O28="?",O29="?",O30="?",O31="?"),"?",IF(AND(O26="NA",O27="NA",O28="NA",O29="NA",O30="NA",O31="NA"),"NA",SUM(O26,O27,O28,O29,O30,O31)/((O26<>"NA")*$H$26+(O27<>"NA")*$H$27+(O28<>"NA")*$H$28+(O29<>"NA")*$H$29+(O30<>"NA")*$H$30+(O31<>"NA")*$H$31)*$H25))) -> ? | P25: =IF(OR(P26="ER",P27="ER",P28="ER",P29="ER",P30="ER",P31="ER"),"ER",IF(OR(P26="?",P27="?",P28="?",P29="?",P30="?",P31="?"),"?",IF(AND(P26="NA",P27="NA",P28="NA",P29="NA",P30="NA",P31="NA"),"NA",SUM(P26,P27,P28,P29,P30,P31)/((P26<>"NA")*$H$26+(P27<>"NA")*$H$27+(P28<>"NA")*$H$28+(P29<>"NA")*$H$29+(P30<>"NA")*$H$30+(P31<>"NA")*$H$31)*$H25))) -> ? | ... AK25: =IF(OR(AK26="ER",AK27="ER",AK28="ER",AK29="ER",AK30="ER",AK31="ER"),"ER",IF(OR(AK26="?",AK27="?",AK28="?",AK29="?",AK30="?",AK31="?"),"?",IF(AND(AK26="NA",AK27="NA",AK28="NA",AK29="NA",AK30="NA",AK31="NA"),"NA",SUM(AK26,AK27,AK28,AK29,AK30,AK31)/((AK26<>"NA")*$H$26+(AK27<>"NA")*$H$27+(AK28<>"NA")*$H$28+(AK29<>"NA")*$H$29+(AK30<>"NA")*$H$30+(AK31<>"NA")*$H$31)*$H25))) -> ?
A26: UPD13a | B26: =IF(ISBLANK($A26),"NO_CODE",VLOOKUP($A26,'UPD Questions_290926 '!$E$1:$N$300,MATCH(B$1,'UPD Questions_290926 '!$E$1:$N$1,0),0)&"") -> Planning | C26: =IF(ISBLANK($A26),"NO_CODE",VLOOKUP($A26,'UPD Questions_290926 '!$E$1:$N$300,MATCH(C$1,'UPD Questions_290926 '!$E$1:$N$1,0),0)&"") -> Municipal/City Plan objectives and contents | D26: =IF(ISBLANK($A26),"NO_CODE",VLOOKUP($A26,'UPD Questions_290926 '!$E$1:$N$300,MATCH(D$1,'UPD Questions_290926 '!$E$1:$N$1,0),0)&"") -> Statutory requirements for plan content | E26: =IF(ISBLANK($A26),"NO_CODE",VLOOKUP($A26,'UPD Questions_290926 '!$E$1:$N$300,MATCH(E$1,'UPD Questions_290926 '!$E$1:$N$1,0),0)&"") -> SQ | F26: =IF(ISBLANK($A26),"NO_CODE",VLOOKUP($A26,'UPD Questions_290926 '!$E$1:$N$300,MATCH(F$1,'UPD Questions_290926 '!$E$1:$N$1,0),0)&"") -> a) Water Supply/ Sewerage, Sanitation and Solid Waste Management | G26: =IF(ISBLANK($A26),"NO_CODE",VLOOKUP($A26,'UPD Questions_290926 '!$E$1:$N$300,MATCH(G$1,'UPD Questions_290926 '!$E$1:$N$1,0),0)&"") -> Law/Policy | H26: =IF(ISBLANK($A26),"NO_CODE",VLOOKUP($A26,'UPD Questions_290926 '!$E$1:$N$300,MATCH(H$1,'UPD Questions_290926 '!$E$1:$N$1,0),0)) -> 1.67 | I26: =IF($H26=0,"NA",IF($A26=INDIRECT("'"&$A26&"'!$B$1"),IF(VLOOKUP(I$1,INDIRECT("'"&$A26&"'!$A$12:$Z$41"),MATCH("Points (Auto-generate)",INDIRECT("'"&$A26&"'!$A$12:$Z$12"),0),0)="","?",VLOOKUP(I$1,INDIRECT("'"&$A26&"'!$A$12:$Z$41"),MATCH("Points (Auto-generate)",INDIRECT("'"&$A26&"'!$A$12:$Z$12"),0),0)),"ER")) -> ? | J26: =IF($H26=0,"NA",IF($A26=INDIRECT("'"&$A26&"'!$B$1"),IF(VLOOKUP(J$1,INDIRECT("'"&$A26&"'!$A$12:$Z$41"),MATCH("Points (Auto-generate)",INDIRECT("'"&$A26&"'!$A$12:$Z$12"),0),0)="","?",VLOOKUP(J$1,INDIRECT("'"&$A26&"'!$A$12:$Z$41"),MATCH("Points (Auto-generate)",INDIRECT("'"&$A26&"'!$A$12:$Z$12"),0),0)),"ER")) -> ? | K26: =IF($H26=0,"NA",IF($A26=INDIRECT("'"&$A26&"'!$B$1"),IF(VLOOKUP(K$1,INDIRECT("'"&$A26&"'!$A$12:$Z$41"),MATCH("Points (Auto-generate)",INDIRECT("'"&$A26&"'!$A$12:$Z$12"),0),0)="","?",VLOOKUP(K$1,INDIRECT("'"&$A26&"'!$A$12:$Z$41"),MATCH("Points (Auto-generate)",INDIRECT("'"&$A26&"'!$A$12:$Z$12"),0),0)),"ER")) -> ? | L26: =IF($H26=0,"NA",IF($A26=INDIRECT("'"&$A26&"'!$B$1"),IF(VLOOKUP(L$1,INDIRECT("'"&$A26&"'!$A$12:$Z$41"),MATCH("Points (Auto-generate)",INDIRECT("'"&$A26&"'!$A$12:$Z$12"),0),0)="","?",VLOOKUP(L$1,INDIRECT("'"&$A26&"'!$A$12:$Z$41"),MATCH("Points (Auto-generate)",INDIRECT("'"&$A26&"'!$A$12:$Z$12"),0),0)),"ER")) -> ? | M26: =IF($H26=0,"NA",IF($A26=INDIRECT("'"&$A26&"'!$B$1"),IF(VLOOKUP(M$1,INDIRECT("'"&$A26&"'!$A$12:$Z$41"),MATCH("Points (Auto-generate)",INDIRECT("'"&$A26&"'!$A$12:$Z$12"),0),0)="","?",VLOOKUP(M$1,INDIRECT("'"&$A26&"'!$A$12:$Z$41"),MATCH("Points (Auto-generate)",INDIRECT("'"&$A26&"'!$A$12:$Z$12"),0),0)),"ER")) -> ? | N26: =IF($H26=0,"NA",IF($A26=INDIRECT("'"&$A26&"'!$B$1"),IF(VLOOKUP(N$1,INDIRECT("'"&$A26&"'!$A$12:$Z$41"),MATCH("Points (Auto-generate)",INDIRECT("'"&$A26&"'!$A$12:$Z$12"),0),0)="","?",VLOOKUP(N$1,INDIRECT("'"&$A26&"'!$A$12:$Z$41"),MATCH("Points (Auto-generate)",INDIRECT("'"&$A26&"'!$A$12:$Z$12"),0),0)),"ER")) -> ? | O26: =IF($H26=0,"NA",IF($A26=INDIRECT("'"&$A26&"'!$B$1"),IF(VLOOKUP(O$1,INDIRECT("'"&$A26&"'!$A$12:$Z$41"),MATCH("Points (Auto-generate)",INDIRECT("'"&$A26&"'!$A$12:$Z$12"),0),0)="","?",VLOOKUP(O$1,INDIRECT("'"&$A26&"'!$A$12:$Z$41"),MATCH("Points (Auto-generate)",INDIRECT("'"&$A26&"'!$A$12:$Z$12"),0),0)),"ER")) -> ? | P26: =IF($H26=0,"NA",IF($A26=INDIRECT("'"&$A26&"'!$B$1"),IF(VLOOKUP(P$1,INDIRECT("'"&$A26&"'!$A$12:$Z$41"),MATCH("Points (Auto-generate)",INDIRECT("'"&$A26&"'!$A$12:$Z$12"),0),0)="","?",VLOOKUP(P$1,INDIRECT("'"&$A26&"'!$A$12:$Z$41"),MATCH("Points (Auto-generate)",INDIRECT("'"&$A26&"'!$A$12:$Z$12"),0),0)),"ER")) -> ? | ... AK26: =IF($H26=0,"NA",IF($A26=INDIRECT("'"&$A26&"'!$B$1"),IF(VLOOKUP(AK$1,INDIRECT("'"&$A26&"'!$A$12:$Z$41"),MATCH("Points (Auto-generate)",INDIRECT("'"&$A26&"'!$A$12:$Z$12"),0),0)="","?",VLOOKUP(AK$1,INDIRECT("'"&$A26&"'!$A$12:$Z$41"),MATCH("Points (Auto-generate)",INDIRECT("'"&$A26&"'!$A$12:$Z$12"),0),0)),"ER")) -> ?
A27: UPD13b | B27: =IF(ISBLANK($A27),"NO_CODE",VLOOKUP($A27,'UPD Questions_290926 '!$E$1:$N$300,MATCH(B$1,'UPD Questions_290926 '!$E$1:$N$1,0),0)&"") -> Planning | C27: =IF(ISBLANK($A27),"NO_CODE",VLOOKUP($A27,'UPD Questions_290926 '!$E$1:$N$300,MATCH(C$1,'UPD Questions_290926 '!$E$1:$N$1,0),0)&"") -> Municipal/City Plan objectives and contents | D27: =IF(ISBLANK($A27),"NO_CODE",VLOOKUP($A27,'UPD Questions_290926 '!$E$1:$N$300,MATCH(D$1,'UPD Questions_290926 '!$E$1:$N$1,0),0)&"") -> Statutory requirements for plan content | E27: =IF(ISBLANK($A27),"NO_CODE",VLOOKUP($A27,'UPD Questions_290926 '!$E$1:$N$300,MATCH(E$1,'UPD Questions_290926 '!$E$1:$N$1,0),0)&"") -> SQ | F27: =IF(ISBLANK($A27),"NO_CODE",VLOOKUP($A27,'UPD Questions_290926 '!$E$1:$N$300,MATCH(F$1,'UPD Questions_290926 '!$E$1:$N$1,0),0)&"") -> b) Disaster Resilience | G27: =IF(ISBLANK($A27),"NO_CODE",VLOOKUP($A27,'UPD Questions_290926 '!$E$1:$N$300,MATCH(G$1,'UPD Questions_290926 '!$E$1:$N$1,0),0)&"") -> Law/Policy | H27: =IF(ISBLANK($A27),"NO_CODE",VLOOKUP($A27,'UPD Questions_290926 '!$E$1:$N$300,MATCH(H$1,'UPD Questions_290926 '!$E$1:$N$1,0),0)) -> 1.67 | I27: =IF($H27=0,"NA",IF($A27=INDIRECT("'"&$A27&"'!$B$1"),IF(VLOOKUP(I$1,INDIRECT("'"&$A27&"'!$A$12:$Z$41"),MATCH("Points (Auto-generate)",INDIRECT("'"&$A27&"'!$A$12:$Z$12"),0),0)="","?",VLOOKUP(I$1,INDIRECT("'"&$A27&"'!$A$12:$Z$41"),MATCH("Points (Auto-generate)",INDIRECT("'"&$A27&"'!$A$12:$Z$12"),0),0)),"ER")) -> ? | J27: =IF($H27=0,"NA",IF($A27=INDIRECT("'"&$A27&"'!$B$1"),IF(VLOOKUP(J$1,INDIRECT("'"&$A27&"'!$A$12:$Z$41"),MATCH("Points (Auto-generate)",INDIRECT("'"&$A27&"'!$A$12:$Z$12"),0),0)="","?",VLOOKUP(J$1,INDIRECT("'"&$A27&"'!$A$12:$Z$41"),MATCH("Points (Auto-generate)",INDIRECT("'"&$A27&"'!$A$12:$Z$12"),0),0)),"ER")) -> ? | K27: =IF($H27=0,"NA",IF($A27=INDIRECT("'"&$A27&"'!$B$1"),IF(VLOOKUP(K$1,INDIRECT("'"&$A27&"'!$A$12:$Z$41"),MATCH("Points (Auto-generate)",INDIRECT("'"&$A27&"'!$A$12:$Z$12"),0),0)="","?",VLOOKUP(K$1,INDIRECT("'"&$A27&"'!$A$12:$Z$41"),MATCH("Points (Auto-generate)",INDIRECT("'"&$A27&"'!$A$12:$Z$12"),0),0)),"ER")) -> ? | L27: =IF($H27=0,"NA",IF($A27=INDIRECT("'"&$A27&"'!$B$1"),IF(VLOOKUP(L$1,INDIRECT("'"&$A27&"'!$A$12:$Z$41"),MATCH("Points (Auto-generate)",INDIRECT("'"&$A27&"'!$A$12:$Z$12"),0),0)="","?",VLOOKUP(L$1,INDIRECT("'"&$A27&"'!$A$12:$Z$41"),MATCH("Points (Auto-generate)",INDIRECT("'"&$A27&"'!$A$12:$Z$12"),0),0)),"ER")) -> ? | M27: =IF($H27=0,"NA",IF($A27=INDIRECT("'"&$A27&"'!$B$1"),IF(VLOOKUP(M$1,INDIRECT("'"&$A27&"'!$A$12:$Z$41"),MATCH("Points (Auto-generate)",INDIRECT("'"&$A27&"'!$A$12:$Z$12"),0),0)="","?",VLOOKUP(M$1,INDIRECT("'"&$A27&"'!$A$12:$Z$41"),MATCH("Points (Auto-generate)",INDIRECT("'"&$A27&"'!$A$12:$Z$12"),0),0)),"ER")) -> ? | N27: =IF($H27=0,"NA",IF($A27=INDIRECT("'"&$A27&"'!$B$1"),IF(VLOOKUP(N$1,INDIRECT("'"&$A27&"'!$A$12:$Z$41"),MATCH("Points (Auto-generate)",INDIRECT("'"&$A27&"'!$A$12:$Z$12"),0),0)="","?",VLOOKUP(N$1,INDIRECT("'"&$A27&"'!$A$12:$Z$41"),MATCH("Points (Auto-generate)",INDIRECT("'"&$A27&"'!$A$12:$Z$12"),0),0)),"ER")) -> ? | O27: =IF($H27=0,"NA",IF($A27=INDIRECT("'"&$A27&"'!$B$1"),IF(VLOOKUP(O$1,INDIRECT("'"&$A27&"'!$A$12:$Z$41"),MATCH("Points (Auto-generate)",INDIRECT("'"&$A27&"'!$A$12:$Z$12"),0),0)="","?",VLOOKUP(O$1,INDIRECT("'"&$A27&"'!$A$12:$Z$41"),MATCH("Points (Auto-generate)",INDIRECT("'"&$A27&"'!$A$12:$Z$12"),0),0)),"ER")) -> ? | P27: =IF($H27=0,"NA",IF($A27=INDIRECT("'"&$A27&"'!$B$1"),IF(VLOOKUP(P$1,INDIRECT("'"&$A27&"'!$A$12:$Z$41"),MATCH("Points (Auto-generate)",INDIRECT("'"&$A27&"'!$A$12:$Z$12"),0),0)="","?",VLOOKUP(P$1,INDIRECT("'"&$A27&"'!$A$12:$Z$41"),MATCH("Points (Auto-generate)",INDIRECT("'"&$A27&"'!$A$12:$Z$12"),0),0)),"ER")) -> ? | ... AK27: =IF($H27=0,"NA",IF($A27=INDIRECT("'"&$A27&"'!$B$1"),IF(VLOOKUP(AK$1,INDIRECT("'"&$A27&"'!$A$12:$Z$41"),MATCH("Points (Auto-generate)",INDIRECT("'"&$A27&"'!$A$12:$Z$12"),0),0)="","?",VLOOKUP(AK$1,INDIRECT("'"&$A27&"'!$A$12:$Z$41"),MATCH("Points (Auto-generate)",INDIRECT("'"&$A27&"'!$A$12:$Z$12"),0),0)),"ER")) -> ?
A28: UPD13c | B28: =IF(ISBLANK($A28),"NO_CODE",VLOOKUP($A28,'UPD Questions_290926 '!$E$1:$N$300,MATCH(B$1,'UPD Questions_290926 '!$E$1:$N$1,0),0)&"") -> Planning | C28: =IF(ISBLANK($A28),"NO_CODE",VLOOKUP($A28,'UPD Questions_290926 '!$E$1:$N$300,MATCH(C$1,'UPD Questions_290926 '!$E$1:$N$1,0),0)&"") -> Municipal/City Plan objectives and contents | D28: =IF(ISBLANK($A28),"NO_CODE",VLOOKUP($A28,'UPD Questions_290926 '!$E$1:$N$300,MATCH(D$1,'UPD Questions_290926 '!$E$1:$N$1,0),0)&"") -> Statutory requirements for plan content | E28: =IF(ISBLANK($A28),"NO_CODE",VLOOKUP($A28,'UPD Questions_290926 '!$E$1:$N$300,MATCH(E$1,'UPD Questions_290926 '!$E$1:$N$1,0),0)&"") -> SQ | F28: =IF(ISBLANK($A28),"NO_CODE",VLOOKUP($A28,'UPD Questions_290926 '!$E$1:$N$300,MATCH(F$1,'UPD Questions_290926 '!$E$1:$N$1,0),0)&"") -> c) Comprehensive mobility | G28: =IF(ISBLANK($A28),"NO_CODE",VLOOKUP($A28,'UPD Questions_290926 '!$E$1:$N$300,MATCH(G$1,'UPD Questions_290926 '!$E$1:$N$1,0),0)&"") -> Law/Policy | H28: =IF(ISBLANK($A28),"NO_CODE",VLOOKUP($A28,'UPD Questions_290926 '!$E$1:$N$300,MATCH(H$1,'UPD Questions_290926 '!$E$1:$N$1,0),0)) -> 1.67 | I28: =IF($H28=0,"NA",IF($A28=INDIRECT("'"&$A28&"'!$B$1"),IF(VLOOKUP(I$1,INDIRECT("'"&$A28&"'!$A$12:$Z$41"),MATCH("Points (Auto-generate)",INDIRECT("'"&$A28&"'!$A$12:$Z$12"),0),0)="","?",VLOOKUP(I$1,INDIRECT("'"&$A28&"'!$A$12:$Z$41"),MATCH("Points (Auto-generate)",INDIRECT("'"&$A28&"'!$A$12:$Z$12"),0),0)),"ER")) -> ? | J28: =IF($H28=0,"NA",IF($A28=INDIRECT("'"&$A28&"'!$B$1"),IF(VLOOKUP(J$1,INDIRECT("'"&$A28&"'!$A$12:$Z$41"),MATCH("Points (Auto-generate)",INDIRECT("'"&$A28&"'!$A$12:$Z$12"),0),0)="","?",VLOOKUP(J$1,INDIRECT("'"&$A28&"'!$A$12:$Z$41"),MATCH("Points (Auto-generate)",INDIRECT("'"&$A28&"'!$A$12:$Z$12"),0),0)),"ER")) -> ? | K28: =IF($H28=0,"NA",IF($A28=INDIRECT("'"&$A28&"'!$B$1"),IF(VLOOKUP(K$1,INDIRECT("'"&$A28&"'!$A$12:$Z$41"),MATCH("Points (Auto-generate)",INDIRECT("'"&$A28&"'!$A$12:$Z$12"),0),0)="","?",VLOOKUP(K$1,INDIRECT("'"&$A28&"'!$A$12:$Z$41"),MATCH("Points (Auto-generate)",INDIRECT("'"&$A28&"'!$A$12:$Z$12"),0),0)),"ER")) -> ? | L28: =IF($H28=0,"NA",IF($A28=INDIRECT("'"&$A28&"'!$B$1"),IF(VLOOKUP(L$1,INDIRECT("'"&$A28&"'!$A$12:$Z$41"),MATCH("Points (Auto-generate)",INDIRECT("'"&$A28&"'!$A$12:$Z$12"),0),0)="","?",VLOOKUP(L$1,INDIRECT("'"&$A28&"'!$A$12:$Z$41"),MATCH("Points (Auto-generate)",INDIRECT("'"&$A28&"'!$A$12:$Z$12"),0),0)),"ER")) -> ? | M28: =IF($H28=0,"NA",IF($A28=INDIRECT("'"&$A28&"'!$B$1"),IF(VLOOKUP(M$1,INDIRECT("'"&$A28&"'!$A$12:$Z$41"),MATCH("Points (Auto-generate)",INDIRECT("'"&$A28&"'!$A$12:$Z$12"),0),0)="","?",VLOOKUP(M$1,INDIRECT("'"&$A28&"'!$A$12:$Z$41"),MATCH("Points (Auto-generate)",INDIRECT("'"&$A28&"'!$A$12:$Z$12"),0),0)),"ER")) -> ? | N28: =IF($H28=0,"NA",IF($A28=INDIRECT("'"&$A28&"'!$B$1"),IF(VLOOKUP(N$1,INDIRECT("'"&$A28&"'!$A$12:$Z$41"),MATCH("Points (Auto-generate)",INDIRECT("'"&$A28&"'!$A$12:$Z$12"),0),0)="","?",VLOOKUP(N$1,INDIRECT("'"&$A28&"'!$A$12:$Z$41"),MATCH("Points (Auto-generate)",INDIRECT("'"&$A28&"'!$A$12:$Z$12"),0),0)),"ER")) -> ? | O28: =IF($H28=0,"NA",IF($A28=INDIRECT("'"&$A28&"'!$B$1"),IF(VLOOKUP(O$1,INDIRECT("'"&$A28&"'!$A$12:$Z$41"),MATCH("Points (Auto-generate)",INDIRECT("'"&$A28&"'!$A$12:$Z$12"),0),0)="","?",VLOOKUP(O$1,INDIRECT("'"&$A28&"'!$A$12:$Z$41"),MATCH("Points (Auto-generate)",INDIRECT("'"&$A28&"'!$A$12:$Z$12"),0),0)),"ER")) -> ? | P28: =IF($H28=0,"NA",IF($A28=INDIRECT("'"&$A28&"'!$B$1"),IF(VLOOKUP(P$1,INDIRECT("'"&$A28&"'!$A$12:$Z$41"),MATCH("Points (Auto-generate)",INDIRECT("'"&$A28&"'!$A$12:$Z$12"),0),0)="","?",VLOOKUP(P$1,INDIRECT("'"&$A28&"'!$A$12:$Z$41"),MATCH("Points (Auto-generate)",INDIRECT("'"&$A28&"'!$A$12:$Z$12"),0),0)),"ER")) -> ? | ... AK28: =IF($H28=0,"NA",IF($A28=INDIRECT("'"&$A28&"'!$B$1"),IF(VLOOKUP(AK$1,INDIRECT("'"&$A28&"'!$A$12:$Z$41"),MATCH("Points (Auto-generate)",INDIRECT("'"&$A28&"'!$A$12:$Z$12"),0),0)="","?",VLOOKUP(AK$1,INDIRECT("'"&$A28&"'!$A$12:$Z$41"),MATCH("Points (Auto-generate)",INDIRECT("'"&$A28&"'!$A$12:$Z$12"),0),0)),"ER")) -> ?
A29: UPD13d | B29: =IF(ISBLANK($A29),"NO_CODE",VLOOKUP($A29,'UPD Questions_290926 '!$E$1:$N$300,MATCH(B$1,'UPD Questions_290926 '!$E$1:$N$1,0),0)&"") -> Planning | C29: =IF(ISBLANK($A29),"NO_CODE",VLOOKUP($A29,'UPD Questions_290926 '!$E$1:$N$300,MATCH(C$1,'UPD Questions_290926 '!$E$1:$N$1,0),0)&"") -> Municipal/City Plan objectives and contents | D29: =IF(ISBLANK($A29),"NO_CODE",VLOOKUP($A29,'UPD Questions_290926 '!$E$1:$N$300,MATCH(D$1,'UPD Questions_290926 '!$E$1:$N$1,0),0)&"") -> Statutory requirements for plan content | E29: =IF(ISBLANK($A29),"NO_CODE",VLOOKUP($A29,'UPD Questions_290926 '!$E$1:$N$300,MATCH(E$1,'UPD Questions_290926 '!$E$1:$N$1,0),0)&"") -> SQ | F29: =IF(ISBLANK($A29),"NO_CODE",VLOOKUP($A29,'UPD Questions_290926 '!$E$1:$N$300,MATCH(F$1,'UPD Questions_290926 '!$E$1:$N$1,0),0)&"") -> d) Sustainability/Climate/Environmental conservation | G29: =IF(ISBLANK($A29),"NO_CODE",VLOOKUP($A29,'UPD Questions_290926 '!$E$1:$N$300,MATCH(G$1,'UPD Questions_290926 '!$E$1:$N$1,0),0)&"") -> Law/Policy | H29: =IF(ISBLANK($A29),"NO_CODE",VLOOKUP($A29,'UPD Questions_290926 '!$E$1:$N$300,MATCH(H$1,'UPD Questions_290926 '!$E$1:$N$1,0),0)) -> 1.67 | I29: =IF($H29=0,"NA",IF($A29=INDIRECT("'"&$A29&"'!$B$1"),IF(VLOOKUP(I$1,INDIRECT("'"&$A29&"'!$A$12:$Z$41"),MATCH("Points (Auto-generate)",INDIRECT("'"&$A29&"'!$A$12:$Z$12"),0),0)="","?",VLOOKUP(I$1,INDIRECT("'"&$A29&"'!$A$12:$Z$41"),MATCH("Points (Auto-generate)",INDIRECT("'"&$A29&"'!$A$12:$Z$12"),0),0)),"ER")) -> ? | J29: =IF($H29=0,"NA",IF($A29=INDIRECT("'"&$A29&"'!$B$1"),IF(VLOOKUP(J$1,INDIRECT("'"&$A29&"'!$A$12:$Z$41"),MATCH("Points (Auto-generate)",INDIRECT("'"&$A29&"'!$A$12:$Z$12"),0),0)="","?",VLOOKUP(J$1,INDIRECT("'"&$A29&"'!$A$12:$Z$41"),MATCH("Points (Auto-generate)",INDIRECT("'"&$A29&"'!$A$12:$Z$12"),0),0)),"ER")) -> ? | K29: =IF($H29=0,"NA",IF($A29=INDIRECT("'"&$A29&"'!$B$1"),IF(VLOOKUP(K$1,INDIRECT("'"&$A29&"'!$A$12:$Z$41"),MATCH("Points (Auto-generate)",INDIRECT("'"&$A29&"'!$A$12:$Z$12"),0),0)="","?",VLOOKUP(K$1,INDIRECT("'"&$A29&"'!$A$12:$Z$41"),MATCH("Points (Auto-generate)",INDIRECT("'"&$A29&"'!$A$12:$Z$12"),0),0)),"ER")) -> ? | L29: =IF($H29=0,"NA",IF($A29=INDIRECT("'"&$A29&"'!$B$1"),IF(VLOOKUP(L$1,INDIRECT("'"&$A29&"'!$A$12:$Z$41"),MATCH("Points (Auto-generate)",INDIRECT("'"&$A29&"'!$A$12:$Z$12"),0),0)="","?",VLOOKUP(L$1,INDIRECT("'"&$A29&"'!$A$12:$Z$41"),MATCH("Points (Auto-generate)",INDIRECT("'"&$A29&"'!$A$12:$Z$12"),0),0)),"ER")) -> ? | M29: =IF($H29=0,"NA",IF($A29=INDIRECT("'"&$A29&"'!$B$1"),IF(VLOOKUP(M$1,INDIRECT("'"&$A29&"'!$A$12:$Z$41"),MATCH("Points (Auto-generate)",INDIRECT("'"&$A29&"'!$A$12:$Z$12"),0),0)="","?",VLOOKUP(M$1,INDIRECT("'"&$A29&"'!$A$12:$Z$41"),MATCH("Points (Auto-generate)",INDIRECT("'"&$A29&"'!$A$12:$Z$12"),0),0)),"ER")) -> ? | N29: =IF($H29=0,"NA",IF($A29=INDIRECT("'"&$A29&"'!$B$1"),IF(VLOOKUP(N$1,INDIRECT("'"&$A29&"'!$A$12:$Z$41"),MATCH("Points (Auto-generate)",INDIRECT("'"&$A29&"'!$A$12:$Z$12"),0),0)="","?",VLOOKUP(N$1,INDIRECT("'"&$A29&"'!$A$12:$Z$41"),MATCH("Points (Auto-generate)",INDIRECT("'"&$A29&"'!$A$12:$Z$12"),0),0)),"ER")) -> ? | O29: =IF($H29=0,"NA",IF($A29=INDIRECT("'"&$A29&"'!$B$1"),IF(VLOOKUP(O$1,INDIRECT("'"&$A29&"'!$A$12:$Z$41"),MATCH("Points (Auto-generate)",INDIRECT("'"&$A29&"'!$A$12:$Z$12"),0),0)="","?",VLOOKUP(O$1,INDIRECT("'"&$A29&"'!$A$12:$Z$41"),MATCH("Points (Auto-generate)",INDIRECT("'"&$A29&"'!$A$12:$Z$12"),0),0)),"ER")) -> ? | P29: =IF($H29=0,"NA",IF($A29=INDIRECT("'"&$A29&"'!$B$1"),IF(VLOOKUP(P$1,INDIRECT("'"&$A29&"'!$A$12:$Z$41"),MATCH("Points (Auto-generate)",INDIRECT("'"&$A29&"'!$A$12:$Z$12"),0),0)="","?",VLOOKUP(P$1,INDIRECT("'"&$A29&"'!$A$12:$Z$41"),MATCH("Points (Auto-generate)",INDIRECT("'"&$A29&"'!$A$12:$Z$12"),0),0)),"ER")) -> ? | ... AK29: =IF($H29=0,"NA",IF($A29=INDIRECT("'"&$A29&"'!$B$1"),IF(VLOOKUP(AK$1,INDIRECT("'"&$A29&"'!$A$12:$Z$41"),MATCH("Points (Auto-generate)",INDIRECT("'"&$A29&"'!$A$12:$Z$12"),0),0)="","?",VLOOKUP(AK$1,INDIRECT("'"&$A29&"'!$A$12:$Z$41"),MATCH("Points (Auto-generate)",INDIRECT("'"&$A29&"'!$A$12:$Z$12"),0),0)),"ER")) -> ?
A30: UPD13e | B30: =IF(ISBLANK($A30),"NO_CODE",VLOOKUP($A30,'UPD Questions_290926 '!$E$1:$N$300,MATCH(B$1,'UPD Questions_290926 '!$E$1:$N$1,0),0)&"") -> Planning | C30: =IF(ISBLANK($A30),"NO_CODE",VLOOKUP($A30,'UPD Questions_290926 '!$E$1:$N$300,MATCH(C$1,'UPD Questions_290926 '!$E$1:$N$1,0),0)&"") -> Municipal/City Plan objectives and contents | D30: =IF(ISBLANK($A30),"NO_CODE",VLOOKUP($A30,'UPD Questions_290926 '!$E$1:$N$300,MATCH(D$1,'UPD Questions_290926 '!$E$1:$N$1,0),0)&"") -> Statutory requirements for plan content | E30: =IF(ISBLANK($A30),"NO_CODE",VLOOKUP($A30,'UPD Questions_290926 '!$E$1:$N$300,MATCH(E$1,'UPD Questions_290926 '!$E$1:$N$1,0),0)&"") -> SQ | F30: =IF(ISBLANK($A30),"NO_CODE",VLOOKUP($A30,'UPD Questions_290926 '!$E$1:$N$300,MATCH(F$1,'UPD Questions_290926 '!$E$1:$N$1,0),0)&"") -> e) Heritage conservation | G30: =IF(ISBLANK($A30),"NO_CODE",VLOOKUP($A30,'UPD Questions_290926 '!$E$1:$N$300,MATCH(G$1,'UPD Questions_290926 '!$E$1:$N$1,0),0)&"") -> Law/Policy | H30: =IF(ISBLANK($A30),"NO_CODE",VLOOKUP($A30,'UPD Questions_290926 '!$E$1:$N$300,MATCH(H$1,'UPD Questions_290926 '!$E$1:$N$1,0),0)) -> 1.67 | I30: =IF($H30=0,"NA",IF($A30=INDIRECT("'"&$A30&"'!$B$1"),IF(VLOOKUP(I$1,INDIRECT("'"&$A30&"'!$A$12:$Z$41"),MATCH("Points (Auto-generate)",INDIRECT("'"&$A30&"'!$A$12:$Z$12"),0),0)="","?",VLOOKUP(I$1,INDIRECT("'"&$A30&"'!$A$12:$Z$41"),MATCH("Points (Auto-generate)",INDIRECT("'"&$A30&"'!$A$12:$Z$12"),0),0)),"ER")) -> ? | J30: =IF($H30=0,"NA",IF($A30=INDIRECT("'"&$A30&"'!$B$1"),IF(VLOOKUP(J$1,INDIRECT("'"&$A30&"'!$A$12:$Z$41"),MATCH("Points (Auto-generate)",INDIRECT("'"&$A30&"'!$A$12:$Z$12"),0),0)="","?",VLOOKUP(J$1,INDIRECT("'"&$A30&"'!$A$12:$Z$41"),MATCH("Points (Auto-generate)",INDIRECT("'"&$A30&"'!$A$12:$Z$12"),0),0)),"ER")) -> ? | K30: =IF($H30=0,"NA",IF($A30=INDIRECT("'"&$A30&"'!$B$1"),IF(VLOOKUP(K$1,INDIRECT("'"&$A30&"'!$A$12:$Z$41"),MATCH("Points (Auto-generate)",INDIRECT("'"&$A30&"'!$A$12:$Z$12"),0),0)="","?",VLOOKUP(K$1,INDIRECT("'"&$A30&"'!$A$12:$Z$41"),MATCH("Points (Auto-generate)",INDIRECT("'"&$A30&"'!$A$12:$Z$12"),0),0)),"ER")) -> ? | L30: =IF($H30=0,"NA",IF($A30=INDIRECT("'"&$A30&"'!$B$1"),IF(VLOOKUP(L$1,INDIRECT("'"&$A30&"'!$A$12:$Z$41"),MATCH("Points (Auto-generate)",INDIRECT("'"&$A30&"'!$A$12:$Z$12"),0),0)="","?",VLOOKUP(L$1,INDIRECT("'"&$A30&"'!$A$12:$Z$41"),MATCH("Points (Auto-generate)",INDIRECT("'"&$A30&"'!$A$12:$Z$12"),0),0)),"ER")) -> ? | M30: =IF($H30=0,"NA",IF($A30=INDIRECT("'"&$A30&"'!$B$1"),IF(VLOOKUP(M$1,INDIRECT("'"&$A30&"'!$A$12:$Z$41"),MATCH("Points (Auto-generate)",INDIRECT("'"&$A30&"'!$A$12:$Z$12"),0),0)="","?",VLOOKUP(M$1,INDIRECT("'"&$A30&"'!$A$12:$Z$41"),MATCH("Points (Auto-generate)",INDIRECT("'"&$A30&"'!$A$12:$Z$12"),0),0)),"ER")) -> ? | N30: =IF($H30=0,"NA",IF($A30=INDIRECT("'"&$A30&"'!$B$1"),IF(VLOOKUP(N$1,INDIRECT("'"&$A30&"'!$A$12:$Z$41"),MATCH("Points (Auto-generate)",INDIRECT("'"&$A30&"'!$A$12:$Z$12"),0),0)="","?",VLOOKUP(N$1,INDIRECT("'"&$A30&"'!$A$12:$Z$41"),MATCH("Points (Auto-generate)",INDIRECT("'"&$A30&"'!$A$12:$Z$12"),0),0)),"ER")) -> ? | O30: =IF($H30=0,"NA",IF($A30=INDIRECT("'"&$A30&"'!$B$1"),IF(VLOOKUP(O$1,INDIRECT("'"&$A30&"'!$A$12:$Z$41"),MATCH("Points (Auto-generate)",INDIRECT("'"&$A30&"'!$A$12:$Z$12"),0),0)="","?",VLOOKUP(O$1,INDIRECT("'"&$A30&"'!$A$12:$Z$41"),MATCH("Points (Auto-generate)",INDIRECT("'"&$A30&"'!$A$12:$Z$12"),0),0)),"ER")) -> ? | P30: =IF($H30=0,"NA",IF($A30=INDIRECT("'"&$A30&"'!$B$1"),IF(VLOOKUP(P$1,INDIRECT("'"&$A30&"'!$A$12:$Z$41"),MATCH("Points (Auto-generate)",INDIRECT("'"&$A30&"'!$A$12:$Z$12"),0),0)="","?",VLOOKUP(P$1,INDIRECT("'"&$A30&"'!$A$12:$Z$41"),MATCH("Points (Auto-generate)",INDIRECT("'"&$A30&"'!$A$12:$Z$12"),0),0)),"ER")) -> ? | ... AK30: =IF($H30=0,"NA",IF($A30=INDIRECT("'"&$A30&"'!$B$1"),IF(VLOOKUP(AK$1,INDIRECT("'"&$A30&"'!$A$12:$Z$41"),MATCH("Points (Auto-generate)",INDIRECT("'"&$A30&"'!$A$12:$Z$12"),0),0)="","?",VLOOKUP(AK$1,INDIRECT("'"&$A30&"'!$A$12:$Z$41"),MATCH("Points (Auto-generate)",INDIRECT("'"&$A30&"'!$A$12:$Z$12"),0),0)),"ER")) -> ?
A31: UPD13f | B31: =IF(ISBLANK($A31),"NO_CODE",VLOOKUP($A31,'UPD Questions_290926 '!$E$1:$N$300,MATCH(B$1,'UPD Questions_290926 '!$E$1:$N$1,0),0)&"") -> Planning | C31: =IF(ISBLANK($A31),"NO_CODE",VLOOKUP($A31,'UPD Questions_290926 '!$E$1:$N$300,MATCH(C$1,'UPD Questions_290926 '!$E$1:$N$1,0),0)&"") -> Municipal/City Plan objectives and contents | D31: =IF(ISBLANK($A31),"NO_CODE",VLOOKUP($A31,'UPD Questions_290926 '!$E$1:$N$300,MATCH(D$1,'UPD Questions_290926 '!$E$1:$N$1,0),0)&"") -> Statutory requirements for plan content | E31: =IF(ISBLANK($A31),"NO_CODE",VLOOKUP($A31,'UPD Questions_290926 '!$E$1:$N$300,MATCH(E$1,'UPD Questions_290926 '!$E$1:$N$1,0),0)&"") -> SQ | F31: =IF(ISBLANK($A31),"NO_CODE",VLOOKUP($A31,'UPD Questions_290926 '!$E$1:$N$300,MATCH(F$1,'UPD Questions_290926 '!$E$1:$N$1,0),0)&"") -> f) Social Development | G31: =IF(ISBLANK($A31),"NO_CODE",VLOOKUP($A31,'UPD Questions_290926 '!$E$1:$N$300,MATCH(G$1,'UPD Questions_290926 '!$E$1:$N$1,0),0)&"") -> Law/Policy | H31: =IF(ISBLANK($A31),"NO_CODE",VLOOKUP($A31,'UPD Questions_290926 '!$E$1:$N$300,MATCH(H$1,'UPD Questions_290926 '!$E$1:$N$1,0),0)) -> 1.67 | I31: =IF($H31=0,"NA",IF($A31=INDIRECT("'"&$A31&"'!$B$1"),IF(VLOOKUP(I$1,INDIRECT("'"&$A31&"'!$A$12:$Z$41"),MATCH("Points (Auto-generate)",INDIRECT("'"&$A31&"'!$A$12:$Z$12"),0),0)="","?",VLOOKUP(I$1,INDIRECT("'"&$A31&"'!$A$12:$Z$41"),MATCH("Points (Auto-generate)",INDIRECT("'"&$A31&"'!$A$12:$Z$12"),0),0)),"ER")) -> ? | J31: =IF($H31=0,"NA",IF($A31=INDIRECT("'"&$A31&"'!$B$1"),IF(VLOOKUP(J$1,INDIRECT("'"&$A31&"'!$A$12:$Z$41"),MATCH("Points (Auto-generate)",INDIRECT("'"&$A31&"'!$A$12:$Z$12"),0),0)="","?",VLOOKUP(J$1,INDIRECT("'"&$A31&"'!$A$12:$Z$41"),MATCH("Points (Auto-generate)",INDIRECT("'"&$A31&"'!$A$12:$Z$12"),0),0)),"ER")) -> ? | K31: =IF($H31=0,"NA",IF($A31=INDIRECT("'"&$A31&"'!$B$1"),IF(VLOOKUP(K$1,INDIRECT("'"&$A31&"'!$A$12:$Z$41"),MATCH("Points (Auto-generate)",INDIRECT("'"&$A31&"'!$A$12:$Z$12"),0),0)="","?",VLOOKUP(K$1,INDIRECT("'"&$A31&"'!$A$12:$Z$41"),MATCH("Points (Auto-generate)",INDIRECT("'"&$A31&"'!$A$12:$Z$12"),0),0)),"ER")) -> ? | L31: =IF($H31=0,"NA",IF($A31=INDIRECT("'"&$A31&"'!$B$1"),IF(VLOOKUP(L$1,INDIRECT("'"&$A31&"'!$A$12:$Z$41"),MATCH("Points (Auto-generate)",INDIRECT("'"&$A31&"'!$A$12:$Z$12"),0),0)="","?",VLOOKUP(L$1,INDIRECT("'"&$A31&"'!$A$12:$Z$41"),MATCH("Points (Auto-generate)",INDIRECT("'"&$A31&"'!$A$12:$Z$12"),0),0)),"ER")) -> ? | M31: =IF($H31=0,"NA",IF($A31=INDIRECT("'"&$A31&"'!$B$1"),IF(VLOOKUP(M$1,INDIRECT("'"&$A31&"'!$A$12:$Z$41"),MATCH("Points (Auto-generate)",INDIRECT("'"&$A31&"'!$A$12:$Z$12"),0),0)="","?",VLOOKUP(M$1,INDIRECT("'"&$A31&"'!$A$12:$Z$41"),MATCH("Points (Auto-generate)",INDIRECT("'"&$A31&"'!$A$12:$Z$12"),0),0)),"ER")) -> ? | N31: =IF($H31=0,"NA",IF($A31=INDIRECT("'"&$A31&"'!$B$1"),IF(VLOOKUP(N$1,INDIRECT("'"&$A31&"'!$A$12:$Z$41"),MATCH("Points (Auto-generate)",INDIRECT("'"&$A31&"'!$A$12:$Z$12"),0),0)="","?",VLOOKUP(N$1,INDIRECT("'"&$A31&"'!$A$12:$Z$41"),MATCH("Points (Auto-generate)",INDIRECT("'"&$A31&"'!$A$12:$Z$12"),0),0)),"ER")) -> ? | O31: =IF($H31=0,"NA",IF($A31=INDIRECT("'"&$A31&"'!$B$1"),IF(VLOOKUP(O$1,INDIRECT("'"&$A31&"'!$A$12:$Z$41"),MATCH("Points (Auto-generate)",INDIRECT("'"&$A31&"'!$A$12:$Z$12"),0),0)="","?",VLOOKUP(O$1,INDIRECT("'"&$A31&"'!$A$12:$Z$41"),MATCH("Points (Auto-generate)",INDIRECT("'"&$A31&"'!$A$12:$Z$12"),0),0)),"ER")) -> ? | P31: =IF($H31=0,"NA",IF($A31=INDIRECT("'"&$A31&"'!$B$1"),IF(VLOOKUP(P$1,INDIRECT("'"&$A31&"'!$A$12:$Z$41"),MATCH("Points (Auto-generate)",INDIRECT("'"&$A31&"'!$A$12:$Z$12"),0),0)="","?",VLOOKUP(P$1,INDIRECT("'"&$A31&"'!$A$12:$Z$41"),MATCH("Points (Auto-generate)",INDIRECT("'"&$A31&"'!$A$12:$Z$12"),0),0)),"ER")) -> ? | ... AK31: =IF($H31=0,"NA",IF($A31=INDIRECT("'"&$A31&"'!$B$1"),IF(VLOOKUP(AK$1,INDIRECT("'"&$A31&"'!$A$12:$Z$41"),MATCH("Points (Auto-generate)",INDIRECT("'"&$A31&"'!$A$12:$Z$12"),0),0)="","?",VLOOKUP(AK$1,INDIRECT("'"&$A31&"'!$A$12:$Z$41"),MATCH("Points (Auto-generate)",INDIRECT("'"&$A31&"'!$A$12:$Z$12"),0),0)),"ER")) -> ?
A32: UPD14 | B32: =IF(ISBLANK($A32),"NO_CODE",VLOOKUP($A32,'UPD Questions_290926 '!$E$1:$N$300,MATCH(B$1,'UPD Questions_290926 '!$E$1:$N$1,0),0)&"") -> Implementation | C32: =IF(ISBLANK($A32),"NO_CODE",VLOOKUP($A32,'UPD Questions_290926 '!$E$1:$N$300,MATCH(C$1,'UPD Questions_290926 '!$E$1:$N$1,0),0)&"") -> Municipal/City Plan status, hierarchy and coordination | D32: =IF(ISBLANK($A32),"NO_CODE",VLOOKUP($A32,'UPD Questions_290926 '!$E$1:$N$300,MATCH(D$1,'UPD Questions_290926 '!$E$1:$N$1,0),0)&"") -> Existence of Municipal/City Plans at each level | E32: =IF(ISBLANK($A32),"NO_CODE",VLOOKUP($A32,'UPD Questions_290926 '!$E$1:$N$300,MATCH(E$1,'UPD Questions_290926 '!$E$1:$N$1,0),0)&"") -> MQ | F32: =IF(ISBLANK($A32),"NO_CODE",VLOOKUP($A32,'UPD Questions_290926 '!$E$1:$N$300,MATCH(F$1,'UPD Questions_290926 '!$E$1:$N$1,0),0)&"") -> Are the spatial plans at the Metropolitan/Regional, Municipal and Ward(s) /Local level notified? | G32: =IF(ISBLANK($A32),"NO_CODE",VLOOKUP($A32,'UPD Questions_290926 '!$E$1:$N$300,MATCH(G$1,'UPD Questions_290926 '!$E$1:$N$1,0),0)&"") -> Implementation | H32: =IF(ISBLANK($A32),"NO_CODE",VLOOKUP($A32,'UPD Questions_290926 '!$E$1:$N$300,MATCH(H$1,'UPD Questions_290926 '!$E$1:$N$1,0),0)) -> 10 | I32: =IF(OR(I33="ER",I34="ER",I35="ER"),"ER",IF(OR(I33="?",I34="?",I35="?"),"?",IF(AND(I33="NA",I34="NA",I35="NA"),"NA",SUM(I33,I34,I35)/((I33<>"NA")*$H$33+(I34<>"NA")*$H$34+(I35<>"NA")*$H$35)*$H32))) -> ? | J32: =IF(OR(J33="ER",J34="ER",J35="ER"),"ER",IF(OR(J33="?",J34="?",J35="?"),"?",IF(AND(J33="NA",J34="NA",J35="NA"),"NA",SUM(J33,J34,J35)/((J33<>"NA")*$H$33+(J34<>"NA")*$H$34+(J35<>"NA")*$H$35)*$H32))) -> ? | K32: =IF(OR(K33="ER",K34="ER",K35="ER"),"ER",IF(OR(K33="?",K34="?",K35="?"),"?",IF(AND(K33="NA",K34="NA",K35="NA"),"NA",SUM(K33,K34,K35)/((K33<>"NA")*$H$33+(K34<>"NA")*$H$34+(K35<>"NA")*$H$35)*$H32))) -> ? | L32: =IF(OR(L33="ER",L34="ER",L35="ER"),"ER",IF(OR(L33="?",L34="?",L35="?"),"?",IF(AND(L33="NA",L34="NA",L35="NA"),"NA",SUM(L33,L34,L35)/((L33<>"NA")*$H$33+(L34<>"NA")*$H$34+(L35<>"NA")*$H$35)*$H32))) -> ? | M32: =IF(OR(M33="ER",M34="ER",M35="ER"),"ER",IF(OR(M33="?",M34="?",M35="?"),"?",IF(AND(M33="NA",M34="NA",M35="NA"),"NA",SUM(M33,M34,M35)/((M33<>"NA")*$H$33+(M34<>"NA")*$H$34+(M35<>"NA")*$H$35)*$H32))) -> ? | N32: =IF(OR(N33="ER",N34="ER",N35="ER"),"ER",IF(OR(N33="?",N34="?",N35="?"),"?",IF(AND(N33="NA",N34="NA",N35="NA"),"NA",SUM(N33,N34,N35)/((N33<>"NA")*$H$33+(N34<>"NA")*$H$34+(N35<>"NA")*$H$35)*$H32))) -> ? | O32: =IF(OR(O33="ER",O34="ER",O35="ER"),"ER",IF(OR(O33="?",O34="?",O35="?"),"?",IF(AND(O33="NA",O34="NA",O35="NA"),"NA",SUM(O33,O34,O35)/((O33<>"NA")*$H$33+(O34<>"NA")*$H$34+(O35<>"NA")*$H$35)*$H32))) -> ? | P32: =IF(OR(P33="ER",P34="ER",P35="ER"),"ER",IF(OR(P33="?",P34="?",P35="?"),"?",IF(AND(P33="NA",P34="NA",P35="NA"),"NA",SUM(P33,P34,P35)/((P33<>"NA")*$H$33+(P34<>"NA")*$H$34+(P35<>"NA")*$H$35)*$H32))) -> ? | ... AK32: =IF(OR(AK33="ER",AK34="ER",AK35="ER"),"ER",IF(OR(AK33="?",AK34="?",AK35="?"),"?",IF(AND(AK33="NA",AK34="NA",AK35="NA"),"NA",SUM(AK33,AK34,AK35)/((AK33<>"NA")*$H$33+(AK34<>"NA")*$H$34+(AK35<>"NA")*$H$35)*$H32))) -> ?
A33: UPD14a | B33: =IF(ISBLANK($A33),"NO_CODE",VLOOKUP($A33,'UPD Questions_290926 '!$E$1:$N$300,MATCH(B$1,'UPD Questions_290926 '!$E$1:$N$1,0),0)&"") -> Implementation | C33: =IF(ISBLANK($A33),"NO_CODE",VLOOKUP($A33,'UPD Questions_290926 '!$E$1:$N$300,MATCH(C$1,'UPD Questions_290926 '!$E$1:$N$1,0),0)&"") -> Municipal/City Plan status, hierarchy and coordination | D33: =IF(ISBLANK($A33),"NO_CODE",VLOOKUP($A33,'UPD Questions_290926 '!$E$1:$N$300,MATCH(D$1,'UPD Questions_290926 '!$E$1:$N$1,0),0)&"") -> Existence of Municipal/City Plans at each level | E33: =IF(ISBLANK($A33),"NO_CODE",VLOOKUP($A33,'UPD Questions_290926 '!$E$1:$N$300,MATCH(E$1,'UPD Questions_290926 '!$E$1:$N$1,0),0)&"") -> SQ | F33: =IF(ISBLANK($A33),"NO_CODE",VLOOKUP($A33,'UPD Questions_290926 '!$E$1:$N$300,MATCH(F$1,'UPD Questions_290926 '!$E$1:$N$1,0),0)&"") -> Is there a Metropolitan/Regional Plan? | G33: =IF(ISBLANK($A33),"NO_CODE",VLOOKUP($A33,'UPD Questions_290926 '!$E$1:$N$300,MATCH(G$1,'UPD Questions_290926 '!$E$1:$N$1,0),0)&"") -> Implementation | H33: =IF(ISBLANK($A33),"NO_CODE",VLOOKUP($A33,'UPD Questions_290926 '!$E$1:$N$300,MATCH(H$1,'UPD Questions_290926 '!$E$1:$N$1,0),0)) -> 3.33 | I33: =IF($H33=0,"NA",IF($A33=INDIRECT("'"&$A33&"'!$B$1"),IF(VLOOKUP(I$1,INDIRECT("'"&$A33&"'!$A$12:$Z$41"),MATCH("Points (Auto-generate)",INDIRECT("'"&$A33&"'!$A$12:$Z$12"),0),0)="","?",VLOOKUP(I$1,INDIRECT("'"&$A33&"'!$A$12:$Z$41"),MATCH("Points (Auto-generate)",INDIRECT("'"&$A33&"'!$A$12:$Z$12"),0),0)),"ER")) -> ? | J33: =IF($H33=0,"NA",IF($A33=INDIRECT("'"&$A33&"'!$B$1"),IF(VLOOKUP(J$1,INDIRECT("'"&$A33&"'!$A$12:$Z$41"),MATCH("Points (Auto-generate)",INDIRECT("'"&$A33&"'!$A$12:$Z$12"),0),0)="","?",VLOOKUP(J$1,INDIRECT("'"&$A33&"'!$A$12:$Z$41"),MATCH("Points (Auto-generate)",INDIRECT("'"&$A33&"'!$A$12:$Z$12"),0),0)),"ER")) -> ? | K33: =IF($H33=0,"NA",IF($A33=INDIRECT("'"&$A33&"'!$B$1"),IF(VLOOKUP(K$1,INDIRECT("'"&$A33&"'!$A$12:$Z$41"),MATCH("Points (Auto-generate)",INDIRECT("'"&$A33&"'!$A$12:$Z$12"),0),0)="","?",VLOOKUP(K$1,INDIRECT("'"&$A33&"'!$A$12:$Z$41"),MATCH("Points (Auto-generate)",INDIRECT("'"&$A33&"'!$A$12:$Z$12"),0),0)),"ER")) -> ? | L33: =IF($H33=0,"NA",IF($A33=INDIRECT("'"&$A33&"'!$B$1"),IF(VLOOKUP(L$1,INDIRECT("'"&$A33&"'!$A$12:$Z$41"),MATCH("Points (Auto-generate)",INDIRECT("'"&$A33&"'!$A$12:$Z$12"),0),0)="","?",VLOOKUP(L$1,INDIRECT("'"&$A33&"'!$A$12:$Z$41"),MATCH("Points (Auto-generate)",INDIRECT("'"&$A33&"'!$A$12:$Z$12"),0),0)),"ER")) -> ? | M33: =IF($H33=0,"NA",IF($A33=INDIRECT("'"&$A33&"'!$B$1"),IF(VLOOKUP(M$1,INDIRECT("'"&$A33&"'!$A$12:$Z$41"),MATCH("Points (Auto-generate)",INDIRECT("'"&$A33&"'!$A$12:$Z$12"),0),0)="","?",VLOOKUP(M$1,INDIRECT("'"&$A33&"'!$A$12:$Z$41"),MATCH("Points (Auto-generate)",INDIRECT("'"&$A33&"'!$A$12:$Z$12"),0),0)),"ER")) -> ? | N33: =IF($H33=0,"NA",IF($A33=INDIRECT("'"&$A33&"'!$B$1"),IF(VLOOKUP(N$1,INDIRECT("'"&$A33&"'!$A$12:$Z$41"),MATCH("Points (Auto-generate)",INDIRECT("'"&$A33&"'!$A$12:$Z$12"),0),0)="","?",VLOOKUP(N$1,INDIRECT("'"&$A33&"'!$A$12:$Z$41"),MATCH("Points (Auto-generate)",INDIRECT("'"&$A33&"'!$A$12:$Z$12"),0),0)),"ER")) -> ? | O33: =IF($H33=0,"NA",IF($A33=INDIRECT("'"&$A33&"'!$B$1"),IF(VLOOKUP(O$1,INDIRECT("'"&$A33&"'!$A$12:$Z$41"),MATCH("Points (Auto-generate)",INDIRECT("'"&$A33&"'!$A$12:$Z$12"),0),0)="","?",VLOOKUP(O$1,INDIRECT("'"&$A33&"'!$A$12:$Z$41"),MATCH("Points (Auto-generate)",INDIRECT("'"&$A33&"'!$A$12:$Z$12"),0),0)),"ER")) -> ? | P33: =IF($H33=0,"NA",IF($A33=INDIRECT("'"&$A33&"'!$B$1"),IF(VLOOKUP(P$1,INDIRECT("'"&$A33&"'!$A$12:$Z$41"),MATCH("Points (Auto-generate)",INDIRECT("'"&$A33&"'!$A$12:$Z$12"),0),0)="","?",VLOOKUP(P$1,INDIRECT("'"&$A33&"'!$A$12:$Z$41"),MATCH("Points (Auto-generate)",INDIRECT("'"&$A33&"'!$A$12:$Z$12"),0),0)),"ER")) -> ? | ... AK33: =IF($H33=0,"NA",IF($A33=INDIRECT("'"&$A33&"'!$B$1"),IF(VLOOKUP(AK$1,INDIRECT("'"&$A33&"'!$A$12:$Z$41"),MATCH("Points (Auto-generate)",INDIRECT("'"&$A33&"'!$A$12:$Z$12"),0),0)="","?",VLOOKUP(AK$1,INDIRECT("'"&$A33&"'!$A$12:$Z$41"),MATCH("Points (Auto-generate)",INDIRECT("'"&$A33&"'!$A$12:$Z$12"),0),0)),"ER")) -> ?
