Workbook

Sheet Check before use
A1: DRAFT PARASTATAL scoring workbook - generated from the methodology sheet
A3: This draft follows the same layout as the UPD scoring workbook, so the app can fill, merge and read it. The scoring experts should:
A4: 1. Replace each question sheet's simple inputs (yellow) and Points formula with the real ones, keeping the row-11 instructions (e.g. SELECT YES / NO) and the column names 'Points (Auto-generate)' and 'SCORER COMMENTS'.
A5: 2. Check 'Applies?' (filled in from each agency's type and the question's Applicability). To change it, fix the agency in the city register or Sources workbook and generate again.
A6: 3. Fix the points below in the methodology sheet and generate again.
A8: Points to check:
A9: • Section 'Decentralised Participatory Governance' has no (CODE); using DPG
A10: • Section 'State Capacities' has no (CODE); using SC
A11: • Question Bank row 57: the ID "SC-5" is used twice. Each question needs its own ID; the second one was skipped.
A12: • UPD 1a: the methodology gives scores up to 10, but the Max Score is 5. Say how the score should be scaled.
A13: • DPG 4 has no Tag or Max Score, so it is left out of the scores. Add them if it should be scored.

Sheet PARASTATAL_SUMMARY_RAW
A1: ASICS 2027_Report_Q No | B1: Group | C1: MQ_SQ | D1: Question | E1: Assessment level | F1: Max Score | G1: Bengaluru – BWSSB | H1: Bengaluru – BMTC | I1: Bengaluru – BDA | J1: Bengaluru – BMRCL | K1: Bengaluru – BMRDA | L1: Surat – SUDA | M1: Surat – GMRC
A2: ENTER | B2: Derived | C2: Derived | D2: Derived | E2: Derived | F2: Derived | G2: Derived | H2: Derived | I2: Derived | J2: Derived | K2: Derived | L2: Derived | M2: Derived
A3: UPD1 | B3: =VLOOKUP($A3,'PARASTATAL Questions'!$A:$J,3,0)&"" -> Urban Planning & Design (UPD) | C3: =VLOOKUP($A3,'PARASTATAL Questions'!$A:$J,4,0)&"" -> MQ | D3: =VLOOKUP($A3,'PARASTATAL Questions'!$A:$J,5,0)&"" -> Does the parastatal coordinate with the ULG(s) in preparing its sectoral plans? | E3: =VLOOKUP($A3,'PARASTATAL Questions'!$A:$J,7,0)&"" -> Law/Policy + Implementation | F3: =VLOOKUP($A3,'PARASTATAL Questions'!$A:$J,6,0) -> 10 | G3: =IF(OR(G4="ER",G5="ER"),"ER",IF(OR(G4="?",G5="?"),"?",IF(AND(G4="NA",G5="NA"),"NA",SUM(G4,G5)/((G4<>"NA")*$F$4+(G5<>"NA")*$F$5)*$F3))) -> 5 | H3: =IF(OR(H4="ER",H5="ER"),"ER",IF(OR(H4="?",H5="?"),"?",IF(AND(H4="NA",H5="NA"),"NA",SUM(H4,H5)/((H4<>"NA")*$F$4+(H5<>"NA")*$F$5)*$F3))) -> ? | I3: =IF(OR(I4="ER",I5="ER"),"ER",IF(OR(I4="?",I5="?"),"?",IF(AND(I4="NA",I5="NA"),"NA",SUM(I4,I5)/((I4<>"NA")*$F$4+(I5<>"NA")*$F$5)*$F3))) -> NA | J3: =IF(OR(J4="ER",J5="ER"),"ER",IF(OR(J4="?",J5="?"),"?",IF(AND(J4="NA",J5="NA"),"NA",SUM(J4,J5)/((J4<>"NA")*$F$4+(J5<>"NA")*$F$5)*$F3))) -> ? | K3: =IF(OR(K4="ER",K5="ER"),"ER",IF(OR(K4="?",K5="?"),"?",IF(AND(K4="NA",K5="NA"),"NA",SUM(K4,K5)/((K4<>"NA")*$F$4+(K5<>"NA")*$F$5)*$F3))) -> NA | L3: =IF(OR(L4="ER",L5="ER"),"ER",IF(OR(L4="?",L5="?"),"?",IF(AND(L4="NA",L5="NA"),"NA",SUM(L4,L5)/((L4<>"NA")*$F$4+(L5<>"NA")*$F$5)*$F3))) -> NA | M3: =IF(OR(M4="ER",M5="ER"),"ER",IF(OR(M4="?",M5="?"),"?",IF(AND(M4="NA",M5="NA"),"NA",SUM(M4,M5)/((M4<>"NA")*$F$4+(M5<>"NA")*$F$5)*$F3))) -> ?
A4: UPD1a | B4: =VLOOKUP($A4,'PARASTATAL Questions'!$A:$J,3,0)&"" -> Urban Planning & Design (UPD) | C4: =VLOOKUP($A4,'PARASTATAL Questions'!$A:$J,4,0)&"" -> SQ | D4: =VLOOKUP($A4,'PARASTATAL Questions'!$A:$J,5,0)&"" -> Is the parastatal mandated to prepare its sectoral plans in coordination with the ULG(s) within its jurisdiction? | E4: =VLOOKUP($A4,'PARASTATAL Questions'!$A:$J,7,0)&"" -> Law/Policy | F4: =VLOOKUP($A4,'PARASTATAL Questions'!$A:$J,6,0) -> 5 | G4: =IF($F4=0,"NA",IF($A4=INDIRECT("'"&$A4&"'!$B$1"),IF(VLOOKUP(G$1,INDIRECT("'"&$A4&"'!$A$12:$Z$19"),MATCH("Points (Auto-generate)",INDIRECT("'"&$A4&"'!$A$12:$Z$12"),0),0)="","?",VLOOKUP(G$1,INDIRECT("'"&$A4&"'!$A$12:$Z$19"),MATCH("Points (Auto-generate)",INDIRECT("'"&$A4&"'!$A$12:$Z$12"),0),0)),"ER")) -> 0 | H4: =IF($F4=0,"NA",IF($A4=INDIRECT("'"&$A4&"'!$B$1"),IF(VLOOKUP(H$1,INDIRECT("'"&$A4&"'!$A$12:$Z$19"),MATCH("Points (Auto-generate)",INDIRECT("'"&$A4&"'!$A$12:$Z$12"),0),0)="","?",VLOOKUP(H$1,INDIRECT("'"&$A4&"'!$A$12:$Z$19"),MATCH("Points (Auto-generate)",INDIRECT("'"&$A4&"'!$A$12:$Z$12"),0),0)),"ER")) -> ? | I4: =IF($F4=0,"NA",IF($A4=INDIRECT("'"&$A4&"'!$B$1"),IF(VLOOKUP(I$1,INDIRECT("'"&$A4&"'!$A$12:$Z$19"),MATCH("Points (Auto-generate)",INDIRECT("'"&$A4&"'!$A$12:$Z$12"),0),0)="","?",VLOOKUP(I$1,INDIRECT("'"&$A4&"'!$A$12:$Z$19"),MATCH("Points (Auto-generate)",INDIRECT("'"&$A4&"'!$A$12:$Z$12"),0),0)),"ER")) -> NA | J4: =IF($F4=0,"NA",IF($A4=INDIRECT("'"&$A4&"'!$B$1"),IF(VLOOKUP(J$1,INDIRECT("'"&$A4&"'!$A$12:$Z$19"),MATCH("Points (Auto-generate)",INDIRECT("'"&$A4&"'!$A$12:$Z$12"),0),0)="","?",VLOOKUP(J$1,INDIRECT("'"&$A4&"'!$A$12:$Z$19"),MATCH("Points (Auto-generate)",INDIRECT("'"&$A4&"'!$A$12:$Z$12"),0),0)),"ER")) -> 0 | K4: =IF($F4=0,"NA",IF($A4=INDIRECT("'"&$A4&"'!$B$1"),IF(VLOOKUP(K$1,INDIRECT("'"&$A4&"'!$A$12:$Z$19"),MATCH("Points (Auto-generate)",INDIRECT("'"&$A4&"'!$A$12:$Z$12"),0),0)="","?",VLOOKUP(K$1,INDIRECT("'"&$A4&"'!$A$12:$Z$19"),MATCH("Points (Auto-generate)",INDIRECT("'"&$A4&"'!$A$12:$Z$12"),0),0)),"ER")) -> NA | L4: =IF($F4=0,"NA",IF($A4=INDIRECT("'"&$A4&"'!$B$1"),IF(VLOOKUP(L$1,INDIRECT("'"&$A4&"'!$A$12:$Z$19"),MATCH("Points (Auto-generate)",INDIRECT("'"&$A4&"'!$A$12:$Z$12"),0),0)="","?",VLOOKUP(L$1,INDIRECT("'"&$A4&"'!$A$12:$Z$19"),MATCH("Points (Auto-generate)",INDIRECT("'"&$A4&"'!$A$12:$Z$12"),0),0)),"ER")) -> NA | M4: =IF($F4=0,"NA",IF($A4=INDIRECT("'"&$A4&"'!$B$1"),IF(VLOOKUP(M$1,INDIRECT("'"&$A4&"'!$A$12:$Z$19"),MATCH("Points (Auto-generate)",INDIRECT("'"&$A4&"'!$A$12:$Z$12"),0),0)="","?",VLOOKUP(M$1,INDIRECT("'"&$A4&"'!$A$12:$Z$19"),MATCH("Points (Auto-generate)",INDIRECT("'"&$A4&"'!$A$12:$Z$12"),0),0)),"ER")) -> ?
A5: UPD1b | B5: =VLOOKUP($A5,'PARASTATAL Questions'!$A:$J,3,0)&"" -> Urban Planning & Design (UPD) | C5: =VLOOKUP($A5,'PARASTATAL Questions'!$A:$J,4,0)&"" -> SQ | D5: =VLOOKUP($A5,'PARASTATAL Questions'!$A:$J,5,0)&"" -> Has the ULG participated in the parastatal’s plan-making process? | E5: =VLOOKUP($A5,'PARASTATAL Questions'!$A:$J,7,0)&"" -> Implementation | F5: =VLOOKUP($A5,'PARASTATAL Questions'!$A:$J,6,0) -> 5 | G5: =IF($F5=0,"NA",IF($A5=INDIRECT("'"&$A5&"'!$B$1"),IF(VLOOKUP(G$1,INDIRECT("'"&$A5&"'!$A$12:$Z$19"),MATCH("Points (Auto-generate)",INDIRECT("'"&$A5&"'!$A$12:$Z$12"),0),0)="","?",VLOOKUP(G$1,INDIRECT("'"&$A5&"'!$A$12:$Z$19"),MATCH("Points (Auto-generate)",INDIRECT("'"&$A5&"'!$A$12:$Z$12"),0),0)),"ER")) -> 5 | H5: =IF($F5=0,"NA",IF($A5=INDIRECT("'"&$A5&"'!$B$1"),IF(VLOOKUP(H$1,INDIRECT("'"&$A5&"'!$A$12:$Z$19"),MATCH("Points (Auto-generate)",INDIRECT("'"&$A5&"'!$A$12:$Z$12"),0),0)="","?",VLOOKUP(H$1,INDIRECT("'"&$A5&"'!$A$12:$Z$19"),MATCH("Points (Auto-generate)",INDIRECT("'"&$A5&"'!$A$12:$Z$12"),0),0)),"ER")) -> ? | I5: =IF($F5=0,"NA",IF($A5=INDIRECT("'"&$A5&"'!$B$1"),IF(VLOOKUP(I$1,INDIRECT("'"&$A5&"'!$A$12:$Z$19"),MATCH("Points (Auto-generate)",INDIRECT("'"&$A5&"'!$A$12:$Z$12"),0),0)="","?",VLOOKUP(I$1,INDIRECT("'"&$A5&"'!$A$12:$Z$19"),MATCH("Points (Auto-generate)",INDIRECT("'"&$A5&"'!$A$12:$Z$12"),0),0)),"ER")) -> NA | J5: =IF($F5=0,"NA",IF($A5=INDIRECT("'"&$A5&"'!$B$1"),IF(VLOOKUP(J$1,INDIRECT("'"&$A5&"'!$A$12:$Z$19"),MATCH("Points (Auto-generate)",INDIRECT("'"&$A5&"'!$A$12:$Z$12"),0),0)="","?",VLOOKUP(J$1,INDIRECT("'"&$A5&"'!$A$12:$Z$19"),MATCH("Points (Auto-generate)",INDIRECT("'"&$A5&"'!$A$12:$Z$12"),0),0)),"ER")) -> ? | K5: =IF($F5=0,"NA",IF($A5=INDIRECT("'"&$A5&"'!$B$1"),IF(VLOOKUP(K$1,INDIRECT("'"&$A5&"'!$A$12:$Z$19"),MATCH("Points (Auto-generate)",INDIRECT("'"&$A5&"'!$A$12:$Z$12"),0),0)="","?",VLOOKUP(K$1,INDIRECT("'"&$A5&"'!$A$12:$Z$19"),MATCH("Points (Auto-generate)",INDIRECT("'"&$A5&"'!$A$12:$Z$12"),0),0)),"ER")) -> NA | L5: =IF($F5=0,"NA",IF($A5=INDIRECT("'"&$A5&"'!$B$1"),IF(VLOOKUP(L$1,INDIRECT("'"&$A5&"'!$A$12:$Z$19"),MATCH("Points (Auto-generate)",INDIRECT("'"&$A5&"'!$A$12:$Z$12"),0),0)="","?",VLOOKUP(L$1,INDIRECT("'"&$A5&"'!$A$12:$Z$19"),MATCH("Points (Auto-generate)",INDIRECT("'"&$A5&"'!$A$12:$Z$12"),0),0)),"ER")) -> NA | M5: =IF($F5=0,"NA",IF($A5=INDIRECT("'"&$A5&"'!$B$1"),IF(VLOOKUP(M$1,INDIRECT("'"&$A5&"'!$A$12:$Z$19"),MATCH("Points (Auto-generate)",INDIRECT("'"&$A5&"'!$A$12:$Z$12"),0),0)="","?",VLOOKUP(M$1,INDIRECT("'"&$A5&"'!$A$12:$Z$19"),MATCH("Points (Auto-generate)",INDIRECT("'"&$A5&"'!$A$12:$Z$12"),0),0)),"ER")) -> ?
A6: UPD2 | B6: =VLOOKUP($A6,'PARASTATAL Questions'!$A:$J,3,0)&"" -> Urban Planning & Design (UPD) | C6: =VLOOKUP($A6,'PARASTATAL Questions'!$A:$J,4,0)&"" -> MQ | D6: =VLOOKUP($A6,'PARASTATAL Questions'!$A:$J,5,0)&"" -> Where multiple statutory or sectoral plans apply to the same territory, does the water supply board and transport corporation ensure consistency with the municipal/city plan for the city? | E6: =VLOOKUP($A6,'PARASTATAL Questions'!$A:$J,7,0)&"" -> Law/Policy + Implementation | F6: =VLOOKUP($A6,'PARASTATAL Questions'!$A:$J,6,0) -> 10 | G6: =IF(OR(G7="ER",G8="ER",G9="ER",G10="ER"),"ER",IF(OR(G7="?",G8="?",G9="?",G10="?"),"?",IF(AND(G7="NA",G8="NA",G9="NA",G10="NA"),"NA",SUM(G7,G8,G9,G10)/((G7<>"NA")*$F$7+(G8<>"NA")*$F$8+(G9<>"NA")*$F$9+(G10<>"NA")*$F$10)*$F6))) -> ? | H6: =IF(OR(H7="ER",H8="ER",H9="ER",H10="ER"),"ER",IF(OR(H7="?",H8="?",H9="?",H10="?"),"?",IF(AND(H7="NA",H8="NA",H9="NA",H10="NA"),"NA",SUM(H7,H8,H9,H10)/((H7<>"NA")*$F$7+(H8<>"NA")*$F$8+(H9<>"NA")*$F$9+(H10<>"NA")*$F$10)*$F6))) -> ? | I6: =IF(OR(I7="ER",I8="ER",I9="ER",I10="ER"),"ER",IF(OR(I7="?",I8="?",I9="?",I10="?"),"?",IF(AND(I7="NA",I8="NA",I9="NA",I10="NA"),"NA",SUM(I7,I8,I9,I10)/((I7<>"NA")*$F$7+(I8<>"NA")*$F$8+(I9<>"NA")*$F$9+(I10<>"NA")*$F$10)*$F6))) -> NA | J6: =IF(OR(J7="ER",J8="ER",J9="ER",J10="ER"),"ER",IF(OR(J7="?",J8="?",J9="?",J10="?"),"?",IF(AND(J7="NA",J8="NA",J9="NA",J10="NA"),"NA",SUM(J7,J8,J9,J10)/((J7<>"NA")*$F$7+(J8<>"NA")*$F$8+(J9<>"NA")*$F$9+(J10<>"NA")*$F$10)*$F6))) -> NA | K6: =IF(OR(K7="ER",K8="ER",K9="ER",K10="ER"),"ER",IF(OR(K7="?",K8="?",K9="?",K10="?"),"?",IF(AND(K7="NA",K8="NA",K9="NA",K10="NA"),"NA",SUM(K7,K8,K9,K10)/((K7<>"NA")*$F$7+(K8<>"NA")*$F$8+(K9<>"NA")*$F$9+(K10<>"NA")*$F$10)*$F6))) -> NA | L6: =IF(OR(L7="ER",L8="ER",L9="ER",L10="ER"),"ER",IF(OR(L7="?",L8="?",L9="?",L10="?"),"?",IF(AND(L7="NA",L8="NA",L9="NA",L10="NA"),"NA",SUM(L7,L8,L9,L10)/((L7<>"NA")*$F$7+(L8<>"NA")*$F$8+(L9<>"NA")*$F$9+(L10<>"NA")*$F$10)*$F6))) -> NA | M6: =IF(OR(M7="ER",M8="ER",M9="ER",M10="ER"),"ER",IF(OR(M7="?",M8="?",M9="?",M10="?"),"?",IF(AND(M7="NA",M8="NA",M9="NA",M10="NA"),"NA",SUM(M7,M8,M9,M10)/((M7<>"NA")*$F$7+(M8<>"NA")*$F$8+(M9<>"NA")*$F$9+(M10<>"NA")*$F$10)*$F6))) -> NA
A7: UPD2a | B7: =VLOOKUP($A7,'PARASTATAL Questions'!$A:$J,3,0)&"" -> Urban Planning & Design (UPD) | C7: =VLOOKUP($A7,'PARASTATAL Questions'!$A:$J,4,0)&"" -> SQ | D7: =VLOOKUP($A7,'PARASTATAL Questions'!$A:$J,5,0)&"" -> Where multiple statutory or sectoral plans apply to the same territory, is the water board mandated to ensure consistency with the applicable city /municipal plan for the city? | E7: =VLOOKUP($A7,'PARASTATAL Questions'!$A:$J,7,0)&"" -> Law/Policy | F7: =VLOOKUP($A7,'PARASTATAL Questions'!$A:$J,6,0) -> 2.5 | G7: =IF($F7=0,"NA",IF($A7=INDIRECT("'"&$A7&"'!$B$1"),IF(VLOOKUP(G$1,INDIRECT("'"&$A7&"'!$A$12:$Z$19"),MATCH("Points (Auto-generate)",INDIRECT("'"&$A7&"'!$A$12:$Z$12"),0),0)="","?",VLOOKUP(G$1,INDIRECT("'"&$A7&"'!$A$12:$Z$19"),MATCH("Points (Auto-generate)",INDIRECT("'"&$A7&"'!$A$12:$Z$12"),0),0)),"ER")) -> ? | H7: =IF($F7=0,"NA",IF($A7=INDIRECT("'"&$A7&"'!$B$1"),IF(VLOOKUP(H$1,INDIRECT("'"&$A7&"'!$A$12:$Z$19"),MATCH("Points (Auto-generate)",INDIRECT("'"&$A7&"'!$A$12:$Z$12"),0),0)="","?",VLOOKUP(H$1,INDIRECT("'"&$A7&"'!$A$12:$Z$19"),MATCH("Points (Auto-generate)",INDIRECT("'"&$A7&"'!$A$12:$Z$12"),0),0)),"ER")) -> NA | I7: =IF($F7=0,"NA",IF($A7=INDIRECT("'"&$A7&"'!$B$1"),IF(VLOOKUP(I$1,INDIRECT("'"&$A7&"'!$A$12:$Z$19"),MATCH("Points (Auto-generate)",INDIRECT("'"&$A7&"'!$A$12:$Z$12"),0),0)="","?",VLOOKUP(I$1,INDIRECT("'"&$A7&"'!$A$12:$Z$19"),MATCH("Points (Auto-generate)",INDIRECT("'"&$A7&"'!$A$12:$Z$12"),0),0)),"ER")) -> NA | J7: =IF($F7=0,"NA",IF($A7=INDIRECT("'"&$A7&"'!$B$1"),IF(VLOOKUP(J$1,INDIRECT("'"&$A7&"'!$A$12:$Z$19"),MATCH("Points (Auto-generate)",INDIRECT("'"&$A7&"'!$A$12:$Z$12"),0),0)="","?",VLOOKUP(J$1,INDIRECT("'"&$A7&"'!$A$12:$Z$19"),MATCH("Points (Auto-generate)",INDIRECT("'"&$A7&"'!$A$12:$Z$12"),0),0)),"ER")) -> NA | K7: =IF($F7=0,"NA",IF($A7=INDIRECT("'"&$A7&"'!$B$1"),IF(VLOOKUP(K$1,INDIRECT("'"&$A7&"'!$A$12:$Z$19"),MATCH("Points (Auto-generate)",INDIRECT("'"&$A7&"'!$A$12:$Z$12"),0),0)="","?",VLOOKUP(K$1,INDIRECT("'"&$A7&"'!$A$12:$Z$19"),MATCH("Points (Auto-generate)",INDIRECT("'"&$A7&"'!$A$12:$Z$12"),0),0)),"ER")) -> NA | L7: =IF($F7=0,"NA",IF($A7=INDIRECT("'"&$A7&"'!$B$1"),IF(VLOOKUP(L$1,INDIRECT("'"&$A7&"'!$A$12:$Z$19"),MATCH("Points (Auto-generate)",INDIRECT("'"&$A7&"'!$A$12:$Z$12"),0),0)="","?",VLOOKUP(L$1,INDIRECT("'"&$A7&"'!$A$12:$Z$19"),MATCH("Points (Auto-generate)",INDIRECT("'"&$A7&"'!$A$12:$Z$12"),0),0)),"ER")) -> NA | M7: =IF($F7=0,"NA",IF($A7=INDIRECT("'"&$A7&"'!$B$1"),IF(VLOOKUP(M$1,INDIRECT("'"&$A7&"'!$A$12:$Z$19"),MATCH("Points (Auto-generate)",INDIRECT("'"&$A7&"'!$A$12:$Z$12"),0),0)="","?",VLOOKUP(M$1,INDIRECT("'"&$A7&"'!$A$12:$Z$19"),MATCH("Points (Auto-generate)",INDIRECT("'"&$A7&"'!$A$12:$Z$12"),0),0)),"ER")) -> NA
A8: UPD2b | B8: =VLOOKUP($A8,'PARASTATAL Questions'!$A:$J,3,0)&"" -> Urban Planning & Design (UPD) | C8: =VLOOKUP($A8,'PARASTATAL Questions'!$A:$J,4,0)&"" -> SQ | D8: =VLOOKUP($A8,'PARASTATAL Questions'!$A:$J,5,0)&"" -> Where multiple statutory or sectoral plans apply to the same territory, does the water supply board ensure consistency with the applicable municipal/city plan for the city? | E8: =VLOOKUP($A8,'PARASTATAL Questions'!$A:$J,7,0)&"" -> Implementation | F8: =VLOOKUP($A8,'PARASTATAL Questions'!$A:$J,6,0) -> 2.5 | G8: =IF($F8=0,"NA",IF($A8=INDIRECT("'"&$A8&"'!$B$1"),IF(VLOOKUP(G$1,INDIRECT("'"&$A8&"'!$A$12:$Z$19"),MATCH("Points (Auto-generate)",INDIRECT("'"&$A8&"'!$A$12:$Z$12"),0),0)="","?",VLOOKUP(G$1,INDIRECT("'"&$A8&"'!$A$12:$Z$19"),MATCH("Points (Auto-generate)",INDIRECT("'"&$A8&"'!$A$12:$Z$12"),0),0)),"ER")) -> ? | H8: =IF($F8=0,"NA",IF($A8=INDIRECT("'"&$A8&"'!$B$1"),IF(VLOOKUP(H$1,INDIRECT("'"&$A8&"'!$A$12:$Z$19"),MATCH("Points (Auto-generate)",INDIRECT("'"&$A8&"'!$A$12:$Z$12"),0),0)="","?",VLOOKUP(H$1,INDIRECT("'"&$A8&"'!$A$12:$Z$19"),MATCH("Points (Auto-generate)",INDIRECT("'"&$A8&"'!$A$12:$Z$12"),0),0)),"ER")) -> NA | I8: =IF($F8=0,"NA",IF($A8=INDIRECT("'"&$A8&"'!$B$1"),IF(VLOOKUP(I$1,INDIRECT("'"&$A8&"'!$A$12:$Z$19"),MATCH("Points (Auto-generate)",INDIRECT("'"&$A8&"'!$A$12:$Z$12"),0),0)="","?",VLOOKUP(I$1,INDIRECT("'"&$A8&"'!$A$12:$Z$19"),MATCH("Points (Auto-generate)",INDIRECT("'"&$A8&"'!$A$12:$Z$12"),0),0)),"ER")) -> NA | J8: =IF($F8=0,"NA",IF($A8=INDIRECT("'"&$A8&"'!$B$1"),IF(VLOOKUP(J$1,INDIRECT("'"&$A8&"'!$A$12:$Z$19"),MATCH("Points (Auto-generate)",INDIRECT("'"&$A8&"'!$A$12:$Z$12"),0),0)="","?",VLOOKUP(J$1,INDIRECT("'"&$A8&"'!$A$12:$Z$19"),MATCH("Points (Auto-generate)",INDIRECT("'"&$A8&"'!$A$12:$Z$12"),0),0)),"ER")) -> NA | K8: =IF($F8=0,"NA",IF($A8=INDIRECT("'"&$A8&"'!$B$1"),IF(VLOOKUP(K$1,INDIRECT("'"&$A8&"'!$A$12:$Z$19"),MATCH("Points (Auto-generate)",INDIRECT("'"&$A8&"'!$A$12:$Z$12"),0),0)="","?",VLOOKUP(K$1,INDIRECT("'"&$A8&"'!$A$12:$Z$19"),MATCH("Points (Auto-generate)",INDIRECT("'"&$A8&"'!$A$12:$Z$12"),0),0)),"ER")) -> NA | L8: =IF($F8=0,"NA",IF($A8=INDIRECT("'"&$A8&"'!$B$1"),IF(VLOOKUP(L$1,INDIRECT("'"&$A8&"'!$A$12:$Z$19"),MATCH("Points (Auto-generate)",INDIRECT("'"&$A8&"'!$A$12:$Z$12"),0),0)="","?",VLOOKUP(L$1,INDIRECT("'"&$A8&"'!$A$12:$Z$19"),MATCH("Points (Auto-generate)",INDIRECT("'"&$A8&"'!$A$12:$Z$12"),0),0)),"ER")) -> NA | M8: =IF($F8=0,"NA",IF($A8=INDIRECT("'"&$A8&"'!$B$1"),IF(VLOOKUP(M$1,INDIRECT("'"&$A8&"'!$A$12:$Z$19"),MATCH("Points (Auto-generate)",INDIRECT("'"&$A8&"'!$A$12:$Z$12"),0),0)="","?",VLOOKUP(M$1,INDIRECT("'"&$A8&"'!$A$12:$Z$19"),MATCH("Points (Auto-generate)",INDIRECT("'"&$A8&"'!$A$12:$Z$12"),0),0)),"ER")) -> NA
A9: UPD2c | B9: =VLOOKUP($A9,'PARASTATAL Questions'!$A:$J,3,0)&"" -> Urban Planning & Design (UPD) | C9: =VLOOKUP($A9,'PARASTATAL Questions'!$A:$J,4,0)&"" -> SQ | D9: =VLOOKUP($A9,'PARASTATAL Questions'!$A:$J,5,0)&"" -> Where multiple statutory or sectoral plans apply to the same territory, is the transport corporation mandated to ensure consistency with the applicable municipal/city plan for the city? | E9: =VLOOKUP($A9,'PARASTATAL Questions'!$A:$J,7,0)&"" -> Law/Policy | F9: =VLOOKUP($A9,'PARASTATAL Questions'!$A:$J,6,0) -> 2.5 | G9: =IF($F9=0,"NA",IF($A9=INDIRECT("'"&$A9&"'!$B$1"),IF(VLOOKUP(G$1,INDIRECT("'"&$A9&"'!$A$12:$Z$19"),MATCH("Points (Auto-generate)",INDIRECT("'"&$A9&"'!$A$12:$Z$12"),0),0)="","?",VLOOKUP(G$1,INDIRECT("'"&$A9&"'!$A$12:$Z$19"),MATCH("Points (Auto-generate)",INDIRECT("'"&$A9&"'!$A$12:$Z$12"),0),0)),"ER")) -> NA | H9: =IF($F9=0,"NA",IF($A9=INDIRECT("'"&$A9&"'!$B$1"),IF(VLOOKUP(H$1,INDIRECT("'"&$A9&"'!$A$12:$Z$19"),MATCH("Points (Auto-generate)",INDIRECT("'"&$A9&"'!$A$12:$Z$12"),0),0)="","?",VLOOKUP(H$1,INDIRECT("'"&$A9&"'!$A$12:$Z$19"),MATCH("Points (Auto-generate)",INDIRECT("'"&$A9&"'!$A$12:$Z$12"),0),0)),"ER")) -> 0 | I9: =IF($F9=0,"NA",IF($A9=INDIRECT("'"&$A9&"'!$B$1"),IF(VLOOKUP(I$1,INDIRECT("'"&$A9&"'!$A$12:$Z$19"),MATCH("Points (Auto-generate)",INDIRECT("'"&$A9&"'!$A$12:$Z$12"),0),0)="","?",VLOOKUP(I$1,INDIRECT("'"&$A9&"'!$A$12:$Z$19"),MATCH("Points (Auto-generate)",INDIRECT("'"&$A9&"'!$A$12:$Z$12"),0),0)),"ER")) -> NA | J9: =IF($F9=0,"NA",IF($A9=INDIRECT("'"&$A9&"'!$B$1"),IF(VLOOKUP(J$1,INDIRECT("'"&$A9&"'!$A$12:$Z$19"),MATCH("Points (Auto-generate)",INDIRECT("'"&$A9&"'!$A$12:$Z$12"),0),0)="","?",VLOOKUP(J$1,INDIRECT("'"&$A9&"'!$A$12:$Z$19"),MATCH("Points (Auto-generate)",INDIRECT("'"&$A9&"'!$A$12:$Z$12"),0),0)),"ER")) -> NA | K9: =IF($F9=0,"NA",IF($A9=INDIRECT("'"&$A9&"'!$B$1"),IF(VLOOKUP(K$1,INDIRECT("'"&$A9&"'!$A$12:$Z$19"),MATCH("Points (Auto-generate)",INDIRECT("'"&$A9&"'!$A$12:$Z$12"),0),0)="","?",VLOOKUP(K$1,INDIRECT("'"&$A9&"'!$A$12:$Z$19"),MATCH("Points (Auto-generate)",INDIRECT("'"&$A9&"'!$A$12:$Z$12"),0),0)),"ER")) -> NA | L9: =IF($F9=0,"NA",IF($A9=INDIRECT("'"&$A9&"'!$B$1"),IF(VLOOKUP(L$1,INDIRECT("'"&$A9&"'!$A$12:$Z$19"),MATCH("Points (Auto-generate)",INDIRECT("'"&$A9&"'!$A$12:$Z$12"),0),0)="","?",VLOOKUP(L$1,INDIRECT("'"&$A9&"'!$A$12:$Z$19"),MATCH("Points (Auto-generate)",INDIRECT("'"&$A9&"'!$A$12:$Z$12"),0),0)),"ER")) -> NA | M9: =IF($F9=0,"NA",IF($A9=INDIRECT("'"&$A9&"'!$B$1"),IF(VLOOKUP(M$1,INDIRECT("'"&$A9&"'!$A$12:$Z$19"),MATCH("Points (Auto-generate)",INDIRECT("'"&$A9&"'!$A$12:$Z$12"),0),0)="","?",VLOOKUP(M$1,INDIRECT("'"&$A9&"'!$A$12:$Z$19"),MATCH("Points (Auto-generate)",INDIRECT("'"&$A9&"'!$A$12:$Z$12"),0),0)),"ER")) -> NA
A10: UPD2d | B10: =VLOOKUP($A10,'PARASTATAL Questions'!$A:$J,3,0)&"" -> Urban Planning & Design (UPD) | C10: =VLOOKUP($A10,'PARASTATAL Questions'!$A:$J,4,0)&"" -> SQ | D10: =VLOOKUP($A10,'PARASTATAL Questions'!$A:$J,5,0)&"" -> Where multiple statutory or sectoral plans apply to the same territory, does the transport corporation ensure consistency with the applicable municipal/city plan for the city? | E10: =VLOOKUP($A10,'PARASTATAL Questions'!$A:$J,7,0)&"" -> Implementation | F10: =VLOOKUP($A10,'PARASTATAL Questions'!$A:$J,6,0) -> 2.5 | G10: =IF($F10=0,"NA",IF($A10=INDIRECT("'"&$A10&"'!$B$1"),IF(VLOOKUP(G$1,INDIRECT("'"&$A10&"'!$A$12:$Z$19"),MATCH("Points (Auto-generate)",INDIRECT("'"&$A10&"'!$A$12:$Z$12"),0),0)="","?",VLOOKUP(G$1,INDIRECT("'"&$A10&"'!$A$12:$Z$19"),MATCH("Points (Auto-generate)",INDIRECT("'"&$A10&"'!$A$12:$Z$12"),0),0)),"ER")) -> NA | H10: =IF($F10=0,"NA",IF($A10=INDIRECT("'"&$A10&"'!$B$1"),IF(VLOOKUP(H$1,INDIRECT("'"&$A10&"'!$A$12:$Z$19"),MATCH("Points (Auto-generate)",INDIRECT("'"&$A10&"'!$A$12:$Z$12"),0),0)="","?",VLOOKUP(H$1,INDIRECT("'"&$A10&"'!$A$12:$Z$19"),MATCH("Points (Auto-generate)",INDIRECT("'"&$A10&"'!$A$12:$Z$12"),0),0)),"ER")) -> ? | I10: =IF($F10=0,"NA",IF($A10=INDIRECT("'"&$A10&"'!$B$1"),IF(VLOOKUP(I$1,INDIRECT("'"&$A10&"'!$A$12:$Z$19"),MATCH("Points (Auto-generate)",INDIRECT("'"&$A10&"'!$A$12:$Z$12"),0),0)="","?",VLOOKUP(I$1,INDIRECT("'"&$A10&"'!$A$12:$Z$19"),MATCH("Points (Auto-generate)",INDIRECT("'"&$A10&"'!$A$12:$Z$12"),0),0)),"ER")) -> NA | J10: =IF($F10=0,"NA",IF($A10=INDIRECT("'"&$A10&"'!$B$1"),IF(VLOOKUP(J$1,INDIRECT("'"&$A10&"'!$A$12:$Z$19"),MATCH("Points (Auto-generate)",INDIRECT("'"&$A10&"'!$A$12:$Z$12"),0),0)="","?",VLOOKUP(J$1,INDIRECT("'"&$A10&"'!$A$12:$Z$19"),MATCH("Points (Auto-generate)",INDIRECT("'"&$A10&"'!$A$12:$Z$12"),0),0)),"ER")) -> NA | K10: =IF($F10=0,"NA",IF($A10=INDIRECT("'"&$A10&"'!$B$1"),IF(VLOOKUP(K$1,INDIRECT("'"&$A10&"'!$A$12:$Z$19"),MATCH("Points (Auto-generate)",INDIRECT("'"&$A10&"'!$A$12:$Z$12"),0),0)="","?",VLOOKUP(K$1,INDIRECT("'"&$A10&"'!$A$12:$Z$19"),MATCH("Points (Auto-generate)",INDIRECT("'"&$A10&"'!$A$12:$Z$12"),0),0)),"ER")) -> NA | L10: =IF($F10=0,"NA",IF($A10=INDIRECT("'"&$A10&"'!$B$1"),IF(VLOOKUP(L$1,INDIRECT("'"&$A10&"'!$A$12:$Z$19"),MATCH("Points (Auto-generate)",INDIRECT("'"&$A10&"'!$A$12:$Z$12"),0),0)="","?",VLOOKUP(L$1,INDIRECT("'"&$A10&"'!$A$12:$Z$19"),MATCH("Points (Auto-generate)",INDIRECT("'"&$A10&"'!$A$12:$Z$12"),0),0)),"ER")) -> NA | M10: =IF($F10=0,"NA",IF($A10=INDIRECT("'"&$A10&"'!$B$1"),IF(VLOOKUP(M$1,INDIRECT("'"&$A10&"'!$A$12:$Z$19"),MATCH("Points (Auto-generate)",INDIRECT("'"&$A10&"'!$A$12:$Z$12"),0),0)="","?",VLOOKUP(M$1,INDIRECT("'"&$A10&"'!$A$12:$Z$19"),MATCH("Points (Auto-generate)",INDIRECT("'"&$A10&"'!$A$12:$Z$12"),0),0)),"ER")) -> NA
A11: UPD3 | B11: =VLOOKUP($A11,'PARASTATAL Questions'!$A:$J,3,0)&"" -> Urban Planning & Design (UPD) | C11: =VLOOKUP($A11,'PARASTATAL Questions'!$A:$J,4,0)&"" -> MQ | D11: =VLOOKUP($A11,'PARASTATAL Questions'!$A:$J,5,0)&"" -> Are the needs of women and the urban poor explicitly considered in the water board’s planning, service delivery or major investment decisions? | E11: =VLOOKUP($A11,'PARASTATAL Questions'!$A:$J,7,0)&"" -> Law/Policy + Implementation | F11: =VLOOKUP($A11,'PARASTATAL Questions'!$A:$J,6,0) -> 10 | G11: =IF(OR(G12="ER",G13="ER"),"ER",IF(OR(G12="?",G13="?"),"?",IF(AND(G12="NA",G13="NA"),"NA",SUM(G12,G13)/((G12<>"NA")*$F$12+(G13<>"NA")*$F$13)*$F11))) -> ? | H11: =IF(OR(H12="ER",H13="ER"),"ER",IF(OR(H12="?",H13="?"),"?",IF(AND(H12="NA",H13="NA"),"NA",SUM(H12,H13)/((H12<>"NA")*$F$12+(H13<>"NA")*$F$13)*$F11))) -> NA | I11: =IF(OR(I12="ER",I13="ER"),"ER",IF(OR(I12="?",I13="?"),"?",IF(AND(I12="NA",I13="NA"),"NA",SUM(I12,I13)/((I12<>"NA")*$F$12+(I13<>"NA")*$F$13)*$F11))) -> NA | J11: =IF(OR(J12="ER",J13="ER"),"ER",IF(OR(J12="?",J13="?"),"?",IF(AND(J12="NA",J13="NA"),"NA",SUM(J12,J13)/((J12<>"NA")*$F$12+(J13<>"NA")*$F$13)*$F11))) -> NA | K11: =IF(OR(K12="ER",K13="ER"),"ER",IF(OR(K12="?",K13="?"),"?",IF(AND(K12="NA",K13="NA"),"NA",SUM(K12,K13)/((K12<>"NA")*$F$12+(K13<>"NA")*$F$13)*$F11))) -> NA | L11: =IF(OR(L12="ER",L13="ER"),"ER",IF(OR(L12="?",L13="?"),"?",IF(AND(L12="NA",L13="NA"),"NA",SUM(L12,L13)/((L12<>"NA")*$F$12+(L13<>"NA")*$F$13)*$F11))) -> NA | M11: =IF(OR(M12="ER",M13="ER"),"ER",IF(OR(M12="?",M13="?"),"?",IF(AND(M12="NA",M13="NA"),"NA",SUM(M12,M13)/((M12<>"NA")*$F$12+(M13<>"NA")*$F$13)*$F11))) -> NA
A12: UPD3a | B12: =VLOOKUP($A12,'PARASTATAL Questions'!$A:$J,3,0)&"" -> Urban Planning & Design (UPD) | C12: =VLOOKUP($A12,'PARASTATAL Questions'!$A:$J,4,0)&"" -> SQ | D12: =VLOOKUP($A12,'PARASTATAL Questions'!$A:$J,5,0)&"" -> Is the water supply board mandated to consider the needs of women and the urban poor in decisions relating to access, affordability and delivery of water and sanitation services? | E12: =VLOOKUP($A12,'PARASTATAL Questions'!$A:$J,7,0)&"" -> Law/Policy | F12: =VLOOKUP($A12,'PARASTATAL Questions'!$A:$J,6,0) -> 5 | G12: =IF($F12=0,"NA",IF($A12=INDIRECT("'"&$A12&"'!$B$1"),IF(VLOOKUP(G$1,INDIRECT("'"&$A12&"'!$A$12:$Z$19"),MATCH("Points (Auto-generate)",INDIRECT("'"&$A12&"'!$A$12:$Z$12"),0),0)="","?",VLOOKUP(G$1,INDIRECT("'"&$A12&"'!$A$12:$Z$19"),MATCH("Points (Auto-generate)",INDIRECT("'"&$A12&"'!$A$12:$Z$12"),0),0)),"ER")) -> ? | H12: =IF($F12=0,"NA",IF($A12=INDIRECT("'"&$A12&"'!$B$1"),IF(VLOOKUP(H$1,INDIRECT("'"&$A12&"'!$A$12:$Z$19"),MATCH("Points (Auto-generate)",INDIRECT("'"&$A12&"'!$A$12:$Z$12"),0),0)="","?",VLOOKUP(H$1,INDIRECT("'"&$A12&"'!$A$12:$Z$19"),MATCH("Points (Auto-generate)",INDIRECT("'"&$A12&"'!$A$12:$Z$12"),0),0)),"ER")) -> NA | I12: =IF($F12=0,"NA",IF($A12=INDIRECT("'"&$A12&"'!$B$1"),IF(VLOOKUP(I$1,INDIRECT("'"&$A12&"'!$A$12:$Z$19"),MATCH("Points (Auto-generate)",INDIRECT("'"&$A12&"'!$A$12:$Z$12"),0),0)="","?",VLOOKUP(I$1,INDIRECT("'"&$A12&"'!$A$12:$Z$19"),MATCH("Points (Auto-generate)",INDIRECT("'"&$A12&"'!$A$12:$Z$12"),0),0)),"ER")) -> NA | J12: =IF($F12=0,"NA",IF($A12=INDIRECT("'"&$A12&"'!$B$1"),IF(VLOOKUP(J$1,INDIRECT("'"&$A12&"'!$A$12:$Z$19"),MATCH("Points (Auto-generate)",INDIRECT("'"&$A12&"'!$A$12:$Z$12"),0),0)="","?",VLOOKUP(J$1,INDIRECT("'"&$A12&"'!$A$12:$Z$19"),MATCH("Points (Auto-generate)",INDIRECT("'"&$A12&"'!$A$12:$Z$12"),0),0)),"ER")) -> NA | K12: =IF($F12=0,"NA",IF($A12=INDIRECT("'"&$A12&"'!$B$1"),IF(VLOOKUP(K$1,INDIRECT("'"&$A12&"'!$A$12:$Z$19"),MATCH("Points (Auto-generate)",INDIRECT("'"&$A12&"'!$A$12:$Z$12"),0),0)="","?",VLOOKUP(K$1,INDIRECT("'"&$A12&"'!$A$12:$Z$19"),MATCH("Points (Auto-generate)",INDIRECT("'"&$A12&"'!$A$12:$Z$12"),0),0)),"ER")) -> NA | L12: =IF($F12=0,"NA",IF($A12=INDIRECT("'"&$A12&"'!$B$1"),IF(VLOOKUP(L$1,INDIRECT("'"&$A12&"'!$A$12:$Z$19"),MATCH("Points (Auto-generate)",INDIRECT("'"&$A12&"'!$A$12:$Z$12"),0),0)="","?",VLOOKUP(L$1,INDIRECT("'"&$A12&"'!$A$12:$Z$19"),MATCH("Points (Auto-generate)",INDIRECT("'"&$A12&"'!$A$12:$Z$12"),0),0)),"ER")) -> NA | M12: =IF($F12=0,"NA",IF($A12=INDIRECT("'"&$A12&"'!$B$1"),IF(VLOOKUP(M$1,INDIRECT("'"&$A12&"'!$A$12:$Z$19"),MATCH("Points (Auto-generate)",INDIRECT("'"&$A12&"'!$A$12:$Z$12"),0),0)="","?",VLOOKUP(M$1,INDIRECT("'"&$A12&"'!$A$12:$Z$19"),MATCH("Points (Auto-generate)",INDIRECT("'"&$A12&"'!$A$12:$Z$12"),0),0)),"ER")) -> NA
A13: UPD3b | B13: =VLOOKUP($A13,'PARASTATAL Questions'!$A:$J,3,0)&"" -> Urban Planning & Design (UPD) | C13: =VLOOKUP($A13,'PARASTATAL Questions'!$A:$J,4,0)&"" -> SQ | D13: =VLOOKUP($A13,'PARASTATAL Questions'!$A:$J,5,0)&"" -> Does the water supply board actually consider the needs of women and the urban poor in decisions relating to access, affordability and delivery of water and sanitation services? | E13: =VLOOKUP($A13,'PARASTATAL Questions'!$A:$J,7,0)&"" -> Implementation | F13: =VLOOKUP($A13,'PARASTATAL Questions'!$A:$J,6,0) -> 5 | G13: =IF($F13=0,"NA",IF($A13=INDIRECT("'"&$A13&"'!$B$1"),IF(VLOOKUP(G$1,INDIRECT("'"&$A13&"'!$A$12:$Z$19"),MATCH("Points (Auto-generate)",INDIRECT("'"&$A13&"'!$A$12:$Z$12"),0),0)="","?",VLOOKUP(G$1,INDIRECT("'"&$A13&"'!$A$12:$Z$19"),MATCH("Points (Auto-generate)",INDIRECT("'"&$A13&"'!$A$12:$Z$12"),0),0)),"ER")) -> 1.25 | H13: =IF($F13=0,"NA",IF($A13=INDIRECT("'"&$A13&"'!$B$1"),IF(VLOOKUP(H$1,INDIRECT("'"&$A13&"'!$A$12:$Z$19"),MATCH("Points (Auto-generate)",INDIRECT("'"&$A13&"'!$A$12:$Z$12"),0),0)="","?",VLOOKUP(H$1,INDIRECT("'"&$A13&"'!$A$12:$Z$19"),MATCH("Points (Auto-generate)",INDIRECT("'"&$A13&"'!$A$12:$Z$12"),0),0)),"ER")) -> NA | I13: =IF($F13=0,"NA",IF($A13=INDIRECT("'"&$A13&"'!$B$1"),IF(VLOOKUP(I$1,INDIRECT("'"&$A13&"'!$A$12:$Z$19"),MATCH("Points (Auto-generate)",INDIRECT("'"&$A13&"'!$A$12:$Z$12"),0),0)="","?",VLOOKUP(I$1,INDIRECT("'"&$A13&"'!$A$12:$Z$19"),MATCH("Points (Auto-generate)",INDIRECT("'"&$A13&"'!$A$12:$Z$12"),0),0)),"ER")) -> NA | J13: =IF($F13=0,"NA",IF($A13=INDIRECT("'"&$A13&"'!$B$1"),IF(VLOOKUP(J$1,INDIRECT("'"&$A13&"'!$A$12:$Z$19"),MATCH("Points (Auto-generate)",INDIRECT("'"&$A13&"'!$A$12:$Z$12"),0),0)="","?",VLOOKUP(J$1,INDIRECT("'"&$A13&"'!$A$12:$Z$19"),MATCH("Points (Auto-generate)",INDIRECT("'"&$A13&"'!$A$12:$Z$12"),0),0)),"ER")) -> NA | K13: =IF($F13=0,"NA",IF($A13=INDIRECT("'"&$A13&"'!$B$1"),IF(VLOOKUP(K$1,INDIRECT("'"&$A13&"'!$A$12:$Z$19"),MATCH("Points (Auto-generate)",INDIRECT("'"&$A13&"'!$A$12:$Z$12"),0),0)="","?",VLOOKUP(K$1,INDIRECT("'"&$A13&"'!$A$12:$Z$19"),MATCH("Points (Auto-generate)",INDIRECT("'"&$A13&"'!$A$12:$Z$12"),0),0)),"ER")) -> NA | L13: =IF($F13=0,"NA",IF($A13=INDIRECT("'"&$A13&"'!$B$1"),IF(VLOOKUP(L$1,INDIRECT("'"&$A13&"'!$A$12:$Z$19"),MATCH("Points (Auto-generate)",INDIRECT("'"&$A13&"'!$A$12:$Z$12"),0),0)="","?",VLOOKUP(L$1,INDIRECT("'"&$A13&"'!$A$12:$Z$19"),MATCH("Points (Auto-generate)",INDIRECT("'"&$A13&"'!$A$12:$Z$12"),0),0)),"ER")) -> NA | M13: =IF($F13=0,"NA",IF($A13=INDIRECT("'"&$A13&"'!$B$1"),IF(VLOOKUP(M$1,INDIRECT("'"&$A13&"'!$A$12:$Z$19"),MATCH("Points (Auto-generate)",INDIRECT("'"&$A13&"'!$A$12:$Z$12"),0),0)="","?",VLOOKUP(M$1,INDIRECT("'"&$A13&"'!$A$12:$Z$19"),MATCH("Points (Auto-generate)",INDIRECT("'"&$A13&"'!$A$12:$Z$12"),0),0)),"ER")) -> NA
A14: UPD4 | B14: =VLOOKUP($A14,'PARASTATAL Questions'!$A:$J,3,0)&"" -> Urban Planning & Design (UPD) | C14: =VLOOKUP($A14,'PARASTATAL Questions'!$A:$J,4,0)&"" -> MQ | D14: =VLOOKUP($A14,'PARASTATAL Questions'!$A:$J,5,0)&"" -> Are the needs of women and the urban poor explicitly considered in the transport Corporation’s planning, service delivery or major investment decisions? | E14: =VLOOKUP($A14,'PARASTATAL Questions'!$A:$J,7,0)&"" -> Law/Policy + Implementation | F14: =VLOOKUP($A14,'PARASTATAL Questions'!$A:$J,6,0) -> 10 | G14: =IF(OR(G15="ER",G16="ER"),"ER",IF(OR(G15="?",G16="?"),"?",IF(AND(G15="NA",G16="NA"),"NA",SUM(G15,G16)/((G15<>"NA")*$F$15+(G16<>"NA")*$F$16)*$F14))) -> NA | H14: =IF(OR(H15="ER",H16="ER"),"ER",IF(OR(H15="?",H16="?"),"?",IF(AND(H15="NA",H16="NA"),"NA",SUM(H15,H16)/((H15<>"NA")*$F$15+(H16<>"NA")*$F$16)*$F14))) -> ? | I14: =IF(OR(I15="ER",I16="ER"),"ER",IF(OR(I15="?",I16="?"),"?",IF(AND(I15="NA",I16="NA"),"NA",SUM(I15,I16)/((I15<>"NA")*$F$15+(I16<>"NA")*$F$16)*$F14))) -> NA | J14: =IF(OR(J15="ER",J16="ER"),"ER",IF(OR(J15="?",J16="?"),"?",IF(AND(J15="NA",J16="NA"),"NA",SUM(J15,J16)/((J15<>"NA")*$F$15+(J16<>"NA")*$F$16)*$F14))) -> NA | K14: =IF(OR(K15="ER",K16="ER"),"ER",IF(OR(K15="?",K16="?"),"?",IF(AND(K15="NA",K16="NA"),"NA",SUM(K15,K16)/((K15<>"NA")*$F$15+(K16<>"NA")*$F$16)*$F14))) -> NA | L14: =IF(OR(L15="ER",L16="ER"),"ER",IF(OR(L15="?",L16="?"),"?",IF(AND(L15="NA",L16="NA"),"NA",SUM(L15,L16)/((L15<>"NA")*$F$15+(L16<>"NA")*$F$16)*$F14))) -> NA | M14: =IF(OR(M15="ER",M16="ER"),"ER",IF(OR(M15="?",M16="?"),"?",IF(AND(M15="NA",M16="NA"),"NA",SUM(M15,M16)/((M15<>"NA")*$F$15+(M16<>"NA")*$F$16)*$F14))) -> NA
A15: UPD4a | B15: =VLOOKUP($A15,'PARASTATAL Questions'!$A:$J,3,0)&"" -> Urban Planning & Design (UPD) | C15: =VLOOKUP($A15,'PARASTATAL Questions'!$A:$J,4,0)&"" -> SQ | D15: =VLOOKUP($A15,'PARASTATAL Questions'!$A:$J,5,0)&"" -> Is the transport corporation mandated to consider the mobility needs of women and the urban poor in planning and delivering public transport services? | E15: =VLOOKUP($A15,'PARASTATAL Questions'!$A:$J,7,0)&"" -> Law/Policy | F15: =VLOOKUP($A15,'PARASTATAL Questions'!$A:$J,6,0) -> 5 | G15: =IF($F15=0,"NA",IF($A15=INDIRECT("'"&$A15&"'!$B$1"),IF(VLOOKUP(G$1,INDIRECT("'"&$A15&"'!$A$12:$Z$19"),MATCH("Points (Auto-generate)",INDIRECT("'"&$A15&"'!$A$12:$Z$12"),0),0)="","?",VLOOKUP(G$1,INDIRECT("'"&$A15&"'!$A$12:$Z$19"),MATCH("Points (Auto-generate)",INDIRECT("'"&$A15&"'!$A$12:$Z$12"),0),0)),"ER")) -> NA | H15: =IF($F15=0,"NA",IF($A15=INDIRECT("'"&$A15&"'!$B$1"),IF(VLOOKUP(H$1,INDIRECT("'"&$A15&"'!$A$12:$Z$19"),MATCH("Points (Auto-generate)",INDIRECT("'"&$A15&"'!$A$12:$Z$12"),0),0)="","?",VLOOKUP(H$1,INDIRECT("'"&$A15&"'!$A$12:$Z$19"),MATCH("Points (Auto-generate)",INDIRECT("'"&$A15&"'!$A$12:$Z$12"),0),0)),"ER")) -> 0 | I15: =IF($F15=0,"NA",IF($A15=INDIRECT("'"&$A15&"'!$B$1"),IF(VLOOKUP(I$1,INDIRECT("'"&$A15&"'!$A$12:$Z$19"),MATCH("Points (Auto-generate)",INDIRECT("'"&$A15&"'!$A$12:$Z$12"),0),0)="","?",VLOOKUP(I$1,INDIRECT("'"&$A15&"'!$A$12:$Z$19"),MATCH("Points (Auto-generate)",INDIRECT("'"&$A15&"'!$A$12:$Z$12"),0),0)),"ER")) -> NA | J15: =IF($F15=0,"NA",IF($A15=INDIRECT("'"&$A15&"'!$B$1"),IF(VLOOKUP(J$1,INDIRECT("'"&$A15&"'!$A$12:$Z$19"),MATCH("Points (Auto-generate)",INDIRECT("'"&$A15&"'!$A$12:$Z$12"),0),0)="","?",VLOOKUP(J$1,INDIRECT("'"&$A15&"'!$A$12:$Z$19"),MATCH("Points (Auto-generate)",INDIRECT("'"&$A15&"'!$A$12:$Z$12"),0),0)),"ER")) -> NA | K15: =IF($F15=0,"NA",IF($A15=INDIRECT("'"&$A15&"'!$B$1"),IF(VLOOKUP(K$1,INDIRECT("'"&$A15&"'!$A$12:$Z$19"),MATCH("Points (Auto-generate)",INDIRECT("'"&$A15&"'!$A$12:$Z$12"),0),0)="","?",VLOOKUP(K$1,INDIRECT("'"&$A15&"'!$A$12:$Z$19"),MATCH("Points (Auto-generate)",INDIRECT("'"&$A15&"'!$A$12:$Z$12"),0),0)),"ER")) -> NA | L15: =IF($F15=0,"NA",IF($A15=INDIRECT("'"&$A15&"'!$B$1"),IF(VLOOKUP(L$1,INDIRECT("'"&$A15&"'!$A$12:$Z$19"),MATCH("Points (Auto-generate)",INDIRECT("'"&$A15&"'!$A$12:$Z$12"),0),0)="","?",VLOOKUP(L$1,INDIRECT("'"&$A15&"'!$A$12:$Z$19"),MATCH("Points (Auto-generate)",INDIRECT("'"&$A15&"'!$A$12:$Z$12"),0),0)),"ER")) -> NA | M15: =IF($F15=0,"NA",IF($A15=INDIRECT("'"&$A15&"'!$B$1"),IF(VLOOKUP(M$1,INDIRECT("'"&$A15&"'!$A$12:$Z$19"),MATCH("Points (Auto-generate)",INDIRECT("'"&$A15&"'!$A$12:$Z$12"),0),0)="","?",VLOOKUP(M$1,INDIRECT("'"&$A15&"'!$A$12:$Z$19"),MATCH("Points (Auto-generate)",INDIRECT("'"&$A15&"'!$A$12:$Z$12"),0),0)),"ER")) -> NA
A16: UPD4b | B16: =VLOOKUP($A16,'PARASTATAL Questions'!$A:$J,3,0)&"" -> Urban Planning & Design (UPD) | C16: =VLOOKUP($A16,'PARASTATAL Questions'!$A:$J,4,0)&"" -> SQ | D16: =VLOOKUP($A16,'PARASTATAL Questions'!$A:$J,5,0)&"" -> Does the Transport Corporation actually consider the needs of women and the urban poor in decisions relating to access, affordability and delivery of public transport services? | E16: =VLOOKUP($A16,'PARASTATAL Questions'!$A:$J,7,0)&"" -> Implementation | F16: =VLOOKUP($A16,'PARASTATAL Questions'!$A:$J,6,0) -> 5 | G16: =IF($F16=0,"NA",IF($A16=INDIRECT("'"&$A16&"'!$B$1"),IF(VLOOKUP(G$1,INDIRECT("'"&$A16&"'!$A$12:$Z$19"),MATCH("Points (Auto-generate)",INDIRECT("'"&$A16&"'!$A$12:$Z$12"),0),0)="","?",VLOOKUP(G$1,INDIRECT("'"&$A16&"'!$A$12:$Z$19"),MATCH("Points (Auto-generate)",INDIRECT("'"&$A16&"'!$A$12:$Z$12"),0),0)),"ER")) -> NA | H16: =IF($F16=0,"NA",IF($A16=INDIRECT("'"&$A16&"'!$B$1"),IF(VLOOKUP(H$1,INDIRECT("'"&$A16&"'!$A$12:$Z$19"),MATCH("Points (Auto-generate)",INDIRECT("'"&$A16&"'!$A$12:$Z$12"),0),0)="","?",VLOOKUP(H$1,INDIRECT("'"&$A16&"'!$A$12:$Z$19"),MATCH("Points (Auto-generate)",INDIRECT("'"&$A16&"'!$A$12:$Z$12"),0),0)),"ER")) -> ? | I16: =IF($F16=0,"NA",IF($A16=INDIRECT("'"&$A16&"'!$B$1"),IF(VLOOKUP(I$1,INDIRECT("'"&$A16&"'!$A$12:$Z$19"),MATCH("Points (Auto-generate)",INDIRECT("'"&$A16&"'!$A$12:$Z$12"),0),0)="","?",VLOOKUP(I$1,INDIRECT("'"&$A16&"'!$A$12:$Z$19"),MATCH("Points (Auto-generate)",INDIRECT("'"&$A16&"'!$A$12:$Z$12"),0),0)),"ER")) -> NA | J16: =IF($F16=0,"NA",IF($A16=INDIRECT("'"&$A16&"'!$B$1"),IF(VLOOKUP(J$1,INDIRECT("'"&$A16&"'!$A$12:$Z$19"),MATCH("Points (Auto-generate)",INDIRECT("'"&$A16&"'!$A$12:$Z$12"),0),0)="","?",VLOOKUP(J$1,INDIRECT("'"&$A16&"'!$A$12:$Z$19"),MATCH("Points (Auto-generate)",INDIRECT("'"&$A16&"'!$A$12:$Z$12"),0),0)),"ER")) -> NA | K16: =IF($F16=0,"NA",IF($A16=INDIRECT("'"&$A16&"'!$B$1"),IF(VLOOKUP(K$1,INDIRECT("'"&$A16&"'!$A$12:$Z$19"),MATCH("Points (Auto-generate)",INDIRECT("'"&$A16&"'!$A$12:$Z$12"),0),0)="","?",VLOOKUP(K$1,INDIRECT("'"&$A16&"'!$A$12:$Z$19"),MATCH("Points (Auto-generate)",INDIRECT("'"&$A16&"'!$A$12:$Z$12"),0),0)),"ER")) -> NA | L16: =IF($F16=0,"NA",IF($A16=INDIRECT("'"&$A16&"'!$B$1"),IF(VLOOKUP(L$1,INDIRECT("'"&$A16&"'!$A$12:$Z$19"),MATCH("Points (Auto-generate)",INDIRECT("'"&$A16&"'!$A$12:$Z$12"),0),0)="","?",VLOOKUP(L$1,INDIRECT("'"&$A16&"'!$A$12:$Z$19"),MATCH("Points (Auto-generate)",INDIRECT("'"&$A16&"'!$A$12:$Z$12"),0),0)),"ER")) -> NA | M16: =IF($F16=0,"NA",IF($A16=INDIRECT("'"&$A16&"'!$B$1"),IF(VLOOKUP(M$1,INDIRECT("'"&$A16&"'!$A$12:$Z$19"),MATCH("Points (Auto-generate)",INDIRECT("'"&$A16&"'!$A$12:$Z$12"),0),0)="","?",VLOOKUP(M$1,INDIRECT("'"&$A16&"'!$A$12:$Z$19"),MATCH("Points (Auto-generate)",INDIRECT("'"&$A16&"'!$A$12:$Z$12"),0),0)),"ER")) -> NA
A17: UPD5 | B17: =VLOOKUP($A17,'PARASTATAL Questions'!$A:$J,3,0)&"" -> Urban Planning & Design (UPD) | C17: =VLOOKUP($A17,'PARASTATAL Questions'!$A:$J,4,0)&"" -> MQ | D17: =VLOOKUP($A17,'PARASTATAL Questions'!$A:$J,5,0)&"" -> Are environmental considerations explicitly required to be integrated into the water supply board’s planning, service-delivery or major investment decisions? | E17: =VLOOKUP($A17,'PARASTATAL Questions'!$A:$J,7,0)&"" -> Law/Policy + Implementation | F17: =VLOOKUP($A17,'PARASTATAL Questions'!$A:$J,6,0) -> 10 | G17: =IF(OR(G18="ER",G19="ER"),"ER",IF(OR(G18="?",G19="?"),"?",IF(AND(G18="NA",G19="NA"),"NA",SUM(G18,G19)/((G18<>"NA")*$F$18+(G19<>"NA")*$F$19)*$F17))) -> 7.5 | H17: =IF(OR(H18="ER",H19="ER"),"ER",IF(OR(H18="?",H19="?"),"?",IF(AND(H18="NA",H19="NA"),"NA",SUM(H18,H19)/((H18<>"NA")*$F$18+(H19<>"NA")*$F$19)*$F17))) -> NA | I17: =IF(OR(I18="ER",I19="ER"),"ER",IF(OR(I18="?",I19="?"),"?",IF(AND(I18="NA",I19="NA"),"NA",SUM(I18,I19)/((I18<>"NA")*$F$18+(I19<>"NA")*$F$19)*$F17))) -> NA | J17: =IF(OR(J18="ER",J19="ER"),"ER",IF(OR(J18="?",J19="?"),"?",IF(AND(J18="NA",J19="NA"),"NA",SUM(J18,J19)/((J18<>"NA")*$F$18+(J19<>"NA")*$F$19)*$F17))) -> NA | K17: =IF(OR(K18="ER",K19="ER"),"ER",IF(OR(K18="?",K19="?"),"?",IF(AND(K18="NA",K19="NA"),"NA",SUM(K18,K19)/((K18<>"NA")*$F$18+(K19<>"NA")*$F$19)*$F17))) -> NA | L17: =IF(OR(L18="ER",L19="ER"),"ER",IF(OR(L18="?",L19="?"),"?",IF(AND(L18="NA",L19="NA"),"NA",SUM(L18,L19)/((L18<>"NA")*$F$18+(L19<>"NA")*$F$19)*$F17))) -> NA | M17: =IF(OR(M18="ER",M19="ER"),"ER",IF(OR(M18="?",M19="?"),"?",IF(AND(M18="NA",M19="NA"),"NA",SUM(M18,M19)/((M18<>"NA")*$F$18+(M19<>"NA")*$F$19)*$F17))) -> NA
A18: UPD5a | B18: =VLOOKUP($A18,'PARASTATAL Questions'!$A:$J,3,0)&"" -> Urban Planning & Design (UPD) | C18: =VLOOKUP($A18,'PARASTATAL Questions'!$A:$J,4,0)&"" -> SQ | D18: =VLOOKUP($A18,'PARASTATAL Questions'!$A:$J,5,0)&"" -> Is the water supply board mandated to consider environmental sustainability in planning and delivering water and sanitation services? | E18: =VLOOKUP($A18,'PARASTATAL Questions'!$A:$J,7,0)&"" -> Law/Policy | F18: =VLOOKUP($A18,'PARASTATAL Questions'!$A:$J,6,0) -> 5 | G18: =IF($F18=0,"NA",IF($A18=INDIRECT("'"&$A18&"'!$B$1"),IF(VLOOKUP(G$1,INDIRECT("'"&$A18&"'!$A$12:$Z$19"),MATCH("Points (Auto-generate)",INDIRECT("'"&$A18&"'!$A$12:$Z$12"),0),0)="","?",VLOOKUP(G$1,INDIRECT("'"&$A18&"'!$A$12:$Z$19"),MATCH("Points (Auto-generate)",INDIRECT("'"&$A18&"'!$A$12:$Z$12"),0),0)),"ER")) -> 2.5 | H18: =IF($F18=0,"NA",IF($A18=INDIRECT("'"&$A18&"'!$B$1"),IF(VLOOKUP(H$1,INDIRECT("'"&$A18&"'!$A$12:$Z$19"),MATCH("Points (Auto-generate)",INDIRECT("'"&$A18&"'!$A$12:$Z$12"),0),0)="","?",VLOOKUP(H$1,INDIRECT("'"&$A18&"'!$A$12:$Z$19"),MATCH("Points (Auto-generate)",INDIRECT("'"&$A18&"'!$A$12:$Z$12"),0),0)),"ER")) -> NA | I18: =IF($F18=0,"NA",IF($A18=INDIRECT("'"&$A18&"'!$B$1"),IF(VLOOKUP(I$1,INDIRECT("'"&$A18&"'!$A$12:$Z$19"),MATCH("Points (Auto-generate)",INDIRECT("'"&$A18&"'!$A$12:$Z$12"),0),0)="","?",VLOOKUP(I$1,INDIRECT("'"&$A18&"'!$A$12:$Z$19"),MATCH("Points (Auto-generate)",INDIRECT("'"&$A18&"'!$A$12:$Z$12"),0),0)),"ER")) -> NA | J18: =IF($F18=0,"NA",IF($A18=INDIRECT("'"&$A18&"'!$B$1"),IF(VLOOKUP(J$1,INDIRECT("'"&$A18&"'!$A$12:$Z$19"),MATCH("Points (Auto-generate)",INDIRECT("'"&$A18&"'!$A$12:$Z$12"),0),0)="","?",VLOOKUP(J$1,INDIRECT("'"&$A18&"'!$A$12:$Z$19"),MATCH("Points (Auto-generate)",INDIRECT("'"&$A18&"'!$A$12:$Z$12"),0),0)),"ER")) -> NA | K18: =IF($F18=0,"NA",IF($A18=INDIRECT("'"&$A18&"'!$B$1"),IF(VLOOKUP(K$1,INDIRECT("'"&$A18&"'!$A$12:$Z$19"),MATCH("Points (Auto-generate)",INDIRECT("'"&$A18&"'!$A$12:$Z$12"),0),0)="","?",VLOOKUP(K$1,INDIRECT("'"&$A18&"'!$A$12:$Z$19"),MATCH("Points (Auto-generate)",INDIRECT("'"&$A18&"'!$A$12:$Z$12"),0),0)),"ER")) -> NA | L18: =IF($F18=0,"NA",IF($A18=INDIRECT("'"&$A18&"'!$B$1"),IF(VLOOKUP(L$1,INDIRECT("'"&$A18&"'!$A$12:$Z$19"),MATCH("Points (Auto-generate)",INDIRECT("'"&$A18&"'!$A$12:$Z$12"),0),0)="","?",VLOOKUP(L$1,INDIRECT("'"&$A18&"'!$A$12:$Z$19"),MATCH("Points (Auto-generate)",INDIRECT("'"&$A18&"'!$A$12:$Z$12"),0),0)),"ER")) -> NA | M18: =IF($F18=0,"NA",IF($A18=INDIRECT("'"&$A18&"'!$B$1"),IF(VLOOKUP(M$1,INDIRECT("'"&$A18&"'!$A$12:$Z$19"),MATCH("Points (Auto-generate)",INDIRECT("'"&$A18&"'!$A$12:$Z$12"),0),0)="","?",VLOOKUP(M$1,INDIRECT("'"&$A18&"'!$A$12:$Z$19"),MATCH("Points (Auto-generate)",INDIRECT("'"&$A18&"'!$A$12:$Z$12"),0),0)),"ER")) -> NA
A19: UPD5b | B19: =VLOOKUP($A19,'PARASTATAL Questions'!$A:$J,3,0)&"" -> Urban Planning & Design (UPD) | C19: =VLOOKUP($A19,'PARASTATAL Questions'!$A:$J,4,0)&"" -> SQ | D19: =VLOOKUP($A19,'PARASTATAL Questions'!$A:$J,5,0)&"" -> Does the water supply board actually consider environmental sustainability in planning and delivering water and sanitation services? | E19: =VLOOKUP($A19,'PARASTATAL Questions'!$A:$J,7,0)&"" -> Implementation | F19: =VLOOKUP($A19,'PARASTATAL Questions'!$A:$J,6,0) -> 5 | G19: =IF($F19=0,"NA",IF($A19=INDIRECT("'"&$A19&"'!$B$1"),IF(VLOOKUP(G$1,INDIRECT("'"&$A19&"'!$A$12:$Z$19"),MATCH("Points (Auto-generate)",INDIRECT("'"&$A19&"'!$A$12:$Z$12"),0),0)="","?",VLOOKUP(G$1,INDIRECT("'"&$A19&"'!$A$12:$Z$19"),MATCH("Points (Auto-generate)",INDIRECT("'"&$A19&"'!$A$12:$Z$12"),0),0)),"ER")) -> 5 | H19: =IF($F19=0,"NA",IF($A19=INDIRECT("'"&$A19&"'!$B$1"),IF(VLOOKUP(H$1,INDIRECT("'"&$A19&"'!$A$12:$Z$19"),MATCH("Points (Auto-generate)",INDIRECT("'"&$A19&"'!$A$12:$Z$12"),0),0)="","?",VLOOKUP(H$1,INDIRECT("'"&$A19&"'!$A$12:$Z$19"),MATCH("Points (Auto-generate)",INDIRECT("'"&$A19&"'!$A$12:$Z$12"),0),0)),"ER")) -> NA | I19: =IF($F19=0,"NA",IF($A19=INDIRECT("'"&$A19&"'!$B$1"),IF(VLOOKUP(I$1,INDIRECT("'"&$A19&"'!$A$12:$Z$19"),MATCH("Points (Auto-generate)",INDIRECT("'"&$A19&"'!$A$12:$Z$12"),0),0)="","?",VLOOKUP(I$1,INDIRECT("'"&$A19&"'!$A$12:$Z$19"),MATCH("Points (Auto-generate)",INDIRECT("'"&$A19&"'!$A$12:$Z$12"),0),0)),"ER")) -> NA | J19: =IF($F19=0,"NA",IF($A19=INDIRECT("'"&$A19&"'!$B$1"),IF(VLOOKUP(J$1,INDIRECT("'"&$A19&"'!$A$12:$Z$19"),MATCH("Points (Auto-generate)",INDIRECT("'"&$A19&"'!$A$12:$Z$12"),0),0)="","?",VLOOKUP(J$1,INDIRECT("'"&$A19&"'!$A$12:$Z$19"),MATCH("Points (Auto-generate)",INDIRECT("'"&$A19&"'!$A$12:$Z$12"),0),0)),"ER")) -> NA | K19: =IF($F19=0,"NA",IF($A19=INDIRECT("'"&$A19&"'!$B$1"),IF(VLOOKUP(K$1,INDIRECT("'"&$A19&"'!$A$12:$Z$19"),MATCH("Points (Auto-generate)",INDIRECT("'"&$A19&"'!$A$12:$Z$12"),0),0)="","?",VLOOKUP(K$1,INDIRECT("'"&$A19&"'!$A$12:$Z$19"),MATCH("Points (Auto-generate)",INDIRECT("'"&$A19&"'!$A$12:$Z$12"),0),0)),"ER")) -> NA | L19: =IF($F19=0,"NA",IF($A19=INDIRECT("'"&$A19&"'!$B$1"),IF(VLOOKUP(L$1,INDIRECT("'"&$A19&"'!$A$12:$Z$19"),MATCH("Points (Auto-generate)",INDIRECT("'"&$A19&"'!$A$12:$Z$12"),0),0)="","?",VLOOKUP(L$1,INDIRECT("'"&$A19&"'!$A$12:$Z$19"),MATCH("Points (Auto-generate)",INDIRECT("'"&$A19&"'!$A$12:$Z$12"),0),0)),"ER")) -> NA | M19: =IF($F19=0,"NA",IF($A19=INDIRECT("'"&$A19&"'!$B$1"),IF(VLOOKUP(M$1,INDIRECT("'"&$A19&"'!$A$12:$Z$19"),MATCH("Points (Auto-generate)",INDIRECT("'"&$A19&"'!$A$12:$Z$12"),0),0)="","?",VLOOKUP(M$1,INDIRECT("'"&$A19&"'!$A$12:$Z$19"),MATCH("Points (Auto-generate)",INDIRECT("'"&$A19&"'!$A$12:$Z$12"),0),0)),"ER")) -> NA
A20: UPD6 | B20: =VLOOKUP($A20,'PARASTATAL Questions'!$A:$J,3,0)&"" -> Urban Planning & Design (UPD) | C20: =VLOOKUP($A20,'PARASTATAL Questions'!$A:$J,4,0)&"" -> MQ | D20: =VLOOKUP($A20,'PARASTATAL Questions'!$A:$J,5,0)&"" -> Are environmental considerations explicitly required to be integrated into the transport corporation’s planning, service-delivery or major investment decisions? | E20: =VLOOKUP($A20,'PARASTATAL Questions'!$A:$J,7,0)&"" -> Law/Policy + Implementation | F20: =VLOOKUP($A20,'PARASTATAL Questions'!$A:$J,6,0) -> 10 | G20: =IF(OR(G21="ER",G22="ER"),"ER",IF(OR(G21="?",G22="?"),"?",IF(AND(G21="NA",G22="NA"),"NA",SUM(G21,G22)/((G21<>"NA")*$F$21+(G22<>"NA")*$F$22)*$F20))) -> NA | H20: =IF(OR(H21="ER",H22="ER"),"ER",IF(OR(H21="?",H22="?"),"?",IF(AND(H21="NA",H22="NA"),"NA",SUM(H21,H22)/((H21<>"NA")*$F$21+(H22<>"NA")*$F$22)*$F20))) -> ? | I20: =IF(OR(I21="ER",I22="ER"),"ER",IF(OR(I21="?",I22="?"),"?",IF(AND(I21="NA",I22="NA"),"NA",SUM(I21,I22)/((I21<>"NA")*$F$21+(I22<>"NA")*$F$22)*$F20))) -> NA | J20: =IF(OR(J21="ER",J22="ER"),"ER",IF(OR(J21="?",J22="?"),"?",IF(AND(J21="NA",J22="NA"),"NA",SUM(J21,J22)/((J21<>"NA")*$F$21+(J22<>"NA")*$F$22)*$F20))) -> NA | K20: =IF(OR(K21="ER",K22="ER"),"ER",IF(OR(K21="?",K22="?"),"?",IF(AND(K21="NA",K22="NA"),"NA",SUM(K21,K22)/((K21<>"NA")*$F$21+(K22<>"NA")*$F$22)*$F20))) -> NA | L20: =IF(OR(L21="ER",L22="ER"),"ER",IF(OR(L21="?",L22="?"),"?",IF(AND(L21="NA",L22="NA"),"NA",SUM(L21,L22)/((L21<>"NA")*$F$21+(L22<>"NA")*$F$22)*$F20))) -> NA | M20: =IF(OR(M21="ER",M22="ER"),"ER",IF(OR(M21="?",M22="?"),"?",IF(AND(M21="NA",M22="NA"),"NA",SUM(M21,M22)/((M21<>"NA")*$F$21+(M22<>"NA")*$F$22)*$F20))) -> NA
A21: UPD6a | B21: =VLOOKUP($A21,'PARASTATAL Questions'!$A:$J,3,0)&"" -> Urban Planning & Design (UPD) | C21: =VLOOKUP($A21,'PARASTATAL Questions'!$A:$J,4,0)&"" -> SQ | D21: =VLOOKUP($A21,'PARASTATAL Questions'!$A:$J,5,0)&"" -> Is the transport corporation mandated to consider environmental sustainability in planning and delivering urban transport services and investments? | E21: =VLOOKUP($A21,'PARASTATAL Questions'!$A:$J,7,0)&"" -> Law/Policy | F21: =VLOOKUP($A21,'PARASTATAL Questions'!$A:$J,6,0) -> 5 | G21: =IF($F21=0,"NA",IF($A21=INDIRECT("'"&$A21&"'!$B$1"),IF(VLOOKUP(G$1,INDIRECT("'"&$A21&"'!$A$12:$Z$19"),MATCH("Points (Auto-generate)",INDIRECT("'"&$A21&"'!$A$12:$Z$12"),0),0)="","?",VLOOKUP(G$1,INDIRECT("'"&$A21&"'!$A$12:$Z$19"),MATCH("Points (Auto-generate)",INDIRECT("'"&$A21&"'!$A$12:$Z$12"),0),0)),"ER")) -> NA | H21: =IF($F21=0,"NA",IF($A21=INDIRECT("'"&$A21&"'!$B$1"),IF(VLOOKUP(H$1,INDIRECT("'"&$A21&"'!$A$12:$Z$19"),MATCH("Points (Auto-generate)",INDIRECT("'"&$A21&"'!$A$12:$Z$12"),0),0)="","?",VLOOKUP(H$1,INDIRECT("'"&$A21&"'!$A$12:$Z$19"),MATCH("Points (Auto-generate)",INDIRECT("'"&$A21&"'!$A$12:$Z$12"),0),0)),"ER")) -> 5 | I21: =IF($F21=0,"NA",IF($A21=INDIRECT("'"&$A21&"'!$B$1"),IF(VLOOKUP(I$1,INDIRECT("'"&$A21&"'!$A$12:$Z$19"),MATCH("Points (Auto-generate)",INDIRECT("'"&$A21&"'!$A$12:$Z$12"),0),0)="","?",VLOOKUP(I$1,INDIRECT("'"&$A21&"'!$A$12:$Z$19"),MATCH("Points (Auto-generate)",INDIRECT("'"&$A21&"'!$A$12:$Z$12"),0),0)),"ER")) -> NA | J21: =IF($F21=0,"NA",IF($A21=INDIRECT("'"&$A21&"'!$B$1"),IF(VLOOKUP(J$1,INDIRECT("'"&$A21&"'!$A$12:$Z$19"),MATCH("Points (Auto-generate)",INDIRECT("'"&$A21&"'!$A$12:$Z$12"),0),0)="","?",VLOOKUP(J$1,INDIRECT("'"&$A21&"'!$A$12:$Z$19"),MATCH("Points (Auto-generate)",INDIRECT("'"&$A21&"'!$A$12:$Z$12"),0),0)),"ER")) -> NA | K21: =IF($F21=0,"NA",IF($A21=INDIRECT("'"&$A21&"'!$B$1"),IF(VLOOKUP(K$1,INDIRECT("'"&$A21&"'!$A$12:$Z$19"),MATCH("Points (Auto-generate)",INDIRECT("'"&$A21&"'!$A$12:$Z$12"),0),0)="","?",VLOOKUP(K$1,INDIRECT("'"&$A21&"'!$A$12:$Z$19"),MATCH("Points (Auto-generate)",INDIRECT("'"&$A21&"'!$A$12:$Z$12"),0),0)),"ER")) -> NA | L21: =IF($F21=0,"NA",IF($A21=INDIRECT("'"&$A21&"'!$B$1"),IF(VLOOKUP(L$1,INDIRECT("'"&$A21&"'!$A$12:$Z$19"),MATCH("Points (Auto-generate)",INDIRECT("'"&$A21&"'!$A$12:$Z$12"),0),0)="","?",VLOOKUP(L$1,INDIRECT("'"&$A21&"'!$A$12:$Z$19"),MATCH("Points (Auto-generate)",INDIRECT("'"&$A21&"'!$A$12:$Z$12"),0),0)),"ER")) -> NA | M21: =IF($F21=0,"NA",IF($A21=INDIRECT("'"&$A21&"'!$B$1"),IF(VLOOKUP(M$1,INDIRECT("'"&$A21&"'!$A$12:$Z$19"),MATCH("Points (Auto-generate)",INDIRECT("'"&$A21&"'!$A$12:$Z$12"),0),0)="","?",VLOOKUP(M$1,INDIRECT("'"&$A21&"'!$A$12:$Z$19"),MATCH("Points (Auto-generate)",INDIRECT("'"&$A21&"'!$A$12:$Z$12"),0),0)),"ER")) -> NA
A22: UPD6b | B22: =VLOOKUP($A22,'PARASTATAL Questions'!$A:$J,3,0)&"" -> Urban Planning & Design (UPD) | C22: =VLOOKUP($A22,'PARASTATAL Questions'!$A:$J,4,0)&"" -> SQ | D22: =VLOOKUP($A22,'PARASTATAL Questions'!$A:$J,5,0)&"" -> Does the transport corporation actually considers environmental sustainability in planning and delivering urban transport services and investments? | E22: =VLOOKUP($A22,'PARASTATAL Questions'!$A:$J,7,0)&"" -> Implementation | F22: =VLOOKUP($A22,'PARASTATAL Questions'!$A:$J,6,0) -> 5 | G22: =IF($F22=0,"NA",IF($A22=INDIRECT("'"&$A22&"'!$B$1"),IF(VLOOKUP(G$1,INDIRECT("'"&$A22&"'!$A$12:$Z$19"),MATCH("Points (Auto-generate)",INDIRECT("'"&$A22&"'!$A$12:$Z$12"),0),0)="","?",VLOOKUP(G$1,INDIRECT("'"&$A22&"'!$A$12:$Z$19"),MATCH("Points (Auto-generate)",INDIRECT("'"&$A22&"'!$A$12:$Z$12"),0),0)),"ER")) -> NA | H22: =IF($F22=0,"NA",IF($A22=INDIRECT("'"&$A22&"'!$B$1"),IF(VLOOKUP(H$1,INDIRECT("'"&$A22&"'!$A$12:$Z$19"),MATCH("Points (Auto-generate)",INDIRECT("'"&$A22&"'!$A$12:$Z$12"),0),0)="","?",VLOOKUP(H$1,INDIRECT("'"&$A22&"'!$A$12:$Z$19"),MATCH("Points (Auto-generate)",INDIRECT("'"&$A22&"'!$A$12:$Z$12"),0),0)),"ER")) -> ? | I22: =IF($F22=0,"NA",IF($A22=INDIRECT("'"&$A22&"'!$B$1"),IF(VLOOKUP(I$1,INDIRECT("'"&$A22&"'!$A$12:$Z$19"),MATCH("Points (Auto-generate)",INDIRECT("'"&$A22&"'!$A$12:$Z$12"),0),0)="","?",VLOOKUP(I$1,INDIRECT("'"&$A22&"'!$A$12:$Z$19"),MATCH("Points (Auto-generate)",INDIRECT("'"&$A22&"'!$A$12:$Z$12"),0),0)),"ER")) -> NA | J22: =IF($F22=0,"NA",IF($A22=INDIRECT("'"&$A22&"'!$B$1"),IF(VLOOKUP(J$1,INDIRECT("'"&$A22&"'!$A$12:$Z$19"),MATCH("Points (Auto-generate)",INDIRECT("'"&$A22&"'!$A$12:$Z$12"),0),0)="","?",VLOOKUP(J$1,INDIRECT("'"&$A22&"'!$A$12:$Z$19"),MATCH("Points (Auto-generate)",INDIRECT("'"&$A22&"'!$A$12:$Z$12"),0),0)),"ER")) -> NA | K22: =IF($F22=0,"NA",IF($A22=INDIRECT("'"&$A22&"'!$B$1"),IF(VLOOKUP(K$1,INDIRECT("'"&$A22&"'!$A$12:$Z$19"),MATCH("Points (Auto-generate)",INDIRECT("'"&$A22&"'!$A$12:$Z$12"),0),0)="","?",VLOOKUP(K$1,INDIRECT("'"&$A22&"'!$A$12:$Z$19"),MATCH("Points (Auto-generate)",INDIRECT("'"&$A22&"'!$A$12:$Z$12"),0),0)),"ER")) -> NA | L22: =IF($F22=0,"NA",IF($A22=INDIRECT("'"&$A22&"'!$B$1"),IF(VLOOKUP(L$1,INDIRECT("'"&$A22&"'!$A$12:$Z$19"),MATCH("Points (Auto-generate)",INDIRECT("'"&$A22&"'!$A$12:$Z$12"),0),0)="","?",VLOOKUP(L$1,INDIRECT("'"&$A22&"'!$A$12:$Z$19"),MATCH("Points (Auto-generate)",INDIRECT("'"&$A22&"'!$A$12:$Z$12"),0),0)),"ER")) -> NA | M22: =IF($F22=0,"NA",IF($A22=INDIRECT("'"&$A22&"'!$B$1"),IF(VLOOKUP(M$1,INDIRECT("'"&$A22&"'!$A$12:$Z$19"),MATCH("Points (Auto-generate)",INDIRECT("'"&$A22&"'!$A$12:$Z$12"),0),0)="","?",VLOOKUP(M$1,INDIRECT("'"&$A22&"'!$A$12:$Z$19"),MATCH("Points (Auto-generate)",INDIRECT("'"&$A22&"'!$A$12:$Z$12"),0),0)),"ER")) -> NA
A23: DPG1 | B23: =VLOOKUP($A23,'PARASTATAL Questions'!$A:$J,3,0)&"" -> Decentralised Participatory Governance | C23: =VLOOKUP($A23,'PARASTATAL Questions'!$A:$J,4,0)&"" -> MQ | D23: =VLOOKUP($A23,'PARASTATAL Questions'!$A:$J,5,0)&"" -> Are the functions and geographical jurisdiction of the parastatal clearly defined vis-à-vis the ULG and other relevant agencies? | E23: =VLOOKUP($A23,'PARASTATAL Questions'!$A:$J,7,0)&"" -> Law/Policy + Implementation | F23: =VLOOKUP($A23,'PARASTATAL Questions'!$A:$J,6,0) -> 10 | G23: =IF(OR(G24="ER",G25="ER"),"ER",IF(OR(G24="?",G25="?"),"?",IF(AND(G24="NA",G25="NA"),"NA",SUM(G24,G25)/((G24<>"NA")*$F$24+(G25<>"NA")*$F$25)*$F23))) -> ? | H23: =IF(OR(H24="ER",H25="ER"),"ER",IF(OR(H24="?",H25="?"),"?",IF(AND(H24="NA",H25="NA"),"NA",SUM(H24,H25)/((H24<>"NA")*$F$24+(H25<>"NA")*$F$25)*$F23))) -> ? | I23: =IF(OR(I24="ER",I25="ER"),"ER",IF(OR(I24="?",I25="?"),"?",IF(AND(I24="NA",I25="NA"),"NA",SUM(I24,I25)/((I24<>"NA")*$F$24+(I25<>"NA")*$F$25)*$F23))) -> 5 | J23: =IF(OR(J24="ER",J25="ER"),"ER",IF(OR(J24="?",J25="?"),"?",IF(AND(J24="NA",J25="NA"),"NA",SUM(J24,J25)/((J24<>"NA")*$F$24+(J25<>"NA")*$F$25)*$F23))) -> ? | K23: =IF(OR(K24="ER",K25="ER"),"ER",IF(OR(K24="?",K25="?"),"?",IF(AND(K24="NA",K25="NA"),"NA",SUM(K24,K25)/((K24<>"NA")*$F$24+(K25<>"NA")*$F$25)*$F23))) -> ? | L23: =IF(OR(L24="ER",L25="ER"),"ER",IF(OR(L24="?",L25="?"),"?",IF(AND(L24="NA",L25="NA"),"NA",SUM(L24,L25)/((L24<>"NA")*$F$24+(L25<>"NA")*$F$25)*$F23))) -> ? | M23: =IF(OR(M24="ER",M25="ER"),"ER",IF(OR(M24="?",M25="?"),"?",IF(AND(M24="NA",M25="NA"),"NA",SUM(M24,M25)/((M24<>"NA")*$F$24+(M25<>"NA")*$F$25)*$F23))) -> ?
A24: DPG1a | B24: =VLOOKUP($A24,'PARASTATAL Questions'!$A:$J,3,0)&"" -> Decentralised Participatory Governance | C24: =VLOOKUP($A24,'PARASTATAL Questions'!$A:$J,4,0)&"" -> SQ | D24: =VLOOKUP($A24,'PARASTATAL Questions'!$A:$J,5,0)&"" -> Does the law clearly demarcate the functions/responsibilities of the parastatal vis-à-vis the ULG? | E24: =VLOOKUP($A24,'PARASTATAL Questions'!$A:$J,7,0)&"" -> Law/policy | F24: =VLOOKUP($A24,'PARASTATAL Questions'!$A:$J,6,0) -> 5 | G24: =IF($F24=0,"NA",IF($A24=INDIRECT("'"&$A24&"'!$B$1"),IF(VLOOKUP(G$1,INDIRECT("'"&$A24&"'!$A$12:$Z$19"),MATCH("Points (Auto-generate)",INDIRECT("'"&$A24&"'!$A$12:$Z$12"),0),0)="","?",VLOOKUP(G$1,INDIRECT("'"&$A24&"'!$A$12:$Z$19"),MATCH("Points (Auto-generate)",INDIRECT("'"&$A24&"'!$A$12:$Z$12"),0),0)),"ER")) -> ? | H24: =IF($F24=0,"NA",IF($A24=INDIRECT("'"&$A24&"'!$B$1"),IF(VLOOKUP(H$1,INDIRECT("'"&$A24&"'!$A$12:$Z$19"),MATCH("Points (Auto-generate)",INDIRECT("'"&$A24&"'!$A$12:$Z$12"),0),0)="","?",VLOOKUP(H$1,INDIRECT("'"&$A24&"'!$A$12:$Z$19"),MATCH("Points (Auto-generate)",INDIRECT("'"&$A24&"'!$A$12:$Z$12"),0),0)),"ER")) -> ? | I24: =IF($F24=0,"NA",IF($A24=INDIRECT("'"&$A24&"'!$B$1"),IF(VLOOKUP(I$1,INDIRECT("'"&$A24&"'!$A$12:$Z$19"),MATCH("Points (Auto-generate)",INDIRECT("'"&$A24&"'!$A$12:$Z$12"),0),0)="","?",VLOOKUP(I$1,INDIRECT("'"&$A24&"'!$A$12:$Z$19"),MATCH("Points (Auto-generate)",INDIRECT("'"&$A24&"'!$A$12:$Z$12"),0),0)),"ER")) -> 0 | J24: =IF($F24=0,"NA",IF($A24=INDIRECT("'"&$A24&"'!$B$1"),IF(VLOOKUP(J$1,INDIRECT("'"&$A24&"'!$A$12:$Z$19"),MATCH("Points (Auto-generate)",INDIRECT("'"&$A24&"'!$A$12:$Z$12"),0),0)="","?",VLOOKUP(J$1,INDIRECT("'"&$A24&"'!$A$12:$Z$19"),MATCH("Points (Auto-generate)",INDIRECT("'"&$A24&"'!$A$12:$Z$12"),0),0)),"ER")) -> ? | K24: =IF($F24=0,"NA",IF($A24=INDIRECT("'"&$A24&"'!$B$1"),IF(VLOOKUP(K$1,INDIRECT("'"&$A24&"'!$A$12:$Z$19"),MATCH("Points (Auto-generate)",INDIRECT("'"&$A24&"'!$A$12:$Z$12"),0),0)="","?",VLOOKUP(K$1,INDIRECT("'"&$A24&"'!$A$12:$Z$19"),MATCH("Points (Auto-generate)",INDIRECT("'"&$A24&"'!$A$12:$Z$12"),0),0)),"ER")) -> ? | L24: =IF($F24=0,"NA",IF($A24=INDIRECT("'"&$A24&"'!$B$1"),IF(VLOOKUP(L$1,INDIRECT("'"&$A24&"'!$A$12:$Z$19"),MATCH("Points (Auto-generate)",INDIRECT("'"&$A24&"'!$A$12:$Z$12"),0),0)="","?",VLOOKUP(L$1,INDIRECT("'"&$A24&"'!$A$12:$Z$19"),MATCH("Points (Auto-generate)",INDIRECT("'"&$A24&"'!$A$12:$Z$12"),0),0)),"ER")) -> ? | M24: =IF($F24=0,"NA",IF($A24=INDIRECT("'"&$A24&"'!$B$1"),IF(VLOOKUP(M$1,INDIRECT("'"&$A24&"'!$A$12:$Z$19"),MATCH("Points (Auto-generate)",INDIRECT("'"&$A24&"'!$A$12:$Z$12"),0),0)="","?",VLOOKUP(M$1,INDIRECT("'"&$A24&"'!$A$12:$Z$19"),MATCH("Points (Auto-generate)",INDIRECT("'"&$A24&"'!$A$12:$Z$12"),0),0)),"ER")) -> ?
A25: DPG1b | B25: =VLOOKUP($A25,'PARASTATAL Questions'!$A:$J,3,0)&"" -> Decentralised Participatory Governance | C25: =VLOOKUP($A25,'PARASTATAL Questions'!$A:$J,4,0)&"" -> SQ | D25: =VLOOKUP($A25,'PARASTATAL Questions'!$A:$J,5,0)&"" -> Is the parastatal's territorial/geographic jurisdiction specifically defined in it's enabling law? | E25: =VLOOKUP($A25,'PARASTATAL Questions'!$A:$J,7,0)&"" -> Law/Policy | F25: =VLOOKUP($A25,'PARASTATAL Questions'!$A:$J,6,0) -> 5 | G25: =IF($F25=0,"NA",IF($A25=INDIRECT("'"&$A25&"'!$B$1"),IF(VLOOKUP(G$1,INDIRECT("'"&$A25&"'!$A$12:$Z$19"),MATCH("Points (Auto-generate)",INDIRECT("'"&$A25&"'!$A$12:$Z$12"),0),0)="","?",VLOOKUP(G$1,INDIRECT("'"&$A25&"'!$A$12:$Z$19"),MATCH("Points (Auto-generate)",INDIRECT("'"&$A25&"'!$A$12:$Z$12"),0),0)),"ER")) -> 5 | H25: =IF($F25=0,"NA",IF($A25=INDIRECT("'"&$A25&"'!$B$1"),IF(VLOOKUP(H$1,INDIRECT("'"&$A25&"'!$A$12:$Z$19"),MATCH("Points (Auto-generate)",INDIRECT("'"&$A25&"'!$A$12:$Z$12"),0),0)="","?",VLOOKUP(H$1,INDIRECT("'"&$A25&"'!$A$12:$Z$19"),MATCH("Points (Auto-generate)",INDIRECT("'"&$A25&"'!$A$12:$Z$12"),0),0)),"ER")) -> ? | I25: =IF($F25=0,"NA",IF($A25=INDIRECT("'"&$A25&"'!$B$1"),IF(VLOOKUP(I$1,INDIRECT("'"&$A25&"'!$A$12:$Z$19"),MATCH("Points (Auto-generate)",INDIRECT("'"&$A25&"'!$A$12:$Z$12"),0),0)="","?",VLOOKUP(I$1,INDIRECT("'"&$A25&"'!$A$12:$Z$19"),MATCH("Points (Auto-generate)",INDIRECT("'"&$A25&"'!$A$12:$Z$12"),0),0)),"ER")) -> 5 | J25: =IF($F25=0,"NA",IF($A25=INDIRECT("'"&$A25&"'!$B$1"),IF(VLOOKUP(J$1,INDIRECT("'"&$A25&"'!$A$12:$Z$19"),MATCH("Points (Auto-generate)",INDIRECT("'"&$A25&"'!$A$12:$Z$12"),0),0)="","?",VLOOKUP(J$1,INDIRECT("'"&$A25&"'!$A$12:$Z$19"),MATCH("Points (Auto-generate)",INDIRECT("'"&$A25&"'!$A$12:$Z$12"),0),0)),"ER")) -> ? | K25: =IF($F25=0,"NA",IF($A25=INDIRECT("'"&$A25&"'!$B$1"),IF(VLOOKUP(K$1,INDIRECT("'"&$A25&"'!$A$12:$Z$19"),MATCH("Points (Auto-generate)",INDIRECT("'"&$A25&"'!$A$12:$Z$12"),0),0)="","?",VLOOKUP(K$1,INDIRECT("'"&$A25&"'!$A$12:$Z$19"),MATCH("Points (Auto-generate)",INDIRECT("'"&$A25&"'!$A$12:$Z$12"),0),0)),"ER")) -> ? | L25: =IF($F25=0,"NA",IF($A25=INDIRECT("'"&$A25&"'!$B$1"),IF(VLOOKUP(L$1,INDIRECT("'"&$A25&"'!$A$12:$Z$19"),MATCH("Points (Auto-generate)",INDIRECT("'"&$A25&"'!$A$12:$Z$12"),0),0)="","?",VLOOKUP(L$1,INDIRECT("'"&$A25&"'!$A$12:$Z$19"),MATCH("Points (Auto-generate)",INDIRECT("'"&$A25&"'!$A$12:$Z$12"),0),0)),"ER")) -> ? | M25: =IF($F25=0,"NA",IF($A25=INDIRECT("'"&$A25&"'!$B$1"),IF(VLOOKUP(M$1,INDIRECT("'"&$A25&"'!$A$12:$Z$19"),MATCH("Points (Auto-generate)",INDIRECT("'"&$A25&"'!$A$12:$Z$12"),0),0)="","?",VLOOKUP(M$1,INDIRECT("'"&$A25&"'!$A$12:$Z$19"),MATCH("Points (Auto-generate)",INDIRECT("'"&$A25&"'!$A$12:$Z$12"),0),0)),"ER")) -> ?
A26: DPG2 | B26: =VLOOKUP($A26,'PARASTATAL Questions'!$A:$J,3,0)&"" -> Decentralised Participatory Governance | C26: =VLOOKUP($A26,'PARASTATAL Questions'!$A:$J,4,0)&"" -> MQ | D26: =VLOOKUP($A26,'PARASTATAL Questions'!$A:$J,5,0)&"" -> Is the parastatal accountable to the ULG? | E26: =VLOOKUP($A26,'PARASTATAL Questions'!$A:$J,7,0)&"" -> Law/Policy | F26: =VLOOKUP($A26,'PARASTATAL Questions'!$A:$J,6,0) -> 10 | G26: =IF(OR(G27="ER",G28="ER"),"ER",IF(OR(G27="?",G28="?"),"?",IF(AND(G27="NA",G28="NA"),"NA",SUM(G27,G28)/((G27<>"NA")*$F$27+(G28<>"NA")*$F$28)*$F26))) -> ? | H26: =IF(OR(H27="ER",H28="ER"),"ER",IF(OR(H27="?",H28="?"),"?",IF(AND(H27="NA",H28="NA"),"NA",SUM(H27,H28)/((H27<>"NA")*$F$27+(H28<>"NA")*$F$28)*$F26))) -> ? | I26: =IF(OR(I27="ER",I28="ER"),"ER",IF(OR(I27="?",I28="?"),"?",IF(AND(I27="NA",I28="NA"),"NA",SUM(I27,I28)/((I27<>"NA")*$F$27+(I28<>"NA")*$F$28)*$F26))) -> ? | J26: =IF(OR(J27="ER",J28="ER"),"ER",IF(OR(J27="?",J28="?"),"?",IF(AND(J27="NA",J28="NA"),"NA",SUM(J27,J28)/((J27<>"NA")*$F$27+(J28<>"NA")*$F$28)*$F26))) -> ? | K26: =IF(OR(K27="ER",K28="ER"),"ER",IF(OR(K27="?",K28="?"),"?",IF(AND(K27="NA",K28="NA"),"NA",SUM(K27,K28)/((K27<>"NA")*$F$27+(K28<>"NA")*$F$28)*$F26))) -> ? | L26: =IF(OR(L27="ER",L28="ER"),"ER",IF(OR(L27="?",L28="?"),"?",IF(AND(L27="NA",L28="NA"),"NA",SUM(L27,L28)/((L27<>"NA")*$F$27+(L28<>"NA")*$F$28)*$F26))) -> ? | M26: =IF(OR(M27="ER",M28="ER"),"ER",IF(OR(M27="?",M28="?"),"?",IF(AND(M27="NA",M28="NA"),"NA",SUM(M27,M28)/((M27<>"NA")*$F$27+(M28<>"NA")*$F$28)*$F26))) -> ?
A27: DPG2a | B27: =VLOOKUP($A27,'PARASTATAL Questions'!$A:$J,3,0)&"" -> Decentralised Participatory Governance | C27: =VLOOKUP($A27,'PARASTATAL Questions'!$A:$J,4,0)&"" -> SQ | D27: =VLOOKUP($A27,'PARASTATAL Questions'!$A:$J,5,0)&"" -> Does the ULG have representation on the parastatal's governing board? | E27: =VLOOKUP($A27,'PARASTATAL Questions'!$A:$J,7,0)&"" -> Law/Policy | F27: =VLOOKUP($A27,'PARASTATAL Questions'!$A:$J,6,0) -> 5 | G27: =IF($F27=0,"NA",IF($A27=INDIRECT("'"&$A27&"'!$B$1"),IF(VLOOKUP(G$1,INDIRECT("'"&$A27&"'!$A$12:$Z$19"),MATCH("Points (Auto-generate)",INDIRECT("'"&$A27&"'!$A$12:$Z$12"),0),0)="","?",VLOOKUP(G$1,INDIRECT("'"&$A27&"'!$A$12:$Z$19"),MATCH("Points (Auto-generate)",INDIRECT("'"&$A27&"'!$A$12:$Z$12"),0),0)),"ER")) -> 0 | H27: =IF($F27=0,"NA",IF($A27=INDIRECT("'"&$A27&"'!$B$1"),IF(VLOOKUP(H$1,INDIRECT("'"&$A27&"'!$A$12:$Z$19"),MATCH("Points (Auto-generate)",INDIRECT("'"&$A27&"'!$A$12:$Z$12"),0),0)="","?",VLOOKUP(H$1,INDIRECT("'"&$A27&"'!$A$12:$Z$19"),MATCH("Points (Auto-generate)",INDIRECT("'"&$A27&"'!$A$12:$Z$12"),0),0)),"ER")) -> ? | I27: =IF($F27=0,"NA",IF($A27=INDIRECT("'"&$A27&"'!$B$1"),IF(VLOOKUP(I$1,INDIRECT("'"&$A27&"'!$A$12:$Z$19"),MATCH("Points (Auto-generate)",INDIRECT("'"&$A27&"'!$A$12:$Z$12"),0),0)="","?",VLOOKUP(I$1,INDIRECT("'"&$A27&"'!$A$12:$Z$19"),MATCH("Points (Auto-generate)",INDIRECT("'"&$A27&"'!$A$12:$Z$12"),0),0)),"ER")) -> 5 | J27: =IF($F27=0,"NA",IF($A27=INDIRECT("'"&$A27&"'!$B$1"),IF(VLOOKUP(J$1,INDIRECT("'"&$A27&"'!$A$12:$Z$19"),MATCH("Points (Auto-generate)",INDIRECT("'"&$A27&"'!$A$12:$Z$12"),0),0)="","?",VLOOKUP(J$1,INDIRECT("'"&$A27&"'!$A$12:$Z$19"),MATCH("Points (Auto-generate)",INDIRECT("'"&$A27&"'!$A$12:$Z$12"),0),0)),"ER")) -> ? | K27: =IF($F27=0,"NA",IF($A27=INDIRECT("'"&$A27&"'!$B$1"),IF(VLOOKUP(K$1,INDIRECT("'"&$A27&"'!$A$12:$Z$19"),MATCH("Points (Auto-generate)",INDIRECT("'"&$A27&"'!$A$12:$Z$12"),0),0)="","?",VLOOKUP(K$1,INDIRECT("'"&$A27&"'!$A$12:$Z$19"),MATCH("Points (Auto-generate)",INDIRECT("'"&$A27&"'!$A$12:$Z$12"),0),0)),"ER")) -> ? | L27: =IF($F27=0,"NA",IF($A27=INDIRECT("'"&$A27&"'!$B$1"),IF(VLOOKUP(L$1,INDIRECT("'"&$A27&"'!$A$12:$Z$19"),MATCH("Points (Auto-generate)",INDIRECT("'"&$A27&"'!$A$12:$Z$12"),0),0)="","?",VLOOKUP(L$1,INDIRECT("'"&$A27&"'!$A$12:$Z$19"),MATCH("Points (Auto-generate)",INDIRECT("'"&$A27&"'!$A$12:$Z$12"),0),0)),"ER")) -> ? | M27: =IF($F27=0,"NA",IF($A27=INDIRECT("'"&$A27&"'!$B$1"),IF(VLOOKUP(M$1,INDIRECT("'"&$A27&"'!$A$12:$Z$19"),MATCH("Points (Auto-generate)",INDIRECT("'"&$A27&"'!$A$12:$Z$12"),0),0)="","?",VLOOKUP(M$1,INDIRECT("'"&$A27&"'!$A$12:$Z$19"),MATCH("Points (Auto-generate)",INDIRECT("'"&$A27&"'!$A$12:$Z$12"),0),0)),"ER")) -> ?
A28: DPG2b | B28: =VLOOKUP($A28,'PARASTATAL Questions'!$A:$J,3,0)&"" -> Decentralised Participatory Governance | C28: =VLOOKUP($A28,'PARASTATAL Questions'!$A:$J,4,0)&"" -> SQ | D28: =VLOOKUP($A28,'PARASTATAL Questions'!$A:$J,5,0)&"" -> Is the parastatal mandated to submit its plans, budgets or reports to the ULG/council? | E28: =VLOOKUP($A28,'PARASTATAL Questions'!$A:$J,7,0)&"" -> Law/Policy | F28: =VLOOKUP($A28,'PARASTATAL Questions'!$A:$J,6,0) -> 5 | G28: =IF($F28=0,"NA",IF($A28=INDIRECT("'"&$A28&"'!$B$1"),IF(VLOOKUP(G$1,INDIRECT("'"&$A28&"'!$A$12:$Z$19"),MATCH("Points (Auto-generate)",INDIRECT("'"&$A28&"'!$A$12:$Z$12"),0),0)="","?",VLOOKUP(G$1,INDIRECT("'"&$A28&"'!$A$12:$Z$19"),MATCH("Points (Auto-generate)",INDIRECT("'"&$A28&"'!$A$12:$Z$12"),0),0)),"ER")) -> ? | H28: =IF($F28=0,"NA",IF($A28=INDIRECT("'"&$A28&"'!$B$1"),IF(VLOOKUP(H$1,INDIRECT("'"&$A28&"'!$A$12:$Z$19"),MATCH("Points (Auto-generate)",INDIRECT("'"&$A28&"'!$A$12:$Z$12"),0),0)="","?",VLOOKUP(H$1,INDIRECT("'"&$A28&"'!$A$12:$Z$19"),MATCH("Points (Auto-generate)",INDIRECT("'"&$A28&"'!$A$12:$Z$12"),0),0)),"ER")) -> ? | I28: =IF($F28=0,"NA",IF($A28=INDIRECT("'"&$A28&"'!$B$1"),IF(VLOOKUP(I$1,INDIRECT("'"&$A28&"'!$A$12:$Z$19"),MATCH("Points (Auto-generate)",INDIRECT("'"&$A28&"'!$A$12:$Z$12"),0),0)="","?",VLOOKUP(I$1,INDIRECT("'"&$A28&"'!$A$12:$Z$19"),MATCH("Points (Auto-generate)",INDIRECT("'"&$A28&"'!$A$12:$Z$12"),0),0)),"ER")) -> ? | J28: =IF($F28=0,"NA",IF($A28=INDIRECT("'"&$A28&"'!$B$1"),IF(VLOOKUP(J$1,INDIRECT("'"&$A28&"'!$A$12:$Z$19"),MATCH("Points (Auto-generate)",INDIRECT("'"&$A28&"'!$A$12:$Z$12"),0),0)="","?",VLOOKUP(J$1,INDIRECT("'"&$A28&"'!$A$12:$Z$19"),MATCH("Points (Auto-generate)",INDIRECT("'"&$A28&"'!$A$12:$Z$12"),0),0)),"ER")) -> ? | K28: =IF($F28=0,"NA",IF($A28=INDIRECT("'"&$A28&"'!$B$1"),IF(VLOOKUP(K$1,INDIRECT("'"&$A28&"'!$A$12:$Z$19"),MATCH("Points (Auto-generate)",INDIRECT("'"&$A28&"'!$A$12:$Z$12"),0),0)="","?",VLOOKUP(K$1,INDIRECT("'"&$A28&"'!$A$12:$Z$19"),MATCH("Points (Auto-generate)",INDIRECT("'"&$A28&"'!$A$12:$Z$12"),0),0)),"ER")) -> ? | L28: =IF($F28=0,"NA",IF($A28=INDIRECT("'"&$A28&"'!$B$1"),IF(VLOOKUP(L$1,INDIRECT("'"&$A28&"'!$A$12:$Z$19"),MATCH("Points (Auto-generate)",INDIRECT("'"&$A28&"'!$A$12:$Z$12"),0),0)="","?",VLOOKUP(L$1,INDIRECT("'"&$A28&"'!$A$12:$Z$19"),MATCH("Points (Auto-generate)",INDIRECT("'"&$A28&"'!$A$12:$Z$12"),0),0)),"ER")) -> ? | M28: =IF($F28=0,"NA",IF($A28=INDIRECT("'"&$A28&"'!$B$1"),IF(VLOOKUP(M$1,INDIRECT("'"&$A28&"'!$A$12:$Z$19"),MATCH("Points (Auto-generate)",INDIRECT("'"&$A28&"'!$A$12:$Z$12"),0),0)="","?",VLOOKUP(M$1,INDIRECT("'"&$A28&"'!$A$12:$Z$19"),MATCH("Points (Auto-generate)",INDIRECT("'"&$A28&"'!$A$12:$Z$12"),0),0)),"ER")) -> ?
A29: DPG3 | B29: =VLOOKUP($A29,'PARASTATAL Questions'!$A:$J,3,0)&"" -> Decentralised Participatory Governance | C29: =VLOOKUP($A29,'PARASTATAL Questions'!$A:$J,4,0)&"" -> MQ | D29: =VLOOKUP($A29,'PARASTATAL Questions'!$A:$J,5,0)&"" -> Does the parastatal maintain an active and functional website? | E29: =VLOOKUP($A29,'PARASTATAL Questions'!$A:$J,7,0)&"" -> Implementation | F29: =VLOOKUP($A29,'PARASTATAL Questions'!$A:$J,6,0) -> 10 | G29: =IF($F29=0,"NA",IF($A29=INDIRECT("'"&$A29&"'!$B$1"),IF(VLOOKUP(G$1,INDIRECT("'"&$A29&"'!$A$12:$Z$19"),MATCH("Points (Auto-generate)",INDIRECT("'"&$A29&"'!$A$12:$Z$12"),0),0)="","?",VLOOKUP(G$1,INDIRECT("'"&$A29&"'!$A$12:$Z$19"),MATCH("Points (Auto-generate)",INDIRECT("'"&$A29&"'!$A$12:$Z$12"),0),0)),"ER")) -> ? | H29: =IF($F29=0,"NA",IF($A29=INDIRECT("'"&$A29&"'!$B$1"),IF(VLOOKUP(H$1,INDIRECT("'"&$A29&"'!$A$12:$Z$19"),MATCH("Points (Auto-generate)",INDIRECT("'"&$A29&"'!$A$12:$Z$12"),0),0)="","?",VLOOKUP(H$1,INDIRECT("'"&$A29&"'!$A$12:$Z$19"),MATCH("Points (Auto-generate)",INDIRECT("'"&$A29&"'!$A$12:$Z$12"),0),0)),"ER")) -> ? | I29: =IF($F29=0,"NA",IF($A29=INDIRECT("'"&$A29&"'!$B$1"),IF(VLOOKUP(I$1,INDIRECT("'"&$A29&"'!$A$12:$Z$19"),MATCH("Points (Auto-generate)",INDIRECT("'"&$A29&"'!$A$12:$Z$12"),0),0)="","?",VLOOKUP(I$1,INDIRECT("'"&$A29&"'!$A$12:$Z$19"),MATCH("Points (Auto-generate)",INDIRECT("'"&$A29&"'!$A$12:$Z$12"),0),0)),"ER")) -> ? | J29: =IF($F29=0,"NA",IF($A29=INDIRECT("'"&$A29&"'!$B$1"),IF(VLOOKUP(J$1,INDIRECT("'"&$A29&"'!$A$12:$Z$19"),MATCH("Points (Auto-generate)",INDIRECT("'"&$A29&"'!$A$12:$Z$12"),0),0)="","?",VLOOKUP(J$1,INDIRECT("'"&$A29&"'!$A$12:$Z$19"),MATCH("Points (Auto-generate)",INDIRECT("'"&$A29&"'!$A$12:$Z$12"),0),0)),"ER")) -> ? | K29: =IF($F29=0,"NA",IF($A29=INDIRECT("'"&$A29&"'!$B$1"),IF(VLOOKUP(K$1,INDIRECT("'"&$A29&"'!$A$12:$Z$19"),MATCH("Points (Auto-generate)",INDIRECT("'"&$A29&"'!$A$12:$Z$12"),0),0)="","?",VLOOKUP(K$1,INDIRECT("'"&$A29&"'!$A$12:$Z$19"),MATCH("Points (Auto-generate)",INDIRECT("'"&$A29&"'!$A$12:$Z$12"),0),0)),"ER")) -> ? | L29: =IF($F29=0,"NA",IF($A29=INDIRECT("'"&$A29&"'!$B$1"),IF(VLOOKUP(L$1,INDIRECT("'"&$A29&"'!$A$12:$Z$19"),MATCH("Points (Auto-generate)",INDIRECT("'"&$A29&"'!$A$12:$Z$12"),0),0)="","?",VLOOKUP(L$1,INDIRECT("'"&$A29&"'!$A$12:$Z$19"),MATCH("Points (Auto-generate)",INDIRECT("'"&$A29&"'!$A$12:$Z$12"),0),0)),"ER")) -> ? | M29: =IF($F29=0,"NA",IF($A29=INDIRECT("'"&$A29&"'!$B$1"),IF(VLOOKUP(M$1,INDIRECT("'"&$A29&"'!$A$12:$Z$19"),MATCH("Points (Auto-generate)",INDIRECT("'"&$A29&"'!$A$12:$Z$12"),0),0)="","?",VLOOKUP(M$1,INDIRECT("'"&$A29&"'!$A$12:$Z$19"),MATCH("Points (Auto-generate)",INDIRECT("'"&$A29&"'!$A$12:$Z$12"),0),0)),"ER")) -> ?
A30: DPG5 | B30: =VLOOKUP($A30,'PARASTATAL Questions'!$A:$J,3,0)&"" -> Decentralised Participatory Governance | C30: =VLOOKUP($A30,'PARASTATAL Questions'!$A:$J,4,0)&"" -> MQ | D30: =VLOOKUP($A30,'PARASTATAL Questions'!$A:$J,5,0)&"" -> Are the parastatal's key financial, operational, and civic data/information available on the website and published in accessible, open-data formats? | E30: =VLOOKUP($A30,'PARASTATAL Questions'!$A:$J,7,0)&"" -> Implementation | F30: =VLOOKUP($A30,'PARASTATAL Questions'!$A:$J,6,0) -> 10 | G30: =IF(OR(G31="ER",G32="ER",G33="ER",G34="ER",G35="ER",G36="ER",G37="ER",G38="ER",G39="ER",G40="ER"),"ER",IF(OR(G31="?",G32="?",G33="?",G34="?",G35="?",G36="?",G37="?",G38="?",G39="?",G40="?"),"?",IF(AND(G31="NA",G32="NA",G33="NA",G34="NA",G35="NA",G36="NA",G37="NA",G38="NA",G39="NA",G40="NA"),"NA",SUM(G31,G32,G33,G34,G35,G36,G37,G38,G39,G40)/((G31<>"NA")*$F$31+(G32<>"NA")*$F$32+(G33<>"NA")*$F$33+(G34<>"NA")*$F$34+(G35<>"NA")*$F$35+(G36<>"NA")*$F$36+(G37<>"NA")*$F$37+(G38<>"NA")*$F$38+(G39<>"NA")*$F$39+(G40<>"NA")*$F$40)*$F30))) -> ? | H30: =IF(OR(H31="ER",H32="ER",H33="ER",H34="ER",H35="ER",H36="ER",H37="ER",H38="ER",H39="ER",H40="ER"),"ER",IF(OR(H31="?",H32="?",H33="?",H34="?",H35="?",H36="?",H37="?",H38="?",H39="?",H40="?"),"?",IF(AND(H31="NA",H32="NA",H33="NA",H34="NA",H35="NA",H36="NA",H37="NA",H38="NA",H39="NA",H40="NA"),"NA",SUM(H31,H32,H33,H34,H35,H36,H37,H38,H39,H40)/((H31<>"NA")*$F$31+(H32<>"NA")*$F$32+(H33<>"NA")*$F$33+(H34<>"NA")*$F$34+(H35<>"NA")*$F$35+(H36<>"NA")*$F$36+(H37<>"NA")*$F$37+(H38<>"NA")*$F$38+(H39<>"NA")*$F$39+(H40<>"NA")*$F$40)*$F30))) -> ? | I30: =IF(OR(I31="ER",I32="ER",I33="ER",I34="ER",I35="ER",I36="ER",I37="ER",I38="ER",I39="ER",I40="ER"),"ER",IF(OR(I31="?",I32="?",I33="?",I34="?",I35="?",I36="?",I37="?",I38="?",I39="?",I40="?"),"?",IF(AND(I31="NA",I32="NA",I33="NA",I34="NA",I35="NA",I36="NA",I37="NA",I38="NA",I39="NA",I40="NA"),"NA",SUM(I31,I32,I33,I34,I35,I36,I37,I38,I39,I40)/((I31<>"NA")*$F$31+(I32<>"NA")*$F$32+(I33<>"NA")*$F$33+(I34<>"NA")*$F$34+(I35<>"NA")*$F$35+(I36<>"NA")*$F$36+(I37<>"NA")*$F$37+(I38<>"NA")*$F$38+(I39<>"NA")*$F$39+(I40<>"NA")*$F$40)*$F30))) -> ? | J30: =IF(OR(J31="ER",J32="ER",J33="ER",J34="ER",J35="ER",J36="ER",J37="ER",J38="ER",J39="ER",J40="ER"),"ER",IF(OR(J31="?",J32="?",J33="?",J34="?",J35="?",J36="?",J37="?",J38="?",J39="?",J40="?"),"?",IF(AND(J31="NA",J32="NA",J33="NA",J34="NA",J35="NA",J36="NA",J37="NA",J38="NA",J39="NA",J40="NA"),"NA",SUM(J31,J32,J33,J34,J35,J36,J37,J38,J39,J40)/((J31<>"NA")*$F$31+(J32<>"NA")*$F$32+(J33<>"NA")*$F$33+(J34<>"NA")*$F$34+(J35<>"NA")*$F$35+(J36<>"NA")*$F$36+(J37<>"NA")*$F$37+(J38<>"NA")*$F$38+(J39<>"NA")*$F$39+(J40<>"NA")*$F$40)*$F30))) -> ? | K30: =IF(OR(K31="ER",K32="ER",K33="ER",K34="ER",K35="ER",K36="ER",K37="ER",K38="ER",K39="ER",K40="ER"),"ER",IF(OR(K31="?",K32="?",K33="?",K34="?",K35="?",K36="?",K37="?",K38="?",K39="?",K40="?"),"?",IF(AND(K31="NA",K32="NA",K33="NA",K34="NA",K35="NA",K36="NA",K37="NA",K38="NA",K39="NA",K40="NA"),"NA",SUM(K31,K32,K33,K34,K35,K36,K37,K38,K39,K40)/((K31<>"NA")*$F$31+(K32<>"NA")*$F$32+(K33<>"NA")*$F$33+(K34<>"NA")*$F$34+(K35<>"NA")*$F$35+(K36<>"NA")*$F$36+(K37<>"NA")*$F$37+(K38<>"NA")*$F$38+(K39<>"NA")*$F$39+(K40<>"NA")*$F$40)*$F30))) -> ? | L30: =IF(OR(L31="ER",L32="ER",L33="ER",L34="ER",L35="ER",L36="ER",L37="ER",L38="ER",L39="ER",L40="ER"),"ER",IF(OR(L31="?",L32="?",L33="?",L34="?",L35="?",L36="?",L37="?",L38="?",L39="?",L40="?"),"?",IF(AND(L31="NA",L32="NA",L33="NA",L34="NA",L35="NA",L36="NA",L37="NA",L38="NA",L39="NA",L40="NA"),"NA",SUM(L31,L32,L33,L34,L35,L36,L37,L38,L39,L40)/((L31<>"NA")*$F$31+(L32<>"NA")*$F$32+(L33<>"NA")*$F$33+(L34<>"NA")*$F$34+(L35<>"NA")*$F$35+(L36<>"NA")*$F$36+(L37<>"NA")*$F$37+(L38<>"NA")*$F$38+(L39<>"NA")*$F$39+(L40<>"NA")*$F$40)*$F30))) -> ? | M30: =IF(OR(M31="ER",M32="ER",M33="ER",M34="ER",M35="ER",M36="ER",M37="ER",M38="ER",M39="ER",M40="ER"),"ER",IF(OR(M31="?",M32="?",M33="?",M34="?",M35="?",M36="?",M37="?",M38="?",M39="?",M40="?"),"?",IF(AND(M31="NA",M32="NA",M33="NA",M34="NA",M35="NA",M36="NA",M37="NA",M38="NA",M39="NA",M40="NA"),"NA",SUM(M31,M32,M33,M34,M35,M36,M37,M38,M39,M40)/((M31<>"NA")*$F$31+(M32<>"NA")*$F$32+(M33<>"NA")*$F$33+(M34<>"NA")*$F$34+(M35<>"NA")*$F$35+(M36<>"NA")*$F$36+(M37<>"NA")*$F$37+(M38<>"NA")*$F$38+(M39<>"NA")*$F$39+(M40<>"NA")*$F$40)*$F30))) -> ?
A31: DPG5a | B31: =VLOOKUP($A31,'PARASTATAL Questions'!$A:$J,3,0)&"" -> Decentralised Participatory Governance | C31: =VLOOKUP($A31,'PARASTATAL Questions'!$A:$J,4,0)&"" -> SQ | D31: =VLOOKUP($A31,'PARASTATAL Questions'!$A:$J,5,0)&"" -> Annual budget | E31: =VLOOKUP($A31,'PARASTATAL Questions'!$A:$J,7,0)&"" -> Implementation | F31: =VLOOKUP($A31,'PARASTATAL Questions'!$A:$J,6,0) -> 1 | G31: =IF($F31=0,"NA",IF($A31=INDIRECT("'"&$A31&"'!$B$1"),IF(VLOOKUP(G$1,INDIRECT("'"&$A31&"'!$A$12:$Z$19"),MATCH("Points (Auto-generate)",INDIRECT("'"&$A31&"'!$A$12:$Z$12"),0),0)="","?",VLOOKUP(G$1,INDIRECT("'"&$A31&"'!$A$12:$Z$19"),MATCH("Points (Auto-generate)",INDIRECT("'"&$A31&"'!$A$12:$Z$12"),0),0)),"ER")) -> ? | H31: =IF($F31=0,"NA",IF($A31=INDIRECT("'"&$A31&"'!$B$1"),IF(VLOOKUP(H$1,INDIRECT("'"&$A31&"'!$A$12:$Z$19"),MATCH("Points (Auto-generate)",INDIRECT("'"&$A31&"'!$A$12:$Z$12"),0),0)="","?",VLOOKUP(H$1,INDIRECT("'"&$A31&"'!$A$12:$Z$19"),MATCH("Points (Auto-generate)",INDIRECT("'"&$A31&"'!$A$12:$Z$12"),0),0)),"ER")) -> ? | I31: =IF($F31=0,"NA",IF($A31=INDIRECT("'"&$A31&"'!$B$1"),IF(VLOOKUP(I$1,INDIRECT("'"&$A31&"'!$A$12:$Z$19"),MATCH("Points (Auto-generate)",INDIRECT("'"&$A31&"'!$A$12:$Z$12"),0),0)="","?",VLOOKUP(I$1,INDIRECT("'"&$A31&"'!$A$12:$Z$19"),MATCH("Points (Auto-generate)",INDIRECT("'"&$A31&"'!$A$12:$Z$12"),0),0)),"ER")) -> ? | J31: =IF($F31=0,"NA",IF($A31=INDIRECT("'"&$A31&"'!$B$1"),IF(VLOOKUP(J$1,INDIRECT("'"&$A31&"'!$A$12:$Z$19"),MATCH("Points (Auto-generate)",INDIRECT("'"&$A31&"'!$A$12:$Z$12"),0),0)="","?",VLOOKUP(J$1,INDIRECT("'"&$A31&"'!$A$12:$Z$19"),MATCH("Points (Auto-generate)",INDIRECT("'"&$A31&"'!$A$12:$Z$12"),0),0)),"ER")) -> ? | K31: =IF($F31=0,"NA",IF($A31=INDIRECT("'"&$A31&"'!$B$1"),IF(VLOOKUP(K$1,INDIRECT("'"&$A31&"'!$A$12:$Z$19"),MATCH("Points (Auto-generate)",INDIRECT("'"&$A31&"'!$A$12:$Z$12"),0),0)="","?",VLOOKUP(K$1,INDIRECT("'"&$A31&"'!$A$12:$Z$19"),MATCH("Points (Auto-generate)",INDIRECT("'"&$A31&"'!$A$12:$Z$12"),0),0)),"ER")) -> ? | L31: =IF($F31=0,"NA",IF($A31=INDIRECT("'"&$A31&"'!$B$1"),IF(VLOOKUP(L$1,INDIRECT("'"&$A31&"'!$A$12:$Z$19"),MATCH("Points (Auto-generate)",INDIRECT("'"&$A31&"'!$A$12:$Z$12"),0),0)="","?",VLOOKUP(L$1,INDIRECT("'"&$A31&"'!$A$12:$Z$19"),MATCH("Points (Auto-generate)",INDIRECT("'"&$A31&"'!$A$12:$Z$12"),0),0)),"ER")) -> ? | M31: =IF($F31=0,"NA",IF($A31=INDIRECT("'"&$A31&"'!$B$1"),IF(VLOOKUP(M$1,INDIRECT("'"&$A31&"'!$A$12:$Z$19"),MATCH("Points (Auto-generate)",INDIRECT("'"&$A31&"'!$A$12:$Z$12"),0),0)="","?",VLOOKUP(M$1,INDIRECT("'"&$A31&"'!$A$12:$Z$19"),MATCH("Points (Auto-generate)",INDIRECT("'"&$A31&"'!$A$12:$Z$12"),0),0)),"ER")) -> ?
A32: DPG5b | B32: =VLOOKUP($A32,'PARASTATAL Questions'!$A:$J,3,0)&"" -> Decentralised Participatory Governance | C32: =VLOOKUP($A32,'PARASTATAL Questions'!$A:$J,4,0)&"" -> SQ | D32: =VLOOKUP($A32,'PARASTATAL Questions'!$A:$J,5,0)&"" -> Audited annual account | E32: =VLOOKUP($A32,'PARASTATAL Questions'!$A:$J,7,0)&"" -> Implementation | F32: =VLOOKUP($A32,'PARASTATAL Questions'!$A:$J,6,0) -> 1 | G32: =IF($F32=0,"NA",IF($A32=INDIRECT("'"&$A32&"'!$B$1"),IF(VLOOKUP(G$1,INDIRECT("'"&$A32&"'!$A$12:$Z$19"),MATCH("Points (Auto-generate)",INDIRECT("'"&$A32&"'!$A$12:$Z$12"),0),0)="","?",VLOOKUP(G$1,INDIRECT("'"&$A32&"'!$A$12:$Z$19"),MATCH("Points (Auto-generate)",INDIRECT("'"&$A32&"'!$A$12:$Z$12"),0),0)),"ER")) -> ? | H32: =IF($F32=0,"NA",IF($A32=INDIRECT("'"&$A32&"'!$B$1"),IF(VLOOKUP(H$1,INDIRECT("'"&$A32&"'!$A$12:$Z$19"),MATCH("Points (Auto-generate)",INDIRECT("'"&$A32&"'!$A$12:$Z$12"),0),0)="","?",VLOOKUP(H$1,INDIRECT("'"&$A32&"'!$A$12:$Z$19"),MATCH("Points (Auto-generate)",INDIRECT("'"&$A32&"'!$A$12:$Z$12"),0),0)),"ER")) -> ? | I32: =IF($F32=0,"NA",IF($A32=INDIRECT("'"&$A32&"'!$B$1"),IF(VLOOKUP(I$1,INDIRECT("'"&$A32&"'!$A$12:$Z$19"),MATCH("Points (Auto-generate)",INDIRECT("'"&$A32&"'!$A$12:$Z$12"),0),0)="","?",VLOOKUP(I$1,INDIRECT("'"&$A32&"'!$A$12:$Z$19"),MATCH("Points (Auto-generate)",INDIRECT("'"&$A32&"'!$A$12:$Z$12"),0),0)),"ER")) -> ? | J32: =IF($F32=0,"NA",IF($A32=INDIRECT("'"&$A32&"'!$B$1"),IF(VLOOKUP(J$1,INDIRECT("'"&$A32&"'!$A$12:$Z$19"),MATCH("Points (Auto-generate)",INDIRECT("'"&$A32&"'!$A$12:$Z$12"),0),0)="","?",VLOOKUP(J$1,INDIRECT("'"&$A32&"'!$A$12:$Z$19"),MATCH("Points (Auto-generate)",INDIRECT("'"&$A32&"'!$A$12:$Z$12"),0),0)),"ER")) -> ? | K32: =IF($F32=0,"NA",IF($A32=INDIRECT("'"&$A32&"'!$B$1"),IF(VLOOKUP(K$1,INDIRECT("'"&$A32&"'!$A$12:$Z$19"),MATCH("Points (Auto-generate)",INDIRECT("'"&$A32&"'!$A$12:$Z$12"),0),0)="","?",VLOOKUP(K$1,INDIRECT("'"&$A32&"'!$A$12:$Z$19"),MATCH("Points (Auto-generate)",INDIRECT("'"&$A32&"'!$A$12:$Z$12"),0),0)),"ER")) -> ? | L32: =IF($F32=0,"NA",IF($A32=INDIRECT("'"&$A32&"'!$B$1"),IF(VLOOKUP(L$1,INDIRECT("'"&$A32&"'!$A$12:$Z$19"),MATCH("Points (Auto-generate)",INDIRECT("'"&$A32&"'!$A$12:$Z$12"),0),0)="","?",VLOOKUP(L$1,INDIRECT("'"&$A32&"'!$A$12:$Z$19"),MATCH("Points (Auto-generate)",INDIRECT("'"&$A32&"'!$A$12:$Z$12"),0),0)),"ER")) -> ? | M32: =IF($F32=0,"NA",IF($A32=INDIRECT("'"&$A32&"'!$B$1"),IF(VLOOKUP(M$1,INDIRECT("'"&$A32&"'!$A$12:$Z$19"),MATCH("Points (Auto-generate)",INDIRECT("'"&$A32&"'!$A$12:$Z$12"),0),0)="","?",VLOOKUP(M$1,INDIRECT("'"&$A32&"'!$A$12:$Z$19"),MATCH("Points (Auto-generate)",INDIRECT("'"&$A32&"'!$A$12:$Z$12"),0),0)),"ER")) -> ?
A33: DPG5c | B33: =VLOOKUP($A33,'PARASTATAL Questions'!$A:$J,3,0)&"" -> Decentralised Participatory Governance | C33: =VLOOKUP($A33,'PARASTATAL Questions'!$A:$J,4,0)&"" -> SQ | D33: =VLOOKUP($A33,'PARASTATAL Questions'!$A:$J,5,0)&"" -> Annual report | E33: =VLOOKUP($A33,'PARASTATAL Questions'!$A:$J,7,0)&"" -> Implementation | F33: =VLOOKUP($A33,'PARASTATAL Questions'!$A:$J,6,0) -> 1 | G33: =IF($F33=0,"NA",IF($A33=INDIRECT("'"&$A33&"'!$B$1"),IF(VLOOKUP(G$1,INDIRECT("'"&$A33&"'!$A$12:$Z$19"),MATCH("Points (Auto-generate)",INDIRECT("'"&$A33&"'!$A$12:$Z$12"),0),0)="","?",VLOOKUP(G$1,INDIRECT("'"&$A33&"'!$A$12:$Z$19"),MATCH("Points (Auto-generate)",INDIRECT("'"&$A33&"'!$A$12:$Z$12"),0),0)),"ER")) -> ? | H33: =IF($F33=0,"NA",IF($A33=INDIRECT("'"&$A33&"'!$B$1"),IF(VLOOKUP(H$1,INDIRECT("'"&$A33&"'!$A$12:$Z$19"),MATCH("Points (Auto-generate)",INDIRECT("'"&$A33&"'!$A$12:$Z$12"),0),0)="","?",VLOOKUP(H$1,INDIRECT("'"&$A33&"'!$A$12:$Z$19"),MATCH("Points (Auto-generate)",INDIRECT("'"&$A33&"'!$A$12:$Z$12"),0),0)),"ER")) -> ? | I33: =IF($F33=0,"NA",IF($A33=INDIRECT("'"&$A33&"'!$B$1"),IF(VLOOKUP(I$1,INDIRECT("'"&$A33&"'!$A$12:$Z$19"),MATCH("Points (Auto-generate)",INDIRECT("'"&$A33&"'!$A$12:$Z$12"),0),0)="","?",VLOOKUP(I$1,INDIRECT("'"&$A33&"'!$A$12:$Z$19"),MATCH("Points (Auto-generate)",INDIRECT("'"&$A33&"'!$A$12:$Z$12"),0),0)),"ER")) -> ? | J33: =IF($F33=0,"NA",IF($A33=INDIRECT("'"&$A33&"'!$B$1"),IF(VLOOKUP(J$1,INDIRECT("'"&$A33&"'!$A$12:$Z$19"),MATCH("Points (Auto-generate)",INDIRECT("'"&$A33&"'!$A$12:$Z$12"),0),0)="","?",VLOOKUP(J$1,INDIRECT("'"&$A33&"'!$A$12:$Z$19"),MATCH("Points (Auto-generate)",INDIRECT("'"&$A33&"'!$A$12:$Z$12"),0),0)),"ER")) -> ? | K33: =IF($F33=0,"NA",IF($A33=INDIRECT("'"&$A33&"'!$B$1"),IF(VLOOKUP(K$1,INDIRECT("'"&$A33&"'!$A$12:$Z$19"),MATCH("Points (Auto-generate)",INDIRECT("'"&$A33&"'!$A$12:$Z$12"),0),0)="","?",VLOOKUP(K$1,INDIRECT("'"&$A33&"'!$A$12:$Z$19"),MATCH("Points (Auto-generate)",INDIRECT("'"&$A33&"'!$A$12:$Z$12"),0),0)),"ER")) -> 0 | L33: =IF($F33=0,"NA",IF($A33=INDIRECT("'"&$A33&"'!$B$1"),IF(VLOOKUP(L$1,INDIRECT("'"&$A33&"'!$A$12:$Z$19"),MATCH("Points (Auto-generate)",INDIRECT("'"&$A33&"'!$A$12:$Z$12"),0),0)="","?",VLOOKUP(L$1,INDIRECT("'"&$A33&"'!$A$12:$Z$19"),MATCH("Points (Auto-generate)",INDIRECT("'"&$A33&"'!$A$12:$Z$12"),0),0)),"ER")) -> ? | M33: =IF($F33=0,"NA",IF($A33=INDIRECT("'"&$A33&"'!$B$1"),IF(VLOOKUP(M$1,INDIRECT("'"&$A33&"'!$A$12:$Z$19"),MATCH("Points (Auto-generate)",INDIRECT("'"&$A33&"'!$A$12:$Z$12"),0),0)="","?",VLOOKUP(M$1,INDIRECT("'"&$A33&"'!$A$12:$Z$19"),MATCH("Points (Auto-generate)",INDIRECT("'"&$A33&"'!$A$12:$Z$12"),0),0)),"ER")) -> ?
A34: DPG5d | B34: =VLOOKUP($A34,'PARASTATAL Questions'!$A:$J,3,0)&"" -> Decentralised Participatory Governance | C34: =VLOOKUP($A34,'PARASTATAL Questions'!$A:$J,4,0)&"" -> SQ | D34: =VLOOKUP($A34,'PARASTATAL Questions'!$A:$J,5,0)&"" -> Annual Audit Report | E34: =VLOOKUP($A34,'PARASTATAL Questions'!$A:$J,7,0)&"" -> Implementation | F34: =VLOOKUP($A34,'PARASTATAL Questions'!$A:$J,6,0) -> 1 | G34: =IF($F34=0,"NA",IF($A34=INDIRECT("'"&$A34&"'!$B$1"),IF(VLOOKUP(G$1,INDIRECT("'"&$A34&"'!$A$12:$Z$19"),MATCH("Points (Auto-generate)",INDIRECT("'"&$A34&"'!$A$12:$Z$12"),0),0)="","?",VLOOKUP(G$1,INDIRECT("'"&$A34&"'!$A$12:$Z$19"),MATCH("Points (Auto-generate)",INDIRECT("'"&$A34&"'!$A$12:$Z$12"),0),0)),"ER")) -> ? | H34: =IF($F34=0,"NA",IF($A34=INDIRECT("'"&$A34&"'!$B$1"),IF(VLOOKUP(H$1,INDIRECT("'"&$A34&"'!$A$12:$Z$19"),MATCH("Points (Auto-generate)",INDIRECT("'"&$A34&"'!$A$12:$Z$12"),0),0)="","?",VLOOKUP(H$1,INDIRECT("'"&$A34&"'!$A$12:$Z$19"),MATCH("Points (Auto-generate)",INDIRECT("'"&$A34&"'!$A$12:$Z$12"),0),0)),"ER")) -> ? | I34: =IF($F34=0,"NA",IF($A34=INDIRECT("'"&$A34&"'!$B$1"),IF(VLOOKUP(I$1,INDIRECT("'"&$A34&"'!$A$12:$Z$19"),MATCH("Points (Auto-generate)",INDIRECT("'"&$A34&"'!$A$12:$Z$12"),0),0)="","?",VLOOKUP(I$1,INDIRECT("'"&$A34&"'!$A$12:$Z$19"),MATCH("Points (Auto-generate)",INDIRECT("'"&$A34&"'!$A$12:$Z$12"),0),0)),"ER")) -> ? | J34: =IF($F34=0,"NA",IF($A34=INDIRECT("'"&$A34&"'!$B$1"),IF(VLOOKUP(J$1,INDIRECT("'"&$A34&"'!$A$12:$Z$19"),MATCH("Points (Auto-generate)",INDIRECT("'"&$A34&"'!$A$12:$Z$12"),0),0)="","?",VLOOKUP(J$1,INDIRECT("'"&$A34&"'!$A$12:$Z$19"),MATCH("Points (Auto-generate)",INDIRECT("'"&$A34&"'!$A$12:$Z$12"),0),0)),"ER")) -> ? | K34: =IF($F34=0,"NA",IF($A34=INDIRECT("'"&$A34&"'!$B$1"),IF(VLOOKUP(K$1,INDIRECT("'"&$A34&"'!$A$12:$Z$19"),MATCH("Points (Auto-generate)",INDIRECT("'"&$A34&"'!$A$12:$Z$12"),0),0)="","?",VLOOKUP(K$1,INDIRECT("'"&$A34&"'!$A$12:$Z$19"),MATCH("Points (Auto-generate)",INDIRECT("'"&$A34&"'!$A$12:$Z$12"),0),0)),"ER")) -> ? | L34: =IF($F34=0,"NA",IF($A34=INDIRECT("'"&$A34&"'!$B$1"),IF(VLOOKUP(L$1,INDIRECT("'"&$A34&"'!$A$12:$Z$19"),MATCH("Points (Auto-generate)",INDIRECT("'"&$A34&"'!$A$12:$Z$12"),0),0)="","?",VLOOKUP(L$1,INDIRECT("'"&$A34&"'!$A$12:$Z$19"),MATCH("Points (Auto-generate)",INDIRECT("'"&$A34&"'!$A$12:$Z$12"),0),0)),"ER")) -> ? | M34: =IF($F34=0,"NA",IF($A34=INDIRECT("'"&$A34&"'!$B$1"),IF(VLOOKUP(M$1,INDIRECT("'"&$A34&"'!$A$12:$Z$19"),MATCH("Points (Auto-generate)",INDIRECT("'"&$A34&"'!$A$12:$Z$12"),0),0)="","?",VLOOKUP(M$1,INDIRECT("'"&$A34&"'!$A$12:$Z$19"),MATCH("Points (Auto-generate)",INDIRECT("'"&$A34&"'!$A$12:$Z$12"),0),0)),"ER")) -> ?
A35: DPG5e | B35: =VLOOKUP($A35,'PARASTATAL Questions'!$A:$J,3,0)&"" -> Decentralised Participatory Governance | C35: =VLOOKUP($A35,'PARASTATAL Questions'!$A:$J,4,0)&"" -> SQ | D35: =VLOOKUP($A35,'PARASTATAL Questions'!$A:$J,5,0)&"" -> Major plans / projects | E35: =VLOOKUP($A35,'PARASTATAL Questions'!$A:$J,7,0)&"" -> Implementation | F35: =VLOOKUP($A35,'PARASTATAL Questions'!$A:$J,6,0) -> 1 | G35: =IF($F35=0,"NA",IF($A35=INDIRECT("'"&$A35&"'!$B$1"),IF(VLOOKUP(G$1,INDIRECT("'"&$A35&"'!$A$12:$Z$19"),MATCH("Points (Auto-generate)",INDIRECT("'"&$A35&"'!$A$12:$Z$12"),0),0)="","?",VLOOKUP(G$1,INDIRECT("'"&$A35&"'!$A$12:$Z$19"),MATCH("Points (Auto-generate)",INDIRECT("'"&$A35&"'!$A$12:$Z$12"),0),0)),"ER")) -> ? | H35: =IF($F35=0,"NA",IF($A35=INDIRECT("'"&$A35&"'!$B$1"),IF(VLOOKUP(H$1,INDIRECT("'"&$A35&"'!$A$12:$Z$19"),MATCH("Points (Auto-generate)",INDIRECT("'"&$A35&"'!$A$12:$Z$12"),0),0)="","?",VLOOKUP(H$1,INDIRECT("'"&$A35&"'!$A$12:$Z$19"),MATCH("Points (Auto-generate)",INDIRECT("'"&$A35&"'!$A$12:$Z$12"),0),0)),"ER")) -> ? | I35: =IF($F35=0,"NA",IF($A35=INDIRECT("'"&$A35&"'!$B$1"),IF(VLOOKUP(I$1,INDIRECT("'"&$A35&"'!$A$12:$Z$19"),MATCH("Points (Auto-generate)",INDIRECT("'"&$A35&"'!$A$12:$Z$12"),0),0)="","?",VLOOKUP(I$1,INDIRECT("'"&$A35&"'!$A$12:$Z$19"),MATCH("Points (Auto-generate)",INDIRECT("'"&$A35&"'!$A$12:$Z$12"),0),0)),"ER")) -> ? | J35: =IF($F35=0,"NA",IF($A35=INDIRECT("'"&$A35&"'!$B$1"),IF(VLOOKUP(J$1,INDIRECT("'"&$A35&"'!$A$12:$Z$19"),MATCH("Points (Auto-generate)",INDIRECT("'"&$A35&"'!$A$12:$Z$12"),0),0)="","?",VLOOKUP(J$1,INDIRECT("'"&$A35&"'!$A$12:$Z$19"),MATCH("Points (Auto-generate)",INDIRECT("'"&$A35&"'!$A$12:$Z$12"),0),0)),"ER")) -> ? | K35: =IF($F35=0,"NA",IF($A35=INDIRECT("'"&$A35&"'!$B$1"),IF(VLOOKUP(K$1,INDIRECT("'"&$A35&"'!$A$12:$Z$19"),MATCH("Points (Auto-generate)",INDIRECT("'"&$A35&"'!$A$12:$Z$12"),0),0)="","?",VLOOKUP(K$1,INDIRECT("'"&$A35&"'!$A$12:$Z$19"),MATCH("Points (Auto-generate)",INDIRECT("'"&$A35&"'!$A$12:$Z$12"),0),0)),"ER")) -> ? | L35: =IF($F35=0,"NA",IF($A35=INDIRECT("'"&$A35&"'!$B$1"),IF(VLOOKUP(L$1,INDIRECT("'"&$A35&"'!$A$12:$Z$19"),MATCH("Points (Auto-generate)",INDIRECT("'"&$A35&"'!$A$12:$Z$12"),0),0)="","?",VLOOKUP(L$1,INDIRECT("'"&$A35&"'!$A$12:$Z$19"),MATCH("Points (Auto-generate)",INDIRECT("'"&$A35&"'!$A$12:$Z$12"),0),0)),"ER")) -> ? | M35: =IF($F35=0,"NA",IF($A35=INDIRECT("'"&$A35&"'!$B$1"),IF(VLOOKUP(M$1,INDIRECT("'"&$A35&"'!$A$12:$Z$19"),MATCH("Points (Auto-generate)",INDIRECT("'"&$A35&"'!$A$12:$Z$12"),0),0)="","?",VLOOKUP(M$1,INDIRECT("'"&$A35&"'!$A$12:$Z$19"),MATCH("Points (Auto-generate)",INDIRECT("'"&$A35&"'!$A$12:$Z$12"),0),0)),"ER")) -> ?
A36: DPG5f | B36: =VLOOKUP($A36,'PARASTATAL Questions'!$A:$J,3,0)&"" -> Decentralised Participatory Governance | C36: =VLOOKUP($A36,'PARASTATAL Questions'!$A:$J,4,0)&"" -> SQ | D36: =VLOOKUP($A36,'PARASTATAL Questions'!$A:$J,5,0)&"" -> Service-level benchmarks and performance reports | E36: =VLOOKUP($A36,'PARASTATAL Questions'!$A:$J,7,0)&"" -> Implementation | F36: =VLOOKUP($A36,'PARASTATAL Questions'!$A:$J,6,0) -> 1 | G36: =IF($F36=0,"NA",IF($A36=INDIRECT("'"&$A36&"'!$B$1"),IF(VLOOKUP(G$1,INDIRECT("'"&$A36&"'!$A$12:$Z$19"),MATCH("Points (Auto-generate)",INDIRECT("'"&$A36&"'!$A$12:$Z$12"),0),0)="","?",VLOOKUP(G$1,INDIRECT("'"&$A36&"'!$A$12:$Z$19"),MATCH("Points (Auto-generate)",INDIRECT("'"&$A36&"'!$A$12:$Z$12"),0),0)),"ER")) -> ? | H36: =IF($F36=0,"NA",IF($A36=INDIRECT("'"&$A36&"'!$B$1"),IF(VLOOKUP(H$1,INDIRECT("'"&$A36&"'!$A$12:$Z$19"),MATCH("Points (Auto-generate)",INDIRECT("'"&$A36&"'!$A$12:$Z$12"),0),0)="","?",VLOOKUP(H$1,INDIRECT("'"&$A36&"'!$A$12:$Z$19"),MATCH("Points (Auto-generate)",INDIRECT("'"&$A36&"'!$A$12:$Z$12"),0),0)),"ER")) -> ? | I36: =IF($F36=0,"NA",IF($A36=INDIRECT("'"&$A36&"'!$B$1"),IF(VLOOKUP(I$1,INDIRECT("'"&$A36&"'!$A$12:$Z$19"),MATCH("Points (Auto-generate)",INDIRECT("'"&$A36&"'!$A$12:$Z$12"),0),0)="","?",VLOOKUP(I$1,INDIRECT("'"&$A36&"'!$A$12:$Z$19"),MATCH("Points (Auto-generate)",INDIRECT("'"&$A36&"'!$A$12:$Z$12"),0),0)),"ER")) -> ? | J36: =IF($F36=0,"NA",IF($A36=INDIRECT("'"&$A36&"'!$B$1"),IF(VLOOKUP(J$1,INDIRECT("'"&$A36&"'!$A$12:$Z$19"),MATCH("Points (Auto-generate)",INDIRECT("'"&$A36&"'!$A$12:$Z$12"),0),0)="","?",VLOOKUP(J$1,INDIRECT("'"&$A36&"'!$A$12:$Z$19"),MATCH("Points (Auto-generate)",INDIRECT("'"&$A36&"'!$A$12:$Z$12"),0),0)),"ER")) -> ? | K36: =IF($F36=0,"NA",IF($A36=INDIRECT("'"&$A36&"'!$B$1"),IF(VLOOKUP(K$1,INDIRECT("'"&$A36&"'!$A$12:$Z$19"),MATCH("Points (Auto-generate)",INDIRECT("'"&$A36&"'!$A$12:$Z$12"),0),0)="","?",VLOOKUP(K$1,INDIRECT("'"&$A36&"'!$A$12:$Z$19"),MATCH("Points (Auto-generate)",INDIRECT("'"&$A36&"'!$A$12:$Z$12"),0),0)),"ER")) -> ? | L36: =IF($F36=0,"NA",IF($A36=INDIRECT("'"&$A36&"'!$B$1"),IF(VLOOKUP(L$1,INDIRECT("'"&$A36&"'!$A$12:$Z$19"),MATCH("Points (Auto-generate)",INDIRECT("'"&$A36&"'!$A$12:$Z$12"),0),0)="","?",VLOOKUP(L$1,INDIRECT("'"&$A36&"'!$A$12:$Z$19"),MATCH("Points (Auto-generate)",INDIRECT("'"&$A36&"'!$A$12:$Z$12"),0),0)),"ER")) -> ? | M36: =IF($F36=0,"NA",IF($A36=INDIRECT("'"&$A36&"'!$B$1"),IF(VLOOKUP(M$1,INDIRECT("'"&$A36&"'!$A$12:$Z$19"),MATCH("Points (Auto-generate)",INDIRECT("'"&$A36&"'!$A$12:$Z$12"),0),0)="","?",VLOOKUP(M$1,INDIRECT("'"&$A36&"'!$A$12:$Z$19"),MATCH("Points (Auto-generate)",INDIRECT("'"&$A36&"'!$A$12:$Z$12"),0),0)),"ER")) -> ?
A37: DPG5g | B37: =VLOOKUP($A37,'PARASTATAL Questions'!$A:$J,3,0)&"" -> Decentralised Participatory Governance | C37: =VLOOKUP($A37,'PARASTATAL Questions'!$A:$J,4,0)&"" -> SQ | D37: =VLOOKUP($A37,'PARASTATAL Questions'!$A:$J,5,0)&"" -> Organisation and staffing information | E37: =VLOOKUP($A37,'PARASTATAL Questions'!$A:$J,7,0)&"" -> Implementation | F37: =VLOOKUP($A37,'PARASTATAL Questions'!$A:$J,6,0) -> 1 | G37: =IF($F37=0,"NA",IF($A37=INDIRECT("'"&$A37&"'!$B$1"),IF(VLOOKUP(G$1,INDIRECT("'"&$A37&"'!$A$12:$Z$19"),MATCH("Points (Auto-generate)",INDIRECT("'"&$A37&"'!$A$12:$Z$12"),0),0)="","?",VLOOKUP(G$1,INDIRECT("'"&$A37&"'!$A$12:$Z$19"),MATCH("Points (Auto-generate)",INDIRECT("'"&$A37&"'!$A$12:$Z$12"),0),0)),"ER")) -> ? | H37: =IF($F37=0,"NA",IF($A37=INDIRECT("'"&$A37&"'!$B$1"),IF(VLOOKUP(H$1,INDIRECT("'"&$A37&"'!$A$12:$Z$19"),MATCH("Points (Auto-generate)",INDIRECT("'"&$A37&"'!$A$12:$Z$12"),0),0)="","?",VLOOKUP(H$1,INDIRECT("'"&$A37&"'!$A$12:$Z$19"),MATCH("Points (Auto-generate)",INDIRECT("'"&$A37&"'!$A$12:$Z$12"),0),0)),"ER")) -> ? | I37: =IF($F37=0,"NA",IF($A37=INDIRECT("'"&$A37&"'!$B$1"),IF(VLOOKUP(I$1,INDIRECT("'"&$A37&"'!$A$12:$Z$19"),MATCH("Points (Auto-generate)",INDIRECT("'"&$A37&"'!$A$12:$Z$12"),0),0)="","?",VLOOKUP(I$1,INDIRECT("'"&$A37&"'!$A$12:$Z$19"),MATCH("Points (Auto-generate)",INDIRECT("'"&$A37&"'!$A$12:$Z$12"),0),0)),"ER")) -> ? | J37: =IF($F37=0,"NA",IF($A37=INDIRECT("'"&$A37&"'!$B$1"),IF(VLOOKUP(J$1,INDIRECT("'"&$A37&"'!$A$12:$Z$19"),MATCH("Points (Auto-generate)",INDIRECT("'"&$A37&"'!$A$12:$Z$12"),0),0)="","?",VLOOKUP(J$1,INDIRECT("'"&$A37&"'!$A$12:$Z$19"),MATCH("Points (Auto-generate)",INDIRECT("'"&$A37&"'!$A$12:$Z$12"),0),0)),"ER")) -> ? | K37: =IF($F37=0,"NA",IF($A37=INDIRECT("'"&$A37&"'!$B$1"),IF(VLOOKUP(K$1,INDIRECT("'"&$A37&"'!$A$12:$Z$19"),MATCH("Points (Auto-generate)",INDIRECT("'"&$A37&"'!$A$12:$Z$12"),0),0)="","?",VLOOKUP(K$1,INDIRECT("'"&$A37&"'!$A$12:$Z$19"),MATCH("Points (Auto-generate)",INDIRECT("'"&$A37&"'!$A$12:$Z$12"),0),0)),"ER")) -> ? | L37: =IF($F37=0,"NA",IF($A37=INDIRECT("'"&$A37&"'!$B$1"),IF(VLOOKUP(L$1,INDIRECT("'"&$A37&"'!$A$12:$Z$19"),MATCH("Points (Auto-generate)",INDIRECT("'"&$A37&"'!$A$12:$Z$12"),0),0)="","?",VLOOKUP(L$1,INDIRECT("'"&$A37&"'!$A$12:$Z$19"),MATCH("Points (Auto-generate)",INDIRECT("'"&$A37&"'!$A$12:$Z$12"),0),0)),"ER")) -> ? | M37: =IF($F37=0,"NA",IF($A37=INDIRECT("'"&$A37&"'!$B$1"),IF(VLOOKUP(M$1,INDIRECT("'"&$A37&"'!$A$12:$Z$19"),MATCH("Points (Auto-generate)",INDIRECT("'"&$A37&"'!$A$12:$Z$12"),0),0)="","?",VLOOKUP(M$1,INDIRECT("'"&$A37&"'!$A$12:$Z$19"),MATCH("Points (Auto-generate)",INDIRECT("'"&$A37&"'!$A$12:$Z$12"),0),0)),"ER")) -> ?
A38: DPG5h | B38: =VLOOKUP($A38,'PARASTATAL Questions'!$A:$J,3,0)&"" -> Decentralised Participatory Governance | C38: =VLOOKUP($A38,'PARASTATAL Questions'!$A:$J,4,0)&"" -> SQ | D38: =VLOOKUP($A38,'PARASTATAL Questions'!$A:$J,5,0)&"" -> Meeting minutes of governing board | E38: =VLOOKUP($A38,'PARASTATAL Questions'!$A:$J,7,0)&"" -> Implementation | F38: =VLOOKUP($A38,'PARASTATAL Questions'!$A:$J,6,0) -> 1 | G38: =IF($F38=0,"NA",IF($A38=INDIRECT("'"&$A38&"'!$B$1"),IF(VLOOKUP(G$1,INDIRECT("'"&$A38&"'!$A$12:$Z$19"),MATCH("Points (Auto-generate)",INDIRECT("'"&$A38&"'!$A$12:$Z$12"),0),0)="","?",VLOOKUP(G$1,INDIRECT("'"&$A38&"'!$A$12:$Z$19"),MATCH("Points (Auto-generate)",INDIRECT("'"&$A38&"'!$A$12:$Z$12"),0),0)),"ER")) -> ? | H38: =IF($F38=0,"NA",IF($A38=INDIRECT("'"&$A38&"'!$B$1"),IF(VLOOKUP(H$1,INDIRECT("'"&$A38&"'!$A$12:$Z$19"),MATCH("Points (Auto-generate)",INDIRECT("'"&$A38&"'!$A$12:$Z$12"),0),0)="","?",VLOOKUP(H$1,INDIRECT("'"&$A38&"'!$A$12:$Z$19"),MATCH("Points (Auto-generate)",INDIRECT("'"&$A38&"'!$A$12:$Z$12"),0),0)),"ER")) -> ? | I38: =IF($F38=0,"NA",IF($A38=INDIRECT("'"&$A38&"'!$B$1"),IF(VLOOKUP(I$1,INDIRECT("'"&$A38&"'!$A$12:$Z$19"),MATCH("Points (Auto-generate)",INDIRECT("'"&$A38&"'!$A$12:$Z$12"),0),0)="","?",VLOOKUP(I$1,INDIRECT("'"&$A38&"'!$A$12:$Z$19"),MATCH("Points (Auto-generate)",INDIRECT("'"&$A38&"'!$A$12:$Z$12"),0),0)),"ER")) -> ? | J38: =IF($F38=0,"NA",IF($A38=INDIRECT("'"&$A38&"'!$B$1"),IF(VLOOKUP(J$1,INDIRECT("'"&$A38&"'!$A$12:$Z$19"),MATCH("Points (Auto-generate)",INDIRECT("'"&$A38&"'!$A$12:$Z$12"),0),0)="","?",VLOOKUP(J$1,INDIRECT("'"&$A38&"'!$A$12:$Z$19"),MATCH("Points (Auto-generate)",INDIRECT("'"&$A38&"'!$A$12:$Z$12"),0),0)),"ER")) -> ? | K38: =IF($F38=0,"NA",IF($A38=INDIRECT("'"&$A38&"'!$B$1"),IF(VLOOKUP(K$1,INDIRECT("'"&$A38&"'!$A$12:$Z$19"),MATCH("Points (Auto-generate)",INDIRECT("'"&$A38&"'!$A$12:$Z$12"),0),0)="","?",VLOOKUP(K$1,INDIRECT("'"&$A38&"'!$A$12:$Z$19"),MATCH("Points (Auto-generate)",INDIRECT("'"&$A38&"'!$A$12:$Z$12"),0),0)),"ER")) -> ? | L38: =IF($F38=0,"NA",IF($A38=INDIRECT("'"&$A38&"'!$B$1"),IF(VLOOKUP(L$1,INDIRECT("'"&$A38&"'!$A$12:$Z$19"),MATCH("Points (Auto-generate)",INDIRECT("'"&$A38&"'!$A$12:$Z$12"),0),0)="","?",VLOOKUP(L$1,INDIRECT("'"&$A38&"'!$A$12:$Z$19"),MATCH("Points (Auto-generate)",INDIRECT("'"&$A38&"'!$A$12:$Z$12"),0),0)),"ER")) -> ? | M38: =IF($F38=0,"NA",IF($A38=INDIRECT("'"&$A38&"'!$B$1"),IF(VLOOKUP(M$1,INDIRECT("'"&$A38&"'!$A$12:$Z$19"),MATCH("Points (Auto-generate)",INDIRECT("'"&$A38&"'!$A$12:$Z$12"),0),0)="","?",VLOOKUP(M$1,INDIRECT("'"&$A38&"'!$A$12:$Z$19"),MATCH("Points (Auto-generate)",INDIRECT("'"&$A38&"'!$A$12:$Z$12"),0),0)),"ER")) -> ?
A39: DPG5i | B39: =VLOOKUP($A39,'PARASTATAL Questions'!$A:$J,3,0)&"" -> Decentralised Participatory Governance | C39: =VLOOKUP($A39,'PARASTATAL Questions'!$A:$J,4,0)&"" -> SQ | D39: =VLOOKUP($A39,'PARASTATAL Questions'!$A:$J,5,0)&"" -> Citizen / Service Charter | E39: =VLOOKUP($A39,'PARASTATAL Questions'!$A:$J,7,0)&"" -> Implementation | F39: =VLOOKUP($A39,'PARASTATAL Questions'!$A:$J,6,0) -> 1 | G39: =IF($F39=0,"NA",IF($A39=INDIRECT("'"&$A39&"'!$B$1"),IF(VLOOKUP(G$1,INDIRECT("'"&$A39&"'!$A$12:$Z$19"),MATCH("Points (Auto-generate)",INDIRECT("'"&$A39&"'!$A$12:$Z$12"),0),0)="","?",VLOOKUP(G$1,INDIRECT("'"&$A39&"'!$A$12:$Z$19"),MATCH("Points (Auto-generate)",INDIRECT("'"&$A39&"'!$A$12:$Z$12"),0),0)),"ER")) -> ? | H39: =IF($F39=0,"NA",IF($A39=INDIRECT("'"&$A39&"'!$B$1"),IF(VLOOKUP(H$1,INDIRECT("'"&$A39&"'!$A$12:$Z$19"),MATCH("Points (Auto-generate)",INDIRECT("'"&$A39&"'!$A$12:$Z$12"),0),0)="","?",VLOOKUP(H$1,INDIRECT("'"&$A39&"'!$A$12:$Z$19"),MATCH("Points (Auto-generate)",INDIRECT("'"&$A39&"'!$A$12:$Z$12"),0),0)),"ER")) -> ? | I39: =IF($F39=0,"NA",IF($A39=INDIRECT("'"&$A39&"'!$B$1"),IF(VLOOKUP(I$1,INDIRECT("'"&$A39&"'!$A$12:$Z$19"),MATCH("Points (Auto-generate)",INDIRECT("'"&$A39&"'!$A$12:$Z$12"),0),0)="","?",VLOOKUP(I$1,INDIRECT("'"&$A39&"'!$A$12:$Z$19"),MATCH("Points (Auto-generate)",INDIRECT("'"&$A39&"'!$A$12:$Z$12"),0),0)),"ER")) -> ? | J39: =IF($F39=0,"NA",IF($A39=INDIRECT("'"&$A39&"'!$B$1"),IF(VLOOKUP(J$1,INDIRECT("'"&$A39&"'!$A$12:$Z$19"),MATCH("Points (Auto-generate)",INDIRECT("'"&$A39&"'!$A$12:$Z$12"),0),0)="","?",VLOOKUP(J$1,INDIRECT("'"&$A39&"'!$A$12:$Z$19"),MATCH("Points (Auto-generate)",INDIRECT("'"&$A39&"'!$A$12:$Z$12"),0),0)),"ER")) -> ? | K39: =IF($F39=0,"NA",IF($A39=INDIRECT("'"&$A39&"'!$B$1"),IF(VLOOKUP(K$1,INDIRECT("'"&$A39&"'!$A$12:$Z$19"),MATCH("Points (Auto-generate)",INDIRECT("'"&$A39&"'!$A$12:$Z$12"),0),0)="","?",VLOOKUP(K$1,INDIRECT("'"&$A39&"'!$A$12:$Z$19"),MATCH("Points (Auto-generate)",INDIRECT("'"&$A39&"'!$A$12:$Z$12"),0),0)),"ER")) -> ? | L39: =IF($F39=0,"NA",IF($A39=INDIRECT("'"&$A39&"'!$B$1"),IF(VLOOKUP(L$1,INDIRECT("'"&$A39&"'!$A$12:$Z$19"),MATCH("Points (Auto-generate)",INDIRECT("'"&$A39&"'!$A$12:$Z$12"),0),0)="","?",VLOOKUP(L$1,INDIRECT("'"&$A39&"'!$A$12:$Z$19"),MATCH("Points (Auto-generate)",INDIRECT("'"&$A39&"'!$A$12:$Z$12"),0),0)),"ER")) -> ? | M39: =IF($F39=0,"NA",IF($A39=INDIRECT("'"&$A39&"'!$B$1"),IF(VLOOKUP(M$1,INDIRECT("'"&$A39&"'!$A$12:$Z$19"),MATCH("Points (Auto-generate)",INDIRECT("'"&$A39&"'!$A$12:$Z$12"),0),0)="","?",VLOOKUP(M$1,INDIRECT("'"&$A39&"'!$A$12:$Z$19"),MATCH("Points (Auto-generate)",INDIRECT("'"&$A39&"'!$A$12:$Z$12"),0),0)),"ER")) -> ?
A40: DPG5j | B40: =VLOOKUP($A40,'PARASTATAL Questions'!$A:$J,3,0)&"" -> Decentralised Participatory Governance | C40: =VLOOKUP($A40,'PARASTATAL Questions'!$A:$J,4,0)&"" -> SQ | D40: =VLOOKUP($A40,'PARASTATAL Questions'!$A:$J,5,0)&"" -> RTI details and designated Public Information Officer contact/procedure | E40: =VLOOKUP($A40,'PARASTATAL Questions'!$A:$J,7,0)&"" -> Implementation | F40: =VLOOKUP($A40,'PARASTATAL Questions'!$A:$J,6,0) -> 1 | G40: =IF($F40=0,"NA",IF($A40=INDIRECT("'"&$A40&"'!$B$1"),IF(VLOOKUP(G$1,INDIRECT("'"&$A40&"'!$A$12:$Z$19"),MATCH("Points (Auto-generate)",INDIRECT("'"&$A40&"'!$A$12:$Z$12"),0),0)="","?",VLOOKUP(G$1,INDIRECT("'"&$A40&"'!$A$12:$Z$19"),MATCH("Points (Auto-generate)",INDIRECT("'"&$A40&"'!$A$12:$Z$12"),0),0)),"ER")) -> ? | H40: =IF($F40=0,"NA",IF($A40=INDIRECT("'"&$A40&"'!$B$1"),IF(VLOOKUP(H$1,INDIRECT("'"&$A40&"'!$A$12:$Z$19"),MATCH("Points (Auto-generate)",INDIRECT("'"&$A40&"'!$A$12:$Z$12"),0),0)="","?",VLOOKUP(H$1,INDIRECT("'"&$A40&"'!$A$12:$Z$19"),MATCH("Points (Auto-generate)",INDIRECT("'"&$A40&"'!$A$12:$Z$12"),0),0)),"ER")) -> ? | I40: =IF($F40=0,"NA",IF($A40=INDIRECT("'"&$A40&"'!$B$1"),IF(VLOOKUP(I$1,INDIRECT("'"&$A40&"'!$A$12:$Z$19"),MATCH("Points (Auto-generate)",INDIRECT("'"&$A40&"'!$A$12:$Z$12"),0),0)="","?",VLOOKUP(I$1,INDIRECT("'"&$A40&"'!$A$12:$Z$19"),MATCH("Points (Auto-generate)",INDIRECT("'"&$A40&"'!$A$12:$Z$12"),0),0)),"ER")) -> ? | J40: =IF($F40=0,"NA",IF($A40=INDIRECT("'"&$A40&"'!$B$1"),IF(VLOOKUP(J$1,INDIRECT("'"&$A40&"'!$A$12:$Z$19"),MATCH("Points (Auto-generate)",INDIRECT("'"&$A40&"'!$A$12:$Z$12"),0),0)="","?",VLOOKUP(J$1,INDIRECT("'"&$A40&"'!$A$12:$Z$19"),MATCH("Points (Auto-generate)",INDIRECT("'"&$A40&"'!$A$12:$Z$12"),0),0)),"ER")) -> ? | K40: =IF($F40=0,"NA",IF($A40=INDIRECT("'"&$A40&"'!$B$1"),IF(VLOOKUP(K$1,INDIRECT("'"&$A40&"'!$A$12:$Z$19"),MATCH("Points (Auto-generate)",INDIRECT("'"&$A40&"'!$A$12:$Z$12"),0),0)="","?",VLOOKUP(K$1,INDIRECT("'"&$A40&"'!$A$12:$Z$19"),MATCH("Points (Auto-generate)",INDIRECT("'"&$A40&"'!$A$12:$Z$12"),0),0)),"ER")) -> ? | L40: =IF($F40=0,"NA",IF($A40=INDIRECT("'"&$A40&"'!$B$1"),IF(VLOOKUP(L$1,INDIRECT("'"&$A40&"'!$A$12:$Z$19"),MATCH("Points (Auto-generate)",INDIRECT("'"&$A40&"'!$A$12:$Z$12"),0),0)="","?",VLOOKUP(L$1,INDIRECT("'"&$A40&"'!$A$12:$Z$19"),MATCH("Points (Auto-generate)",INDIRECT("'"&$A40&"'!$A$12:$Z$12"),0),0)),"ER")) -> ? | M40: =IF($F40=0,"NA",IF($A40=INDIRECT("'"&$A40&"'!$B$1"),IF(VLOOKUP(M$1,INDIRECT("'"&$A40&"'!$A$12:$Z$19"),MATCH("Points (Auto-generate)",INDIRECT("'"&$A40&"'!$A$12:$Z$12"),0),0)="","?",VLOOKUP(M$1,INDIRECT("'"&$A40&"'!$A$12:$Z$19"),MATCH("Points (Auto-generate)",INDIRECT("'"&$A40&"'!$A$12:$Z$12"),0),0)),"ER")) -> ?
A41: DPG6 | B41: =VLOOKUP($A41,'PARASTATAL Questions'!$A:$J,3,0)&"" -> Decentralised Participatory Governance | C41: =VLOOKUP($A41,'PARASTATAL Questions'!$A:$J,4,0)&"" -> MQ | D41: =VLOOKUP($A41,'PARASTATAL Questions'!$A:$J,5,0)&"" -> Does the parastatal provide for and maintain an accessible grievance-redressal mechanism? | E41: =VLOOKUP($A41,'PARASTATAL Questions'!$A:$J,7,0)&"" -> Law/Policy | F41: =VLOOKUP($A41,'PARASTATAL Questions'!$A:$J,6,0) -> 10 | G41: =IF(OR(G42="ER",G43="ER"),"ER",IF(OR(G42="?",G43="?"),"?",IF(AND(G42="NA",G43="NA"),"NA",SUM(G42,G43)/((G42<>"NA")*$F$42+(G43<>"NA")*$F$43)*$F41))) -> ? | H41: =IF(OR(H42="ER",H43="ER"),"ER",IF(OR(H42="?",H43="?"),"?",IF(AND(H42="NA",H43="NA"),"NA",SUM(H42,H43)/((H42<>"NA")*$F$42+(H43<>"NA")*$F$43)*$F41))) -> ? | I41: =IF(OR(I42="ER",I43="ER"),"ER",IF(OR(I42="?",I43="?"),"?",IF(AND(I42="NA",I43="NA"),"NA",SUM(I42,I43)/((I42<>"NA")*$F$42+(I43<>"NA")*$F$43)*$F41))) -> ? | J41: =IF(OR(J42="ER",J43="ER"),"ER",IF(OR(J42="?",J43="?"),"?",IF(AND(J42="NA",J43="NA"),"NA",SUM(J42,J43)/((J42<>"NA")*$F$42+(J43<>"NA")*$F$43)*$F41))) -> ? | K41: =IF(OR(K42="ER",K43="ER"),"ER",IF(OR(K42="?",K43="?"),"?",IF(AND(K42="NA",K43="NA"),"NA",SUM(K42,K43)/((K42<>"NA")*$F$42+(K43<>"NA")*$F$43)*$F41))) -> ? | L41: =IF(OR(L42="ER",L43="ER"),"ER",IF(OR(L42="?",L43="?"),"?",IF(AND(L42="NA",L43="NA"),"NA",SUM(L42,L43)/((L42<>"NA")*$F$42+(L43<>"NA")*$F$43)*$F41))) -> ? | M41: =IF(OR(M42="ER",M43="ER"),"ER",IF(OR(M42="?",M43="?"),"?",IF(AND(M42="NA",M43="NA"),"NA",SUM(M42,M43)/((M42<>"NA")*$F$42+(M43<>"NA")*$F$43)*$F41))) -> ?
A42: DPG6a | B42: =VLOOKUP($A42,'PARASTATAL Questions'!$A:$J,3,0)&"" -> Decentralised Participatory Governance | C42: =VLOOKUP($A42,'PARASTATAL Questions'!$A:$J,4,0)&"" -> SQ | D42: =VLOOKUP($A42,'PARASTATAL Questions'!$A:$J,5,0)&"" -> Is the parastatal mandated to provide a grievance-redressal mechanism? | E42: =VLOOKUP($A42,'PARASTATAL Questions'!$A:$J,7,0)&"" -> Law/Policy | F42: =VLOOKUP($A42,'PARASTATAL Questions'!$A:$J,6,0) -> 5 | G42: =IF($F42=0,"NA",IF($A42=INDIRECT("'"&$A42&"'!$B$1"),IF(VLOOKUP(G$1,INDIRECT("'"&$A42&"'!$A$12:$Z$19"),MATCH("Points (Auto-generate)",INDIRECT("'"&$A42&"'!$A$12:$Z$12"),0),0)="","?",VLOOKUP(G$1,INDIRECT("'"&$A42&"'!$A$12:$Z$19"),MATCH("Points (Auto-generate)",INDIRECT("'"&$A42&"'!$A$12:$Z$12"),0),0)),"ER")) -> ? | H42: =IF($F42=0,"NA",IF($A42=INDIRECT("'"&$A42&"'!$B$1"),IF(VLOOKUP(H$1,INDIRECT("'"&$A42&"'!$A$12:$Z$19"),MATCH("Points (Auto-generate)",INDIRECT("'"&$A42&"'!$A$12:$Z$12"),0),0)="","?",VLOOKUP(H$1,INDIRECT("'"&$A42&"'!$A$12:$Z$19"),MATCH("Points (Auto-generate)",INDIRECT("'"&$A42&"'!$A$12:$Z$12"),0),0)),"ER")) -> ? | I42: =IF($F42=0,"NA",IF($A42=INDIRECT("'"&$A42&"'!$B$1"),IF(VLOOKUP(I$1,INDIRECT("'"&$A42&"'!$A$12:$Z$19"),MATCH("Points (Auto-generate)",INDIRECT("'"&$A42&"'!$A$12:$Z$12"),0),0)="","?",VLOOKUP(I$1,INDIRECT("'"&$A42&"'!$A$12:$Z$19"),MATCH("Points (Auto-generate)",INDIRECT("'"&$A42&"'!$A$12:$Z$12"),0),0)),"ER")) -> ? | J42: =IF($F42=0,"NA",IF($A42=INDIRECT("'"&$A42&"'!$B$1"),IF(VLOOKUP(J$1,INDIRECT("'"&$A42&"'!$A$12:$Z$19"),MATCH("Points (Auto-generate)",INDIRECT("'"&$A42&"'!$A$12:$Z$12"),0),0)="","?",VLOOKUP(J$1,INDIRECT("'"&$A42&"'!$A$12:$Z$19"),MATCH("Points (Auto-generate)",INDIRECT("'"&$A42&"'!$A$12:$Z$12"),0),0)),"ER")) -> ? | K42: =IF($F42=0,"NA",IF($A42=INDIRECT("'"&$A42&"'!$B$1"),IF(VLOOKUP(K$1,INDIRECT("'"&$A42&"'!$A$12:$Z$19"),MATCH("Points (Auto-generate)",INDIRECT("'"&$A42&"'!$A$12:$Z$12"),0),0)="","?",VLOOKUP(K$1,INDIRECT("'"&$A42&"'!$A$12:$Z$19"),MATCH("Points (Auto-generate)",INDIRECT("'"&$A42&"'!$A$12:$Z$12"),0),0)),"ER")) -> ? | L42: =IF($F42=0,"NA",IF($A42=INDIRECT("'"&$A42&"'!$B$1"),IF(VLOOKUP(L$1,INDIRECT("'"&$A42&"'!$A$12:$Z$19"),MATCH("Points (Auto-generate)",INDIRECT("'"&$A42&"'!$A$12:$Z$12"),0),0)="","?",VLOOKUP(L$1,INDIRECT("'"&$A42&"'!$A$12:$Z$19"),MATCH("Points (Auto-generate)",INDIRECT("'"&$A42&"'!$A$12:$Z$12"),0),0)),"ER")) -> ? | M42: =IF($F42=0,"NA",IF($A42=INDIRECT("'"&$A42&"'!$B$1"),IF(VLOOKUP(M$1,INDIRECT("'"&$A42&"'!$A$12:$Z$19"),MATCH("Points (Auto-generate)",INDIRECT("'"&$A42&"'!$A$12:$Z$12"),0),0)="","?",VLOOKUP(M$1,INDIRECT("'"&$A42&"'!$A$12:$Z$19"),MATCH("Points (Auto-generate)",INDIRECT("'"&$A42&"'!$A$12:$Z$12"),0),0)),"ER")) -> ?
A43: DPG6b | B43: =VLOOKUP($A43,'PARASTATAL Questions'!$A:$J,3,0)&"" -> Decentralised Participatory Governance | C43: =VLOOKUP($A43,'PARASTATAL Questions'!$A:$J,4,0)&"" -> SQ | D43: =VLOOKUP($A43,'PARASTATAL Questions'!$A:$J,5,0)&"" -> Are accessible grievance-redressal channels available and functional in practice? | E43: =VLOOKUP($A43,'PARASTATAL Questions'!$A:$J,7,0)&"" -> Implementation | F43: =VLOOKUP($A43,'PARASTATAL Questions'!$A:$J,6,0) -> 5 | G43: =IF($F43=0,"NA",IF($A43=INDIRECT("'"&$A43&"'!$B$1"),IF(VLOOKUP(G$1,INDIRECT("'"&$A43&"'!$A$12:$Z$19"),MATCH("Points (Auto-generate)",INDIRECT("'"&$A43&"'!$A$12:$Z$12"),0),0)="","?",VLOOKUP(G$1,INDIRECT("'"&$A43&"'!$A$12:$Z$19"),MATCH("Points (Auto-generate)",INDIRECT("'"&$A43&"'!$A$12:$Z$12"),0),0)),"ER")) -> ? | H43: =IF($F43=0,"NA",IF($A43=INDIRECT("'"&$A43&"'!$B$1"),IF(VLOOKUP(H$1,INDIRECT("'"&$A43&"'!$A$12:$Z$19"),MATCH("Points (Auto-generate)",INDIRECT("'"&$A43&"'!$A$12:$Z$12"),0),0)="","?",VLOOKUP(H$1,INDIRECT("'"&$A43&"'!$A$12:$Z$19"),MATCH("Points (Auto-generate)",INDIRECT("'"&$A43&"'!$A$12:$Z$12"),0),0)),"ER")) -> ? | I43: =IF($F43=0,"NA",IF($A43=INDIRECT("'"&$A43&"'!$B$1"),IF(VLOOKUP(I$1,INDIRECT("'"&$A43&"'!$A$12:$Z$19"),MATCH("Points (Auto-generate)",INDIRECT("'"&$A43&"'!$A$12:$Z$12"),0),0)="","?",VLOOKUP(I$1,INDIRECT("'"&$A43&"'!$A$12:$Z$19"),MATCH("Points (Auto-generate)",INDIRECT("'"&$A43&"'!$A$12:$Z$12"),0),0)),"ER")) -> ? | J43: =IF($F43=0,"NA",IF($A43=INDIRECT("'"&$A43&"'!$B$1"),IF(VLOOKUP(J$1,INDIRECT("'"&$A43&"'!$A$12:$Z$19"),MATCH("Points (Auto-generate)",INDIRECT("'"&$A43&"'!$A$12:$Z$12"),0),0)="","?",VLOOKUP(J$1,INDIRECT("'"&$A43&"'!$A$12:$Z$19"),MATCH("Points (Auto-generate)",INDIRECT("'"&$A43&"'!$A$12:$Z$12"),0),0)),"ER")) -> ? | K43: =IF($F43=0,"NA",IF($A43=INDIRECT("'"&$A43&"'!$B$1"),IF(VLOOKUP(K$1,INDIRECT("'"&$A43&"'!$A$12:$Z$19"),MATCH("Points (Auto-generate)",INDIRECT("'"&$A43&"'!$A$12:$Z$12"),0),0)="","?",VLOOKUP(K$1,INDIRECT("'"&$A43&"'!$A$12:$Z$19"),MATCH("Points (Auto-generate)",INDIRECT("'"&$A43&"'!$A$12:$Z$12"),0),0)),"ER")) -> ? | L43: =IF($F43=0,"NA",IF($A43=INDIRECT("'"&$A43&"'!$B$1"),IF(VLOOKUP(L$1,INDIRECT("'"&$A43&"'!$A$12:$Z$19"),MATCH("Points (Auto-generate)",INDIRECT("'"&$A43&"'!$A$12:$Z$12"),0),0)="","?",VLOOKUP(L$1,INDIRECT("'"&$A43&"'!$A$12:$Z$19"),MATCH("Points (Auto-generate)",INDIRECT("'"&$A43&"'!$A$12:$Z$12"),0),0)),"ER")) -> ? | M43: =IF($F43=0,"NA",IF($A43=INDIRECT("'"&$A43&"'!$B$1"),IF(VLOOKUP(M$1,INDIRECT("'"&$A43&"'!$A$12:$Z$19"),MATCH("Points (Auto-generate)",INDIRECT("'"&$A43&"'!$A$12:$Z$12"),0),0)="","?",VLOOKUP(M$1,INDIRECT("'"&$A43&"'!$A$12:$Z$19"),MATCH("Points (Auto-generate)",INDIRECT("'"&$A43&"'!$A$12:$Z$12"),0),0)),"ER")) -> ?
A44: DPG7 | B44: =VLOOKUP($A44,'PARASTATAL Questions'!$A:$J,3,0)&"" -> Decentralised Participatory Governance | C44: =VLOOKUP($A44,'PARASTATAL Questions'!$A:$J,4,0)&"" -> MQ | D44: =VLOOKUP($A44,'PARASTATAL Questions'!$A:$J,5,0)&"" -> Does the law mandate citizen participation in the preparation of plans for which the parastatal is responsible, and does the parastatal provide for such participation in practice? | E44: =VLOOKUP($A44,'PARASTATAL Questions'!$A:$J,7,0)&"" -> Law/Policy and Implementation | F44: =VLOOKUP($A44,'PARASTATAL Questions'!$A:$J,6,0) -> 10 | G44: =IF(OR(G45="ER",G46="ER"),"ER",IF(OR(G45="?",G46="?"),"?",IF(AND(G45="NA",G46="NA"),"NA",SUM(G45,G46)/((G45<>"NA")*$F$45+(G46<>"NA")*$F$46)*$F44))) -> ? | H44: =IF(OR(H45="ER",H46="ER"),"ER",IF(OR(H45="?",H46="?"),"?",IF(AND(H45="NA",H46="NA"),"NA",SUM(H45,H46)/((H45<>"NA")*$F$45+(H46<>"NA")*$F$46)*$F44))) -> ? | I44: =IF(OR(I45="ER",I46="ER"),"ER",IF(OR(I45="?",I46="?"),"?",IF(AND(I45="NA",I46="NA"),"NA",SUM(I45,I46)/((I45<>"NA")*$F$45+(I46<>"NA")*$F$46)*$F44))) -> NA | J44: =IF(OR(J45="ER",J46="ER"),"ER",IF(OR(J45="?",J46="?"),"?",IF(AND(J45="NA",J46="NA"),"NA",SUM(J45,J46)/((J45<>"NA")*$F$45+(J46<>"NA")*$F$46)*$F44))) -> 5 | K44: =IF(OR(K45="ER",K46="ER"),"ER",IF(OR(K45="?",K46="?"),"?",IF(AND(K45="NA",K46="NA"),"NA",SUM(K45,K46)/((K45<>"NA")*$F$45+(K46<>"NA")*$F$46)*$F44))) -> NA | L44: =IF(OR(L45="ER",L46="ER"),"ER",IF(OR(L45="?",L46="?"),"?",IF(AND(L45="NA",L46="NA"),"NA",SUM(L45,L46)/((L45<>"NA")*$F$45+(L46<>"NA")*$F$46)*$F44))) -> NA | M44: =IF(OR(M45="ER",M46="ER"),"ER",IF(OR(M45="?",M46="?"),"?",IF(AND(M45="NA",M46="NA"),"NA",SUM(M45,M46)/((M45<>"NA")*$F$45+(M46<>"NA")*$F$46)*$F44))) -> ?
A45: DPG7a | B45: =VLOOKUP($A45,'PARASTATAL Questions'!$A:$J,3,0)&"" -> Decentralised Participatory Governance | C45: =VLOOKUP($A45,'PARASTATAL Questions'!$A:$J,4,0)&"" -> SQ | D45: =VLOOKUP($A45,'PARASTATAL Questions'!$A:$J,5,0)&"" -> Is citizen participation in the preparation of the parastatal's plans mandated? | E45: =VLOOKUP($A45,'PARASTATAL Questions'!$A:$J,7,0)&"" -> Law/Policy | F45: =VLOOKUP($A45,'PARASTATAL Questions'!$A:$J,6,0) -> 5 | G45: =IF($F45=0,"NA",IF($A45=INDIRECT("'"&$A45&"'!$B$1"),IF(VLOOKUP(G$1,INDIRECT("'"&$A45&"'!$A$12:$Z$19"),MATCH("Points (Auto-generate)",INDIRECT("'"&$A45&"'!$A$12:$Z$12"),0),0)="","?",VLOOKUP(G$1,INDIRECT("'"&$A45&"'!$A$12:$Z$19"),MATCH("Points (Auto-generate)",INDIRECT("'"&$A45&"'!$A$12:$Z$12"),0),0)),"ER")) -> ? | H45: =IF($F45=0,"NA",IF($A45=INDIRECT("'"&$A45&"'!$B$1"),IF(VLOOKUP(H$1,INDIRECT("'"&$A45&"'!$A$12:$Z$19"),MATCH("Points (Auto-generate)",INDIRECT("'"&$A45&"'!$A$12:$Z$12"),0),0)="","?",VLOOKUP(H$1,INDIRECT("'"&$A45&"'!$A$12:$Z$19"),MATCH("Points (Auto-generate)",INDIRECT("'"&$A45&"'!$A$12:$Z$12"),0),0)),"ER")) -> 2.5 | I45: =IF($F45=0,"NA",IF($A45=INDIRECT("'"&$A45&"'!$B$1"),IF(VLOOKUP(I$1,INDIRECT("'"&$A45&"'!$A$12:$Z$19"),MATCH("Points (Auto-generate)",INDIRECT("'"&$A45&"'!$A$12:$Z$12"),0),0)="","?",VLOOKUP(I$1,INDIRECT("'"&$A45&"'!$A$12:$Z$19"),MATCH("Points (Auto-generate)",INDIRECT("'"&$A45&"'!$A$12:$Z$12"),0),0)),"ER")) -> NA | J45: =IF($F45=0,"NA",IF($A45=INDIRECT("'"&$A45&"'!$B$1"),IF(VLOOKUP(J$1,INDIRECT("'"&$A45&"'!$A$12:$Z$19"),MATCH("Points (Auto-generate)",INDIRECT("'"&$A45&"'!$A$12:$Z$12"),0),0)="","?",VLOOKUP(J$1,INDIRECT("'"&$A45&"'!$A$12:$Z$19"),MATCH("Points (Auto-generate)",INDIRECT("'"&$A45&"'!$A$12:$Z$12"),0),0)),"ER")) -> 2.5 | K45: =IF($F45=0,"NA",IF($A45=INDIRECT("'"&$A45&"'!$B$1"),IF(VLOOKUP(K$1,INDIRECT("'"&$A45&"'!$A$12:$Z$19"),MATCH("Points (Auto-generate)",INDIRECT("'"&$A45&"'!$A$12:$Z$12"),0),0)="","?",VLOOKUP(K$1,INDIRECT("'"&$A45&"'!$A$12:$Z$19"),MATCH("Points (Auto-generate)",INDIRECT("'"&$A45&"'!$A$12:$Z$12"),0),0)),"ER")) -> NA | L45: =IF($F45=0,"NA",IF($A45=INDIRECT("'"&$A45&"'!$B$1"),IF(VLOOKUP(L$1,INDIRECT("'"&$A45&"'!$A$12:$Z$19"),MATCH("Points (Auto-generate)",INDIRECT("'"&$A45&"'!$A$12:$Z$12"),0),0)="","?",VLOOKUP(L$1,INDIRECT("'"&$A45&"'!$A$12:$Z$19"),MATCH("Points (Auto-generate)",INDIRECT("'"&$A45&"'!$A$12:$Z$12"),0),0)),"ER")) -> NA | M45: =IF($F45=0,"NA",IF($A45=INDIRECT("'"&$A45&"'!$B$1"),IF(VLOOKUP(M$1,INDIRECT("'"&$A45&"'!$A$12:$Z$19"),MATCH("Points (Auto-generate)",INDIRECT("'"&$A45&"'!$A$12:$Z$12"),0),0)="","?",VLOOKUP(M$1,INDIRECT("'"&$A45&"'!$A$12:$Z$19"),MATCH("Points (Auto-generate)",INDIRECT("'"&$A45&"'!$A$12:$Z$12"),0),0)),"ER")) -> ?
A46: DPG7b | B46: =VLOOKUP($A46,'PARASTATAL Questions'!$A:$J,3,0)&"" -> Decentralised Participatory Governance | C46: =VLOOKUP($A46,'PARASTATAL Questions'!$A:$J,4,0)&"" -> SQ | D46: =VLOOKUP($A46,'PARASTATAL Questions'!$A:$J,5,0)&"" -> Are citizens consulted in practice in the preparation of plans by the parastatal? | E46: =VLOOKUP($A46,'PARASTATAL Questions'!$A:$J,7,0)&"" -> Implementation | F46: =VLOOKUP($A46,'PARASTATAL Questions'!$A:$J,6,0) -> 5 | G46: =IF($F46=0,"NA",IF($A46=INDIRECT("'"&$A46&"'!$B$1"),IF(VLOOKUP(G$1,INDIRECT("'"&$A46&"'!$A$12:$Z$19"),MATCH("Points (Auto-generate)",INDIRECT("'"&$A46&"'!$A$12:$Z$12"),0),0)="","?",VLOOKUP(G$1,INDIRECT("'"&$A46&"'!$A$12:$Z$19"),MATCH("Points (Auto-generate)",INDIRECT("'"&$A46&"'!$A$12:$Z$12"),0),0)),"ER")) -> ? | H46: =IF($F46=0,"NA",IF($A46=INDIRECT("'"&$A46&"'!$B$1"),IF(VLOOKUP(H$1,INDIRECT("'"&$A46&"'!$A$12:$Z$19"),MATCH("Points (Auto-generate)",INDIRECT("'"&$A46&"'!$A$12:$Z$12"),0),0)="","?",VLOOKUP(H$1,INDIRECT("'"&$A46&"'!$A$12:$Z$19"),MATCH("Points (Auto-generate)",INDIRECT("'"&$A46&"'!$A$12:$Z$12"),0),0)),"ER")) -> ? | I46: =IF($F46=0,"NA",IF($A46=INDIRECT("'"&$A46&"'!$B$1"),IF(VLOOKUP(I$1,INDIRECT("'"&$A46&"'!$A$12:$Z$19"),MATCH("Points (Auto-generate)",INDIRECT("'"&$A46&"'!$A$12:$Z$12"),0),0)="","?",VLOOKUP(I$1,INDIRECT("'"&$A46&"'!$A$12:$Z$19"),MATCH("Points (Auto-generate)",INDIRECT("'"&$A46&"'!$A$12:$Z$12"),0),0)),"ER")) -> NA | J46: =IF($F46=0,"NA",IF($A46=INDIRECT("'"&$A46&"'!$B$1"),IF(VLOOKUP(J$1,INDIRECT("'"&$A46&"'!$A$12:$Z$19"),MATCH("Points (Auto-generate)",INDIRECT("'"&$A46&"'!$A$12:$Z$12"),0),0)="","?",VLOOKUP(J$1,INDIRECT("'"&$A46&"'!$A$12:$Z$19"),MATCH("Points (Auto-generate)",INDIRECT("'"&$A46&"'!$A$12:$Z$12"),0),0)),"ER")) -> 2.5 | K46: =IF($F46=0,"NA",IF($A46=INDIRECT("'"&$A46&"'!$B$1"),IF(VLOOKUP(K$1,INDIRECT("'"&$A46&"'!$A$12:$Z$19"),MATCH("Points (Auto-generate)",INDIRECT("'"&$A46&"'!$A$12:$Z$12"),0),0)="","?",VLOOKUP(K$1,INDIRECT("'"&$A46&"'!$A$12:$Z$19"),MATCH("Points (Auto-generate)",INDIRECT("'"&$A46&"'!$A$12:$Z$12"),0),0)),"ER")) -> NA | L46: =IF($F46=0,"NA",IF($A46=INDIRECT("'"&$A46&"'!$B$1"),IF(VLOOKUP(L$1,INDIRECT("'"&$A46&"'!$A$12:$Z$19"),MATCH("Points (Auto-generate)",INDIRECT("'"&$A46&"'!$A$12:$Z$12"),0),0)="","?",VLOOKUP(L$1,INDIRECT("'"&$A46&"'!$A$12:$Z$19"),MATCH("Points (Auto-generate)",INDIRECT("'"&$A46&"'!$A$12:$Z$12"),0),0)),"ER")) -> NA | M46: =IF($F46=0,"NA",IF($A46=INDIRECT("'"&$A46&"'!$B$1"),IF(VLOOKUP(M$1,INDIRECT("'"&$A46&"'!$A$12:$Z$19"),MATCH("Points (Auto-generate)",INDIRECT("'"&$A46&"'!$A$12:$Z$12"),0),0)="","?",VLOOKUP(M$1,INDIRECT("'"&$A46&"'!$A$12:$Z$19"),MATCH("Points (Auto-generate)",INDIRECT("'"&$A46&"'!$A$12:$Z$12"),0),0)),"ER")) -> ?
A47: SC1 | B47: =VLOOKUP($A47,'PARASTATAL Questions'!$A:$J,3,0)&"" -> State Capacities | C47: =VLOOKUP($A47,'PARASTATAL Questions'!$A:$J,4,0)&"" -> MQ | D47: =VLOOKUP($A47,'PARASTATAL Questions'!$A:$J,5,0)&"" -> What proportion of the parastatal's total expenditure is financed through its own revenues? | E47: =VLOOKUP($A47,'PARASTATAL Questions'!$A:$J,7,0)&"" -> Implementation (Numeric) | F47: =VLOOKUP($A47,'PARASTATAL Questions'!$A:$J,6,0) -> 10 | G47: =IF($F47=0,"NA",IF($A47=INDIRECT("'"&$A47&"'!$B$1"),IF(VLOOKUP(G$1,INDIRECT("'"&$A47&"'!$A$12:$Z$19"),MATCH("Points (Auto-generate)",INDIRECT("'"&$A47&"'!$A$12:$Z$12"),0),0)="","?",VLOOKUP(G$1,INDIRECT("'"&$A47&"'!$A$12:$Z$19"),MATCH("Points (Auto-generate)",INDIRECT("'"&$A47&"'!$A$12:$Z$12"),0),0)),"ER")) -> ? | H47: =IF($F47=0,"NA",IF($A47=INDIRECT("'"&$A47&"'!$B$1"),IF(VLOOKUP(H$1,INDIRECT("'"&$A47&"'!$A$12:$Z$19"),MATCH("Points (Auto-generate)",INDIRECT("'"&$A47&"'!$A$12:$Z$12"),0),0)="","?",VLOOKUP(H$1,INDIRECT("'"&$A47&"'!$A$12:$Z$19"),MATCH("Points (Auto-generate)",INDIRECT("'"&$A47&"'!$A$12:$Z$12"),0),0)),"ER")) -> ? | I47: =IF($F47=0,"NA",IF($A47=INDIRECT("'"&$A47&"'!$B$1"),IF(VLOOKUP(I$1,INDIRECT("'"&$A47&"'!$A$12:$Z$19"),MATCH("Points (Auto-generate)",INDIRECT("'"&$A47&"'!$A$12:$Z$12"),0),0)="","?",VLOOKUP(I$1,INDIRECT("'"&$A47&"'!$A$12:$Z$19"),MATCH("Points (Auto-generate)",INDIRECT("'"&$A47&"'!$A$12:$Z$12"),0),0)),"ER")) -> ? | J47: =IF($F47=0,"NA",IF($A47=INDIRECT("'"&$A47&"'!$B$1"),IF(VLOOKUP(J$1,INDIRECT("'"&$A47&"'!$A$12:$Z$19"),MATCH("Points (Auto-generate)",INDIRECT("'"&$A47&"'!$A$12:$Z$12"),0),0)="","?",VLOOKUP(J$1,INDIRECT("'"&$A47&"'!$A$12:$Z$19"),MATCH("Points (Auto-generate)",INDIRECT("'"&$A47&"'!$A$12:$Z$12"),0),0)),"ER")) -> NA | K47: =IF($F47=0,"NA",IF($A47=INDIRECT("'"&$A47&"'!$B$1"),IF(VLOOKUP(K$1,INDIRECT("'"&$A47&"'!$A$12:$Z$19"),MATCH("Points (Auto-generate)",INDIRECT("'"&$A47&"'!$A$12:$Z$12"),0),0)="","?",VLOOKUP(K$1,INDIRECT("'"&$A47&"'!$A$12:$Z$19"),MATCH("Points (Auto-generate)",INDIRECT("'"&$A47&"'!$A$12:$Z$12"),0),0)),"ER")) -> NA | L47: =IF($F47=0,"NA",IF($A47=INDIRECT("'"&$A47&"'!$B$1"),IF(VLOOKUP(L$1,INDIRECT("'"&$A47&"'!$A$12:$Z$19"),MATCH("Points (Auto-generate)",INDIRECT("'"&$A47&"'!$A$12:$Z$12"),0),0)="","?",VLOOKUP(L$1,INDIRECT("'"&$A47&"'!$A$12:$Z$19"),MATCH("Points (Auto-generate)",INDIRECT("'"&$A47&"'!$A$12:$Z$12"),0),0)),"ER")) -> NA | M47: =IF($F47=0,"NA",IF($A47=INDIRECT("'"&$A47&"'!$B$1"),IF(VLOOKUP(M$1,INDIRECT("'"&$A47&"'!$A$12:$Z$19"),MATCH("Points (Auto-generate)",INDIRECT("'"&$A47&"'!$A$12:$Z$12"),0),0)="","?",VLOOKUP(M$1,INDIRECT("'"&$A47&"'!$A$12:$Z$19"),MATCH("Points (Auto-generate)",INDIRECT("'"&$A47&"'!$A$12:$Z$12"),0),0)),"ER")) -> NA
A48: SC2 | B48: =VLOOKUP($A48,'PARASTATAL Questions'!$A:$J,3,0)&"" -> State Capacities | C48: =VLOOKUP($A48,'PARASTATAL Questions'!$A:$J,4,0)&"" -> MQ | D48: =VLOOKUP($A48,'PARASTATAL Questions'!$A:$J,5,0)&"" -> What is the parastatal's per-capita capital expenditure? | E48: =VLOOKUP($A48,'PARASTATAL Questions'!$A:$J,7,0)&"" -> Implementation (Numeric) | F48: =VLOOKUP($A48,'PARASTATAL Questions'!$A:$J,6,0) -> 10 | G48: =IF($F48=0,"NA",IF($A48=INDIRECT("'"&$A48&"'!$B$1"),IF(VLOOKUP(G$1,INDIRECT("'"&$A48&"'!$A$12:$Z$19"),MATCH("Points (Auto-generate)",INDIRECT("'"&$A48&"'!$A$12:$Z$12"),0),0)="","?",VLOOKUP(G$1,INDIRECT("'"&$A48&"'!$A$12:$Z$19"),MATCH("Points (Auto-generate)",INDIRECT("'"&$A48&"'!$A$12:$Z$12"),0),0)),"ER")) -> ? | H48: =IF($F48=0,"NA",IF($A48=INDIRECT("'"&$A48&"'!$B$1"),IF(VLOOKUP(H$1,INDIRECT("'"&$A48&"'!$A$12:$Z$19"),MATCH("Points (Auto-generate)",INDIRECT("'"&$A48&"'!$A$12:$Z$12"),0),0)="","?",VLOOKUP(H$1,INDIRECT("'"&$A48&"'!$A$12:$Z$19"),MATCH("Points (Auto-generate)",INDIRECT("'"&$A48&"'!$A$12:$Z$12"),0),0)),"ER")) -> ? | I48: =IF($F48=0,"NA",IF($A48=INDIRECT("'"&$A48&"'!$B$1"),IF(VLOOKUP(I$1,INDIRECT("'"&$A48&"'!$A$12:$Z$19"),MATCH("Points (Auto-generate)",INDIRECT("'"&$A48&"'!$A$12:$Z$12"),0),0)="","?",VLOOKUP(I$1,INDIRECT("'"&$A48&"'!$A$12:$Z$19"),MATCH("Points (Auto-generate)",INDIRECT("'"&$A48&"'!$A$12:$Z$12"),0),0)),"ER")) -> ? | J48: =IF($F48=0,"NA",IF($A48=INDIRECT("'"&$A48&"'!$B$1"),IF(VLOOKUP(J$1,INDIRECT("'"&$A48&"'!$A$12:$Z$19"),MATCH("Points (Auto-generate)",INDIRECT("'"&$A48&"'!$A$12:$Z$12"),0),0)="","?",VLOOKUP(J$1,INDIRECT("'"&$A48&"'!$A$12:$Z$19"),MATCH("Points (Auto-generate)",INDIRECT("'"&$A48&"'!$A$12:$Z$12"),0),0)),"ER")) -> ? | K48: =IF($F48=0,"NA",IF($A48=INDIRECT("'"&$A48&"'!$B$1"),IF(VLOOKUP(K$1,INDIRECT("'"&$A48&"'!$A$12:$Z$19"),MATCH("Points (Auto-generate)",INDIRECT("'"&$A48&"'!$A$12:$Z$12"),0),0)="","?",VLOOKUP(K$1,INDIRECT("'"&$A48&"'!$A$12:$Z$19"),MATCH("Points (Auto-generate)",INDIRECT("'"&$A48&"'!$A$12:$Z$12"),0),0)),"ER")) -> NA | L48: =IF($F48=0,"NA",IF($A48=INDIRECT("'"&$A48&"'!$B$1"),IF(VLOOKUP(L$1,INDIRECT("'"&$A48&"'!$A$12:$Z$19"),MATCH("Points (Auto-generate)",INDIRECT("'"&$A48&"'!$A$12:$Z$12"),0),0)="","?",VLOOKUP(L$1,INDIRECT("'"&$A48&"'!$A$12:$Z$19"),MATCH("Points (Auto-generate)",INDIRECT("'"&$A48&"'!$A$12:$Z$12"),0),0)),"ER")) -> NA | M48: =IF($F48=0,"NA",IF($A48=INDIRECT("'"&$A48&"'!$B$1"),IF(VLOOKUP(M$1,INDIRECT("'"&$A48&"'!$A$12:$Z$19"),MATCH("Points (Auto-generate)",INDIRECT("'"&$A48&"'!$A$12:$Z$12"),0),0)="","?",VLOOKUP(M$1,INDIRECT("'"&$A48&"'!$A$12:$Z$19"),MATCH("Points (Auto-generate)",INDIRECT("'"&$A48&"'!$A$12:$Z$12"),0),0)),"ER")) -> ?
A49: SC3 | B49: =VLOOKUP($A49,'PARASTATAL Questions'!$A:$J,3,0)&"" -> State Capacities | C49: =VLOOKUP($A49,'PARASTATAL Questions'!$A:$J,4,0)&"" -> MQ | D49: =VLOOKUP($A49,'PARASTATAL Questions'!$A:$J,5,0)&"" -> How realistic is the parastatal's annual budget? | E49: =VLOOKUP($A49,'PARASTATAL Questions'!$A:$J,7,0)&"" -> Implementation (Numeric) | F49: =VLOOKUP($A49,'PARASTATAL Questions'!$A:$J,6,0) -> 10 | G49: =IF($F49=0,"NA",IF($A49=INDIRECT("'"&$A49&"'!$B$1"),IF(VLOOKUP(G$1,INDIRECT("'"&$A49&"'!$A$12:$Z$19"),MATCH("Points (Auto-generate)",INDIRECT("'"&$A49&"'!$A$12:$Z$12"),0),0)="","?",VLOOKUP(G$1,INDIRECT("'"&$A49&"'!$A$12:$Z$19"),MATCH("Points (Auto-generate)",INDIRECT("'"&$A49&"'!$A$12:$Z$12"),0),0)),"ER")) -> ? | H49: =IF($F49=0,"NA",IF($A49=INDIRECT("'"&$A49&"'!$B$1"),IF(VLOOKUP(H$1,INDIRECT("'"&$A49&"'!$A$12:$Z$19"),MATCH("Points (Auto-generate)",INDIRECT("'"&$A49&"'!$A$12:$Z$12"),0),0)="","?",VLOOKUP(H$1,INDIRECT("'"&$A49&"'!$A$12:$Z$19"),MATCH("Points (Auto-generate)",INDIRECT("'"&$A49&"'!$A$12:$Z$12"),0),0)),"ER")) -> ? | I49: =IF($F49=0,"NA",IF($A49=INDIRECT("'"&$A49&"'!$B$1"),IF(VLOOKUP(I$1,INDIRECT("'"&$A49&"'!$A$12:$Z$19"),MATCH("Points (Auto-generate)",INDIRECT("'"&$A49&"'!$A$12:$Z$12"),0),0)="","?",VLOOKUP(I$1,INDIRECT("'"&$A49&"'!$A$12:$Z$19"),MATCH("Points (Auto-generate)",INDIRECT("'"&$A49&"'!$A$12:$Z$12"),0),0)),"ER")) -> ? | J49: =IF($F49=0,"NA",IF($A49=INDIRECT("'"&$A49&"'!$B$1"),IF(VLOOKUP(J$1,INDIRECT("'"&$A49&"'!$A$12:$Z$19"),MATCH("Points (Auto-generate)",INDIRECT("'"&$A49&"'!$A$12:$Z$12"),0),0)="","?",VLOOKUP(J$1,INDIRECT("'"&$A49&"'!$A$12:$Z$19"),MATCH("Points (Auto-generate)",INDIRECT("'"&$A49&"'!$A$12:$Z$12"),0),0)),"ER")) -> ? | K49: =IF($F49=0,"NA",IF($A49=INDIRECT("'"&$A49&"'!$B$1"),IF(VLOOKUP(K$1,INDIRECT("'"&$A49&"'!$A$12:$Z$19"),MATCH("Points (Auto-generate)",INDIRECT("'"&$A49&"'!$A$12:$Z$12"),0),0)="","?",VLOOKUP(K$1,INDIRECT("'"&$A49&"'!$A$12:$Z$19"),MATCH("Points (Auto-generate)",INDIRECT("'"&$A49&"'!$A$12:$Z$12"),0),0)),"ER")) -> ? | L49: =IF($F49=0,"NA",IF($A49=INDIRECT("'"&$A49&"'!$B$1"),IF(VLOOKUP(L$1,INDIRECT("'"&$A49&"'!$A$12:$Z$19"),MATCH("Points (Auto-generate)",INDIRECT("'"&$A49&"'!$A$12:$Z$12"),0),0)="","?",VLOOKUP(L$1,INDIRECT("'"&$A49&"'!$A$12:$Z$19"),MATCH("Points (Auto-generate)",INDIRECT("'"&$A49&"'!$A$12:$Z$12"),0),0)),"ER")) -> ? | M49: =IF($F49=0,"NA",IF($A49=INDIRECT("'"&$A49&"'!$B$1"),IF(VLOOKUP(M$1,INDIRECT("'"&$A49&"'!$A$12:$Z$19"),MATCH("Points (Auto-generate)",INDIRECT("'"&$A49&"'!$A$12:$Z$12"),0),0)="","?",VLOOKUP(M$1,INDIRECT("'"&$A49&"'!$A$12:$Z$19"),MATCH("Points (Auto-generate)",INDIRECT("'"&$A49&"'!$A$12:$Z$12"),0),0)),"ER")) -> ?
A50: SC4 | B50: =VLOOKUP($A50,'PARASTATAL Questions'!$A:$J,3,0)&"" -> State Capacities | C50: =VLOOKUP($A50,'PARASTATAL Questions'!$A:$J,4,0)&"" -> MQ | D50: =VLOOKUP($A50,'PARASTATAL Questions'!$A:$J,5,0)&"" -> Is the parastatal mandated to prepare a medium-term and/or long-term fiscal plan, and has it prepared a current plan in accordance with that mandate? | E50: =VLOOKUP($A50,'PARASTATAL Questions'!$A:$J,7,0)&"" -> Law/Policy | F50: =VLOOKUP($A50,'PARASTATAL Questions'!$A:$J,6,0) -> 10 | G50: =IF(OR(G51="ER",G52="ER"),"ER",IF(OR(G51="?",G52="?"),"?",IF(AND(G51="NA",G52="NA"),"NA",SUM(G51,G52)/((G51<>"NA")*$F$51+(G52<>"NA")*$F$52)*$F50))) -> ? | H50: =IF(OR(H51="ER",H52="ER"),"ER",IF(OR(H51="?",H52="?"),"?",IF(AND(H51="NA",H52="NA"),"NA",SUM(H51,H52)/((H51<>"NA")*$F$51+(H52<>"NA")*$F$52)*$F50))) -> ? | I50: =IF(OR(I51="ER",I52="ER"),"ER",IF(OR(I51="?",I52="?"),"?",IF(AND(I51="NA",I52="NA"),"NA",SUM(I51,I52)/((I51<>"NA")*$F$51+(I52<>"NA")*$F$52)*$F50))) -> ? | J50: =IF(OR(J51="ER",J52="ER"),"ER",IF(OR(J51="?",J52="?"),"?",IF(AND(J51="NA",J52="NA"),"NA",SUM(J51,J52)/((J51<>"NA")*$F$51+(J52<>"NA")*$F$52)*$F50))) -> ? | K50: =IF(OR(K51="ER",K52="ER"),"ER",IF(OR(K51="?",K52="?"),"?",IF(AND(K51="NA",K52="NA"),"NA",SUM(K51,K52)/((K51<>"NA")*$F$51+(K52<>"NA")*$F$52)*$F50))) -> ? | L50: =IF(OR(L51="ER",L52="ER"),"ER",IF(OR(L51="?",L52="?"),"?",IF(AND(L51="NA",L52="NA"),"NA",SUM(L51,L52)/((L51<>"NA")*$F$51+(L52<>"NA")*$F$52)*$F50))) -> ? | M50: =IF(OR(M51="ER",M52="ER"),"ER",IF(OR(M51="?",M52="?"),"?",IF(AND(M51="NA",M52="NA"),"NA",SUM(M51,M52)/((M51<>"NA")*$F$51+(M52<>"NA")*$F$52)*$F50))) -> ?
A51: SC4a | B51: =VLOOKUP($A51,'PARASTATAL Questions'!$A:$J,3,0)&"" -> State Capacities | C51: =VLOOKUP($A51,'PARASTATAL Questions'!$A:$J,4,0)&"" -> SQ | D51: =VLOOKUP($A51,'PARASTATAL Questions'!$A:$J,5,0)&"" -> Is a medium-term (3-5 year) and/or long-term (>5 year) fiscal plan legally mandated? | E51: =VLOOKUP($A51,'PARASTATAL Questions'!$A:$J,7,0)&"" -> Law/Policy | F51: =VLOOKUP($A51,'PARASTATAL Questions'!$A:$J,6,0) -> 5 | G51: =IF($F51=0,"NA",IF($A51=INDIRECT("'"&$A51&"'!$B$1"),IF(VLOOKUP(G$1,INDIRECT("'"&$A51&"'!$A$12:$Z$19"),MATCH("Points (Auto-generate)",INDIRECT("'"&$A51&"'!$A$12:$Z$12"),0),0)="","?",VLOOKUP(G$1,INDIRECT("'"&$A51&"'!$A$12:$Z$19"),MATCH("Points (Auto-generate)",INDIRECT("'"&$A51&"'!$A$12:$Z$12"),0),0)),"ER")) -> ? | H51: =IF($F51=0,"NA",IF($A51=INDIRECT("'"&$A51&"'!$B$1"),IF(VLOOKUP(H$1,INDIRECT("'"&$A51&"'!$A$12:$Z$19"),MATCH("Points (Auto-generate)",INDIRECT("'"&$A51&"'!$A$12:$Z$12"),0),0)="","?",VLOOKUP(H$1,INDIRECT("'"&$A51&"'!$A$12:$Z$19"),MATCH("Points (Auto-generate)",INDIRECT("'"&$A51&"'!$A$12:$Z$12"),0),0)),"ER")) -> ? | I51: =IF($F51=0,"NA",IF($A51=INDIRECT("'"&$A51&"'!$B$1"),IF(VLOOKUP(I$1,INDIRECT("'"&$A51&"'!$A$12:$Z$19"),MATCH("Points (Auto-generate)",INDIRECT("'"&$A51&"'!$A$12:$Z$12"),0),0)="","?",VLOOKUP(I$1,INDIRECT("'"&$A51&"'!$A$12:$Z$19"),MATCH("Points (Auto-generate)",INDIRECT("'"&$A51&"'!$A$12:$Z$12"),0),0)),"ER")) -> ? | J51: =IF($F51=0,"NA",IF($A51=INDIRECT("'"&$A51&"'!$B$1"),IF(VLOOKUP(J$1,INDIRECT("'"&$A51&"'!$A$12:$Z$19"),MATCH("Points (Auto-generate)",INDIRECT("'"&$A51&"'!$A$12:$Z$12"),0),0)="","?",VLOOKUP(J$1,INDIRECT("'"&$A51&"'!$A$12:$Z$19"),MATCH("Points (Auto-generate)",INDIRECT("'"&$A51&"'!$A$12:$Z$12"),0),0)),"ER")) -> ? | K51: =IF($F51=0,"NA",IF($A51=INDIRECT("'"&$A51&"'!$B$1"),IF(VLOOKUP(K$1,INDIRECT("'"&$A51&"'!$A$12:$Z$19"),MATCH("Points (Auto-generate)",INDIRECT("'"&$A51&"'!$A$12:$Z$12"),0),0)="","?",VLOOKUP(K$1,INDIRECT("'"&$A51&"'!$A$12:$Z$19"),MATCH("Points (Auto-generate)",INDIRECT("'"&$A51&"'!$A$12:$Z$12"),0),0)),"ER")) -> ? | L51: =IF($F51=0,"NA",IF($A51=INDIRECT("'"&$A51&"'!$B$1"),IF(VLOOKUP(L$1,INDIRECT("'"&$A51&"'!$A$12:$Z$19"),MATCH("Points (Auto-generate)",INDIRECT("'"&$A51&"'!$A$12:$Z$12"),0),0)="","?",VLOOKUP(L$1,INDIRECT("'"&$A51&"'!$A$12:$Z$19"),MATCH("Points (Auto-generate)",INDIRECT("'"&$A51&"'!$A$12:$Z$12"),0),0)),"ER")) -> ? | M51: =IF($F51=0,"NA",IF($A51=INDIRECT("'"&$A51&"'!$B$1"),IF(VLOOKUP(M$1,INDIRECT("'"&$A51&"'!$A$12:$Z$19"),MATCH("Points (Auto-generate)",INDIRECT("'"&$A51&"'!$A$12:$Z$12"),0),0)="","?",VLOOKUP(M$1,INDIRECT("'"&$A51&"'!$A$12:$Z$19"),MATCH("Points (Auto-generate)",INDIRECT("'"&$A51&"'!$A$12:$Z$12"),0),0)),"ER")) -> ?
A52: SC4b | B52: =VLOOKUP($A52,'PARASTATAL Questions'!$A:$J,3,0)&"" -> State Capacities | C52: =VLOOKUP($A52,'PARASTATAL Questions'!$A:$J,4,0)&"" -> SQ | D52: =VLOOKUP($A52,'PARASTATAL Questions'!$A:$J,5,0)&"" -> Is the medium/long-term fiscal plan publicly available? | E52: =VLOOKUP($A52,'PARASTATAL Questions'!$A:$J,7,0)&"" -> Implementation | F52: =VLOOKUP($A52,'PARASTATAL Questions'!$A:$J,6,0) -> 5 | G52: =IF($F52=0,"NA",IF($A52=INDIRECT("'"&$A52&"'!$B$1"),IF(VLOOKUP(G$1,INDIRECT("'"&$A52&"'!$A$12:$Z$19"),MATCH("Points (Auto-generate)",INDIRECT("'"&$A52&"'!$A$12:$Z$12"),0),0)="","?",VLOOKUP(G$1,INDIRECT("'"&$A52&"'!$A$12:$Z$19"),MATCH("Points (Auto-generate)",INDIRECT("'"&$A52&"'!$A$12:$Z$12"),0),0)),"ER")) -> ? | H52: =IF($F52=0,"NA",IF($A52=INDIRECT("'"&$A52&"'!$B$1"),IF(VLOOKUP(H$1,INDIRECT("'"&$A52&"'!$A$12:$Z$19"),MATCH("Points (Auto-generate)",INDIRECT("'"&$A52&"'!$A$12:$Z$12"),0),0)="","?",VLOOKUP(H$1,INDIRECT("'"&$A52&"'!$A$12:$Z$19"),MATCH("Points (Auto-generate)",INDIRECT("'"&$A52&"'!$A$12:$Z$12"),0),0)),"ER")) -> ? | I52: =IF($F52=0,"NA",IF($A52=INDIRECT("'"&$A52&"'!$B$1"),IF(VLOOKUP(I$1,INDIRECT("'"&$A52&"'!$A$12:$Z$19"),MATCH("Points (Auto-generate)",INDIRECT("'"&$A52&"'!$A$12:$Z$12"),0),0)="","?",VLOOKUP(I$1,INDIRECT("'"&$A52&"'!$A$12:$Z$19"),MATCH("Points (Auto-generate)",INDIRECT("'"&$A52&"'!$A$12:$Z$12"),0),0)),"ER")) -> ? | J52: =IF($F52=0,"NA",IF($A52=INDIRECT("'"&$A52&"'!$B$1"),IF(VLOOKUP(J$1,INDIRECT("'"&$A52&"'!$A$12:$Z$19"),MATCH("Points (Auto-generate)",INDIRECT("'"&$A52&"'!$A$12:$Z$12"),0),0)="","?",VLOOKUP(J$1,INDIRECT("'"&$A52&"'!$A$12:$Z$19"),MATCH("Points (Auto-generate)",INDIRECT("'"&$A52&"'!$A$12:$Z$12"),0),0)),"ER")) -> ? | K52: =IF($F52=0,"NA",IF($A52=INDIRECT("'"&$A52&"'!$B$1"),IF(VLOOKUP(K$1,INDIRECT("'"&$A52&"'!$A$12:$Z$19"),MATCH("Points (Auto-generate)",INDIRECT("'"&$A52&"'!$A$12:$Z$12"),0),0)="","?",VLOOKUP(K$1,INDIRECT("'"&$A52&"'!$A$12:$Z$19"),MATCH("Points (Auto-generate)",INDIRECT("'"&$A52&"'!$A$12:$Z$12"),0),0)),"ER")) -> ? | L52: =IF($F52=0,"NA",IF($A52=INDIRECT("'"&$A52&"'!$B$1"),IF(VLOOKUP(L$1,INDIRECT("'"&$A52&"'!$A$12:$Z$19"),MATCH("Points (Auto-generate)",INDIRECT("'"&$A52&"'!$A$12:$Z$12"),0),0)="","?",VLOOKUP(L$1,INDIRECT("'"&$A52&"'!$A$12:$Z$19"),MATCH("Points (Auto-generate)",INDIRECT("'"&$A52&"'!$A$12:$Z$12"),0),0)),"ER")) -> ? | M52: =IF($F52=0,"NA",IF($A52=INDIRECT("'"&$A52&"'!$B$1"),IF(VLOOKUP(M$1,INDIRECT("'"&$A52&"'!$A$12:$Z$19"),MATCH("Points (Auto-generate)",INDIRECT("'"&$A52&"'!$A$12:$Z$12"),0),0)="","?",VLOOKUP(M$1,INDIRECT("'"&$A52&"'!$A$12:$Z$19"),MATCH("Points (Auto-generate)",INDIRECT("'"&$A52&"'!$A$12:$Z$12"),0),0)),"ER")) -> ?
A53: SC5 | B53: =VLOOKUP($A53,'PARASTATAL Questions'!$A:$J,3,0)&"" -> State Capacities | C53: =VLOOKUP($A53,'PARASTATAL Questions'!$A:$J,4,0)&"" -> MQ | D53: =VLOOKUP($A53,'PARASTATAL Questions'!$A:$J,5,0)&"" -> Does the parastatal follow a double-entry accounting system? | E53: =VLOOKUP($A53,'PARASTATAL Questions'!$A:$J,7,0)&"" -> Implementation | F53: =VLOOKUP($A53,'PARASTATAL Questions'!$A:$J,6,0) -> 10 | G53: =IF($F53=0,"NA",IF($A53=INDIRECT("'"&$A53&"'!$B$1"),IF(VLOOKUP(G$1,INDIRECT("'"&$A53&"'!$A$12:$Z$19"),MATCH("Points (Auto-generate)",INDIRECT("'"&$A53&"'!$A$12:$Z$12"),0),0)="","?",VLOOKUP(G$1,INDIRECT("'"&$A53&"'!$A$12:$Z$19"),MATCH("Points (Auto-generate)",INDIRECT("'"&$A53&"'!$A$12:$Z$12"),0),0)),"ER")) -> ? | H53: =IF($F53=0,"NA",IF($A53=INDIRECT("'"&$A53&"'!$B$1"),IF(VLOOKUP(H$1,INDIRECT("'"&$A53&"'!$A$12:$Z$19"),MATCH("Points (Auto-generate)",INDIRECT("'"&$A53&"'!$A$12:$Z$12"),0),0)="","?",VLOOKUP(H$1,INDIRECT("'"&$A53&"'!$A$12:$Z$19"),MATCH("Points (Auto-generate)",INDIRECT("'"&$A53&"'!$A$12:$Z$12"),0),0)),"ER")) -> ? | I53: =IF($F53=0,"NA",IF($A53=INDIRECT("'"&$A53&"'!$B$1"),IF(VLOOKUP(I$1,INDIRECT("'"&$A53&"'!$A$12:$Z$19"),MATCH("Points (Auto-generate)",INDIRECT("'"&$A53&"'!$A$12:$Z$12"),0),0)="","?",VLOOKUP(I$1,INDIRECT("'"&$A53&"'!$A$12:$Z$19"),MATCH("Points (Auto-generate)",INDIRECT("'"&$A53&"'!$A$12:$Z$12"),0),0)),"ER")) -> ? | J53: =IF($F53=0,"NA",IF($A53=INDIRECT("'"&$A53&"'!$B$1"),IF(VLOOKUP(J$1,INDIRECT("'"&$A53&"'!$A$12:$Z$19"),MATCH("Points (Auto-generate)",INDIRECT("'"&$A53&"'!$A$12:$Z$12"),0),0)="","?",VLOOKUP(J$1,INDIRECT("'"&$A53&"'!$A$12:$Z$19"),MATCH("Points (Auto-generate)",INDIRECT("'"&$A53&"'!$A$12:$Z$12"),0),0)),"ER")) -> ? | K53: =IF($F53=0,"NA",IF($A53=INDIRECT("'"&$A53&"'!$B$1"),IF(VLOOKUP(K$1,INDIRECT("'"&$A53&"'!$A$12:$Z$19"),MATCH("Points (Auto-generate)",INDIRECT("'"&$A53&"'!$A$12:$Z$12"),0),0)="","?",VLOOKUP(K$1,INDIRECT("'"&$A53&"'!$A$12:$Z$19"),MATCH("Points (Auto-generate)",INDIRECT("'"&$A53&"'!$A$12:$Z$12"),0),0)),"ER")) -> ? | L53: =IF($F53=0,"NA",IF($A53=INDIRECT("'"&$A53&"'!$B$1"),IF(VLOOKUP(L$1,INDIRECT("'"&$A53&"'!$A$12:$Z$19"),MATCH("Points (Auto-generate)",INDIRECT("'"&$A53&"'!$A$12:$Z$12"),0),0)="","?",VLOOKUP(L$1,INDIRECT("'"&$A53&"'!$A$12:$Z$19"),MATCH("Points (Auto-generate)",INDIRECT("'"&$A53&"'!$A$12:$Z$12"),0),0)),"ER")) -> ? | M53: =IF($F53=0,"NA",IF($A53=INDIRECT("'"&$A53&"'!$B$1"),IF(VLOOKUP(M$1,INDIRECT("'"&$A53&"'!$A$12:$Z$19"),MATCH("Points (Auto-generate)",INDIRECT("'"&$A53&"'!$A$12:$Z$12"),0),0)="","?",VLOOKUP(M$1,INDIRECT("'"&$A53&"'!$A$12:$Z$19"),MATCH("Points (Auto-generate)",INDIRECT("'"&$A53&"'!$A$12:$Z$12"),0),0)),"ER")) -> ?
A54: SC6 | B54: =VLOOKUP($A54,'PARASTATAL Questions'!$A:$J,3,0)&"" -> State Capacities | C54: =VLOOKUP($A54,'PARASTATAL Questions'!$A:$J,4,0)&"" -> MQ | D54: =VLOOKUP($A54,'PARASTATAL Questions'!$A:$J,5,0)&"" -> What is the average tenure of the chief executive/executive authority of the parastatal? | E54: =VLOOKUP($A54,'PARASTATAL Questions'!$A:$J,7,0)&"" -> Implementation (Numeric) | F54: =VLOOKUP($A54,'PARASTATAL Questions'!$A:$J,6,0) -> 10 | G54: =IF($F54=0,"NA",IF($A54=INDIRECT("'"&$A54&"'!$B$1"),IF(VLOOKUP(G$1,INDIRECT("'"&$A54&"'!$A$12:$Z$19"),MATCH("Points (Auto-generate)",INDIRECT("'"&$A54&"'!$A$12:$Z$12"),0),0)="","?",VLOOKUP(G$1,INDIRECT("'"&$A54&"'!$A$12:$Z$19"),MATCH("Points (Auto-generate)",INDIRECT("'"&$A54&"'!$A$12:$Z$12"),0),0)),"ER")) -> ? | H54: =IF($F54=0,"NA",IF($A54=INDIRECT("'"&$A54&"'!$B$1"),IF(VLOOKUP(H$1,INDIRECT("'"&$A54&"'!$A$12:$Z$19"),MATCH("Points (Auto-generate)",INDIRECT("'"&$A54&"'!$A$12:$Z$12"),0),0)="","?",VLOOKUP(H$1,INDIRECT("'"&$A54&"'!$A$12:$Z$19"),MATCH("Points (Auto-generate)",INDIRECT("'"&$A54&"'!$A$12:$Z$12"),0),0)),"ER")) -> ? | I54: =IF($F54=0,"NA",IF($A54=INDIRECT("'"&$A54&"'!$B$1"),IF(VLOOKUP(I$1,INDIRECT("'"&$A54&"'!$A$12:$Z$19"),MATCH("Points (Auto-generate)",INDIRECT("'"&$A54&"'!$A$12:$Z$12"),0),0)="","?",VLOOKUP(I$1,INDIRECT("'"&$A54&"'!$A$12:$Z$19"),MATCH("Points (Auto-generate)",INDIRECT("'"&$A54&"'!$A$12:$Z$12"),0),0)),"ER")) -> ? | J54: =IF($F54=0,"NA",IF($A54=INDIRECT("'"&$A54&"'!$B$1"),IF(VLOOKUP(J$1,INDIRECT("'"&$A54&"'!$A$12:$Z$19"),MATCH("Points (Auto-generate)",INDIRECT("'"&$A54&"'!$A$12:$Z$12"),0),0)="","?",VLOOKUP(J$1,INDIRECT("'"&$A54&"'!$A$12:$Z$19"),MATCH("Points (Auto-generate)",INDIRECT("'"&$A54&"'!$A$12:$Z$12"),0),0)),"ER")) -> ? | K54: =IF($F54=0,"NA",IF($A54=INDIRECT("'"&$A54&"'!$B$1"),IF(VLOOKUP(K$1,INDIRECT("'"&$A54&"'!$A$12:$Z$19"),MATCH("Points (Auto-generate)",INDIRECT("'"&$A54&"'!$A$12:$Z$12"),0),0)="","?",VLOOKUP(K$1,INDIRECT("'"&$A54&"'!$A$12:$Z$19"),MATCH("Points (Auto-generate)",INDIRECT("'"&$A54&"'!$A$12:$Z$12"),0),0)),"ER")) -> ? | L54: =IF($F54=0,"NA",IF($A54=INDIRECT("'"&$A54&"'!$B$1"),IF(VLOOKUP(L$1,INDIRECT("'"&$A54&"'!$A$12:$Z$19"),MATCH("Points (Auto-generate)",INDIRECT("'"&$A54&"'!$A$12:$Z$12"),0),0)="","?",VLOOKUP(L$1,INDIRECT("'"&$A54&"'!$A$12:$Z$19"),MATCH("Points (Auto-generate)",INDIRECT("'"&$A54&"'!$A$12:$Z$12"),0),0)),"ER")) -> ? | M54: =IF($F54=0,"NA",IF($A54=INDIRECT("'"&$A54&"'!$B$1"),IF(VLOOKUP(M$1,INDIRECT("'"&$A54&"'!$A$12:$Z$19"),MATCH("Points (Auto-generate)",INDIRECT("'"&$A54&"'!$A$12:$Z$12"),0),0)="","?",VLOOKUP(M$1,INDIRECT("'"&$A54&"'!$A$12:$Z$19"),MATCH("Points (Auto-generate)",INDIRECT("'"&$A54&"'!$A$12:$Z$12"),0),0)),"ER")) -> ?
A55: SC7 | B55: =VLOOKUP($A55,'PARASTATAL Questions'!$A:$J,3,0)&"" -> State Capacities | C55: =VLOOKUP($A55,'PARASTATAL Questions'!$A:$J,4,0)&"" -> MQ | D55: =VLOOKUP($A55,'PARASTATAL Questions'!$A:$J,5,0)&"" -> Does the parastatal have adequate and representative staffing capacity to discharge its mandate? | E55: =VLOOKUP($A55,'PARASTATAL Questions'!$A:$J,7,0)&"" -> Implementation (Numeric) | F55: =VLOOKUP($A55,'PARASTATAL Questions'!$A:$J,6,0) -> 10 | G55: =IF(OR(G56="ER",G57="ER"),"ER",IF(OR(G56="?",G57="?"),"?",IF(AND(G56="NA",G57="NA"),"NA",SUM(G56,G57)/((G56<>"NA")*$F$56+(G57<>"NA")*$F$57)*$F55))) -> ? | H55: =IF(OR(H56="ER",H57="ER"),"ER",IF(OR(H56="?",H57="?"),"?",IF(AND(H56="NA",H57="NA"),"NA",SUM(H56,H57)/((H56<>"NA")*$F$56+(H57<>"NA")*$F$57)*$F55))) -> ? | I55: =IF(OR(I56="ER",I57="ER"),"ER",IF(OR(I56="?",I57="?"),"?",IF(AND(I56="NA",I57="NA"),"NA",SUM(I56,I57)/((I56<>"NA")*$F$56+(I57<>"NA")*$F$57)*$F55))) -> ? | J55: =IF(OR(J56="ER",J57="ER"),"ER",IF(OR(J56="?",J57="?"),"?",IF(AND(J56="NA",J57="NA"),"NA",SUM(J56,J57)/((J56<>"NA")*$F$56+(J57<>"NA")*$F$57)*$F55))) -> ? | K55: =IF(OR(K56="ER",K57="ER"),"ER",IF(OR(K56="?",K57="?"),"?",IF(AND(K56="NA",K57="NA"),"NA",SUM(K56,K57)/((K56<>"NA")*$F$56+(K57<>"NA")*$F$57)*$F55))) -> ? | L55: =IF(OR(L56="ER",L57="ER"),"ER",IF(OR(L56="?",L57="?"),"?",IF(AND(L56="NA",L57="NA"),"NA",SUM(L56,L57)/((L56<>"NA")*$F$56+(L57<>"NA")*$F$57)*$F55))) -> ? | M55: =IF(OR(M56="ER",M57="ER"),"ER",IF(OR(M56="?",M57="?"),"?",IF(AND(M56="NA",M57="NA"),"NA",SUM(M56,M57)/((M56<>"NA")*$F$56+(M57<>"NA")*$F$57)*$F55))) -> ?
A56: SC7a | B56: =VLOOKUP($A56,'PARASTATAL Questions'!$A:$J,3,0)&"" -> State Capacities | C56: =VLOOKUP($A56,'PARASTATAL Questions'!$A:$J,4,0)&"" -> SQ | D56: =VLOOKUP($A56,'PARASTATAL Questions'!$A:$J,5,0)&"" -> Does the parastatal have adequate staffing capacity to discharge its mandate? | E56: =VLOOKUP($A56,'PARASTATAL Questions'!$A:$J,7,0)&"" -> Implementation (Numeric) | F56: =VLOOKUP($A56,'PARASTATAL Questions'!$A:$J,6,0) -> 5 | G56: =IF($F56=0,"NA",IF($A56=INDIRECT("'"&$A56&"'!$B$1"),IF(VLOOKUP(G$1,INDIRECT("'"&$A56&"'!$A$12:$Z$19"),MATCH("Points (Auto-generate)",INDIRECT("'"&$A56&"'!$A$12:$Z$12"),0),0)="","?",VLOOKUP(G$1,INDIRECT("'"&$A56&"'!$A$12:$Z$19"),MATCH("Points (Auto-generate)",INDIRECT("'"&$A56&"'!$A$12:$Z$12"),0),0)),"ER")) -> ? | H56: =IF($F56=0,"NA",IF($A56=INDIRECT("'"&$A56&"'!$B$1"),IF(VLOOKUP(H$1,INDIRECT("'"&$A56&"'!$A$12:$Z$19"),MATCH("Points (Auto-generate)",INDIRECT("'"&$A56&"'!$A$12:$Z$12"),0),0)="","?",VLOOKUP(H$1,INDIRECT("'"&$A56&"'!$A$12:$Z$19"),MATCH("Points (Auto-generate)",INDIRECT("'"&$A56&"'!$A$12:$Z$12"),0),0)),"ER")) -> ? | I56: =IF($F56=0,"NA",IF($A56=INDIRECT("'"&$A56&"'!$B$1"),IF(VLOOKUP(I$1,INDIRECT("'"&$A56&"'!$A$12:$Z$19"),MATCH("Points (Auto-generate)",INDIRECT("'"&$A56&"'!$A$12:$Z$12"),0),0)="","?",VLOOKUP(I$1,INDIRECT("'"&$A56&"'!$A$12:$Z$19"),MATCH("Points (Auto-generate)",INDIRECT("'"&$A56&"'!$A$12:$Z$12"),0),0)),"ER")) -> ? | J56: =IF($F56=0,"NA",IF($A56=INDIRECT("'"&$A56&"'!$B$1"),IF(VLOOKUP(J$1,INDIRECT("'"&$A56&"'!$A$12:$Z$19"),MATCH("Points (Auto-generate)",INDIRECT("'"&$A56&"'!$A$12:$Z$12"),0),0)="","?",VLOOKUP(J$1,INDIRECT("'"&$A56&"'!$A$12:$Z$19"),MATCH("Points (Auto-generate)",INDIRECT("'"&$A56&"'!$A$12:$Z$12"),0),0)),"ER")) -> ? | K56: =IF($F56=0,"NA",IF($A56=INDIRECT("'"&$A56&"'!$B$1"),IF(VLOOKUP(K$1,INDIRECT("'"&$A56&"'!$A$12:$Z$19"),MATCH("Points (Auto-generate)",INDIRECT("'"&$A56&"'!$A$12:$Z$12"),0),0)="","?",VLOOKUP(K$1,INDIRECT("'"&$A56&"'!$A$12:$Z$19"),MATCH("Points (Auto-generate)",INDIRECT("'"&$A56&"'!$A$12:$Z$12"),0),0)),"ER")) -> ? | L56: =IF($F56=0,"NA",IF($A56=INDIRECT("'"&$A56&"'!$B$1"),IF(VLOOKUP(L$1,INDIRECT("'"&$A56&"'!$A$12:$Z$19"),MATCH("Points (Auto-generate)",INDIRECT("'"&$A56&"'!$A$12:$Z$12"),0),0)="","?",VLOOKUP(L$1,INDIRECT("'"&$A56&"'!$A$12:$Z$19"),MATCH("Points (Auto-generate)",INDIRECT("'"&$A56&"'!$A$12:$Z$12"),0),0)),"ER")) -> ? | M56: =IF($F56=0,"NA",IF($A56=INDIRECT("'"&$A56&"'!$B$1"),IF(VLOOKUP(M$1,INDIRECT("'"&$A56&"'!$A$12:$Z$19"),MATCH("Points (Auto-generate)",INDIRECT("'"&$A56&"'!$A$12:$Z$12"),0),0)="","?",VLOOKUP(M$1,INDIRECT("'"&$A56&"'!$A$12:$Z$19"),MATCH("Points (Auto-generate)",INDIRECT("'"&$A56&"'!$A$12:$Z$12"),0),0)),"ER")) -> ?
A57: SC7b | B57: =VLOOKUP($A57,'PARASTATAL Questions'!$A:$J,3,0)&"" -> State Capacities | C57: =VLOOKUP($A57,'PARASTATAL Questions'!$A:$J,4,0)&"" -> SQ | D57: =VLOOKUP($A57,'PARASTATAL Questions'!$A:$J,5,0)&"" -> What proportion of the parastatal's workforce is women? | E57: =VLOOKUP($A57,'PARASTATAL Questions'!$A:$J,7,0)&"" -> Implementation (Numeric) | F57: =VLOOKUP($A57,'PARASTATAL Questions'!$A:$J,6,0) -> 5 | G57: =IF($F57=0,"NA",IF($A57=INDIRECT("'"&$A57&"'!$B$1"),IF(VLOOKUP(G$1,INDIRECT("'"&$A57&"'!$A$12:$Z$19"),MATCH("Points (Auto-generate)",INDIRECT("'"&$A57&"'!$A$12:$Z$12"),0),0)="","?",VLOOKUP(G$1,INDIRECT("'"&$A57&"'!$A$12:$Z$19"),MATCH("Points (Auto-generate)",INDIRECT("'"&$A57&"'!$A$12:$Z$12"),0),0)),"ER")) -> ? | H57: =IF($F57=0,"NA",IF($A57=INDIRECT("'"&$A57&"'!$B$1"),IF(VLOOKUP(H$1,INDIRECT("'"&$A57&"'!$A$12:$Z$19"),MATCH("Points (Auto-generate)",INDIRECT("'"&$A57&"'!$A$12:$Z$12"),0),0)="","?",VLOOKUP(H$1,INDIRECT("'"&$A57&"'!$A$12:$Z$19"),MATCH("Points (Auto-generate)",INDIRECT("'"&$A57&"'!$A$12:$Z$12"),0),0)),"ER")) -> ? | I57: =IF($F57=0,"NA",IF($A57=INDIRECT("'"&$A57&"'!$B$1"),IF(VLOOKUP(I$1,INDIRECT("'"&$A57&"'!$A$12:$Z$19"),MATCH("Points (Auto-generate)",INDIRECT("'"&$A57&"'!$A$12:$Z$12"),0),0)="","?",VLOOKUP(I$1,INDIRECT("'"&$A57&"'!$A$12:$Z$19"),MATCH("Points (Auto-generate)",INDIRECT("'"&$A57&"'!$A$12:$Z$12"),0),0)),"ER")) -> ? | J57: =IF($F57=0,"NA",IF($A57=INDIRECT("'"&$A57&"'!$B$1"),IF(VLOOKUP(J$1,INDIRECT("'"&$A57&"'!$A$12:$Z$19"),MATCH("Points (Auto-generate)",INDIRECT("'"&$A57&"'!$A$12:$Z$12"),0),0)="","?",VLOOKUP(J$1,INDIRECT("'"&$A57&"'!$A$12:$Z$19"),MATCH("Points (Auto-generate)",INDIRECT("'"&$A57&"'!$A$12:$Z$12"),0),0)),"ER")) -> ? | K57: =IF($F57=0,"NA",IF($A57=INDIRECT("'"&$A57&"'!$B$1"),IF(VLOOKUP(K$1,INDIRECT("'"&$A57&"'!$A$12:$Z$19"),MATCH("Points (Auto-generate)",INDIRECT("'"&$A57&"'!$A$12:$Z$12"),0),0)="","?",VLOOKUP(K$1,INDIRECT("'"&$A57&"'!$A$12:$Z$19"),MATCH("Points (Auto-generate)",INDIRECT("'"&$A57&"'!$A$12:$Z$12"),0),0)),"ER")) -> ? | L57: =IF($F57=0,"NA",IF($A57=INDIRECT("'"&$A57&"'!$B$1"),IF(VLOOKUP(L$1,INDIRECT("'"&$A57&"'!$A$12:$Z$19"),MATCH("Points (Auto-generate)",INDIRECT("'"&$A57&"'!$A$12:$Z$12"),0),0)="","?",VLOOKUP(L$1,INDIRECT("'"&$A57&"'!$A$12:$Z$19"),MATCH("Points (Auto-generate)",INDIRECT("'"&$A57&"'!$A$12:$Z$12"),0),0)),"ER")) -> ? | M57: =IF($F57=0,"NA",IF($A57=INDIRECT("'"&$A57&"'!$B$1"),IF(VLOOKUP(M$1,INDIRECT("'"&$A57&"'!$A$12:$Z$19"),MATCH("Points (Auto-generate)",INDIRECT("'"&$A57&"'!$A$12:$Z$12"),0),0)="","?",VLOOKUP(M$1,INDIRECT("'"&$A57&"'!$A$12:$Z$19"),MATCH("Points (Auto-generate)",INDIRECT("'"&$A57&"'!$A$12:$Z$12"),0),0)),"ER")) -> ?
D59: PARASTATAL_Scores | G59: Bengaluru – BWSSB | H59: Bengaluru – BMTC | I59: Bengaluru – BDA | J59: Bengaluru – BMRCL | K59: Bengaluru – BMRDA | L59: Surat – SUDA | M59: Surat – GMRC
D60: PARASTATAL_OVERALL_SCORE | G60: =IFERROR(SUMIFS(G$3:G$57,$C$3:$C$57,"MQ")/(COUNTIFS($C$3:$C$57,"MQ")-COUNTIFS($C$3:$C$57,"MQ",G$3:G$57,"NA")),"NA") -> 0.73529412 | H60: =IFERROR(SUMIFS(H$3:H$57,$C$3:$C$57,"MQ")/(COUNTIFS($C$3:$C$57,"MQ")-COUNTIFS($C$3:$C$57,"MQ",H$3:H$57,"NA")),"NA") -> 0 | I60: =IFERROR(SUMIFS(I$3:I$57,$C$3:$C$57,"MQ")/(COUNTIFS($C$3:$C$57,"MQ")-COUNTIFS($C$3:$C$57,"MQ",I$3:I$57,"NA")),"NA") -> 0.41666667 | J60: =IFERROR(SUMIFS(J$3:J$57,$C$3:$C$57,"MQ")/(COUNTIFS($C$3:$C$57,"MQ")-COUNTIFS($C$3:$C$57,"MQ",J$3:J$57,"NA")),"NA") -> 0.38461538 | K60: =IFERROR(SUMIFS(K$3:K$57,$C$3:$C$57,"MQ")/(COUNTIFS($C$3:$C$57,"MQ")-COUNTIFS($C$3:$C$57,"MQ",K$3:K$57,"NA")),"NA") -> 0 | L60: =IFERROR(SUMIFS(L$3:L$57,$C$3:$C$57,"MQ")/(COUNTIFS($C$3:$C$57,"MQ")-COUNTIFS($C$3:$C$57,"MQ",L$3:L$57,"NA")),"NA") -> 0 | M60: =IFERROR(SUMIFS(M$3:M$57,$C$3:$C$57,"MQ")/(COUNTIFS($C$3:$C$57,"MQ")-COUNTIFS($C$3:$C$57,"MQ",M$3:M$57,"NA")),"NA") -> 0
D61: No. of MQs not yet scored ("?") - overall score is provisional while > 0 | G61: =COUNTIFS($C$3:$C$57,"MQ",G$3:G$57,"?") -> 16 | H61: =COUNTIFS($C$3:$C$57,"MQ",H$3:H$57,"?") -> 17 | I61: =COUNTIFS($C$3:$C$57,"MQ",I$3:I$57,"?") -> 12 | J61: =COUNTIFS($C$3:$C$57,"MQ",J$3:J$57,"?") -> 13 | K61: =COUNTIFS($C$3:$C$57,"MQ",K$3:K$57,"?") -> 10 | L61: =COUNTIFS($C$3:$C$57,"MQ",L$3:L$57,"?") -> 10 | M61: =COUNTIFS($C$3:$C$57,"MQ",M$3:M$57,"?") -> 13
D62: No. of MQs marked NA (excluded from overall score) | G62: =COUNTIFS($C$3:$C$57,"MQ",G$3:G$57,"NA") -> 2 | H62: =COUNTIFS($C$3:$C$57,"MQ",H$3:H$57,"NA") -> 2 | I62: =COUNTIFS($C$3:$C$57,"MQ",I$3:I$57,"NA") -> 7 | J62: =COUNTIFS($C$3:$C$57,"MQ",J$3:J$57,"NA") -> 6 | K62: =COUNTIFS($C$3:$C$57,"MQ",K$3:K$57,"NA") -> 9 | L62: =COUNTIFS($C$3:$C$57,"MQ",L$3:L$57,"NA") -> 9 | M62: =COUNTIFS($C$3:$C$57,"MQ",M$3:M$57,"NA") -> 6

Sheet PARASTATAL_CITY_SCORES
A1: City | B1: Agencies | C1: PARASTATAL score | D1: Agencies with a score
A2: Bengaluru | B2: BWSSB, BMTC, BDA, BMRCL, BMRDA | C2: =IFERROR(AVERAGEIFS(PARASTATAL_SUMMARY_RAW!$G$60:$M$60,PARASTATAL_SUMMARY_RAW!$G$59:$M$59,$A2&" – *"),"NA") -> 0.30731523 | D2: =COUNTIFS(PARASTATAL_SUMMARY_RAW!$G$59:$M$59,$A2&" – *",PARASTATAL_SUMMARY_RAW!$G$60:$M$60,">=0") -> 5
A3: Surat | B3: SUDA, GMRC | C3: =IFERROR(AVERAGEIFS(PARASTATAL_SUMMARY_RAW!$G$60:$M$60,PARASTATAL_SUMMARY_RAW!$G$59:$M$59,$A3&" – *"),"NA") -> 0 | D3: =COUNTIFS(PARASTATAL_SUMMARY_RAW!$G$59:$M$59,$A3&" – *",PARASTATAL_SUMMARY_RAW!$G$60:$M$60,">=0") -> 2
A5: A city's score is the average of its agencies' overall scores. Agencies with no applicable questions (NA) are left out.

Sheet PARASTATAL Questions
A1: Q No | B1: Original ID | C1: Group | D1: MQ_SQ | E1: Question | F1: Max Score | G1: Assessment level | H1: Applicability | I1: Detailed Methodology | J1: Notes for scorers
A2: UPD1 | B2: UPD 1 | C2: Urban Planning & Design (UPD) | D2: MQ | E2: Does the parastatal coordinate with the ULG(s) in preparing its sectoral plans? | F2: 10 | G2: Law/Policy + Implementation | H2: All parastatals excluding Development Authorities | I2: Sum total of the sub-indicators below - | J2: See sub-indicators
A3: UPD1a | B3: UPD 1a | C3: Urban Planning & Design (UPD) | D3: SQ | E3: Is the parastatal mandated to prepare its sectoral plans in coordination with the ULG(s) within its jurisdiction? | F3: 5 | G3: Law/Policy | H3: All parastatals excluding Development Authorities | I3: Check the relevant Parastatal Act/Rules and the State Town and Country Planning Act to determine whether the parastatal is required to coordinate with the ULG(s) while preparing its sectoral plans. Identify the nature of the ULG’s formal role in the plan-making process and score as follows: 10 — ULG approval/concurrence is mandatory with terms such as 'shall consult' 2.5 — Consultation with the ULG is discretionary with terms such as “may consult”. 0 — No formal role for the ULG in preparation of the parastatal’s plan can be established. Where different provisions apply to different plans prepared by the parastatal, assess the principal sectoral plan relevant to the service being evaluated. | J3: Relevant Parastatal Act; applicable Town and Country Planning (T&CP) Act.
A4: UPD1b | B4: UPD 1b | C4: Urban Planning & Design (UPD) | D4: SQ | E4: Has the ULG participated in the parastatal’s plan-making process? | F4: 5 | G4: Implementation | H4: All parastatals excluding Development Authorities | I4: Check the latest available plan-making cycle for evidence of ULG participation in the parastatal’s plan-making process, irrespective of whether such participation is legally mandated. Score 10 where there is evidence of ULG participation. Such evidence may include plan documents, consultation records, meeting minutes, ULG resolutions/comments, responses to ULG inputs, or information published on the parastatal/ULG website. Score 0 where there is no such evidence. Where different provisions apply to different plans prepared by the parastatal, assess the principal sectoral plan relevant to the service being evaluated. | J4: Evidence may include plan documents, consultation records, meeting minutes, ULG resolutions/comments, responses to ULG inputs, or information published on the parastatal/ULG website.
A5: UPD2 | B5: UPD 2 | C5: Urban Planning & Design (UPD) | D5: MQ | E5: Where multiple statutory or sectoral plans apply to the same territory, does the water supply board and transport corporation ensure consistency with the municipal/city plan for the city? | F5: 10 | G5: Law/Policy + Implementation | H5: All parastatals excluding Development Authorities | I5: Sum of the sub-questions below - | J5: See sub-indicators
A6: UPD2a | B6: UPD 2a | C6: Urban Planning & Design (UPD) | D6: SQ | E6: Where multiple statutory or sectoral plans apply to the same territory, is the water board mandated to ensure consistency with the applicable city /municipal plan for the city? | F6: 2.5 | G6: Law/Policy | H6: Water supply board | I6: Check the relevant Parastatal Act and Town and Country Planning Act. Score 2.50 if the parastatal 'shall/is required to' ensure that its sectoral plan is consistent with the applicable city or municipal plan. Score 1.25 if the law provides that such alignment is discretionary. ('May' provision) Score 0 if no such provision exists. For example, a provision stating that a water supply plan shall conform to the applicable city/municipal plan would score 2.5, while a provision stating that the authority may have regard to such a plan would score 1.25. | J6: Relevant Parastatal Act; applicable Town and Country Planning (T&CP) Act.
A7: UPD2b | B7: UPD 2b | C7: Urban Planning & Design (UPD) | D7: SQ | E7: Where multiple statutory or sectoral plans apply to the same territory, does the water supply board ensure consistency with the applicable municipal/city plan for the city? | F7: 2.5 | G7: Implementation | H7: Water supply board | I7: Check the Board’s current water supply/sewerage master plan, or equivalent sectoral planning document, together with the applicable Master Plan. Score 2.5 if the water plan demonstrates substantive spatial alignment with the city’s master plan: It explicitly draws reference to the city master plan, uses the master plan’s growth/service areas and/or land-use framework to determine network expansion and major infrastructure siting, and also refers to the master plan or its projections as an input. Score 1.25 if there is partial alignment: the water plan refers to the master plan and/or uses its population, density or land-use projections, but does not clearly demonstrate that these inputs determine the spatial location of network expansion, service areas or major infrastructure. Score 0 if there is no identifiable evidence that the Master Plan or its spatial/population framework informs water planning. | J7: Water Supply Board's current water supply/sewerage master plan or equivalent sectoral planning document; applicable Master Plan/Development Plan/Metropolitan or Regional Plan; land-use conversion/regularisation records for major treatment plants or trunk infrastructure, where available.
A8: UPD2c | B8: UPD 2c | C8: Urban Planning & Design (UPD) | D8: SQ | E8: Where multiple statutory or sectoral plans apply to the same territory, is the transport corporation mandated to ensure consistency with the applicable municipal/city plan for the city? | F8: 2.5 | G8: Law/Policy | H8: Transport Corporation | I8: Review the relevant Parastatal Act and Town and Country Planning Act. Score 2.5 if the parastatal 'shall/is required to' ensure that its sectoral plan is consistent with the applicable municipal/city plan. Score 1.25 if the law provides that such alignment is discretionary. ('May' provision) Score 0 if no such provision exists. For example, a provision stating that a transport plan shall conform to the applicable city/municipal plan would score 2.5, while a provision stating that the authority may have regard to such a plan would score 1.25. | J8: Relevant Parastatal Act; applicable Town and Country Planning (T&CP) Act.
A9: UPD2d | B9: UPD 2d | C9: Urban Planning & Design (UPD) | D9: SQ | E9: Where multiple statutory or sectoral plans apply to the same territory, does the transport corporation ensure consistency with the applicable municipal/city plan for the city? | F9: 2.5 | G9: Implementation | H9: Transport Corporation | I9: Check the transport corporation's current transport/mobility master plan, network expansion plan, or equivalent sectoral planning document, together with the applicable city/municipal Master Plan. Score 2.5 if the transport plan demonstrates substantive spatial alignment with the city/municipal's master plan: it explicitly draws reference to the city master plan, uses the master plan's growth corridors, land-use framework and/or density projections to determine route planning, station/depot siting or network expansion, and refers to the master plan or its projections as an input. Score 1.25 if there is partial alignment: the transport plan refers to the master plan and/or uses its population, density or land-use projections, but does not clearly demonstrate that these inputs determine the spatial location of routes, stations or major infrastructure. Score 0 if there is no identifiable evidence that the Master Plan or its spatial/population framework informs transport planning. | J9: Transport corporation's current mobility/network plan; applicable Master Plan/Development Plan/Metropolitan or Regional Plan; land-use conversion/regularisation records for major transport infrastructure, where available.
A10: UPD3 | B10: UPD 3 | C10: Urban Planning & Design (UPD) | D10: MQ | E10: Are the needs of women and the urban poor explicitly considered in the water board’s planning, service delivery or major investment decisions? | F10: 10 | G10: Law/Policy + Implementation | H10: Water supply board | I10: Check the relevant Act of the parastatal and applicable sectoral legislation, rules, regulations and other binding policy instruments. Do not award credit solely for broad references such as “public interest”, “public welfare” or “welfare of inhabitants”; there must be an identifiable requirement relating to women, the urban poor, EWS/slum residents, persons with disabilities, informal workers, disadvantaged/vulnerable groups, affordability, equitable/universal access, safety, or rehabilitation/resettlement protections. | J10: Relevant Act of the parastatal and applicable sectoral legislation, rules, regulations and other binding policy instruments
A11: UPD3a | B11: UPD 3a | C11: Urban Planning & Design (UPD) | D11: SQ | E11: Is the water supply board mandated to consider the needs of women and the urban poor in decisions relating to access, affordability and delivery of water and sanitation services? | F11: 5 | G11: Law/Policy | H11: Water supply board | I11: Check the Water Supply Board/utility Act, rules, tariff regulations and other binding legal instruments. Assess whether the legal framework requires the Board to address the needs of economically vulnerable groups and women in decisions relating to access, affordability and service delivery. Do not award credit for generic obligations such as “public interest”, “universal supply”, “adequate service” or “service to all” unless these are translated into a specific legal requirement relating to affordability, service access, coverage or the needs of women. Part A – Urban Poor: Affordability and access – 2.5 marks Look for identifiable legal requirements such as: concessional, lifeline or differentiated tariffs for EWS/BPL/low-income households; concessions relating to connection charges, deposits or other service-access costs; requirements to provide services to slums, informal settlements, low-income or underserved areas; tenure-neutral or other provisions enabling access irrespective of land tenure/status; minimum/lifeline supply or alternative service arrangements for underserved populations. Score 2.5: There is a clear mandatory requirement (“shall”, “must” or equivalent) addressing affordability or access for economically vulnerable groups. Score 1.25: The legal framework permits or encourages such measures (“may” or equivalent), but does not make them mandatory. Score 0: No specific legal provision addressing affordability or access for economically vulnerable groups is found. Part B – Women: Gender-responsive access and service delivery – 2.5 marks Look for identifiable legal requirements such as: consideration of women’s needs in water and sanitation planning or service provision; requirements relating to location, accessibility or safety of shared/public water infrastructure; gender-sensitive planning, assessment or consultation requirements; service or design requirements intended to reduce barriers faced by women in accessing water and sanitation services. Score 2.5: There is a clear mandatory requirement (“shall”, “must” or equivalent) addressing women’s access or service-delivery needs. Score 1.25: The legal framework permits or encourages consideration of women’s needs (“may” or equivalent), but does not make it mandatory. Score 0: No specific legal provision addressing women’s access or service-delivery needs is found. | J11: Water Supply Board/utility Act, water and sanitation legislation, tariff regulations, service rules, State policies and other applicable binding instruments
A12: UPD3b | B12: UPD 3b | C12: Urban Planning & Design (UPD) | D12: SQ | E12: Does the water supply board actually consider the needs of women and the urban poor in decisions relating to access, affordability and delivery of water and sanitation services? | F12: 5 | G12: Implementation | H12: Water supply board | I12: Check the Board’s current water supply/sanitation plan, applicable policy documents, active schemes, tariff/connection-concession orders and service or design standards. Assess whether the needs of economically vulnerable groups and women are recognised and translated into specific policies, schemes, targets, projects or service-delivery measures. Check for implementation, whether or not such measures are legally mandated. Do not award full credit for generic language such as “public interest”, “all consumers”, “universal service” or “inclusive development”. Credit should depend on how well identified needs translate into specific, operational measures. Part A – Urban Poor: Affordability and inclusion in service coverage – 2.5 marks Look for measures such as: concessional/lifeline tariffs or reductions in connection charges, deposits or other service costs; policies or schemes targeting EWS/BPL, slum, informal-settlement or low-income households; explicit inclusion of slums/informal or underserved settlements in service-area, demand or network planning; targeted network extension or service-coverage commitments; alternative service-delivery arrangements where household connections are not feasible; defined coverage, connection, tariff or service targets/projects for economically vulnerable groups. Score 2.5: The needs of economically vulnerable groups are addressed through a comprehensive policy or scheme and translated into specific operational measures, targets, projects or service commitments relating to affordability and/or access. Score 1.25: Economically vulnerable groups are explicitly recognised, but the response is limited to broad policy intent, isolated provisions or measures without clearly defined operational targets/projects. Score 0 — No identifiable consideration of affordability or service access for economically vulnerable groups is found. Part B – Women: Gender-responsive planning and service delivery – 2.5 marks Look for measures such as: policies or schemes specifically addressing women’s water and sanitation access; gender/GESI analysis or screening in water-supply or sanitation planning; siting of shared infrastructure to address women’s time, distance or physical burden; safety or accessibility measures at community/public water or sanitation facilities; gender-responsive design or service standards; defined targets, projects or investments addressing identified barriers faced by women. Scoring Score 2.5: Women’s needs are addressed through a comprehensive policy or scheme and translated into specific operational/design measures, targets or projects. Score 1.25: Women are explicitly identified and their needs recognised, but this is limited to broad policy intent or isolated provisions without clearly defined operational/design measures, targets or projects. Score 0: No identifiable consideration of women’s access or service-delivery needs is found. | J12: Water Supply Board's current water supply/sanitation plan; scheme/coverage documents; tariff or connection-concession orders; design/service standards.
A13: UPD4 | B13: UPD 4 | C13: Urban Planning & Design (UPD) | D13: MQ | E13: Are the needs of women and the urban poor explicitly considered in the transport Corporation’s planning, service delivery or major investment decisions? | F13: 10 | G13: Law/Policy + Implementation | H13: Transport Corporation | I13: Sum of the sub-questions below - | J13: See sub-indicators
... A28: DPG3 | B28: DPG 3 | C28: Decentralised Participatory Governance | D28: MQ | E28: Does the parastatal maintain an active and functional website? | F28: 10 | G28: Implementation | H28: Common. | I28: Check the official website of the relevant parastatal. Score 10 if an official website of the relevant parastatal exists, opens without error, and shows content updated within the last 12 months (verifiable "last updated" date or dated content such as a recent notice/circular). Score 0 if no official website is found. | J28: Live URL, screenshot/web-archive capture, date of check of the website of the relevant parastatal
A29: DPG4 | B29: DPG 4 | C29: Decentralised Participatory Governance | E29: Is the parastatal mandated to publish key financial, operational, and civic data/information in accessible, open-data formats? | G29: Law/Policy | H29: Common. | I29: [Note: The scoring of this question has not been undertaken in the manual exercise as he universe of legislation and subordinate legislation governing the parastatals are not fully clear. Awaiting support from the state teams before manually scoring this question.]
A30: DPG5 | B30: DPG 5 | C30: Decentralised Participatory Governance | D30: MQ | E30: Are the parastatal's key financial, operational, and civic data/information available on the website and published in accessible, open-data formats? | F30: 10 | G30: Implementation | H30: Common. | I30: Check the parastatal website. Assess each of the ten components below independently. Each component carries 1 point: 0.5 for online availability and 0.5 for publication in an open, machine-readable/reusable format, as appropriate to the information type. Aggregate the scores across all ten components to arrive at the total score out of 10. | J30: Website screenshots/archived URLs with date of access, for each document type
A31: DPG5a | B31: DPG5a | C31: Decentralised Participatory Governance | D31: SQ | E31: Annual budget | F31: 1 | G31: Implementation | H31: Common. | I31: Part A: Availability and currency — 0.5 Score 0.5: Budget for the current FY or either of the immediately preceding two FYs is publicly available online. Score 0: Budget cannot be found/accessed online, or the latest available budget is older than the permitted period. Part B: Open-data format — 0.5 Score 0.5: Budget information is available in an open, structured and reusable data format, such as: 1. CSV; 2. XLS/XLSX; 3. ODS; 4. structured HTML table; or 5. another downloadable structured dataset. Score 0 — Budget information is available only in a non-open or non-reusable format, including: 1. PDF, whether searchable or scanned; 2. image files; 3. unstructured webpages; 4. documents containing tables that are not provided as structured downloadable data. The open-data format should allow budget figures to be readily extracted, analysed and reused without manual transcription. | J31: Website screenshots/archived URLs with date of access, for each document type
A32: DPG5b | B32: DPG 5b | C32: Decentralised Participatory Governance | D32: SQ | E32: Audited annual account | F32: 1 | G32: Implementation | H32: Common. | I32: Part A: Availability and currency — 0.5 Score 0.5 — Audited annual accounts are publicly available online, and the latest available accounts are not older than two years. Score 0 — Audited annual accounts cannot be found/accessed online, or the latest available accounts are older than the permitted period. Part B: Open-data format — 0.5 Score 0.5 — Audited financial information is available in an open, structured and reusable data format, such as: 1. CSV; 2. XLS/XLSX; 3. ODS; 4. structured HTML table; or 5. another downloadable structured dataset. Score 0 — Audited financial information is available only in a non-open or non-reusable format, including: 1. PDF, whether searchable or scanned; 2. image files; 3. unstructured webpages; or 4. documents containing financial tables that are not provided as structured reusable data. The open-data format should allow audited financial figures to be readily extracted, analysed and reused without manual transcription. | J32: Website screenshots/archived URLs with date of access, for each document type
A33: DPG5c | B33: DPG 5c | C33: Decentralised Participatory Governance | D33: SQ | E33: Annual report | F33: 1 | G33: Implementation | H33: Common. | I33: Part A: Availability and currency — 0.5 Score 0.5: The annual report is publicly available online, and the latest available report is not older than two years. Score 0: The annual report cannot be found/accessed online, or the latest available report is older than the permitted period. Part B: Open-data format — 0.5 Score 0.5: Key information contained in the annual report is also available in an open, structured and reusable format, such as: 1. CSV; 2. XLS/XLSX; 3. ODS; 4. structured HTML tables; or Score 0: The annual report is available only as a document or other non-structured format, including: 1. PDF, whether searchable or scanned; 2. DOC/DOCX; 3. image files; 4. e-publications; or 5. webpages containing narrative information without structured reusable data. The open-data format should allow key annual-report information to be extracted, analysed and reused without manual transcription. | J33: Website screenshots/archived URLs with date of access, for each document type
A34: DPG5d | B34: DPG5d | C34: Decentralised Participatory Governance | D34: SQ | E34: Annual Audit Report | F34: 1 | G34: Implementation | H34: Common. | I34: Part A: Availability and currency — 0.5 Score 0.5: Annual audit report is publicly available online, and the latest available information is not older than two years. Score 0: Annual audit report cannot be found/accessed online, or the latest available information is older than two years. Part B: Open-data format — 0.5 Score 0.5: Key information contained in the annual audit report is also available in an open, structured and reusable format, such as: 1. CSV; 2. XLS/XLSX; 3. ODS; 4. structured HTML tables; or Score 0: The annual audit report is available only as a document or other non-structured format, including: 1. PDF, whether searchable or scanned; 2. DOC/DOCX; 3. image files; 4. e-publications; or 5. webpages containing narrative information without structured reusable data. The open-data format should allow key annual audit report information to be extracted, analysed and reused without manual transcription.
A35: DPG5e | B35: DPG5e | C35: Decentralised Participatory Governance | D35: SQ | E35: Major plans / projects | F35: 1 | G35: Implementation | H35: Common. | I35: Part A: Availability and currency — 0.5 Score 0.5: Major plans and/or information on ongoing projects is publicly available online, and the latest available information is not older than two years. Score 0: Major plans and/or information on ongoing projects cannot be found/accessed online, or the latest available information is older than two years. Part B: Open-data format — 0.5 Score 0.5 — Information on major plans and/or ongoing projects is available in an open, structured and reusable format, such as: 1. structured HTML webpage/table or project dashboard; 2. CSV; 3. XLS/XLSX; 4. ODS; 5. Other downloadable structured dataset containing identifiable plan/project information. Score 0 — Information is available only in a non-structured or non-reusable format, such as: 1. PDF, including searchable PDF; 2. scanned document; 3. image-only plan/project information; 4. individual project pages or notices that do not provide structured, reusable data; 5. project information presented only through images or unstructured text. | J35: Website screenshots/archived URLs with date of access, for each document type
A36: DPG5f | B36: DPG5f | C36: Decentralised Participatory Governance | D36: SQ | E36: Service-level benchmarks and performance reports | F36: 1 | G36: Implementation | H36: Common. | I36: Part A: Availability and currency — 0.5 Score 0.5: Service-level benchmark/performance information is publicly available online, and the latest available information is not older than two years. Score 0 — Performance information cannot be found/accessed online, or the latest available information is older than the permitted period. Part B: Open-data format — 0.5 Score 0.5 — Performance information is available in an open, structured and reusable format, such as: 1. CSV; 2. XLS/XLSX; 3. ODS; 4. structured HTML table/dashboard; or 5. another downloadable structured dataset containing service-level or performance information. Score 0: Performance information is available only in a non-open or non-reusable format, including: 1. PDF, whether searchable or scanned; 2. image/chart without the underlying data; 3. narrative webpage without structured data; or 4. other formats that do not allow the information to be readily extracted, analysed and reused. The open-data format should allow service-level or performance information to be analysed and reused without manual transcription. Note: For Development Authorities whose functions are limited to planning and preparation of spatial/development plans, mark this indicator ‘NA’. Where a Development Authority also performs operational or service-delivery functions — such as building/development permissions, land allotment/development, infrastructure provision, housing, estate management or other citizen-facing services — assess this indicator against the performance information relevant to those functions. | J36: Website screenshots/archived URLs with date of access, for each document type
A37: DPG5g | B37: DPG5g | C37: Decentralised Participatory Governance | D37: SQ | E37: Organisation and staffing information | F37: 1 | G37: Implementation | H37: Common. | I37: Part A: Check availability — 0.5 Score 0.5: Both of the following are publicly available online: the parastatal’s organisational structure/organogram; and details of key officers, including name/designation and at least one official contact detail (phone number and/or email address). Score 0: Either the organisational structure/organogram or the required officer details/contact information is not publicly available online. Part B: Minimum format/accessibility — 0.5 Score 0.5 — Both the organisational structure and officer/contact information are available in a searchable and readable format, such as: a searchable webpage; searchable/downloadable PDF or document; structured table or directory. Score 0 — Either item is available only in a non-searchable/non-readable format, such as an image-only organogram, scanned list or image-based directory. | J37: Website screenshots/archived URLs with date of access, for each document type
A38: DPG5h | B38: DPG5h | C38: Decentralised Participatory Governance | D38: SQ | E38: Meeting minutes of governing board | F38: 1 | G38: Implementation | H38: Common. | I38: Part A: Check availability and currency — 0.5 Score 0.5: At least one set of minutes from the current FY or immediately preceding FY is publicly available online. Score 0: Meeting Minutes cannot be found/accessed online or is older than the permitted period. Record the FY/year/date of the latest information found in a separate evidence field even where the score is 0. Part B: Minimum format/accessibility — 0.5 Score 0.5: Meeting Minutes available in a searchable/text-readable and downloadable document (Searchable PDF, HTML, DOC/DOCX) Score 0: Meeting Minutes is available but does not meet that standard (Scanned/image-only minutes; image gallery) | J38: Website screenshots/archived URLs with date of access, for each document type
A39: DPG5i | B39: DPG5i | C39: Decentralised Participatory Governance | D39: SQ | E39: Citizen / Service Charter | F39: 1 | G39: Implementation | H39: Common. | I39: Part A: Check availability and currency — 0.5 Score 0.5: A currently applicable Charter is publicly available. Do not treat it as outdated solely because it predates the preceding FY if it remains in force. There may be no annual publication requirement; Score 0: Charter cannot be found/accessed online. Part B: Check Minimum format/accessibility — 0.5 Score 0.5: Charter available in a searchable/text-readable webpage or downloadable document (Searchable PDF, HTML, DOC/DOCX) Score 0: Charter is available but does not meet that standard (Scanned/image-only Charter) | J39: Website screenshots/archived URLs with date of access, for each document type
A40: DPG5j | B40: DPG5j | C40: Decentralised Participatory Governance | D40: SQ | E40: RTI details and designated Public Information Officer contact/procedure | F40: 1 | G40: Implementation | H40: Common. | I40: Part A: Check availability and currency — 0.5 Score 0.5: Current PIO/APIO details and RTI procedure are publicly available; information should be treated as current where the named office-holder/contact details remain valid. Score 0: Information cannot be found/accessed online or the named office-holder/contact details are invalid. Part B: Check minimum format/accessibility — 0.5 Score 0.5: Information available in a searchable webpage or searchable/downloadable document (HTML RTI page; searchable PDF/DOC containing PIO/contact details) Score 0: Information is available but does not meet that standard (Image-only notice; scanned PDF) | J40: Website screenshots/archived URLs with date of access, for each document type
A41: DPG6 | B41: DPG 6 | C41: Decentralised Participatory Governance | D41: MQ | E41: Does the parastatal provide for and maintain an accessible grievance-redressal mechanism? | F41: 10 | G41: Law/Policy | H41: Common. | I41: Sum total of the sub-indicators below - | J41: See sub-indicators
A42: DPG6a | B42: DPG 6a | C42: Decentralised Participatory Governance | D42: SQ | E42: Is the parastatal mandated to provide a grievance-redressal mechanism? | F42: 5 | G42: Law/Policy | H42: Common. | I42: Check the Parastatal Act, applicable subordinate legislation, and citizen/service charter for a requirement to provide a grievance-redressal mechanism. This assessment tests whether citizens have access to a remedial mechanism when a service failure, delay, denial, deficiency or other grievance occurs. Do not award credit merely because the framework specifies service standards, service timelines or a Right to Service entitlement, unless it also provides a mechanism through which an aggrieved person can seek redress, escalation or resolution. Score 5: The applicable legal or binding policy framework requires the parastatal to provide a grievance-redressal mechanism (“shall”, “must”). Score 2.5: The applicable framework permits or enables the parastatal to provide a grievance-redressal mechanism (“may” ), but does not make it mandatory. Score 0: No specific provision for a grievance-redressal mechanism is found. | J42: Parastatal Act/ corresponding subordinate legislation/ citizen or service charter
A43: DPG6b | B43: DPG 6b | C43: Decentralised Participatory Governance | D43: SQ | E43: Are accessible grievance-redressal channels available and functional in practice? | F43: 5 | G43: Implementation | H43: Common. | I43: Check the parastatal’s official website and other officially notified grievance channels. Score out of 5 based on the following four components: 1. Web-based grievance channel — 1.25 marks Score 1.25 if an official website/portal provides a functioning mechanism through which a grievance can be lodged online. A dedicated grievance form, integrated government grievance portal or equivalent mechanism qualifies. 2. Mobile/electronic grievance channel — 1.25 marks Score 1.25 if a currently operational mobile app, designated grievance email, WhatsApp number or other officially notified electronic channel is available for lodging grievances. 3. Telephone grievance channel — 1.25 marks Score 1.25 if a dedicated or clearly designated helpline, call centre or telephone number is provided for complaints or grievances. A generic office switchboard should not qualify unless it is explicitly identified as a channel for lodging grievances. 4. Grievance acknowledgement and tracking — 1.25 marks Score 1.25 if the grievance mechanism provides for acknowledgement and subsequent tracking of a registered grievance through a complaint/reference number, status-tracking facility or equivalent mechanism. Where all four components are available, award the full score of 5. | J43: Relevant parastatal's official website Detailed evidence information provided in the methodology column (I 33)
A44: DPG7 | B44: DPG 7 | C44: Decentralised Participatory Governance | D44: MQ | E44: Does the law mandate citizen participation in the preparation of plans for which the parastatal is responsible, and does the parastatal provide for such participation in practice? | F44: 10 | G44: Law/Policy and Implementation | H44: All parastatals excluding Development Authorities | I44: Sum of sub-questions below - | J44: Provisions on plan approval procedure in enabling act of the relevant parastatal/T&CP Act
A45: DPG7a | B45: DPG 7a | C45: Decentralised Participatory Governance | D45: SQ | E45: Is citizen participation in the preparation of the parastatal's plans mandated? | F45: 5 | G45: Law/Policy | H45: All parastatals excluding Development Authorities | I45: Check the parastatal Act and rules first. Also review the applicable T&CP/planning Act, Municipal Act to identify whether a citizen-participation requirement applies to the parastatal directly or to all authorities preparing the relevant category of plan. Score 5 if the applicable law/rules mandate a defined citizen-participation process before finalisation/approval of the plan, including publication of a draft plan and invitation of objections/suggestions, public hearing, consultation or equivalent. Score 2.5 if participation is provided for but is discretionary (may), or applies only to specified plan types/stages. If the mandate provides for a citizen participation forum with a shall provision. Score 1.25 if the citizen participation forum is discretionary. Score 0 if no applicable requirement is found. Record the legal provision, plan type, form of participation prescribed, and whether the provision uses mandatory or discretionary language. | J45: Parastatal Act and rules; applicable T&CP Act; State Municipal Act.
A46: DPG7b | B46: DPG 7b | C46: Decentralised Participatory Governance | D46: SQ | E46: Are citizens consulted in practice in the preparation of plans by the parastatal? | F46: 5 | G46: Implementation | H46: All parastatals excluding Development Authorities | I46: Check the parastatal’s official website and the latest applicable plan/planning exercise. Check the plan document, consultation reports, public notices, minutes/proceedings of consultations or public hearings, and other relevant records available on the website. Score 5 if there is publicly verifiable evidence that citizens were provided an opportunity to participate through objections/suggestions, public hearings, consultations or an equivalent process before the plan was finalised. Score 2.5 if there is credible evidence that consultation took place, but the process cannot be fully verified from official records—for example, where only a consultation notice, minutes/proceedings, a reference in the final plan, media reports, or other partial documentation is available. | J46: Plan document; consultation reports; public notices; minutes/proceedings of consultations or hearings on the parastatal's official website; media reports.
... A57: SC7b | B57: SC-7b | C57: State Capacities | D57: SQ | E57: What proportion of the parastatal's workforce is women? | F57: 5 | G57: Implementation (Numeric) | H57: Common — all parastatal types. | I57: Compute women employees as a proportion of total filled posts using the latest available staffing data. % women in workforce = (Number of women employees ÷ Total filled posts) × 100, using the latest available staffing data. Score 5: women constitute ≥33% of the workforce Score 2.5: women constitute 15–32% of the workforce Score 0 — women constitute <15% of the workforce | J57: Staffing records on the website/ RTI and/or formal data request with the parastatal/ annual report

Sheet UPD1a
A1: Question Code | B1: UPD1a | C1: <Sheet name and this code must match>
A2: Group | B2: =VLOOKUP($B$1,'PARASTATAL Questions'!$A:$J,3,0)&"" -> Urban Planning & Design (UPD)
A3: Original ID | B3: =VLOOKUP($B$1,'PARASTATAL Questions'!$A:$J,2,0)&"" -> UPD 1a
A4: MQ_SQ | B4: =VLOOKUP($B$1,'PARASTATAL Questions'!$A:$J,4,0)&"" -> SQ
A5: Question | B5: =VLOOKUP($B$1,'PARASTATAL Questions'!$A:$J,5,0)&"" -> Is the parastatal mandated to prepare its sectoral plans in coordination with the ULG(s) within its jurisdiction?
A6: Max Score | B6: =VLOOKUP($B$1,'PARASTATAL Questions'!$A:$J,6,0) -> 5
A7: Assessment level | B7: =VLOOKUP($B$1,'PARASTATAL Questions'!$A:$J,7,0)&"" -> Law/Policy
A8: Applicability | B8: =VLOOKUP($B$1,'PARASTATAL Questions'!$A:$J,8,0)&"" -> All parastatals excluding Development Authorities
A9: Detailed Methodology | B9: =VLOOKUP($B$1,'PARASTATAL Questions'!$A:$J,9,0)&"" -> Check the relevant Parastatal Act/Rules and the State Town and Country Planning Act to determine whether the parastatal is required to coordinate with the ULG(s) while preparing its sectoral plans.Identify the nature of the ULG’s formal role in the plan-making process and score as follows:10 — ULG approval/concurrence is mandatory with terms such as 'shall consult' 2.5 — Consultation with the ULG is discretionary with terms such as “may consult”.0 — No formal role for the ULG in preparation of the parastatal’s plan can be established. Where different provisions apply to different plans prepared by the parastatal, assess the principal sectoral plan relevant to the service being evaluated.
A10: Notes for scorers | B10: =VLOOKUP($B$1,'PARASTATAL Questions'!$A:$J,10,0)&"" -> Relevant Parastatal Act; applicable Town and Country Planning (T&CP) Act.
B11: PRE-FILLED - DO NOT ALTER | I11: ENTER A NUMBER 0 TO 5 | J11: DO NOT ALTER FORMULA
A12: City | B12: Applies? | C12: Act Name/Web name/Doc name | D12: Chapter | E12: Provision | F12: Clause | G12: Page Number | H12: Link | I12: Score | J12: Points (Auto-generate) | K12: SCORER COMMENTS
A13: Bengaluru – BWSSB | B13: YES | C13: THE BANGALORE WATER SUPPLY AND SEWERAGE ACT, 1964 (FAOLEX PDF) [BWSSB-04] | D13: Chapter II (Board, its powers and duties) | E13: Section 15(2)(b)-(c) and proviso (General duties of the Board); also Section 14 (Consultative Committee) | F13: s.15(2)(b), s.15(2)(c), proviso inserted by Act 6 of 1966; s.14(1), s.14(4)(i) | G13: 13 | H13: https://faolex.fao.org/docs/pdf/ind201320.pdf | I13: 0 | J13: =IF($B13="NO","NA",IF(I13="","",MIN(I13,$B$6))) -> 0 | K13: AI (medium confidence), from Step 2 answer (Partially Answered) and BWSSB-04: Score: 0. No source gives the city corporation (the ULG) a formal role in preparing BWSSB's plans. **What the Act says about plans** - BWSSB's main plans are its water supply and sewerage 'schemes'. Section 15(2)(b) and (c) of the BWSSB Act, 1964 make preparing and carrying out these schemes the Board's own duty. - The only outside sign-off on these plans is in the proviso inserted by Act 6 of 1966: "no scheme under clause (b) or (c) estimated to cost more than a crore of rupees shall be carried out by the Board except with the approval of the State Government." That approval comes from the State Government, not the city corporation. - No provision in the Act text I could read says the Board shall consult the Corporation, get its concurrence, or prepare plans with it. **Why Section 14 doesn't change the score** - Section 14 (Consultative Committee) only allows indirect representation. The State Government appoints 3 to 9 members "after consultation with such representatives or bodies representative of the following interests as the State Government thinks fit". The Municipal Corporation is one of those interests. - The committee's role is advisory: "to advise the Board on major questions of policy and major schemes". This is not a duty on BWSSB to consult the ULG when preparing plans. At most, any city corporation link depends on the State Government's choice and is not specific to plans. - Section 38(2) (consulting the Corporation Commissioner before closing a public hydrant) is about day-to-day operations, not planning. **How this compares with Step 2** I agree with Step 2's reading. I went further and checked Section 15 itself, which confirms that the only approval role on schemes belongs to the State Government. **Scale** The methodology uses 10 / 2.5 / 0, but the maximum score is 5. A score of 0 is the same under any rescaling, so the mismatch doesn't affect this result. **Things a reviewer should check** 1. The Karnataka Town and Country Planning Act is not in the Citation Sheet, so I couldn't check whether it requires utility plans to be coordinated with ULGs. If it does, the score could change. 2. Some sections of the Act were cut from the excerpts, including Section 3 (who sits on the Board). The current amended text should be confirmed. The copy is a FAOLEX reproduction, not an official Karnataka source. 3. The Act still refers to the 'Municipal Corporation of the City of Bangalore'. Whether it has been changed for the Greater Bengaluru Authority and the city corporations isn't shown in the sheet. Quote: "(b) for preparing and carrying out schemes 1[x x x] 1 for the supply of wholesome water for domestic purposes within the Bangalore Metropolitan Area;"
A14: Bengaluru – BMTC | B14: YES | J14: =IF($B14="NO","NA",IF(I14="","",MIN(I14,$B$6))) | K14: AI: left for a person. Step 2 found no evidence (Insufficient Evidence). Source needed: Three sources are needed. (1) The full text of the Road Transport Corporations Act, 1950, which constitutes and governs BMTC, to check for any duty to prepare plans with, consult, or obtain the concurrence of municipal bodies. (2) The full text of Sections 24 onward of the BMLTA Act, 2022, and any regulations under it, to confirm whether BMTC is an 'Urban Transport Agency' and whether preparing its Sectoral Mobility Investment Program involves ULG consultation or concurrence. (3) The Greater Bengaluru Governance Act / GBA legislation, or any government order setting coordination duties between BMTC and the city corporations.
A15: Bengaluru – BDA | B15: NO | J15: =IF($B15="NO","NA",IF(I15="","",MIN(I15,$B$6))) -> NA
A16: Bengaluru – BMRCL | B16: YES | C16: The Bengaluru Metropolitan Land Transport Authority Act, 2022 (Karnataka Act 6 of 2023) [BMRCL-35] | D16: Chapter VI – Sectoral and City Mobility Investment Program and Annual Implementation Plan | E16: Section 24 | F16: Section 24(b); see also Section 21(2), first proviso | G16: 19 | H16: https://prsindia.org/files/bills_acts/acts_states/karnataka/2023/Act6of2023Karnataka.pdf | I16: 0 | J16: =IF($B16="NO","NA",IF(I16="","",MIN(I16,$B$6))) -> 0 | K16: AI (medium confidence), from Step 2 answer (Partially Answered) and BMRCL-35: Score 0: none of the sources on the Citation Sheet gives the ULG (the Greater Bengaluru Authority or its city corporations) a formal role in preparing BMRCL's sectoral plans. **What the sources say** - BMRCL is a Government company, not a body created by its own Act (BMRCL-01). So no parastatal Act sets out how it must plan. - Its sectoral plan is the Sectoral Mobility Investment Program under the BMLTA Act, defined in Section 2(v) as the investment program prepared by the respective Urban Transport Agency. Section 24(b) says it "shall be prepared in consultation with the Authority." Here "the Authority" means BMLTA, a state transport authority, not the ULG. - The Annual Implementation Plan under Section 25(2) is reviewed and approved by BMLTA. - Under Section 21(2), first proviso, other authorities that plan urban mobility "shall necessarily consult" BMLTA. That duty also runs to BMLTA, not the ULG. - Section 15(5) of the Greater Bengaluru Governance Act (BMRCL-34) only binds agencies to assist the GBA if it chooses ("may") to assign them planning work. That does not make BMRCL coordinate its own plans with the ULG. - The Metro Rail Policy 2017 (BMRCL-18) gives non-binding advice only. **Check of the Step 2 answer** The sources support Step 2's score of 0. I added Section 24(b) because it is the provision most directly about BMRCL's own sectoral plan. **Gaps for a person to check** 1. Whether BMLTA's board includes the ULG commissioner. If it does, the ULG takes part only indirectly through BMLTA, which does not meet the 'ULG approval/consultation' test. 2. Whether any BMLTA regulations, the full Karnataka Town and Country Planning Act text (BMRCL-31 was not reviewed in full), or any government order gives the GBA or city corporations a role in BMRCL's plans. **Scale note:** the rubric uses a 10-point scale but the question's maximum is 5. A score of 0 is the same either way. Quote: "(b) The Sectoral Mobility Investment Program shall be prepared in consultation with the Authority;"
A17: Bengaluru – BMRDA | B17: NO | J17: =IF($B17="NO","NA",IF(I17="","",MIN(I17,$B$6))) -> NA
A18: Surat – SUDA | B18: NO | J18: =IF($B18="NO","NA",IF(I18="","",MIN(I18,$B$6))) -> NA
A19: Surat – GMRC | B19: YES | J19: =IF($B19="NO","NA",IF(I19="","",MIN(I19,$B$6)))

Sheet UPD1b
A1: Question Code | B1: UPD1b | C1: <Sheet name and this code must match>
A2: Group | B2: =VLOOKUP($B$1,'PARASTATAL Questions'!$A:$J,3,0)&"" -> Urban Planning & Design (UPD)
A3: Original ID | B3: =VLOOKUP($B$1,'PARASTATAL Questions'!$A:$J,2,0)&"" -> UPD 1b
A4: MQ_SQ | B4: =VLOOKUP($B$1,'PARASTATAL Questions'!$A:$J,4,0)&"" -> SQ
A5: Question | B5: =VLOOKUP($B$1,'PARASTATAL Questions'!$A:$J,5,0)&"" -> Has the ULG participated in the parastatal’s plan-making process?
A6: Max Score | B6: =VLOOKUP($B$1,'PARASTATAL Questions'!$A:$J,6,0) -> 5
A7: Assessment level | B7: =VLOOKUP($B$1,'PARASTATAL Questions'!$A:$J,7,0)&"" -> Implementation
A8: Applicability | B8: =VLOOKUP($B$1,'PARASTATAL Questions'!$A:$J,8,0)&"" -> All parastatals excluding Development Authorities
A9: Detailed Methodology | B9: =VLOOKUP($B$1,'PARASTATAL Questions'!$A:$J,9,0)&"" -> Check the latest available plan-making cycle for evidence of ULG participation in the parastatal’s plan-making process, irrespective of whether such participation is legally mandated.Score 10 where there is evidence of ULG participation. Such evidence may include plan documents, consultation records, meeting minutes, ULG resolutions/comments, responses to ULG inputs, or information published on the parastatal/ULG website.Score 0 where there is no such evidence.Where different provisions apply to different plans prepared by the parastatal, assess the principal sectoral plan relevant to the service being evaluated.
A10: Notes for scorers | B10: =VLOOKUP($B$1,'PARASTATAL Questions'!$A:$J,10,0)&"" -> Evidence may include plan documents, consultation records, meeting minutes, ULG resolutions/comments, responses to ULG inputs, or information published on the parastatal/ULG website.
B11: PRE-FILLED - DO NOT ALTER | I11: ENTER A NUMBER 0 TO 5 | J11: DO NOT ALTER FORMULA
A12: City | B12: Applies? | C12: Act Name/Web name/Doc name | D12: Chapter | E12: Provision | F12: Clause | G12: Page Number | H12: Link | I12: Score | J12: Points (Auto-generate) | K12: SCORER COMMENTS
A13: Bengaluru – BWSSB | B13: YES | C13: JICA – Bengaluru Water Supply and Sewerage Project (Phase 3), Final Report (Main Report), November 2017 [BWSSB-22] | D13: Chapter 5 (Population projection / water balance study), Section 5.1.5 Projection of Population in the BBMP for the Water Balance Study | E13: Section 5.1.5, item 2) 110 Villages (pp. 5-7 to 5-8, PDF pages 227-228) | F13: Item 2) 110 Villages (Main Report, page 5-7 / PDF page 227) | G13: 227 | H13: https://openjicareport.jica.go.jp/pdf/12300356_01.pdf | I13: 5 | J13: =IF($B13="NO","NA",IF(I13="","",MIN(I13,$B$6))) -> 5 | K13: AI (medium confidence), from Step 2 answer (Partially Answered) and BWSSB-22: I am proposing 5, the maximum. Step 2 proposed 2.5, and I am not following it. 1) How the methodology scores: there are only two outcomes. It gives full marks ('Score 10') where there is any evidence of ULG participation in the plan-making process, whether or not the law requires it. It gives 0 where there is none. It has no band for 'limited or informal engagement', so the 2.5 from Step 2 has no basis. The question's maximum is 5, so I read the 'Score 10' band as full marks, which is 5. A human should confirm that reading of the scale. 2) What the evidence shows: I reread the sheet and found a passage Step 2 did not use. BWSSB-22 (JICA Preparatory Survey Final Report, Main Report, Nov 2017), Section 5.1.5, says the planning population for the 110 Villages was authorised at a tripartite meeting of BDA, BBMP and BWSSB. That population is the basis of the 110 Villages water supply and sewerage plan and DPR. This shows BBMP (the ULG) helped set a core planning input, so it is more than a briefing. It is backed by BWSSB-23, Section 14.12: BBMP took part in BWSSB's stakeholders' meeting on 22 August 2017 for the planned 110 Villages water supply and sewerage project. Taken together, these meet the methodology's test that 'evidence of ULG participation' exists, and the methodology lists meeting records among acceptable evidence. 3) Caveats a reviewer should check: (a) The evidence comes from a 2017 JICA consultant report, not from a BWSSB or BBMP publication. The minutes are in a Supporting Report that is not in the Citation Sheet. (b) The plan in question is the 110 Villages project plan/DPR. It is not clearly the 'principal sectoral plan'. BWSSB-22 says the BWSSB Master Plan begun in 2015 was still a draft and had not been approved. No source shows ULG participation in that Master Plan, or in the Cauvery Water Supply Scheme Stage VI DPR that BWSSB-12 says is under preparation. (c) The 'latest available plan-making cycle' may come after 2017, and BBMP has since been succeeded by the Greater Bengaluru Authority and its corporations. If a reviewer decides the latest cycle is the Master Plan or the Stage VI DPR, the score should be 0 unless further evidence turns up, because the sheet has none for those plans. (d) BWSSB-04, Section 14 (the Consultative Committee, which includes the Municipal Corporation) is a legal provision only, so I have not credited it at Implementation level. Quote: "The population for the next three decades were authorized through a tripartite meeting by BDA, BBMP and BWSSB."
A14: Bengaluru – BMTC | B14: YES | J14: =IF($B14="NO","NA",IF(I14="","",MIN(I14,$B$6))) | K14: AI: left for a person. Step 2 found no evidence (Insufficient Evidence). Source needed: Any of the following, from BMTC's latest plan-making cycle: (a) BMTC's latest plan document (e.g. a fleet augmentation, route rationalisation or bus priority/network plan, or BMTC's Sectoral Mobility Investment Program / Annual Implementation Plan under the BMLTA Act) showing consultation with, inputs from, or concurrence of BBMP/GBA; (b) BMTC Board meeting minutes or consultation records listing the ULG as a participant; (c) GBA/BBMP council or standing committee resolutions or letters commenting on BMTC plans; (d) BMLTA or DULT records of a recent CMP or bus plan prepared jointly with BMTC and the ULG.
A15: Bengaluru – BDA | B15: NO | J15: =IF($B15="NO","NA",IF(I15="","",MIN(I15,$B$6))) -> NA
A16: Bengaluru – BMRCL | B16: YES | J16: =IF($B16="NO","NA",IF(I16="","",MIN(I16,$B$6))) | K16: AI: left for a person. Step 2 found no evidence (Insufficient Evidence). Source needed: Any of the following, from the latest plan-making cycle, would answer the question: - BMRCL's latest Detailed Project Report (e.g., Phase 2A/2B/3), or its consultation chapter or appendix, listing stakeholder agencies consulted, including the GBA or city corporations / BBMP, and their comments. - Minutes of BMRCL Board meetings, or of inter-agency coordination meetings, showing municipal commissioner participation in plan or alignment decisions. - ULG council resolutions or letters commenting on or concurring with BMRCL metro plans. - Appendix 4 of the Line 6 EIA (participant lists and queries), to check whether municipal officials attended. - The Comprehensive Mobility Plan preparation record showing joint metro planning with the ULG.
A17: Bengaluru – BMRDA | B17: NO | J17: =IF($B17="NO","NA",IF(I17="","",MIN(I17,$B$6))) -> NA
A18: Surat – SUDA | B18: NO | J18: =IF($B18="NO","NA",IF(I18="","",MIN(I18,$B$6))) -> NA
A19: Surat – GMRC | B19: YES | J19: =IF($B19="NO","NA",IF(I19="","",MIN(I19,$B$6)))

Sheet UPD2a
A1: Question Code | B1: UPD2a | C1: <Sheet name and this code must match>
A2: Group | B2: =VLOOKUP($B$1,'PARASTATAL Questions'!$A:$J,3,0)&"" -> Urban Planning & Design (UPD)
A3: Original ID | B3: =VLOOKUP($B$1,'PARASTATAL Questions'!$A:$J,2,0)&"" -> UPD 2a
A4: MQ_SQ | B4: =VLOOKUP($B$1,'PARASTATAL Questions'!$A:$J,4,0)&"" -> SQ
A5: Question | B5: =VLOOKUP($B$1,'PARASTATAL Questions'!$A:$J,5,0)&"" -> Where multiple statutory or sectoral plans apply to the same territory, is the water board mandated to ensure consistency with the applicable city /municipal plan for the city?
A6: Max Score | B6: =VLOOKUP($B$1,'PARASTATAL Questions'!$A:$J,6,0) -> 2.5
A7: Assessment level | B7: =VLOOKUP($B$1,'PARASTATAL Questions'!$A:$J,7,0)&"" -> Law/Policy
A8: Applicability | B8: =VLOOKUP($B$1,'PARASTATAL Questions'!$A:$J,8,0)&"" -> Water supply board
A9: Detailed Methodology | B9: =VLOOKUP($B$1,'PARASTATAL Questions'!$A:$J,9,0)&"" -> Check the relevant Parastatal Act and Town and Country Planning Act.Score 2.50 if the parastatal 'shall/is required to' ensure that its sectoral plan is consistent with the applicable city or municipal plan.Score 1.25 if the law provides that such alignment is discretionary. ('May' provision)Score 0 if no such provision exists.For example, a provision stating that a water supply plan shall conform to the applicable city/municipal plan would score 2.5, while a provision stating that the authority may have regard to such a plan would score 1.25.
A10: Notes for scorers | B10: =VLOOKUP($B$1,'PARASTATAL Questions'!$A:$J,10,0)&"" -> Relevant Parastatal Act; applicable Town and Country Planning (T&CP) Act.
B11: PRE-FILLED - DO NOT ALTER | I11: ENTER A NUMBER 0 TO 2.5 | J11: DO NOT ALTER FORMULA
A12: City | B12: Applies? | C12: Act Name/Web name/Doc name | D12: Chapter | E12: Provision | F12: Clause | G12: Page Number | H12: Link | I12: Score | J12: Points (Auto-generate) | K12: SCORER COMMENTS
A13: Bengaluru – BWSSB | B13: YES | J13: =IF($B13="NO","NA",IF(I13="","",MIN(I13,$B$6))) | K13: AI: left for a person. Step 2 found no evidence (Insufficient Evidence). Source needed: Two sources are needed: (1) the complete, current consolidated text of the Bangalore Water Supply and Sewerage Act, 1964, with all amendments, to check for any provision requiring or permitting BWSSB schemes to conform to the Master Plan, CDP or regional plan; and (2) the full text of the Karnataka Town and Country Planning Act, 1961, with amendments, especially its provisions on the Master Plan / Comprehensive Development Plan and on the binding effect of the plan on authorities and public agencies. The Bangalore Metropolitan Region Development Authority Act, 1985 and any Greater Bengaluru Authority legislation on plan coordination would also be relevant.
A14: Bengaluru – BMTC | B14: NO | J14: =IF($B14="NO","NA",IF(I14="","",MIN(I14,$B$6))) -> NA
A15: Bengaluru – BDA | B15: NO | J15: =IF($B15="NO","NA",IF(I15="","",MIN(I15,$B$6))) -> NA
A16: Bengaluru – BMRCL | B16: NO | J16: =IF($B16="NO","NA",IF(I16="","",MIN(I16,$B$6))) -> NA
A17: Bengaluru – BMRDA | B17: NO | J17: =IF($B17="NO","NA",IF(I17="","",MIN(I17,$B$6))) -> NA
A18: Surat – SUDA | B18: NO | J18: =IF($B18="NO","NA",IF(I18="","",MIN(I18,$B$6))) -> NA
A19: Surat – GMRC | B19: NO | J19: =IF($B19="NO","NA",IF(I19="","",MIN(I19,$B$6))) -> NA

Sheet UPD2b
A1: Question Code | B1: UPD2b | C1: <Sheet name and this code must match>
A2: Group | B2: =VLOOKUP($B$1,'PARASTATAL Questions'!$A:$J,3,0)&"" -> Urban Planning & Design (UPD)
A3: Original ID | B3: =VLOOKUP($B$1,'PARASTATAL Questions'!$A:$J,2,0)&"" -> UPD 2b
A4: MQ_SQ | B4: =VLOOKUP($B$1,'PARASTATAL Questions'!$A:$J,4,0)&"" -> SQ
A5: Question | B5: =VLOOKUP($B$1,'PARASTATAL Questions'!$A:$J,5,0)&"" -> Where multiple statutory or sectoral plans apply to the same territory, does the water supply board ensure consistency with the applicable municipal/city plan for the city?
A6: Max Score | B6: =VLOOKUP($B$1,'PARASTATAL Questions'!$A:$J,6,0) -> 2.5
A7: Assessment level | B7: =VLOOKUP($B$1,'PARASTATAL Questions'!$A:$J,7,0)&"" -> Implementation
A8: Applicability | B8: =VLOOKUP($B$1,'PARASTATAL Questions'!$A:$J,8,0)&"" -> Water supply board
A9: Detailed Methodology | B9: =VLOOKUP($B$1,'PARASTATAL Questions'!$A:$J,9,0)&"" -> Check the Board’s current water supply/sewerage master plan, or equivalent sectoral planning document, together with the applicable Master Plan. Score 2.5 if the water plan demonstrates substantive spatial alignment with the city’s master plan: It explicitly draws reference to the city master plan, uses the master plan’s growth/service areas and/or land-use framework to determine network expansion and major infrastructure siting, and also refers to the master plan or its projections as an input.Score 1.25 if there is partial alignment: the water plan refers to the master plan and/or uses its population, density or land-use projections, but does not clearly demonstrate that these inputs determine the spatial location of network expansion, service areas or major infrastructure.Score 0 if there is no identifiable evidence that the Master Plan or its spatial/population framework informs water planning.
A10: Notes for scorers | B10: =VLOOKUP($B$1,'PARASTATAL Questions'!$A:$J,10,0)&"" -> Water Supply Board's current water supply/sewerage master plan or equivalent sectoral planning document; applicable Master Plan/Development Plan/Metropolitan or Regional Plan; land-use conversion/regularisation records for major treatment plants or trunk infrastructure, where available.
B11: PRE-FILLED - DO NOT ALTER | I11: ENTER A NUMBER 0 TO 2.5 | J11: DO NOT ALTER FORMULA
A12: City | B12: Applies? | C12: Act Name/Web name/Doc name | D12: Chapter | E12: Provision | F12: Clause | G12: Page Number | H12: Link | I12: Score | J12: Points (Auto-generate) | K12: SCORER COMMENTS
